{
  "type": "Feature",
  "properties": {
    "addr:full":"1034 Tiffany Rd Belmont VT 05730",
    "addr:housenumber":"1034",
    "addr:postcode":"05730",
    "addr:street":"Tiffany Rd",
    "iso:country":"US",
    "sg:address":"1034 Tiffany Rd",
    "sg:city":"Belmont",
    "sg:classifiers":[
        {
            "category":"Organizations",
            "subcategory":"Non-profit Organization",
            "type":"Services"
        }
    ],
    "sg:phone":"+1 802 259 2759",
    "sg:postcode":"05730",
    "sg:province":"VT",
    "sg:website":"www.vfp.org",
    "wof:name":"VFP Intl Work Camps",
    "wof:placetype":"venue"
},
  "geometry": {"coordinates":[-72.836782,43.422556],"type":"Point"}
}