{
  "type": "Feature",
  "properties": {
    "iso:country":"US",
    "sg:address":"175 Lakeside Ave",
    "sg:city":"Burlington",
    "sg:classifiers":[
        {
            "category":"Utilities",
            "subcategory":"Refuse",
            "type":"Services"
        }
    ],
    "sg:phone":"+1 802 660 0442",
    "sg:postcode":"05401",
    "sg:province":"VT",
    "sg:tags":[
        "system"
    ],
    "wof:name":"Cwm Transportation",
    "wof:placetype":"venue"
},
  "geometry": {"coordinates":[-73.215451,44.461208],"type":"Point"}
}