{
  "type": "Feature",
  "properties": {
    "addr:full":"31 Rutland St Rutland VT 05701",
    "addr:housenumber":"31",
    "addr:postcode":"05701",
    "addr:street":"Rutland St",
    "iso:country":"US",
    "sg:address":"31 Rutland St",
    "sg:city":"Rutland",
    "sg:classifiers":[
        {
            "category":"Building & Trades",
            "subcategory":"Equipment Rental",
            "type":"Services"
        }
    ],
    "sg:phone":"+1 802 773 0491",
    "sg:postcode":"05701",
    "sg:province":"VT",
    "sg:tags":[
        "yard"
    ],
    "wof:name":"Rent-A-Center",
    "wof:placetype":"venue"
},
  "geometry": {"coordinates":[-72.962332,43.611416],"type":"Point"}
}