{
  "type": "Feature",
  "properties": {
    "iso:country":"US",
    "sg:address":"59 Pearl St",
    "sg:city":"Grand Isle",
    "sg:classifiers":[
        {
            "category":"Home & Garden",
            "subcategory":"Garden Supply",
            "type":"Retail Goods"
        }
    ],
    "sg:phone":"+1 802 372 3811",
    "sg:postcode":"05458",
    "sg:province":"VT",
    "wof:name":"Acorn Ridge Nursery Inc",
    "wof:placetype":"venue"
},
  "geometry": {"coordinates":[-73.33032300000001,44.689895],"type":"Point"}
}