{
  "type": "Feature",
  "properties": {
    "iso:country":"US",
    "sg:address":"196 Baldwin Rd",
    "sg:city":"Hinesburg",
    "sg:classifiers":[
        {
            "category":"Real Estate",
            "subcategory":"Real Estate Agent",
            "type":"Services"
        }
    ],
    "sg:phone":"+1 802 482 6607",
    "sg:postcode":"05461",
    "sg:province":"VT",
    "sg:tags":[
        "inspection"
    ],
    "sg:website":"www.tombarden.com",
    "wof:name":"Barden Inspection & Consulting",
    "wof:placetype":"venue"
},
  "geometry": {"coordinates":[-73.13238,44.320918],"type":"Point"}
}