{
  "type": "Feature",
  "properties": {
    "iso:country":"US",
    "sg:address":"195 Hospital Loop",
    "sg:city":"Montpelier",
    "sg:classifiers":[
        {
            "category":"Health Services",
            "subcategory":"Doctor",
            "type":"Services"
        }
    ],
    "sg:phone":"+1 802 223 5430",
    "sg:postcode":"05602",
    "sg:province":"VT",
    "sg:tags":[
        "medical"
    ],
    "wof:name":"Anthony Lapinsky",
    "wof:placetype":"venue"
},
  "geometry": {"coordinates":[-72.561179,44.221327],"type":"Point"}
}