{
  "type": "Feature",
  "properties": {
    "iso:country":"US",
    "sg:address":"62 Park St",
    "sg:city":"Essex Junction",
    "sg:classifiers":[
        {
            "category":"Food & Beverages",
            "subcategory":"Groceries & Convenience Stores",
            "type":"Retail Goods"
        },
        {
            "category":"Retail",
            "subcategory":"Car Wash",
            "type":"Services"
        }
    ],
    "sg:phone":"+1 802 878 8440",
    "sg:postcode":"05452",
    "sg:province":"VT",
    "sg:tags":[
        "carwash",
        "automobile",
        "detail",
        "clean",
        "alcoholic"
    ],
    "wof:name":"Abair's Quality Car Care",
    "wof:placetype":"venue"
},
  "geometry": {"coordinates":[-73.11303599999999,44.487452],"type":"Point"}
}