{
  "type": "Feature",
  "properties": {
    "iso:country":"US",
    "sg:address":"2274 Malletts Bay Ave",
    "sg:city":"Colchester",
    "sg:classifiers":[
        {
            "category":"Building & Trades",
            "subcategory":"Electrical",
            "type":"Services"
        }
    ],
    "sg:phone":"+1 802 655 1986",
    "sg:postcode":"05446",
    "sg:province":"VT",
    "sg:tags":[
        "industrial",
        "electrician",
        "contractors-commercial",
        "electric"
    ],
    "wof:name":"Don King Electrical Services, Inc.",
    "wof:placetype":"venue"
},
  "geometry": {"coordinates":[-73.20192,44.507801],"type":"Point"}
}