{
  "type": "Feature",
  "properties": {
    "iso:country":"US",
    "sg:address":"177 River St",
    "sg:city":"Montpelier",
    "sg:classifiers":[
        {
            "category":"Retail",
            "subcategory":"Repair Shop",
            "type":"Services"
        }
    ],
    "sg:phone":"+1 802 223 5110",
    "sg:postcode":"05602",
    "sg:province":"VT",
    "sg:tags":[
        "equipment"
    ],
    "wof:name":"Commercial Services Inc",
    "wof:placetype":"venue"
},
  "geometry": {"coordinates":[-72.559298,44.249505],"type":"Point"}
}