{
  "type": "Feature",
  "properties": {
    "addr:full":"55 Wilkinson Dr Essex Junction VT 05452",
    "addr:housenumber":"55",
    "addr:postcode":"05452",
    "addr:street":"Wilkinson Dr",
    "iso:country":"US",
    "sg:address":"55 Wilkinson Dr",
    "sg:city":"Essex Junction",
    "sg:classifiers":[
        {
            "category":"Professional",
            "subcategory":"Detective & Security Services",
            "type":"Services"
        }
    ],
    "sg:phone":"+1 802 878 5858",
    "sg:postcode":"05452",
    "sg:province":"VT",
    "sg:tags":[
        "car"
    ],
    "wof:name":"Computer Detective The",
    "wof:placetype":"venue"
},
  "geometry": {"coordinates":[-73.132426,44.487495],"type":"Point"}
}