{
  "type": "Feature",
  "properties": {
    "iso:country":"US",
    "sg:address":"14 Elizabeth St",
    "sg:city":"Port Henry",
    "sg:classifiers":[
        {
            "category":"Building & Trades",
            "subcategory":"Plumbing",
            "type":"Services"
        }
    ],
    "sg:phone":"+1 518 546 8252",
    "sg:postcode":"12974",
    "sg:province":"NY",
    "sg:tags":[
        "contractor"
    ],
    "wof:name":"Salerno & Son Plumbing & Htg",
    "wof:placetype":"venue"
},
  "geometry": {"coordinates":[-73.46072,44.044539],"type":"Point"}
}