{
  "type": "Feature",
  "properties": {
    "addr:full":"105 Glen Rd Burlington VT 05401",
    "addr:housenumber":"105",
    "addr:postcode":"05401",
    "addr:street":"Glen Rd",
    "iso:country":"US",
    "sg:address":"105 Glen Rd",
    "sg:city":"Burlington",
    "sg:classifiers":[
        {
            "category":"Banks & Credit Unions",
            "subcategory":"Investment Brokerage",
            "type":"Services"
        }
    ],
    "sg:phone":"+1 802 862 4367",
    "sg:postcode":"05401",
    "sg:province":"VT",
    "sg:tags":[
        "commodity"
    ],
    "wof:name":"J A Solomon & Co",
    "wof:placetype":"venue"
},
  "geometry": {"coordinates":[-73.201691,44.455229],"type":"Point"}
}