{
  "type": "Feature",
  "properties": {
    "iso:country":"US",
    "sg:address":"382 Canal St",
    "sg:city":"Brattleboro",
    "sg:classifiers":[
        {
            "category":"Health Services",
            "subcategory":"Health Practitioner",
            "type":"Services"
        }
    ],
    "sg:phone":"+1 802 254 5020",
    "sg:postcode":"05301",
    "sg:province":"VT",
    "sg:tags":[
        "acupuncture"
    ],
    "wof:name":"Acupuncture Institute",
    "wof:placetype":"venue"
},
  "geometry": {"coordinates":[-72.56806400000001,42.833737],"type":"Point"}
}