{
  "type": "Feature",
  "properties": {
    "iso:country":"US",
    "sg:address":"316 Main St",
    "sg:city":"Norwich",
    "sg:classifiers":[
        {
            "category":"Utilities",
            "subcategory":"Water",
            "type":"Services"
        }
    ],
    "sg:phone":"+1 802 649 5424",
    "sg:postcode":"05055",
    "sg:province":"VT",
    "sg:tags":[
        "company",
        "sewage"
    ],
    "wof:name":"Water Dept",
    "wof:placetype":"venue"
},
  "geometry": {"coordinates":[-72.308649,43.715823],"type":"Point"}
}