{
  "type": "Feature",
  "properties": {
    "iso:country":"US",
    "sg:address":"185 Higley Hill Rd",
    "sg:city":"Wilmington",
    "sg:classifiers":[
        {
            "category":"Professional",
            "subcategory":"Computer Services",
            "type":"Services"
        }
    ],
    "sg:phone":"+1 802 464 6572",
    "sg:postcode":"05363",
    "sg:province":"VT",
    "sg:tags":[
        "consultant",
        "designer"
    ],
    "wof:name":"Adams Results Unltd",
    "wof:placetype":"venue"
},
  "geometry": {"coordinates":[-72.832914,42.897771],"type":"Point"}
}