{
  "type": "Feature",
  "properties": {
    "iso:country":"US",
    "sg:address":"132 S Main St",
    "sg:city":"Hardwick",
    "sg:classifiers":[
        {
            "category":"Insurance",
            "subcategory":"Insurance Agent",
            "type":"Services"
        }
    ],
    "sg:phone":"+1 802 472 5517",
    "sg:postcode":"05843",
    "sg:province":"VT",
    "wof:name":"Calderwood Insurance",
    "wof:placetype":"venue"
},
  "geometry": {"coordinates":[-72.36837800000001,44.503738],"type":"Point"}
}