{
  "type": "Feature",
  "properties": {
    "iso:country":"US",
    "sg:address":"462 Stone Rd",
    "sg:city":"Williamstown",
    "sg:classifiers":[
        {
            "category":"Farming",
            "subcategory":"Farm",
            "type":"Manufacturing & Wholesale Goods"
        }
    ],
    "sg:phone":"+1 802 433 1079",
    "sg:postcode":"05679",
    "sg:province":"VT",
    "wof:name":"Fairmont Farm",
    "wof:placetype":"venue"
},
  "geometry": {"coordinates":[-72.59912300000001,44.104898],"type":"Point"}
}