{
  "type": "Feature",
  "properties": {
    "addr:full":"476 Quechee Rd Hartland VT 05048",
    "addr:housenumber":"476",
    "addr:postcode":"05048",
    "addr:street":"Quechee Rd",
    "iso:country":"US",
    "sg:address":"476 Quechee Rd",
    "sg:city":"Hartland",
    "sg:classifiers":[
        {
            "category":"Professional",
            "subcategory":"Business Services",
            "type":"Services"
        }
    ],
    "sg:phone":"+1 802 436 2085",
    "sg:postcode":"05048",
    "sg:province":"VT",
    "sg:tags":[
        "plant",
        "design",
        "maintenance"
    ],
    "wof:name":"Talbot's Herb & Perennial Farm",
    "wof:placetype":"venue"
},
  "geometry": {"coordinates":[-72.406634,43.600533],"type":"Point"}
}