{
  "type": "Feature",
  "properties": {
    "iso:country":"US",
    "sg:address":"5 Gauthier Dr",
    "sg:city":"Essex Junction",
    "sg:classifiers":[
        {
            "category":"Utilities",
            "subcategory":"Refuse",
            "type":"Services"
        }
    ],
    "sg:phone":"+1 802 879 4020",
    "sg:postcode":"05452",
    "sg:province":"VT",
    "sg:tags":[
        "garbage",
        "collection"
    ],
    "wof:name":"Gauthier Trucking Co",
    "wof:placetype":"venue"
},
  "geometry": {"coordinates":[-73.13376100000001,44.511818],"type":"Point"}
}