{
  "type": "Feature",
  "properties": {
    "iso:country":"US",
    "sg:address":"5163 State Rte 116",
    "sg:city":"Shelburne",
    "sg:classifiers":[
        {
            "category":"Building & Trades",
            "subcategory":"Construction",
            "type":"Services"
        }
    ],
    "sg:phone":"+1 802 862 4455",
    "sg:postcode":"05482",
    "sg:province":"VT",
    "sg:tags":[
        "excavation",
        "excavating",
        "contractor"
    ],
    "wof:name":"Du Bois Moe Excavating Inc",
    "wof:placetype":"venue"
},
  "geometry": {"coordinates":[-73.14276700000001,44.40131],"type":"Point"}
}