{
  "type": "Feature",
  "properties": {
    "iso:country":"US",
    "sg:address":"49 Richards Rd",
    "sg:city":"Fairfax",
    "sg:classifiers":[
        {
            "category":"Professional",
            "type":"Services"
        }
    ],
    "sg:phone":"+1 802 849 2181",
    "sg:postcode":"05454",
    "sg:province":"VT",
    "wof:name":"Henna Expressions East",
    "wof:placetype":"venue"
},
  "geometry": {"coordinates":[-73.033242,44.655091],"type":"Point"}
}