{
  "type": "Feature",
  "properties": {
    "addr:full":"16 Old Sawmill Rd S Londonderry VT 05148",
    "addr:housenumber":"16",
    "addr:postcode":"05148",
    "addr:street":"Old Sawmill Rd S",
    "iso:country":"US",
    "sg:address":"16 Old Sawmill Rd",
    "sg:city":"S Londonderry",
    "sg:classifiers":[
        {
            "category":"Professional",
            "type":"Services"
        }
    ],
    "sg:phone":"+1 802 297 3759",
    "sg:postcode":"05148",
    "sg:province":"VT",
    "sg:tags":[
        "establishment"
    ],
    "wof:name":"O'Halloran & O'Halloran",
    "wof:placetype":"venue"
},
  "geometry": {"coordinates":[-72.76389399999999,43.21586],"type":"Point"}
}