{
  "type": "Feature",
  "properties": {
    "iso:country":"US",
    "sg:address":"267 Deer Run Ln",
    "sg:city":"Lyndonville",
    "sg:classifiers":[
        {
            "category":"Health Services",
            "subcategory":"Nursing And Care Facility",
            "type":"Services"
        }
    ],
    "sg:phone":"+1 802 626 4412",
    "sg:postcode":"05851",
    "sg:province":"VT",
    "sg:tags":[
        "home",
        "retirement",
        "community"
    ],
    "wof:name":"Great West Retirement Svc",
    "wof:placetype":"venue"
},
  "geometry": {"coordinates":[-71.97814,44.547736],"type":"Point"}
}