{
  "type": "Feature",
  "properties": {
    "iso:country":"US",
    "sg:address":"21 Merchant St",
    "sg:city":"Barre",
    "sg:classifiers":[
        {
            "category":"Health Services",
            "subcategory":"Nursing And Care Facility",
            "type":"Services"
        }
    ],
    "sg:phone":"+1 802 479 0092",
    "sg:postcode":"05641",
    "sg:province":"VT",
    "sg:tags":[
        "home",
        "retirement",
        "community"
    ],
    "wof:name":"Retirement Solutions",
    "wof:placetype":"venue"
},
  "geometry": {"coordinates":[-72.50301899999999,44.200116],"type":"Point"}
}