{
  "type": "Feature",
  "properties": {
    "iso:country":"US",
    "sg:address":"668 Rutland Rd",
    "sg:city":"West Rutland",
    "sg:classifiers":[
        {
            "category":"Building & Trades",
            "subcategory":"Construction",
            "type":"Services"
        }
    ],
    "sg:phone":"+1 802 438 5151",
    "sg:postcode":"05777",
    "sg:province":"VT",
    "sg:tags":[
        "excavating",
        "contractor"
    ],
    "wof:name":"Blanchard Trucking & Excvtng",
    "wof:placetype":"venue"
},
  "geometry": {"coordinates":[-73.032537,43.593757],"type":"Point"}
}