{
  "type": "Feature",
  "properties": {
    "addr:full":"37 Concord Ave Newport VT 05855",
    "addr:housenumber":"37",
    "addr:postcode":"05855",
    "addr:street":"Concord Ave",
    "iso:country":"US",
    "sg:address":"37 Concord Ave",
    "sg:city":"Newport",
    "sg:classifiers":[
        {
            "category":"Organizations",
            "subcategory":"Religious Organization",
            "type":"Services"
        }
    ],
    "sg:phone":"+1 802 334 3096",
    "sg:postcode":"05855",
    "sg:province":"VT",
    "sg:tags":[
        "church"
    ],
    "wof:name":"Seventh Day Adventist Church",
    "wof:placetype":"venue"
},
  "geometry": {"coordinates":[-72.19656500000001,44.943729],"type":"Point"}
}