{
  "type": "Feature",
  "properties": {
    "iso:country":"US",
    "sg:address":"172 Broadlake Rd",
    "sg:city":"Colchester",
    "sg:classifiers":[
        {
            "category":"Banks & Credit Unions",
            "subcategory":"Bank",
            "type":"Services"
        }
    ],
    "sg:phone":"+1 802 860 2002",
    "sg:postcode":"05446",
    "sg:province":"VT",
    "wof:name":"Bank Broker Dealer Solutions",
    "wof:placetype":"venue"
},
  "geometry": {"coordinates":[-73.286575,44.543548],"type":"Point"}
}