{
  "type": "Feature",
  "properties": {
    "addr:full":"231 Red Village Rd Lyndonville VT 05851",
    "addr:housenumber":"231",
    "addr:postcode":"05851",
    "addr:street":"Red Village Rd",
    "iso:country":"US",
    "sg:address":"231 Red Village Rd",
    "sg:city":"Lyndonville",
    "sg:classifiers":[
        {
            "category":"Retail",
            "subcategory":"Repair Shop",
            "type":"Services"
        },
        {
            "category":"Retail",
            "subcategory":"Auto Repair",
            "type":"Services"
        }
    ],
    "sg:phone":"+1 802 626 9611",
    "sg:postcode":"05851",
    "sg:province":"VT",
    "sg:tags":[
        "truck"
    ],
    "wof:name":"New England Truck Maintenance",
    "wof:placetype":"venue"
},
  "geometry": {"coordinates":[-72.00019500000001,44.517238],"type":"Point"}
}