{
  "type": "Feature",
  "properties": {
    "iso:country":"US",
    "sg:address":"199 Paine Tpke N",
    "sg:city":"Berlin",
    "sg:classifiers":[
        {
            "category":"Freight",
            "type":"Transportation"
        }
    ],
    "sg:phone":"+1 802 229 4092",
    "sg:postcode":"05602",
    "sg:province":"VT",
    "sg:tags":[
        "commercial",
        "storage"
    ],
    "wof:name":"Stor-N-Lok",
    "wof:placetype":"venue"
},
  "geometry": {"coordinates":[-72.57442399999999,44.213769],"type":"Point"}
}