{
  "type": "Feature",
  "properties": {
    "iso:country":"US",
    "sg:address":"1759 Vt Route 7A",
    "sg:city":"Arlington",
    "sg:classifiers":[
        {
            "category":"Travel",
            "subcategory":"Hotels & Motels",
            "type":"Entertainment"
        }
    ],
    "sg:phone":"+1 802 375 2212",
    "sg:postcode":"05250",
    "sg:province":"VT",
    "sg:tags":[
        "lodging"
    ],
    "sg:website":"http://www.valhallamotel.com",
    "wof:name":"Valhalla Motel",
    "wof:placetype":"venue"
},
  "geometry": {"coordinates":[-73.113015,43.116745],"type":"Point"}
}