{
  "type": "Feature",
  "properties": {
    "iso:country":"US",
    "sg:address":"5308 Main St",
    "sg:city":"Waitsfield",
    "sg:classifiers":[
        {
            "category":"Social Services",
            "type":"Services"
        }
    ],
    "sg:phone":"+1 802 496 2020",
    "sg:postcode":"05673",
    "sg:province":"VT",
    "sg:tags":[
        "senior",
        "citizen"
    ],
    "wof:name":"Mad River Valley Senior Ctr",
    "wof:placetype":"venue"
},
  "geometry": {"coordinates":[-72.83890599999999,44.182531],"type":"Point"}
}