{
  "type": "Feature",
  "properties": {
    "addr:full":"713 US Hwy 5 Norwich VT 05055",
    "addr:housenumber":"713",
    "addr:postcode":"05055",
    "addr:street":"Us Hwy 5",
    "iso:country":"US",
    "sg:address":"713 US Hwy 5",
    "sg:city":"Norwich",
    "sg:classifiers":[
        {
            "category":"Organizations",
            "subcategory":"Religious Organization",
            "type":"Services"
        }
    ],
    "sg:phone":"+1 802 649 1615",
    "sg:postcode":"05055",
    "sg:province":"VT",
    "sg:tags":[
        "church"
    ],
    "wof:name":"Norwich Full Gospel Voice Chr",
    "wof:placetype":"venue"
},
  "geometry": {"coordinates":[-72.31408999999999,43.681563],"type":"Point"}
}