{
  "type": "Feature",
  "properties": {
    "iso:country":"US",
    "sg:address":"830 US Route 5",
    "sg:city":"Dummerston",
    "sg:classifiers":[
        {
            "category":"Retail",
            "subcategory":"Auto Rental",
            "type":"Services"
        },
        {
            "category":"Professional",
            "type":"Services"
        },
        {
            "category":"Retail",
            "subcategory":"Storage",
            "type":"Services"
        },
        {
            "category":"Transit Center",
            "subcategory":"Freight",
            "type":"Transportation"
        },
        {
            "category":"Freight",
            "type":"Transportation"
        },
        {
            "category":"Personal",
            "type":"Services"
        }
    ],
    "sg:phone":"+1 802 257 0543",
    "sg:postcode":"05301",
    "sg:province":"VT",
    "sg:tags":[
        "moving-self",
        "trucking-motor",
        "material",
        "trucking",
        "truck",
        "services-labor",
        "moving",
        "mover",
        "local"
    ],
    "sg:website":"http://brattleboro.upack.com",
    "wof:name":"Abf",
    "wof:placetype":"venue"
},
  "geometry": {"coordinates":[-72.53707900000001,42.916271],"type":"Point"}
}