{
  "type": "Feature",
  "properties": {
    "addr:full":"207 Dorset Hollow Rd Dorset VT 05251",
    "addr:housenumber":"207",
    "addr:postcode":"05251",
    "addr:street":"Dorset Hollow Rd",
    "iso:country":"US",
    "sg:address":"207 Dorset Hollow Rd",
    "sg:city":"Dorset",
    "sg:classifiers":[
        {
            "category":"Professional",
            "type":"Services"
        }
    ],
    "sg:phone":"+1 802 867 5536",
    "sg:postcode":"05251",
    "sg:province":"VT",
    "sg:tags":[
        "establishment"
    ],
    "wof:name":"Gilbride Cottage",
    "wof:placetype":"venue"
},
  "geometry": {"coordinates":[-73.09286899999999,43.256835],"type":"Point"}
}