{
  "type": "Feature",
  "properties": {
    "iso:country":"US",
    "sg:address":"43 E Main St",
    "sg:city":"Wilmington",
    "sg:classifiers":[
        {
            "category":"Autos & Motor Vehicles",
            "subcategory":"Fuel & Gas Station",
            "type":"Retail Goods"
        }
    ],
    "sg:phone":"+1 802 464 3372",
    "sg:postcode":"05363",
    "sg:province":"VT",
    "sg:tags":[
        "oil"
    ],
    "wof:name":"Tom's Sunoco",
    "wof:placetype":"venue"
},
  "geometry": {"coordinates":[-72.864783,42.865849],"type":"Point"}
}