{
  "type": "Feature",
  "properties": {
    "addr:full":"159 Industrial Pkwy Burlington VT 05401",
    "addr:housenumber":"159",
    "addr:postcode":"05401",
    "addr:street":"Industrial Pkwy",
    "iso:country":"US",
    "sg:address":"159 Industrial Pkwy",
    "sg:city":"Burlington",
    "sg:classifiers":[
        {
            "category":"Real Estate",
            "subcategory":"Developer",
            "type":"Services"
        }
    ],
    "sg:phone":"+1 802 862 1223",
    "sg:postcode":"05401",
    "sg:province":"VT",
    "wof:name":"Investment Properties",
    "wof:placetype":"venue"
},
  "geometry": {"coordinates":[-73.219043,44.450932],"type":"Point"}
}