{
  "type": "Feature",
  "properties": {
    "iso:country":"US",
    "sg:address":"98 Mill St",
    "sg:city":"Northfield Falls",
    "sg:classifiers":[
        {
            "category":"Shopping",
            "type":"Retail Goods"
        }
    ],
    "sg:phone":"+1 802 485 4900",
    "sg:postcode":"05664",
    "sg:province":"VT",
    "sg:tags":[
        "product",
        "wood"
    ],
    "wof:name":"Blackbear Wood Products Inc",
    "wof:placetype":"venue"
},
  "geometry": {"coordinates":[-72.64986399999999,44.17388],"type":"Point"}
}