{
  "type": "Feature",
  "properties": {
    "addr:full":"1076 Williston Rd South Burlington VT 05403",
    "addr:housenumber":"1076",
    "addr:postcode":"05403",
    "addr:street":"Williston Rd",
    "iso:country":"US",
    "sg:address":"1076 Williston Rd",
    "sg:city":"South Burlington",
    "sg:classifiers":[
        {
            "category":"Travel",
            "subcategory":"Hotels & Motels",
            "type":"Entertainment"
        }
    ],
    "sg:phone":"+1 802 862 6585",
    "sg:postcode":"05403",
    "sg:province":"VT",
    "sg:website":"www.windjammerrestaurant.com",
    "wof:name":"Windjammer Restaurant",
    "wof:placetype":"venue"
},
  "geometry": {"coordinates":[-73.17048200000001,44.466746],"type":"Point"}
}