{
  "type": "Feature",
  "properties": {
    "iso:country":"US",
    "sg:address":"742 Jennings Rd",
    "sg:city":"Bradford",
    "sg:classifiers":[
        {
            "category":"Professional",
            "subcategory":"Computer Services",
            "type":"Services"
        }
    ],
    "sg:phone":"+1 802 222 3333",
    "sg:postcode":"05033",
    "sg:province":"VT",
    "sg:tags":[
        "related"
    ],
    "wof:name":"Cubeglobal",
    "wof:placetype":"venue"
},
  "geometry": {"coordinates":[-72.20711799999999,43.982522],"type":"Point"}
}