{
  "type": "Feature",
  "properties": {
    "addr:full":"4991 State Rte 313 Arlington VT 05250",
    "addr:housenumber":"4991",
    "addr:postcode":"05250",
    "addr:street":"State Rte 313",
    "iso:country":"US",
    "sg:address":"4991 State Rte 313",
    "sg:city":"Arlington",
    "sg:classifiers":[
        {
            "category":"Professional",
            "subcategory":"Business Services",
            "type":"Services"
        }
    ],
    "sg:phone":"+1 802 375 6497",
    "sg:postcode":"05250",
    "sg:province":"VT",
    "wof:name":"Battenkill Technical Assoc",
    "wof:placetype":"venue"
},
  "geometry": {"coordinates":[-73.22998699999999,43.1045],"type":"Point"}
}