{
  "type": "Feature",
  "properties": {
    "iso:country":"US",
    "sg:address":"52 White River Ln",
    "sg:city":"White River Jct",
    "sg:classifiers":[
        {
            "category":"Autos & Motor Vehicles",
            "subcategory":"Auto Supplies",
            "type":"Retail Goods"
        }
    ],
    "sg:phone":"+1 802 295 6005",
    "sg:postcode":"05001",
    "sg:province":"VT",
    "sg:tags":[
        "tire"
    ],
    "wof:name":"Tip Top Tire",
    "wof:placetype":"venue"
},
  "geometry": {"coordinates":[-72.43223500000001,43.723481],"type":"Point"}
}