{
  "type": "Feature",
  "properties": {
    "addr:full":"25 Raymond Rd Colchester VT 05446",
    "addr:housenumber":"25",
    "addr:postcode":"05446",
    "addr:street":"Raymond Rd",
    "iso:country":"US",
    "sg:address":"25 Raymond Rd",
    "sg:city":"Colchester",
    "sg:classifiers":[
        {
            "category":"Recreation",
            "type":"Entertainment"
        }
    ],
    "sg:phone":"+1 802 893 8893",
    "sg:postcode":"05446",
    "sg:province":"VT",
    "sg:tags":[
        "arts",
        "facility",
        "instruction",
        "martial",
        "fitness",
        "physical"
    ],
    "wof:name":"Martial Way Self Defense Ctr",
    "wof:placetype":"venue"
},
  "geometry": {"coordinates":[-73.18858,44.594515],"type":"Point"}
}