{
  "type": "Feature",
  "properties": {
    "iso:country":"US",
    "sg:address":"57 Monument Ave",
    "sg:city":"Bennington",
    "sg:classifiers":[
        {
            "category":"Shopping",
            "subcategory":"Clothing, Apparel, & Fashions",
            "type":"Retail Goods"
        }
    ],
    "sg:phone":"+1 802 447 8227",
    "sg:postcode":"05201",
    "sg:province":"VT",
    "sg:tags":[
        "sportswear"
    ],
    "wof:name":"Wicked Smart Inc",
    "wof:placetype":"venue"
},
  "geometry": {"coordinates":[-73.21346,42.884322],"type":"Point"}
}