{
  "type": "Feature",
  "properties": {
    "iso:country":"US",
    "sg:address":"195 S Prospect St",
    "sg:city":"Burlington",
    "sg:classifiers":[
        {
            "category":"Professional",
            "type":"Services"
        }
    ],
    "sg:phone":"+1 802 864 7645",
    "sg:postcode":"05401",
    "sg:province":"VT",
    "sg:tags":[
        "consulting",
        "business"
    ],
    "wof:name":"Robert V Daniels",
    "wof:placetype":"venue"
},
  "geometry": {"coordinates":[-73.200744,44.475744],"type":"Point"}
}