{
  "type": "Feature",
  "properties": {
    "iso:country":"US",
    "sg:address":"1090 State Rte 30",
    "sg:city":"Dorset",
    "sg:classifiers":[
        {
            "category":"Personal",
            "subcategory":"Beauty Salon",
            "type":"Services"
        }
    ],
    "sg:phone":"+1 802 362 4435",
    "sg:postcode":"05251",
    "sg:province":"VT",
    "sg:tags":[
        "treatment",
        "skin"
    ],
    "wof:name":"Jenny Farrands Skin & Body Cr",
    "wof:placetype":"venue"
},
  "geometry": {"coordinates":[-73.075,43.226671],"type":"Point"}
}