{
  "type": "Feature",
  "properties": {
    "iso:country":"US",
    "sg:address":"427 State Rte 4a",
    "sg:city":"Bomoseen",
    "sg:classifiers":[
        {
            "category":"Home & Garden",
            "subcategory":"Building Materials",
            "type":"Retail Goods"
        }
    ],
    "sg:phone":"+1 802 468 5676",
    "sg:postcode":"05735",
    "sg:province":"VT",
    "sg:website":"www.gilmorehomecenter.com",
    "wof:name":"Gilmore Home Ctr",
    "wof:placetype":"venue"
},
  "geometry": {"coordinates":[-73.21600100000001,43.60819],"type":"Point"}
}