{
  "type": "Feature",
  "properties": {
    "iso:country":"US",
    "sg:address":"95 Powder Horn Glen Rd",
    "sg:city":"Montpelier",
    "sg:classifiers":[
        {
            "category":"Home & Garden",
            "subcategory":"Home Furnishings",
            "type":"Retail Goods"
        }
    ],
    "sg:phone":"+1 802 223 8926",
    "sg:postcode":"05602",
    "sg:province":"VT",
    "sg:tags":[
        "mfg"
    ],
    "wof:name":"Thistle Hill Pottery",
    "wof:placetype":"venue"
},
  "geometry": {"coordinates":[-72.530536,44.295021],"type":"Point"}
}