{
  "type": "Feature",
  "properties": {
    "addr:full":"512 Woodstock Rd Woodstock VT 05091",
    "addr:housenumber":"512",
    "addr:postcode":"05091",
    "addr:street":"Woodstock Rd",
    "iso:country":"US",
    "sg:address":"512 Woodstock Rd",
    "sg:city":"Woodstock",
    "sg:classifiers":[
        {
            "category":"Manufacturing",
            "subcategory":"Printing",
            "type":"Manufacturing & Wholesale Goods"
        }
    ],
    "sg:phone":"+1 802 457 1205",
    "sg:postcode":"05091",
    "sg:province":"VT",
    "sg:tags":[
        "work",
        "bookbinding",
        "related"
    ],
    "sg:website":"www.lewisbibles.com",
    "wof:name":"Robert F Lewis Inc",
    "wof:placetype":"venue"
},
  "geometry": {"coordinates":[-72.506473,43.627484],"type":"Point"}
}