{
  "type": "Feature",
  "properties": {
    "iso:country":"US",
    "sg:address":"280 Flynn Ave",
    "sg:city":"Burlington",
    "sg:classifiers":[
        {
            "category":"Wholesale",
            "subcategory":"Machinery & Supplies",
            "type":"Manufacturing & Wholesale Goods"
        }
    ],
    "sg:phone":"+1 802 860 9977",
    "sg:postcode":"05401",
    "sg:province":"VT",
    "sg:tags":[
        "equipment",
        "industrial"
    ],
    "wof:name":"Amphitek",
    "wof:placetype":"venue"
},
  "geometry": {"coordinates":[-73.21459400000001,44.455517],"type":"Point"}
}