{
  "type": "Feature",
  "properties": {
    "iso:country":"US",
    "sg:address":"16 Church St",
    "sg:city":"Barton",
    "sg:classifiers":[
        {
            "category":"Wholesale",
            "subcategory":"Drugs",
            "type":"Manufacturing & Wholesale Goods"
        },
        {
            "category":"Shopping",
            "subcategory":"Pharmacy",
            "type":"Retail Goods"
        }
    ],
    "sg:phone":"+1 802 525 4098",
    "sg:postcode":"05822",
    "sg:province":"VT",
    "wof:name":"Barton Pharmacy Inc",
    "wof:placetype":"venue"
},
  "geometry": {"coordinates":[-72.180198,44.750821],"type":"Point"}
}