{
  "type": "Feature",
  "properties": {
    "iso:country":"US",
    "sg:address":"1300 Putney Rd",
    "sg:city":"Brattleboro",
    "sg:classifiers":[
        {
            "category":"Building & Trades",
            "subcategory":"Construction",
            "type":"Services"
        }
    ],
    "sg:phone":"+1 802 257 4999",
    "sg:postcode":"05301",
    "sg:province":"VT",
    "sg:tags":[
        "designer",
        "dealer",
        "pool",
        "swimming"
    ],
    "wof:name":"Brattleboro Pool & Spa",
    "wof:placetype":"venue"
},
  "geometry": {"coordinates":[-72.55127899999999,42.893144],"type":"Point"}
}