{
  "type": "Feature",
  "properties": {
    "iso:country":"US",
    "sg:address":"86 N Main St",
    "sg:city":"Barre",
    "sg:classifiers":[
        {
            "category":"Shopping",
            "subcategory":"Clothing, Apparel, & Fashions",
            "type":"Retail Goods"
        }
    ],
    "sg:phone":"+1 802 476 7912",
    "sg:postcode":"05641",
    "sg:province":"VT",
    "sg:tags":[
        "accessory"
    ],
    "wof:name":"Harvard Clothes Shop",
    "wof:placetype":"venue"
},
  "geometry": {"coordinates":[-72.501762,44.197453],"type":"Point"}
}