{
  "type": "Feature",
  "properties": {
    "addr:full":"128 Intervale Rd Burlington VT 05401",
    "addr:housenumber":"128",
    "addr:postcode":"05401",
    "addr:street":"Intervale Rd",
    "iso:country":"US",
    "sg:address":"128 Intervale Rd",
    "sg:city":"Burlington",
    "sg:classifiers":[
        {
            "category":"Shopping",
            "subcategory":"Catalog Store",
            "type":"Retail Goods"
        }
    ],
    "sg:phone":"+1 802 660 3500",
    "sg:postcode":"05401",
    "sg:province":"VT",
    "sg:tags":[
        "farm",
        "mail",
        "house",
        "supply"
    ],
    "wof:name":"Gardeners Supply Co",
    "wof:placetype":"venue"
},
  "geometry": {"coordinates":[-73.205279,44.492609],"type":"Point"}
}