{
  "type": "Feature",
  "properties": {
    "iso:country":"US",
    "sg:address":"1350 Shelburne Rd",
    "sg:city":"South Burlington",
    "sg:classifiers":[
        {
            "category":"Manufacturing",
            "subcategory":"Printing",
            "type":"Manufacturing & Wholesale Goods"
        }
    ],
    "sg:phone":"+1 802 863 8287",
    "sg:postcode":"05403",
    "sg:province":"VT",
    "sg:tags":[
        "publisher"
    ],
    "wof:name":"Ski Magazine",
    "wof:placetype":"venue"
},
  "geometry": {"coordinates":[-73.210657,44.435582],"type":"Point"}
}