{
  "type": "Feature",
  "properties": {
    "iso:country":"US",
    "sg:address":"25 Curtis Ave",
    "sg:city":"Rutland",
    "sg:phone":"+1 802 773 8400",
    "sg:postcode":"05701",
    "sg:province":"VT",
    "sg:tags":[
        "equipment",
        "commercial"
    ],
    "wof:name":"Steiger Supply",
    "wof:placetype":"venue"
},
  "geometry": {"coordinates":[-72.966926,43.591915],"type":"Point"}
}