{
  "type": "Feature",
  "properties": {
    "iso:country":"US",
    "sg:address":"85 Main St",
    "sg:city":"Brattleboro",
    "sg:classifiers":[
        {
            "category":"Shopping",
            "subcategory":"Stationery & Office Supplies",
            "type":"Retail Goods"
        }
    ],
    "sg:phone":"+1 802 254 2328",
    "sg:postcode":"05301",
    "sg:province":"VT",
    "wof:name":"Baker's Office Products",
    "wof:placetype":"venue"
},
  "geometry": {"coordinates":[-72.55766800000001,42.851437],"type":"Point"}
}