{
  "type": "Feature",
  "properties": {
    "iso:country":"US",
    "sg:address":"2447 US Hwy 5",
    "sg:city":"Derby",
    "sg:classifiers":[
        {
            "category":"Wholesale",
            "subcategory":"Machinery & Supplies",
            "type":"Manufacturing & Wholesale Goods"
        }
    ],
    "sg:phone":"+1 802 766 4908",
    "sg:postcode":"05829",
    "sg:province":"VT",
    "wof:name":"J C's Green Mountain Granite",
    "wof:placetype":"venue"
},
  "geometry": {"coordinates":[-72.12545900000001,44.9629],"type":"Point"}
}