{
  "type": "Feature",
  "properties": {
    "iso:country":"US",
    "sg:address":"22 Brookside Rd",
    "sg:city":"Westford",
    "sg:classifiers":[
        {
            "category":"Shopping",
            "subcategory":"Bicycles & Sporting Goods",
            "type":"Retail Goods"
        }
    ],
    "sg:phone":"+1 802 878 4690",
    "sg:postcode":"05494",
    "sg:province":"VT",
    "sg:tags":[
        "ski",
        "sales",
        "wax"
    ],
    "wof:name":"Hwk USA",
    "wof:placetype":"venue"
},
  "geometry": {"coordinates":[-73.029582,44.591894],"type":"Point"}
}