{
  "type": "Feature",
  "properties": {
    "iso:country":"US",
    "sg:address":"269 Gilman Ave",
    "sg:city":"Saint Johnsbury",
    "sg:classifiers":[
        {
            "category":"Manufacturing",
            "subcategory":"Food",
            "type":"Manufacturing & Wholesale Goods"
        }
    ],
    "sg:phone":"+1 802 748 5607",
    "sg:postcode":"05819",
    "sg:province":"VT",
    "sg:tags":[
        "juice",
        "product"
    ],
    "wof:name":"Juice Products",
    "wof:placetype":"venue"
},
  "geometry": {"coordinates":[-72.010757,44.425925],"type":"Point"}
}