{
  "type": "Feature",
  "properties": {
    "addr:full":"91 Old Orchard Way Ferrisburg VT 05456",
    "addr:housenumber":"91",
    "addr:postcode":"05456",
    "addr:street":"Old Orchard Way",
    "iso:country":"US",
    "sg:address":"91 Old Orchard Way",
    "sg:city":"Ferrisburg",
    "sg:classifiers":[
        {
            "category":"Building & Trades",
            "subcategory":"Construction",
            "type":"Services"
        }
    ],
    "sg:phone":"+1 802 877 9906",
    "sg:postcode":"05456",
    "sg:province":"VT",
    "sg:tags":[
        "contractor"
    ],
    "wof:name":"Krh Masonry",
    "wof:placetype":"venue"
},
  "geometry": {"coordinates":[-73.246945,44.212453],"type":"Point"}
}