{
  "type": "Feature",
  "properties": {
    "addr:full":"250 Huntington Woods Rd Huntington VT 05462",
    "addr:housenumber":"250",
    "addr:postcode":"05462",
    "addr:street":"Huntington Woods Rd",
    "iso:country":"US",
    "sg:address":"250 Huntington Woods Rd",
    "sg:city":"Huntington",
    "sg:classifiers":[
        {
            "category":"Retail",
            "subcategory":"Repair Shop",
            "type":"Services"
        }
    ],
    "sg:phone":"+1 802 434 5041",
    "sg:postcode":"05462",
    "sg:province":"VT",
    "sg:tags":[
        "tool",
        "parts"
    ],
    "wof:name":"Tool Wizard",
    "wof:placetype":"venue"
},
  "geometry": {"coordinates":[-72.982167,44.322363],"type":"Point"}
}