{
  "type": "Feature",
  "properties": {
    "iso:country":"US",
    "sg:address":"151 McNall Rd",
    "sg:city":"Fairfax",
    "sg:classifiers":[
        {
            "category":"Farming",
            "subcategory":"Dairy Farm",
            "type":"Manufacturing & Wholesale Goods"
        }
    ],
    "sg:phone":"+1 802 849 6612",
    "sg:postcode":"05454",
    "sg:province":"VT",
    "wof:name":"Two River Farm",
    "wof:placetype":"venue"
},
  "geometry": {"coordinates":[-73.02659199999999,44.656194],"type":"Point"}
}