{
  "type": "Feature",
  "properties": {
    "iso:country":"US",
    "sg:address":"59 Ave C",
    "sg:city":"Williston",
    "sg:classifiers":[
        {
            "category":"Freight",
            "type":"Transportation"
        }
    ],
    "sg:phone":"+1 802 863 5062",
    "sg:postcode":"05495",
    "sg:province":"VT",
    "sg:tags":[
        "trucking"
    ],
    "sg:website":"www.mylandair.com",
    "wof:name":"Land Air Express New England",
    "wof:placetype":"venue"
},
  "geometry": {"coordinates":[-73.126644,44.465631],"type":"Point"}
}