{
  "type": "Feature",
  "properties": {
    "iso:country":"US",
    "sg:address":"774 US Hwy 2",
    "sg:city":"St Johnsbury",
    "sg:classifiers":[
        {
            "category":"Professional",
            "subcategory":"Business Services",
            "type":"Services"
        }
    ],
    "sg:phone":"+1 802 748 9144",
    "sg:postcode":"05819",
    "sg:province":"VT",
    "sg:tags":[
        "packaging"
    ],
    "wof:name":"Vermont Packaging",
    "wof:placetype":"venue"
},
  "geometry": {"coordinates":[-71.998929,44.421586],"type":"Point"}
}