{
  "type": "Feature",
  "properties": {
    "iso:country":"US",
    "sg:address":"364 Twp Hwy 4",
    "sg:city":"Saint Johnsbury",
    "sg:classifiers":[
        {
            "category":"Education",
            "subcategory":"School",
            "type":"Public Place"
        }
    ],
    "sg:phone":"+1 802 748 5624",
    "sg:postcode":"05819",
    "sg:province":"VT",
    "wof:name":"Adult Basic Education Program",
    "wof:placetype":"venue"
},
  "geometry": {"coordinates":[-71.938146,44.432975],"type":"Point"}
}