{
  "type": "Feature",
  "properties": {
    "addr:full":"1333 Shelburne Rd South Burlington VT 05403",
    "addr:housenumber":"1333",
    "addr:postcode":"05403",
    "addr:street":"Shelburne Rd",
    "iso:country":"US",
    "sg:address":"1333 Shelburne Rd",
    "sg:city":"South Burlington",
    "sg:classifiers":[
        {
            "category":"Shopping",
            "subcategory":"Shoes",
            "type":"Retail Goods"
        }
    ],
    "sg:phone":"+1 802 862 2666",
    "sg:postcode":"05403",
    "sg:province":"VT",
    "wof:name":"Sportshoe Center",
    "wof:placetype":"venue"
},
  "geometry": {"coordinates":[-73.210527,44.435335],"type":"Point"}
}