{
  "type": "Feature",
  "properties": {
    "addr:full":"13 Upper Rd Manchester Center VT 05255",
    "addr:housenumber":"13",
    "addr:postcode":"05255",
    "addr:street":"Upper Rd",
    "iso:country":"US",
    "sg:address":"13 Upper Rd",
    "sg:city":"Manchester Center",
    "sg:classifiers":[
        {
            "category":"Utilities",
            "subcategory":"Refuse",
            "type":"Services"
        }
    ],
    "sg:phone":"+1 802 362 2098",
    "sg:postcode":"05255",
    "sg:province":"VT",
    "sg:tags":[
        "system"
    ],
    "wof:name":"Breton Townslee",
    "wof:placetype":"venue"
},
  "geometry": {"coordinates":[-73.028942,43.17875],"type":"Point"}
}