{
  "type": "Feature",
  "properties": {
    "iso:country":"US",
    "sg:address":"14 Summit St",
    "sg:city":"Burlington",
    "sg:classifiers":[
        {
            "category":"Real Estate",
            "subcategory":"Real Estate Agent",
            "type":"Services"
        }
    ],
    "sg:phone":"+1 802 865 6991",
    "sg:postcode":"05401",
    "sg:province":"VT",
    "sg:tags":[
        "consultant"
    ],
    "wof:name":"Heartland Group Community Dev",
    "wof:placetype":"venue"
},
  "geometry": {"coordinates":[-73.202179,44.474562],"type":"Point"}
}