{
  "type": "Feature",
  "properties": {
    "addr:full":"188 Sweet Pond Rd Brattleboro VT 05301",
    "addr:housenumber":"188",
    "addr:postcode":"05301",
    "addr:street":"Sweet Pond Rd",
    "iso:country":"US",
    "sg:address":"188 Sweet Pond Rd",
    "sg:city":"Brattleboro",
    "sg:classifiers":[
        {
            "category":"Utilities",
            "subcategory":"Refuse",
            "type":"Services"
        }
    ],
    "sg:phone":"+1 802 257 1211",
    "sg:postcode":"05301",
    "sg:province":"VT",
    "sg:tags":[
        "garbage",
        "system",
        "collection"
    ],
    "wof:name":"Reed & Sons Rubbish",
    "wof:placetype":"venue"
},
  "geometry": {"coordinates":[-72.631775,42.782696],"type":"Point"}
}