{
  "type": "Feature",
  "properties": {
    "iso:country":"US",
    "sg:address":"1306 State Rte 125",
    "sg:city":"Ripton",
    "sg:classifiers":[
        {
            "category":"Professional",
            "subcategory":"Engineering",
            "type":"Services"
        }
    ],
    "sg:phone":"+1 802 233 1489",
    "sg:postcode":"05766",
    "sg:province":"VT",
    "wof:name":"Burgess Edge",
    "wof:placetype":"venue"
},
  "geometry": {"coordinates":[-73.038219,43.9744],"type":"Point"}
}