{
  "type": "Feature",
  "properties": {
    "addr:full":"16 Derby Cir South Burlington VT 05403",
    "addr:housenumber":"16",
    "addr:postcode":"05403",
    "addr:street":"Derby Cir",
    "iso:country":"US",
    "sg:address":"16 Derby Cir",
    "sg:city":"South Burlington",
    "sg:classifiers":[
        {
            "category":"Shopping",
            "type":"Retail Goods"
        }
    ],
    "sg:phone":"+1 802 862 2102",
    "sg:postcode":"05403",
    "sg:province":"VT",
    "sg:tags":[
        "cosmetic",
        "perfume"
    ],
    "wof:name":"Mary Kay Cosmetics",
    "wof:placetype":"venue"
},
  "geometry": {"coordinates":[-73.160518,44.450353],"type":"Point"}
}