{
  "type": "Feature",
  "properties": {
    "iso:country":"US",
    "sg:address":"158 West St",
    "sg:city":"Essex Junction",
    "sg:classifiers":[
        {
            "category":"Organizations",
            "subcategory":"Religious Organization",
            "type":"Services"
        }
    ],
    "sg:phone":"+1 802 878 8271",
    "sg:postcode":"05452",
    "sg:province":"VT",
    "sg:tags":[
        "church"
    ],
    "wof:name":"St Lawrence Church Rectory",
    "wof:placetype":"venue"
},
  "geometry": {"coordinates":[-73.129334,44.495188],"type":"Point"}
}