{
  "type": "Feature",
  "properties": {
    "iso:country":"US",
    "sg:address":"63 Elm St",
    "sg:city":"Montpelier",
    "sg:classifiers":[
        {
            "category":"Real Estate",
            "subcategory":"Real Estate Agent",
            "type":"Services"
        }
    ],
    "sg:phone":"+1 802 229 4807",
    "sg:postcode":"05602",
    "sg:province":"VT",
    "sg:tags":[
        "appraiser"
    ],
    "wof:name":"Martin Appraisal Svc",
    "wof:placetype":"venue"
},
  "geometry": {"coordinates":[-72.57543699999999,44.261663],"type":"Point"}
}