{
  "type": "Feature",
  "properties": {
    "addr:full":"270 College St Burlington VT 05401",
    "addr:housenumber":"270",
    "addr:postcode":"05401",
    "addr:street":"College St",
    "iso:country":"US",
    "sg:address":"270 College St",
    "sg:city":"Burlington",
    "sg:classifiers":[
        {
            "category":"Personal",
            "type":"Services"
        }
    ],
    "sg:phone":"+1 802 363 5282",
    "sg:postcode":"05401",
    "sg:province":"VT",
    "sg:tags":[
        "therapist",
        "massage"
    ],
    "wof:name":"Joy Of Being Healing Arts",
    "wof:placetype":"venue"
},
  "geometry": {"coordinates":[-73.207071,44.477491],"type":"Point"}
}