{
  "type": "Feature",
  "properties": {
    "iso:country":"US",
    "sg:address":"227 Chapel Rd",
    "sg:city":"Bennington",
    "sg:classifiers":[
        {
            "category":"Manufacturing",
            "subcategory":"Buildings",
            "type":"Manufacturing & Wholesale Goods"
        },
        {
            "category":"Building & Trades",
            "subcategory":"Construction",
            "type":"Services"
        }
    ],
    "sg:phone":"+1 802 442 3882",
    "sg:postcode":"05201",
    "sg:province":"VT",
    "sg:tags":[
        "industrial",
        "builder",
        "system",
        "specialty",
        "heating",
        "contractor",
        "contractors-commercial",
        "home",
        "air conditioning",
        "carpenter"
    ],
    "wof:name":"Krawczyk's Carpentry",
    "wof:placetype":"venue"
},
  "geometry": {"coordinates":[-73.181529,42.89345],"type":"Point"}
}