{
  "type": "Feature",
  "properties": {
    "iso:country":"US",
    "sg:address":"21 Sandhill Rd",
    "sg:city":"Fairfax",
    "sg:classifiers":[
        {
            "category":"Shopping",
            "subcategory":"Bicycles & Sporting Goods",
            "type":"Retail Goods"
        }
    ],
    "sg:phone":"+1 802 849 2625",
    "sg:postcode":"05454",
    "sg:province":"VT",
    "wof:name":"Green Mountain Representatives",
    "wof:placetype":"venue"
},
  "geometry": {"coordinates":[-73.004204,44.651248],"type":"Point"}
}