{
  "type": "Feature",
  "properties": {
    "iso:country":"US",
    "sg:address":"205 Dorset St",
    "sg:city":"South Burlington",
    "sg:classifiers":[
        {
            "category":"Personal",
            "type":"Services"
        }
    ],
    "sg:phone":"+1 802 658 7715",
    "sg:postcode":"05403",
    "sg:province":"VT",
    "sg:tags":[
        "therapist",
        "massage"
    ],
    "wof:name":"Touchstone Healing Arts",
    "wof:placetype":"venue"
},
  "geometry": {"coordinates":[-73.181358,44.466301],"type":"Point"}
}