{
  "type": "Feature",
  "properties": {
    "iso:country":"US",
    "sg:address":"24 4th St",
    "sg:city":"Swanton",
    "sg:classifiers":[
        {
            "category":"Education",
            "subcategory":"School",
            "type":"Public Place"
        }
    ],
    "sg:phone":"+1 802 868 5346",
    "sg:postcode":"05488",
    "sg:province":"VT",
    "wof:name":"Swanton Central School",
    "wof:placetype":"venue"
},
  "geometry": {"coordinates":[-73.11635,44.914235],"type":"Point"}
}