{
  "type": "Feature",
  "properties": {
    "addr:full":"6378 State Rte 7a Arlington VT 05250",
    "addr:housenumber":"6378",
    "addr:postcode":"05250",
    "addr:street":"State Rte 7A",
    "iso:country":"US",
    "sg:address":"6378 State Rte 7a",
    "sg:city":"Arlington",
    "sg:classifiers":[
        {
            "category":"Real Estate",
            "subcategory":"Real Estate Agent",
            "type":"Services"
        }
    ],
    "sg:phone":"+1 802 430 0140",
    "sg:postcode":"05250",
    "sg:province":"VT",
    "wof:name":"Vermont Commercial Real Estate",
    "wof:placetype":"venue"
},
  "geometry": {"coordinates":[-73.13829200000001,43.101175],"type":"Point"}
}