{
  "type": "Feature",
  "properties": {
    "addr:full":"76 Birch Ct Burlington VT 05408",
    "addr:housenumber":"76",
    "addr:postcode":"05408",
    "addr:street":"Birch Ct",
    "iso:country":"US",
    "sg:address":"76 Birch Ct",
    "sg:city":"Burlington",
    "sg:classifiers":[
        {
            "category":"Freight",
            "type":"Transportation"
        }
    ],
    "sg:phone":"+1 802 658 0306",
    "sg:postcode":"05408",
    "sg:province":"VT",
    "sg:tags":[
        "operator",
        "local",
        "trucking"
    ],
    "wof:name":"Little Roger Trucking & Clg",
    "wof:placetype":"venue"
},
  "geometry": {"coordinates":[-72.49408,44.184889],"type":"Point"}
}