{
  "type": "Feature",
  "properties": {
    "iso:country":"US",
    "sg:address":"4 Main St",
    "sg:city":"Proctor",
    "sg:classifiers":[
        {
            "category":"Education",
            "subcategory":"Library",
            "type":"Public Place"
        }
    ],
    "sg:phone":"+1 802 459 3539",
    "sg:postcode":"05765",
    "sg:province":"VT",
    "wof:name":"Proctor Free Library",
    "wof:placetype":"venue"
},
  "geometry": {"coordinates":[-73.032568,43.661437],"type":"Point"}
}