{
  "type": "Feature",
  "properties": {
    "iso:country":"US",
    "sg:address":"302 W River Rd",
    "sg:city":"Lincoln",
    "sg:classifiers":[
        {
            "category":"Retail",
            "subcategory":"Repair Shop",
            "type":"Services"
        }
    ],
    "sg:phone":"+1 802 453 2039",
    "sg:postcode":"05443",
    "sg:province":"VT",
    "sg:tags":[
        "upholsterer"
    ],
    "wof:name":"Lise Lathrop Upholstery",
    "wof:placetype":"venue"
},
  "geometry": {"coordinates":[-73.000449,44.109007],"type":"Point"}
}