{
  "type": "Feature",
  "properties": {
    "iso:country":"US",
    "sg:address":"162 S Main St",
    "sg:city":"Rutland",
    "sg:classifiers":[
        {
            "category":"Professional",
            "subcategory":"Business Services",
            "type":"Services"
        }
    ],
    "sg:phone":"+1 802 775 0893",
    "sg:postcode":"05701",
    "sg:province":"VT",
    "sg:tags":[
        "information",
        "referral"
    ],
    "wof:name":"Medicare Information SSA",
    "wof:placetype":"venue"
},
  "geometry": {"coordinates":[-72.971954,43.606407],"type":"Point"}
}