{
  "type": "Feature",
  "properties": {
    "iso:country":"US",
    "sg:address":"7 Park Ave",
    "sg:city":"Williston",
    "sg:classifiers":[
        {
            "category":"Building & Trades",
            "subcategory":"Equipment Rental",
            "type":"Services"
        }
    ],
    "sg:phone":"+1 802 878 7279",
    "sg:postcode":"05495",
    "sg:province":"VT",
    "sg:tags":[
        "medical",
        "rent",
        "specialty"
    ],
    "wof:name":"K C I USA Inc",
    "wof:placetype":"venue"
},
  "geometry": {"coordinates":[-73.115897,44.475519],"type":"Point"}
}