{
  "type": "Feature",
  "properties": {
    "iso:country":"US",
    "sg:address":"282 Berlin Mall Rd",
    "sg:city":"Berlin",
    "sg:classifiers":[
        {
            "category":"Personal",
            "subcategory":"Beauty Salon",
            "type":"Services"
        }
    ],
    "sg:phone":"+1 802 223 2170",
    "sg:postcode":"05602",
    "sg:province":"VT",
    "wof:name":"Regis Salons",
    "wof:placetype":"venue"
},
  "geometry": {"coordinates":[-72.565186,44.215891],"type":"Point"}
}