{
  "type": "Feature",
  "properties": {
    "iso:country":"US",
    "sg:address":"37 Russell St",
    "sg:city":"Burlington",
    "sg:classifiers":[
        {
            "category":"Professional",
            "type":"Services"
        }
    ],
    "sg:phone":"+1 802 658 1723",
    "sg:postcode":"05401",
    "sg:province":"VT",
    "wof:name":"Effects Personal Training",
    "wof:placetype":"venue"
},
  "geometry": {"coordinates":[-73.206968,44.485185],"type":"Point"}
}