{
  "type": "Feature",
  "properties": {
    "iso:country":"US",
    "sg:address":"21 Quail Hollow Dr",
    "sg:city":"Milton",
    "sg:classifiers":[
        {
            "category":"Manufacturing",
            "subcategory":"Printing",
            "type":"Manufacturing & Wholesale Goods"
        }
    ],
    "sg:phone":"+1 802 893 0751",
    "sg:postcode":"05468",
    "sg:province":"VT",
    "sg:tags":[
        "book"
    ],
    "wof:name":"PC Images",
    "wof:placetype":"venue"
},
  "geometry": {"coordinates":[-73.131083,44.64433],"type":"Point"}
}