{
  "type": "Feature",
  "properties": {
    "iso:country":"US",
    "sg:address":"371 River St",
    "sg:city":"Montpelier",
    "sg:classifiers":[
        {
            "category":"Banks & Credit Unions",
            "subcategory":"Investment Brokerage",
            "type":"Services"
        }
    ],
    "sg:phone":"+1 802 223 0600",
    "sg:postcode":"05602",
    "sg:province":"VT",
    "sg:tags":[
        "consultant",
        "planning",
        "financial"
    ],
    "wof:name":"American Express Financial Adv",
    "wof:placetype":"venue"
},
  "geometry": {"coordinates":[-72.553535,44.23737],"type":"Point"}
}