{
  "type": "Feature",
  "properties": {
    "iso:country":"US",
    "sg:address":"228 Lincoln Ave",
    "sg:city":"Rutland",
    "sg:classifiers":[
        {
            "category":"Building & Trades",
            "subcategory":"Electrical",
            "type":"Services"
        }
    ],
    "sg:phone":"+1 802 773 0670",
    "sg:postcode":"05701",
    "sg:province":"VT",
    "sg:tags":[
        "electrical",
        "contractor"
    ],
    "wof:name":"J Browne Electric",
    "wof:placetype":"venue"
},
  "geometry": {"coordinates":[-72.978404,43.623463],"type":"Point"}
}