{
  "type": "Feature",
  "properties": {
    "iso:country":"US",
    "sg:address":"55 Church St",
    "sg:city":"Swanton",
    "sg:classifiers":[
        {
            "category":"Social Services",
            "subcategory":"Adult Care",
            "type":"Services"
        }
    ],
    "sg:phone":"+1 802 868 8904",
    "sg:postcode":"05488",
    "sg:province":"VT",
    "sg:tags":[
        "residential"
    ],
    "wof:name":"Lake Champlain Hsing Ventures",
    "wof:placetype":"venue"
},
  "geometry": {"coordinates":[-73.12261599999999,44.915515],"type":"Point"}
}