{
  "type": "Feature",
  "properties": {
    "addr:full":"595 Main St West Rutland VT 05777",
    "addr:housenumber":"595",
    "addr:postcode":"05777",
    "addr:street":"Main St",
    "iso:country":"US",
    "sg:address":"595 Main St",
    "sg:city":"West Rutland",
    "sg:classifiers":[
        {
            "category":"Education",
            "subcategory":"Library",
            "type":"Public Place"
        }
    ],
    "sg:phone":"+1 802 438 2964",
    "sg:postcode":"05777",
    "sg:province":"VT",
    "wof:name":"West Rutland Free Library Corp",
    "wof:placetype":"venue"
},
  "geometry": {"coordinates":[-73.048624,43.594548],"type":"Point"}
}