{
  "type": "Feature",
  "properties": {
    "addr:full":"36 Brickyard Rd Essex Junction VT 05452",
    "addr:housenumber":"36",
    "addr:postcode":"05452",
    "addr:street":"Brickyard Rd",
    "iso:country":"US",
    "sg:address":"36 Brickyard Rd",
    "sg:city":"Essex Junction",
    "sg:classifiers":[
        {
            "category":"Professional",
            "type":"Services"
        }
    ],
    "sg:phone":"+1 802 878 7124",
    "sg:postcode":"05452",
    "sg:province":"VT",
    "sg:tags":[
        "information",
        "bureau"
    ],
    "wof:name":"Fishing Info Svcs & Hotline",
    "wof:placetype":"venue"
},
  "geometry": {"coordinates":[-73.09711799999999,44.493226],"type":"Point"}
}