{
  "type": "Feature",
  "properties": {
    "iso:country":"US",
    "sg:address":"159 Bank St",
    "sg:city":"Burlington",
    "sg:classifiers":[
        {
            "category":"Food & Beverages",
            "subcategory":"Bakery",
            "type":"Retail Goods"
        }
    ],
    "sg:phone":"+1 802 660 4020",
    "sg:postcode":"05401",
    "sg:province":"VT",
    "sg:tags":[
        "bagel"
    ],
    "wof:name":"Bruegger's Enterprise Inc",
    "wof:placetype":"venue"
},
  "geometry": {"coordinates":[-73.213651,44.478098],"type":"Point"}
}