{
  "type": "Feature",
  "properties": {
    "iso:country":"US",
    "sg:address":"22 Main St",
    "sg:city":"Winooski",
    "sg:classifiers":[
        {
            "category":"Restaurant",
            "type":"Food & Drink"
        }
    ],
    "sg:phone":"+1 802 655 7888",
    "sg:postcode":"05404",
    "sg:province":"VT",
    "wof:name":"Donny's New York Pizza",
    "wof:placetype":"venue"
},
  "geometry": {"coordinates":[-73.18653399999999,44.489543],"type":"Point"}
}