{
  "type": "Feature",
  "properties": {
    "iso:country":"US",
    "sg:address":"1033 Bullock Rd",
    "sg:city":"Brandon",
    "sg:classifiers":[
        {
            "category":"Shopping",
            "type":"Retail Goods"
        }
    ],
    "sg:phone":"+1 802 247 3479",
    "sg:postcode":"05733",
    "sg:province":"VT",
    "sg:tags":[
        "merchandise"
    ],
    "wof:name":"James Maroney Inc",
    "wof:placetype":"venue"
},
  "geometry": {"coordinates":[-73.13059699999999,43.86546],"type":"Point"}
}