{
  "type": "Feature",
  "properties": {
    "iso:country":"US",
    "sg:address":"94 Gibson Ave",
    "sg:city":"Rutland",
    "sg:classifiers":[
        {
            "category":"Insurance",
            "subcategory":"Insurance Agent",
            "type":"Services"
        }
    ],
    "sg:phone":"+1 802 773 7859",
    "sg:postcode":"05701",
    "sg:province":"VT",
    "wof:name":"All Insurance Agency Inc",
    "wof:placetype":"venue"
},
  "geometry": {"coordinates":[-72.97821999999999,43.596553],"type":"Point"}
}