{
  "type": "Feature",
  "properties": {
    "addr:full":"20 Liberty St Fair Haven VT 05743",
    "addr:housenumber":"20",
    "addr:postcode":"05743",
    "addr:street":"Liberty St",
    "iso:country":"US",
    "sg:address":"20 Liberty St",
    "sg:city":"Fair Haven",
    "sg:classifiers":[
        {
            "category":"Autos & Motor Vehicles",
            "subcategory":"Automobile Sales",
            "type":"Retail Goods"
        }
    ],
    "sg:phone":"+1 802 265 4964",
    "sg:postcode":"05743",
    "sg:province":"VT",
    "sg:tags":[
        "car",
        "dealer"
    ],
    "wof:name":"Fair Haven Chrysler Dodge Inc",
    "wof:placetype":"venue"
},
  "geometry": {"coordinates":[-73.263142,43.592274],"type":"Point"}
}