{
  "type": "Feature",
  "properties": {
    "iso:country":"US",
    "sg:address":"704 Hier Rd",
    "sg:city":"West Rutland",
    "sg:classifiers":[
        {
            "category":"Building & Trades",
            "subcategory":"Plumbing",
            "type":"Services"
        }
    ],
    "sg:phone":"+1 802 438 5358",
    "sg:postcode":"05777",
    "sg:province":"VT",
    "sg:tags":[
        "septic"
    ],
    "wof:name":"Scribner's Septic Svc",
    "wof:placetype":"venue"
},
  "geometry": {"coordinates":[-73.03057699999999,43.525434],"type":"Point"}
}