{
  "type": "Feature",
  "properties": {
    "iso:country":"US",
    "sg:address":"5222 Berkshire Center Rd",
    "sg:city":"Enosburg Falls",
    "sg:classifiers":[
        {
            "category":"Government",
            "subcategory":"Fire Station",
            "type":"Public Place"
        }
    ],
    "sg:phone":"+1 802 933 4345",
    "sg:postcode":"05450",
    "sg:province":"VT",
    "sg:tags":[
        "dept",
        "volunteer"
    ],
    "wof:name":"Berkshire Volunteer Fire Dept",
    "wof:placetype":"venue"
},
  "geometry": {"coordinates":[-72.73866599999999,44.941928],"type":"Point"}
}