{
  "type": "Feature",
  "properties": {
    "addr:full":"45 Depot Rd Townshend VT 05353",
    "addr:housenumber":"45",
    "addr:postcode":"05353",
    "addr:street":"Depot Rd",
    "iso:country":"US",
    "sg:address":"45 Depot Rd",
    "sg:city":"Townshend",
    "sg:classifiers":[
        {
            "category":"Manufacturing",
            "subcategory":"Lumber",
            "type":"Manufacturing & Wholesale Goods"
        }
    ],
    "sg:phone":"+1 802 365 7721",
    "sg:postcode":"05353",
    "sg:province":"VT",
    "sg:tags":[
        "company",
        "logging"
    ],
    "wof:name":"Carl W Steiner Logging",
    "wof:placetype":"venue"
},
  "geometry": {"coordinates":[-72.667159,43.038199],"type":"Point"}
}