{
  "type": "Feature",
  "properties": {
    "iso:country":"US",
    "sg:address":"6802 State Rte 116",
    "sg:city":"Shelburne",
    "sg:classifiers":[
        {
            "category":"Farming",
            "subcategory":"Dairy Farm",
            "type":"Manufacturing & Wholesale Goods"
        }
    ],
    "sg:phone":"+1 802 862 0915",
    "sg:postcode":"05482",
    "sg:province":"VT",
    "wof:name":"Guillemette Farm",
    "wof:placetype":"venue"
},
  "geometry": {"coordinates":[-73.137794,44.380509],"type":"Point"}
}