{
  "type": "Feature",
  "properties": {
    "iso:country":"US",
    "sg:address":"385 Barre-Montpelier Rd",
    "sg:city":"Barre",
    "sg:classifiers":[
        {
            "category":"Restaurant",
            "type":"Food & Drink"
        }
    ],
    "sg:phone":"+1 802 479 9757",
    "sg:postcode":"05641",
    "sg:province":"VT",
    "sg:website":"www.mcdonalds.com",
    "wof:name":"Mc Donald's",
    "wof:placetype":"venue"
},
  "geometry": {"coordinates":[-72.539574,44.218161],"type":"Point"}
}