{
  "type": "Feature",
  "properties": {
    "iso:country":"US",
    "sg:address":"6274 State Rte 14",
    "sg:city":"Williamstown",
    "sg:classifiers":[
        {
            "category":"Social Services",
            "subcategory":"Child Care",
            "type":"Services"
        }
    ],
    "sg:phone":"+1 802 433 1265",
    "sg:postcode":"05679",
    "sg:province":"VT",
    "sg:tags":[
        "day"
    ],
    "wof:name":"Gulf House Daycare",
    "wof:placetype":"venue"
},
  "geometry": {"coordinates":[-72.568724,44.070209],"type":"Point"}
}