{
  "type": "Feature",
  "properties": {
    "addr:full":"120 Ox Yoke Dr Rutland VT 05701",
    "addr:housenumber":"120",
    "addr:postcode":"05701",
    "addr:street":"Ox Yoke Dr",
    "iso:country":"US",
    "sg:address":"120 Ox Yoke Dr",
    "sg:city":"Rutland",
    "sg:classifiers":[
        {
            "category":"Insurance",
            "subcategory":"Insurance Agent",
            "type":"Services"
        }
    ],
    "sg:phone":"+1 802 747 4797",
    "sg:postcode":"05701",
    "sg:province":"VT",
    "wof:name":"Dana Associates",
    "wof:placetype":"venue"
},
  "geometry": {"coordinates":[-73.001817,43.661914],"type":"Point"}
}