{
  "type": "Feature",
  "properties": {
    "iso:country":"US",
    "sg:address":"81 Hall St",
    "sg:city":"Winooski",
    "sg:classifiers":[
        {
            "category":"Utilities",
            "subcategory":"Refuse",
            "type":"Services"
        }
    ],
    "sg:phone":"+1 802 655 2455",
    "sg:postcode":"05404",
    "sg:province":"VT",
    "sg:tags":[
        "system"
    ],
    "wof:name":"Nolin S Rubbish Removal",
    "wof:placetype":"venue"
},
  "geometry": {"coordinates":[-73.193693,44.49624],"type":"Point"}
}