{
  "type": "Feature",
  "properties": {
    "iso:country":"US",
    "sg:address":"366 Pinnacle Ridge Rd",
    "sg:city":"Rutland",
    "sg:classifiers":[
        {
            "category":"Building & Trades",
            "subcategory":"Electrical",
            "type":"Services"
        }
    ],
    "sg:phone":"+1 802 770 6225",
    "sg:postcode":"05701",
    "sg:province":"VT",
    "sg:tags":[
        "electrician"
    ],
    "wof:name":"Vt Transco",
    "wof:placetype":"venue"
},
  "geometry": {"coordinates":[-72.994212,43.661191],"type":"Point"}
}