{
  "type": "Feature",
  "properties": {
    "iso:country":"US",
    "sg:address":"442 Woodstock Rd",
    "sg:city":"Woodstock",
    "sg:classifiers":[
        {
            "category":"Professional",
            "subcategory":"Computer Services",
            "type":"Services"
        }
    ],
    "sg:phone":"+1 802 457 9454",
    "sg:postcode":"05091",
    "sg:province":"VT",
    "sg:tags":[
        "website",
        "design"
    ],
    "wof:name":"Eds Up",
    "wof:placetype":"venue"
},
  "geometry": {"coordinates":[-72.504548,43.632494],"type":"Point"}
}