{
  "type": "Feature",
  "properties": {
    "addr:full":"24 Stevens Rd East Thetford VT 05043",
    "addr:housenumber":"24",
    "addr:postcode":"05043",
    "addr:street":"Stevens Rd",
    "iso:country":"US",
    "sg:address":"24 Stevens Rd",
    "sg:city":"East Thetford",
    "sg:classifiers":[
        {
            "category":"Home & Garden",
            "subcategory":"Home Furnishings",
            "type":"Retail Goods"
        }
    ],
    "sg:phone":"+1 802 785 4230",
    "sg:postcode":"05043",
    "sg:province":"VT",
    "sg:tags":[
        "trade",
        "contractor"
    ],
    "wof:name":"Window Energy Designs",
    "wof:placetype":"venue"
},
  "geometry": {"coordinates":[-72.212346,43.795635],"type":"Point"}
}