{
  "type": "Feature",
  "properties": {
    "iso:country":"US",
    "sg:address":"199 Lincoln St",
    "sg:city":"Pownal",
    "sg:classifiers":[
        {
            "category":"Manufacturing",
            "subcategory":"Lumber",
            "type":"Manufacturing & Wholesale Goods"
        }
    ],
    "sg:phone":"+1 802 823 5006",
    "sg:postcode":"05261",
    "sg:province":"VT",
    "sg:tags":[
        "forestry",
        "logging"
    ],
    "wof:name":"Walloomsac Forestry Co Inc",
    "wof:placetype":"venue"
},
  "geometry": {"coordinates":[-73.243066,42.770466],"type":"Point"}
}