{
  "type": "Feature",
  "properties": {
    "iso:country":"US",
    "sg:address":"447 Canal St",
    "sg:city":"Brattleboro",
    "sg:classifiers":[
        {
            "category":"Home & Garden",
            "subcategory":"Furniture",
            "type":"Retail Goods"
        }
    ],
    "sg:phone":"+1 802 254 4119",
    "sg:postcode":"05301",
    "sg:province":"VT",
    "sg:tags":[
        "equipment",
        "computer",
        "business"
    ],
    "sg:website":"www.newtonbusiness.com",
    "wof:name":"Newton Business",
    "wof:placetype":"venue"
},
  "geometry": {"coordinates":[-72.568133,42.833685],"type":"Point"}
}