{
  "type": "Feature",
  "properties": {
    "iso:country":"US",
    "sg:address":"58 Barre St",
    "sg:city":"Montpelier",
    "sg:classifiers":[
        {
            "category":"Professional",
            "type":"Services"
        }
    ],
    "sg:phone":"+1 802 223 4101",
    "sg:postcode":"05602",
    "sg:province":"VT",
    "sg:tags":[
        "establishment"
    ],
    "wof:name":"National Institute-Community",
    "wof:placetype":"venue"
},
  "geometry": {"coordinates":[-72.574671,44.257124],"type":"Point"}
}