{
  "type": "Feature",
  "properties": {
    "iso:country":"US",
    "sg:address":"427 Mountain Rd",
    "sg:city":"Monkton",
    "sg:classifiers":[
        {
            "category":"Building & Trades",
            "subcategory":"Construction",
            "type":"Services"
        }
    ],
    "sg:phone":"+1 802 453 5155",
    "sg:postcode":"05471",
    "sg:province":"VT",
    "sg:tags":[
        "contractor"
    ],
    "wof:name":"Distinctive Restoration Inc",
    "wof:placetype":"venue"
},
  "geometry": {"coordinates":[-72.604162,44.88227],"type":"Point"}
}