{
  "type": "Feature",
  "properties": {
    "iso:country":"US",
    "sg:address":"200 Johnson Rd",
    "sg:city":"Windsor",
    "sg:classifiers":[
        {
            "category":"Autos & Motor Vehicles",
            "subcategory":"Automobile Sales",
            "type":"Retail Goods"
        }
    ],
    "sg:phone":"+1 802 674 5656",
    "sg:postcode":"05089",
    "sg:province":"VT",
    "wof:name":"Robbins Sled Shop",
    "wof:placetype":"venue"
},
  "geometry": {"coordinates":[-72.41801,43.502992],"type":"Point"}
}