{
  "type": "Feature",
  "properties": {
    "iso:country":"US",
    "sg:address":"1200 Airport Dr",
    "sg:city":"South Burlington",
    "sg:classifiers":[
        {
            "category":"Shopping",
            "subcategory":"Gifts & Souvenirs",
            "type":"Retail Goods"
        }
    ],
    "sg:phone":"+1 802 865 4208",
    "sg:postcode":"05403",
    "sg:province":"VT",
    "sg:tags":[
        "shop"
    ],
    "wof:name":"Duty Free Shop",
    "wof:placetype":"venue"
},
  "geometry": {"coordinates":[-73.15895500000001,44.473124],"type":"Point"}
}