{
  "type": "Feature",
  "properties": {
    "addr:full":"284 S Union St Burlington VT 05401",
    "addr:housenumber":"284",
    "addr:postcode":"05401",
    "addr:street":"S Union St",
    "iso:country":"US",
    "sg:address":"284 S Union St",
    "sg:city":"Burlington",
    "sg:classifiers":[
        {
            "category":"Real Estate",
            "subcategory":"Architect",
            "type":"Services"
        }
    ],
    "sg:phone":"+1 802 862 9631",
    "sg:postcode":"05401",
    "sg:province":"VT",
    "wof:name":"Guillot Vivian Viehmann Archtc",
    "wof:placetype":"venue"
},
  "geometry": {"coordinates":[-73.20863199999999,44.471651],"type":"Point"}
}