{
  "type": "Feature",
  "properties": {
    "iso:country":"US",
    "sg:address":"341 Lavigne Rd",
    "sg:city":"Colchester",
    "sg:classifiers":[
        {
            "category":"Professional",
            "subcategory":"Computer Services",
            "type":"Services"
        }
    ],
    "sg:phone":"+1 802 655 3083",
    "sg:postcode":"05446",
    "sg:province":"VT",
    "sg:tags":[
        "internet"
    ],
    "wof:name":"Morse Design",
    "wof:placetype":"venue"
},
  "geometry": {"coordinates":[-73.199984,44.530616],"type":"Point"}
}