{
  "type": "Feature",
  "properties": {
    "iso:country":"US",
    "sg:address":"663 Broad St",
    "sg:city":"Lyndonville",
    "sg:classifiers":[
        {
            "category":"Restaurant",
            "type":"Food & Drink"
        }
    ],
    "sg:phone":"+1 802 626 4766",
    "sg:postcode":"05851",
    "sg:province":"VT",
    "sg:tags":[
        "pizza"
    ],
    "wof:name":"The Pizza Man",
    "wof:placetype":"venue"
},
  "geometry": {"coordinates":[-72.000558,44.527936],"type":"Point"}
}