{
  "type": "Feature",
  "properties": {
    "addr:full":"7 Essex Way Essex Junction VT 05452",
    "addr:housenumber":"7",
    "addr:postcode":"05452",
    "addr:street":"Essex Way",
    "iso:country":"US",
    "sg:address":"7 Essex Way",
    "sg:city":"Essex Junction",
    "sg:classifiers":[
        {
            "category":"Sports & Exercise",
            "subcategory":"Gym",
            "type":"Entertainment"
        }
    ],
    "sg:phone":"+1 802 872 8600",
    "sg:postcode":"05452",
    "sg:province":"VT",
    "sg:tags":[
        "club",
        "health",
        "studio",
        "gymnasium"
    ],
    "wof:name":"Curves For Women",
    "wof:placetype":"venue"
},
  "geometry": {"coordinates":[-73.07847,44.50998],"type":"Point"}
}