{
  "type": "Feature",
  "properties": {
    "iso:country":"US",
    "sg:address":"40 North St",
    "sg:city":"Bristol",
    "sg:classifiers":[
        {
            "category":"Education",
            "subcategory":"Library",
            "type":"Public Place"
        }
    ],
    "sg:phone":"+1 802 453 2366",
    "sg:postcode":"05443",
    "sg:province":"VT",
    "wof:name":"Lawrence Memorial Library Inc",
    "wof:placetype":"venue"
},
  "geometry": {"coordinates":[-73.078746,44.135355],"type":"Point"}
}