{
  "type": "Feature",
  "properties": {
    "iso:country":"US",
    "sg:address":"192 College St",
    "sg:city":"Burlington",
    "sg:classifiers":[
        {
            "category":"Professional",
            "subcategory":"Lawyer & Legal Services",
            "type":"Services"
        }
    ],
    "sg:phone":"+1 802 658 6352",
    "sg:postcode":"05401",
    "sg:province":"VT",
    "sg:tags":[
        "attorney"
    ],
    "wof:name":"William C Kittell",
    "wof:placetype":"venue"
},
  "geometry": {"coordinates":[-73.21198200000001,44.477188],"type":"Point"}
}