{
  "type": "Feature",
  "properties": {
    "iso:country":"US",
    "sg:address":"163 S Willard St",
    "sg:city":"Burlington",
    "sg:classifiers":[
        {
            "category":"Education",
            "subcategory":"College",
            "type":"Public Place"
        }
    ],
    "sg:phone":"+1 802 865 5415",
    "sg:postcode":"05401",
    "sg:province":"VT",
    "sg:tags":[
        "distance"
    ],
    "wof:name":"Esolutions Champlaincollege",
    "wof:placetype":"venue"
},
  "geometry": {"coordinates":[-73.205496,44.475411],"type":"Point"}
}