{
  "type": "Feature",
  "properties": {
    "iso:country":"US",
    "sg:address":"118 Park St",
    "sg:city":"Springfield",
    "sg:classifiers":[
        {
            "category":"Social Services",
            "subcategory":"Job Training",
            "type":"Services"
        }
    ],
    "sg:phone":"+1 802 885 5170",
    "sg:postcode":"05156",
    "sg:province":"VT",
    "sg:tags":[
        "retardation",
        "disabled",
        "mental",
        "dev"
    ],
    "wof:name":"Health Care & Rehabilitation",
    "wof:placetype":"venue"
},
  "geometry": {"coordinates":[-72.489704,43.297979],"type":"Point"}
}