{
  "type": "Feature",
  "properties": {
    "iso:country":"US",
    "sg:address":"329 Union St",
    "sg:city":"Newport",
    "sg:classifiers":[
        {
            "category":"Professional",
            "subcategory":"Management & Consulting",
            "type":"Services"
        }
    ],
    "sg:phone":"+1 802 334 5022",
    "sg:postcode":"05855",
    "sg:province":"VT",
    "sg:tags":[
        "consultant",
        "business"
    ],
    "wof:name":"Patrick R Higgins & Assoc Inc",
    "wof:placetype":"venue"
},
  "geometry": {"coordinates":[-72.200445,44.948153],"type":"Point"}
}