{
  "type": "Feature",
  "properties": {
    "addr:full":"3494 State Rte 103 Proctorsville VT 05153",
    "addr:housenumber":"3494",
    "addr:postcode":"05153",
    "addr:street":"State Rte 103",
    "iso:country":"US",
    "sg:address":"3494 State Rte 103",
    "sg:city":"Proctorsville",
    "sg:classifiers":[
        {
            "category":"Social Services",
            "subcategory":"Job Training",
            "type":"Services"
        }
    ],
    "sg:phone":"+1 802 228 5434",
    "sg:postcode":"05153",
    "sg:province":"VT",
    "sg:tags":[
        "rehabilitation"
    ],
    "wof:name":"Beekman House",
    "wof:placetype":"venue"
},
  "geometry": {"coordinates":[-72.657152,43.388628],"type":"Point"}
}