{
  "type": "Feature",
  "properties": {
    "addr:full":"85 N Main St White River Jct VT 05001",
    "addr:housenumber":"85",
    "addr:postcode":"05001",
    "addr:street":"N Main St",
    "iso:country":"US",
    "sg:address":"85 N Main St",
    "sg:city":"White River Jct",
    "sg:classifiers":[
        {
            "category":"Professional",
            "subcategory":"Art Services",
            "type":"Services"
        }
    ],
    "sg:phone":"+1 802 280 1888",
    "sg:postcode":"05001",
    "sg:province":"VT",
    "sg:tags":[
        "photographer"
    ],
    "wof:name":"Northlight Digital",
    "wof:placetype":"venue"
},
  "geometry": {"coordinates":[-72.321123,43.649577],"type":"Point"}
}