{
  "type": "Feature",
  "properties": {
    "addr:full":"95 Main St Newport VT 05855",
    "addr:housenumber":"95",
    "addr:postcode":"05855",
    "addr:street":"Main St",
    "iso:country":"US",
    "sg:address":"95 Main St",
    "sg:city":"Newport",
    "sg:classifiers":[
        {
            "category":"Shopping",
            "subcategory":"Used Merchandise",
            "type":"Retail Goods"
        }
    ],
    "sg:phone":"+1 802 334 2063",
    "sg:postcode":"05855",
    "sg:province":"VT",
    "sg:tags":[
        "home",
        "furnishing"
    ],
    "wof:name":"Sage Advice Interiors",
    "wof:placetype":"venue"
},
  "geometry": {"coordinates":[-72.214572,44.933754],"type":"Point"}
}