{
  "type": "Feature",
  "properties": {
    "iso:country":"US",
    "sg:address":"41 Barre St",
    "sg:city":"Montpelier",
    "sg:classifiers":[
        {
            "category":"Social Services",
            "subcategory":"Child Care",
            "type":"Services"
        }
    ],
    "sg:phone":"+1 802 223 3373",
    "sg:postcode":"05602",
    "sg:province":"VT",
    "sg:tags":[
        "day"
    ],
    "wof:name":"Montpelier Children's House",
    "wof:placetype":"venue"
},
  "geometry": {"coordinates":[-72.575531,44.257804],"type":"Point"}
}