{
  "type": "Feature",
  "properties": {
    "addr:full":"188 S Main St Chester VT 05143",
    "addr:housenumber":"188",
    "addr:postcode":"05143",
    "addr:street":"S Main St",
    "iso:country":"US",
    "sg:address":"188 S Main St",
    "sg:city":"Chester",
    "sg:classifiers":[
        {
            "category":"Banks & Credit Unions",
            "subcategory":"Bank",
            "type":"Services"
        }
    ],
    "sg:phone":"+1 802 875 1630",
    "sg:postcode":"05143",
    "sg:province":"VT",
    "wof:name":"UBS Financial Svc",
    "wof:placetype":"venue"
},
  "geometry": {"coordinates":[-72.59169799999999,43.26042],"type":"Point"}
}