{
  "type": "Feature",
  "properties": {
    "iso:country":"US",
    "sg:address":"5301 Lake St",
    "sg:city":"Bridport",
    "sg:classifiers":[
        {
            "category":"Farming",
            "subcategory":"Dairy Farm",
            "type":"Manufacturing & Wholesale Goods"
        }
    ],
    "sg:phone":"+1 802 758 2497",
    "sg:postcode":"05734",
    "sg:province":"VT",
    "wof:name":"Champlain Acres",
    "wof:placetype":"venue"
},
  "geometry": {"coordinates":[-73.3921,43.934471],"type":"Point"}
}