{
  "type": "Feature",
  "properties": {
    "addr:full":"218 E Main St Newport VT 05855",
    "addr:housenumber":"218",
    "addr:postcode":"05855",
    "addr:street":"E Main St",
    "iso:country":"US",
    "sg:address":"218 E Main St",
    "sg:city":"Newport",
    "sg:classifiers":[
        {
            "category":"Retail",
            "subcategory":"Repair Shop",
            "type":"Services"
        }
    ],
    "sg:phone":"+1 802 334 5855",
    "sg:postcode":"05855",
    "sg:province":"VT",
    "wof:name":"Custom Picture Framing",
    "wof:placetype":"venue"
},
  "geometry": {"coordinates":[-72.202051,44.9427],"type":"Point"}
}