{
  "type": "Feature",
  "properties": {
    "addr:full":"35 High St Barton VT 05822",
    "addr:housenumber":"35",
    "addr:postcode":"05822",
    "addr:street":"High St",
    "iso:country":"US",
    "sg:address":"35 High St",
    "sg:city":"Barton",
    "sg:classifiers":[
        {
            "category":"Retail",
            "subcategory":"Auto Repair",
            "type":"Services"
        }
    ],
    "sg:phone":"+1 802 525 8808",
    "sg:postcode":"05822",
    "sg:province":"VT",
    "sg:tags":[
        "body",
        "automobile",
        "painting"
    ],
    "wof:name":"Vanasse Auto Body",
    "wof:placetype":"venue"
},
  "geometry": {"coordinates":[-72.175775,44.748137],"type":"Point"}
}