{
  "type": "Feature",
  "properties": {
    "addr:full":"76 Bishop St Saint Albans VT 05478",
    "addr:housenumber":"76",
    "addr:postcode":"05478",
    "addr:street":"Bishop St",
    "iso:country":"US",
    "sg:address":"76 Bishop St",
    "sg:city":"Saint Albans",
    "sg:classifiers":[
        {
            "category":"Restaurant",
            "type":"Food & Drink"
        }
    ],
    "sg:phone":"+1 802 524 7718",
    "sg:postcode":"05478",
    "sg:province":"VT",
    "sg:tags":[
        "eating"
    ],
    "wof:name":"Simple Pleasures Cafe",
    "wof:placetype":"venue"
},
  "geometry": {"coordinates":[-73.074994,44.809744],"type":"Point"}
}