{
  "type": "Feature",
  "properties": {
    "iso:country":"US",
    "sg:address":"95 Underpass Rd",
    "sg:city":"Sutton",
    "sg:classifiers":[
        {
            "category":"Education",
            "subcategory":"School",
            "type":"Public Place"
        }
    ],
    "sg:phone":"+1 802 467 3492",
    "sg:postcode":"05867",
    "sg:province":"VT",
    "wof:name":"Sutton Elementary School",
    "wof:placetype":"venue"
},
  "geometry": {"coordinates":[-72.033586,44.642365],"type":"Point"}
}