{
  "type": "Feature",
  "properties": {
    "iso:country":"US",
    "sg:address":"20 George St",
    "sg:city":"Montpelier",
    "sg:classifiers":[
        {
            "category":"Building & Trades",
            "subcategory":"Construction",
            "type":"Services"
        }
    ],
    "sg:phone":"+1 802 229 9981",
    "sg:postcode":"05602",
    "sg:province":"VT",
    "sg:tags":[
        "sandblasting",
        "contractor"
    ],
    "wof:name":"Mobile Sand Blast",
    "wof:placetype":"venue"
},
  "geometry": {"coordinates":[-72.56738300000001,44.244936],"type":"Point"}
}