{
  "type": "Feature",
  "properties": {
    "iso:country":"US",
    "sg:address":"257 Heineberg Dr Ste 283",
    "sg:city":"Colchester",
    "sg:classifiers":[
        {
            "category":"Retail",
            "subcategory":"Auto Repair",
            "type":"Services"
        }
    ],
    "sg:phone":"+1 802 863 9203",
    "sg:postcode":"05446",
    "sg:province":"VT",
    "sg:tags":[
        "body",
        "painting",
        "repairing",
        "automobile"
    ],
    "wof:name":"Allphase Auto Body & Restoration",
    "wof:placetype":"venue"
},
  "geometry": {"coordinates":[-73.250227,44.533283],"type":"Point"}
}