{
  "type": "Feature",
  "properties": {
    "iso:country":"US",
    "sg:address":"30 Phillips Rd",
    "sg:city":"Derby",
    "sg:classifiers":[
        {
            "category":"Freight",
            "type":"Transportation"
        }
    ],
    "sg:phone":"+1 802 748 1546",
    "sg:postcode":"05866",
    "sg:province":"VT",
    "sg:tags":[
        "delivery"
    ],
    "wof:name":"Fed Ex Trade Networks",
    "wof:placetype":"venue"
},
  "geometry": {"coordinates":[-72.107462,44.614091],"type":"Point"}
}