{
  "type": "Feature",
  "properties": {
    "addr:full":"864 Ethan Allen Hwy Milton VT 05468",
    "addr:housenumber":"864",
    "addr:postcode":"05468",
    "addr:street":"Ethan Allen Hwy",
    "iso:country":"US",
    "sg:address":"864 Ethan Allen Hwy",
    "sg:city":"Milton",
    "sg:classifiers":[
        {
            "category":"Travel",
            "subcategory":"Campground",
            "type":"Entertainment"
        }
    ],
    "sg:phone":"+1 802 524 2356",
    "sg:postcode":"05468",
    "sg:province":"VT",
    "sg:tags":[
        "trailer"
    ],
    "wof:name":"Homestead Campgrounds Inc",
    "wof:placetype":"venue"
},
  "geometry": {"coordinates":[-73.10890499999999,44.69101],"type":"Point"}
}