{
  "type": "Feature",
  "properties": {
    "addr:full":"185 Church St Exd Jeffersonville VT 05464",
    "addr:housenumber":"185",
    "addr:postcode":"05464",
    "addr:street":"Church St Exd",
    "iso:country":"US",
    "sg:address":"185 Church St Exd",
    "sg:city":"Jeffersonville",
    "sg:classifiers":[
        {
            "category":"Home & Garden",
            "subcategory":"Building Materials",
            "type":"Retail Goods"
        }
    ],
    "sg:phone":"+1 802 644 6664",
    "sg:postcode":"05464",
    "sg:province":"VT",
    "sg:tags":[
        "glass",
        "window",
        "plate"
    ],
    "wof:name":"Windshield Doctor",
    "wof:placetype":"venue"
},
  "geometry": {"coordinates":[-72.83281100000001,44.643353],"type":"Point"}
}