{
  "type": "Feature",
  "properties": {
    "iso:country":"US",
    "sg:address":"87 Portland St",
    "sg:city":"Morrisville",
    "sg:classifiers":[
        {
            "category":"Personal",
            "subcategory":"Beauty Salon",
            "type":"Services"
        }
    ],
    "sg:phone":"+1 802 888 4872",
    "sg:postcode":"05661",
    "sg:province":"VT",
    "wof:name":"Retro Metro Hair Design",
    "wof:placetype":"venue"
},
  "geometry": {"coordinates":[-72.59845799999999,44.563078],"type":"Point"}
}