{
  "type": "Feature",
  "properties": {
    "iso:country":"US",
    "sg:address":"22 E Parkside Ter",
    "sg:city":"Barre",
    "sg:classifiers":[
        {
            "category":"Freight",
            "type":"Transportation"
        }
    ],
    "sg:phone":"+1 802 476 7766",
    "sg:postcode":"05641",
    "sg:province":"VT",
    "sg:tags":[
        "commercial",
        "storage"
    ],
    "wof:name":"All Stored Up",
    "wof:placetype":"venue"
},
  "geometry": {"coordinates":[-72.496854,44.180968],"type":"Point"}
}