{
  "type": "Feature",
  "properties": {
    "addr:full":"173 West St Rutland VT 05701",
    "addr:housenumber":"173",
    "addr:postcode":"05701",
    "addr:street":"West St",
    "iso:country":"US",
    "sg:address":"173 West St",
    "sg:city":"Rutland",
    "sg:classifiers":[
        {
            "category":"Retail",
            "subcategory":"Repair Shop",
            "type":"Services"
        }
    ],
    "sg:phone":"+1 802 786 5837",
    "sg:postcode":"05701",
    "sg:province":"VT",
    "sg:tags":[
        "clocks",
        "parts"
    ],
    "wof:name":"Employment Service",
    "wof:placetype":"venue"
},
  "geometry": {"coordinates":[-72.98368000000001,43.607573],"type":"Point"}
}