{
  "type": "Feature",
  "properties": {
    "iso:country":"US",
    "sg:address":"310 N Williston Rd",
    "sg:city":"Williston",
    "sg:classifiers":[
        {
            "category":"Fast Food",
            "type":"Food & Drink"
        },
        {
            "category":"Restaurant",
            "type":"Food & Drink"
        },
        {
            "category":"Ice Cream",
            "type":"Food & Drink"
        },
        {
            "category":"Food & Beverages",
            "subcategory":"Groceries & Convenience Stores",
            "type":"Retail Goods"
        }
    ],
    "sg:phone":"+1 802 879 1404",
    "sg:postcode":"05495",
    "sg:province":"VT",
    "sg:tags":[
        "shop",
        "style",
        "sandwich",
        "hamburger",
        "family",
        "frozen",
        "dessert",
        "dog",
        "lunch",
        "hot",
        "american",
        "brunch",
        "breakfast"
    ],
    "sg:website":"http://www.friendlys.com",
    "wof:name":"Friendly's",
    "wof:placetype":"venue"
},
  "geometry": {"coordinates":[-73.065279,44.441281],"type":"Point"}
}