{
  "type": "Feature",
  "properties": {
    "addr:full":"169 Water Tower Rd Enosburg Falls VT 05450",
    "addr:housenumber":"169",
    "addr:postcode":"05450",
    "addr:street":"Water Tower Rd",
    "iso:country":"US",
    "sg:address":"169 Water Tower Rd",
    "sg:city":"Enosburg Falls",
    "sg:classifiers":[
        {
            "category":"Retail",
            "subcategory":"Veterinary Services",
            "type":"Services"
        }
    ],
    "sg:phone":"+1 802 933 4533",
    "sg:postcode":"05450",
    "sg:province":"VT",
    "sg:tags":[
        "veterinarian"
    ],
    "wof:name":"Animal Doctor",
    "wof:placetype":"venue"
},
  "geometry": {"coordinates":[-72.797355,44.913966],"type":"Point"}
}