{
  "type": "Feature",
  "properties": {
    "iso:country":"US",
    "sg:address":"58 Locust St",
    "sg:city":"Burlington",
    "sg:classifiers":[
        {
            "category":"Health Services",
            "subcategory":"Chiropractor",
            "type":"Services"
        }
    ],
    "sg:phone":"+1 802 864 0019",
    "sg:postcode":"05401",
    "sg:province":"VT",
    "wof:name":"Hilde S Betts DC",
    "wof:placetype":"venue"
},
  "geometry": {"coordinates":[-73.212189,44.463055],"type":"Point"}
}