{
  "type": "Feature",
  "properties": {
    "iso:country":"US",
    "sg:address":"496 Woodstock Rd",
    "sg:city":"Woodstock",
    "sg:classifiers":[
        {
            "category":"Education",
            "subcategory":"School",
            "type":"Public Place"
        }
    ],
    "sg:phone":"+1 802 457 1213",
    "sg:postcode":"05091",
    "sg:province":"VT",
    "wof:name":"Windsor Central School Supt",
    "wof:placetype":"venue"
},
  "geometry": {"coordinates":[-72.506272,43.627913],"type":"Point"}
}