{
  "type": "Feature",
  "properties": {
    "addr:full":"2211 State Rte 128 Westford VT 05494",
    "addr:housenumber":"2211",
    "addr:postcode":"05494",
    "addr:street":"State Rte 128",
    "iso:country":"US",
    "sg:address":"2211 State Rte 128",
    "sg:city":"Westford",
    "sg:classifiers":[
        {
            "category":"Manufacturing",
            "subcategory":"Watercraft",
            "type":"Manufacturing & Wholesale Goods"
        }
    ],
    "sg:phone":"+1 802 849 6579",
    "sg:postcode":"05494",
    "sg:province":"VT",
    "wof:name":"Two Daughter Boatworks",
    "wof:placetype":"venue"
},
  "geometry": {"coordinates":[-73.014388,44.646671],"type":"Point"}
}