{
  "type": "Feature",
  "properties": {
    "iso:country":"US",
    "sg:address":"35 Mad Tom Rd",
    "sg:city":"East Dorset",
    "sg:classifiers":[
        {
            "category":"Government",
            "subcategory":"Post Office",
            "type":"Public Place"
        }
    ],
    "sg:phone":"+1 802 362 3233",
    "sg:postcode":"05253",
    "sg:province":"VT",
    "wof:name":"US Post Office",
    "wof:placetype":"venue"
},
  "geometry": {"coordinates":[-73.00990299999999,43.239944],"type":"Point"}
}