{
  "type": "Feature",
  "properties": {
    "iso:country":"US",
    "sg:address":"2949 E Hill Rd",
    "sg:city":"North Troy",
    "sg:classifiers":[
        {
            "category":"Manufacturing",
            "subcategory":"Tools & Machinery",
            "type":"Manufacturing & Wholesale Goods"
        }
    ],
    "sg:phone":"+1 802 988 2979",
    "sg:postcode":"05859",
    "sg:province":"VT",
    "sg:tags":[
        "mfg"
    ],
    "wof:name":"Rafoss Innovations",
    "wof:placetype":"venue"
},
  "geometry": {"coordinates":[-72.37317400000001,44.949249],"type":"Point"}
}