{
  "type": "Feature",
  "properties": {
    "addr:full":"4879 Vt Route 15 Jeffersonville VT 05464",
    "addr:housenumber":"4879",
    "addr:postcode":"05464",
    "addr:street":"Vt Route 15",
    "iso:country":"US",
    "sg:address":"4879 Vt Route 15",
    "sg:city":"Jeffersonville",
    "sg:classifiers":[
        {
            "category":"Cinema",
            "subcategory":"Movie Rental",
            "type":"Entertainment"
        }
    ],
    "sg:phone":"+1 802 644 8111",
    "sg:postcode":"05464",
    "sg:province":"VT",
    "sg:tags":[
        "game",
        "video"
    ],
    "wof:name":"Video Matinee",
    "wof:placetype":"venue"
},
  "geometry": {"coordinates":[-72.836304,44.644001],"type":"Point"}
}