{
  "type": "Feature",
  "properties": {
    "iso:country":"US",
    "sg:address":"416 Cadreact Rd",
    "sg:city":"Milton",
    "sg:classifiers":[
        {
            "category":"Farming",
            "subcategory":"Farm",
            "type":"Manufacturing & Wholesale Goods"
        }
    ],
    "sg:phone":"+1 802 893 7895",
    "sg:postcode":"05468",
    "sg:province":"VT",
    "sg:tags":[
        "crop",
        "general"
    ],
    "wof:name":"Parizo Farms",
    "wof:placetype":"venue"
},
  "geometry": {"coordinates":[-73.191254,44.633523],"type":"Point"}
}