{
  "type": "Feature",
  "properties": {
    "addr:full":"29 Center St Rutland VT 05701",
    "addr:housenumber":"29",
    "addr:postcode":"05701",
    "addr:street":"Center St",
    "iso:country":"US",
    "sg:address":"29 Center St",
    "sg:city":"Rutland",
    "sg:classifiers":[
        {
            "category":"Wholesale",
            "subcategory":"Hardware",
            "type":"Manufacturing & Wholesale Goods"
        }
    ],
    "sg:phone":"+1 802 747 2577",
    "sg:postcode":"05701",
    "sg:province":"VT",
    "sg:tags":[
        "equipment",
        "energy",
        "solar"
    ],
    "wof:name":"Central Vermont Solar & Wind",
    "wof:placetype":"venue"
},
  "geometry": {"coordinates":[-72.978982,43.606562],"type":"Point"}
}