{
  "type": "Feature",
  "properties": {
    "addr:full":"263 McCullough Hill Rd Montpelier VT 05602",
    "addr:housenumber":"263",
    "addr:postcode":"05602",
    "addr:street":"Mccullough Hill Rd",
    "iso:country":"US",
    "sg:address":"263 McCullough Hill Rd",
    "sg:city":"Montpelier",
    "sg:classifiers":[
        {
            "category":"Building & Trades",
            "subcategory":"Landscaping Services",
            "type":"Services"
        }
    ],
    "sg:phone":"+1 802 223 3039",
    "sg:postcode":"05602",
    "sg:province":"VT",
    "sg:tags":[
        "landscape"
    ],
    "wof:name":"Kiefer Brothers Landscape",
    "wof:placetype":"venue"
},
  "geometry": {"coordinates":[-72.638518,44.306874],"type":"Point"}
}