{
  "type": "Feature",
  "properties": {
    "iso:country":"US",
    "sg:address":"43 Suburban Sq",
    "sg:city":"South Burlington",
    "sg:classifiers":[
        {
            "category":"Organizations",
            "subcategory":"Community Association",
            "type":"Services"
        }
    ],
    "sg:phone":"+1 802 658 3744",
    "sg:postcode":"05403",
    "sg:province":"VT",
    "sg:tags":[
        "club",
        "dining",
        "plan"
    ],
    "sg:website":"www.vermontrestaurants.com",
    "wof:name":"Vermont Restaurant Card",
    "wof:placetype":"venue"
},
  "geometry": {"coordinates":[-73.16477399999999,44.469352],"type":"Point"}
}