{
  "type": "Feature",
  "properties": {
    "addr:full":"229 North St Bennington VT 05201",
    "addr:housenumber":"229",
    "addr:postcode":"05201",
    "addr:street":"North St",
    "iso:country":"US",
    "sg:address":"229 North St",
    "sg:city":"Bennington",
    "sg:classifiers":[
        {
            "category":"Retail",
            "subcategory":"Photofinishing",
            "type":"Services"
        }
    ],
    "sg:phone":"+1 802 442 6357",
    "sg:postcode":"05201",
    "sg:province":"VT",
    "sg:tags":[
        "laboratory",
        "finishing",
        "photo"
    ],
    "wof:name":"Photographer S Eye Inc",
    "wof:placetype":"venue"
},
  "geometry": {"coordinates":[-73.1968,42.88434],"type":"Point"}
}