{
  "type": "Feature",
  "properties": {
    "iso:country":"US",
    "sg:address":"710 Western Ave",
    "sg:city":"Brattleboro",
    "sg:classifiers":[
        {
            "category":"Professional",
            "subcategory":"Art Services",
            "type":"Services"
        }
    ],
    "sg:phone":"+1 802 258 2654",
    "sg:postcode":"05301",
    "sg:province":"VT",
    "sg:tags":[
        "commercial",
        "design"
    ],
    "wof:name":"John S Gurney",
    "wof:placetype":"venue"
},
  "geometry": {"coordinates":[-72.58957100000001,42.85033],"type":"Point"}
}