{
  "type": "Feature",
  "properties": {
    "iso:country":"US",
    "sg:address":"630 Main St",
    "sg:city":"Weston",
    "sg:classifiers":[
        {
            "category":"Restaurant",
            "type":"Food & Drink"
        }
    ],
    "sg:phone":"+1 802 824 6789",
    "sg:postcode":"05153",
    "sg:province":"VT",
    "sg:website":"www.innweston.com",
    "wof:name":"Inn At Weston",
    "wof:placetype":"venue"
},
  "geometry": {"coordinates":[-72.638492,43.382642],"type":"Point"}
}