{
  "type": "Feature",
  "properties": {
    "iso:country":"US",
    "sg:address":"3749 Main St",
    "sg:city":"Manchester Ctr",
    "sg:classifiers":[
        {
            "category":"Professional",
            "type":"Services"
        }
    ],
    "sg:phone":"+1 802 362 0662",
    "sg:postcode":"05255",
    "sg:province":"VT",
    "sg:tags":[
        "establishment"
    ],
    "wof:name":"Alparslan Dasdogan",
    "wof:placetype":"venue"
},
  "geometry": {"coordinates":[-73.0692,43.166387],"type":"Point"}
}