{
  "type": "Feature",
  "properties": {
    "addr:full":"31 Main St N Wells River VT 05081",
    "addr:housenumber":"31",
    "addr:postcode":"05081",
    "addr:street":"Main St N",
    "iso:country":"US",
    "sg:address":"31 Main St N",
    "sg:city":"Wells River",
    "sg:classifiers":[
        {
            "category":"Government",
            "subcategory":"Post Office",
            "type":"Public Place"
        }
    ],
    "sg:phone":"+1 802 757 2221",
    "sg:postcode":"05081",
    "sg:province":"VT",
    "wof:name":"US Post Office",
    "wof:placetype":"venue"
},
  "geometry": {"coordinates":[-72.04693899999999,44.153766],"type":"Point"}
}