{
  "type": "Feature",
  "properties": {
    "iso:country":"US",
    "sg:address":"220 Western Ave",
    "sg:city":"Brattleboro",
    "sg:classifiers":[
        {
            "category":"Health Services",
            "subcategory":"Clinic",
            "type":"Services"
        }
    ],
    "sg:phone":"+1 802 254 2928",
    "sg:postcode":"05301",
    "sg:province":"VT",
    "sg:tags":[
        "holistic",
        "practitioner"
    ],
    "wof:name":"Spero Latchis",
    "wof:placetype":"venue"
},
  "geometry": {"coordinates":[-72.59949400000001,42.853012],"type":"Point"}
}