{
  "type": "Feature",
  "properties": {
    "iso:country":"US",
    "sg:address":"2590 N Hartland Rd",
    "sg:city":"White River Junction",
    "sg:classifiers":[
        {
            "category":"Government",
            "subcategory":"Office",
            "type":"Public Place"
        }
    ],
    "sg:phone":"+1 802 295 5740",
    "sg:postcode":"05001",
    "sg:province":"VT",
    "sg:tags":[
        "landfill"
    ],
    "wof:name":"Landfill Office",
    "wof:placetype":"venue"
},
  "geometry": {"coordinates":[-72.354141,43.611247],"type":"Point"}
}