{
  "type": "Feature",
  "properties": {
    "iso:country":"US",
    "sg:address":"163 N Main St",
    "sg:city":"St Albans",
    "sg:classifiers":[
        {
            "category":"Professional",
            "subcategory":"Management & Consulting",
            "type":"Services"
        }
    ],
    "sg:phone":"+1 802 524 2194",
    "sg:postcode":"05478",
    "sg:province":"VT",
    "sg:tags":[
        "development",
        "industrial"
    ],
    "sg:website":"www.fcid.com",
    "wof:name":"Franklin County Ind Dev",
    "wof:placetype":"venue"
},
  "geometry": {"coordinates":[-73.0823,44.816557],"type":"Point"}
}