{
  "type": "Feature",
  "properties": {
    "iso:country":"US",
    "sg:address":"24 Washington St",
    "sg:city":"Middlebury",
    "sg:classifiers":[
        {
            "category":"Banks & Credit Unions",
            "subcategory":"Bank",
            "type":"Services"
        }
    ],
    "sg:phone":"+1 802 388 7036",
    "sg:postcode":"05753",
    "sg:province":"VT",
    "sg:tags":[
        "federal"
    ],
    "wof:name":"Vermont Federal Credit Union",
    "wof:placetype":"venue"
},
  "geometry": {"coordinates":[-73.16104199999999,44.01679],"type":"Point"}
}