{
  "type": "Feature",
  "properties": {
    "addr:full":"32 Cherry St Burlington VT 05401",
    "addr:housenumber":"32",
    "addr:postcode":"05401",
    "addr:street":"Cherry St",
    "iso:country":"US",
    "sg:address":"32 Cherry St",
    "sg:city":"Burlington",
    "sg:classifiers":[
        {
            "category":"Government",
            "subcategory":"Court House",
            "type":"Public Place"
        }
    ],
    "sg:phone":"+1 802 651 1800",
    "sg:postcode":"05401",
    "sg:province":"VT",
    "wof:name":"Chittenden County District Crt",
    "wof:placetype":"venue"
},
  "geometry": {"coordinates":[-73.21718799999999,44.479235],"type":"Point"}
}