{
  "type": "Feature",
  "properties": {
    "iso:country":"US",
    "sg:address":"1804 Brand Farm Dr",
    "sg:city":"South Burlington",
    "sg:classifiers":[
        {
            "category":"Professional",
            "subcategory":"Lawyer & Legal Services",
            "type":"Services"
        }
    ],
    "sg:phone":"+1 802 864 6627",
    "sg:postcode":"05403",
    "sg:province":"VT",
    "wof:name":"Bruce Allan Atty",
    "wof:placetype":"venue"
},
  "geometry": {"coordinates":[-73.16874300000001,44.446561],"type":"Point"}
}