{
  "type": "Feature",
  "properties": {
    "iso:country":"US",
    "sg:address":"103 Hassett Ln",
    "sg:city":"Williston",
    "sg:classifiers":[
        {
            "category":"Real Estate",
            "subcategory":"Real Estate Agent",
            "type":"Services"
        }
    ],
    "sg:phone":"+1 802 878 1743",
    "sg:postcode":"05495",
    "sg:province":"VT",
    "wof:name":"XYZ Real Estate Inc",
    "wof:placetype":"venue"
},
  "geometry": {"coordinates":[-73.108975,44.419474],"type":"Point"}
}