{
  "type": "Feature",
  "properties": {
    "iso:country":"US",
    "sg:address":"2649 Shelburne Rd",
    "sg:city":"Shelburne",
    "sg:classifiers":[
        {
            "category":"Autos & Motor Vehicles",
            "subcategory":"Boat Sales",
            "type":"Retail Goods"
        }
    ],
    "sg:phone":"+1 802 985 5222",
    "sg:postcode":"05482",
    "sg:province":"VT",
    "sg:website":"www.smallboatvt.com",
    "wof:name":"Small Boat Exchange",
    "wof:placetype":"venue"
},
  "geometry": {"coordinates":[-73.213196,44.417054],"type":"Point"}
}