{
  "type": "Feature",
  "properties": {
    "iso:country":"US",
    "sg:address":"478 Pearl Rd",
    "sg:city":"Danville",
    "sg:classifiers":[
        {
            "category":"Professional",
            "type":"Services"
        }
    ],
    "sg:phone":"+1 802 748 9615",
    "sg:postcode":"05828",
    "sg:province":"VT",
    "wof:name":"Lane Slow Press",
    "wof:placetype":"venue"
},
  "geometry": {"coordinates":[-72.09995499999999,44.444532],"type":"Point"}
}