{
  "type": "Feature",
  "properties": {
    "iso:country":"US",
    "sg:address":"45 Walnut St",
    "sg:city":"Brattleboro",
    "sg:classifiers":[
        {
            "category":"Professional",
            "subcategory":"Lawyer & Legal Services",
            "type":"Services"
        }
    ],
    "sg:phone":"+1 802 257 2221",
    "sg:postcode":"05301",
    "sg:province":"VT",
    "wof:name":"Kramer Theodore C",
    "wof:placetype":"venue"
},
  "geometry": {"coordinates":[-72.55695799999999,42.856398],"type":"Point"}
}