{
  "type": "Feature",
  "properties": {
    "iso:country":"US",
    "sg:address":"78 Buck Dr",
    "sg:city":"Weston",
    "sg:classifiers":[
        {
            "category":"Personal",
            "type":"Services"
        }
    ],
    "sg:phone":"+1 802 722 4882",
    "sg:postcode":"05158",
    "sg:province":"VT",
    "sg:tags":[
        "therapist",
        "massage"
    ],
    "wof:name":"For A Healthy Tomorrow",
    "wof:placetype":"venue"
},
  "geometry": {"coordinates":[-72.447006,43.093757],"type":"Point"}
}