{
  "type": "Feature",
  "properties": {
    "iso:country":"US",
    "sg:address":"263 Farm and Wilderness Rd",
    "sg:city":"Plymouth",
    "sg:classifiers":[
        {
            "category":"Travel",
            "subcategory":"Campground",
            "type":"Entertainment"
        }
    ],
    "sg:phone":"+1 802 422 3761",
    "sg:postcode":"05056",
    "sg:province":"VT",
    "sg:tags":[
        "camp"
    ],
    "sg:website":"www.farmandwilderness.com",
    "wof:name":"Farm & Wilderness Camps",
    "wof:placetype":"venue"
},
  "geometry": {"coordinates":[-72.75785,43.572418],"type":"Point"}
}