{
  "type": "Feature",
  "properties": {
    "addr:full":"157 Old Guilford Rd Brattleboro VT 05301",
    "addr:housenumber":"157",
    "addr:postcode":"05301",
    "addr:street":"Old Guilford Rd",
    "iso:country":"US",
    "sg:address":"157 Old Guilford Rd",
    "sg:city":"Brattleboro",
    "sg:classifiers":[
        {
            "category":"Education",
            "subcategory":"College",
            "type":"Public Place"
        }
    ],
    "sg:phone":"+1 802 257 9411",
    "sg:postcode":"05301",
    "sg:province":"VT",
    "sg:tags":[
        "academic",
        "school"
    ],
    "wof:name":"Union Institute & University",
    "wof:placetype":"venue"
},
  "geometry": {"coordinates":[-72.56054899999999,42.831036],"type":"Point"}
}