{
  "type": "Feature",
  "properties": {
    "iso:country":"US",
    "sg:address":"72 Cotton Mill Hill",
    "sg:city":"Brattleboro",
    "sg:classifiers":[
        {
            "category":"Wholesale",
            "subcategory":"Drugs",
            "type":"Manufacturing & Wholesale Goods"
        }
    ],
    "sg:phone":"+1 802 254 4070",
    "sg:postcode":"05301",
    "sg:province":"VT",
    "sg:tags":[
        "cosmetic"
    ],
    "wof:name":"Paradise Soap Works",
    "wof:placetype":"venue"
},
  "geometry": {"coordinates":[-72.55407700000001,42.834765],"type":"Point"}
}