{
  "type": "Feature",
  "properties": {
    "addr:full":"11 W Main St Wilmington VT 05363",
    "addr:housenumber":"11",
    "addr:postcode":"05363",
    "addr:street":"W Main St",
    "iso:country":"US",
    "sg:address":"11 W Main St",
    "sg:city":"Wilmington",
    "sg:classifiers":[
        {
            "category":"Shopping",
            "type":"Retail Goods"
        }
    ],
    "sg:phone":"+1 802 464 2780",
    "sg:postcode":"05363",
    "sg:province":"VT",
    "sg:tags":[
        "craft",
        "gallery",
        "dealer"
    ],
    "wof:name":"Quaigh Design Ctr",
    "wof:placetype":"venue"
},
  "geometry": {"coordinates":[-72.873283,42.869599],"type":"Point"}
}