{
  "type": "Feature",
  "properties": {
    "iso:country":"US",
    "sg:address":"247 Jourdan St",
    "sg:city":"Hinesburg",
    "sg:classifiers":[
        {
            "category":"Building & Trades",
            "subcategory":"Construction",
            "type":"Services"
        }
    ],
    "sg:phone":"+1 802 373 8398",
    "sg:postcode":"05461",
    "sg:province":"VT",
    "sg:tags":[
        "dry wall",
        "contractor"
    ],
    "wof:name":"Protec Drywall",
    "wof:placetype":"venue"
},
  "geometry": {"coordinates":[-73.087091,44.346252],"type":"Point"}
}