{
  "type": "Feature",
  "properties": {
    "iso:country":"US",
    "sg:address":"37 Paus Ln",
    "sg:city":"Hyde Park",
    "sg:classifiers":[
        {
            "category":"Real Estate",
            "subcategory":"Architect",
            "type":"Services"
        }
    ],
    "sg:phone":"+1 802 888 2400",
    "sg:postcode":"05655",
    "sg:province":"VT",
    "wof:name":"Silver Ridge Design Inc",
    "wof:placetype":"venue"
},
  "geometry": {"coordinates":[-72.593011,44.5869],"type":"Point"}
}