{
  "type": "Feature",
  "properties": {
    "iso:country":"US",
    "sg:address":"95 Falls Rd",
    "sg:city":"Shelburne",
    "sg:classifiers":[
        {
            "category":"Professional",
            "subcategory":"Engineering",
            "type":"Services"
        }
    ],
    "sg:phone":"+1 802 985 1512",
    "sg:postcode":"05482",
    "sg:province":"VT",
    "sg:tags":[
        "transportation",
        "engineer"
    ],
    "wof:name":"Fuss & O'Neill Inc",
    "wof:placetype":"venue"
},
  "geometry": {"coordinates":[-73.219909,44.370813],"type":"Point"}
}