{
  "type": "Feature",
  "properties": {
    "iso:country":"US",
    "sg:address":"440 Goodfellow Rd",
    "sg:city":"Groton",
    "sg:classifiers":[
        {
            "category":"Professional",
            "subcategory":"Computer Services",
            "type":"Services"
        }
    ],
    "sg:phone":"+1 802 584 4840",
    "sg:postcode":"05046",
    "sg:province":"VT",
    "sg:tags":[
        "repair"
    ],
    "wof:name":"Gordon Viewpoint",
    "wof:placetype":"venue"
},
  "geometry": {"coordinates":[-72.21862900000001,44.243361],"type":"Point"}
}