{
  "type": "Feature",
  "properties": {
    "iso:country":"US",
    "sg:address":"1661 E Warren Rd",
    "sg:city":"Waitsfield",
    "sg:classifiers":[
        {
            "category":"Restaurant",
            "type":"Food & Drink"
        }
    ],
    "sg:phone":"+1 802 583 1091",
    "sg:postcode":"05673",
    "sg:province":"VT",
    "sg:tags":[
        "caterer"
    ],
    "sg:website":"www.theroundbarn.com",
    "wof:name":"Cooking From The Heart Ctrng",
    "wof:placetype":"venue"
},
  "geometry": {"coordinates":[-72.811671,44.16812],"type":"Point"}
}