{
  "type": "Feature",
  "properties": {
    "addr:full":"26 Terry Ct Montpelier VT 05641",
    "addr:housenumber":"26",
    "addr:postcode":"05641",
    "addr:street":"Terry Ct",
    "iso:country":"US",
    "sg:address":"26 Terry Ct",
    "sg:city":"Montpelier",
    "sg:classifiers":[
        {
            "category":"Government",
            "subcategory":"Office",
            "type":"Public Place"
        }
    ],
    "sg:phone":"+1 802 828 2464",
    "sg:postcode":"05641",
    "sg:province":"VT",
    "sg:tags":[
        "division",
        "election"
    ],
    "wof:name":"Office of Elections",
    "wof:placetype":"venue"
},
  "geometry": {"coordinates":[-72.46172300000001,44.147583],"type":"Point"}
}