{
  "type": "Feature",
  "properties": {
    "addr:full":"3156 Georgia Shore Rd St Albans VT 05478",
    "addr:housenumber":"3156",
    "addr:postcode":"05478",
    "addr:street":"Georgia Shore Rd",
    "iso:country":"US",
    "sg:address":"3156 Georgia Shore Rd",
    "sg:city":"St Albans",
    "sg:classifiers":[
        {
            "category":"Building & Trades",
            "subcategory":"Landscaping Services",
            "type":"Services"
        }
    ],
    "sg:phone":"+1 802 527 2323",
    "sg:postcode":"05478",
    "sg:province":"VT",
    "sg:tags":[
        "tree"
    ],
    "wof:name":"Jenkins Tree & Stump Removal",
    "wof:placetype":"venue"
},
  "geometry": {"coordinates":[-73.18296599999999,44.750216],"type":"Point"}
}