{
  "type": "Feature",
  "properties": {
    "addr:full":"36 Summer St Barre VT 05641",
    "addr:housenumber":"36",
    "addr:postcode":"05641",
    "addr:street":"Summer St",
    "iso:country":"US",
    "sg:address":"36 Summer St",
    "sg:city":"Barre",
    "sg:classifiers":[
        {
            "category":"Real Estate",
            "subcategory":"Real Estate Agent",
            "type":"Services"
        }
    ],
    "sg:phone":"+1 802 479 2630",
    "sg:postcode":"05641",
    "sg:province":"VT",
    "wof:name":"Potvin Real Estate",
    "wof:placetype":"venue"
},
  "geometry": {"coordinates":[-72.502516,44.200177],"type":"Point"}
}