{
  "type": "Feature",
  "properties": {
    "addr:full":"13 East St Bennington VT 05201",
    "addr:housenumber":"13",
    "addr:postcode":"05201",
    "addr:street":"East St",
    "iso:country":"US",
    "sg:address":"13 East St",
    "sg:city":"Bennington",
    "sg:classifiers":[
        {
            "category":"Retail",
            "subcategory":"Repair Shop",
            "type":"Services"
        }
    ],
    "sg:phone":"+1 802 447 1496",
    "sg:postcode":"05201",
    "sg:province":"VT",
    "wof:name":"Morse Repair",
    "wof:placetype":"venue"
},
  "geometry": {"coordinates":[-73.166659,42.877182],"type":"Point"}
}