{
  "type": "Feature",
  "properties": {
    "iso:country":"US",
    "sg:address":"2639 Middle Rd",
    "sg:city":"North Clarendon",
    "sg:classifiers":[
        {
            "category":"Manufacturing",
            "subcategory":"Lumber",
            "type":"Manufacturing & Wholesale Goods"
        }
    ],
    "sg:phone":"+1 802 775 0032",
    "sg:postcode":"05759",
    "sg:province":"VT",
    "sg:tags":[
        "planing",
        "mills",
        "sawmill"
    ],
    "sg:website":"www.millriverlumber.com",
    "wof:name":"Mill River Lumber LTD",
    "wof:placetype":"venue"
},
  "geometry": {"coordinates":[-72.970726,43.552961],"type":"Point"}
}