{
  "type": "Feature",
  "properties": {
    "addr:full":"56 Old Farm Rd Stowe VT 05672",
    "addr:housenumber":"56",
    "addr:postcode":"05672",
    "addr:street":"Old Farm Rd",
    "iso:country":"US",
    "sg:address":"56 Old Farm Rd",
    "sg:city":"Stowe",
    "sg:classifiers":[
        {
            "category":"Health Services",
            "subcategory":"Clinic",
            "type":"Services"
        }
    ],
    "sg:phone":"+1 802 253 3070",
    "sg:postcode":"05672",
    "sg:province":"VT",
    "wof:name":"Body & Sole",
    "wof:placetype":"venue"
},
  "geometry": {"coordinates":[-72.69682299999999,44.452005],"type":"Point"}
}