{
  "type": "Feature",
  "properties": {
    "iso:country":"US",
    "sg:address":"88 Mainelli Rd",
    "sg:city":"Middlebury",
    "sg:classifiers":[
        {
            "category":"Building & Trades",
            "subcategory":"Electrical",
            "type":"Services"
        }
    ],
    "sg:phone":"+1 802 388 1332",
    "sg:postcode":"05753",
    "sg:province":"VT",
    "sg:tags":[
        "communication",
        "line"
    ],
    "wof:name":"Dtc",
    "wof:placetype":"venue"
},
  "geometry": {"coordinates":[-73.170436,44.035182],"type":"Point"}
}