{
  "type": "Feature",
  "properties": {
    "iso:country":"US",
    "sg:address":"705 Province St",
    "sg:city":"Richford",
    "sg:classifiers":[
        {
            "category":"Government",
            "subcategory":"Office",
            "type":"Public Place"
        }
    ],
    "sg:phone":"+1 802 848 7786",
    "sg:postcode":"05476",
    "sg:province":"VT",
    "sg:tags":[
        "entry",
        "port"
    ],
    "wof:name":"Port of Entry-Richford",
    "wof:placetype":"venue"
},
  "geometry": {"coordinates":[-72.661456,45.004204],"type":"Point"}
}