{
  "type": "Feature",
  "properties": {
    "addr:full":"218 S Main St Wallingford VT 05778",
    "addr:housenumber":"218",
    "addr:postcode":"05778",
    "addr:street":"S Main St",
    "iso:country":"US",
    "sg:address":"218 S Main St",
    "sg:city":"Wallingford",
    "sg:classifiers":[
        {
            "category":"Organizations",
            "subcategory":"Religious Organization",
            "type":"Services"
        }
    ],
    "sg:phone":"+1 802 446 2161",
    "sg:postcode":"05778",
    "sg:province":"VT",
    "wof:name":"St Patricks Parish",
    "wof:placetype":"venue"
},
  "geometry": {"coordinates":[-73.199865,43.851816],"type":"Point"}
}