{
  "type": "Feature",
  "properties": {
    "iso:country":"US",
    "sg:address":"252 High St",
    "sg:city":"Plainfield",
    "sg:classifiers":[
        {
            "category":"Retail",
            "subcategory":"Auto Repair",
            "type":"Services"
        }
    ],
    "sg:phone":"+1 802 454 1400",
    "sg:postcode":"05667",
    "sg:province":"VT",
    "sg:tags":[
        "repairing",
        "automobile"
    ],
    "wof:name":"R & S Auto",
    "wof:placetype":"venue"
},
  "geometry": {"coordinates":[-72.42997,44.277958],"type":"Point"}
}