{
  "type": "Feature",
  "properties": {
    "iso:country":"US",
    "sg:address":"8 Stratton Rd",
    "sg:city":"Rutland",
    "sg:classifiers":[
        {
            "category":"Education",
            "subcategory":"Vocational School",
            "type":"Public Place"
        }
    ],
    "sg:phone":"+1 802 773 1990",
    "sg:postcode":"05701",
    "sg:province":"VT",
    "wof:name":"Stafford Technical School",
    "wof:placetype":"venue"
},
  "geometry": {"coordinates":[-72.95686499999999,43.618087],"type":"Point"}
}