{
  "type": "Feature",
  "properties": {
    "addr:full":"1335 Shelburne Rd South Burlington VT 05403",
    "addr:housenumber":"1335",
    "addr:postcode":"05403",
    "addr:street":"Shelburne Rd",
    "iso:country":"US",
    "sg:address":"1335 Shelburne Rd",
    "sg:city":"South Burlington",
    "sg:classifiers":[
        {
            "category":"Restaurant",
            "type":"Food & Drink"
        }
    ],
    "sg:menulink":"http://www.allmenus.com/vt/south-burlington/139074-quiznos-sub/menu/",
    "sg:phone":"+1 802 864 0800",
    "sg:postcode":"05403",
    "sg:province":"VT",
    "sg:tags":[
        "wrap",
        "american",
        "sandwich"
    ],
    "wof:name":"Quiznos Sub",
    "wof:placetype":"venue"
},
  "geometry": {"coordinates":[-73.211494,44.432811],"type":"Point"}
}