{
  "type": "Feature",
  "properties": {
    "addr:full":"350 N Pasture Ln Charlotte VT 05445",
    "addr:housenumber":"350",
    "addr:postcode":"05445",
    "addr:street":"N Pasture Ln",
    "iso:country":"US",
    "sg:address":"350 N Pasture Ln",
    "sg:city":"Charlotte",
    "sg:classifiers":[
        {
            "category":"Manufacturing",
            "subcategory":"Printing",
            "type":"Manufacturing & Wholesale Goods"
        }
    ],
    "sg:phone":"+1 802 425 2030",
    "sg:postcode":"05445",
    "sg:province":"VT",
    "sg:tags":[
        "book"
    ],
    "wof:name":"Shanty Pond Press",
    "wof:placetype":"venue"
},
  "geometry": {"coordinates":[-73.165982,44.346727],"type":"Point"}
}