{
  "type": "Feature",
  "properties": {
    "addr:full":"8 Harrington Ave Barre VT 05641",
    "addr:housenumber":"8",
    "addr:postcode":"05641",
    "addr:street":"Harrington Ave",
    "iso:country":"US",
    "sg:address":"8 Harrington Ave",
    "sg:city":"Barre",
    "sg:classifiers":[
        {
            "category":"Taxi",
            "type":"Transportation"
        }
    ],
    "sg:phone":"+1 802 476 0882",
    "sg:postcode":"05641",
    "sg:province":"VT",
    "sg:tags":[
        "taxicab"
    ],
    "wof:name":"K C Taxi",
    "wof:placetype":"venue"
},
  "geometry": {"coordinates":[-72.50589600000001,44.205356],"type":"Point"}
}