{
  "type": "Feature",
  "properties": {
    "addr:full":"1 Main St Glover VT 05829",
    "addr:housenumber":"1",
    "addr:postcode":"05829",
    "addr:street":"Main St",
    "iso:country":"US",
    "sg:address":"1 Main St",
    "sg:city":"Glover",
    "sg:classifiers":[
        {
            "category":"Food & Beverages",
            "subcategory":"Groceries & Convenience Stores",
            "type":"Retail Goods"
        }
    ],
    "sg:phone":"+1 802 525 8822",
    "sg:postcode":"05829",
    "sg:province":"VT",
    "sg:tags":[
        "market"
    ],
    "wof:name":"Currier's Quality Market",
    "wof:placetype":"venue"
},
  "geometry": {"coordinates":[-72.10078300000001,45.003808],"type":"Point"}
}