{
  "type": "Feature",
  "properties": {
    "iso:country":"US",
    "sg:address":"31 Macfarlane Rd",
    "sg:city":"Hyde Park",
    "sg:classifiers":[
        {
            "category":"Manufacturing",
            "subcategory":"Lumber",
            "type":"Manufacturing & Wholesale Goods"
        }
    ],
    "sg:phone":"+1 802 888 3451",
    "sg:postcode":"05661",
    "sg:province":"VT",
    "sg:tags":[
        "logging"
    ],
    "wof:name":"Ferlands Logging Co",
    "wof:placetype":"venue"
},
  "geometry": {"coordinates":[-72.537451,44.583998],"type":"Point"}
}