{
  "type": "Feature",
  "properties": {
    "iso:country":"US",
    "sg:address":"2735 Shelburne Rd",
    "sg:city":"Shelburne",
    "sg:classifiers":[
        {
            "category":"Home & Garden",
            "subcategory":"Furniture",
            "type":"Retail Goods"
        }
    ],
    "sg:phone":"+1 802 985 8028",
    "sg:postcode":"05482",
    "sg:province":"VT",
    "wof:name":"Carriage House Interiors Inc",
    "wof:placetype":"venue"
},
  "geometry": {"coordinates":[-73.213531,44.415806],"type":"Point"}
}