{
  "type": "Feature",
  "properties": {
    "iso:country":"US",
    "sg:address":"978 State Rte 11",
    "sg:city":"Chester",
    "sg:classifiers":[
        {
            "category":"Government",
            "subcategory":"Office",
            "type":"Public Place"
        }
    ],
    "sg:phone":"+1 802 875 2991",
    "sg:postcode":"05143",
    "sg:province":"VT",
    "sg:tags":[
        "federal",
        "security"
    ],
    "wof:name":"US Army Reserve Hospital",
    "wof:placetype":"venue"
},
  "geometry": {"coordinates":[-72.57916899999999,43.263248],"type":"Point"}
}