{
  "type": "Feature",
  "properties": {
    "iso:country":"US",
    "sg:address":"5 Pierpoint Ave",
    "sg:city":"Rutland",
    "sg:phone":"+1 802 773 7183",
    "sg:postcode":"05701",
    "sg:province":"VT",
    "sg:tags":[
        "equipment",
        "supply"
    ],
    "wof:name":"Hobart Sales & Svc",
    "wof:placetype":"venue"
},
  "geometry": {"coordinates":[-72.99199,43.612661],"type":"Point"}
}