{
  "type": "Feature",
  "properties": {
    "addr:full":"322 North St Bennington VT 05201",
    "addr:housenumber":"322",
    "addr:postcode":"05201",
    "addr:street":"North St",
    "iso:country":"US",
    "sg:address":"322 North St",
    "sg:city":"Bennington",
    "sg:classifiers":[
        {
            "category":"Retail",
            "subcategory":"Auto Repair",
            "type":"Services"
        }
    ],
    "sg:phone":"+1 802 442 9070",
    "sg:postcode":"05201",
    "sg:province":"VT",
    "sg:tags":[
        "repairing",
        "tire"
    ],
    "wof:name":"Wassick's Tire Svc",
    "wof:placetype":"venue"
},
  "geometry": {"coordinates":[-73.20013899999999,42.887604],"type":"Point"}
}