{
  "type": "Feature",
  "properties": {
    "iso:country":"US",
    "sg:address":"21 Curtis Ave",
    "sg:city":"Burlington",
    "sg:classifiers":[
        {
            "category":"Shopping",
            "subcategory":"Gifts & Souvenirs",
            "type":"Retail Goods"
        }
    ],
    "sg:phone":"+1 802 864 5091",
    "sg:postcode":"05408",
    "sg:province":"VT",
    "wof:name":"TCS Collectibles",
    "wof:placetype":"venue"
},
  "geometry": {"coordinates":[-72.44520199999999,44.217529],"type":"Point"}
}