{
  "type": "Feature",
  "properties": {
    "iso:country":"US",
    "sg:address":"10 S Main St",
    "sg:city":"St Albans",
    "sg:classifiers":[
        {
            "category":"Utilities",
            "subcategory":"Mobile Phone",
            "type":"Services"
        },
        {
            "category":"Shopping",
            "type":"Retail Goods"
        }
    ],
    "sg:phone":"+1 802 524 9640",
    "sg:postcode":"05478",
    "sg:province":"VT",
    "sg:tags":[
        "communication",
        "radiotelephone",
        "cellular",
        "telephone"
    ],
    "wof:name":"Rt 7 Cellular",
    "wof:placetype":"venue"
},
  "geometry": {"coordinates":[-73.083552,44.810365],"type":"Point"}
}