{
  "type": "Feature",
  "properties": {
    "iso:country":"US",
    "sg:address":"262 River St",
    "sg:city":"Springfield",
    "sg:classifiers":[
        {
            "category":"Cinema",
            "subcategory":"Movie Rental",
            "type":"Entertainment"
        }
    ],
    "sg:phone":"+1 802 885 2868",
    "sg:postcode":"05156",
    "sg:province":"VT",
    "sg:tags":[
        "video",
        "tape"
    ],
    "wof:name":"Video Time",
    "wof:placetype":"venue"
},
  "geometry": {"coordinates":[-72.49495400000001,43.306898],"type":"Point"}
}