{
  "type": "Feature",
  "properties": {
    "iso:country":"US",
    "sg:address":"17 Village Sq",
    "sg:city":"Barton",
    "sg:classifiers":[
        {
            "category":"Government",
            "subcategory":"Office",
            "type":"Public Place"
        }
    ],
    "sg:phone":"+1 802 525 4747",
    "sg:postcode":"05822",
    "sg:province":"VT",
    "sg:tags":[
        "village"
    ],
    "wof:name":"Barton Elect & Village",
    "wof:placetype":"venue"
},
  "geometry": {"coordinates":[-72.17984300000001,44.75054],"type":"Point"}
}