{
  "type": "Feature",
  "properties": {
    "iso:country":"US",
    "sg:address":"51 S Main St",
    "sg:city":"Stowe",
    "sg:classifiers":[
        {
            "category":"Travel",
            "subcategory":"Travel Agent",
            "type":"Entertainment"
        }
    ],
    "sg:phone":"+1 802 253 7752",
    "sg:postcode":"05672",
    "sg:province":"VT",
    "sg:tags":[
        "agency",
        "bureau"
    ],
    "wof:name":"Stowe Travel Svc",
    "wof:placetype":"venue"
},
  "geometry": {"coordinates":[-72.688267,44.465191],"type":"Point"}
}