{
  "type": "Feature",
  "properties": {
    "iso:country":"US",
    "sg:address":"5203 Shelburne Rd",
    "sg:city":"Shelburne",
    "sg:classifiers":[
        {
            "category":"Real Estate",
            "subcategory":"Real Estate Operator",
            "type":"Services"
        }
    ],
    "sg:phone":"+1 802 985 2764",
    "sg:postcode":"05482",
    "sg:province":"VT",
    "sg:tags":[
        "apartment"
    ],
    "sg:website":"www.vaoa.com",
    "wof:name":"Apartment Owners Association Llc",
    "wof:placetype":"venue"
},
  "geometry": {"coordinates":[-73.226885,44.381849],"type":"Point"}
}