{
  "type": "Feature",
  "properties": {
    "addr:full":"10 Hyde Rd Grand Isle VT 05458",
    "addr:housenumber":"10",
    "addr:postcode":"05458",
    "addr:street":"Hyde Rd",
    "iso:country":"US",
    "sg:address":"10 Hyde Rd",
    "sg:city":"Grand Isle",
    "sg:classifiers":[
        {
            "category":"Education",
            "subcategory":"Library",
            "type":"Public Place"
        }
    ],
    "sg:phone":"+1 802 372 4797",
    "sg:postcode":"05458",
    "sg:province":"VT",
    "wof:name":"Grand Isle Free Library",
    "wof:placetype":"venue"
},
  "geometry": {"coordinates":[-73.295828,44.722348],"type":"Point"}
}