{
  "type": "Feature",
  "properties": {
    "iso:country":"US",
    "sg:address":"22 Commerce St Unit 8A",
    "sg:city":"Hinesburg",
    "sg:classifiers":[
        {
            "category":"Health Services",
            "subcategory":"Chiropractor",
            "type":"Services"
        }
    ],
    "sg:phone":"+1 802 482 4476",
    "sg:postcode":"05461",
    "sg:province":"VT",
    "sg:tags":[
        "chiropractic"
    ],
    "sg:website":"http://www.vtsportschiro.com",
    "wof:name":"Vermont Chiropractic & Sports Therapy",
    "wof:placetype":"venue"
},
  "geometry": {"coordinates":[-73.11190000000001,44.334511],"type":"Point"}
}