{
  "type": "Feature",
  "properties": {
    "iso:country":"US",
    "sg:address":"905 Killington Rd",
    "sg:city":"Killington",
    "sg:classifiers":[
        {
            "category":"Travel",
            "subcategory":"Hotels & Motels",
            "type":"Entertainment"
        }
    ],
    "sg:phone":"+1 802 422 4222",
    "sg:postcode":"05751",
    "sg:province":"VT",
    "sg:website":"www.comfortk1.com",
    "wof:name":"Comfort Inn",
    "wof:placetype":"venue"
},
  "geometry": {"coordinates":[-72.79220599999999,43.658507],"type":"Point"}
}