{
  "type": "Feature",
  "properties": {
    "addr:full":"355 Main St West Rutland VT 05777",
    "addr:housenumber":"355",
    "addr:postcode":"05777",
    "addr:street":"Main St",
    "iso:country":"US",
    "sg:address":"355 Main St",
    "sg:city":"West Rutland",
    "sg:classifiers":[
        {
            "category":"Autos & Motor Vehicles",
            "subcategory":"Fuel & Gas Station",
            "type":"Retail Goods"
        }
    ],
    "sg:phone":"+1 802 438 2571",
    "sg:postcode":"05777",
    "sg:province":"VT",
    "sg:tags":[
        "oil"
    ],
    "wof:name":"Mc Gann's Mobil Station",
    "wof:placetype":"venue"
},
  "geometry": {"coordinates":[-73.04481199999999,43.593166],"type":"Point"}
}