{
  "type": "Feature",
  "properties": {
    "iso:country":"US",
    "sg:address":"29 Rockingham St",
    "sg:city":"Bellows Falls",
    "sg:classifiers":[
        {
            "category":"Personal",
            "type":"Services"
        }
    ],
    "sg:phone":"+1 802 463 3307",
    "sg:postcode":"05101",
    "sg:province":"VT",
    "wof:name":"Gerry Chandler",
    "wof:placetype":"venue"
},
  "geometry": {"coordinates":[-72.44444799999999,43.134177],"type":"Point"}
}