{
  "type": "Feature",
  "properties": {
    "iso:country":"US",
    "sg:address":"303 US Hwy 5",
    "sg:city":"Norwich",
    "sg:classifiers":[
        {
            "category":"Shopping",
            "type":"Retail Goods"
        }
    ],
    "sg:phone":"+1 802 649 3124",
    "sg:postcode":"05055",
    "sg:province":"VT",
    "sg:tags":[
        "merchandise"
    ],
    "wof:name":"Pitney Bowes",
    "wof:placetype":"venue"
},
  "geometry": {"coordinates":[-72.318515,43.697003],"type":"Point"}
}