{
  "type": "Feature",
  "properties": {
    "iso:country":"US",
    "sg:address":"14 Hull Ave",
    "sg:city":"Wallingford",
    "sg:classifiers":[
        {
            "category":"Building & Trades",
            "subcategory":"Cleaning & Sanitation",
            "type":"Services"
        }
    ],
    "sg:phone":"+1 802 446 2234",
    "sg:postcode":"05773",
    "sg:province":"VT",
    "sg:tags":[
        "janitor"
    ],
    "wof:name":"Clean Sweep",
    "wof:placetype":"venue"
},
  "geometry": {"coordinates":[-72.97671,43.473985],"type":"Point"}
}