{
  "type": "Feature",
  "properties": {
    "iso:country":"US",
    "sg:address":"126 Stirling Pl",
    "sg:city":"Burlington",
    "sg:classifiers":[
        {
            "category":"Building & Trades",
            "subcategory":"Electrical",
            "type":"Services"
        }
    ],
    "sg:phone":"+1 802 658 0821",
    "sg:postcode":"05408",
    "sg:province":"VT",
    "sg:tags":[
        "industrial",
        "electrician",
        "electric",
        "contractors-commercial"
    ],
    "wof:name":"Soutiere Electric",
    "wof:placetype":"venue"
},
  "geometry": {"coordinates":[-73.259365,44.506736],"type":"Point"}
}