{
  "type": "Feature",
  "properties": {
    "addr:full":"2032 Earl Gray Rd Morrisville VT 05661",
    "addr:housenumber":"2032",
    "addr:postcode":"05661",
    "addr:street":"Earl Gray Rd",
    "iso:country":"US",
    "sg:address":"2032 Earl Gray Rd",
    "sg:city":"Morrisville",
    "sg:classifiers":[
        {
            "category":"Retail",
            "subcategory":"Repair Shop",
            "type":"Services"
        }
    ],
    "sg:phone":"+1 802 888 4524",
    "sg:postcode":"05661",
    "sg:province":"VT",
    "wof:name":"Andys Repair",
    "wof:placetype":"venue"
},
  "geometry": {"coordinates":[-72.566698,44.512604],"type":"Point"}
}