{
  "type": "Feature",
  "properties": {
    "addr:full":"436 Washing Brook Rd Bennington VT 05201",
    "addr:housenumber":"436",
    "addr:postcode":"05201",
    "addr:street":"Washing Brook Rd",
    "iso:country":"US",
    "sg:address":"436 Washing Brook Rd",
    "sg:city":"Bennington",
    "sg:classifiers":[
        {
            "category":"Real Estate",
            "subcategory":"Real Estate Services",
            "type":"Services"
        },
        {
            "category":"Real Estate",
            "subcategory":"Real Estate Agent",
            "type":"Services"
        }
    ],
    "sg:phone":"+1 802 823 5859",
    "sg:postcode":"05201",
    "sg:province":"VT",
    "sg:tags":[
        "buyer",
        "broker"
    ],
    "wof:name":"Tripp Painting Rl",
    "wof:placetype":"venue"
},
  "geometry": {"coordinates":[-73.19203400000001,42.80599],"type":"Point"}
}