{
  "type": "Feature",
  "properties": {
    "addr:full":"18 Elm St Woodstock VT 05091",
    "addr:housenumber":"18",
    "addr:postcode":"05091",
    "addr:street":"Elm St",
    "iso:country":"US",
    "sg:address":"18 Elm St",
    "sg:city":"Woodstock",
    "sg:classifiers":[
        {
            "category":"Real Estate",
            "subcategory":"Real Estate Agent",
            "type":"Services"
        }
    ],
    "sg:phone":"+1 802 457 3700",
    "sg:postcode":"05091",
    "sg:province":"VT",
    "sg:tags":[
        "consultant"
    ],
    "sg:website":"www.woodstockcorp-re.com",
    "wof:name":"Woodstock Corp",
    "wof:placetype":"venue"
},
  "geometry": {"coordinates":[-72.51849199999999,43.626004],"type":"Point"}
}