{
  "type": "Feature",
  "properties": {
    "iso:country":"US",
    "sg:address":"6 Maple St",
    "sg:city":"Winooski",
    "sg:classifiers":[
        {
            "category":"Organizations",
            "subcategory":"Community Association",
            "type":"Services"
        }
    ],
    "sg:phone":"+1 802 655 9832",
    "sg:postcode":"05404",
    "sg:province":"VT",
    "sg:tags":[
        "club"
    ],
    "wof:name":"Veterans Of Foreign Wars",
    "wof:placetype":"venue"
},
  "geometry": {"coordinates":[-73.187929,44.492711],"type":"Point"}
}