{
  "type": "Feature",
  "properties": {
    "addr:full":"114 Main St Montpelier VT 05602",
    "addr:housenumber":"114",
    "addr:postcode":"05602",
    "addr:street":"Main St",
    "iso:country":"US",
    "sg:address":"114 Main St",
    "sg:city":"Montpelier",
    "sg:classifiers":[
        {
            "category":"Professional",
            "subcategory":"Computer Services",
            "type":"Services"
        }
    ],
    "sg:phone":"+1 802 223 3729",
    "sg:postcode":"05602",
    "sg:province":"VT",
    "sg:tags":[
        "programing",
        "custom"
    ],
    "wof:name":"Green Mountain Logic Inc",
    "wof:placetype":"venue"
},
  "geometry": {"coordinates":[-72.574558,44.261041],"type":"Point"}
}