{
  "type": "Feature",
  "properties": {
    "iso:country":"US",
    "sg:address":"64 Elm Hill St",
    "sg:city":"Springfield",
    "sg:classifiers":[
        {
            "category":"Real Estate",
            "subcategory":"Real Estate Services",
            "type":"Services"
        }
    ],
    "sg:phone":"+1 802 885 3705",
    "sg:postcode":"05156",
    "sg:province":"VT",
    "sg:tags":[
        "company",
        "title"
    ],
    "wof:name":"Crown Point Title Svc",
    "wof:placetype":"venue"
},
  "geometry": {"coordinates":[-72.48262800000001,43.303595],"type":"Point"}
}