{
  "type": "Feature",
  "properties": {
    "iso:country":"US",
    "sg:address":"2454 Sugar Hollow Rd",
    "sg:city":"Pittsford",
    "sg:classifiers":[
        {
            "category":"Professional",
            "subcategory":"Lawyer & Legal Services",
            "type":"Services"
        }
    ],
    "sg:phone":"+1 802 483 9434",
    "sg:postcode":"05763",
    "sg:province":"VT",
    "wof:name":"Kimberly K Hayden",
    "wof:placetype":"venue"
},
  "geometry": {"coordinates":[-73.018783,43.756325],"type":"Point"}
}