{
  "type": "Feature",
  "properties": {
    "iso:country":"US",
    "sg:address":"296 E Montpelier Rd",
    "sg:city":"Barre",
    "sg:classifiers":[
        {
            "category":"Autos & Motor Vehicles",
            "subcategory":"Automobile Sales",
            "type":"Retail Goods"
        }
    ],
    "sg:phone":"+1 802 479 0140",
    "sg:postcode":"05641",
    "sg:province":"VT",
    "sg:tags":[
        "car",
        "dealer"
    ],
    "wof:name":"Just Good Autos",
    "wof:placetype":"venue"
},
  "geometry": {"coordinates":[-72.496886,44.213149],"type":"Point"}
}