{
  "type": "Feature",
  "properties": {
    "iso:country":"US",
    "sg:address":"2142 Willoughby Lake Rd",
    "sg:city":"Barton",
    "sg:classifiers":[
        {
            "category":"Farming",
            "subcategory":"Farm",
            "type":"Manufacturing & Wholesale Goods"
        }
    ],
    "sg:phone":"+1 802 525 4539",
    "sg:postcode":"05822",
    "sg:province":"VT",
    "sg:tags":[
        "crop",
        "general"
    ],
    "wof:name":"Rainbow Farm",
    "wof:placetype":"venue"
},
  "geometry": {"coordinates":[-72.151139,44.757822],"type":"Point"}
}