{
  "type": "Feature",
  "properties": {
    "iso:country":"US",
    "sg:address":"80 S Main St",
    "sg:city":"Waterbury",
    "sg:classifiers":[
        {
            "category":"Retail",
            "subcategory":"Photofinishing",
            "type":"Services"
        }
    ],
    "sg:phone":"+1 802 244 5937",
    "sg:postcode":"05676",
    "sg:province":"VT",
    "sg:tags":[
        "photo",
        "finishing",
        "store",
        "merchandise"
    ],
    "wof:name":"Last Frame Photo Lab & Gallery",
    "wof:placetype":"venue"
},
  "geometry": {"coordinates":[-72.753208,44.334607],"type":"Point"}
}