{
  "type": "Feature",
  "properties": {
    "iso:country":"US",
    "sg:address":"1097 Main St",
    "sg:city":"St Johnsbury",
    "sg:classifiers":[
        {
            "category":"Professional",
            "subcategory":"Lawyer & Legal Services",
            "type":"Services"
        }
    ],
    "sg:phone":"+1 802 748 5525",
    "sg:postcode":"05819",
    "sg:province":"VT",
    "sg:tags":[
        "attorney"
    ],
    "sg:website":"www.vtlegalhelp.com",
    "wof:name":"Deborah T Bucknam Law Office",
    "wof:placetype":"venue"
},
  "geometry": {"coordinates":[-72.02079000000001,44.41805],"type":"Point"}
}