{
  "type": "Feature",
  "properties": {
    "iso:country":"US",
    "sg:address":"12 S Main St",
    "sg:city":"Randolph",
    "sg:classifiers":[
        {
            "category":"Banks & Credit Unions",
            "subcategory":"Investment Brokerage",
            "type":"Services"
        }
    ],
    "sg:phone":"+1 802 728 4602",
    "sg:postcode":"05060",
    "sg:province":"VT",
    "sg:tags":[
        "security"
    ],
    "wof:name":"Edward Jones 08010",
    "wof:placetype":"venue"
},
  "geometry": {"coordinates":[-72.664818,43.922289],"type":"Point"}
}