{
  "type": "Feature",
  "properties": {
    "iso:country":"US",
    "sg:address":"1 Pine Haven Shores Rd",
    "sg:city":"Shelburne",
    "sg:classifiers":[
        {
            "category":"Manufacturing",
            "subcategory":"Printing",
            "type":"Manufacturing & Wholesale Goods"
        }
    ],
    "sg:phone":"+1 802 985 2400",
    "sg:postcode":"05482",
    "sg:province":"VT",
    "sg:tags":[
        "newspaper"
    ],
    "wof:name":"Vermont TIMES/Vox",
    "wof:placetype":"venue"
},
  "geometry": {"coordinates":[-73.216504,44.419644],"type":"Point"}
}