{
  "type": "Feature",
  "properties": {
    "iso:country":"US",
    "sg:address":"11 Main St",
    "sg:city":"Fair Haven",
    "sg:classifiers":[
        {
            "category":"Autos & Motor Vehicles",
            "subcategory":"Automobile Sales",
            "type":"Retail Goods"
        }
    ],
    "sg:phone":"+1 802 265 3441",
    "sg:postcode":"05743",
    "sg:province":"VT",
    "sg:tags":[
        "car",
        "dealer"
    ],
    "wof:name":"George Pritchard New-Used Cars",
    "wof:placetype":"venue"
},
  "geometry": {"coordinates":[-73.26494599999999,43.590606],"type":"Point"}
}