{
  "type": "Feature",
  "properties": {
    "iso:country":"US",
    "sg:address":"3 Grove St",
    "sg:city":"Brattleboro",
    "sg:classifiers":[
        {
            "category":"Shopping",
            "subcategory":"Optical Goods",
            "type":"Retail Goods"
        }
    ],
    "sg:phone":"+1 802 257 1400",
    "sg:postcode":"05301",
    "sg:province":"VT",
    "wof:name":"Omega Optical Inc",
    "wof:placetype":"venue"
},
  "geometry": {"coordinates":[-72.559408,42.854854],"type":"Point"}
}