{
  "type": "Feature",
  "properties": {
    "iso:country":"US",
    "sg:address":"102 Airport Rd",
    "sg:city":"Swanton",
    "sg:classifiers":[
        {
            "category":"Freight",
            "type":"Transportation"
        }
    ],
    "sg:phone":"+1 802 868 3741",
    "sg:postcode":"05488",
    "sg:province":"VT",
    "wof:name":"Champlain Valley Intl",
    "wof:placetype":"venue"
},
  "geometry": {"coordinates":[-73.094666,44.938513],"type":"Point"}
}