{
  "type": "Feature",
  "properties": {
    "addr:full":"264 N Winooski Ave Burlington VT 05401",
    "addr:housenumber":"264",
    "addr:postcode":"05401",
    "addr:street":"N Winooski Ave",
    "iso:country":"US",
    "sg:address":"264 N Winooski Ave",
    "sg:city":"Burlington",
    "sg:classifiers":[
        {
            "category":"Professional",
            "subcategory":"Lawyer & Legal Services",
            "type":"Services"
        }
    ],
    "sg:phone":"+1 802 863 2871",
    "sg:postcode":"05401",
    "sg:province":"VT",
    "sg:website":"www.vtlegalaid.org",
    "wof:name":"Vermont Legal Aid Inc",
    "wof:placetype":"venue"
},
  "geometry": {"coordinates":[-73.209254,44.486639],"type":"Point"}
}