{
  "type": "Feature",
  "properties": {
    "iso:country":"US",
    "sg:address":"8 Alta Rd",
    "sg:city":"Bondville",
    "sg:classifiers":[
        {
            "category":"Manufacturing",
            "subcategory":"Apparel",
            "type":"Manufacturing & Wholesale Goods"
        }
    ],
    "sg:phone":"+1 802 297 2996",
    "sg:postcode":"05340",
    "sg:province":"VT",
    "sg:tags":[
        "outerwear",
        "mfg"
    ],
    "wof:name":"Amber Rose",
    "wof:placetype":"venue"
},
  "geometry": {"coordinates":[-72.911237,43.157038],"type":"Point"}
}