{
  "type": "Feature",
  "properties": {
    "iso:country":"US",
    "sg:address":"2067 North Rd",
    "sg:city":"Hinesburg",
    "sg:classifiers":[
        {
            "category":"Farming",
            "subcategory":"Farm",
            "type":"Manufacturing & Wholesale Goods"
        }
    ],
    "sg:phone":"+1 802 482 4070",
    "sg:postcode":"05461",
    "sg:province":"VT",
    "sg:tags":[
        "crop",
        "general"
    ],
    "wof:name":"Peaches of Vermont",
    "wof:placetype":"venue"
},
  "geometry": {"coordinates":[-73.076111,44.335843],"type":"Point"}
}