{
  "type": "Feature",
  "properties": {
    "iso:country":"US",
    "sg:address":"54 Woodstock Ave",
    "sg:city":"Rutland",
    "sg:classifiers":[
        {
            "category":"Personal",
            "subcategory":"Beauty Salon",
            "type":"Services"
        }
    ],
    "sg:phone":"+1 802 786 2204",
    "sg:postcode":"05701",
    "sg:province":"VT",
    "sg:tags":[
        "manicuring"
    ],
    "wof:name":"Unisex Nail Salon",
    "wof:placetype":"venue"
},
  "geometry": {"coordinates":[-72.96768899999999,43.611976],"type":"Point"}
}