{
  "type": "Feature",
  "properties": {
    "iso:country":"US",
    "sg:address":"41 Parsonage Rd",
    "sg:city":"Starksboro",
    "sg:classifiers":[
        {
            "category":"Education",
            "subcategory":"Special Training",
            "type":"Public Place"
        },
        {
            "category":"Education",
            "subcategory":"School",
            "type":"Public Place"
        },
        {
            "category":"Government",
            "subcategory":"Office",
            "type":"Public Place"
        }
    ],
    "sg:phone":"+1 802 453 2949",
    "sg:postcode":"05487",
    "sg:province":"VT",
    "sg:tags":[
        "elementary",
        "educational"
    ],
    "wof:name":"Robinson School",
    "wof:placetype":"venue"
},
  "geometry": {"coordinates":[-73.058171,44.224221],"type":"Point"}
}