{
  "type": "Feature",
  "properties": {
    "iso:country":"US",
    "sg:address":"244 River St",
    "sg:city":"Springfield",
    "sg:classifiers":[
        {
            "category":"Restaurant",
            "type":"Food & Drink"
        }
    ],
    "sg:phone":"+1 802 885 9231",
    "sg:postcode":"05156",
    "sg:province":"VT",
    "wof:name":"Jonathan's Family Restaurant",
    "wof:placetype":"venue"
},
  "geometry": {"coordinates":[-72.4961,43.308093],"type":"Point"}
}