{
  "type": "Feature",
  "properties": {
    "iso:country":"US",
    "sg:address":"44 S Main St",
    "sg:city":"Randolph",
    "sg:classifiers":[
        {
            "category":"Health Services",
            "subcategory":"Doctor",
            "type":"Services"
        }
    ],
    "sg:phone":"+1 802 728 2430",
    "sg:postcode":"05060",
    "sg:province":"VT",
    "sg:tags":[
        "medical"
    ],
    "wof:name":"Joseph R Kiernan",
    "wof:placetype":"venue"
},
  "geometry": {"coordinates":[-72.66609800000001,43.917183],"type":"Point"}
}