{
  "type": "Feature",
  "properties": {
    "iso:country":"US",
    "sg:address":"447 Brooklyn St",
    "sg:city":"Morrisville",
    "sg:classifiers":[
        {
            "category":"Education",
            "subcategory":"Special Training",
            "type":"Public Place"
        }
    ],
    "sg:phone":"+1 802 888 9814",
    "sg:postcode":"05661",
    "sg:province":"VT",
    "sg:tags":[
        "educational"
    ],
    "wof:name":"Preparedness Educational Svcs",
    "wof:placetype":"venue"
},
  "geometry": {"coordinates":[-72.59827799999999,44.568868],"type":"Point"}
}