{
  "type": "Feature",
  "properties": {
    "iso:country":"US",
    "sg:address":"89 S Main St",
    "sg:city":"Waterbury",
    "sg:classifiers":[
        {
            "category":"Social Services",
            "type":"Services"
        }
    ],
    "sg:phone":"+1 802 241 4188",
    "sg:postcode":"05676",
    "sg:province":"VT",
    "sg:tags":[
        "counseling"
    ],
    "wof:name":"Fieldstone Counseling",
    "wof:placetype":"venue"
},
  "geometry": {"coordinates":[-72.753208,44.334607],"type":"Point"}
}