{
  "type": "Feature",
  "properties": {
    "iso:country":"US",
    "sg:address":"15 Railroad St",
    "sg:city":"Waterbury",
    "sg:classifiers":[
        {
            "category":"Home & Garden",
            "subcategory":"Building Materials",
            "type":"Retail Goods"
        }
    ],
    "sg:phone":"+1 802 244 6685",
    "sg:postcode":"05676",
    "sg:province":"VT",
    "sg:tags":[
        "supply"
    ],
    "wof:name":"Station Lumber & Building Sups",
    "wof:placetype":"venue"
},
  "geometry": {"coordinates":[-72.754334,44.337819],"type":"Point"}
}