{
  "type": "Feature",
  "properties": {
    "addr:full":"314 South St Essex Junction VT 05452",
    "addr:housenumber":"314",
    "addr:postcode":"05452",
    "addr:street":"South St",
    "iso:country":"US",
    "sg:address":"314 South St",
    "sg:city":"Essex Junction",
    "sg:classifiers":[
        {
            "category":"Farming",
            "subcategory":"Dairy Farm",
            "type":"Manufacturing & Wholesale Goods"
        }
    ],
    "sg:phone":"+1 802 878 4479",
    "sg:postcode":"05452",
    "sg:province":"VT",
    "wof:name":"North Williston Cattle Co Inc",
    "wof:placetype":"venue"
},
  "geometry": {"coordinates":[-73.13751999999999,44.487753],"type":"Point"}
}