{
  "type": "Feature",
  "properties": {
    "addr:full":"145 Pine Haven Shores Rd Shelburne VT 05482",
    "addr:housenumber":"145",
    "addr:postcode":"05482",
    "addr:street":"Pine Haven Shores Rd",
    "iso:country":"US",
    "sg:address":"145 Pine Haven Shores Rd",
    "sg:city":"Shelburne",
    "sg:classifiers":[
        {
            "category":"Real Estate",
            "subcategory":"Architect",
            "type":"Services"
        }
    ],
    "sg:phone":"+1 802 863 9715",
    "sg:postcode":"05482",
    "sg:province":"VT",
    "wof:name":"Timberworks Design",
    "wof:placetype":"venue"
},
  "geometry": {"coordinates":[-73.213757,44.419221],"type":"Point"}
}