{
  "type": "Feature",
  "properties": {
    "iso:country":"US",
    "sg:address":"436 Middle Rd N",
    "sg:city":"Middlebury",
    "sg:classifiers":[
        {
            "category":"Education",
            "subcategory":"Special Training",
            "type":"Public Place"
        }
    ],
    "sg:phone":"+1 802 388 7281",
    "sg:postcode":"05753",
    "sg:province":"VT",
    "wof:name":"Arrive Alive Driving School",
    "wof:placetype":"venue"
},
  "geometry": {"coordinates":[-73.153904,43.997322],"type":"Point"}
}