{
  "type": "Feature",
  "properties": {
    "iso:country":"US",
    "sg:address":"111 Brush Hill Rd",
    "sg:city":"Williamstown",
    "sg:classifiers":[
        {
            "category":"Education",
            "subcategory":"School",
            "type":"Public Place"
        }
    ],
    "sg:phone":"+1 802 433 5818",
    "sg:postcode":"05679",
    "sg:province":"VT",
    "wof:name":"Orange North Supervisory Union",
    "wof:placetype":"venue"
},
  "geometry": {"coordinates":[-72.546915,44.123719],"type":"Point"}
}