{
  "type": "Feature",
  "properties": {
    "iso:country":"US",
    "sg:address":"100 Hospital Dr",
    "sg:city":"Bennington",
    "sg:classifiers":[
        {
            "category":"Education",
            "subcategory":"Library",
            "type":"Public Place"
        }
    ],
    "sg:phone":"+1 802 447 5120",
    "sg:postcode":"05201",
    "sg:province":"VT",
    "sg:tags":[
        "special",
        "interest"
    ],
    "wof:name":"Medical Library",
    "wof:placetype":"venue"
},
  "geometry": {"coordinates":[-73.204211,42.873909],"type":"Point"}
}