{
  "type": "Feature",
  "properties": {
    "iso:country":"US",
    "sg:address":"1494 State Rte 105",
    "sg:city":"Newport",
    "sg:classifiers":[
        {
            "category":"Retail",
            "subcategory":"Portrait Studio",
            "type":"Services"
        }
    ],
    "sg:phone":"+1 802 334 7355",
    "sg:postcode":"05855",
    "sg:province":"VT",
    "sg:tags":[
        "photography"
    ],
    "wof:name":"Jay Foto",
    "wof:placetype":"venue"
},
  "geometry": {"coordinates":[-72.177994,44.946123],"type":"Point"}
}