{
  "type": "Feature",
  "properties": {
    "iso:country":"US",
    "sg:address":"916 Orchard Rd",
    "sg:city":"Bennington",
    "sg:classifiers":[
        {
            "category":"Travel",
            "subcategory":"Hotels & Motels",
            "type":"Entertainment"
        }
    ],
    "sg:phone":"+1 802 442 5619",
    "sg:postcode":"05201",
    "sg:province":"VT",
    "sg:tags":[
        "breakfast",
        "accommodation",
        "bed"
    ],
    "sg:website":"www.alexandrainn.com",
    "wof:name":"Alexandra Bed & Breakfast",
    "wof:placetype":"venue"
},
  "geometry": {"coordinates":[-73.21173899999999,42.905086],"type":"Point"}
}