{
  "type": "Feature",
  "properties": {
    "iso:country":"US",
    "sg:address":"33 Lewis Ct",
    "sg:city":"St Johnsbury",
    "sg:classifiers":[
        {
            "category":"Utilities",
            "subcategory":"Fuel Oil & Lpg",
            "type":"Services"
        }
    ],
    "sg:phone":"+1 802 748 3011",
    "sg:postcode":"05819",
    "sg:province":"VT",
    "sg:tags":[
        "home",
        "kerosene",
        "heating"
    ],
    "wof:name":"Fred W Lewis Oil Co Inc",
    "wof:placetype":"venue"
},
  "geometry": {"coordinates":[-72.012199,44.420062],"type":"Point"}
}