{
  "type": "Feature",
  "properties": {
    "iso:country":"US",
    "sg:address":"8 N Main St",
    "sg:city":"Wilmington",
    "sg:classifiers":[
        {
            "category":"Organizations",
            "subcategory":"Religious Organization",
            "type":"Services"
        }
    ],
    "sg:phone":"+1 802 464 5667",
    "sg:postcode":"05363",
    "sg:province":"VT",
    "sg:tags":[
        "church"
    ],
    "wof:name":"Wilmington Baptist Church",
    "wof:placetype":"venue"
},
  "geometry": {"coordinates":[-72.86931199999999,42.869208],"type":"Point"}
}