{
  "type": "Feature",
  "properties": {
    "iso:country":"US",
    "sg:address":"1150 10 Mile Square Rd",
    "sg:city":"Island Pond",
    "sg:classifiers":[
        {
            "category":"Retail",
            "subcategory":"Animal Services",
            "type":"Services"
        }
    ],
    "sg:phone":"+1 802 723 6194",
    "sg:postcode":"05846",
    "sg:province":"VT",
    "sg:tags":[
        "pet",
        "boarding",
        "sitting"
    ],
    "wof:name":"Maxwell's Kingdom Kennel",
    "wof:placetype":"venue"
},
  "geometry": {"coordinates":[-71.879803,44.81472],"type":"Point"}
}