{
  "type": "Feature",
  "properties": {
    "iso:country":"US",
    "sg:address":"16 Carver St",
    "sg:city":"Brandon",
    "sg:classifiers":[
        {
            "category":"Manufacturing",
            "subcategory":"Glass & Minerals",
            "type":"Manufacturing & Wholesale Goods"
        }
    ],
    "sg:phone":"+1 802 247 8473",
    "sg:postcode":"05733",
    "sg:province":"VT",
    "sg:tags":[
        "lamp",
        "parts"
    ],
    "wof:name":"Shades Plus",
    "wof:placetype":"venue"
},
  "geometry": {"coordinates":[-73.08538299999999,43.796735],"type":"Point"}
}