{
  "type": "Feature",
  "properties": {
    "addr:full":"39 Main St Montpelier VT 05602",
    "addr:housenumber":"39",
    "addr:postcode":"05602",
    "addr:street":"Main St",
    "iso:country":"US",
    "sg:address":"39 Main St",
    "sg:city":"Montpelier",
    "sg:classifiers":[
        {
            "category":"Government",
            "subcategory":"Office",
            "type":"Public Place"
        }
    ],
    "sg:phone":"+1 802 223 9604",
    "sg:postcode":"05602",
    "sg:province":"VT",
    "sg:tags":[
        "village"
    ],
    "wof:name":"Montpelier Downtown Comm Assoc",
    "wof:placetype":"venue"
},
  "geometry": {"coordinates":[-72.575833,44.259432],"type":"Point"}
}