{
  "type": "Feature",
  "properties": {
    "iso:country":"US",
    "sg:address":"59 Waterfront Plz",
    "sg:city":"Newport",
    "sg:classifiers":[
        {
            "category":"Government",
            "subcategory":"Office",
            "type":"Public Place"
        }
    ],
    "sg:phone":"+1 802 334 8325",
    "sg:postcode":"05855",
    "sg:province":"VT",
    "sg:tags":[
        "federal"
    ],
    "wof:name":"Natural Resources Conservation",
    "wof:placetype":"venue"
},
  "geometry": {"coordinates":[-72.205803,44.938871],"type":"Point"}
}