{
  "type": "Feature",
  "properties": {
    "iso:country":"US",
    "sg:address":"1945 Main St",
    "sg:city":"Colchester",
    "sg:classifiers":[
        {
            "category":"Wholesale",
            "subcategory":"Toys & Hobbies",
            "type":"Manufacturing & Wholesale Goods"
        }
    ],
    "sg:phone":"+1 802 288 1587",
    "sg:postcode":"05446",
    "sg:province":"VT",
    "sg:tags":[
        "wholesaler",
        "tires-wholesale",
        "manufacturer"
    ],
    "sg:website":"http://www.nokiantyresinc.com",
    "wof:name":"University Wholesalers",
    "wof:placetype":"venue"
},
  "geometry": {"coordinates":[-73.134246,44.534828],"type":"Point"}
}