{
  "type": "Feature",
  "properties": {
    "addr:full":"227 Sugar House Ln Manchester Ctr VT 05255",
    "addr:housenumber":"227",
    "addr:postcode":"05255",
    "addr:street":"Sugar House Ln",
    "iso:country":"US",
    "sg:address":"227 Sugar House Ln",
    "sg:city":"Manchester Ctr",
    "sg:classifiers":[
        {
            "category":"Travel",
            "subcategory":"Hotels & Motels",
            "type":"Entertainment"
        }
    ],
    "sg:phone":"+1 802 362 1602",
    "sg:postcode":"05255",
    "sg:province":"VT",
    "sg:tags":[
        "breakfast",
        "accommodation",
        "bed"
    ],
    "wof:name":"River Meadow Farm",
    "wof:placetype":"venue"
},
  "geometry": {"coordinates":[-73.072723,43.132175],"type":"Point"}
}