{
  "type": "Feature",
  "properties": {
    "iso:country":"US",
    "sg:address":"15 Green Hill Ln",
    "sg:city":"Rutland",
    "sg:classifiers":[
        {
            "category":"Utilities",
            "subcategory":"Natural Gas",
            "type":"Services"
        }
    ],
    "sg:phone":"+1 802 775 7441",
    "sg:postcode":"05701",
    "sg:province":"VT",
    "wof:name":"Ameri Gas Inc",
    "wof:placetype":"venue"
},
  "geometry": {"coordinates":[-72.99355199999999,43.60525],"type":"Point"}
}