{
  "type": "Feature",
  "properties": {
    "iso:country":"US",
    "sg:address":"238 Main St",
    "sg:city":"Bennington",
    "sg:classifiers":[
        {
            "category":"Organizations",
            "subcategory":"Religious Organization",
            "type":"Services"
        }
    ],
    "sg:phone":"+1 802 442 3141",
    "sg:postcode":"05201",
    "sg:province":"VT",
    "wof:name":"Sacred Hrt St Francis Rmn Chrc",
    "wof:placetype":"venue"
},
  "geometry": {"coordinates":[-73.20218,42.880617],"type":"Point"}
}