{
  "type": "Feature",
  "properties": {
    "iso:country":"US",
    "sg:address":"2053 W Barnet Rd",
    "sg:city":"Barnet",
    "sg:classifiers":[
        {
            "category":"Professional",
            "subcategory":"Lawyer & Legal Services",
            "type":"Services"
        }
    ],
    "sg:phone":"+1 802 633 2625",
    "sg:postcode":"05821",
    "sg:province":"VT",
    "sg:tags":[
        "attorney"
    ],
    "wof:name":"Gary C Roy Sr",
    "wof:placetype":"venue"
},
  "geometry": {"coordinates":[-72.09213099999999,44.3094],"type":"Point"}
}