{
  "type": "Feature",
  "properties": {
    "addr:full":"74 Cotton Mill Hill Brattleboro VT 05301",
    "addr:housenumber":"74",
    "addr:postcode":"05301",
    "addr:street":"Cotton Mill",
    "iso:country":"US",
    "sg:address":"74 Cotton Mill Hill",
    "sg:city":"Brattleboro",
    "sg:classifiers":[
        {
            "category":"Communications",
            "subcategory":"Film & Video Production",
            "type":"Services"
        }
    ],
    "sg:phone":"+1 802 254 7390",
    "sg:postcode":"05301",
    "sg:province":"VT",
    "sg:tags":[
        "motion",
        "picture"
    ],
    "wof:name":"Center For Digital Art",
    "wof:placetype":"venue"
},
  "geometry": {"coordinates":[-72.554051,42.834645],"type":"Point"}
}