{
  "type": "Feature",
  "properties": {
    "addr:full":"202 Main St Burlington VT 05401",
    "addr:housenumber":"202",
    "addr:postcode":"05401",
    "addr:street":"Main St",
    "iso:country":"US",
    "sg:address":"202 Main St",
    "sg:city":"Burlington",
    "sg:classifiers":[
        {
            "category":"Shopping",
            "subcategory":"Musical Instruments",
            "type":"Retail Goods"
        }
    ],
    "sg:phone":"+1 802 863 4613",
    "sg:postcode":"05401",
    "sg:province":"VT",
    "wof:name":"Burlington Guitar & Amp",
    "wof:placetype":"venue"
},
  "geometry": {"coordinates":[-73.211851,44.47604],"type":"Point"}
}