{
  "type": "Feature",
  "properties": {
    "addr:full":"22 Commerce St Hinesburg VT 05461",
    "addr:housenumber":"22",
    "addr:postcode":"05461",
    "addr:street":"Commerce St",
    "iso:country":"US",
    "sg:address":"22 Commerce St",
    "sg:city":"Hinesburg",
    "sg:classifiers":[
        {
            "category":"Restaurant",
            "type":"Food & Drink"
        }
    ],
    "sg:phone":"+1 802 482 6888",
    "sg:postcode":"05461",
    "sg:province":"VT",
    "wof:name":"Dragon House Restaurant",
    "wof:placetype":"venue"
},
  "geometry": {"coordinates":[-73.10806700000001,44.334783],"type":"Point"}
}