{
  "type": "Feature",
  "properties": {
    "iso:country":"US",
    "sg:address":"1400 Bowen Rd",
    "sg:city":"East Corinth",
    "sg:classifiers":[
        {
            "category":"Shopping",
            "type":"Retail Goods"
        }
    ],
    "sg:phone":"+1 802 439 5102",
    "sg:postcode":"05040",
    "sg:province":"VT",
    "sg:tags":[
        "merchandise"
    ],
    "wof:name":"Hicks Sales & Service",
    "wof:placetype":"venue"
},
  "geometry": {"coordinates":[-72.189699,44.092498],"type":"Point"}
}