{
  "type": "Feature",
  "properties": {
    "addr:full":"1 Scale Ave Ste 101 Rutland VT 05701",
    "addr:housenumber":"1",
    "addr:postcode":"05701",
    "addr:street":"Scale Ave Ste 101",
    "iso:country":"US",
    "sg:address":"1 Scale Ave Ste 101",
    "sg:city":"Rutland",
    "sg:classifiers":[
        {
            "category":"Place Of Worship",
            "subcategory":"Church",
            "type":"Public Place"
        },
        {
            "category":"Place Of Worship",
            "type":"Public Place"
        },
        {
            "category":"Organizations",
            "subcategory":"Religious Organization",
            "type":"Services"
        }
    ],
    "sg:phone":"+1 802 773 3613",
    "sg:postcode":"05701",
    "sg:province":"VT",
    "sg:tags":[
        "churches-interdenominational",
        "churches-various",
        "denomination"
    ],
    "wof:name":"Alliance Community Fellowship",
    "wof:placetype":"venue"
},
  "geometry": {"coordinates":[-72.973511,43.600899],"type":"Point"}
}