{
  "type": "Feature",
  "properties": {
    "iso:country":"US",
    "sg:address":"58 Winding Brook Dr",
    "sg:city":"South Burlington",
    "sg:classifiers":[
        {
            "category":"Professional",
            "type":"Services"
        }
    ],
    "sg:phone":"+1 802 658 1066",
    "sg:postcode":"05403",
    "sg:province":"VT",
    "wof:name":"Mad As A Hatter Studio",
    "wof:placetype":"venue"
},
  "geometry": {"coordinates":[-73.15996800000001,44.45771],"type":"Point"}
}