{
  "type": "Feature",
  "properties": {
    "iso:country":"US",
    "sg:address":"133 Lower Main St E",
    "sg:city":"Johnson",
    "sg:classifiers":[
        {
            "category":"Retail",
            "subcategory":"Auto Repair",
            "type":"Services"
        }
    ],
    "sg:phone":"+1 802 635 9700",
    "sg:postcode":"05656",
    "sg:province":"VT",
    "sg:tags":[
        "repairing",
        "automobile"
    ],
    "wof:name":"Blake's Towing & Auto Repair",
    "wof:placetype":"venue"
},
  "geometry": {"coordinates":[-72.67688800000001,44.634338],"type":"Point"}
}