{
  "type": "Feature",
  "properties": {
    "addr:full":"175 S Main St Rutland VT 05701",
    "addr:housenumber":"175",
    "addr:postcode":"05701",
    "addr:street":"S Main St",
    "iso:country":"US",
    "sg:address":"175 S Main St",
    "sg:city":"Rutland",
    "sg:classifiers":[
        {
            "category":"Shopping",
            "subcategory":"Jewelry",
            "type":"Retail Goods"
        }
    ],
    "sg:phone":"+1 802 786 0665",
    "sg:postcode":"05701",
    "sg:province":"VT",
    "sg:tags":[
        "jeweler"
    ],
    "wof:name":"Kay Jewelers",
    "wof:placetype":"venue"
},
  "geometry": {"coordinates":[-72.97192200000001,43.606181],"type":"Point"}
}