{
  "type": "Feature",
  "properties": {
    "iso:country":"US",
    "sg:address":"100 Main St",
    "sg:city":"Burlington",
    "sg:classifiers":[
        {
            "category":"Food & Beverages",
            "subcategory":"Specialty",
            "type":"Retail Goods"
        }
    ],
    "sg:phone":"+1 802 865 4372",
    "sg:postcode":"05401",
    "sg:province":"VT",
    "wof:name":"Herbs Purple Shutter",
    "wof:placetype":"venue"
},
  "geometry": {"coordinates":[-73.21417,44.475953],"type":"Point"}
}