{
  "type": "Feature",
  "properties": {
    "iso:country":"US",
    "sg:address":"212 Browns Trace Rd",
    "sg:city":"Jericho",
    "sg:classifiers":[
        {
            "category":"Building & Trades",
            "subcategory":"Construction",
            "type":"Services"
        }
    ],
    "sg:phone":"+1 802 899 3534",
    "sg:postcode":"05465",
    "sg:province":"VT",
    "sg:tags":[
        "altering",
        "remodeling",
        "contractor"
    ],
    "sg:website":"http://www.landsrad.com",
    "wof:name":"Landsrad Co",
    "wof:placetype":"venue"
},
  "geometry": {"coordinates":[-72.96431,44.485737],"type":"Point"}
}