{
  "type": "Feature",
  "properties": {
    "addr:full":"178 Dukes Rd Johnson VT 05656",
    "addr:housenumber":"178",
    "addr:postcode":"05656",
    "addr:street":"Dukes Rd",
    "iso:country":"US",
    "sg:address":"178 Dukes Rd",
    "sg:city":"Johnson",
    "sg:classifiers":[
        {
            "category":"Building & Trades",
            "subcategory":"Plumbing",
            "type":"Services"
        }
    ],
    "sg:phone":"+1 802 635 2592",
    "sg:postcode":"05656",
    "sg:province":"VT",
    "sg:tags":[
        "contractor"
    ],
    "wof:name":"Bill K Gonyea Inc",
    "wof:placetype":"venue"
},
  "geometry": {"coordinates":[-72.628345,44.663919],"type":"Point"}
}