{
  "type": "Feature",
  "properties": {
    "iso:country":"US",
    "sg:address":"1170 US Hwy 2",
    "sg:city":"Montpelier",
    "sg:classifiers":[
        {
            "category":"Government",
            "subcategory":"Office",
            "type":"Public Place"
        }
    ],
    "sg:phone":"+1 802 828 2697",
    "sg:postcode":"05602",
    "sg:province":"VT",
    "wof:name":"Vermont State Garage",
    "wof:placetype":"venue"
},
  "geometry": {"coordinates":[-72.539635,44.24136],"type":"Point"}
}