{
  "type": "Feature",
  "properties": {
    "addr:full":"1069 Mountain Rd Stowe VT 05672",
    "addr:housenumber":"1069",
    "addr:postcode":"05672",
    "addr:street":"Mountain Rd",
    "iso:country":"US",
    "sg:address":"1069 Mountain Rd",
    "sg:city":"Stowe",
    "sg:classifiers":[
        {
            "category":"Professional",
            "subcategory":"Lawyer & Legal Services",
            "type":"Services"
        }
    ],
    "sg:phone":"+1 802 253 8330",
    "sg:postcode":"05672",
    "sg:province":"VT",
    "sg:tags":[
        "attorney"
    ],
    "wof:name":"Ronald I Merelman",
    "wof:placetype":"venue"
},
  "geometry": {"coordinates":[-72.69983999999999,44.474229],"type":"Point"}
}