{
  "type": "Feature",
  "properties": {
    "iso:country":"US",
    "sg:address":"158 S Main St",
    "sg:city":"Rutland",
    "sg:classifiers":[
        {
            "category":"Home & Garden",
            "subcategory":"Household Appliances",
            "type":"Retail Goods"
        }
    ],
    "sg:phone":"+1 802 775 1103",
    "sg:postcode":"05701",
    "sg:province":"VT",
    "sg:website":"www.showcaseappliance.com",
    "wof:name":"Showcase Appliance & TV",
    "wof:placetype":"venue"
},
  "geometry": {"coordinates":[-72.971963,43.606476],"type":"Point"}
}