{
  "type": "Feature",
  "properties": {
    "iso:country":"US",
    "sg:address":"134 Ascutney St",
    "sg:city":"Windsor",
    "sg:classifiers":[
        {
            "category":"Professional",
            "type":"Services"
        }
    ],
    "sg:phone":"+1 802 674 6279",
    "sg:postcode":"05089",
    "sg:province":"VT",
    "sg:tags":[
        "establishment"
    ],
    "wof:name":"Regione Call Phyllis",
    "wof:placetype":"venue"
},
  "geometry": {"coordinates":[-72.404099,43.473136],"type":"Point"}
}