{
  "type": "Feature",
  "properties": {
    "addr:city":"Shelburne",
    "addr:full":"1611 Harbor Road Shelburne, Vt 05482",
    "addr:house_number":"1611",
    "addr:housenumber":"1611",
    "addr:phone":"+1 802-985-0326",
    "addr:postcode":"05482",
    "addr:road":"Harbor Road",
    "addr:state":"VT",
    "addr:street":"Harbor Rd",
    "iso:country":"US",
    "sg:address":"1611 Harbor Rd",
    "sg:city":"Shelburne",
    "sg:classifiers":[
        {
            "category":"Education",
            "subcategory":"Special Training",
            "type":"Public Place"
        }
    ],
    "sg:phone":"+1 802 985 8686",
    "sg:postcode":"05482",
    "sg:province":"VT",
    "sg:tags":[
        "cheese",
        "social",
        "mfg"
    ],
    "sg:website":"www.shelburnefarms.org",
    "wof:airports":[
        102532853
    ],
    "wof:name":"Shelburne Farms",
    "wof:placetype":"venue"
},
  "geometry": {"coordinates":[-73.24751000000001,44.40754],"type":"Point"}
}