{
  "type": "Feature",
  "properties": {
    "iso:country":"US",
    "sg:address":"1611 Harbor Rd",
    "sg:city":"Shelburne",
    "sg:classifiers":[
        {
            "category":"Education",
            "subcategory":"Special Training",
            "type":"Public Place"
        }
    ],
    "sg:phone":"+1 802 985 8686",
    "sg:postcode":"05482",
    "sg:province":"VT",
    "sg:tags":[
        "cheese",
        "social",
        "mfg"
    ],
    "sg:website":"www.shelburnefarms.org",
    "wof:name":"Shelburne Farms",
    "wof:placetype":"venue"
},
  "geometry": {"coordinates":[-73.251688,44.414559],"type":"Point"}
}