{
  "type": "Feature",
  "properties": {
    "addr:full":"103 S Main St Waterbury VT 05641",
    "addr:housenumber":"103",
    "addr:postcode":"05641",
    "addr:street":"S Main St",
    "iso:country":"US",
    "sg:address":"103 S Main St",
    "sg:city":"Waterbury",
    "sg:classifiers":[
        {
            "category":"Education",
            "subcategory":"Library",
            "type":"Public Place"
        },
        {
            "category":"Health Services",
            "subcategory":"Hospital",
            "type":"Services"
        }
    ],
    "sg:phone":"+1 802 241 3246",
    "sg:postcode":"05641",
    "sg:province":"VT",
    "sg:tags":[
        "psychiatric",
        "special",
        "interest"
    ],
    "wof:name":"Vermont State Hospital Library",
    "wof:placetype":"venue"
},
  "geometry": {"coordinates":[-72.499263,44.191177],"type":"Point"}
}