{
  "type": "Feature",
  "properties": {
    "iso:country":"US",
    "sg:address":"257 Pine St",
    "sg:city":"Burlington",
    "sg:classifiers":[
        {
            "category":"Recreation",
            "type":"Entertainment"
        }
    ],
    "sg:phone":"+1 802 951 8900",
    "sg:postcode":"05401",
    "sg:province":"VT",
    "wof:name":"Aikido Of Champlain Valley",
    "wof:placetype":"venue"
},
  "geometry": {"coordinates":[-73.2153,44.470891],"type":"Point"}
}