{
  "type": "Feature",
  "properties": {
    "addr:full":"57 Pinnacle Dr South Burlington VT 05403",
    "addr:housenumber":"57",
    "addr:postcode":"05403",
    "addr:street":"Pinnacle Dr",
    "iso:country":"US",
    "sg:address":"57 Pinnacle Dr",
    "sg:city":"South Burlington",
    "sg:classifiers":[
        {
            "category":"Retail",
            "subcategory":"Animal Services",
            "type":"Services"
        }
    ],
    "sg:phone":"+1 802 860 3348",
    "sg:postcode":"05403",
    "sg:province":"VT",
    "wof:name":"Autumn Hill Cavaliers",
    "wof:placetype":"venue"
},
  "geometry": {"coordinates":[-73.19047500000001,44.431419],"type":"Point"}
}