{
  "type": "Feature",
  "properties": {
    "iso:country":"US",
    "sg:address":"37 Industrial Park Dr",
    "sg:city":"Morrisville",
    "sg:classifiers":[
        {
            "category":"Manufacturing",
            "subcategory":"Food",
            "type":"Manufacturing & Wholesale Goods"
        }
    ],
    "sg:phone":"+1 802 888 3491",
    "sg:postcode":"05661",
    "sg:province":"VT",
    "sg:tags":[
        "preparation",
        "sugar",
        "maple",
        "refining",
        "mfg"
    ],
    "wof:name":"Butternut Mountain Farm",
    "wof:placetype":"venue"
},
  "geometry": {"coordinates":[-72.591756,44.571749],"type":"Point"}
}