{
  "type": "Feature",
  "properties": {
    "iso:country":"US",
    "sg:address":"212 Prouty Dr",
    "sg:city":"Newport",
    "sg:classifiers":[
        {
            "category":"Health Services",
            "subcategory":"Doctor",
            "type":"Services"
        }
    ],
    "sg:phone":"+1 802 334 8002",
    "sg:postcode":"05855",
    "sg:province":"VT",
    "sg:tags":[
        "medical"
    ],
    "wof:name":"Saparoff Gerald R Inc MD",
    "wof:placetype":"venue"
},
  "geometry": {"coordinates":[-72.197973,44.954301],"type":"Point"}
}