{
  "type": "Feature",
  "properties": {
    "iso:country":"US",
    "sg:address":"54 Brook St",
    "sg:city":"Brattleboro",
    "sg:classifiers":[
        {
            "category":"Place Of Worship",
            "subcategory":"Church",
            "type":"Public Place"
        },
        {
            "category":"Place Of Worship",
            "type":"Public Place"
        }
    ],
    "sg:phone":"+1 802 254 7073",
    "sg:postcode":"05301",
    "sg:province":"VT",
    "sg:tags":[
        "churches-greek",
        "churches-eastern",
        "orthodox"
    ],
    "wof:name":"Saint Nectarios Greek Orthodox",
    "wof:placetype":"venue"
},
  "geometry": {"coordinates":[-72.563648,42.847265],"type":"Point"}
}