{
  "type": "Feature",
  "properties": {
    "addr:full":"47 N Orwell Rd Orwell VT 05760",
    "addr:housenumber":"47",
    "addr:postcode":"05760",
    "addr:street":"N Orwell Rd",
    "iso:country":"US",
    "sg:address":"47 N Orwell Rd",
    "sg:city":"Orwell",
    "sg:classifiers":[
        {
            "category":"Building & Trades",
            "subcategory":"Construction",
            "type":"Services"
        }
    ],
    "sg:phone":"+1 802 948 2153",
    "sg:postcode":"05760",
    "sg:province":"VT",
    "sg:tags":[
        "contractor"
    ],
    "wof:name":"Four By Four Construction",
    "wof:placetype":"venue"
},
  "geometry": {"coordinates":[-73.296271,43.80573],"type":"Point"}
}