{
  "type": "Feature",
  "properties": {
    "iso:country":"US",
    "sg:address":"42 Laura Ln",
    "sg:city":"Colchester",
    "sg:classifiers":[
        {
            "category":"Real Estate",
            "subcategory":"Real Estate Services",
            "type":"Services"
        },
        {
            "category":"Building & Trades",
            "subcategory":"Construction",
            "type":"Services"
        }
    ],
    "sg:phone":"+1 802 922 8992",
    "sg:postcode":"05446",
    "sg:province":"VT",
    "sg:tags":[
        "roofing",
        "industrial",
        "consultant",
        "contractor",
        "contractors-commercial",
        "maintenance"
    ],
    "wof:name":"1st Choice Roofing",
    "wof:placetype":"venue"
},
  "geometry": {"coordinates":[-73.201564,44.541178],"type":"Point"}
}