{
  "type": "Feature",
  "properties": {
    "iso:country":"US",
    "sg:address":"98 Southfield Dr",
    "sg:city":"Williston",
    "sg:classifiers":[
        {
            "category":"Professional",
            "subcategory":"Business Services",
            "type":"Services"
        }
    ],
    "sg:phone":"+1 802 878 0830",
    "sg:postcode":"05495",
    "sg:province":"VT",
    "wof:name":"Erdman Technology Solutions",
    "wof:placetype":"venue"
},
  "geometry": {"coordinates":[-73.074676,44.445941],"type":"Point"}
}