{
  "type": "Feature",
  "properties": {
    "iso:country":"US",
    "sg:address":"245 Marble St",
    "sg:city":"West Rutland",
    "sg:classifiers":[
        {
            "category":"Home & Garden",
            "subcategory":"Carpets & Floor Coverings",
            "type":"Retail Goods"
        }
    ],
    "sg:phone":"+1 802 438 2077",
    "sg:postcode":"05777",
    "sg:province":"VT",
    "sg:tags":[
        "dealer",
        "rug"
    ],
    "wof:name":"Carpet King Of Vermont",
    "wof:placetype":"venue"
},
  "geometry": {"coordinates":[-73.049508,43.597539],"type":"Point"}
}