{
  "type": "Feature",
  "properties": {
    "addr:full":"109 State St Montpelier VT 05602",
    "addr:housenumber":"109",
    "addr:postcode":"05602",
    "addr:street":"State St",
    "iso:country":"US",
    "sg:address":"109 State St",
    "sg:city":"Montpelier",
    "sg:classifiers":[
        {
            "category":"Government",
            "subcategory":"Court House",
            "type":"Public Place"
        }
    ],
    "sg:phone":"+1 802 828 3186",
    "sg:postcode":"05602",
    "sg:province":"VT",
    "sg:tags":[
        "environmental",
        "unit"
    ],
    "wof:name":"Environmental Unit",
    "wof:placetype":"venue"
},
  "geometry": {"coordinates":[-72.581816,44.261553],"type":"Point"}
}