{
  "type": "Feature",
  "properties": {
    "addr:full":"78 Rose St Burlington VT 05401",
    "addr:housenumber":"78",
    "addr:postcode":"05401",
    "addr:street":"Rose St",
    "iso:country":"US",
    "sg:address":"78 Rose St",
    "sg:city":"Burlington",
    "sg:classifiers":[
        {
            "category":"Professional",
            "type":"Services"
        }
    ],
    "sg:phone":"+1 802 865 2504",
    "sg:postcode":"05401",
    "sg:province":"VT",
    "sg:tags":[
        "establishment"
    ],
    "wof:name":"RSHLP",
    "wof:placetype":"venue"
},
  "geometry": {"coordinates":[-73.216438,44.485858],"type":"Point"}
}