{
  "type": "Feature",
  "properties": {
    "iso:country":"US",
    "sg:address":"100 I- Corporate Center",
    "sg:city":"Williston",
    "sg:classifiers":[
        {
            "category":"Shopping",
            "type":"Retail Goods"
        }
    ],
    "sg:phone":"+1 802 872 1400",
    "sg:postcode":"05495",
    "sg:province":"VT",
    "sg:tags":[
        "ice"
    ],
    "wof:name":"Us Govt Dhs Ice",
    "wof:placetype":"venue"
},
  "geometry": {"coordinates":[-73.11130799999999,44.448563],"type":"Point"}
}