{
  "type": "Feature",
  "properties": {
    "iso:country":"US",
    "sg:address":"61 E Washington St",
    "sg:city":"Rutland",
    "sg:classifiers":[
        {
            "category":"Shopping",
            "subcategory":"Pharmacy",
            "type":"Retail Goods"
        }
    ],
    "sg:phone":"+1 802 773 3253",
    "sg:postcode":"05701",
    "sg:province":"VT",
    "wof:name":"Rx Transcription",
    "wof:placetype":"venue"
},
  "geometry": {"coordinates":[-72.962822,43.607566],"type":"Point"}
}