{
  "type": "Feature",
  "properties": {
    "iso:country":"US",
    "sg:address":"15 Central St",
    "sg:city":"Woodstock",
    "sg:classifiers":[
        {
            "category":"Real Estate",
            "subcategory":"Architect",
            "type":"Services"
        }
    ],
    "sg:phone":"+1 802 457 1602",
    "sg:postcode":"05091",
    "sg:province":"VT",
    "sg:tags":[
        "architectural"
    ],
    "wof:name":"Ertel Associates Architects",
    "wof:placetype":"venue"
},
  "geometry": {"coordinates":[-72.51761999999999,43.625432],"type":"Point"}
}