{
  "type": "Feature",
  "properties": {
    "iso:country":"US",
    "sg:address":"46 Logwood St",
    "sg:city":"South Burlington",
    "sg:classifiers":[
        {
            "category":"Building & Trades",
            "subcategory":"Construction",
            "type":"Services"
        }
    ],
    "sg:phone":"+1 802 863 5274",
    "sg:postcode":"05403",
    "sg:province":"VT",
    "sg:tags":[
        "roofing",
        "contractor"
    ],
    "wof:name":"Billado Roofing",
    "wof:placetype":"venue"
},
  "geometry": {"coordinates":[-73.157634,44.466916],"type":"Point"}
}