{
  "type": "Feature",
  "properties": {
    "iso:country":"US",
    "sg:address":"156 Green Mountain Tr Park",
    "sg:city":"Pownal",
    "sg:classifiers":[
        {
            "category":"Home & Garden",
            "subcategory":"Mobile Homes",
            "type":"Retail Goods"
        }
    ],
    "sg:phone":"+1 802 823 5165",
    "sg:postcode":"05261",
    "sg:province":"VT",
    "wof:name":"Green Mountain Mobile Home Par",
    "wof:placetype":"venue"
},
  "geometry": {"coordinates":[-73.23419199999999,42.761768],"type":"Point"}
}