{
  "type": "Feature",
  "properties": {
    "iso:country":"US",
    "sg:address":"113 Church St",
    "sg:city":"Burlington",
    "sg:classifiers":[
        {
            "category":"Personal",
            "subcategory":"Beauty Salon",
            "type":"Services"
        }
    ],
    "sg:phone":"+1 802 657 3233",
    "sg:postcode":"05401",
    "sg:province":"VT",
    "wof:name":"Dish Beauty Lounge & Spa",
    "wof:placetype":"venue"
},
  "geometry": {"coordinates":[-73.21256200000001,44.478111],"type":"Point"}
}