{
  "type": "Feature",
  "properties": {
    "addr:full":"340 Ave D Williston VT 05495",
    "addr:housenumber":"340",
    "addr:postcode":"05495",
    "addr:street":"Ave D",
    "iso:country":"US",
    "sg:address":"340 Ave D",
    "sg:city":"Williston",
    "sg:classifiers":[
        {
            "category":"Wholesale",
            "subcategory":"Medical Equipment & Supplies",
            "type":"Manufacturing & Wholesale Goods"
        }
    ],
    "sg:phone":"+1 802 865 7899",
    "sg:postcode":"05495",
    "sg:province":"VT",
    "sg:tags":[
        "dental"
    ],
    "wof:name":"Patterson Companies  Inc",
    "wof:placetype":"venue"
},
  "geometry": {"coordinates":[-73.12379300000001,44.465745],"type":"Point"}
}