{
  "type": "Feature",
  "properties": {
    "iso:country":"US",
    "sg:address":"14 Gove St",
    "sg:city":"Bellows Falls",
    "sg:classifiers":[
        {
            "category":"Retail",
            "subcategory":"Repair Shop",
            "type":"Services"
        }
    ],
    "sg:phone":"+1 802 463 3702",
    "sg:postcode":"05101",
    "sg:province":"VT",
    "sg:tags":[
        "lock",
        "locksmith"
    ],
    "wof:name":"Gochey's Lockouts",
    "wof:placetype":"venue"
},
  "geometry": {"coordinates":[-72.452365,43.130923],"type":"Point"}
}