{
  "type": "Feature",
  "properties": {
    "iso:country":"US",
    "sg:address":"126 N Brownell Rd",
    "sg:city":"Williston",
    "sg:classifiers":[
        {
            "category":"Retail",
            "subcategory":"Auto Repair",
            "type":"Services"
        }
    ],
    "sg:phone":"+1 802 863 6900",
    "sg:postcode":"05495",
    "sg:province":"VT",
    "sg:tags":[
        "repairing",
        "automobile"
    ],
    "wof:name":"Mark's Auto Svc",
    "wof:placetype":"venue"
},
  "geometry": {"coordinates":[-73.11965600000001,44.46158],"type":"Point"}
}