{
  "type": "Feature",
  "properties": {
    "iso:country":"US",
    "sg:address":"24 Highland Ave",
    "sg:city":"Manchester Ctr",
    "sg:classifiers":[
        {
            "category":"Shopping",
            "type":"Retail Goods"
        }
    ],
    "sg:phone":"+1 802 362 3022",
    "sg:postcode":"05255",
    "sg:province":"VT",
    "sg:tags":[
        "art",
        "gallery",
        "dealer"
    ],
    "wof:name":"Tilting At Windmills",
    "wof:placetype":"venue"
},
  "geometry": {"coordinates":[-73.046702,43.173419],"type":"Point"}
}