{
  "type": "Feature",
  "properties": {
    "addr:full":"948 Hercules Dr Colchester VT 05446",
    "addr:housenumber":"948",
    "addr:postcode":"05446",
    "addr:street":"Hercules Dr",
    "iso:country":"US",
    "sg:address":"948 Hercules Dr",
    "sg:city":"Colchester",
    "sg:classifiers":[
        {
            "category":"Manufacturing",
            "subcategory":"Metals",
            "type":"Manufacturing & Wholesale Goods"
        },
        {
            "category":"Wholesale",
            "subcategory":"Hardware",
            "type":"Manufacturing & Wholesale Goods"
        }
    ],
    "sg:phone":"+1 802 654 7500",
    "sg:postcode":"05446",
    "sg:province":"VT",
    "sg:tags":[
        "plumbing",
        "fixture",
        "supply"
    ],
    "sg:website":"www.mysoninc.com",
    "wof:name":"Myson Inc",
    "wof:placetype":"venue"
},
  "geometry": {"coordinates":[-73.17233299999999,44.499994],"type":"Point"}
}