{
  "type": "Feature",
  "properties": {
    "addr:full":"54 Buck Dr Westminster VT 05158",
    "addr:housenumber":"54",
    "addr:postcode":"05158",
    "addr:street":"Buck Dr",
    "iso:country":"US",
    "sg:address":"54 Buck Dr",
    "sg:city":"Westminster",
    "sg:classifiers":[
        {
            "category":"Social Services",
            "subcategory":"Child Care",
            "type":"Services"
        }
    ],
    "sg:phone":"+1 802 722 9813",
    "sg:postcode":"05158",
    "sg:province":"VT",
    "sg:tags":[
        "day"
    ],
    "wof:name":"Headstart Early Education Svcs",
    "wof:placetype":"venue"
},
  "geometry": {"coordinates":[-72.447113,43.093745],"type":"Point"}
}