{
  "type": "Feature",
  "properties": {
    "iso:country":"US",
    "sg:address":"2293 State Rte 74",
    "sg:city":"Shoreham",
    "sg:classifiers":[
        {
            "category":"Professional",
            "subcategory":"Employment Agencies",
            "type":"Services"
        }
    ],
    "sg:phone":"+1 802 897 2857",
    "sg:postcode":"05770",
    "sg:province":"VT",
    "wof:name":"Valerie Szymkowicz Consultant",
    "wof:placetype":"venue"
},
  "geometry": {"coordinates":[-73.335945,43.869265],"type":"Point"}
}