{
  "type": "Feature",
  "properties": {
    "iso:country":"US",
    "sg:address":"2517 Shelburne Rd",
    "sg:city":"Shelburne",
    "sg:classifiers":[
        {
            "category":"Restaurant",
            "type":"Food & Drink"
        }
    ],
    "sg:phone":"+1 802 985 8076",
    "sg:postcode":"05482",
    "sg:province":"VT",
    "sg:tags":[
        "drinking"
    ],
    "wof:name":"Reel Hospitality LLC",
    "wof:placetype":"venue"
},
  "geometry": {"coordinates":[-73.21249299999999,44.418865],"type":"Point"}
}