{
  "type": "Feature",
  "properties": {
    "addr:full":"2941 Dugway Rd Richmond VT 05477",
    "addr:housenumber":"2941",
    "addr:postcode":"05477",
    "addr:street":"Dugway Rd",
    "iso:country":"US",
    "sg:address":"2941 Dugway Rd",
    "sg:city":"Richmond",
    "sg:classifiers":[
        {
            "category":"Retail",
            "subcategory":"Repair Shop",
            "type":"Services"
        }
    ],
    "sg:phone":"+1 802 434 3047",
    "sg:postcode":"05477",
    "sg:province":"VT",
    "sg:tags":[
        "welding"
    ],
    "wof:name":"Shattuck Welding",
    "wof:placetype":"venue"
},
  "geometry": {"coordinates":[-72.990094,44.365393],"type":"Point"}
}