{
  "type": "Feature",
  "properties": {
    "iso:country":"US",
    "sg:address":"1 Greenwich St",
    "sg:city":"Swanton",
    "sg:classifiers":[
        {
            "category":"Personal",
            "subcategory":"Beauty Salon",
            "type":"Services"
        }
    ],
    "sg:phone":"+1 802 868 4981",
    "sg:postcode":"05488",
    "sg:province":"VT",
    "sg:tags":[
        "shop"
    ],
    "wof:name":"Roses Beauty Salon",
    "wof:placetype":"venue"
},
  "geometry": {"coordinates":[-73.12085999999999,44.920784],"type":"Point"}
}