{
  "type": "Feature",
  "properties": {
    "iso:country":"US",
    "sg:address":"349 Bonnet St",
    "sg:city":"Manchester Ctr",
    "sg:classifiers":[
        {
            "category":"Travel",
            "subcategory":"Hotels & Motels",
            "type":"Entertainment"
        }
    ],
    "sg:phone":"+1 802 362 1619",
    "sg:postcode":"05255",
    "sg:province":"VT",
    "sg:website":"www.barnsteadinn.com",
    "wof:name":"Barnstead Inn",
    "wof:placetype":"venue"
},
  "geometry": {"coordinates":[-73.057829,43.18127],"type":"Point"}
}