{
  "type": "Feature",
  "properties": {
    "iso:country":"US",
    "sg:address":"22 US Hwy 4",
    "sg:city":"Rutland",
    "sg:classifiers":[
        {
            "category":"Health Services",
            "subcategory":"Chiropractor",
            "type":"Services"
        }
    ],
    "sg:phone":"+1 802 773 4155",
    "sg:postcode":"05701",
    "sg:province":"VT",
    "sg:tags":[
        "medical"
    ],
    "wof:name":"Kirbach Chiropractic Clinic",
    "wof:placetype":"venue"
},
  "geometry": {"coordinates":[-72.935202,43.636458],"type":"Point"}
}