{
  "type": "Feature",
  "properties": {
    "iso:country":"US",
    "sg:address":"1041 US Hwy 302",
    "sg:city":"Barre",
    "sg:classifiers":[
        {
            "category":"Home & Garden",
            "subcategory":"Building Materials",
            "type":"Retail Goods"
        }
    ],
    "sg:phone":"+1 802 479 0515",
    "sg:postcode":"05641",
    "sg:province":"VT",
    "sg:tags":[
        "installs",
        "wholesale",
        "glass"
    ],
    "wof:name":"Portland/Harmon Autoglass",
    "wof:placetype":"venue"
},
  "geometry": {"coordinates":[-72.448367,44.16077],"type":"Point"}
}