{
  "type": "Feature",
  "properties": {
    "addr:full":"85 Harvest Ln Shelburne VT 05482",
    "addr:housenumber":"85",
    "addr:postcode":"05482",
    "addr:street":"Harvest Ln",
    "iso:country":"US",
    "sg:address":"85 Harvest Ln",
    "sg:city":"Shelburne",
    "sg:classifiers":[
        {
            "category":"Real Estate",
            "subcategory":"Architect",
            "type":"Services"
        }
    ],
    "sg:phone":"+1 802 985 9815",
    "sg:postcode":"05482",
    "sg:province":"VT",
    "sg:tags":[
        "architectural"
    ],
    "wof:name":"Stephen G Moore Jr",
    "wof:placetype":"venue"
},
  "geometry": {"coordinates":[-73.221177,44.387117],"type":"Point"}
}