{
  "type": "Feature",
  "properties": {
    "iso:country":"US",
    "sg:address":"15 Downes Ave",
    "sg:city":"Barre",
    "sg:classifiers":[
        {
            "category":"Organizations",
            "subcategory":"Labor Organization",
            "type":"Services"
        }
    ],
    "sg:phone":"+1 802 479 9518",
    "sg:postcode":"05641",
    "sg:province":"VT",
    "wof:name":"Central Vermont Municapl Emply",
    "wof:placetype":"venue"
},
  "geometry": {"coordinates":[-72.495751,44.182201],"type":"Point"}
}