{
  "type": "Feature",
  "properties": {
    "addr:full":"615 Old County Rd Cavendish VT 05142",
    "addr:housenumber":"615",
    "addr:postcode":"05142",
    "addr:street":"Old County Rd",
    "iso:country":"US",
    "sg:address":"615 Old County Rd",
    "sg:city":"Cavendish",
    "sg:classifiers":[
        {
            "category":"Professional",
            "type":"Services"
        }
    ],
    "sg:phone":"+1 802 226 8030",
    "sg:postcode":"05142",
    "sg:province":"VT",
    "wof:name":"Spiders Band",
    "wof:placetype":"venue"
},
  "geometry": {"coordinates":[-72.58199999999999,43.41973],"type":"Point"}
}