{
  "type": "Feature",
  "properties": {
    "iso:country":"US",
    "sg:address":"1273 Oak Hill Rd",
    "sg:city":"Williston",
    "sg:classifiers":[
        {
            "category":"Farming",
            "subcategory":"Farm",
            "type":"Manufacturing & Wholesale Goods"
        }
    ],
    "sg:phone":"+1 802 878 3742",
    "sg:postcode":"05495",
    "sg:province":"VT",
    "sg:tags":[
        "crop",
        "general"
    ],
    "wof:name":"Yandell Farm",
    "wof:placetype":"venue"
},
  "geometry": {"coordinates":[-73.080502,44.421355],"type":"Point"}
}