{
  "type": "Feature",
  "properties": {
    "addr:full":"502 Longmore Hill Rd Hyde Park VT 05655",
    "addr:housenumber":"502",
    "addr:postcode":"05655",
    "addr:street":"Longmore Hill Rd",
    "iso:country":"US",
    "sg:address":"502 Longmore Hill Rd",
    "sg:city":"Hyde Park",
    "sg:classifiers":[
        {
            "category":"Manufacturing",
            "subcategory":"Retail Goods",
            "type":"Manufacturing & Wholesale Goods"
        }
    ],
    "sg:phone":"+1 802 888 7973",
    "sg:postcode":"05655",
    "sg:province":"VT",
    "sg:tags":[
        "product",
        "mfg"
    ],
    "wof:name":"Robert W Wylie",
    "wof:placetype":"venue"
},
  "geometry": {"coordinates":[-72.591714,44.630358],"type":"Point"}
}