{
  "type": "Feature",
  "properties": {
    "iso:country":"US",
    "sg:address":"544 Sykes Mountain Ave",
    "sg:city":"White River Junction",
    "sg:classifiers":[
        {
            "category":"Social Services",
            "subcategory":"Child Care",
            "type":"Services"
        }
    ],
    "sg:phone":"+1 802 295 4839",
    "sg:postcode":"05001",
    "sg:province":"VT",
    "sg:tags":[
        "day"
    ],
    "wof:name":"Babble On Day Care Inc",
    "wof:placetype":"venue"
},
  "geometry": {"coordinates":[-72.324477,43.643698],"type":"Point"}
}