{
  "type": "Feature",
  "properties": {
    "iso:country":"US",
    "sg:address":"16 Railroad St",
    "sg:city":"Barre",
    "sg:classifiers":[
        {
            "category":"Manufacturing",
            "subcategory":"Glass & Minerals",
            "type":"Manufacturing & Wholesale Goods"
        }
    ],
    "sg:phone":"+1 802 476 6624",
    "sg:postcode":"05641",
    "sg:province":"VT",
    "sg:tags":[
        "granite",
        "product"
    ],
    "sg:website":"www.northbarregranite.com",
    "wof:name":"North Barre Granite Co",
    "wof:placetype":"venue"
},
  "geometry": {"coordinates":[-72.513668,44.203194],"type":"Point"}
}