{
  "type": "Feature",
  "properties": {
    "iso:country":"US",
    "sg:address":"879 Buttolph Rd",
    "sg:city":"Whiting",
    "sg:classifiers":[
        {
            "category":"Farming",
            "subcategory":"Dairy Farm",
            "type":"Manufacturing & Wholesale Goods"
        }
    ],
    "sg:phone":"+1 802 897 2610",
    "sg:postcode":"05778",
    "sg:province":"VT",
    "wof:name":"Dream On Farm",
    "wof:placetype":"venue"
},
  "geometry": {"coordinates":[-73.263673,43.897008],"type":"Point"}
}