{
  "type": "Feature",
  "properties": {
    "addr:full":"101 Old Colchester Rd Essex Junction VT 05452",
    "addr:housenumber":"101",
    "addr:postcode":"05452",
    "addr:street":"Old Colchester Rd",
    "iso:country":"US",
    "sg:address":"101 Old Colchester Rd",
    "sg:city":"Essex Junction",
    "sg:classifiers":[
        {
            "category":"Social Services",
            "subcategory":"Child Care",
            "type":"Services"
        }
    ],
    "sg:phone":"+1 802 872 1152",
    "sg:postcode":"05452",
    "sg:province":"VT",
    "sg:tags":[
        "day"
    ],
    "wof:name":"It Takes A Village",
    "wof:placetype":"venue"
},
  "geometry": {"coordinates":[-73.1155,44.507573],"type":"Point"}
}