{
  "type": "Feature",
  "properties": {
    "iso:country":"US",
    "sg:address":"2120 Maple Hill Rd",
    "sg:city":"Plainfield",
    "sg:classifiers":[
        {
            "category":"Autos & Motor Vehicles",
            "subcategory":"Auto Supplies",
            "type":"Retail Goods"
        }
    ],
    "sg:phone":"+1 802 454 7132",
    "sg:postcode":"05667",
    "sg:province":"VT",
    "sg:tags":[
        "automobile",
        "used",
        "parts"
    ],
    "wof:name":"Peugeot Parts",
    "wof:placetype":"venue"
},
  "geometry": {"coordinates":[-72.379097,44.266655],"type":"Point"}
}