{
  "type": "Feature",
  "properties": {
    "iso:country":"US",
    "sg:address":"74 Grand Ave",
    "sg:city":"Swanton",
    "sg:classifiers":[
        {
            "category":"Personal",
            "subcategory":"Beauty Salon",
            "type":"Services"
        }
    ],
    "sg:phone":"+1 802 868 4575",
    "sg:postcode":"05488",
    "sg:province":"VT",
    "sg:tags":[
        "shop"
    ],
    "wof:name":"Stambrys Bath & Beauty Pdts",
    "wof:placetype":"venue"
},
  "geometry": {"coordinates":[-73.119518,44.915481],"type":"Point"}
}