{
  "type": "Feature",
  "properties": {
    "addr:full":"1040 Osgood Hill Rd Westford VT 05494",
    "addr:housenumber":"1040",
    "addr:postcode":"05494",
    "addr:street":"Osgood Hill Rd",
    "iso:country":"US",
    "sg:address":"1040 Osgood Hill Rd",
    "sg:city":"Westford",
    "sg:classifiers":[
        {
            "category":"Building & Trades",
            "subcategory":"Construction",
            "type":"Services"
        }
    ],
    "sg:phone":"+1 802 878 3027",
    "sg:postcode":"05494",
    "sg:province":"VT",
    "sg:tags":[
        "excavation",
        "local",
        "t",
        "contractor"
    ],
    "wof:name":"Green Mtn Roofg Trckg & Excvtg",
    "wof:placetype":"venue"
},
  "geometry": {"coordinates":[-73.00088599999999,44.596933],"type":"Point"}
}