{
  "type": "Feature",
  "properties": {
    "addr:full":"249 Brockway Mills Rd Springfield VT 05156",
    "addr:housenumber":"249",
    "addr:postcode":"05156",
    "addr:street":"Brockway Mills Rd",
    "iso:country":"US",
    "sg:address":"249 Brockway Mills Rd",
    "sg:city":"Springfield",
    "sg:classifiers":[
        {
            "category":"Retail",
            "subcategory":"Repair Shop",
            "type":"Services"
        }
    ],
    "sg:phone":"+1 802 885 5474",
    "sg:postcode":"05156",
    "sg:province":"VT",
    "wof:name":"G H Gagnier",
    "wof:placetype":"venue"
},
  "geometry": {"coordinates":[-72.48643300000001,43.262885],"type":"Point"}
}