{
  "type": "Feature",
  "properties": {
    "iso:country":"US",
    "sg:address":"27 Park St",
    "sg:city":"Essex Junction",
    "sg:classifiers":[
        {
            "category":"Home & Garden",
            "subcategory":"Furniture",
            "type":"Retail Goods"
        }
    ],
    "sg:phone":"+1 802 878 5333",
    "sg:postcode":"05452",
    "sg:province":"VT",
    "sg:tags":[
        "equipment",
        "kitchen",
        "cabinet"
    ],
    "wof:name":"Wood Stock Kitchen & Bath",
    "wof:placetype":"venue"
},
  "geometry": {"coordinates":[-73.112522,44.488609],"type":"Point"}
}