{
  "type": "Feature",
  "properties": {
    "addr:full":"50 State St Montpelier VT 05602",
    "addr:housenumber":"50",
    "addr:postcode":"05602",
    "addr:street":"State St",
    "iso:country":"US",
    "sg:address":"50 State St",
    "sg:city":"Montpelier",
    "sg:classifiers":[
        {
            "category":"Building & Trades",
            "subcategory":"Plumbing",
            "type":"Services"
        }
    ],
    "sg:phone":"+1 802 223 7770",
    "sg:postcode":"05602",
    "sg:province":"VT",
    "sg:tags":[
        "product",
        "management",
        "energy",
        "system"
    ],
    "wof:name":"Biomass Energy Resource Ctr",
    "wof:placetype":"venue"
},
  "geometry": {"coordinates":[-72.57693999999999,44.260351],"type":"Point"}
}