{
  "type": "Feature",
  "properties": {
    "addr:full":"115 US Hwy 2 Alburg VT 05440",
    "addr:housenumber":"115",
    "addr:postcode":"05440",
    "addr:street":"Us Hwy 2",
    "iso:country":"US",
    "sg:address":"115 US Hwy 2",
    "sg:city":"Alburg",
    "sg:classifiers":[
        {
            "category":"Travel",
            "subcategory":"Campground",
            "type":"Entertainment"
        }
    ],
    "sg:phone":"+1 802 796 3636",
    "sg:postcode":"05440",
    "sg:province":"VT",
    "sg:tags":[
        "camp"
    ],
    "wof:name":"Downer 4h Camp Inc",
    "wof:placetype":"venue"
},
  "geometry": {"coordinates":[-73.300669,44.975377],"type":"Point"}
}