{
  "type": "Feature",
  "properties": {
    "addr:full":"394 Mountain Rd Stowe VT 05672",
    "addr:housenumber":"394",
    "addr:postcode":"05672",
    "addr:street":"Mountain Rd",
    "iso:country":"US",
    "sg:address":"394 Mountain Rd",
    "sg:city":"Stowe",
    "sg:classifiers":[
        {
            "category":"Restaurant",
            "type":"Food & Drink"
        }
    ],
    "sg:phone":"+1 802 253 4600",
    "sg:postcode":"05672",
    "sg:province":"VT",
    "sg:tags":[
        "delicatessen"
    ],
    "wof:name":"Brown Bag Deli",
    "wof:placetype":"venue"
},
  "geometry": {"coordinates":[-72.68750900000001,44.470171],"type":"Point"}
}