{
  "type": "Feature",
  "properties": {
    "addr:full":"1111 Putney Rd Brattleboro VT 05301",
    "addr:housenumber":"1111",
    "addr:postcode":"05301",
    "addr:street":"Putney Rd",
    "iso:country":"US",
    "sg:address":"1111 Putney Rd",
    "sg:city":"Brattleboro",
    "sg:classifiers":[
        {
            "category":"Restaurant",
            "type":"Food & Drink"
        }
    ],
    "sg:menulink":"http://www.allmenus.com/vt/brattleboro/219127-bickfords-family-restaurant/menu/",
    "sg:phone":"+1 802 258 4786",
    "sg:postcode":"05301",
    "sg:province":"VT",
    "sg:tags":[
        "american"
    ],
    "wof:name":"Bickford's Family Restaurant",
    "wof:placetype":"venue"
},
  "geometry": {"coordinates":[-72.55651,42.884391],"type":"Point"}
}