{
  "type": "Feature",
  "properties": {
    "iso:country":"US",
    "sg:address":"6 Gregory Dr",
    "sg:city":"South Burlington",
    "sg:classifiers":[
        {
            "category":"Retail",
            "subcategory":"Auto Repair",
            "type":"Services"
        }
    ],
    "sg:phone":"+1 802 658 2629",
    "sg:postcode":"05403",
    "sg:province":"VT",
    "sg:tags":[
        "machine",
        "automotive",
        "shop",
        "automobile"
    ],
    "wof:name":"Motion Machine Inc",
    "wof:placetype":"venue"
},
  "geometry": {"coordinates":[-73.139687,44.455443],"type":"Point"}
}