{
  "type": "Feature",
  "properties": {
    "addr:full":"2038 Mountain Rd Stowe VT 05672",
    "addr:housenumber":"2038",
    "addr:postcode":"05672",
    "addr:street":"Mountain Rd",
    "iso:country":"US",
    "sg:address":"2038 Mountain Rd",
    "sg:city":"Stowe",
    "sg:classifiers":[
        {
            "category":"Restaurant",
            "type":"Food & Drink"
        }
    ],
    "sg:phone":"+1 802 253 9500",
    "sg:postcode":"05672",
    "sg:province":"VT",
    "sg:tags":[
        "tea",
        "rooms"
    ],
    "wof:name":"Old Vienna Tea Room",
    "wof:placetype":"venue"
},
  "geometry": {"coordinates":[-72.71519499999999,44.474197],"type":"Point"}
}