{
  "type": "Feature",
  "properties": {
    "addr:full":"99 Washington St Barre VT 05641",
    "addr:housenumber":"99",
    "addr:postcode":"05641",
    "addr:street":"Washington St",
    "iso:country":"US",
    "sg:address":"99 Washington St",
    "sg:city":"Barre",
    "sg:classifiers":[
        {
            "category":"Insurance",
            "subcategory":"Insurance Agent",
            "type":"Services"
        }
    ],
    "sg:phone":"+1 802 479 3388",
    "sg:postcode":"05641",
    "sg:province":"VT",
    "sg:website":"www.ishaminsagency.com",
    "wof:name":"Isham Insurance",
    "wof:placetype":"venue"
},
  "geometry": {"coordinates":[-72.496539,44.19448],"type":"Point"}
}