{
  "type": "Feature",
  "properties": {
    "iso:country":"US",
    "sg:address":"4477 Mill Brook Rd",
    "sg:city":"Waitsfield",
    "sg:classifiers":[
        {
            "category":"Utilities",
            "subcategory":"Telephone",
            "type":"Services"
        }
    ],
    "sg:phone":"+1 802 496 9802",
    "sg:postcode":"05673",
    "sg:province":"VT",
    "sg:tags":[
        "telecommunication"
    ],
    "wof:name":"GLC Communications",
    "wof:placetype":"venue"
},
  "geometry": {"coordinates":[-72.91642400000001,44.20201],"type":"Point"}
}