{
  "type": "Feature",
  "properties": {
    "iso:country":"US",
    "sg:address":"218 Poor Farm Rd",
    "sg:city":"Alburgh",
    "sg:classifiers":[
        {
            "category":"Government",
            "subcategory":"Court House",
            "type":"Public Place"
        },
        {
            "category":"Travel",
            "subcategory":"Hotels & Motels",
            "type":"Entertainment"
        },
        {
            "category":"Recreation",
            "type":"Entertainment"
        }
    ],
    "sg:phone":"+1 802 796 3616",
    "sg:postcode":"05440",
    "sg:province":"VT",
    "sg:tags":[
        "cottage",
        "chalet",
        "cabin",
        "camps-recreational"
    ],
    "wof:name":"Henry's Sportsmans Cottages Inc",
    "wof:placetype":"venue"
},
  "geometry": {"coordinates":[-73.288152,44.86081],"type":"Point"}
}