{
  "type": "Feature",
  "properties": {
    "addr:full":"5 Scarff Ave Burlington VT 05401",
    "addr:housenumber":"5",
    "addr:postcode":"05401",
    "addr:street":"Scarff Ave",
    "iso:country":"US",
    "sg:address":"5 Scarff Ave",
    "sg:city":"Burlington",
    "sg:classifiers":[
        {
            "category":"Real Estate",
            "subcategory":"Architect",
            "type":"Services"
        }
    ],
    "sg:phone":"+1 802 863 4331",
    "sg:postcode":"05401",
    "sg:province":"VT",
    "sg:tags":[
        "architectural"
    ],
    "wof:name":"Ralph P Branon Assocs",
    "wof:placetype":"venue"
},
  "geometry": {"coordinates":[-73.21127799999999,44.451892],"type":"Point"}
}