{
  "type": "Feature",
  "properties": {
    "addr:full":"63 Main St Putney VT 05346",
    "addr:housenumber":"63",
    "addr:postcode":"05346",
    "addr:street":"Main St",
    "iso:country":"US",
    "sg:address":"63 Main St",
    "sg:city":"Putney",
    "sg:classifiers":[
        {
            "category":"Health Services",
            "subcategory":"Health Practitioner",
            "type":"Services"
        }
    ],
    "sg:phone":"+1 802 387 5577",
    "sg:postcode":"05346",
    "sg:province":"VT",
    "sg:tags":[
        "therapist",
        "physical"
    ],
    "wof:name":"Full Circle Therapy & Training",
    "wof:placetype":"venue"
},
  "geometry": {"coordinates":[-72.522335,42.97128],"type":"Point"}
}