{
  "type": "Feature",
  "properties": {
    "iso:country":"US",
    "sg:address":"18 S Gorham Ln",
    "sg:city":"Middlebury",
    "sg:classifiers":[
        {
            "category":"Insurance",
            "subcategory":"Hazard Insurance",
            "type":"Services"
        }
    ],
    "sg:phone":"+1 802 388 3739",
    "sg:postcode":"05753",
    "sg:province":"VT",
    "sg:tags":[
        "profit",
        "fund",
        "sharing",
        "pension",
        "plan"
    ],
    "wof:name":"Actuarial Pension Analysts Inc",
    "wof:placetype":"venue"
},
  "geometry": {"coordinates":[-73.181673,44.01525],"type":"Point"}
}