{
  "type": "Feature",
  "properties": {
    "addr:full":"41 Countryside Dr Essex Junction VT 05452",
    "addr:housenumber":"41",
    "addr:postcode":"05452",
    "addr:street":"Countryside Dr",
    "iso:country":"US",
    "sg:address":"41 Countryside Dr",
    "sg:city":"Essex Junction",
    "sg:classifiers":[
        {
            "category":"Professional",
            "type":"Services"
        },
        {
            "category":"Shopping",
            "type":"Retail Goods"
        }
    ],
    "sg:phone":"+1 802 878 1011",
    "sg:postcode":"05452",
    "sg:province":"VT",
    "sg:tags":[
        "repair",
        "frame",
        "picture"
    ],
    "sg:website":"www.carolboucher.com",
    "wof:name":"Carol Boucher Fine Artist",
    "wof:placetype":"venue"
},
  "geometry": {"coordinates":[-73.086258,44.496164],"type":"Point"}
}