{
  "type": "Feature",
  "properties": {
    "iso:country":"US",
    "sg:address":"224 US Hwy 2",
    "sg:city":"Grand Isle",
    "sg:classifiers":[
        {
            "category":"Government",
            "subcategory":"Fire Station",
            "type":"Public Place"
        }
    ],
    "sg:phone":"+1 802 372 6942",
    "sg:postcode":"05458",
    "sg:province":"VT",
    "sg:tags":[
        "protection"
    ],
    "wof:name":"Early Childhood Program",
    "wof:placetype":"venue"
},
  "geometry": {"coordinates":[-73.292331,44.726588],"type":"Point"}
}