{
  "type": "Feature",
  "properties": {
    "iso:country":"US",
    "sg:address":"2529 N Ridge Rd",
    "sg:city":"Sutton",
    "sg:classifiers":[
        {
            "category":"Building & Trades",
            "subcategory":"Construction",
            "type":"Services"
        }
    ],
    "sg:phone":"+1 802 467 3357",
    "sg:postcode":"05867",
    "sg:province":"VT",
    "sg:tags":[
        "excavating",
        "contractor"
    ],
    "wof:name":"E Weed & Son",
    "wof:placetype":"venue"
},
  "geometry": {"coordinates":[-72.006387,44.661085],"type":"Point"}
}