{
  "type": "Feature",
  "properties": {
    "addr:full":"38 Scribner Rd Stowe VT 05672",
    "addr:housenumber":"38",
    "addr:postcode":"05672",
    "addr:street":"Scribner Rd",
    "iso:country":"US",
    "sg:address":"38 Scribner Rd",
    "sg:city":"Stowe",
    "sg:classifiers":[
        {
            "category":"Professional",
            "subcategory":"Computer Services",
            "type":"Services"
        }
    ],
    "sg:phone":"+1 802 253 6379",
    "sg:postcode":"05672",
    "sg:province":"VT",
    "wof:name":"MLF Computer Svc",
    "wof:placetype":"venue"
},
  "geometry": {"coordinates":[-72.661057,44.482284],"type":"Point"}
}