{
  "type": "Feature",
  "properties": {
    "addr:full":"71 Center Rd Essex Junction VT 05452",
    "addr:housenumber":"71",
    "addr:postcode":"05452",
    "addr:street":"Center Rd",
    "iso:country":"US",
    "sg:address":"71 Center Rd",
    "sg:city":"Essex Junction",
    "sg:classifiers":[
        {
            "category":"Social Services",
            "subcategory":"Child Care",
            "type":"Services"
        }
    ],
    "sg:phone":"+1 802 878 8799",
    "sg:postcode":"05452",
    "sg:province":"VT",
    "wof:name":"Dinosaur Daycare",
    "wof:placetype":"venue"
},
  "geometry": {"coordinates":[-73.073027,44.510534],"type":"Point"}
}