{
  "type": "Feature",
  "properties": {
    "iso:country":"US",
    "sg:address":"471 Lawrence Pl",
    "sg:city":"Williston",
    "sg:classifiers":[
        {
            "category":"Real Estate",
            "subcategory":"Real Estate Operator",
            "type":"Services"
        }
    ],
    "sg:phone":"+1 802 879 0990",
    "sg:postcode":"05495",
    "sg:province":"VT",
    "sg:tags":[
        "company",
        "holding"
    ],
    "wof:name":"East Wllstn Rd Assoc Ltd Prtnr",
    "wof:placetype":"venue"
},
  "geometry": {"coordinates":[-73.11353699999999,44.451613],"type":"Point"}
}