{
  "type": "Feature",
  "properties": {
    "iso:country":"US",
    "sg:address":"88 Ardec Ln",
    "sg:city":"Richmond",
    "sg:classifiers":[
        {
            "category":"Building & Trades",
            "subcategory":"Construction",
            "type":"Services"
        }
    ],
    "sg:phone":"+1 802 434 2544",
    "sg:postcode":"05477",
    "sg:province":"VT",
    "sg:tags":[
        "hanging",
        "contractor"
    ],
    "wof:name":"Renaissance Painters",
    "wof:placetype":"venue"
},
  "geometry": {"coordinates":[-72.849581,44.42174],"type":"Point"}
}