{
  "type": "Feature",
  "properties": {
    "addr:full":"80 Belden Rd Rutland VT 05701",
    "addr:housenumber":"80",
    "addr:postcode":"05701",
    "addr:street":"Belden Rd",
    "iso:country":"US",
    "sg:address":"80 Belden Rd",
    "sg:city":"Rutland",
    "sg:classifiers":[
        {
            "category":"Retail",
            "subcategory":"Auto Repair",
            "type":"Services"
        }
    ],
    "sg:phone":"+1 802 747 3407",
    "sg:postcode":"05701",
    "sg:province":"VT",
    "sg:tags":[
        "repairing",
        "automotive",
        "automobile",
        "general"
    ],
    "wof:name":"Jim's Imported Car Clinic",
    "wof:placetype":"venue"
},
  "geometry": {"coordinates":[-72.992265,43.604536],"type":"Point"}
}