{
  "type": "Feature",
  "properties": {
    "iso:country":"US",
    "sg:address":"4581 Memorial Dr",
    "sg:city":"St Johnsbury",
    "sg:classifiers":[
        {
            "category":"Wholesale",
            "subcategory":"Hardware",
            "type":"Manufacturing & Wholesale Goods"
        },
        {
            "category":"Home & Garden",
            "subcategory":"Building Materials",
            "type":"Retail Goods"
        }
    ],
    "sg:phone":"+1 802 748 4513",
    "sg:postcode":"05819",
    "sg:province":"VT",
    "sg:tags":[
        "plumbing",
        "fixture",
        "merchandise",
        "supply"
    ],
    "wof:name":"Appalachian Supply Inc",
    "wof:placetype":"venue"
},
  "geometry": {"coordinates":[-72.004589,44.495823],"type":"Point"}
}