{
  "type": "Feature",
  "properties": {
    "addr:full":"120 Kimball Ave South Burlington VT 05403",
    "addr:housenumber":"120",
    "addr:postcode":"05403",
    "addr:street":"Kimball Ave",
    "iso:country":"US",
    "sg:address":"120 Kimball Ave",
    "sg:city":"South Burlington",
    "sg:classifiers":[
        {
            "category":"Real Estate",
            "subcategory":"Real Estate Agent",
            "type":"Services"
        }
    ],
    "sg:phone":"+1 802 878 0099",
    "sg:postcode":"05403",
    "sg:province":"VT",
    "wof:name":"Nancy Jenkinsbarges",
    "wof:placetype":"venue"
},
  "geometry": {"coordinates":[-73.151218,44.457057],"type":"Point"}
}