{
  "type": "Feature",
  "properties": {
    "iso:country":"US",
    "sg:address":"1101 State Rte 11",
    "sg:city":"Manchester Ctr",
    "sg:classifiers":[
        {
            "category":"Shopping",
            "type":"Retail Goods"
        }
    ],
    "sg:phone":"+1 802 366 9133",
    "sg:postcode":"05255",
    "sg:province":"VT",
    "sg:tags":[
        "factory",
        "outlet"
    ],
    "wof:name":"Orvis",
    "wof:placetype":"venue"
},
  "geometry": {"coordinates":[-73.03605399999999,43.173974],"type":"Point"}
}