{
  "type": "Feature",
  "properties": {
    "addr:full":"36 Three Mile Bridge Rd Montpelier VT 05602",
    "addr:housenumber":"36",
    "addr:postcode":"05602",
    "addr:street":"Three Mile Bridge Rd",
    "iso:country":"US",
    "sg:address":"36 Three Mile Bridge Rd",
    "sg:city":"Montpelier",
    "sg:classifiers":[
        {
            "category":"Retail",
            "subcategory":"Veterinary Services",
            "type":"Services"
        }
    ],
    "sg:phone":"+1 802 223 7765",
    "sg:postcode":"05602",
    "sg:province":"VT",
    "sg:tags":[
        "veterinarian"
    ],
    "wof:name":"Onion River Animal Hospital",
    "wof:placetype":"venue"
},
  "geometry": {"coordinates":[-72.618953,44.261516],"type":"Point"}
}