{
  "type": "Feature",
  "properties": {
    "iso:country":"US",
    "sg:address":"3620 State Rte 14",
    "sg:city":"Sharon",
    "sg:classifiers":[
        {
            "category":"Retail",
            "subcategory":"Auto Repair",
            "type":"Services"
        }
    ],
    "sg:phone":"+1 802 763 2000",
    "sg:postcode":"05065",
    "sg:province":"VT",
    "sg:tags":[
        "body",
        "automobile",
        "painting"
    ],
    "wof:name":"Al Miller's Auto Body",
    "wof:placetype":"venue"
},
  "geometry": {"coordinates":[-72.44663799999999,43.768246],"type":"Point"}
}