{
  "type": "Feature",
  "properties": {
    "iso:country":"US",
    "sg:address":"96 Upper Plain",
    "sg:city":"Bradford",
    "sg:classifiers":[
        {
            "category":"Retail",
            "subcategory":"Funeral Services",
            "type":"Services"
        }
    ],
    "sg:phone":"+1 802 222 5758",
    "sg:postcode":"05033",
    "sg:province":"VT",
    "sg:tags":[
        "director"
    ],
    "wof:name":"Hale Funeral Homes",
    "wof:placetype":"venue"
},
  "geometry": {"coordinates":[-72.11891900000001,44.000707],"type":"Point"}
}