{
  "type": "Feature",
  "properties": {
    "iso:country":"US",
    "sg:address":"72 Landmark Hill Dr",
    "sg:city":"Brattleboro",
    "sg:classifiers":[
        {
            "category":"Health Services",
            "subcategory":"Doctor",
            "type":"Services"
        }
    ],
    "sg:phone":"+1 802 254 9244",
    "sg:postcode":"05301",
    "sg:province":"VT",
    "sg:tags":[
        "dentist"
    ],
    "wof:name":"Horizon Dental Associates PC",
    "wof:placetype":"venue"
},
  "geometry": {"coordinates":[-72.557761,42.875159],"type":"Point"}
}