{
  "type": "Feature",
  "properties": {
    "addr:full":"401 E Clarendon Rd North Clarendon VT 05759",
    "addr:housenumber":"401",
    "addr:postcode":"05759",
    "addr:street":"E Clarendon Rd",
    "iso:country":"US",
    "sg:address":"401 E Clarendon Rd",
    "sg:city":"North Clarendon",
    "sg:classifiers":[
        {
            "category":"Professional",
            "type":"Services"
        },
        {
            "category":"Shopping",
            "subcategory":"Catalog Store",
            "type":"Retail Goods"
        }
    ],
    "sg:phone":"+1 802 775 4177",
    "sg:postcode":"05759",
    "sg:province":"VT",
    "sg:tags":[
        "mail",
        "establishment",
        "house"
    ],
    "sg:website":"www.vcsapothecary.com",
    "wof:name":"Vermont Country Store Bakery",
    "wof:placetype":"venue"
},
  "geometry": {"coordinates":[-72.93292599999999,43.531395],"type":"Point"}
}