{
  "type": "Feature",
  "properties": {
    "addr:full":"1845 Carter Hill Rd Swanton VT 05488",
    "addr:housenumber":"1845",
    "addr:postcode":"05488",
    "addr:street":"Carter Hill Rd",
    "iso:country":"US",
    "sg:address":"1845 Carter Hill Rd",
    "sg:city":"Swanton",
    "sg:classifiers":[
        {
            "category":"Building & Trades",
            "subcategory":"Plumbing",
            "type":"Services"
        }
    ],
    "sg:phone":"+1 802 868 5300",
    "sg:postcode":"05488",
    "sg:province":"VT",
    "sg:tags":[
        "heating",
        "contractor"
    ],
    "wof:name":"C & R Heating",
    "wof:placetype":"venue"
},
  "geometry": {"coordinates":[-73.09196,44.954154],"type":"Point"}
}