{
  "type": "Feature",
  "properties": {
    "iso:country":"US",
    "sg:address":"70 Hazel Dr",
    "sg:city":"Bristol",
    "sg:classifiers":[
        {
            "category":"Building & Trades",
            "subcategory":"Construction",
            "type":"Services"
        }
    ],
    "sg:phone":"+1 802 453 2587",
    "sg:postcode":"05443",
    "sg:province":"VT",
    "sg:tags":[
        "excavation",
        "contractor"
    ],
    "wof:name":"Heffernan Excavating Inc",
    "wof:placetype":"venue"
},
  "geometry": {"coordinates":[-73.08347000000001,44.147026],"type":"Point"}
}