{
  "type": "Feature",
  "properties": {
    "iso:country":"US",
    "sg:address":"27 Marvin St",
    "sg:city":"Montpelier",
    "sg:classifiers":[
        {
            "category":"Retail",
            "subcategory":"Portrait Studio",
            "type":"Services"
        }
    ],
    "sg:phone":"+1 802 223 2464",
    "sg:postcode":"05602",
    "sg:province":"VT",
    "sg:tags":[
        "photo"
    ],
    "wof:name":"Digitechvt",
    "wof:placetype":"venue"
},
  "geometry": {"coordinates":[-72.566343,44.257838],"type":"Point"}
}