{
  "type": "Feature",
  "properties": {
    "addr:full":"37 Taft Corners Shopping Center Williston VT 05495",
    "addr:housenumber":"37",
    "addr:postcode":"05495",
    "addr:street":"Taft Corners Shopping",
    "iso:country":"US",
    "sg:address":"37 Taft Corners Shopping Center",
    "sg:city":"Williston",
    "sg:classifiers":[
        {
            "category":"Shopping",
            "subcategory":"Gifts & Souvenirs",
            "type":"Retail Goods"
        }
    ],
    "sg:phone":"+1 802 872 8891",
    "sg:postcode":"05495",
    "sg:province":"VT",
    "wof:name":"Noble Inspirations",
    "wof:placetype":"venue"
},
  "geometry": {"coordinates":[-73.109865,44.450842],"type":"Point"}
}