{
  "type": "Feature",
  "properties": {
    "iso:country":"US",
    "sg:address":"349 Hillview Rd",
    "sg:city":"Richmond",
    "sg:classifiers":[
        {
            "category":"Building & Trades",
            "subcategory":"Construction",
            "type":"Services"
        }
    ],
    "sg:phone":"+1 802 434 2843",
    "sg:postcode":"05477",
    "sg:province":"VT",
    "sg:tags":[
        "excavation",
        "work"
    ],
    "wof:name":"Spence Excavating & Cnstr",
    "wof:placetype":"venue"
},
  "geometry": {"coordinates":[-73.01857099999999,44.392227],"type":"Point"}
}