{
  "type": "Feature",
  "properties": {
    "iso:country":"US",
    "sg:address":"43 Woodstock Ave",
    "sg:city":"Rutland",
    "sg:classifiers":[
        {
            "category":"Home & Garden",
            "subcategory":"Home Furnishings",
            "type":"Retail Goods"
        }
    ],
    "sg:phone":"+1 802 775 6289",
    "sg:postcode":"05701",
    "sg:province":"VT",
    "sg:tags":[
        "stove",
        "wood",
        "burning"
    ],
    "wof:name":"Country Stoves",
    "wof:placetype":"venue"
},
  "geometry": {"coordinates":[-72.968007,43.611939],"type":"Point"}
}