{
  "type": "Feature",
  "properties": {
    "iso:country":"US",
    "sg:address":"12 Butler Dr",
    "sg:city":"South Burlington",
    "sg:classifiers":[
        {
            "category":"Health Services",
            "subcategory":"Clinic",
            "type":"Services"
        }
    ],
    "sg:phone":"+1 802 862 8637",
    "sg:postcode":"05403",
    "sg:province":"VT",
    "wof:name":"Nutrition Insights",
    "wof:placetype":"venue"
},
  "geometry": {"coordinates":[-73.159864,44.435357],"type":"Point"}
}