{
  "type": "Feature",
  "properties": {
    "iso:country":"US",
    "sg:address":"54 S Main St",
    "sg:city":"Alburg",
    "sg:classifiers":[
        {
            "category":"Professional",
            "subcategory":"Research",
            "type":"Services"
        }
    ],
    "sg:phone":"+1 802 796 3169",
    "sg:postcode":"05440",
    "sg:province":"VT",
    "sg:tags":[
        "development",
        "laboratory"
    ],
    "wof:name":"Frontier Institute",
    "wof:placetype":"venue"
},
  "geometry": {"coordinates":[-73.300326,44.976131],"type":"Point"}
}