{
  "type": "Feature",
  "properties": {
    "iso:country":"US",
    "sg:address":"400 Riddel Pond Rd",
    "sg:city":"West Topsham",
    "sg:classifiers":[
        {
            "category":"Building & Trades",
            "subcategory":"Construction",
            "type":"Services"
        }
    ],
    "sg:phone":"+1 802 439 5340",
    "sg:postcode":"05086",
    "sg:province":"VT",
    "sg:tags":[
        "residential"
    ],
    "wof:name":"Brian T Omeara",
    "wof:placetype":"venue"
},
  "geometry": {"coordinates":[-72.345939,44.139917],"type":"Point"}
}