{
  "type": "Feature",
  "properties": {
    "addr:full":"28 Church St West Rutland VT 05777",
    "addr:housenumber":"28",
    "addr:postcode":"05777",
    "addr:street":"Church St",
    "iso:country":"US",
    "sg:address":"28 Church St",
    "sg:city":"West Rutland",
    "sg:classifiers":[
        {
            "category":"Organizations",
            "subcategory":"Religious Organization",
            "type":"Services"
        }
    ],
    "sg:phone":"+1 802 438 2490",
    "sg:postcode":"05777",
    "sg:province":"VT",
    "sg:tags":[
        "church"
    ],
    "wof:name":"St Bridgets Catholic Church",
    "wof:placetype":"venue"
},
  "geometry": {"coordinates":[-73.048395,43.605992],"type":"Point"}
}