{
  "type": "Feature",
  "properties": {
    "iso:country":"US",
    "sg:address":"54 Birchwood Dr",
    "sg:city":"Colchester",
    "sg:classifiers":[
        {
            "category":"Social Services",
            "type":"Services"
        }
    ],
    "sg:phone":"+1 802 878 8981",
    "sg:postcode":"05446",
    "sg:province":"VT",
    "wof:name":"World Wide Mrrage Encounter VT",
    "wof:placetype":"venue"
},
  "geometry": {"coordinates":[-73.13637199999999,44.535851],"type":"Point"}
}