{
  "type": "Feature",
  "properties": {
    "addr:full":"81 Weaver St Newport VT 05855",
    "addr:housenumber":"81",
    "addr:postcode":"05855",
    "addr:street":"Weaver St",
    "iso:country":"US",
    "sg:address":"81 Weaver St",
    "sg:city":"Newport",
    "sg:classifiers":[
        {
            "category":"Manufacturing",
            "subcategory":"Apparel",
            "type":"Manufacturing & Wholesale Goods"
        }
    ],
    "sg:phone":"+1 802 334 6565",
    "sg:postcode":"05855",
    "sg:province":"VT",
    "sg:tags":[
        "house",
        "furnishing",
        "drapery"
    ],
    "sg:website":"www.greenmountainlinens.com",
    "wof:name":"Sel-Bar Weaving Inc",
    "wof:placetype":"venue"
},
  "geometry": {"coordinates":[-72.201668,44.935216],"type":"Point"}
}