{
  "type": "Feature",
  "properties": {
    "addr:full":"472 State Rte 114 Norton VT 05907",
    "addr:housenumber":"472",
    "addr:postcode":"05907",
    "addr:street":"State Rte 114",
    "iso:country":"US",
    "sg:address":"472 State Rte 114",
    "sg:city":"Norton",
    "sg:classifiers":[
        {
            "category":"Government",
            "subcategory":"Office",
            "type":"Public Place"
        }
    ],
    "sg:phone":"+1 802 822 9935",
    "sg:postcode":"05907",
    "sg:province":"VT",
    "sg:tags":[
        "village"
    ],
    "wof:name":"Norton Town Office",
    "wof:placetype":"venue"
},
  "geometry": {"coordinates":[-71.89509,44.88804],"type":"Point"}
}