{
  "type": "Feature",
  "properties": {
    "iso:country":"US",
    "sg:address":"5 Perry St",
    "sg:city":"Barre",
    "sg:classifiers":[
        {
            "category":"Government",
            "subcategory":"Office",
            "type":"Public Place"
        }
    ],
    "sg:phone":"+1 802 479 4250",
    "sg:postcode":"05641",
    "sg:province":"VT",
    "sg:tags":[
        "state",
        "program",
        "health"
    ],
    "wof:name":"Alcohol & Drug Abuse Ofc",
    "wof:placetype":"venue"
},
  "geometry": {"coordinates":[-72.498158,44.195222],"type":"Point"}
}