{
  "type": "Feature",
  "properties": {
    "iso:country":"US",
    "sg:address":"156 School Rd",
    "sg:city":"Shoreham",
    "sg:classifiers":[
        {
            "category":"Education",
            "subcategory":"School",
            "type":"Public Place"
        }
    ],
    "sg:phone":"+1 802 897 2888",
    "sg:postcode":"05770",
    "sg:province":"VT",
    "wof:name":"Shoreham Preschool",
    "wof:placetype":"venue"
},
  "geometry": {"coordinates":[-73.31590199999999,43.891581],"type":"Point"}
}