{
  "type": "Feature",
  "properties": {
    "iso:country":"US",
    "sg:address":"87 Stoneshed Rd",
    "sg:city":"South Ryegate",
    "sg:classifiers":[
        {
            "category":"Manufacturing",
            "subcategory":"Glass & Minerals",
            "type":"Manufacturing & Wholesale Goods"
        }
    ],
    "sg:phone":"+1 802 584 3521",
    "sg:postcode":"05069",
    "sg:province":"VT",
    "sg:tags":[
        "stone",
        "cut",
        "product"
    ],
    "wof:name":"Gandin Brothers Plant",
    "wof:placetype":"venue"
},
  "geometry": {"coordinates":[-72.141175,44.187784],"type":"Point"}
}