{
  "type": "Feature",
  "properties": {
    "iso:country":"US",
    "sg:address":"51 Berlin St",
    "sg:city":"Montpelier",
    "sg:classifiers":[
        {
            "category":"Bagels",
            "type":"Food & Drink"
        },
        {
            "category":"Coffee & Tea",
            "type":"Food & Drink"
        },
        {
            "category":"Food & Beverages",
            "subcategory":"Bakery",
            "type":"Retail Goods"
        },
        {
            "category":"Bakery",
            "type":"Food & Drink"
        },
        {
            "category":"Donuts",
            "type":"Food & Drink"
        }
    ],
    "sg:menulink":"http://www.allmenus.com/vt/montpelier/139032-dunkin-donuts/menu/",
    "sg:phone":"+1 802 223 0928",
    "sg:postcode":"05602",
    "sg:province":"VT",
    "sg:tags":[
        "coffee",
        "tea",
        "american",
        "bagel",
        "bakery",
        "pastry"
    ],
    "wof:name":"Dunkin' Donuts",
    "wof:placetype":"venue"
},
  "geometry": {"coordinates":[-72.576003,44.255908],"type":"Point"}
}