{
  "type": "Feature",
  "properties": {
    "addr:full":"32 San Remo Dr South Burlington VT 05403",
    "addr:housenumber":"32",
    "addr:postcode":"05403",
    "addr:street":"San Remo Dr",
    "iso:country":"US",
    "sg:address":"32 San Remo Dr",
    "sg:city":"South Burlington",
    "sg:classifiers":[
        {
            "category":"Wholesale",
            "subcategory":"Durable Goods & Equipment",
            "type":"Manufacturing & Wholesale Goods"
        }
    ],
    "sg:phone":"+1 802 862 2500",
    "sg:postcode":"05403",
    "sg:province":"VT",
    "sg:tags":[
        "fire",
        "extinguisher"
    ],
    "wof:name":"Burlington Petroleum Equipment",
    "wof:placetype":"venue"
},
  "geometry": {"coordinates":[-73.17900899999999,44.458013],"type":"Point"}
}