{
  "type": "Feature",
  "properties": {
    "iso:country":"US",
    "sg:address":"72 Bridge St",
    "sg:city":"Richmond",
    "sg:classifiers":[
        {
            "category":"Health Services",
            "subcategory":"Chiropractor",
            "type":"Services"
        }
    ],
    "sg:phone":"+1 802 434 5755",
    "sg:postcode":"05477",
    "sg:province":"VT",
    "wof:name":"Mary Kintner DC",
    "wof:placetype":"venue"
},
  "geometry": {"coordinates":[-72.993776,44.404492],"type":"Point"}
}