{
  "type": "Feature",
  "properties": {
    "addr:full":"205 Northside Dr Bennington VT 05201",
    "addr:housenumber":"205",
    "addr:postcode":"05201",
    "addr:street":"Northside Dr",
    "iso:country":"US",
    "sg:address":"205 Northside Dr",
    "sg:city":"Bennington",
    "sg:classifiers":[
        {
            "category":"Shopping",
            "subcategory":"Gifts & Souvenirs",
            "type":"Retail Goods"
        }
    ],
    "sg:phone":"+1 802 442 9489",
    "sg:postcode":"05201",
    "sg:province":"VT",
    "wof:name":"M & M Balloons",
    "wof:placetype":"venue"
},
  "geometry": {"coordinates":[-73.20981999999999,42.899403],"type":"Point"}
}