{
  "type": "Feature",
  "properties": {
    "iso:country":"US",
    "sg:address":"245 Stratton Rd",
    "sg:city":"Rutland",
    "sg:classifiers":[
        {
            "category":"Health Services",
            "subcategory":"Chiropractor",
            "type":"Services"
        }
    ],
    "sg:phone":"+1 802 775 6961",
    "sg:postcode":"05701",
    "sg:province":"VT",
    "wof:name":"Physical Rehabilitation & Hlth",
    "wof:placetype":"venue"
},
  "geometry": {"coordinates":[-72.950169,43.592226],"type":"Point"}
}