{
  "type": "Feature",
  "properties": {
    "iso:country":"US",
    "sg:address":"21 Lake Dunmore Rd",
    "sg:city":"Brandon",
    "sg:classifiers":[
        {
            "category":"Restaurant",
            "type":"Food & Drink"
        }
    ],
    "sg:phone":"+1 802 247 3615",
    "sg:postcode":"05733",
    "sg:province":"VT",
    "sg:tags":[
        "barbecue"
    ],
    "wof:name":"Ward Mann's Hog Heaven B-B-Q",
    "wof:placetype":"venue"
},
  "geometry": {"coordinates":[-73.063951,43.897877],"type":"Point"}
}