{
  "type": "Feature",
  "properties": {
    "iso:country":"US",
    "sg:address":"198 Norway Dr",
    "sg:city":"Colchester",
    "sg:classifiers":[
        {
            "category":"Shopping",
            "subcategory":"Hobbies, Toys, & Games",
            "type":"Retail Goods"
        }
    ],
    "sg:phone":"+1 802 660 4762",
    "sg:postcode":"05446",
    "sg:province":"VT",
    "wof:name":"Kammel Arts",
    "wof:placetype":"venue"
},
  "geometry": {"coordinates":[-73.26324,44.546882],"type":"Point"}
}