{
  "type": "Feature",
  "properties": {
    "addr:full":"475 Delfrate Rd Huntington VT 05462",
    "addr:housenumber":"475",
    "addr:postcode":"05462",
    "addr:street":"Delfrate Rd",
    "iso:country":"US",
    "sg:address":"475 Delfrate Rd",
    "sg:city":"Huntington",
    "sg:classifiers":[
        {
            "category":"Professional",
            "subcategory":"Management & Consulting",
            "type":"Services"
        }
    ],
    "sg:phone":"+1 802 434 2173",
    "sg:postcode":"05462",
    "sg:province":"VT",
    "sg:tags":[
        "business"
    ],
    "wof:name":"Karen Steeb Consulting",
    "wof:placetype":"venue"
},
  "geometry": {"coordinates":[-72.961427,44.331482],"type":"Point"}
}