{
  "type": "Feature",
  "properties": {
    "iso:country":"US",
    "sg:address":"129 Skunk Hollow Rd",
    "sg:city":"Jericho",
    "sg:classifiers":[
        {
            "category":"Organizations",
            "subcategory":"Professional Association",
            "type":"Services"
        }
    ],
    "sg:phone":"+1 802 899 1357",
    "sg:postcode":"05465",
    "sg:province":"VT",
    "wof:name":"Freinds of Silence",
    "wof:placetype":"venue"
},
  "geometry": {"coordinates":[-73.01055700000001,44.488819],"type":"Point"}
}