{
  "type": "Feature",
  "properties": {
    "iso:country":"US",
    "sg:address":"2440 Sugarbush Access Rd",
    "sg:city":"Warren",
    "sg:classifiers":[
        {
            "category":"Travel",
            "subcategory":"Hotels & Motels",
            "type":"Entertainment"
        }
    ],
    "sg:phone":"+1 802 583 3211",
    "sg:postcode":"05674",
    "sg:province":"VT",
    "sg:website":"www.mad-river-valley.com",
    "wof:name":"Sugartree-A Country Inn",
    "wof:placetype":"venue"
},
  "geometry": {"coordinates":[-72.88511200000001,44.139861],"type":"Point"}
}