{
  "type": "Feature",
  "properties": {
    "iso:country":"US",
    "sg:address":"1114 Kelley Hill Rd",
    "sg:city":"Pawlet",
    "sg:classifiers":[
        {
            "category":"Farming",
            "subcategory":"Livestock Farm",
            "type":"Manufacturing & Wholesale Goods"
        }
    ],
    "sg:phone":"+1 802 325 3090",
    "sg:postcode":"05761",
    "sg:province":"VT",
    "wof:name":"Charles Eirmann",
    "wof:placetype":"venue"
},
  "geometry": {"coordinates":[-73.12835099999999,43.374267],"type":"Point"}
}