{
  "type": "Feature",
  "properties": {
    "addr:full":"8 Conant Sq Brandon VT 05733",
    "addr:housenumber":"8",
    "addr:postcode":"05733",
    "addr:street":"Conant Sq",
    "iso:country":"US",
    "sg:address":"8 Conant Sq",
    "sg:city":"Brandon",
    "sg:classifiers":[
        {
            "category":"Education",
            "subcategory":"Special Training",
            "type":"Public Place"
        }
    ],
    "sg:phone":"+1 802 247 3695",
    "sg:postcode":"05733",
    "sg:province":"VT",
    "sg:tags":[
        "educational"
    ],
    "wof:name":"Country Owl Studio",
    "wof:placetype":"venue"
},
  "geometry": {"coordinates":[-73.09251500000001,43.79995],"type":"Point"}
}