{
  "type": "Feature",
  "properties": {
    "iso:country":"US",
    "sg:address":"331 Belair Dr",
    "sg:city":"Colchester",
    "sg:classifiers":[
        {
            "category":"Building & Trades",
            "subcategory":"Construction",
            "type":"Services"
        }
    ],
    "sg:phone":"+1 802 862 0269",
    "sg:postcode":"05446",
    "sg:province":"VT",
    "sg:tags":[
        "general",
        "contractor"
    ],
    "wof:name":"Bedard Construction & Roofing",
    "wof:placetype":"venue"
},
  "geometry": {"coordinates":[-73.251785,44.546181],"type":"Point"}
}