{
  "type": "Feature",
  "properties": {
    "iso:country":"US",
    "sg:address":"66 Grandview Ter",
    "sg:city":"Montpelier",
    "sg:classifiers":[
        {
            "category":"Home & Garden",
            "subcategory":"Building Materials",
            "type":"Retail Goods"
        }
    ],
    "sg:phone":"+1 802 223 0495",
    "sg:postcode":"05602",
    "sg:province":"VT",
    "wof:name":"Julie M Bevins",
    "wof:placetype":"venue"
},
  "geometry": {"coordinates":[-72.55371599999999,44.259211],"type":"Point"}
}