{
  "type": "Feature",
  "properties": {
    "iso:country":"US",
    "sg:address":"125 Bradford St",
    "sg:city":"Bennington",
    "sg:classifiers":[
        {
            "category":"Organizations",
            "subcategory":"Religious Organization",
            "type":"Services"
        }
    ],
    "sg:phone":"+1 802 447 0139",
    "sg:postcode":"05201",
    "sg:province":"VT",
    "wof:name":"Mormon Missionaries",
    "wof:placetype":"venue"
},
  "geometry": {"coordinates":[-73.18384,42.881173],"type":"Point"}
}