{
  "type": "Feature",
  "properties": {
    "addr:full":"40 Court St Middlebury VT 05753",
    "addr:housenumber":"40",
    "addr:postcode":"05753",
    "addr:street":"Court St",
    "iso:country":"US",
    "sg:address":"40 Court St",
    "sg:city":"Middlebury",
    "sg:classifiers":[
        {
            "category":"Home & Garden",
            "subcategory":"Hardware",
            "type":"Retail Goods"
        }
    ],
    "sg:phone":"+1 802 388 1400",
    "sg:postcode":"05753",
    "sg:province":"VT",
    "wof:name":"Aubuchon Hardware",
    "wof:placetype":"venue"
},
  "geometry": {"coordinates":[-73.163732,44.010907],"type":"Point"}
}