{
  "type": "Feature",
  "properties": {
    "iso:country":"US",
    "sg:address":"81 Park Ave",
    "sg:city":"Williston",
    "sg:classifiers":[
        {
            "category":"Home & Garden",
            "subcategory":"Building Materials",
            "type":"Retail Goods"
        }
    ],
    "sg:phone":"+1 802 878 4338",
    "sg:postcode":"05495",
    "sg:province":"VT",
    "sg:tags":[
        "repair",
        "elect",
        "mfg"
    ],
    "wof:name":"Limoge & Sons Garage Doors",
    "wof:placetype":"venue"
},
  "geometry": {"coordinates":[-73.11609199999999,44.476424],"type":"Point"}
}