{
  "type": "Feature",
  "properties": {
    "iso:country":"US",
    "sg:address":"430 East Rd",
    "sg:city":"Milton",
    "sg:classifiers":[
        {
            "category":"Retail",
            "subcategory":"Auto Repair",
            "type":"Services"
        }
    ],
    "sg:phone":"+1 802 893 7554",
    "sg:postcode":"05468",
    "sg:province":"VT",
    "sg:tags":[
        "body",
        "automobile",
        "painting"
    ],
    "wof:name":"Lou & Sons Body Shop",
    "wof:placetype":"venue"
},
  "geometry": {"coordinates":[-73.102508,44.606629],"type":"Point"}
}