{
  "type": "Feature",
  "properties": {
    "addr:full":"159 N Main St Wallingford VT 05773",
    "addr:housenumber":"159",
    "addr:postcode":"05773",
    "addr:street":"N Main St",
    "iso:country":"US",
    "sg:address":"159 N Main St",
    "sg:city":"Wallingford",
    "sg:classifiers":[
        {
            "category":"Home & Garden",
            "subcategory":"Furniture",
            "type":"Retail Goods"
        }
    ],
    "sg:phone":"+1 802 446 2961",
    "sg:postcode":"05773",
    "sg:province":"VT",
    "sg:tags":[
        "store"
    ],
    "wof:name":"New Face Furniture",
    "wof:placetype":"venue"
},
  "geometry": {"coordinates":[-72.977814,43.469269],"type":"Point"}
}