{
  "type": "Feature",
  "properties": {
    "iso:country":"US",
    "sg:address":"205 Main St Ste 1",
    "sg:city":"Brattleboro",
    "sg:classifiers":[
        {
            "category":"Real Estate",
            "subcategory":"Real Estate Services",
            "type":"Services"
        },
        {
            "category":"Banks & Credit Unions",
            "subcategory":"Bank",
            "type":"Services"
        }
    ],
    "sg:phone":"+1 802 257 7961",
    "sg:postcode":"05301",
    "sg:province":"VT",
    "sg:tags":[
        "commercial",
        "loan",
        "saving"
    ],
    "sg:website":"http://www.mbvt.com",
    "wof:name":"Merchants Bank The",
    "wof:placetype":"venue"
},
  "geometry": {"coordinates":[-72.559112,42.854639],"type":"Point"}
}