{
  "type": "Feature",
  "properties": {
    "iso:country":"US",
    "sg:address":"16 Dorset St",
    "sg:city":"South Burlington",
    "sg:classifiers":[
        {
            "category":"Shopping",
            "subcategory":"Pharmacy",
            "type":"Retail Goods"
        }
    ],
    "sg:phone":"+1 802 865 4507",
    "sg:postcode":"05403",
    "sg:province":"VT",
    "wof:name":"N C S Healthcare of Vermont",
    "wof:placetype":"venue"
},
  "geometry": {"coordinates":[-73.18123300000001,44.467202],"type":"Point"}
}