{
  "type": "Feature",
  "properties": {
    "iso:country":"US",
    "sg:address":"5 Derby Dr",
    "sg:city":"Woodbury",
    "sg:classifiers":[
        {
            "category":"Education",
            "subcategory":"School",
            "type":"Public Place"
        }
    ],
    "sg:phone":"+1 802 244 4074",
    "sg:postcode":"05602",
    "sg:province":"VT",
    "wof:name":"Harwood Community Learning Ctr",
    "wof:placetype":"venue"
},
  "geometry": {"coordinates":[-72.583488,44.252012],"type":"Point"}
}