{
  "type": "Feature",
  "properties": {
    "iso:country":"US",
    "sg:address":"311 Country Club Dr",
    "sg:city":"Pittsford",
    "sg:classifiers":[
        {
            "category":"Sports & Exercise",
            "subcategory":"Golf",
            "type":"Entertainment"
        }
    ],
    "sg:phone":"+1 802 483 9379",
    "sg:postcode":"05763",
    "sg:province":"VT",
    "sg:tags":[
        "course"
    ],
    "wof:name":"Proctor-Pittsford Country Club",
    "wof:placetype":"venue"
},
  "geometry": {"coordinates":[-73.01002099999999,43.685258],"type":"Point"}
}