{
  "type": "Feature",
  "properties": {
    "iso:country":"US",
    "sg:address":"916 W River Rd",
    "sg:city":"Brattleboro",
    "sg:classifiers":[
        {
            "category":"Organizations",
            "subcategory":"Membership Organization",
            "type":"Services"
        }
    ],
    "sg:phone":"+1 802 254 2232",
    "sg:postcode":"05301",
    "sg:province":"VT",
    "sg:tags":[
        "society",
        "humane"
    ],
    "wof:name":"Windham County Humane Society",
    "wof:placetype":"venue"
},
  "geometry": {"coordinates":[-72.58617700000001,42.882387],"type":"Point"}
}