{
  "type": "Feature",
  "properties": {
    "addr:full":"67 Monroe St Burlington VT 05401",
    "addr:housenumber":"67",
    "addr:postcode":"05401",
    "addr:street":"Monroe St",
    "iso:country":"US",
    "sg:address":"67 Monroe St",
    "sg:city":"Burlington",
    "sg:classifiers":[
        {
            "category":"Professional",
            "type":"Services"
        },
        {
            "category":"Taxi",
            "type":"Transportation"
        },
        {
            "category":"Airport",
            "type":"Transportation"
        }
    ],
    "sg:phone":"+1 802 734 1293",
    "sg:postcode":"05401",
    "sg:province":"VT",
    "sg:website":"http://www.vermonttourandcharter.com/reservations/",
    "wof:name":"Vermont Tour and Charter Taxi & Airport Shuttle",
    "wof:placetype":"venue"
},
  "geometry": {"coordinates":[-73.21616899999999,44.481458],"type":"Point"}
}