{
  "type": "Feature",
  "properties": {
    "iso:country":"US",
    "sg:address":"1735 Main Rd",
    "sg:city":"Huntington",
    "sg:classifiers":[
        {
            "category":"Retail",
            "subcategory":"Repair Shop",
            "type":"Services"
        }
    ],
    "sg:phone":"+1 802 434 3871",
    "sg:postcode":"05462",
    "sg:province":"VT",
    "wof:name":"Huntington River Smithy",
    "wof:placetype":"venue"
},
  "geometry": {"coordinates":[-72.997727,44.33853],"type":"Point"}
}