{
  "type": "Feature",
  "properties": {
    "iso:country":"US",
    "sg:address":"1000 Shelburne Rd",
    "sg:city":"South Burlington",
    "sg:classifiers":[
        {
            "category":"Government",
            "subcategory":"Office",
            "type":"Public Place"
        }
    ],
    "sg:phone":"+1 802 864 4416",
    "sg:postcode":"05403",
    "sg:province":"VT",
    "sg:tags":[
        "armed",
        "force",
        "recruiting"
    ],
    "wof:name":"US Marine Corps Recruiting",
    "wof:placetype":"venue"
},
  "geometry": {"coordinates":[-73.210134,44.440607],"type":"Point"}
}