{
  "type": "Feature",
  "properties": {
    "iso:country":"US",
    "sg:address":"499 Canal St Ste 9",
    "sg:city":"Brattleboro",
    "sg:classifiers":[
        {
            "category":"Personal",
            "subcategory":"Beauty Salon",
            "type":"Services"
        },
        {
            "category":"Personal",
            "subcategory":"Nail Salon",
            "type":"Services"
        }
    ],
    "sg:phone":"+1 802 257 7911",
    "sg:postcode":"05301",
    "sg:province":"VT",
    "sg:tags":[
        "hair",
        "accessory",
        "stylist",
        "supply"
    ],
    "sg:website":"http://www.enrightandcompany.com",
    "wof:name":"Enright and Company",
    "wof:placetype":"venue"
},
  "geometry": {"coordinates":[-72.56532300000001,42.838581],"type":"Point"}
}