{
  "type": "Feature",
  "properties": {
    "iso:country":"US",
    "sg:address":"213 School St",
    "sg:city":"Bennington",
    "sg:classifiers":[
        {
            "category":"Health Services",
            "subcategory":"Podiatrist",
            "type":"Services"
        }
    ],
    "sg:phone":"+1 802 442 8448",
    "sg:postcode":"05201",
    "sg:province":"VT",
    "wof:name":"Tri State Podiatry",
    "wof:placetype":"venue"
},
  "geometry": {"coordinates":[-73.19487599999999,42.879295],"type":"Point"}
}