{
  "type": "Feature",
  "properties": {
    "iso:country":"US",
    "sg:address":"273 Pearl St",
    "sg:city":"Burlington",
    "sg:classifiers":[
        {
            "category":"Health Services",
            "subcategory":"Doctor",
            "type":"Services"
        }
    ],
    "sg:phone":"+1 802 862 7906",
    "sg:postcode":"05401",
    "sg:province":"VT",
    "wof:name":"Lavoie John F",
    "wof:placetype":"venue"
},
  "geometry": {"coordinates":[-73.208939,44.480495],"type":"Point"}
}