{
  "type": "Feature",
  "properties": {
    "iso:country":"US",
    "sg:address":"79 W Shore Rd",
    "sg:city":"South Hero",
    "sg:classifiers":[
        {
            "category":"Building & Trades",
            "subcategory":"Construction",
            "type":"Services"
        }
    ],
    "sg:phone":"+1 802 372 5089",
    "sg:postcode":"05486",
    "sg:province":"VT",
    "sg:tags":[
        "house"
    ],
    "wof:name":"Tg Quality Builders",
    "wof:placetype":"venue"
},
  "geometry": {"coordinates":[-73.315577,44.619347],"type":"Point"}
}