{
  "type": "Feature",
  "properties": {
    "iso:country":"US",
    "sg:address":"38 Carver St",
    "sg:city":"Brandon",
    "sg:classifiers":[
        {
            "category":"Organizations",
            "subcategory":"Religious Organization",
            "type":"Services"
        }
    ],
    "sg:phone":"+1 802 247 6351",
    "sg:postcode":"05733",
    "sg:province":"VT",
    "wof:name":"Our Lady of Good Help",
    "wof:placetype":"venue"
},
  "geometry": {"coordinates":[-73.082718,43.794831],"type":"Point"}
}