{
  "type": "Feature",
  "properties": {
    "iso:country":"US",
    "sg:address":"6637 State Rte 116",
    "sg:city":"Shelburne",
    "sg:classifiers":[
        {
            "category":"Building & Trades",
            "subcategory":"Construction",
            "type":"Services"
        }
    ],
    "sg:phone":"+1 802 863 2049",
    "sg:postcode":"05482",
    "sg:province":"VT",
    "sg:tags":[
        "contractor"
    ],
    "wof:name":"Barton Builders",
    "wof:placetype":"venue"
},
  "geometry": {"coordinates":[-73.13842,44.382167],"type":"Point"}
}