{
  "type": "Feature",
  "properties": {
    "iso:country":"US",
    "sg:address":"3 Commerce Ave",
    "sg:city":"South Burlington",
    "sg:classifiers":[
        {
            "category":"Retail",
            "subcategory":"Auto Repair",
            "type":"Services"
        }
    ],
    "sg:phone":"+1 802 862 8539",
    "sg:postcode":"05403",
    "sg:province":"VT",
    "sg:tags":[
        "body",
        "automobile",
        "painting"
    ],
    "wof:name":"Riverside Auto Body Inc",
    "wof:placetype":"venue"
},
  "geometry": {"coordinates":[-73.159644,44.483444],"type":"Point"}
}