{
  "type": "Feature",
  "properties": {
    "iso:country":"US",
    "sg:address":"368 Dorset St",
    "sg:city":"South Burlington",
    "sg:classifiers":[
        {
            "category":"Health Services",
            "subcategory":"Doctor",
            "type":"Services"
        }
    ],
    "sg:phone":"+1 802 860 1441",
    "sg:postcode":"05403",
    "sg:province":"VT",
    "sg:tags":[
        "physician",
        "surgeon"
    ],
    "wof:name":"Good Health",
    "wof:placetype":"venue"
},
  "geometry": {"coordinates":[-73.17999,44.460774],"type":"Point"}
}