{
  "type": "Feature",
  "properties": {
    "iso:country":"US",
    "sg:address":"320 Hardwood Hill Rd",
    "sg:city":"Richford",
    "sg:classifiers":[
        {
            "category":"Building & Trades",
            "subcategory":"Construction",
            "type":"Services"
        }
    ],
    "sg:phone":"+1 802 848 3328",
    "sg:postcode":"05476",
    "sg:province":"VT",
    "sg:tags":[
        "roofing",
        "sheet",
        "metal",
        "contractor"
    ],
    "wof:name":"Parsons Construction",
    "wof:placetype":"venue"
},
  "geometry": {"coordinates":[-72.67507999999999,44.981105],"type":"Point"}
}