{
  "type": "Feature",
  "properties": {
    "iso:country":"US",
    "sg:address":"889 State Rte 44",
    "sg:city":"Brownsville",
    "sg:classifiers":[
        {
            "category":"Government",
            "subcategory":"Fire Station",
            "type":"Public Place"
        }
    ],
    "sg:phone":"+1 802 484 7872",
    "sg:postcode":"05037",
    "sg:province":"VT",
    "sg:tags":[
        "department"
    ],
    "wof:name":"West Windsor Volunteer Fire",
    "wof:placetype":"venue"
},
  "geometry": {"coordinates":[-72.46992299999999,43.467694],"type":"Point"}
}