{
  "type": "Feature",
  "properties": {
    "iso:country":"US",
    "sg:address":"22 Taft Corners Shopping Center",
    "sg:city":"Williston",
    "sg:classifiers":[
        {
            "category":"Shopping",
            "subcategory":"Florist",
            "type":"Retail Goods"
        }
    ],
    "sg:phone":"+1 802 878 2057",
    "sg:postcode":"05495",
    "sg:province":"VT",
    "wof:name":"Buds & Roses",
    "wof:placetype":"venue"
},
  "geometry": {"coordinates":[-73.110472,44.450851],"type":"Point"}
}