{
  "type": "Feature",
  "properties": {
    "iso:country":"US",
    "sg:address":"204 Main St",
    "sg:city":"Brattleboro",
    "sg:classifiers":[
        {
            "category":"Government",
            "subcategory":"Police Station",
            "type":"Public Place"
        }
    ],
    "sg:phone":"+1 802 257 1464",
    "sg:postcode":"05301",
    "sg:province":"VT",
    "sg:tags":[
        "enforcement",
        "law"
    ],
    "wof:name":"Marshals Service United States",
    "wof:placetype":"venue"
},
  "geometry": {"coordinates":[-72.55900800000001,42.854188],"type":"Point"}
}