{
  "type": "Feature",
  "properties": {
    "iso:country":"US",
    "sg:address":"686 US Hwy 7",
    "sg:city":"Middlebury",
    "sg:classifiers":[
        {
            "category":"Home & Garden",
            "subcategory":"Furniture",
            "type":"Retail Goods"
        }
    ],
    "sg:phone":"+1 802 388 1300",
    "sg:postcode":"05753",
    "sg:province":"VT",
    "sg:tags":[
        "mattress"
    ],
    "wof:name":"Bob's Furniture & Bedding",
    "wof:placetype":"venue"
},
  "geometry": {"coordinates":[-73.143052,43.99394],"type":"Point"}
}