{
  "type": "Feature",
  "properties": {
    "addr:full":"42 Summer St Barre VT 05641",
    "addr:housenumber":"42",
    "addr:postcode":"05641",
    "addr:street":"Summer St",
    "iso:country":"US",
    "sg:address":"42 Summer St",
    "sg:city":"Barre",
    "sg:classifiers":[
        {
            "category":"Personal",
            "subcategory":"Tanning Parlor",
            "type":"Services"
        }
    ],
    "sg:phone":"+1 802 479 3394",
    "sg:postcode":"05641",
    "sg:province":"VT",
    "sg:tags":[
        "salon"
    ],
    "wof:name":"Aspiratins Salon & Day Spa",
    "wof:placetype":"venue"
},
  "geometry": {"coordinates":[-72.50344200000001,44.200914],"type":"Point"}
}