{
  "type": "Feature",
  "properties": {
    "iso:country":"US",
    "sg:address":"51 Nashville Rd",
    "sg:city":"Jericho",
    "sg:classifiers":[
        {
            "category":"Building & Trades",
            "subcategory":"Construction",
            "type":"Services"
        }
    ],
    "sg:phone":"+1 802 899 4230",
    "sg:postcode":"05465",
    "sg:province":"VT",
    "sg:tags":[
        "hanging",
        "contractor"
    ],
    "wof:name":"Vermont Interior Painting",
    "wof:placetype":"venue"
},
  "geometry": {"coordinates":[-72.967755,44.453542],"type":"Point"}
}