{
  "type": "Feature",
  "properties": {
    "iso:country":"US",
    "sg:address":"115 Hillinger Ln",
    "sg:city":"Sharon",
    "sg:classifiers":[
        {
            "category":"Professional",
            "subcategory":"Computer Services",
            "type":"Services"
        }
    ],
    "sg:phone":"+1 802 763 7599",
    "sg:postcode":"05065",
    "sg:province":"VT",
    "sg:tags":[
        "programing",
        "custom"
    ],
    "wof:name":"Lexicon Systems",
    "wof:placetype":"venue"
},
  "geometry": {"coordinates":[-72.407923,43.799636],"type":"Point"}
}