{
  "type": "Feature",
  "properties": {
    "iso:country":"US",
    "sg:address":"26 Ferry Rd",
    "sg:city":"Hartland",
    "sg:classifiers":[
        {
            "category":"Wholesale",
            "subcategory":"Durable Goods & Equipment",
            "type":"Manufacturing & Wholesale Goods"
        }
    ],
    "sg:phone":"+1 802 436 1300",
    "sg:postcode":"05048",
    "sg:province":"VT",
    "sg:tags":[
        "mfg",
        "timber"
    ],
    "wof:name":"Global Timber Products LTD",
    "wof:placetype":"venue"
},
  "geometry": {"coordinates":[-72.38777,43.536868],"type":"Point"}
}