{
  "type": "Feature",
  "properties": {
    "addr:full":"107 E Hill Rd Barnet VT 05821",
    "addr:housenumber":"107",
    "addr:postcode":"05821",
    "addr:street":"E Hill Rd",
    "iso:country":"US",
    "sg:address":"107 E Hill Rd",
    "sg:city":"Barnet",
    "sg:classifiers":[
        {
            "category":"Retail",
            "subcategory":"Auto Repair",
            "type":"Services"
        }
    ],
    "sg:phone":"+1 802 633 3863",
    "sg:postcode":"05821",
    "sg:province":"VT",
    "sg:tags":[
        "repairing",
        "automobile"
    ],
    "wof:name":"Mark's Automotive",
    "wof:placetype":"venue"
},
  "geometry": {"coordinates":[-72.134614,44.352317],"type":"Point"}
}