{
  "type": "Feature",
  "properties": {
    "iso:country":"US",
    "sg:address":"213 Main St",
    "sg:city":"Ludlow",
    "sg:classifiers":[
        {
            "category":"Banks & Credit Unions",
            "subcategory":"Bank",
            "type":"Services"
        }
    ],
    "sg:phone":"+1 802 228 8821",
    "sg:postcode":"05149",
    "sg:province":"VT",
    "sg:website":"www.chittenden.com",
    "wof:name":"Chittenden Bank",
    "wof:placetype":"venue"
},
  "geometry": {"coordinates":[-72.704026,43.395891],"type":"Point"}
}