{
  "type": "Feature",
  "properties": {
    "iso:country":"US",
    "sg:address":"162 Battery St",
    "sg:city":"Burlington",
    "sg:classifiers":[
        {
            "category":"Personal",
            "subcategory":"Beauty Salon",
            "type":"Services"
        }
    ],
    "sg:phone":"+1 802 863 0007",
    "sg:postcode":"05401",
    "sg:province":"VT",
    "sg:tags":[
        "shop"
    ],
    "wof:name":"Hair Studio Assoc",
    "wof:placetype":"venue"
},
  "geometry": {"coordinates":[-73.21853900000001,44.475067],"type":"Point"}
}