{
  "type": "Feature",
  "properties": {
    "iso:country":"US",
    "sg:address":"2273 Sand Rd",
    "sg:city":"Ferrisburgh",
    "sg:classifiers":[
        {
            "category":"Transit Center",
            "subcategory":"Freight",
            "type":"Transportation"
        },
        {
            "category":"Freight",
            "type":"Transportation"
        }
    ],
    "sg:phone":"+1 802 877 1009",
    "sg:postcode":"05456",
    "sg:province":"VT",
    "sg:tags":[
        "local",
        "trucking-motor",
        "trucking"
    ],
    "wof:name":"Titus Trucking",
    "wof:placetype":"venue"
},
  "geometry": {"coordinates":[-73.303327,44.187052],"type":"Point"}
}