{
  "type": "Feature",
  "properties": {
    "iso:country":"US",
    "sg:address":"6 North St",
    "sg:city":"Barre",
    "sg:classifiers":[
        {
            "category":"Health Services",
            "subcategory":"Doctor",
            "type":"Services"
        }
    ],
    "sg:phone":"+1 802 476 3255",
    "sg:postcode":"05641",
    "sg:province":"VT",
    "wof:name":"Kosh George Lamsky Dntl Assoc",
    "wof:placetype":"venue"
},
  "geometry": {"coordinates":[-72.49785799999999,44.197516],"type":"Point"}
}