{
  "type": "Feature",
  "properties": {
    "addr:full":"1444 Prickly Mtn Rd Warren VT 05674",
    "addr:housenumber":"1444",
    "addr:postcode":"05674",
    "addr:street":"Prickly Mtn Rd",
    "iso:country":"US",
    "sg:address":"1444 Prickly Mtn Rd",
    "sg:city":"Warren",
    "sg:classifiers":[
        {
            "category":"Manufacturing",
            "subcategory":"Pottery",
            "type":"Manufacturing & Wholesale Goods"
        }
    ],
    "sg:phone":"+1 802 496 2201",
    "sg:postcode":"05674",
    "sg:province":"VT",
    "sg:tags":[
        "product",
        "mfg"
    ],
    "wof:name":"Broadwing Pottery",
    "wof:placetype":"venue"
},
  "geometry": {"coordinates":[-72.822875,44.071313],"type":"Point"}
}