{
  "type": "Feature",
  "properties": {
    "iso:country":"US",
    "sg:address":"141 Dog River Rd",
    "sg:city":"Montpelier",
    "sg:classifiers":[
        {
            "category":"Retail",
            "subcategory":"Auto Repair",
            "type":"Services"
        }
    ],
    "sg:phone":"+1 802 223 3524",
    "sg:postcode":"05602",
    "sg:province":"VT",
    "sg:tags":[
        "automotive",
        "mechanic"
    ],
    "wof:name":"Stephen Miracle Mechanician",
    "wof:placetype":"venue"
},
  "geometry": {"coordinates":[-72.599746,44.250889],"type":"Point"}
}