{
  "type": "Feature",
  "properties": {
    "iso:country":"US",
    "sg:address":"19 Pearl St",
    "sg:city":"Essex Junction",
    "sg:classifiers":[
        {
            "category":"Building & Trades",
            "subcategory":"Construction",
            "type":"Services"
        }
    ],
    "sg:phone":"+1 802 878 6630",
    "sg:postcode":"05452",
    "sg:province":"VT",
    "sg:tags":[
        "contractor"
    ],
    "wof:name":"Jim Mead Construction Inc",
    "wof:placetype":"venue"
},
  "geometry": {"coordinates":[-73.11462899999999,44.491766],"type":"Point"}
}