{
  "type": "Feature",
  "properties": {
    "addr:full":"124 Woodstock Ave Rutland VT 05701",
    "addr:housenumber":"124",
    "addr:postcode":"05701",
    "addr:street":"Woodstock Ave",
    "iso:country":"US",
    "sg:address":"124 Woodstock Ave",
    "sg:city":"Rutland",
    "sg:classifiers":[
        {
            "category":"Restaurant",
            "type":"Food & Drink"
        }
    ],
    "sg:menulink":"http://www.allmenus.com/vt/rutland/240799-weathervane-seafood/menu/",
    "sg:phone":"+1 802 773 0382",
    "sg:postcode":"05701",
    "sg:province":"VT",
    "sg:tags":[
        "seafood",
        "american"
    ],
    "wof:name":"Weathervane Seafood",
    "wof:placetype":"venue"
},
  "geometry": {"coordinates":[-72.962249,43.614788],"type":"Point"}
}