{
  "type": "Feature",
  "properties": {
    "iso:country":"US",
    "sg:address":"89 Grand Ave",
    "sg:city":"Swanton",
    "sg:classifiers":[
        {
            "category":"Retail",
            "subcategory":"Funeral Services",
            "type":"Services"
        }
    ],
    "sg:phone":"+1 802 868 3331",
    "sg:postcode":"05488",
    "sg:province":"VT",
    "sg:tags":[
        "home"
    ],
    "wof:name":"Kidder Memorial Home",
    "wof:placetype":"venue"
},
  "geometry": {"coordinates":[-73.117757,44.914864],"type":"Point"}
}