{
  "type": "Feature",
  "properties": {
    "addr:full":"3697 State Rte 144 Fair Haven VT 05743",
    "addr:housenumber":"3697",
    "addr:postcode":"05743",
    "addr:street":"State Rte 144;Haven",
    "iso:country":"US",
    "sg:address":"3697 State Rte 144",
    "sg:city":"Fair Haven",
    "sg:classifiers":[
        {
            "category":"Professional",
            "subcategory":"Research",
            "type":"Services"
        }
    ],
    "sg:phone":"+1 802 537 2827",
    "sg:postcode":"05743",
    "sg:province":"VT",
    "sg:tags":[
        "biological"
    ],
    "wof:name":"Binding Site VT Inc",
    "wof:placetype":"venue"
},
  "geometry": {"coordinates":[-73.239801,43.741944],"type":"Point"}
}