{
  "type": "Feature",
  "properties": {
    "addr:full":"27 Ash St White River Jct VT 05001",
    "addr:housenumber":"27",
    "addr:postcode":"05001",
    "addr:street":"Ash St",
    "iso:country":"US",
    "sg:address":"27 Ash St",
    "sg:city":"White River Jct",
    "sg:classifiers":[
        {
            "category":"Building & Trades",
            "subcategory":"Construction",
            "type":"Services"
        }
    ],
    "sg:phone":"+1 802 295 0616",
    "sg:postcode":"05001",
    "sg:province":"VT",
    "sg:tags":[
        "dry wall",
        "contractor"
    ],
    "wof:name":"Upper Valley Drywall Inc",
    "wof:placetype":"venue"
},
  "geometry": {"coordinates":[-72.33178700000001,43.646711],"type":"Point"}
}