{
  "type": "Feature",
  "properties": {
    "iso:country":"US",
    "sg:address":"78 Weathervane Dr",
    "sg:city":"Killington",
    "sg:classifiers":[
        {
            "category":"Travel",
            "subcategory":"Hotels & Motels",
            "type":"Entertainment"
        }
    ],
    "sg:phone":"+1 802 422 4040",
    "sg:postcode":"05751",
    "sg:province":"VT",
    "sg:tags":[
        "lodge",
        "ski"
    ],
    "sg:website":"www.northstarinn.com",
    "wof:name":"North Star Lodge",
    "wof:placetype":"venue"
},
  "geometry": {"coordinates":[-72.78801799999999,43.657708],"type":"Point"}
}