{
  "type": "Feature",
  "properties": {
    "addr:full":"198 Railroad St St Johnsbury VT 05819",
    "addr:housenumber":"198",
    "addr:postcode":"05819",
    "addr:street":"Railroad St",
    "iso:country":"US",
    "sg:address":"198 Railroad St",
    "sg:city":"St Johnsbury",
    "sg:classifiers":[
        {
            "category":"Professional",
            "subcategory":"Research",
            "type":"Services"
        }
    ],
    "sg:phone":"+1 802 434 2715",
    "sg:postcode":"05819",
    "sg:province":"VT",
    "sg:tags":[
        "environmental",
        "ecological"
    ],
    "sg:website":"www.aimgroupvt.com",
    "wof:name":"Aim Group In Environmental",
    "wof:placetype":"venue"
},
  "geometry": {"coordinates":[-72.016671,44.41413],"type":"Point"}
}