{
  "type": "Feature",
  "properties": {
    "iso:country":"US",
    "sg:address":"219 Gore Rd",
    "sg:city":"Highgate Center",
    "sg:classifiers":[
        {
            "category":"Education",
            "subcategory":"School",
            "type":"Public Place"
        }
    ],
    "sg:phone":"+1 802 868 4259",
    "sg:postcode":"05459",
    "sg:province":"VT",
    "wof:name":"Highgate Elementary School",
    "wof:placetype":"venue"
},
  "geometry": {"coordinates":[-73.03728700000001,44.948266],"type":"Point"}
}