{
  "type": "Feature",
  "properties": {
    "iso:country":"US",
    "sg:address":"60 Mercier Dr",
    "sg:city":"Colchester",
    "sg:classifiers":[
        {
            "category":"Manufacturing",
            "subcategory":"Petroleum Products",
            "type":"Manufacturing & Wholesale Goods"
        }
    ],
    "sg:phone":"+1 802 860 7113",
    "sg:postcode":"05446",
    "sg:province":"VT",
    "sg:tags":[
        "salon",
        "construction",
        "beauty",
        "asphalt",
        "mfg"
    ],
    "wof:name":"Black Beauty Driveway Sealing",
    "wof:placetype":"venue"
},
  "geometry": {"coordinates":[-73.24282100000001,44.534937],"type":"Point"}
}