{
  "type": "Feature",
  "properties": {
    "iso:country":"US",
    "sg:address":"30 W Main St",
    "sg:city":"Wilmington",
    "sg:classifiers":[
        {
            "category":"Shopping",
            "subcategory":"Crafts & Fabrics",
            "type":"Retail Goods"
        }
    ],
    "sg:phone":"+1 802 464 7213",
    "sg:postcode":"05363",
    "sg:province":"VT",
    "sg:tags":[
        "shop"
    ],
    "sg:website":"www.norquilt.com",
    "wof:name":"Norton House A Quilter's",
    "wof:placetype":"venue"
},
  "geometry": {"coordinates":[-72.872643,42.869185],"type":"Point"}
}