{
  "type": "Feature",
  "properties": {
    "iso:country":"US",
    "sg:address":"1025 Airport Dr",
    "sg:city":"South Burlington",
    "sg:classifiers":[
        {
            "category":"Organizations",
            "subcategory":"Non-profit Organization",
            "type":"Services"
        }
    ],
    "sg:phone":"+1 802 658 7711",
    "sg:postcode":"05403",
    "sg:province":"VT",
    "sg:tags":[
        "information",
        "alcoholism",
        "treatment"
    ],
    "wof:name":"Centerpoint",
    "wof:placetype":"venue"
},
  "geometry": {"coordinates":[-73.15907799999999,44.473668],"type":"Point"}
}