{
  "type": "Feature",
  "properties": {
    "iso:country":"US",
    "sg:address":"212 Drew Rd",
    "sg:city":"Richford",
    "sg:classifiers":[
        {
            "category":"Farming",
            "subcategory":"Farm",
            "type":"Manufacturing & Wholesale Goods"
        }
    ],
    "sg:phone":"+1 802 848 7644",
    "sg:postcode":"05476",
    "sg:province":"VT",
    "sg:tags":[
        "crop",
        "general"
    ],
    "wof:name":"Wayne Hantubise",
    "wof:placetype":"venue"
},
  "geometry": {"coordinates":[-72.67456199999999,45.013376],"type":"Point"}
}