{
  "type": "Feature",
  "properties": {
    "iso:country":"US",
    "sg:address":"2385 Shelburne Falls Rd",
    "sg:city":"Hinesburg",
    "sg:classifiers":[
        {
            "category":"Professional",
            "subcategory":"Business Services",
            "type":"Services"
        }
    ],
    "sg:phone":"+1 802 482 7473",
    "sg:postcode":"05461",
    "sg:province":"VT",
    "wof:name":"Bella Casa Design",
    "wof:placetype":"venue"
},
  "geometry": {"coordinates":[-73.157414,44.358229],"type":"Point"}
}