{
  "type": "Feature",
  "properties": {
    "addr:full":"34 Fletcher Pl Burlington VT 05401",
    "addr:housenumber":"34",
    "addr:postcode":"05401",
    "addr:street":"Fletcher Pl",
    "iso:country":"US",
    "sg:address":"34 Fletcher Pl",
    "sg:city":"Burlington",
    "sg:classifiers":[
        {
            "category":"Social Services",
            "subcategory":"Child Care",
            "type":"Services"
        }
    ],
    "sg:phone":"+1 802 846 7131",
    "sg:postcode":"05401",
    "sg:province":"VT",
    "wof:name":"Trinity Children's Ctr",
    "wof:placetype":"venue"
},
  "geometry": {"coordinates":[-73.195443,44.481432],"type":"Point"}
}