{
  "type": "Feature",
  "properties": {
    "iso:country":"US",
    "sg:address":"989 Cabot Rd",
    "sg:city":"Marshfield",
    "sg:classifiers":[
        {
            "category":"Professional",
            "subcategory":"Business Services",
            "type":"Services"
        }
    ],
    "sg:phone":"+1 802 426 3435",
    "sg:postcode":"05681",
    "sg:province":"VT",
    "sg:tags":[
        "help",
        "supply"
    ],
    "wof:name":"Ducharme Sr G Lumbering Trckg",
    "wof:placetype":"venue"
},
  "geometry": {"coordinates":[-72.377717,44.432191],"type":"Point"}
}