{
  "type": "Feature",
  "properties": {
    "addr:full":"768 Putney Rd Brattleboro VT 05301",
    "addr:housenumber":"768",
    "addr:postcode":"05301",
    "addr:street":"Putney Rd",
    "iso:country":"US",
    "sg:address":"768 Putney Rd",
    "sg:city":"Brattleboro",
    "sg:classifiers":[
        {
            "category":"Shopping",
            "subcategory":"Stationery & Office Supplies",
            "type":"Retail Goods"
        }
    ],
    "sg:phone":"+1 802 257 5596",
    "sg:postcode":"05301",
    "sg:province":"VT",
    "wof:name":"Staples The Office Superstore",
    "wof:placetype":"venue"
},
  "geometry": {"coordinates":[-72.55834299999999,42.872073],"type":"Point"}
}