{
  "type": "Feature",
  "properties": {
    "iso:country":"US",
    "sg:address":"69 Dover Rd",
    "sg:city":"Williamsville",
    "sg:classifiers":[
        {
            "category":"Insurance",
            "subcategory":"Insurance Agent",
            "type":"Services"
        }
    ],
    "sg:phone":"+1 802 348 6631",
    "sg:postcode":"05362",
    "sg:province":"VT",
    "wof:name":"Druke Insurance",
    "wof:placetype":"venue"
},
  "geometry": {"coordinates":[-72.68132900000001,42.945256],"type":"Point"}
}