{
  "type": "Feature",
  "properties": {
    "addr:full":"820 Western Ave Brattleboro VT 05301",
    "addr:housenumber":"820",
    "addr:postcode":"05301",
    "addr:street":"Western Ave",
    "iso:country":"US",
    "sg:address":"820 Western Ave",
    "sg:city":"Brattleboro",
    "sg:classifiers":[
        {
            "category":"Insurance",
            "subcategory":"Insurance Agent",
            "type":"Services"
        }
    ],
    "sg:phone":"+1 802 257 5555",
    "sg:postcode":"05301",
    "sg:province":"VT",
    "wof:name":"M W Wocell & Assoc Inc",
    "wof:placetype":"venue"
},
  "geometry": {"coordinates":[-72.595669,42.8516],"type":"Point"}
}