{
  "type": "Feature",
  "properties": {
    "iso:country":"US",
    "sg:address":"441 Burpee Rd",
    "sg:city":"Bristol",
    "sg:classifiers":[
        {
            "category":"Social Services",
            "subcategory":"Child Care",
            "type":"Services"
        }
    ],
    "sg:phone":"+1 802 453 4905",
    "sg:postcode":"05443",
    "sg:province":"VT",
    "sg:tags":[
        "day"
    ],
    "wof:name":"Playful Learning Kids Place",
    "wof:placetype":"venue"
},
  "geometry": {"coordinates":[-73.09917299999999,44.13665],"type":"Point"}
}