{
  "type": "Feature",
  "properties": {
    "iso:country":"US",
    "sg:address":"17 Prospect St",
    "sg:city":"Fair Haven",
    "sg:classifiers":[
        {
            "category":"Local Transit",
            "type":"Transportation"
        }
    ],
    "sg:phone":"+1 802 265 3620",
    "sg:postcode":"05743",
    "sg:province":"VT",
    "sg:tags":[
        "ambulance"
    ],
    "wof:name":"Fair Haven Rescue Squad Inc",
    "wof:placetype":"venue"
},
  "geometry": {"coordinates":[-73.26512,43.589912],"type":"Point"}
}