{
  "type": "Feature",
  "properties": {
    "iso:country":"US",
    "sg:address":"898 Pond Rd",
    "sg:city":"Fairfield",
    "sg:classifiers":[
        {
            "category":"Building & Trades",
            "subcategory":"Construction",
            "type":"Services"
        }
    ],
    "sg:phone":"+1 802 827 3857",
    "sg:postcode":"05455",
    "sg:province":"VT",
    "sg:tags":[
        "excavation",
        "contractor"
    ],
    "wof:name":"Stan Combs Utility Excavating",
    "wof:placetype":"venue"
},
  "geometry": {"coordinates":[-72.966217,44.854944],"type":"Point"}
}