{
  "type": "Feature",
  "properties": {
    "iso:country":"US",
    "sg:address":"71 Merchants Row",
    "sg:city":"Rutland",
    "sg:classifiers":[
        {
            "category":"Social Services",
            "type":"Services"
        }
    ],
    "sg:phone":"+1 802 747 4944",
    "sg:postcode":"05701",
    "sg:province":"VT",
    "sg:tags":[
        "youth",
        "organization",
        "center"
    ],
    "sg:website":"www.rutlandbgclub.org",
    "wof:name":"Boys & Girls Club-Rutland Cnty",
    "wof:placetype":"venue"
},
  "geometry": {"coordinates":[-72.979101,43.605641],"type":"Point"}
}