{
  "type": "Feature",
  "properties": {
    "iso:country":"US",
    "sg:address":"16 Berard Dr",
    "sg:city":"South Burlington",
    "sg:classifiers":[
        {
            "category":"Real Estate",
            "subcategory":"Real Estate Agent",
            "type":"Services"
        }
    ],
    "sg:phone":"+1 802 865 3755",
    "sg:postcode":"05403",
    "sg:province":"VT",
    "sg:tags":[
        "management"
    ],
    "wof:name":"All Seasons Property Mgmt",
    "wof:placetype":"venue"
},
  "geometry": {"coordinates":[-73.167602,44.483701],"type":"Point"}
}