{
  "type": "Feature",
  "properties": {
    "iso:country":"US",
    "sg:address":"162 Elm St",
    "sg:city":"Montpelier",
    "sg:classifiers":[
        {
            "category":"Health Services",
            "subcategory":"Health Practitioner",
            "type":"Services"
        }
    ],
    "sg:phone":"+1 802 229 6700",
    "sg:postcode":"05602",
    "sg:province":"VT",
    "wof:name":"Shari Stahl",
    "wof:placetype":"venue"
},
  "geometry": {"coordinates":[-72.57543699999999,44.261663],"type":"Point"}
}