{
  "type": "Feature",
  "properties": {
    "addr:full":"127 E Wells Rd Wells VT 05774",
    "addr:housenumber":"127",
    "addr:postcode":"05774",
    "addr:street":"E Wells Rd",
    "iso:country":"US",
    "sg:address":"127 E Wells Rd",
    "sg:city":"Wells",
    "sg:classifiers":[
        {
            "category":"Organizations",
            "subcategory":"Religious Organization",
            "type":"Services"
        }
    ],
    "sg:phone":"+1 802 325 3038",
    "sg:postcode":"05774",
    "sg:province":"VT",
    "sg:tags":[
        "church"
    ],
    "wof:name":"Wells United Methodist Church",
    "wof:placetype":"venue"
},
  "geometry": {"coordinates":[-73.20137099999999,43.416746],"type":"Point"}
}