{
  "type": "Feature",
  "properties": {
    "iso:country":"US",
    "sg:address":"15 State St",
    "sg:city":"Montpelier",
    "sg:classifiers":[
        {
            "category":"Communications",
            "subcategory":"Television Station",
            "type":"Services"
        }
    ],
    "sg:phone":"+1 802 223 5264",
    "sg:postcode":"05602",
    "sg:province":"VT",
    "sg:tags":[
        "broadcasting",
        "co"
    ],
    "sg:website":"www.wcax.com",
    "wof:name":"Wcax",
    "wof:placetype":"venue"
},
  "geometry": {"coordinates":[-72.576014,44.260318],"type":"Point"}
}