{
  "type": "Feature",
  "properties": {
    "iso:country":"US",
    "sg:address":"126 Washington Ave",
    "sg:city":"Bennington",
    "sg:classifiers":[
        {
            "category":"Freight",
            "type":"Transportation"
        }
    ],
    "sg:phone":"+1 802 442 4808",
    "sg:postcode":"05201",
    "sg:province":"VT",
    "wof:name":"Bennington Bus Station",
    "wof:placetype":"venue"
},
  "geometry": {"coordinates":[-73.199703,42.878093],"type":"Point"}
}