{
  "type": "Feature",
  "properties": {
    "addr:full":"865 Blood Brook Rd Fairlee VT 05045",
    "addr:housenumber":"865",
    "addr:postcode":"05045",
    "addr:street":"Blood Brook Rd",
    "iso:country":"US",
    "sg:address":"865 Blood Brook Rd",
    "sg:city":"Fairlee",
    "sg:classifiers":[
        {
            "category":"Recreation",
            "type":"Entertainment"
        }
    ],
    "sg:phone":"+1 802 333 9090",
    "sg:postcode":"05045",
    "sg:province":"VT",
    "sg:tags":[
        "paint",
        "ball",
        "sport"
    ],
    "wof:name":"Paintball Paranoia LLC",
    "wof:placetype":"venue"
},
  "geometry": {"coordinates":[-72.208798,43.909271],"type":"Point"}
}