{
  "type": "Feature",
  "properties": {
    "iso:country":"US",
    "sg:address":"148 Pine Tree Ln",
    "sg:city":"Jeffersonville",
    "sg:classifiers":[
        {
            "category":"Building & Trades",
            "subcategory":"Cleaning & Sanitation",
            "type":"Services"
        }
    ],
    "sg:phone":"+1 802 644 5648",
    "sg:postcode":"05460",
    "sg:province":"VT",
    "sg:tags":[
        "maintenance"
    ],
    "wof:name":"Blue Sky Window Cleaning",
    "wof:placetype":"venue"
},
  "geometry": {"coordinates":[-72.874426,44.655397],"type":"Point"}
}