{
  "type": "Feature",
  "properties": {
    "addr:full":"556 Main St Castleton VT 05735",
    "addr:housenumber":"556",
    "addr:postcode":"05735",
    "addr:street":"Main St",
    "iso:country":"US",
    "sg:address":"556 Main St",
    "sg:city":"Castleton",
    "sg:classifiers":[
        {
            "category":"Government",
            "subcategory":"Office",
            "type":"Public Place"
        }
    ],
    "sg:phone":"+1 802 468 2212",
    "sg:postcode":"05735",
    "sg:province":"VT",
    "sg:tags":[
        "city"
    ],
    "wof:name":"Castleton Town Clerk",
    "wof:placetype":"venue"
},
  "geometry": {"coordinates":[-73.176852,43.612052],"type":"Point"}
}