{
  "type": "Feature",
  "properties": {
    "iso:country":"US",
    "sg:address":"21 Wolcott St",
    "sg:city":"Hardwick",
    "sg:classifiers":[
        {
            "category":"Real Estate",
            "subcategory":"Real Estate Agent",
            "type":"Services"
        }
    ],
    "sg:phone":"+1 802 472 3338",
    "sg:postcode":"05843",
    "sg:province":"VT",
    "wof:name":"Peter D Watson Agency Inc",
    "wof:placetype":"venue"
},
  "geometry": {"coordinates":[-72.36926200000001,44.505351],"type":"Point"}
}