{
  "type": "Feature",
  "properties": {
    "iso:country":"US",
    "sg:address":"11 Pearl St",
    "sg:city":"Essex Junction",
    "sg:classifiers":[
        {
            "category":"Banks & Credit Unions",
            "subcategory":"Bank",
            "type":"Services"
        }
    ],
    "sg:phone":"+1 802 878 6393",
    "sg:postcode":"05452",
    "sg:province":"VT",
    "sg:tags":[
        "loan",
        "real estate"
    ],
    "wof:name":"Select Mortgage Solutions",
    "wof:placetype":"venue"
},
  "geometry": {"coordinates":[-73.112048,44.490804],"type":"Point"}
}