{
  "type": "Feature",
  "properties": {
    "iso:country":"US",
    "sg:address":"1770 Route 74",
    "sg:city":"Middlebury",
    "sg:classifiers":[
        {
            "category":"Retail",
            "subcategory":"Auto Repair",
            "type":"Services"
        }
    ],
    "sg:phone":"+1 802 462 2658",
    "sg:postcode":"05753",
    "sg:province":"VT",
    "sg:tags":[
        "body",
        "painting",
        "repairing",
        "automobile"
    ],
    "wof:name":"Cornwall Auto Body",
    "wof:placetype":"venue"
},
  "geometry": {"coordinates":[-73.237101,43.943514],"type":"Point"}
}