{
  "type": "Feature",
  "properties": {
    "iso:country":"US",
    "sg:address":"241 N Winooski Ave",
    "sg:city":"Burlington",
    "sg:classifiers":[
        {
            "category":"Social Services",
            "type":"Services"
        }
    ],
    "sg:phone":"+1 802 658 3585",
    "sg:postcode":"05401",
    "sg:province":"VT",
    "sg:tags":[
        "senior",
        "citizen"
    ],
    "wof:name":"Multi Generational Center",
    "wof:placetype":"venue"
},
  "geometry": {"coordinates":[-73.208866,44.487076],"type":"Point"}
}