{
  "type": "Feature",
  "properties": {
    "iso:country":"US",
    "sg:address":"252 Carriage Hill Rd",
    "sg:city":"Brattleboro",
    "sg:classifiers":[
        {
            "category":"Manufacturing",
            "subcategory":"Chemicals & Compounds",
            "type":"Manufacturing & Wholesale Goods"
        }
    ],
    "sg:phone":"+1 802 257 1895",
    "sg:postcode":"05301",
    "sg:province":"VT",
    "sg:tags":[
        "preparation",
        "toilet",
        "mfg"
    ],
    "wof:name":"Green Mountain Essentials",
    "wof:placetype":"venue"
},
  "geometry": {"coordinates":[-72.61028,42.856857],"type":"Point"}
}