{
  "type": "Feature",
  "properties": {
    "iso:country":"US",
    "sg:address":"979 US Hwy 7",
    "sg:city":"Bennington",
    "sg:classifiers":[
        {
            "category":"Travel",
            "subcategory":"Hotels & Motels",
            "type":"Entertainment"
        }
    ],
    "sg:phone":"+1 802 442 6588",
    "sg:postcode":"05201",
    "sg:province":"VT",
    "sg:tags":[
        "inn",
        "cafe"
    ],
    "wof:name":"Apple Valley Inn & Cafe",
    "wof:placetype":"venue"
},
  "geometry": {"coordinates":[-73.204173,42.853483],"type":"Point"}
}