{
  "type": "Feature",
  "properties": {
    "iso:country":"US",
    "sg:address":"251 Luce Hill Rd",
    "sg:city":"Stowe",
    "sg:classifiers":[
        {
            "category":"Building & Trades",
            "subcategory":"Construction",
            "type":"Services"
        }
    ],
    "sg:phone":"+1 802 253 9701",
    "sg:postcode":"05672",
    "sg:province":"VT",
    "sg:tags":[
        "builder",
        "operative"
    ],
    "wof:name":"Stonybrook Inc",
    "wof:placetype":"venue"
},
  "geometry": {"coordinates":[-72.72077400000001,44.473333],"type":"Point"}
}