{
  "type": "Feature",
  "properties": {
    "iso:country":"US",
    "sg:address":"533 Derby St",
    "sg:city":"Island Pond",
    "sg:classifiers":[
        {
            "category":"Travel",
            "subcategory":"Hotels & Motels",
            "type":"Entertainment"
        }
    ],
    "sg:phone":"+1 802 723 5663",
    "sg:postcode":"05846",
    "sg:province":"VT",
    "wof:name":"Clyde River Hotel",
    "wof:placetype":"venue"
},
  "geometry": {"coordinates":[-71.887175,44.807018],"type":"Point"}
}