{
  "type": "Feature",
  "properties": {
    "iso:country":"US",
    "sg:address":"15 Henry St",
    "sg:city":"Bellows Falls",
    "sg:classifiers":[
        {
            "category":"Building & Trades",
            "subcategory":"Construction",
            "type":"Services"
        }
    ],
    "sg:phone":"+1 802 463 9999",
    "sg:postcode":"05101",
    "sg:province":"VT",
    "sg:tags":[
        "house"
    ],
    "wof:name":"Home Doctor",
    "wof:placetype":"venue"
},
  "geometry": {"coordinates":[-72.445881,43.131465],"type":"Point"}
}