{
  "type": "Feature",
  "properties": {
    "iso:country":"US",
    "sg:address":"3270 State Rte 315",
    "sg:city":"Rupert",
    "sg:classifiers":[
        {
            "category":"Travel",
            "subcategory":"Campground",
            "type":"Entertainment"
        }
    ],
    "sg:phone":"+1 802 394 7836",
    "sg:postcode":"05768",
    "sg:province":"VT",
    "sg:website":"www.merckforest.org",
    "wof:name":"Merck Forest Foundation",
    "wof:placetype":"venue"
},
  "geometry": {"coordinates":[-73.164146,43.283973],"type":"Point"}
}