{
  "type": "Feature",
  "properties": {
    "addr:full":"12 State Rte 2b Danville VT 05828",
    "addr:housenumber":"12",
    "addr:postcode":"05828",
    "addr:street":"State Rte 2B",
    "iso:country":"US",
    "sg:address":"12 State Rte 2b",
    "sg:city":"Danville",
    "sg:classifiers":[
        {
            "category":"Shopping",
            "subcategory":"Discount & Variety Stores",
            "type":"Retail Goods"
        }
    ],
    "sg:phone":"+1 802 684 3300",
    "sg:postcode":"05828",
    "sg:province":"VT",
    "sg:tags":[
        "merchandise",
        "general"
    ],
    "wof:name":"Danville Variety",
    "wof:placetype":"venue"
},
  "geometry": {"coordinates":[-72.10661,44.427402],"type":"Point"}
}