{
  "type": "Feature",
  "properties": {
    "iso:country":"US",
    "sg:address":"209 College St",
    "sg:city":"Burlington",
    "sg:classifiers":[
        {
            "category":"Professional",
            "subcategory":"Art Services",
            "type":"Services"
        }
    ],
    "sg:phone":"+1 802 865 5015",
    "sg:postcode":"05401",
    "sg:province":"VT",
    "sg:tags":[
        "commercial",
        "design"
    ],
    "wof:name":"Seek Design Inc",
    "wof:placetype":"venue"
},
  "geometry": {"coordinates":[-73.212566,44.477098],"type":"Point"}
}