{
  "type": "Feature",
  "properties": {
    "iso:country":"US",
    "sg:address":"49 Birchview Exn",
    "sg:city":"Westminster",
    "sg:classifiers":[
        {
            "category":"Autos & Motor Vehicles",
            "subcategory":"Motorcycle Sales",
            "type":"Retail Goods"
        }
    ],
    "sg:phone":"+1 802 463 1475",
    "sg:postcode":"05158",
    "sg:province":"VT",
    "wof:name":"K & K Cycle",
    "wof:placetype":"venue"
},
  "geometry": {"coordinates":[-72.45863900000001,43.103903],"type":"Point"}
}