{
  "type": "Feature",
  "properties": {
    "iso:country":"US",
    "sg:address":"896 Putney Rd",
    "sg:city":"Brattleboro",
    "sg:classifiers":[
        {
            "category":"Home & Garden",
            "subcategory":"Building Materials",
            "type":"Retail Goods"
        }
    ],
    "sg:phone":"+1 802 251 0223",
    "sg:postcode":"05301",
    "sg:province":"VT",
    "sg:tags":[
        "center"
    ],
    "wof:name":"Home Depot",
    "wof:placetype":"venue"
},
  "geometry": {"coordinates":[-72.559175,42.880095],"type":"Point"}
}