{
  "type": "Feature",
  "properties": {
    "iso:country":"US",
    "sg:address":"30 Howland Rd",
    "sg:city":"Brattleboro",
    "sg:classifiers":[
        {
            "category":"Wholesale",
            "subcategory":"Furniture",
            "type":"Manufacturing & Wholesale Goods"
        }
    ],
    "sg:phone":"+1 802 257 4808",
    "sg:postcode":"05301",
    "sg:province":"VT",
    "wof:name":"Leonard Rv",
    "wof:placetype":"venue"
},
  "geometry": {"coordinates":[-72.582509,42.898255],"type":"Point"}
}