{
  "type": "Feature",
  "properties": {
    "iso:country":"US",
    "sg:address":"44 Bramble Ln",
    "sg:city":"Norwich",
    "sg:classifiers":[
        {
            "category":"Professional",
            "subcategory":"Computer Services",
            "type":"Services"
        }
    ],
    "sg:phone":"+1 802 649 8800",
    "sg:postcode":"05055",
    "sg:province":"VT",
    "sg:tags":[
        "comp",
        "design",
        "system",
        "programing",
        "custom"
    ],
    "wof:name":"Ireland Solutions",
    "wof:placetype":"venue"
},
  "geometry": {"coordinates":[-72.339173,43.775199],"type":"Point"}
}