{
  "type": "Feature",
  "properties": {
    "iso:country":"US",
    "sg:address":"29 Holy Cross Rd",
    "sg:city":"Colchester",
    "sg:classifiers":[
        {
            "category":"Building & Trades",
            "subcategory":"Cleaning & Sanitation",
            "type":"Services"
        }
    ],
    "sg:phone":"+1 802 865 6270",
    "sg:postcode":"05446",
    "sg:province":"VT",
    "sg:tags":[
        "ventilating",
        "system"
    ],
    "wof:name":"Supreme Air Care",
    "wof:placetype":"venue"
},
  "geometry": {"coordinates":[-73.25017099999999,44.550808],"type":"Point"}
}