{
  "type": "Feature",
  "properties": {
    "addr:full":"2025 Waterbury Rd Stowe VT 05672",
    "addr:housenumber":"2025",
    "addr:postcode":"05672",
    "addr:street":"Waterbury Rd",
    "iso:country":"US",
    "sg:address":"2025 Waterbury Rd",
    "sg:city":"Stowe",
    "sg:classifiers":[
        {
            "category":"Building & Trades",
            "subcategory":"Construction",
            "type":"Services"
        }
    ],
    "sg:phone":"+1 802 253 2976",
    "sg:postcode":"05672",
    "sg:province":"VT",
    "sg:tags":[
        "maker",
        "cabinet"
    ],
    "wof:name":"Willard's Workshop",
    "wof:placetype":"venue"
},
  "geometry": {"coordinates":[-72.71708700000001,44.427506],"type":"Point"}
}