{
  "type": "Feature",
  "properties": {
    "addr:full":"139 Cross Rd Lake Elmore VT 05657",
    "addr:housenumber":"139",
    "addr:postcode":"05657",
    "addr:street":"Cross Rd",
    "iso:country":"US",
    "sg:address":"139 Cross Rd",
    "sg:city":"Lake Elmore",
    "sg:classifiers":[
        {
            "category":"Retail",
            "subcategory":"Repair Shop",
            "type":"Services"
        }
    ],
    "sg:phone":"+1 802 888 3229",
    "sg:postcode":"05657",
    "sg:province":"VT",
    "sg:tags":[
        "upholsterer"
    ],
    "wof:name":"Linda's Upholstery",
    "wof:placetype":"venue"
},
  "geometry": {"coordinates":[-72.512602,44.500705],"type":"Point"}
}