{
  "type": "Feature",
  "properties": {
    "addr:full":"221 Maple St White River Junction VT 05001",
    "addr:housenumber":"221",
    "addr:postcode":"05001",
    "addr:street":"Maple St",
    "iso:country":"US",
    "sg:address":"221 Maple St",
    "sg:city":"White River Junction",
    "sg:classifiers":[
        {
            "category":"Health Services",
            "subcategory":"Chiropractor",
            "type":"Services"
        }
    ],
    "sg:phone":"+1 802 280 2225",
    "sg:postcode":"05001",
    "sg:province":"VT",
    "wof:name":"McDermott Chiropractic",
    "wof:placetype":"venue"
},
  "geometry": {"coordinates":[-72.318195,43.651713],"type":"Point"}
}