{
  "type": "Feature",
  "properties": {
    "iso:country":"US",
    "sg:address":"114 River St",
    "sg:city":"Montpelier",
    "sg:classifiers":[
        {
            "category":"Shopping",
            "subcategory":"Jewelry",
            "type":"Retail Goods"
        }
    ],
    "sg:phone":"+1 802 223 1354",
    "sg:postcode":"05602",
    "sg:province":"VT",
    "sg:tags":[
        "jeweler"
    ],
    "sg:website":"www.beading.com",
    "wof:name":"South Pacific Wholesale",
    "wof:placetype":"venue"
},
  "geometry": {"coordinates":[-72.56283999999999,44.248979],"type":"Point"}
}