{
  "type": "Feature",
  "properties": {
    "iso:country":"US",
    "sg:address":"1321 Main St",
    "sg:city":"Sheldon",
    "sg:classifiers":[
        {
            "category":"Building & Trades",
            "subcategory":"Construction",
            "type":"Services"
        }
    ],
    "sg:phone":"+1 802 933 9663",
    "sg:postcode":"05483",
    "sg:province":"VT",
    "sg:tags":[
        "resurfacing",
        "floor",
        "laying",
        "refinishing",
        "contractor"
    ],
    "wof:name":"Abbott Matthew A Wood Floors",
    "wof:placetype":"venue"
},
  "geometry": {"coordinates":[-72.947097,44.88522],"type":"Point"}
}