{
  "type": "Feature",
  "properties": {
    "addr:full":"117 Main St Plainfield VT 05667",
    "addr:housenumber":"117",
    "addr:postcode":"05667",
    "addr:street":"Main St",
    "iso:country":"US",
    "sg:address":"117 Main St",
    "sg:city":"Plainfield",
    "sg:classifiers":[
        {
            "category":"Building & Trades",
            "subcategory":"Cleaning & Sanitation",
            "type":"Services"
        }
    ],
    "sg:phone":"+1 802 454 1776",
    "sg:postcode":"05667",
    "sg:province":"VT",
    "sg:tags":[
        "fireplace",
        "chimney"
    ],
    "wof:name":"Chimney Works",
    "wof:placetype":"venue"
},
  "geometry": {"coordinates":[-72.419917,44.27784],"type":"Point"}
}