{
  "type": "Feature",
  "properties": {
    "addr:full":"110 Main St Brattleboro VT 05301",
    "addr:housenumber":"110",
    "addr:postcode":"05301",
    "addr:street":"Main St",
    "iso:country":"US",
    "sg:address":"110 Main St",
    "sg:city":"Brattleboro",
    "sg:classifiers":[
        {
            "category":"Organizations",
            "subcategory":"Non-profit Organization",
            "type":"Services"
        },
        {
            "category":"Education",
            "subcategory":"Special Training",
            "type":"Public Place"
        }
    ],
    "sg:phone":"+1 802 254 6590",
    "sg:postcode":"05301",
    "sg:province":"VT",
    "sg:tags":[
        "educational",
        "social"
    ],
    "sg:website":"www.gmtchealth.org",
    "wof:name":"Green Mountain Training Center",
    "wof:placetype":"venue"
},
  "geometry": {"coordinates":[-72.55842199999999,42.852755],"type":"Point"}
}