{
  "type": "Feature",
  "properties": {
    "iso:country":"US",
    "sg:address":"362 Middle Rd",
    "sg:city":"Colchester",
    "sg:classifiers":[
        {
            "category":"Real Estate",
            "subcategory":"Real Estate Operator",
            "type":"Services"
        }
    ],
    "sg:phone":"+1 802 879 4369",
    "sg:postcode":"05446",
    "sg:province":"VT",
    "sg:tags":[
        "building",
        "nonresidential"
    ],
    "wof:name":"Lankin Properties",
    "wof:placetype":"venue"
},
  "geometry": {"coordinates":[-73.139848,44.579888],"type":"Point"}
}