{
  "type": "Feature",
  "properties": {
    "addr:full":"51 S Main St Northfield VT 05663",
    "addr:housenumber":"51",
    "addr:postcode":"05663",
    "addr:street":"S Main St",
    "iso:country":"US",
    "sg:address":"51 S Main St",
    "sg:city":"Northfield",
    "sg:classifiers":[
        {
            "category":"Government",
            "subcategory":"Fire Station",
            "type":"Public Place"
        }
    ],
    "sg:phone":"+1 802 485 8443",
    "sg:postcode":"05663",
    "sg:province":"VT",
    "sg:tags":[
        "department"
    ],
    "wof:name":"Fire Chief",
    "wof:placetype":"venue"
},
  "geometry": {"coordinates":[-72.657313,44.141726],"type":"Point"}
}