{
  "type": "Feature",
  "properties": {
    "iso:country":"US",
    "sg:address":"16 School St",
    "sg:city":"Orleans",
    "sg:classifiers":[
        {
            "category":"Manufacturing",
            "subcategory":"Lumber",
            "type":"Manufacturing & Wholesale Goods"
        }
    ],
    "sg:phone":"+1 802 754 2142",
    "sg:postcode":"05860",
    "sg:province":"VT",
    "sg:tags":[
        "forestry"
    ],
    "wof:name":"Peter Jarry",
    "wof:placetype":"venue"
},
  "geometry": {"coordinates":[-72.20157399999999,44.809466],"type":"Point"}
}