{
  "type": "Feature",
  "properties": {
    "iso:country":"US",
    "sg:address":"1282 Main St",
    "sg:city":"Fairfax",
    "sg:classifiers":[
        {
            "category":"Health Services",
            "subcategory":"Health Practitioner",
            "type":"Services"
        }
    ],
    "sg:phone":"+1 802 849 9308",
    "sg:postcode":"05454",
    "sg:province":"VT",
    "sg:tags":[
        "therapist",
        "physical"
    ],
    "wof:name":"Fairfax Family Physical Thrpy",
    "wof:placetype":"venue"
},
  "geometry": {"coordinates":[-73.02195399999999,44.676365],"type":"Point"}
}