{
  "type": "Feature",
  "properties": {
    "iso:country":"US",
    "sg:address":"166 Ferguson Ave",
    "sg:city":"Burlington",
    "sg:classifiers":[
        {
            "category":"Health Services",
            "subcategory":"Health Practitioner",
            "type":"Services"
        }
    ],
    "sg:phone":"+1 802 658 9428",
    "sg:postcode":"05401",
    "sg:province":"VT",
    "wof:name":"Barbara Collins",
    "wof:placetype":"venue"
},
  "geometry": {"coordinates":[-73.209068,44.454156],"type":"Point"}
}