{
  "type": "Feature",
  "properties": {
    "iso:country":"US",
    "sg:address":"316 US Hwy 2",
    "sg:city":"South Hero",
    "sg:classifiers":[
        {
            "category":"Food & Beverages",
            "subcategory":"Candy",
            "type":"Retail Goods"
        }
    ],
    "sg:phone":"+1 802 372 4654",
    "sg:postcode":"05486",
    "sg:province":"VT",
    "sg:tags":[
        "confectionery"
    ],
    "wof:name":"Vermont Nut Free Chocolates",
    "wof:placetype":"venue"
},
  "geometry": {"coordinates":[-73.304039,44.645706],"type":"Point"}
}