{
  "type": "Feature",
  "properties": {
    "iso:country":"US",
    "sg:address":"45 Commerce Ave",
    "sg:city":"South Burlington",
    "sg:classifiers":[
        {
            "category":"Building & Trades",
            "subcategory":"Construction",
            "type":"Services"
        }
    ],
    "sg:phone":"+1 802 863 0027",
    "sg:postcode":"05403",
    "sg:province":"VT",
    "sg:tags":[
        "insulation",
        "heat",
        "contractor"
    ],
    "wof:name":"North Country Mechanical Inc",
    "wof:placetype":"venue"
},
  "geometry": {"coordinates":[-73.15974900000001,44.482868],"type":"Point"}
}