{
  "type": "Feature",
  "properties": {
    "iso:country":"US",
    "sg:address":"9679 County Rd",
    "sg:city":"Calais",
    "sg:classifiers":[
        {
            "category":"Home & Garden",
            "subcategory":"Furniture",
            "type":"Retail Goods"
        }
    ],
    "sg:phone":"+1 802 229 4985",
    "sg:postcode":"05648",
    "sg:province":"VT",
    "sg:tags":[
        "store"
    ],
    "wof:name":"Maple Corner Woodworks",
    "wof:placetype":"venue"
},
  "geometry": {"coordinates":[-72.496101,44.373798],"type":"Point"}
}