{
  "type": "Feature",
  "properties": {
    "addr:full":"212 Centerville Rd Hyde Park VT 05655",
    "addr:housenumber":"212",
    "addr:postcode":"05655",
    "addr:street":"Centerville Rd",
    "iso:country":"US",
    "sg:address":"212 Centerville Rd",
    "sg:city":"Hyde Park",
    "sg:classifiers":[
        {
            "category":"Government",
            "subcategory":"Fire Station",
            "type":"Public Place"
        }
    ],
    "sg:phone":"+1 802 888 3694",
    "sg:postcode":"05655",
    "sg:province":"VT",
    "sg:tags":[
        "department"
    ],
    "wof:name":"Fire Dept",
    "wof:placetype":"venue"
},
  "geometry": {"coordinates":[-72.60380499999999,44.598679],"type":"Point"}
}