{
  "type": "Feature",
  "properties": {
    "iso:country":"US",
    "sg:address":"161 Elm St",
    "sg:city":"Newport",
    "sg:classifiers":[
        {
            "category":"Organizations",
            "subcategory":"Religious Organization",
            "type":"Services"
        }
    ],
    "sg:phone":"+1 802 334 2628",
    "sg:postcode":"05855",
    "sg:province":"VT",
    "wof:name":"Church of Nazarene",
    "wof:placetype":"venue"
},
  "geometry": {"coordinates":[-72.19893999999999,44.945879],"type":"Point"}
}