{
  "type": "Feature",
  "properties": {
    "iso:country":"US",
    "sg:address":"280 State Rte 110",
    "sg:city":"Chelsea",
    "sg:classifiers":[
        {
            "category":"Farming",
            "subcategory":"Dairy Farm",
            "type":"Manufacturing & Wholesale Goods"
        }
    ],
    "sg:phone":"+1 802 685 3123",
    "sg:postcode":"05038",
    "sg:province":"VT",
    "wof:name":"Horizon Organic",
    "wof:placetype":"venue"
},
  "geometry": {"coordinates":[-72.44811,43.986259],"type":"Point"}
}