{
  "type": "Feature",
  "properties": {
    "addr:full":"884 Garvin Hill Rd Greensboro VT 05841",
    "addr:housenumber":"884",
    "addr:postcode":"05841",
    "addr:street":"Garvin Hill Rd",
    "iso:country":"US",
    "sg:address":"884 Garvin Hill Rd",
    "sg:city":"Greensboro",
    "sg:classifiers":[
        {
            "category":"Farming",
            "subcategory":"Farm",
            "type":"Manufacturing & Wholesale Goods"
        }
    ],
    "sg:phone":"+1 802 533 2566",
    "sg:postcode":"05841",
    "sg:province":"VT",
    "sg:tags":[
        "crop",
        "general"
    ],
    "wof:name":"Jasper Hill Farm",
    "wof:placetype":"venue"
},
  "geometry": {"coordinates":[-72.25899,44.595694],"type":"Point"}
}