{
  "type": "Feature",
  "properties": {
    "addr:full":"116 Royalton Tpke South Royalton VT 05068",
    "addr:housenumber":"116",
    "addr:postcode":"05068",
    "addr:street":"Royalton Tpke South",
    "iso:country":"US",
    "sg:address":"116 Royalton Tpke",
    "sg:city":"South Royalton",
    "sg:classifiers":[
        {
            "category":"Farming",
            "subcategory":"Dairy Farm",
            "type":"Manufacturing & Wholesale Goods"
        }
    ],
    "sg:phone":"+1 802 763 7095",
    "sg:postcode":"05068",
    "sg:province":"VT",
    "sg:tags":[
        "field",
        "crop"
    ],
    "wof:name":"William Benoit",
    "wof:placetype":"venue"
},
  "geometry": {"coordinates":[-72.59487,43.723862],"type":"Point"}
}