{
  "type": "Feature",
  "properties": {
    "addr:full":"2 Carmichael St Essex Junction VT 05452",
    "addr:housenumber":"2",
    "addr:postcode":"05452",
    "addr:street":"Carmichael St",
    "iso:country":"US",
    "sg:address":"2 Carmichael St",
    "sg:city":"Essex Junction",
    "sg:classifiers":[
        {
            "category":"Restaurant",
            "type":"Food & Drink"
        }
    ],
    "sg:menulink":"http://www.allmenus.com/vt/essex/139068-quiznos-sub/menu/",
    "sg:phone":"+1 802 879 1009",
    "sg:postcode":"05452",
    "sg:province":"VT",
    "sg:tags":[
        "wrap",
        "american",
        "sandwich"
    ],
    "wof:name":"Quiznos Sub",
    "wof:placetype":"venue"
},
  "geometry": {"coordinates":[-73.085655,44.508033],"type":"Point"}
}