{
  "type": "Feature",
  "properties": {
    "iso:country":"US",
    "sg:address":"143 Fairground Rd",
    "sg:city":"Bradford",
    "sg:classifiers":[
        {
            "category":"Education",
            "subcategory":"School",
            "type":"Public Place"
        }
    ],
    "sg:phone":"+1 802 222 4077",
    "sg:postcode":"05033",
    "sg:province":"VT",
    "wof:name":"Bradford Elementary School",
    "wof:placetype":"venue"
},
  "geometry": {"coordinates":[-72.121461,44.002815],"type":"Point"}
}