{
  "type": "Feature",
  "properties": {
    "addr:full":"135 Strongs Ave Rutland VT 05701",
    "addr:housenumber":"135",
    "addr:postcode":"05701",
    "addr:street":"Strongs Ave",
    "iso:country":"US",
    "sg:address":"135 Strongs Ave",
    "sg:city":"Rutland",
    "sg:classifiers":[
        {
            "category":"Retail",
            "subcategory":"Auto Rental",
            "type":"Services"
        }
    ],
    "sg:phone":"+1 802 773 3054",
    "sg:postcode":"05701",
    "sg:province":"VT",
    "sg:tags":[
        "renting",
        "truck",
        "leasing"
    ],
    "wof:name":"Budget Truck Rental",
    "wof:placetype":"venue"
},
  "geometry": {"coordinates":[-72.976243,43.603215],"type":"Point"}
}