{
  "type": "Feature",
  "properties": {
    "addr:full":"463 West St Rutland VT 05701",
    "addr:housenumber":"463",
    "addr:postcode":"05701",
    "addr:street":"West St",
    "iso:country":"US",
    "sg:address":"463 West St",
    "sg:city":"Rutland",
    "sg:classifiers":[
        {
            "category":"Home & Garden",
            "subcategory":"Home Furnishings",
            "type":"Retail Goods"
        }
    ],
    "sg:phone":"+1 802 747 9950",
    "sg:postcode":"05701",
    "sg:province":"VT",
    "wof:name":"Stove Depot",
    "wof:placetype":"venue"
},
  "geometry": {"coordinates":[-73.00348099999999,43.604276],"type":"Point"}
}