{
  "type": "Feature",
  "properties": {
    "iso:country":"US",
    "sg:address":"80 Tayer Ln",
    "sg:city":"Waterbury",
    "sg:classifiers":[
        {
            "category":"Building & Trades",
            "subcategory":"Cleaning & Sanitation",
            "type":"Services"
        }
    ],
    "sg:phone":"+1 802 244 8742",
    "sg:postcode":"05677",
    "sg:province":"VT",
    "sg:tags":[
        "property",
        "maintenance"
    ],
    "wof:name":"Lawn Rangers",
    "wof:placetype":"venue"
},
  "geometry": {"coordinates":[-72.722734,44.414496],"type":"Point"}
}