{
  "type": "Feature",
  "properties": {
    "iso:country":"US",
    "sg:address":"39 S Depot St",
    "sg:city":"Ludlow",
    "sg:classifiers":[
        {
            "category":"Government",
            "subcategory":"Office",
            "type":"Public Place"
        }
    ],
    "sg:phone":"+1 802 228 7206",
    "sg:postcode":"05149",
    "sg:province":"VT",
    "sg:tags":[
        "village"
    ],
    "wof:name":"Listers Town Building",
    "wof:placetype":"venue"
},
  "geometry": {"coordinates":[-72.70110699999999,43.395786],"type":"Point"}
}