{
  "type": "Feature",
  "properties": {
    "iso:country":"US",
    "sg:address":"1330 Main St",
    "sg:city":"St Johnsbury",
    "sg:classifiers":[
        {
            "category":"Professional",
            "subcategory":"Lawyer & Legal Services",
            "type":"Services"
        }
    ],
    "sg:phone":"+1 802 748 8958",
    "sg:postcode":"05819",
    "sg:province":"VT",
    "sg:tags":[
        "attorney"
    ],
    "wof:name":"Zuccaro Willis & Bent",
    "wof:placetype":"venue"
},
  "geometry": {"coordinates":[-72.019777,44.420739],"type":"Point"}
}