{
  "type": "Feature",
  "properties": {
    "addr:full":"2434 Depot St Manchester Ctr VT 05255",
    "addr:housenumber":"2434",
    "addr:postcode":"05255",
    "addr:street":"Depot St",
    "iso:country":"US",
    "sg:address":"2434 Depot St",
    "sg:city":"Manchester Ctr",
    "sg:classifiers":[
        {
            "category":"Professional",
            "subcategory":"Printing & Photocopies",
            "type":"Services"
        }
    ],
    "sg:phone":"+1 802 362 3149",
    "sg:postcode":"05255",
    "sg:province":"VT",
    "sg:tags":[
        "duplicating",
        "copying"
    ],
    "sg:website":"www.historicalpages.com",
    "wof:name":"Homes Magazine Inc",
    "wof:placetype":"venue"
},
  "geometry": {"coordinates":[-73.012372,43.179384],"type":"Point"}
}