{
  "type": "Feature",
  "properties": {
    "iso:country":"US",
    "sg:address":"82 Park Rd",
    "sg:city":"Middlebury",
    "sg:classifiers":[
        {
            "category":"Professional",
            "subcategory":"Management & Consulting",
            "type":"Services"
        }
    ],
    "sg:phone":"+1 802 388 1235",
    "sg:postcode":"05753",
    "sg:province":"VT",
    "sg:tags":[
        "construction"
    ],
    "sg:website":"www.barrandbarr.com",
    "wof:name":"Barr & Barr Inc",
    "wof:placetype":"venue"
},
  "geometry": {"coordinates":[-73.17038100000001,44.035118],"type":"Point"}
}