{
  "type": "Feature",
  "properties": {
    "addr:full":"79 Weaver St Winooski VT 05404",
    "addr:housenumber":"79",
    "addr:postcode":"05404",
    "addr:street":"Weaver St",
    "iso:country":"US",
    "sg:address":"79 Weaver St",
    "sg:city":"Winooski",
    "sg:classifiers":[
        {
            "category":"Social Services",
            "type":"Services"
        }
    ],
    "sg:phone":"+1 802 655 0006",
    "sg:postcode":"05404",
    "sg:province":"VT",
    "sg:tags":[
        "agency",
        "adoption"
    ],
    "sg:website":"www.vtcas.org",
    "wof:name":"Vermont Children's Aid Society",
    "wof:placetype":"venue"
},
  "geometry": {"coordinates":[-73.187939,44.492161],"type":"Point"}
}