{
  "type": "Feature",
  "properties": {
    "iso:country":"US",
    "sg:address":"15 Shadow Ln",
    "sg:city":"Hinesburg",
    "sg:classifiers":[
        {
            "category":"Building & Trades",
            "subcategory":"Construction",
            "type":"Services"
        }
    ],
    "sg:phone":"+1 802 482 3024",
    "sg:postcode":"05461",
    "sg:province":"VT",
    "sg:tags":[
        "general",
        "contractor"
    ],
    "wof:name":"B & H Construction Inc",
    "wof:placetype":"venue"
},
  "geometry": {"coordinates":[-73.091886,44.368934],"type":"Point"}
}