{
  "type": "Feature",
  "properties": {
    "iso:country":"US",
    "sg:address":"254 Wilkins St",
    "sg:city":"Morrisville",
    "sg:classifiers":[
        {
            "category":"Manufacturing",
            "subcategory":"Metals",
            "type":"Manufacturing & Wholesale Goods"
        }
    ],
    "sg:phone":"+1 802 888 0033",
    "sg:postcode":"05655",
    "sg:province":"VT",
    "wof:name":"Custom Metal Fabricators",
    "wof:placetype":"venue"
},
  "geometry": {"coordinates":[-72.602946,44.569328],"type":"Point"}
}