{
  "type": "Feature",
  "properties": {
    "iso:country":"US",
    "sg:address":"18A Chaplin Ave",
    "sg:city":"Rutland",
    "sg:classifiers":[
        {
            "category":"Autos & Motor Vehicles",
            "subcategory":"Auto Supplies",
            "type":"Retail Goods"
        },
        {
            "category":"Retail",
            "subcategory":"Auto Repair",
            "type":"Services"
        }
    ],
    "sg:phone":"+1 802 775 3777",
    "sg:postcode":"05701",
    "sg:province":"VT",
    "sg:tags":[
        "body",
        "repairing",
        "automobile",
        "removal",
        "truck",
        "dent",
        "painting"
    ],
    "sg:website":"http://www.parkersauto.com",
    "wof:name":"Parker's Classic Auto Works",
    "wof:placetype":"venue"
},
  "geometry": {"coordinates":[-72.96924,43.594117],"type":"Point"}
}