{
  "type": "Feature",
  "properties": {
    "iso:country":"US",
    "sg:address":"326 Bluff Rd",
    "sg:city":"Newport",
    "sg:classifiers":[
        {
            "category":"Manufacturing",
            "subcategory":"Tools & Machinery",
            "type":"Manufacturing & Wholesale Goods"
        }
    ],
    "sg:phone":"+1 802 334 1588",
    "sg:postcode":"05855",
    "sg:province":"VT",
    "sg:tags":[
        "equipment",
        "sewing",
        "mfg"
    ],
    "wof:name":"Tex Fab",
    "wof:placetype":"venue"
},
  "geometry": {"coordinates":[-72.201888,44.951099],"type":"Point"}
}