{
  "type": "Feature",
  "properties": {
    "addr:full":"195 State Rte 242 Montgomery Ctr VT 05471",
    "addr:housenumber":"195",
    "addr:postcode":"05471",
    "addr:street":"State Rte 242 Montgomery",
    "iso:country":"US",
    "sg:address":"195 State Rte 242",
    "sg:city":"Montgomery Ctr",
    "sg:classifiers":[
        {
            "category":"Travel",
            "subcategory":"Hotels & Motels",
            "type":"Entertainment"
        }
    ],
    "sg:phone":"+1 802 326 3232",
    "sg:postcode":"05471",
    "sg:province":"VT",
    "sg:tags":[
        "breakfast",
        "accommodation",
        "bed"
    ],
    "sg:website":"www.englishroseinnvermont.com",
    "wof:name":"English Rose Inn",
    "wof:placetype":"venue"
},
  "geometry": {"coordinates":[-72.607257,44.878836],"type":"Point"}
}