{
  "type": "Feature",
  "properties": {
    "iso:country":"US",
    "sg:address":"39 Bombardier Rd",
    "sg:city":"Milton",
    "sg:classifiers":[
        {
            "category":"Education",
            "subcategory":"Library",
            "type":"Public Place"
        }
    ],
    "sg:phone":"+1 802 893 4644",
    "sg:postcode":"05468",
    "sg:province":"VT",
    "wof:name":"Milton Public Library",
    "wof:placetype":"venue"
},
  "geometry": {"coordinates":[-73.122851,44.619148],"type":"Point"}
}