{
  "type": "Feature",
  "properties": {
    "iso:country":"US",
    "sg:address":"1024 State Rte 30",
    "sg:city":"Middlebury",
    "sg:classifiers":[
        {
            "category":"Home & Garden",
            "subcategory":"Home Furnishings",
            "type":"Retail Goods"
        }
    ],
    "sg:phone":"+1 802 462 2842",
    "sg:postcode":"05753",
    "sg:province":"VT",
    "sg:tags":[
        "pottery"
    ],
    "wof:name":"Crystal Pottery",
    "wof:placetype":"venue"
},
  "geometry": {"coordinates":[-73.201908,43.984157],"type":"Point"}
}