{
  "type": "Feature",
  "properties": {
    "iso:country":"US",
    "sg:address":"1480 Paine Tpke N",
    "sg:city":"Berlin",
    "sg:classifiers":[
        {
            "category":"Government",
            "subcategory":"Office",
            "type":"Public Place"
        }
    ],
    "sg:phone":"+1 802 229 2009",
    "sg:postcode":"05602",
    "sg:province":"VT",
    "sg:tags":[
        "govt",
        "city"
    ],
    "wof:name":"Water Treatment Plant Mntplr",
    "wof:placetype":"venue"
},
  "geometry": {"coordinates":[-72.56317799999999,44.233174],"type":"Point"}
}