{
  "type": "Feature",
  "properties": {
    "addr:full":"79 Center Rd Essex Junction VT 05452",
    "addr:housenumber":"79",
    "addr:postcode":"05452",
    "addr:street":"Center Rd",
    "iso:country":"US",
    "sg:address":"79 Center Rd",
    "sg:city":"Essex Junction",
    "sg:classifiers":[
        {
            "category":"Building & Trades",
            "subcategory":"Landscaping Services",
            "type":"Services"
        }
    ],
    "sg:phone":"+1 802 878 8691",
    "sg:postcode":"05452",
    "sg:province":"VT",
    "sg:tags":[
        "lawn",
        "maintenance",
        "grounds"
    ],
    "wof:name":"James Lawn Care Plus",
    "wof:placetype":"venue"
},
  "geometry": {"coordinates":[-73.059569,44.511769],"type":"Point"}
}