{
  "type": "Feature",
  "properties": {
    "iso:country":"US",
    "sg:address":"3 Court St",
    "sg:city":"Middlebury",
    "sg:classifiers":[
        {
            "category":"Organizations",
            "subcategory":"Membership Organization",
            "type":"Services"
        }
    ],
    "sg:phone":"+1 802 388 3942",
    "sg:postcode":"05753",
    "sg:province":"VT",
    "sg:website":"www.vermontwomensfund.org",
    "wof:name":"Vermont Women's Fund",
    "wof:placetype":"venue"
},
  "geometry": {"coordinates":[-73.165424,44.013802],"type":"Point"}
}