{
  "type": "Feature",
  "properties": {
    "iso:country":"US",
    "sg:address":"1337 State Rte 10",
    "sg:city":"Chester",
    "sg:classifiers":[
        {
            "category":"Food & Beverages",
            "subcategory":"Bakery",
            "type":"Retail Goods"
        }
    ],
    "sg:phone":"+1 802 875 1880",
    "sg:postcode":"05143",
    "sg:province":"VT",
    "sg:tags":[
        "baker"
    ],
    "wof:name":"Mystic Moose Cheesecakes",
    "wof:placetype":"venue"
},
  "geometry": {"coordinates":[-72.584349,43.327349],"type":"Point"}
}