{
  "type": "Feature",
  "properties": {
    "iso:country":"US",
    "sg:address":"361 E Allen St",
    "sg:city":"Winooski",
    "sg:classifiers":[
        {
            "category":"Building & Trades",
            "subcategory":"Construction",
            "type":"Services"
        }
    ],
    "sg:phone":"+1 802 655 3664",
    "sg:postcode":"05404",
    "sg:province":"VT",
    "sg:tags":[
        "dry wall",
        "contractor"
    ],
    "wof:name":"Chuck's Dry Wall",
    "wof:placetype":"venue"
},
  "geometry": {"coordinates":[-73.172954,44.493398],"type":"Point"}
}