{
  "type": "Feature",
  "properties": {
    "iso:country":"US",
    "sg:address":"359 Main St",
    "sg:city":"Bennington",
    "sg:classifiers":[
        {
            "category":"Professional",
            "subcategory":"Management & Consulting",
            "type":"Services"
        }
    ],
    "sg:phone":"+1 802 447 2566",
    "sg:postcode":"05201",
    "sg:province":"VT",
    "sg:tags":[
        "consultant",
        "business"
    ],
    "wof:name":"Matteson Associates",
    "wof:placetype":"venue"
},
  "geometry": {"coordinates":[-73.197981,42.8787],"type":"Point"}
}