{
  "type": "Feature",
  "properties": {
    "iso:country":"US",
    "sg:address":"414 Old Guilford Rd",
    "sg:city":"Brattleboro",
    "sg:classifiers":[
        {
            "category":"Professional",
            "subcategory":"Computer Services",
            "type":"Services"
        }
    ],
    "sg:phone":"+1 802 254 9364",
    "sg:postcode":"05301",
    "sg:province":"VT",
    "sg:tags":[
        "website",
        "design"
    ],
    "wof:name":"Distinctive Webs",
    "wof:placetype":"venue"
},
  "geometry": {"coordinates":[-72.56494000000001,42.826938],"type":"Point"}
}