{
  "type": "Feature",
  "properties": {
    "addr:full":"426 Plains Rd Pittsford VT 05763",
    "addr:housenumber":"426",
    "addr:postcode":"05763",
    "addr:street":"Plains Rd",
    "iso:country":"US",
    "sg:address":"426 Plains Rd",
    "sg:city":"Pittsford",
    "sg:classifiers":[
        {
            "category":"Government",
            "subcategory":"Office",
            "type":"Public Place"
        }
    ],
    "sg:phone":"+1 802 483 2275",
    "sg:postcode":"05763",
    "sg:province":"VT",
    "sg:tags":[
        "village"
    ],
    "wof:name":"Pittsford Board Of Listers",
    "wof:placetype":"venue"
},
  "geometry": {"coordinates":[-73.02787600000001,43.716142],"type":"Point"}
}