{
  "type": "Feature",
  "properties": {
    "iso:country":"US",
    "sg:address":"1 Catherine St",
    "sg:city":"St Albans",
    "sg:classifiers":[
        {
            "category":"Manufacturing",
            "subcategory":"Printing",
            "type":"Manufacturing & Wholesale Goods"
        }
    ],
    "sg:phone":"+1 802 524 2488",
    "sg:postcode":"05478",
    "sg:province":"VT",
    "sg:tags":[
        "printer"
    ],
    "wof:name":"Mountain View Printing",
    "wof:placetype":"venue"
},
  "geometry": {"coordinates":[-73.085758,44.810888],"type":"Point"}
}