{
  "type": "Feature",
  "properties": {
    "iso:country":"US",
    "sg:address":"39 Edson Hill Rd",
    "sg:city":"Stowe",
    "sg:classifiers":[
        {
            "category":"Travel",
            "subcategory":"Hotels & Motels",
            "type":"Entertainment"
        }
    ],
    "sg:phone":"+1 802 253 7223",
    "sg:postcode":"05672",
    "sg:province":"VT",
    "sg:tags":[
        "resort",
        "center",
        "skiing"
    ],
    "wof:name":"Round Hearth Lodge At Stowe",
    "wof:placetype":"venue"
},
  "geometry": {"coordinates":[-72.729114,44.489557],"type":"Point"}
}