{
  "type": "Feature",
  "properties": {
    "iso:country":"US",
    "sg:address":"2569 W Enosburg Rd",
    "sg:city":"Enosburg Falls",
    "sg:classifiers":[
        {
            "category":"Building & Trades",
            "subcategory":"Construction",
            "type":"Services"
        }
    ],
    "sg:phone":"+1 802 933 2020",
    "sg:postcode":"05450",
    "sg:province":"VT",
    "sg:tags":[
        "contractor"
    ],
    "wof:name":"Roy Carpenter Construction",
    "wof:placetype":"venue"
},
  "geometry": {"coordinates":[-72.797461,44.869677],"type":"Point"}
}