{
  "type": "Feature",
  "properties": {
    "iso:country":"US",
    "sg:address":"6 Village Sq",
    "sg:city":"S Londonderry",
    "sg:classifiers":[
        {
            "category":"Banks & Credit Unions",
            "subcategory":"Investment Brokerage",
            "type":"Services"
        }
    ],
    "sg:phone":"+1 802 297 3300",
    "sg:postcode":"05155",
    "sg:province":"VT",
    "sg:tags":[
        "advisory",
        "financial"
    ],
    "wof:name":"Playground Financial",
    "wof:placetype":"venue"
},
  "geometry": {"coordinates":[-72.905607,43.112835],"type":"Point"}
}