{
  "type": "Feature",
  "properties": {
    "addr:full":"109 South St Bennington VT 05201",
    "addr:housenumber":"109",
    "addr:postcode":"05201",
    "addr:street":"South St",
    "iso:country":"US",
    "sg:address":"109 South St",
    "sg:city":"Bennington",
    "sg:classifiers":[
        {
            "category":"Manufacturing",
            "subcategory":"Printing",
            "type":"Manufacturing & Wholesale Goods"
        }
    ],
    "sg:phone":"+1 802 447 3381",
    "sg:postcode":"05201",
    "sg:province":"VT",
    "sg:tags":[
        "newspaper"
    ],
    "wof:name":"Pennysaver Press",
    "wof:placetype":"venue"
},
  "geometry": {"coordinates":[-73.197233,42.878015],"type":"Point"}
}