{
  "type": "Feature",
  "properties": {
    "iso:country":"US",
    "sg:address":"2024 Randolph Rd",
    "sg:city":"Morrisville",
    "sg:classifiers":[
        {
            "category":"Manufacturing",
            "subcategory":"Lumber",
            "type":"Manufacturing & Wholesale Goods"
        }
    ],
    "sg:phone":"+1 802 888 2700",
    "sg:postcode":"05661",
    "sg:province":"VT",
    "wof:name":"Saw Mill",
    "wof:placetype":"venue"
},
  "geometry": {"coordinates":[-72.593181,44.532059],"type":"Point"}
}