{
  "type": "Feature",
  "properties": {
    "addr:full":"30 Central St Windsor VT 05089",
    "addr:housenumber":"30",
    "addr:postcode":"05089",
    "addr:street":"Central St",
    "iso:country":"US",
    "sg:address":"30 Central St",
    "sg:city":"Windsor",
    "sg:classifiers":[
        {
            "category":"Building & Trades",
            "subcategory":"Construction",
            "type":"Services"
        }
    ],
    "sg:phone":"+1 802 674 6000",
    "sg:postcode":"05089",
    "sg:province":"VT",
    "sg:tags":[
        "marking",
        "maintenance",
        "parking"
    ],
    "wof:name":"Windsor Highway Dept",
    "wof:placetype":"venue"
},
  "geometry": {"coordinates":[-72.386343,43.476942],"type":"Point"}
}