{
  "type": "Feature",
  "properties": {
    "iso:country":"US",
    "sg:address":"19 Commerce Ave",
    "sg:city":"South Burlington",
    "sg:classifiers":[
        {
            "category":"Wholesale",
            "subcategory":"Machinery & Supplies",
            "type":"Manufacturing & Wholesale Goods"
        }
    ],
    "sg:phone":"+1 802 660 8500",
    "sg:postcode":"05403",
    "sg:province":"VT",
    "sg:tags":[
        "equipment",
        "industrial",
        "valve"
    ],
    "wof:name":"Independent Pipe & Supply Corp",
    "wof:placetype":"venue"
},
  "geometry": {"coordinates":[-73.15968599999999,44.483215],"type":"Point"}
}