{
  "type": "Feature",
  "properties": {
    "iso:country":"US",
    "sg:address":"62 Main St",
    "sg:city":"Proctor",
    "sg:classifiers":[
        {
            "category":"Professional",
            "subcategory":"Management & Consulting",
            "type":"Services"
        }
    ],
    "sg:phone":"+1 802 459 9900",
    "sg:postcode":"05765",
    "sg:province":"VT",
    "sg:tags":[
        "consultant",
        "business"
    ],
    "wof:name":"Allenby Associates",
    "wof:placetype":"venue"
},
  "geometry": {"coordinates":[-73.032895,43.661338],"type":"Point"}
}