{
  "type": "Feature",
  "properties": {
    "iso:country":"US",
    "sg:address":"164 Hill St",
    "sg:city":"Montpelier",
    "sg:classifiers":[
        {
            "category":"Organizations",
            "subcategory":"Religious Organization",
            "type":"Services"
        }
    ],
    "sg:phone":"+1 802 229 4028",
    "sg:postcode":"05602",
    "sg:province":"VT",
    "sg:tags":[
        "church"
    ],
    "wof:name":"Kagyu Tenjay Choling Tibetian",
    "wof:placetype":"venue"
},
  "geometry": {"coordinates":[-72.572586,44.250726],"type":"Point"}
}