{
  "type": "Feature",
  "properties": {
    "addr:full":"326 Main St Derby VT 05829",
    "addr:housenumber":"326",
    "addr:postcode":"05829",
    "addr:street":"Main St",
    "iso:country":"US",
    "sg:address":"326 Main St",
    "sg:city":"Derby",
    "sg:classifiers":[
        {
            "category":"Building & Trades",
            "subcategory":"Plumbing",
            "type":"Services"
        }
    ],
    "sg:phone":"+1 802 766 4949",
    "sg:postcode":"05829",
    "sg:province":"VT",
    "sg:tags":[
        "plumbing",
        "contractor"
    ],
    "wof:name":"Fred's Plumbing & Heating Corp",
    "wof:placetype":"venue"
},
  "geometry": {"coordinates":[-72.133548,44.947959],"type":"Point"}
}