{
  "type": "Feature",
  "properties": {
    "addr:full":"22 Hill Rd Brookline VT 05345",
    "addr:housenumber":"22",
    "addr:postcode":"05345",
    "addr:street":"Hill Rd",
    "iso:country":"US",
    "sg:address":"22 Hill Rd",
    "sg:city":"Brookline",
    "sg:classifiers":[
        {
            "category":"Retail",
            "subcategory":"Repair Shop",
            "type":"Services"
        }
    ],
    "sg:phone":"+1 802 365 4902",
    "sg:postcode":"05345",
    "sg:province":"VT",
    "sg:tags":[
        "ironwork"
    ],
    "wof:name":"Swing Welding",
    "wof:placetype":"venue"
},
  "geometry": {"coordinates":[-72.63346900000001,42.995964],"type":"Point"}
}