{
  "type": "Feature",
  "properties": {
    "addr:full":"1868 State Rte 116 Bristol VT 05443",
    "addr:housenumber":"1868",
    "addr:postcode":"05443",
    "addr:street":"State Rte 116",
    "iso:country":"US",
    "sg:address":"1868 State Rte 116",
    "sg:city":"Bristol",
    "sg:classifiers":[
        {
            "category":"Travel",
            "subcategory":"Hotels & Motels",
            "type":"Entertainment"
        }
    ],
    "sg:phone":"+1 802 453 2432",
    "sg:postcode":"05443",
    "sg:province":"VT",
    "sg:tags":[
        "inn"
    ],
    "sg:website":"www.innatbaldwincreek.com",
    "wof:name":"Inn At Baldwin Creek",
    "wof:placetype":"venue"
},
  "geometry": {"coordinates":[-73.09666300000001,44.102313],"type":"Point"}
}