{
  "type": "Feature",
  "properties": {
    "iso:country":"US",
    "sg:address":"179 St Albans Rd",
    "sg:city":"Swanton",
    "sg:classifiers":[
        {
            "category":"Retail",
            "subcategory":"Animal Services",
            "type":"Services"
        }
    ],
    "sg:phone":"+1 802 868 3387",
    "sg:postcode":"05488",
    "sg:province":"VT",
    "wof:name":"Kim Tam Kennels",
    "wof:placetype":"venue"
},
  "geometry": {"coordinates":[-73.095389,44.859126],"type":"Point"}
}