{
  "type": "Feature",
  "properties": {
    "iso:country":"US",
    "sg:address":"200 Park St",
    "sg:city":"Morrisville",
    "sg:classifiers":[
        {
            "category":"Professional",
            "subcategory":"Management & Consulting",
            "type":"Services"
        },
        {
            "category":"Organizations",
            "subcategory":"Professional Association",
            "type":"Services"
        }
    ],
    "sg:phone":"+1 802 888 3183",
    "sg:postcode":"05661",
    "sg:province":"VT",
    "sg:tags":[
        "religious",
        "business"
    ],
    "wof:name":"Vermont Humanities Council",
    "wof:placetype":"venue"
},
  "geometry": {"coordinates":[-72.592753,44.563198],"type":"Point"}
}