{
  "type": "Feature",
  "properties": {
    "addr:full":"91 Dart Hill North Ferrisburg VT 05473",
    "addr:housenumber":"91",
    "addr:postcode":"05473",
    "addr:street":"Dart Hill North",
    "iso:country":"US",
    "sg:address":"91 Dart Hill",
    "sg:city":"North Ferrisburg",
    "sg:classifiers":[
        {
            "category":"Shopping",
            "subcategory":"Beauty & Cosmetics",
            "type":"Retail Goods"
        }
    ],
    "sg:phone":"+1 802 425 3768",
    "sg:postcode":"05473",
    "sg:province":"VT",
    "sg:tags":[
        "merchandise"
    ],
    "wof:name":"Valerie Mullin",
    "wof:placetype":"venue"
},
  "geometry": {"coordinates":[-73.179773,44.262486],"type":"Point"}
}