{
  "type": "Feature",
  "properties": {
    "addr:full":"433 Woodstock Rd Woodstock VT 05091",
    "addr:housenumber":"433",
    "addr:postcode":"05091",
    "addr:street":"Woodstock Rd",
    "iso:country":"US",
    "sg:address":"433 Woodstock Rd",
    "sg:city":"Woodstock",
    "sg:classifiers":[
        {
            "category":"Food & Beverages",
            "subcategory":"Groceries & Convenience Stores",
            "type":"Retail Goods"
        }
    ],
    "sg:phone":"+1 802 457 9147",
    "sg:postcode":"05091",
    "sg:province":"VT",
    "sg:tags":[
        "station",
        "gasoline"
    ],
    "wof:name":"Cumberland Farms 8008",
    "wof:placetype":"venue"
},
  "geometry": {"coordinates":[-72.50487699999999,43.632097],"type":"Point"}
}