{
  "type": "Feature",
  "properties": {
    "iso:country":"US",
    "sg:address":"76 Cotton Mill Hill",
    "sg:city":"Brattleboro",
    "sg:classifiers":[
        {
            "category":"Professional",
            "subcategory":"Management & Consulting",
            "type":"Services"
        }
    ],
    "sg:phone":"+1 802 258 2255",
    "sg:postcode":"05301",
    "sg:province":"VT",
    "sg:tags":[
        "consultant",
        "educational"
    ],
    "wof:name":"Mentoring Project/All",
    "wof:placetype":"venue"
},
  "geometry": {"coordinates":[-72.554025,42.834525],"type":"Point"}
}