{
  "type": "Feature",
  "properties": {
    "addr:full":"451 Lawrence Pl Williston VT 05495",
    "addr:housenumber":"451",
    "addr:postcode":"05495",
    "addr:street":"Lawrence Pl",
    "iso:country":"US",
    "sg:address":"451 Lawrence Pl",
    "sg:city":"Williston",
    "sg:phone":"+1 802 288 1581",
    "sg:postcode":"05495",
    "sg:province":"VT",
    "sg:tags":[
        "video",
        "conferencing"
    ],
    "wof:name":"Vermont Interactive Television",
    "wof:placetype":"venue"
},
  "geometry": {"coordinates":[-73.11356499999999,44.451661],"type":"Point"}
}