{
  "type": "Feature",
  "properties": {
    "iso:country":"US",
    "sg:address":"4969 Mountain Rd",
    "sg:city":"Stowe",
    "sg:classifiers":[
        {
            "category":"Restaurant",
            "type":"Food & Drink"
        }
    ],
    "sg:phone":"+1 802 253 8198",
    "sg:postcode":"05672",
    "sg:province":"VT",
    "wof:name":"Matterhorn Restaurant",
    "wof:placetype":"venue"
},
  "geometry": {"coordinates":[-72.75036299999999,44.501018],"type":"Point"}
}