{
  "type": "Feature",
  "properties": {
    "iso:country":"US",
    "sg:address":"510 US Hwy 7",
    "sg:city":"Middlebury",
    "sg:classifiers":[
        {
            "category":"Retail",
            "subcategory":"Auto Repair",
            "type":"Services"
        }
    ],
    "sg:phone":"+1 802 388 4932",
    "sg:postcode":"05753",
    "sg:province":"VT",
    "sg:tags":[
        "repairing",
        "automobile"
    ],
    "sg:website":"www.sheamotorco.com",
    "wof:name":"Shea Motor Co",
    "wof:placetype":"venue"
},
  "geometry": {"coordinates":[-73.145453,43.996567],"type":"Point"}
}