{
  "type": "Feature",
  "properties": {
    "iso:country":"US",
    "sg:address":"2687 Greenbush Rd",
    "sg:city":"Charlotte",
    "sg:classifiers":[
        {
            "category":"Professional",
            "subcategory":"Management & Consulting",
            "type":"Services"
        }
    ],
    "sg:phone":"+1 802 425 7600",
    "sg:postcode":"05445",
    "sg:province":"VT",
    "sg:tags":[
        "consultant",
        "educational"
    ],
    "sg:website":"www.edanswers.com",
    "wof:name":"Mason & Assoc",
    "wof:placetype":"venue"
},
  "geometry": {"coordinates":[-73.253027,44.312351],"type":"Point"}
}