{
  "type": "Feature",
  "properties": {
    "addr:full":"3356 Shelburne Rd Shelburne VT 05482",
    "addr:housenumber":"3356",
    "addr:postcode":"05482",
    "addr:street":"Shelburne Rd",
    "iso:country":"US",
    "sg:address":"3356 Shelburne Rd",
    "sg:city":"Shelburne",
    "sg:classifiers":[
        {
            "category":"Shopping",
            "subcategory":"Shoes",
            "type":"Retail Goods"
        }
    ],
    "sg:phone":"+1 802 985 3483",
    "sg:postcode":"05482",
    "sg:province":"VT",
    "wof:name":"Danform Shoe Stores",
    "wof:placetype":"venue"
},
  "geometry": {"coordinates":[-73.216448,44.407228],"type":"Point"}
}