{
  "type": "Feature",
  "properties": {
    "iso:country":"US",
    "sg:address":"2715 State Rte 100",
    "sg:city":"Pittsfield",
    "sg:classifiers":[
        {
            "category":"Shopping",
            "subcategory":"Florist",
            "type":"Retail Goods"
        }
    ],
    "sg:phone":"+1 802 746 8148",
    "sg:postcode":"05751",
    "sg:province":"VT",
    "wof:name":"French's Garden & Gift Shop",
    "wof:placetype":"venue"
},
  "geometry": {"coordinates":[-72.8233,43.704723],"type":"Point"}
}