{
  "type": "Feature",
  "properties": {
    "iso:country":"US",
    "sg:address":"1177 North Ave",
    "sg:city":"Burlington",
    "sg:classifiers":[
        {
            "category":"Wholesale",
            "subcategory":"Durable Goods & Equipment",
            "type":"Manufacturing & Wholesale Goods"
        }
    ],
    "sg:phone":"+1 802 864 0151",
    "sg:postcode":"05401",
    "sg:province":"VT",
    "sg:tags":[
        "video"
    ],
    "wof:name":"Video World",
    "wof:placetype":"venue"
},
  "geometry": {"coordinates":[-73.24529,44.507074],"type":"Point"}
}