{
  "type": "Feature",
  "properties": {
    "iso:country":"US",
    "sg:address":"333 Rutland Rd",
    "sg:city":"West Rutland",
    "sg:classifiers":[
        {
            "category":"Organizations",
            "subcategory":"Community Association",
            "type":"Services"
        }
    ],
    "sg:phone":"+1 802 438 5111",
    "sg:postcode":"05777",
    "sg:province":"VT",
    "wof:name":"American Legion Post No 87",
    "wof:placetype":"venue"
},
  "geometry": {"coordinates":[-73.027601,43.595292],"type":"Point"}
}