{
  "type": "Feature",
  "properties": {
    "addr:full":"253 Canal St Brattleboro VT 05301",
    "addr:housenumber":"253",
    "addr:postcode":"05301",
    "addr:street":"Canal St",
    "iso:country":"US",
    "sg:address":"253 Canal St",
    "sg:city":"Brattleboro",
    "sg:classifiers":[
        {
            "category":"Building & Trades",
            "subcategory":"Landscaping Services",
            "type":"Services"
        }
    ],
    "sg:phone":"+1 802 257 0278",
    "sg:postcode":"05301",
    "sg:province":"VT",
    "sg:tags":[
        "designer",
        "landscape"
    ],
    "wof:name":"William Jewell & Co",
    "wof:placetype":"venue"
},
  "geometry": {"coordinates":[-72.565572,42.837807],"type":"Point"}
}