{
  "type": "Feature",
  "properties": {
    "iso:country":"US",
    "sg:address":"2850 Mountain Rd",
    "sg:city":"Stowe",
    "sg:classifiers":[
        {
            "category":"Shopping",
            "subcategory":"Shoes",
            "type":"Retail Goods"
        }
    ],
    "sg:phone":"+1 802 253 0009",
    "sg:postcode":"05672",
    "sg:province":"VT",
    "wof:name":"Well Heeled Speciality Shoes",
    "wof:placetype":"venue"
},
  "geometry": {"coordinates":[-72.72631800000001,44.480833],"type":"Point"}
}