{
  "type": "Feature",
  "properties": {
    "iso:country":"US",
    "sg:address":"214 Main St",
    "sg:city":"Brattleboro",
    "sg:classifiers":[
        {
            "category":"Building & Trades",
            "subcategory":"Construction",
            "type":"Services"
        }
    ],
    "sg:phone":"+1 802 257 4705",
    "sg:postcode":"05301",
    "sg:province":"VT",
    "sg:tags":[
        "stonework",
        "masonry",
        "other"
    ],
    "wof:name":"Rick Mason Kenyon",
    "wof:placetype":"venue"
},
  "geometry": {"coordinates":[-72.559451,42.855114],"type":"Point"}
}