{
  "type": "Feature",
  "properties": {
    "iso:country":"US",
    "sg:address":"831 US Hwy 7",
    "sg:city":"Rutland",
    "sg:classifiers":[
        {
            "category":"Shopping",
            "subcategory":"Books",
            "type":"Retail Goods"
        }
    ],
    "sg:phone":"+1 802 747 5955",
    "sg:postcode":"05701",
    "sg:province":"VT",
    "sg:tags":[
        "dealer"
    ],
    "wof:name":"Book Market",
    "wof:placetype":"venue"
},
  "geometry": {"coordinates":[-72.982198,43.642714],"type":"Point"}
}