{
  "type": "Feature",
  "properties": {
    "iso:country":"US",
    "sg:address":"102 E Main St",
    "sg:city":"Poultney",
    "sg:classifiers":[
        {
            "category":"Manufacturing",
            "subcategory":"Printing",
            "type":"Manufacturing & Wholesale Goods"
        }
    ],
    "sg:phone":"+1 802 287 5168",
    "sg:postcode":"05764",
    "sg:province":"VT",
    "sg:tags":[
        "periodical"
    ],
    "wof:name":"Vermont Planet Magazine",
    "wof:placetype":"venue"
},
  "geometry": {"coordinates":[-73.22498899999999,43.518855],"type":"Point"}
}