{
  "type": "Feature",
  "properties": {
    "iso:country":"US",
    "sg:address":"5 Notch Rd",
    "sg:city":"Rutland",
    "sg:classifiers":[
        {
            "category":"Building & Trades",
            "subcategory":"Construction",
            "type":"Services"
        }
    ],
    "sg:phone":"+1 802 775 5904",
    "sg:postcode":"05701",
    "sg:province":"VT",
    "sg:tags":[
        "hanging",
        "commercial",
        "contractor"
    ],
    "wof:name":"Beaudry Painting Co",
    "wof:placetype":"venue"
},
  "geometry": {"coordinates":[-72.935877,43.608781],"type":"Point"}
}