{
  "type": "Feature",
  "properties": {
    "iso:country":"US",
    "sg:address":"43 Bombardier Rd",
    "sg:city":"Milton",
    "sg:classifiers":[
        {
            "category":"Government",
            "subcategory":"Office",
            "type":"Public Place"
        }
    ],
    "sg:phone":"+1 802 893 6033",
    "sg:postcode":"05468",
    "sg:province":"VT",
    "sg:tags":[
        "village"
    ],
    "wof:name":"Milton Town Finance Office",
    "wof:placetype":"venue"
},
  "geometry": {"coordinates":[-73.122728,44.619084],"type":"Point"}
}