{
  "type": "Feature",
  "properties": {
    "iso:country":"US",
    "sg:address":"76 Windridge Ln",
    "sg:city":"Craftsbury Cmn",
    "sg:classifiers":[
        {
            "category":"Travel",
            "subcategory":"Campground",
            "type":"Entertainment"
        }
    ],
    "sg:phone":"+1 802 586 9646",
    "sg:postcode":"05827",
    "sg:province":"VT",
    "sg:tags":[
        "camp"
    ],
    "wof:name":"Windridge Tennis Camp",
    "wof:placetype":"venue"
},
  "geometry": {"coordinates":[-72.354421,44.697622],"type":"Point"}
}