{
  "type": "Feature",
  "properties": {
    "iso:country":"US",
    "sg:address":"169 S Main St",
    "sg:city":"Brattleboro",
    "sg:classifiers":[
        {
            "category":"Professional",
            "subcategory":"Business Services",
            "type":"Services"
        }
    ],
    "sg:phone":"+1 802 257 5024",
    "sg:postcode":"05301",
    "sg:province":"VT",
    "wof:name":"Liddle Christopher C",
    "wof:placetype":"venue"
},
  "geometry": {"coordinates":[-72.55662700000001,42.84595],"type":"Point"}
}