{
  "type": "Feature",
  "properties": {
    "iso:country":"US",
    "sg:address":"147 Barber Farm Rd",
    "sg:city":"Jericho",
    "sg:classifiers":[
        {
            "category":"Professional",
            "subcategory":"Testing Lab",
            "type":"Services"
        }
    ],
    "sg:phone":"+1 802 879 1415",
    "sg:postcode":"05465",
    "sg:province":"VT",
    "sg:tags":[
        "laboratory"
    ],
    "sg:website":"www.vtndt.com",
    "wof:name":"Vermont Non-Destructive Inc",
    "wof:placetype":"venue"
},
  "geometry": {"coordinates":[-72.988105,44.462328],"type":"Point"}
}