{
  "type": "Feature",
  "properties": {
    "addr:full":"2104 E Burke Rd Lyndonville VT 05851",
    "addr:housenumber":"2104",
    "addr:postcode":"05851",
    "addr:street":"E Burke Rd",
    "iso:country":"US",
    "sg:address":"2104 E Burke Rd",
    "sg:city":"Lyndonville",
    "sg:classifiers":[
        {
            "category":"Social Services",
            "type":"Services"
        }
    ],
    "sg:phone":"+1 802 626 3900",
    "sg:postcode":"05851",
    "sg:province":"VT",
    "sg:tags":[
        "care",
        "center",
        "day"
    ],
    "wof:name":"Riverside Life Enrichment Ctr",
    "wof:placetype":"venue"
},
  "geometry": {"coordinates":[-71.967324,44.555275],"type":"Point"}
}