{
  "type": "Feature",
  "properties": {
    "iso:country":"US",
    "sg:address":"2254 Craftsbury Rd",
    "sg:city":"Greensboro",
    "sg:classifiers":[
        {
            "category":"Manufacturing",
            "subcategory":"Textiles",
            "type":"Manufacturing & Wholesale Goods"
        }
    ],
    "sg:phone":"+1 802 533 7733",
    "sg:postcode":"05841",
    "sg:province":"VT",
    "sg:tags":[
        "mill",
        "sewing",
        "fabric"
    ],
    "wof:name":"Judy B Dales",
    "wof:placetype":"venue"
},
  "geometry": {"coordinates":[-72.31405100000001,44.604545],"type":"Point"}
}