{
  "type": "Feature",
  "properties": {
    "iso:country":"US",
    "sg:address":"34 Curtis Ave",
    "sg:city":"Rutland",
    "sg:classifiers":[
        {
            "category":"Personal",
            "subcategory":"Beauty Salon",
            "type":"Services"
        }
    ],
    "sg:phone":"+1 802 773 8880",
    "sg:postcode":"05701",
    "sg:province":"VT",
    "wof:name":"Shear Heaven Salon & Day Spa",
    "wof:placetype":"venue"
},
  "geometry": {"coordinates":[-72.964347,43.592248],"type":"Point"}
}