{
  "type": "Feature",
  "properties": {
    "addr:full":"43 S Main St Randolph VT 05060",
    "addr:housenumber":"43",
    "addr:postcode":"05060",
    "addr:street":"S Main St",
    "iso:country":"US",
    "sg:address":"43 S Main St",
    "sg:city":"Randolph",
    "sg:classifiers":[
        {
            "category":"Personal",
            "type":"Services"
        }
    ],
    "sg:phone":"+1 802 728 5565",
    "sg:postcode":"05060",
    "sg:province":"VT",
    "wof:name":"Massage By Terry Heath",
    "wof:placetype":"venue"
},
  "geometry": {"coordinates":[-72.66633,43.91743],"type":"Point"}
}