{
  "type": "Feature",
  "properties": {
    "addr:full":"36 Burnham St Barre VT 05641",
    "addr:housenumber":"36",
    "addr:postcode":"05641",
    "addr:street":"Burnham St",
    "iso:country":"US",
    "sg:address":"36 Burnham St",
    "sg:city":"Barre",
    "sg:classifiers":[
        {
            "category":"Manufacturing",
            "subcategory":"Glass & Minerals",
            "type":"Manufacturing & Wholesale Goods"
        }
    ],
    "sg:phone":"+1 802 476 7831",
    "sg:postcode":"05641",
    "sg:province":"VT",
    "sg:tags":[
        "granite",
        "product"
    ],
    "wof:name":"Family Memorials Inc",
    "wof:placetype":"venue"
},
  "geometry": {"coordinates":[-72.506365,44.197551],"type":"Point"}
}