{
  "type": "Feature",
  "properties": {
    "addr:full":"592 Camp Rd Brandon VT 05733",
    "addr:housenumber":"592",
    "addr:postcode":"05733",
    "addr:street":"Camp Rd",
    "iso:country":"US",
    "sg:address":"592 Camp Rd",
    "sg:city":"Brandon",
    "sg:classifiers":[
        {
            "category":"Building & Trades",
            "subcategory":"Electrical",
            "type":"Services"
        }
    ],
    "sg:phone":"+1 802 273 3935",
    "sg:postcode":"05733",
    "sg:province":"VT",
    "sg:tags":[
        "electrician"
    ],
    "wof:name":"Reck Electric",
    "wof:placetype":"venue"
},
  "geometry": {"coordinates":[-73.198502,43.746731],"type":"Point"}
}