{
  "type": "Feature",
  "properties": {
    "iso:country":"US",
    "sg:address":"608 Main St",
    "sg:city":"Sheldon",
    "sg:classifiers":[
        {
            "category":"Building & Trades",
            "subcategory":"Construction",
            "type":"Services"
        }
    ],
    "sg:phone":"+1 802 933 6832",
    "sg:postcode":"05483",
    "sg:province":"VT",
    "sg:tags":[
        "roofing",
        "contractor"
    ],
    "wof:name":"ECM Roofing Construction",
    "wof:placetype":"venue"
},
  "geometry": {"coordinates":[-72.94629399999999,44.895227],"type":"Point"}
}