{
  "type": "Feature",
  "properties": {
    "addr:full":"5 Carmichael St Essex Junction VT 05452",
    "addr:housenumber":"5",
    "addr:postcode":"05452",
    "addr:street":"Carmichael St",
    "iso:country":"US",
    "sg:address":"5 Carmichael St",
    "sg:city":"Essex Junction",
    "sg:classifiers":[
        {
            "category":"Restaurant",
            "type":"Food & Drink"
        }
    ],
    "sg:menulink":"http://www.allmenus.com/vt/essex/246151-joyces-noodle-house-orient-cuisine/menu/",
    "sg:phone":"+1 802 288 9828",
    "sg:postcode":"05452",
    "sg:province":"VT",
    "sg:tags":[
        "asian",
        "chinese"
    ],
    "wof:name":"Joyce's Noodle House Orient Cuisine",
    "wof:placetype":"venue"
},
  "geometry": {"coordinates":[-73.08572700000001,44.507641],"type":"Point"}
}