{
  "type": "Feature",
  "properties": {
    "addr:full":"1590 US Hwy 7 Middlebury VT 05753",
    "addr:housenumber":"1590",
    "addr:postcode":"05753",
    "addr:street":"Us Hwy 7",
    "iso:country":"US",
    "sg:address":"1590 US Hwy 7",
    "sg:city":"Middlebury",
    "sg:classifiers":[
        {
            "category":"Retail",
            "subcategory":"Repair Shop",
            "type":"Services"
        }
    ],
    "sg:phone":"+1 802 388 7633",
    "sg:postcode":"05753",
    "sg:province":"VT",
    "sg:tags":[
        "lock",
        "locksmith"
    ],
    "sg:website":"www.theglassden.com",
    "wof:name":"Locking Glass Crafters",
    "wof:placetype":"venue"
},
  "geometry": {"coordinates":[-73.13120000000001,43.985043],"type":"Point"}
}