{
  "type": "Feature",
  "properties": {
    "addr:full":"153 Gale St Canaan VT 05903",
    "addr:housenumber":"153",
    "addr:postcode":"05903",
    "addr:street":"Gale St",
    "iso:country":"US",
    "sg:address":"153 Gale St",
    "sg:city":"Canaan",
    "sg:classifiers":[
        {
            "category":"Personal",
            "type":"Services"
        }
    ],
    "sg:phone":"+1 802 266 8626",
    "sg:postcode":"05903",
    "sg:province":"VT",
    "sg:tags":[
        "therapist",
        "massage"
    ],
    "wof:name":"Kneading Knotts",
    "wof:placetype":"venue"
},
  "geometry": {"coordinates":[-71.537913,44.996156],"type":"Point"}
}