{
  "type": "Feature",
  "properties": {
    "iso:country":"US",
    "sg:address":"3 Main St",
    "sg:city":"Burlington",
    "sg:classifiers":[
        {
            "category":"Professional",
            "subcategory":"Management & Consulting",
            "type":"Services"
        }
    ],
    "sg:phone":"+1 802 865 7950",
    "sg:postcode":"05401",
    "sg:province":"VT",
    "sg:tags":[
        "medical",
        "administration",
        "business"
    ],
    "wof:name":"Med Peak",
    "wof:placetype":"venue"
},
  "geometry": {"coordinates":[-73.218694,44.475647],"type":"Point"}
}