{
  "type": "Feature",
  "properties": {
    "iso:country":"US",
    "sg:address":"113 S Main St",
    "sg:city":"Rutland",
    "sg:classifiers":[
        {
            "category":"Manufacturing",
            "subcategory":"Metals",
            "type":"Manufacturing & Wholesale Goods"
        }
    ],
    "sg:phone":"+1 802 775 5759",
    "sg:postcode":"05701",
    "sg:province":"VT",
    "wof:name":"Vermont Platting",
    "wof:placetype":"venue"
},
  "geometry": {"coordinates":[-72.97208500000001,43.607254],"type":"Point"}
}