{
  "type": "Feature",
  "properties": {
    "iso:country":"US",
    "sg:address":"123 Old 108 Loop",
    "sg:city":"Jeffersonville",
    "sg:classifiers":[
        {
            "category":"Shopping",
            "subcategory":"Bicycles & Sporting Goods",
            "type":"Retail Goods"
        }
    ],
    "sg:phone":"+1 802 644 5853",
    "sg:postcode":"05464",
    "sg:province":"VT",
    "sg:tags":[
        "outdoor",
        "gear"
    ],
    "sg:website":"www.noschoolsnowboardshop.com",
    "wof:name":"No School Snowboard Shop",
    "wof:placetype":"venue"
},
  "geometry": {"coordinates":[-72.791444,44.589581],"type":"Point"}
}