{
  "type": "Feature",
  "properties": {
    "iso:country":"US",
    "sg:address":"276 Monroe St",
    "sg:city":"Middlebury",
    "sg:classifiers":[
        {
            "category":"Professional",
            "subcategory":"Business Services",
            "type":"Services"
        }
    ],
    "sg:phone":"+1 802 388 7018",
    "sg:postcode":"05753",
    "sg:province":"VT",
    "sg:tags":[
        "broker",
        "merchandise"
    ],
    "wof:name":"Windfall Traders",
    "wof:placetype":"venue"
},
  "geometry": {"coordinates":[-73.157292,44.007415],"type":"Point"}
}