{
  "type": "Feature",
  "properties": {
    "iso:country":"US",
    "sg:address":"1110 Prim Rd",
    "sg:city":"Colchester",
    "sg:classifiers":[
        {
            "category":"Social Services",
            "type":"Services"
        }
    ],
    "sg:phone":"+1 802 860 4420",
    "sg:postcode":"05446",
    "sg:province":"VT",
    "wof:name":"Expecttion Child Brth Prenting",
    "wof:placetype":"venue"
},
  "geometry": {"coordinates":[-73.245994,44.538892],"type":"Point"}
}