{
  "type": "Feature",
  "properties": {
    "iso:country":"US",
    "sg:address":"100 S Main St",
    "sg:city":"Waterbury",
    "sg:classifiers":[
        {
            "category":"Health Services",
            "subcategory":"Chiropractor",
            "type":"Services"
        }
    ],
    "sg:phone":"+1 802 244 1332",
    "sg:postcode":"05676",
    "sg:province":"VT",
    "wof:name":"Mountainview Chiropractic",
    "wof:placetype":"venue"
},
  "geometry": {"coordinates":[-72.75162,44.333128],"type":"Point"}
}