{
  "type": "Feature",
  "properties": {
    "iso:country":"US",
    "sg:address":"2324 Killington Rd",
    "sg:city":"Killington",
    "sg:classifiers":[
        {
            "category":"Shopping",
            "subcategory":"Bicycles & Sporting Goods",
            "type":"Retail Goods"
        }
    ],
    "sg:phone":"+1 802 422 3950",
    "sg:postcode":"05751",
    "sg:province":"VT",
    "sg:tags":[
        "equipment",
        "rent",
        "skiing"
    ],
    "wof:name":"Forerunner Ski Shop",
    "wof:placetype":"venue"
},
  "geometry": {"coordinates":[-72.78805199999999,43.640032],"type":"Point"}
}