{
  "type": "Feature",
  "properties": {
    "iso:country":"US",
    "sg:address":"88 Royalton Tpke",
    "sg:city":"South Royalton",
    "sg:classifiers":[
        {
            "category":"Farming",
            "subcategory":"Dairy Farm",
            "type":"Manufacturing & Wholesale Goods"
        }
    ],
    "sg:phone":"+1 802 763 8141",
    "sg:postcode":"05068",
    "sg:province":"VT",
    "wof:name":"Clark Farm",
    "wof:placetype":"venue"
},
  "geometry": {"coordinates":[-72.59419699999999,43.723917],"type":"Point"}
}