{
  "type": "Feature",
  "properties": {
    "iso:country":"US",
    "sg:address":"12 N Main St",
    "sg:city":"Danby",
    "sg:classifiers":[
        {
            "category":"Home & Garden",
            "subcategory":"Garden Supply",
            "type":"Retail Goods"
        }
    ],
    "sg:phone":"+1 802 293 5991",
    "sg:postcode":"05739",
    "sg:province":"VT",
    "sg:tags":[
        "house",
        "bird",
        "feeder"
    ],
    "wof:name":"Vermont Country Bird Houses",
    "wof:placetype":"venue"
},
  "geometry": {"coordinates":[-72.996494,43.348792],"type":"Point"}
}