{
  "type": "Feature",
  "properties": {
    "iso:country":"US",
    "sg:address":"5111 US Hwy 5",
    "sg:city":"Westminster Sta",
    "sg:classifiers":[
        {
            "category":"Professional",
            "subcategory":"Accounting & Tax Preparation",
            "type":"Services"
        }
    ],
    "sg:phone":"+1 802 722 4500",
    "sg:postcode":"05158",
    "sg:province":"VT",
    "sg:tags":[
        "return",
        "filing"
    ],
    "wof:name":"Spaulding & Madden Tax Svc",
    "wof:placetype":"venue"
},
  "geometry": {"coordinates":[-72.439471,43.085254],"type":"Point"}
}