{
  "type": "Feature",
  "properties": {
    "iso:country":"US",
    "sg:address":"24 Spring Lake Rd",
    "sg:city":"Cuttingsville",
    "sg:classifiers":[
        {
            "category":"Shopping",
            "subcategory":"Florist",
            "type":"Retail Goods"
        }
    ],
    "sg:phone":"+1 802 492 2202",
    "sg:postcode":"05738",
    "sg:province":"VT",
    "wof:name":"Mill River Wildflower Farm",
    "wof:placetype":"venue"
},
  "geometry": {"coordinates":[-72.894187,43.496568],"type":"Point"}
}