{
  "type": "Feature",
  "properties": {
    "iso:country":"US",
    "sg:address":"165 State Rte 12 Alt",
    "sg:city":"Northfield",
    "sg:classifiers":[
        {
            "category":"Restaurant",
            "type":"Food & Drink"
        }
    ],
    "sg:phone":"+1 802 485 4336",
    "sg:postcode":"05663",
    "sg:province":"VT",
    "sg:tags":[
        "eating"
    ],
    "wof:name":"Red Kettle Restaurant",
    "wof:placetype":"venue"
},
  "geometry": {"coordinates":[-72.661658,44.131938],"type":"Point"}
}