{
  "type": "Feature",
  "properties": {
    "iso:country":"US",
    "sg:address":"320 Lefebvre Ln",
    "sg:city":"Williston",
    "sg:classifiers":[
        {
            "category":"Professional",
            "subcategory":"Advertising",
            "type":"Services"
        }
    ],
    "sg:phone":"+1 802 350 5136",
    "sg:postcode":"05495",
    "sg:province":"VT",
    "sg:tags":[
        "guide"
    ],
    "wof:name":"Champlain Valley Menu Guide",
    "wof:placetype":"venue"
},
  "geometry": {"coordinates":[-73.066086,44.438864],"type":"Point"}
}