{
  "type": "Feature",
  "properties": {
    "iso:country":"US",
    "sg:address":"31 Pierce St",
    "sg:city":"Norwich",
    "sg:classifiers":[
        {
            "category":"Health Services",
            "subcategory":"Health Practitioner",
            "type":"Services"
        }
    ],
    "sg:phone":"+1 802 649 9095",
    "sg:postcode":"05001",
    "sg:province":"VT",
    "sg:tags":[
        "psychotherapist"
    ],
    "wof:name":"Jeanne Baer",
    "wof:placetype":"venue"
},
  "geometry": {"coordinates":[-72.315245,43.659207],"type":"Point"}
}