{
  "type": "Feature",
  "properties": {
    "addr:full":"115 Whitcomb St Colchester VT 05446",
    "addr:housenumber":"115",
    "addr:postcode":"05446",
    "addr:street":"Whitcomb St",
    "iso:country":"US",
    "sg:address":"115 Whitcomb St",
    "sg:city":"Colchester",
    "sg:classifiers":[
        {
            "category":"Manufacturing",
            "subcategory":"Petroleum Products",
            "type":"Manufacturing & Wholesale Goods"
        }
    ],
    "sg:phone":"+1 802 655 1270",
    "sg:postcode":"05446",
    "sg:province":"VT",
    "sg:tags":[
        "asphalt"
    ],
    "wof:name":"Frank W Whitcomb Construction",
    "wof:placetype":"venue"
},
  "geometry": {"coordinates":[-73.18211700000001,44.504375],"type":"Point"}
}