{
  "type": "Feature",
  "properties": {
    "addr:full":"17 State Rte 17 Vergennes VT 05491",
    "addr:housenumber":"17",
    "addr:postcode":"05491",
    "addr:street":"State Rte 17",
    "iso:country":"US",
    "sg:address":"17 State Rte 17",
    "sg:city":"Vergennes",
    "sg:classifiers":[
        {
            "category":"Restaurant",
            "type":"Food & Drink"
        }
    ],
    "sg:phone":"+1 802 759 2152",
    "sg:postcode":"05491",
    "sg:province":"VT",
    "sg:tags":[
        "eating"
    ],
    "wof:name":"Bridge Family Restaurant",
    "wof:placetype":"venue"
},
  "geometry": {"coordinates":[-73.246961,44.0859],"type":"Point"}
}