{
  "type": "Feature",
  "properties": {
    "iso:country":"US",
    "sg:address":"27 Hinton Hill Rd",
    "sg:city":"Orleans",
    "sg:classifiers":[
        {
            "category":"Organizations",
            "subcategory":"Religious Organization",
            "type":"Services"
        }
    ],
    "sg:phone":"+1 802 525 1108",
    "sg:postcode":"05872",
    "sg:province":"VT",
    "sg:tags":[
        "church"
    ],
    "wof:name":"Westmore Community Church",
    "wof:placetype":"venue"
},
  "geometry": {"coordinates":[-72.05260699999999,44.772338],"type":"Point"}
}