{
  "type": "Feature",
  "properties": {
    "iso:country":"US",
    "sg:address":"12 S Main St",
    "sg:city":"Danby",
    "sg:classifiers":[
        {
            "category":"Professional",
            "subcategory":"Lawyer & Legal Services",
            "type":"Services"
        }
    ],
    "sg:phone":"+1 802 293 2693",
    "sg:postcode":"05739",
    "sg:province":"VT",
    "sg:tags":[
        "attorney",
        "practice"
    ],
    "wof:name":"Ogden Law Offices",
    "wof:placetype":"venue"
},
  "geometry": {"coordinates":[-72.996229,43.346526],"type":"Point"}
}