{
  "type": "Feature",
  "properties": {
    "iso:country":"US",
    "sg:address":"187 S Winooski Ave",
    "sg:city":"Burlington",
    "sg:classifiers":[
        {
            "category":"Professional",
            "subcategory":"Research",
            "type":"Services"
        }
    ],
    "sg:phone":"+1 802 660 2051",
    "sg:postcode":"05401",
    "sg:province":"VT",
    "sg:tags":[
        "nonphysical",
        "commercial"
    ],
    "wof:name":"Place Creative Co",
    "wof:placetype":"venue"
},
  "geometry": {"coordinates":[-73.21079899999999,44.473914],"type":"Point"}
}