{
  "type": "Feature",
  "properties": {
    "iso:country":"US",
    "sg:address":"523 Clyde St",
    "sg:city":"Newport",
    "sg:classifiers":[
        {
            "category":"Building & Trades",
            "subcategory":"Construction",
            "type":"Services"
        }
    ],
    "sg:phone":"+1 802 334 6809",
    "sg:postcode":"05855",
    "sg:province":"VT",
    "sg:tags":[
        "house"
    ],
    "wof:name":"Yvans Construction",
    "wof:placetype":"venue"
},
  "geometry": {"coordinates":[-72.187534,44.939856],"type":"Point"}
}