{
  "type": "Feature",
  "properties": {
    "addr:full":"41 Main St Milton VT 05468",
    "addr:housenumber":"41",
    "addr:postcode":"05468",
    "addr:street":"Main St",
    "iso:country":"US",
    "sg:address":"41 Main St",
    "sg:city":"Milton",
    "sg:classifiers":[
        {
            "category":"Organizations",
            "subcategory":"Religious Organization",
            "type":"Services"
        }
    ],
    "sg:phone":"+1 802 893 2487",
    "sg:postcode":"05468",
    "sg:province":"VT",
    "sg:tags":[
        "church"
    ],
    "wof:name":"St Ann Church",
    "wof:placetype":"venue"
},
  "geometry": {"coordinates":[-73.10756000000001,44.639229],"type":"Point"}
}