{
  "type": "Feature",
  "properties": {
    "iso:country":"US",
    "sg:address":"1583 Royalton Hill",
    "sg:city":"South Royalton",
    "sg:classifiers":[
        {
            "category":"Banks & Credit Unions",
            "subcategory":"Bank",
            "type":"Services"
        }
    ],
    "sg:phone":"+1 802 234 5549",
    "sg:postcode":"05068",
    "sg:province":"VT",
    "wof:name":"Randolph National Bank",
    "wof:placetype":"venue"
},
  "geometry": {"coordinates":[-72.581382,43.808592],"type":"Point"}
}