{
  "type": "Feature",
  "properties": {
    "addr:full":"370 Railroad St St Johnsbury VT 05819",
    "addr:housenumber":"370",
    "addr:postcode":"05819",
    "addr:street":"Railroad St",
    "iso:country":"US",
    "sg:address":"370 Railroad St",
    "sg:city":"St Johnsbury",
    "sg:classifiers":[
        {
            "category":"Shopping",
            "subcategory":"Used Merchandise",
            "type":"Retail Goods"
        }
    ],
    "sg:phone":"+1 802 748 2423",
    "sg:postcode":"05819",
    "sg:province":"VT",
    "sg:tags":[
        "antique"
    ],
    "wof:name":"Moose River Lake & Lodge",
    "wof:placetype":"venue"
},
  "geometry": {"coordinates":[-72.01562,44.418534],"type":"Point"}
}