{
  "type": "Feature",
  "properties": {
    "iso:country":"US",
    "sg:address":"5508 State Rte 106",
    "sg:city":"Reading",
    "sg:classifiers":[
        {
            "category":"Real Estate",
            "subcategory":"Real Estate Operator",
            "type":"Services"
        }
    ],
    "sg:phone":"+1 802 263 9420",
    "sg:postcode":"05062",
    "sg:province":"VT",
    "sg:tags":[
        "residential",
        "construction",
        "renovation"
    ],
    "wof:name":"Plumb Level & Square",
    "wof:placetype":"venue"
},
  "geometry": {"coordinates":[-72.551552,43.521484],"type":"Point"}
}