{
  "type": "Feature",
  "properties": {
    "iso:country":"US",
    "sg:address":"242 Bauer Rd",
    "sg:city":"West Pawlet",
    "sg:classifiers":[
        {
            "category":"Building & Trades",
            "subcategory":"Landscaping Services",
            "type":"Services"
        }
    ],
    "sg:phone":"+1 802 645 0803",
    "sg:postcode":"05775",
    "sg:province":"VT",
    "wof:name":"Baierlein Landscaping Inc",
    "wof:placetype":"venue"
},
  "geometry": {"coordinates":[-73.232848,43.336224],"type":"Point"}
}