{
  "type": "Feature",
  "properties": {
    "iso:country":"US",
    "sg:address":"107 Gold Brook Cir",
    "sg:city":"Stowe",
    "sg:classifiers":[
        {
            "category":"Professional",
            "subcategory":"Art Services",
            "type":"Services"
        }
    ],
    "sg:phone":"+1 802 253 4748",
    "sg:postcode":"05672",
    "sg:province":"VT",
    "sg:tags":[
        "graphic",
        "designer"
    ],
    "wof:name":"Lance Violette Design",
    "wof:placetype":"venue"
},
  "geometry": {"coordinates":[-72.700225,44.441464],"type":"Point"}
}