{
  "type": "Feature",
  "properties": {
    "iso:country":"US",
    "sg:address":"604 Rood Pond Rd",
    "sg:city":"Williamstown",
    "sg:classifiers":[
        {
            "category":"Organizations",
            "subcategory":"Non-profit Organization",
            "type":"Services"
        }
    ],
    "sg:phone":"+1 802 433 1526",
    "sg:postcode":"05679",
    "sg:province":"VT",
    "sg:tags":[
        "social"
    ],
    "wof:name":"Siberian Interculture Bridges",
    "wof:placetype":"venue"
},
  "geometry": {"coordinates":[-72.564024,44.108181],"type":"Point"}
}