{
  "type": "Feature",
  "properties": {
    "iso:country":"US",
    "sg:address":"34 Gifford Woods Acc",
    "sg:city":"Killington",
    "sg:classifiers":[
        {
            "category":"Recreation",
            "type":"Entertainment"
        }
    ],
    "sg:phone":"+1 802 775 5354",
    "sg:postcode":"05751",
    "sg:province":"VT",
    "sg:tags":[
        "parks"
    ],
    "wof:name":"Gifford Woods State Park",
    "wof:placetype":"venue"
},
  "geometry": {"coordinates":[-72.81007,43.67396],"type":"Point"}
}