{
  "type": "Feature",
  "properties": {
    "addr:full":"400 Cornerstone Dr Williston VT 05495",
    "addr:housenumber":"400",
    "addr:postcode":"05495",
    "addr:street":"Cornerstone Dr",
    "iso:country":"US",
    "sg:address":"400 Cornerstone Dr",
    "sg:city":"Williston",
    "sg:classifiers":[
        {
            "category":"Utilities",
            "subcategory":"Telephone",
            "type":"Services"
        }
    ],
    "sg:phone":"+1 802 288 1000",
    "sg:postcode":"05495",
    "sg:province":"VT",
    "sg:tags":[
        "company"
    ],
    "wof:name":"CTC Communications Corp",
    "wof:placetype":"venue"
},
  "geometry": {"coordinates":[-73.10359099999999,44.447067],"type":"Point"}
}