{
  "type": "Feature",
  "properties": {
    "iso:country":"US",
    "sg:address":"323 Beech St",
    "sg:city":"Bennington",
    "sg:classifiers":[
        {
            "category":"Retail",
            "subcategory":"Animal Services",
            "type":"Services"
        }
    ],
    "sg:phone":"+1 802 447 2147",
    "sg:postcode":"05201",
    "sg:province":"VT",
    "wof:name":"Bennington County Kennel Club",
    "wof:placetype":"venue"
},
  "geometry": {"coordinates":[-73.178679,42.872498],"type":"Point"}
}