{
  "type": "Feature",
  "properties": {
    "iso:country":"US",
    "sg:address":"1 Veterans Memorial Dr",
    "sg:city":"Bennington",
    "sg:classifiers":[
        {
            "category":"Government",
            "subcategory":"Office",
            "type":"Public Place"
        }
    ],
    "sg:phone":"+1 802 442 3929",
    "sg:postcode":"05201",
    "sg:province":"VT",
    "sg:tags":[
        "state",
        "program",
        "health"
    ],
    "wof:name":"Alcohol & Drug Abuse Ofc",
    "wof:placetype":"venue"
},
  "geometry": {"coordinates":[-73.19980700000001,42.888819],"type":"Point"}
}