{
  "type": "Feature",
  "properties": {
    "addr:full":"132 Main St Montpelier VT 05602",
    "addr:housenumber":"132",
    "addr:postcode":"05602",
    "addr:street":"Main St",
    "iso:country":"US",
    "sg:address":"132 Main St",
    "sg:city":"Montpelier",
    "sg:classifiers":[
        {
            "category":"Professional",
            "subcategory":"Lawyer & Legal Services",
            "type":"Services"
        }
    ],
    "sg:phone":"+1 802 229 5111",
    "sg:postcode":"05602",
    "sg:province":"VT",
    "wof:name":"Law Offices of Ritvo Jim",
    "wof:placetype":"venue"
},
  "geometry": {"coordinates":[-72.573145,44.262012],"type":"Point"}
}