{
  "type": "Feature",
  "properties": {
    "addr:full":"56 Church St Burlington VT 05401",
    "addr:housenumber":"56",
    "addr:postcode":"05401",
    "addr:street":"Church St",
    "iso:country":"US",
    "sg:address":"56 Church St",
    "sg:city":"Burlington",
    "sg:classifiers":[
        {
            "category":"Shopping",
            "subcategory":"Clothing, Apparel, & Fashions",
            "type":"Retail Goods"
        }
    ],
    "sg:phone":"+1 802 865 1230",
    "sg:postcode":"05401",
    "sg:province":"VT",
    "wof:name":"Banana Republic",
    "wof:placetype":"venue"
},
  "geometry": {"coordinates":[-73.21260700000001,44.478718],"type":"Point"}
}