{
  "type": "Feature",
  "properties": {
    "iso:country":"US",
    "sg:address":"1314 State Rte 8a",
    "sg:city":"Jacksonville",
    "sg:classifiers":[
        {
            "category":"Home & Garden",
            "subcategory":"Garden Supply",
            "type":"Retail Goods"
        }
    ],
    "sg:phone":"+1 802 368 7616",
    "sg:postcode":"05342",
    "sg:province":"VT",
    "sg:tags":[
        "herb",
        "order",
        "nursery",
        "herbal",
        "mail",
        "class"
    ],
    "wof:name":"Isabelles Herbs & Things",
    "wof:placetype":"venue"
},
  "geometry": {"coordinates":[-72.812648,42.766053],"type":"Point"}
}