{
  "type": "Feature",
  "properties": {
    "addr:full":"308 Main St Burlington VT 05401",
    "addr:housenumber":"308",
    "addr:postcode":"05401",
    "addr:street":"Main St",
    "iso:country":"US",
    "sg:address":"308 Main St",
    "sg:city":"Burlington",
    "sg:classifiers":[
        {
            "category":"Professional",
            "type":"Services"
        }
    ],
    "sg:phone":"+1 802 865 4587",
    "sg:postcode":"05401",
    "sg:province":"VT",
    "wof:name":"Vsm Inc",
    "wof:placetype":"venue"
},
  "geometry": {"coordinates":[-73.207616,44.476038],"type":"Point"}
}