{
  "type": "Feature",
  "properties": {
    "addr:full":"2357 Jersey St Vergennes VT 05491",
    "addr:housenumber":"2357",
    "addr:postcode":"05491",
    "addr:street":"Jersey St",
    "iso:country":"US",
    "sg:address":"2357 Jersey St",
    "sg:city":"Vergennes",
    "sg:classifiers":[
        {
            "category":"Farming",
            "subcategory":"Farm",
            "type":"Manufacturing & Wholesale Goods"
        }
    ],
    "sg:phone":"+1 802 475 2583",
    "sg:postcode":"05491",
    "sg:province":"VT",
    "sg:tags":[
        "crop",
        "general"
    ],
    "wof:name":"Allendale Farm",
    "wof:placetype":"venue"
},
  "geometry": {"coordinates":[-73.336324,44.158237],"type":"Point"}
}