{
  "type": "Feature",
  "properties": {
    "iso:country":"US",
    "sg:address":"19 N Harbor Rd",
    "sg:city":"Colchester",
    "sg:classifiers":[
        {
            "category":"Government",
            "subcategory":"Office",
            "type":"Public Place"
        }
    ],
    "sg:phone":"+1 508 856 3109",
    "sg:postcode":"05446",
    "sg:province":"VT",
    "sg:tags":[
        "survey",
        "geological"
    ],
    "wof:name":"Usgs Eastern Region",
    "wof:placetype":"venue"
},
  "geometry": {"coordinates":[-73.19409899999999,44.601487],"type":"Point"}
}