{
  "type": "Feature",
  "properties": {
    "iso:country":"US",
    "sg:address":"114 Snowcrest Rd",
    "sg:city":"Fairfax",
    "sg:classifiers":[
        {
            "category":"Building & Trades",
            "subcategory":"Construction",
            "type":"Services"
        }
    ],
    "sg:phone":"+1 802 524 0942",
    "sg:postcode":"05454",
    "sg:province":"VT",
    "sg:tags":[
        "dry wall",
        "contractor"
    ],
    "wof:name":"Champlain Drywall",
    "wof:placetype":"venue"
},
  "geometry": {"coordinates":[-73.05314199999999,44.758114],"type":"Point"}
}