{
  "type": "Feature",
  "properties": {
    "iso:country":"US",
    "sg:address":"722 Putney Rd",
    "sg:city":"Brattleboro",
    "sg:classifiers":[
        {
            "category":"Professional",
            "type":"Services"
        }
    ],
    "sg:phone":"+1 802 257 5083",
    "sg:postcode":"05301",
    "sg:province":"VT",
    "sg:tags":[
        "establishment"
    ],
    "wof:name":"Brattleboro Development Credit",
    "wof:placetype":"venue"
},
  "geometry": {"coordinates":[-72.556804,42.867669],"type":"Point"}
}