{
  "type": "Feature",
  "properties": {
    "addr:full":"1614 Gilbert Rd Williamstown VT 05679",
    "addr:housenumber":"1614",
    "addr:postcode":"05679",
    "addr:street":"Gilbert Rd",
    "iso:country":"US",
    "sg:address":"1614 Gilbert Rd",
    "sg:city":"Williamstown",
    "sg:classifiers":[
        {
            "category":"Communications",
            "subcategory":"Radio Station",
            "type":"Services"
        }
    ],
    "sg:phone":"+1 802 433 6114",
    "sg:postcode":"05679",
    "sg:province":"VT",
    "sg:tags":[
        "broadcast"
    ],
    "wof:name":"Rama Radio",
    "wof:placetype":"venue"
},
  "geometry": {"coordinates":[-72.52646300000001,44.104143],"type":"Point"}
}