{
  "type": "Feature",
  "properties": {
    "iso:country":"US",
    "sg:address":"42 Newfane Hill Rd",
    "sg:city":"Newfane",
    "sg:classifiers":[
        {
            "category":"Building & Trades",
            "subcategory":"Construction",
            "type":"Services"
        }
    ],
    "sg:phone":"+1 802 380 0204",
    "sg:postcode":"05345",
    "sg:province":"VT",
    "sg:tags":[
        "contractor"
    ],
    "wof:name":"True Craft Construction",
    "wof:placetype":"venue"
},
  "geometry": {"coordinates":[-72.65506999999999,42.953779],"type":"Point"}
}