{
  "type": "Feature",
  "properties": {
    "addr:full":"531 State Rte 105 Newport VT 05855",
    "addr:housenumber":"531",
    "addr:postcode":"05855",
    "addr:street":"State Rte 105",
    "iso:country":"US",
    "sg:address":"531 State Rte 105",
    "sg:city":"Newport",
    "sg:classifiers":[
        {
            "category":"Autos & Motor Vehicles",
            "subcategory":"Automobile Sales",
            "type":"Retail Goods"
        }
    ],
    "sg:phone":"+1 802 334 7333",
    "sg:postcode":"05855",
    "sg:province":"VT",
    "sg:tags":[
        "car",
        "dealer"
    ],
    "wof:name":"White Mountain Auto Broker",
    "wof:placetype":"venue"
},
  "geometry": {"coordinates":[-72.226705,44.933753],"type":"Point"}
}