{
  "type": "Feature",
  "properties": {
    "iso:country":"US",
    "sg:address":"48 Sherry Rd",
    "sg:city":"South Burlington",
    "sg:classifiers":[
        {
            "category":"Building & Trades",
            "subcategory":"Construction",
            "type":"Services"
        }
    ],
    "sg:phone":"+1 802 865 0171",
    "sg:postcode":"05403",
    "sg:province":"VT",
    "sg:tags":[
        "roofing",
        "contractor"
    ],
    "wof:name":"Leggett & Son Roofing & Contr",
    "wof:placetype":"venue"
},
  "geometry": {"coordinates":[-73.180988,44.459675],"type":"Point"}
}