{
  "type": "Feature",
  "properties": {
    "addr:full":"109 Heineberg Dr Colchester VT 05446",
    "addr:housenumber":"109",
    "addr:postcode":"05446",
    "addr:street":"Heineberg Dr",
    "iso:country":"US",
    "sg:address":"109 Heineberg Dr",
    "sg:city":"Colchester",
    "sg:classifiers":[
        {
            "category":"Personal",
            "subcategory":"Beauty Salon",
            "type":"Services"
        }
    ],
    "sg:phone":"+1 802 864 0899",
    "sg:postcode":"05446",
    "sg:province":"VT",
    "sg:tags":[
        "shop"
    ],
    "wof:name":"Malletts Bay Self-Storage",
    "wof:placetype":"venue"
},
  "geometry": {"coordinates":[-73.248582,44.534877],"type":"Point"}
}