{
  "type": "Feature",
  "properties": {
    "iso:country":"US",
    "sg:address":"677 Middle Pownal Rd",
    "sg:city":"Bennington",
    "sg:classifiers":[
        {
            "category":"Building & Trades",
            "subcategory":"Construction",
            "type":"Services"
        }
    ],
    "sg:phone":"+1 802 442 3194",
    "sg:postcode":"05201",
    "sg:province":"VT",
    "sg:tags":[
        "nonresidential"
    ],
    "wof:name":"Crosby O Howe & Son",
    "wof:placetype":"venue"
},
  "geometry": {"coordinates":[-73.18597699999999,42.860178],"type":"Point"}
}