{
  "type": "Feature",
  "properties": {
    "iso:country":"US",
    "sg:address":"137 Saint Paul St",
    "sg:city":"Burlington",
    "sg:classifiers":[
        {
            "category":"Shopping",
            "subcategory":"Clothing, Apparel, & Fashions",
            "type":"Retail Goods"
        }
    ],
    "sg:phone":"+1 802 658 4449",
    "sg:postcode":"05401",
    "sg:province":"VT",
    "wof:name":"Hempest",
    "wof:placetype":"venue"
},
  "geometry": {"coordinates":[-73.214124,44.47667],"type":"Point"}
}