{
  "type": "Feature",
  "properties": {
    "iso:country":"US",
    "sg:address":"3042 State Rte 100",
    "sg:city":"Lowell",
    "sg:classifiers":[
        {
            "category":"Shopping",
            "subcategory":"Discount & Variety Stores",
            "type":"Retail Goods"
        }
    ],
    "sg:phone":"+1 802 744 6858",
    "sg:postcode":"05857",
    "sg:province":"VT",
    "sg:tags":[
        "merchandise",
        "general"
    ],
    "wof:name":"Lowell's General Store",
    "wof:placetype":"venue"
},
  "geometry": {"coordinates":[-72.333321,44.917168],"type":"Point"}
}