{
  "type": "Feature",
  "properties": {
    "iso:country":"US",
    "sg:address":"448 Bean Rd",
    "sg:city":"Colchester",
    "sg:classifiers":[
        {
            "category":"Social Services",
            "subcategory":"Child Care",
            "type":"Services"
        }
    ],
    "sg:phone":"+1 802 864 9616",
    "sg:postcode":"05446",
    "sg:province":"VT",
    "sg:tags":[
        "day"
    ],
    "wof:name":"Benoit's Day Care",
    "wof:placetype":"venue"
},
  "geometry": {"coordinates":[-73.23930900000001,44.542018],"type":"Point"}
}