{
  "type": "Feature",
  "properties": {
    "iso:country":"US",
    "sg:address":"140 Tarbell Hill Rd",
    "sg:city":"Cavendish",
    "sg:classifiers":[
        {
            "category":"Real Estate",
            "subcategory":"Real Estate Agent",
            "type":"Services"
        }
    ],
    "sg:phone":"+1 802 226 7682",
    "sg:postcode":"05142",
    "sg:province":"VT",
    "wof:name":"Eagleshead Home Inspection Svc",
    "wof:placetype":"venue"
},
  "geometry": {"coordinates":[-72.520894,43.416026],"type":"Point"}
}