{
  "type": "Feature",
  "properties": {
    "iso:country":"US",
    "sg:address":"8 Leroy Rd",
    "sg:city":"Williston",
    "sg:classifiers":[
        {
            "category":"Manufacturing",
            "subcategory":"Tools & Machinery",
            "type":"Manufacturing & Wholesale Goods"
        }
    ],
    "sg:phone":"+1 802 863 1193",
    "sg:postcode":"05495",
    "sg:province":"VT",
    "sg:tags":[
        "control"
    ],
    "sg:website":"www.ttiglobal.com",
    "wof:name":"Total Temperature Instrmntn",
    "wof:placetype":"venue"
},
  "geometry": {"coordinates":[-73.130854,44.449248],"type":"Point"}
}