{
  "type": "Feature",
  "properties": {
    "addr:full":"12 Lacross Rd Springfield VT 05156",
    "addr:housenumber":"12",
    "addr:postcode":"05156",
    "addr:street":"Lacross Rd",
    "iso:country":"US",
    "sg:address":"12 Lacross Rd",
    "sg:city":"Springfield",
    "sg:classifiers":[
        {
            "category":"Retail",
            "subcategory":"Auto Repair",
            "type":"Services"
        }
    ],
    "sg:phone":"+1 802 885 4009",
    "sg:postcode":"05156",
    "sg:province":"VT",
    "sg:tags":[
        "repairing",
        "automobile"
    ],
    "wof:name":"Fay's Wrecker Svc",
    "wof:placetype":"venue"
},
  "geometry": {"coordinates":[-72.54789,43.279554],"type":"Point"}
}