{
  "type": "Feature",
  "properties": {
    "addr:full":"41 Susie Wilson Rd Essex Junction VT 05452",
    "addr:housenumber":"41",
    "addr:postcode":"05452",
    "addr:street":"Susie Wilson Rd",
    "iso:country":"US",
    "sg:address":"41 Susie Wilson Rd",
    "sg:city":"Essex Junction",
    "sg:classifiers":[
        {
            "category":"Restaurant",
            "type":"Food & Drink"
        }
    ],
    "sg:phone":"+1 802 872 9718",
    "sg:postcode":"05452",
    "sg:province":"VT",
    "sg:tags":[
        "eating"
    ],
    "wof:name":"Marys Midnight Cafe Inc",
    "wof:placetype":"venue"
},
  "geometry": {"coordinates":[-73.132149,44.508997],"type":"Point"}
}