{
  "type": "Feature",
  "properties": {
    "iso:country":"US",
    "sg:address":"1169 Railroad St",
    "sg:city":"Saint Johnsbury",
    "sg:classifiers":[
        {
            "category":"Building & Trades",
            "subcategory":"Construction",
            "type":"Services"
        }
    ],
    "sg:phone":"+1 802 751 8364",
    "sg:postcode":"05819",
    "sg:province":"VT",
    "sg:tags":[
        "floor",
        "laying",
        "contractor"
    ],
    "wof:name":"Floors & More",
    "wof:placetype":"venue"
},
  "geometry": {"coordinates":[-72.017067,44.428166],"type":"Point"}
}