{
  "type": "Feature",
  "properties": {
    "iso:country":"US",
    "sg:address":"469 Ridgefield Rd",
    "sg:city":"Shelburne",
    "sg:classifiers":[
        {
            "category":"Health Services",
            "subcategory":"Optometrist",
            "type":"Services"
        }
    ],
    "sg:phone":"+1 802 985 3506",
    "sg:postcode":"05482",
    "sg:province":"VT",
    "wof:name":"Puma J Allen OD",
    "wof:placetype":"venue"
},
  "geometry": {"coordinates":[-73.240196,44.361301],"type":"Point"}
}