{
  "type": "Feature",
  "properties": {
    "iso:country":"US",
    "sg:address":"596 Richmond Rd",
    "sg:city":"Hinesburg",
    "sg:classifiers":[
        {
            "category":"Retail",
            "subcategory":"Auto Repair",
            "type":"Services"
        },
        {
            "category":"Manufacturing",
            "subcategory":"Motor Vehicles & Parts",
            "type":"Manufacturing & Wholesale Goods"
        }
    ],
    "sg:phone":"+1 802 482 2155",
    "sg:postcode":"05461",
    "sg:province":"VT",
    "sg:tags":[
        "steel",
        "body",
        "all",
        "aluminum",
        "mfg",
        "bus",
        "frame",
        "truck",
        "type"
    ],
    "wof:name":"Iroquois Manufacturing Company",
    "wof:placetype":"venue"
},
  "geometry": {"coordinates":[-73.092839,44.345896],"type":"Point"}
}