{
  "type": "Feature",
  "properties": {
    "iso:country":"US",
    "sg:address":"211 Allen St",
    "sg:city":"Barre",
    "sg:classifiers":[
        {
            "category":"Farming",
            "subcategory":"Farm",
            "type":"Manufacturing & Wholesale Goods"
        }
    ],
    "sg:phone":"+1 802 476 0508",
    "sg:postcode":"05641",
    "sg:province":"VT",
    "wof:name":"Bedard Brother's Farm",
    "wof:placetype":"venue"
},
  "geometry": {"coordinates":[-72.509394,44.183853],"type":"Point"}
}