{
  "type": "Feature",
  "properties": {
    "iso:country":"US",
    "sg:address":"155 Dorset St",
    "sg:city":"South Burlington",
    "sg:classifiers":[
        {
            "category":"Restaurant",
            "type":"Food & Drink"
        }
    ],
    "sg:menulink":"http://www.allmenus.com/vt/south-burlington/213001-mcdonalds/menu/",
    "sg:phone":"+1 802 862 7733",
    "sg:postcode":"05403",
    "sg:province":"VT",
    "sg:tags":[
        "burger",
        "american"
    ],
    "wof:name":"McDonald's",
    "wof:placetype":"venue"
},
  "geometry": {"coordinates":[-73.184211,44.464893],"type":"Point"}
}