{
  "type": "Feature",
  "properties": {
    "addr:full":"205 River St Essex Junction VT 05452",
    "addr:housenumber":"205",
    "addr:postcode":"05452",
    "addr:street":"River St",
    "iso:country":"US",
    "sg:address":"205 River St",
    "sg:city":"Essex Junction",
    "sg:classifiers":[
        {
            "category":"Real Estate",
            "subcategory":"Real Estate Agent",
            "type":"Services"
        }
    ],
    "sg:phone":"+1 802 879 1180",
    "sg:postcode":"05452",
    "sg:province":"VT",
    "wof:name":"Alling Realty Corporation",
    "wof:placetype":"venue"
},
  "geometry": {"coordinates":[-73.112133,44.484259],"type":"Point"}
}