{
  "type": "Feature",
  "properties": {
    "iso:country":"US",
    "sg:address":"102 Meadow Dr",
    "sg:city":"Morrisville",
    "sg:classifiers":[
        {
            "category":"Utilities",
            "subcategory":"Refuse",
            "type":"Services"
        }
    ],
    "sg:phone":"+1 802 888 2469",
    "sg:postcode":"05661",
    "sg:province":"VT",
    "sg:tags":[
        "garbage",
        "collection"
    ],
    "wof:name":"Lamoille Kennels",
    "wof:placetype":"venue"
},
  "geometry": {"coordinates":[-72.619573,44.546615],"type":"Point"}
}