{
  "type": "Feature",
  "properties": {
    "iso:country":"US",
    "sg:address":"429 Rabbit Hollow Rd",
    "sg:city":"Northfield",
    "sg:classifiers":[
        {
            "category":"Manufacturing",
            "subcategory":"Printing",
            "type":"Manufacturing & Wholesale Goods"
        }
    ],
    "sg:phone":"+1 802 229 2288",
    "sg:postcode":"05663",
    "sg:province":"VT",
    "sg:tags":[
        "publisher"
    ],
    "wof:name":"Mythical Books",
    "wof:placetype":"venue"
},
  "geometry": {"coordinates":[-72.735011,44.12102],"type":"Point"}
}