{
  "type": "Feature",
  "properties": {
    "iso:country":"US",
    "sg:address":"32 Malletts Bay Ave",
    "sg:city":"Winooski",
    "sg:classifiers":[
        {
            "category":"Food & Beverages",
            "subcategory":"Groceries & Convenience Stores",
            "type":"Retail Goods"
        }
    ],
    "sg:phone":"+1 802 655 0099",
    "sg:postcode":"05404",
    "sg:province":"VT",
    "sg:tags":[
        "market"
    ],
    "wof:name":"Euro Market",
    "wof:placetype":"venue"
},
  "geometry": {"coordinates":[-73.190319,44.492554],"type":"Point"}
}