{
  "type": "Feature",
  "properties": {
    "iso:country":"US",
    "sg:address":"1155 Putney Rd",
    "sg:city":"Brattleboro",
    "sg:classifiers":[
        {
            "category":"Restaurant",
            "type":"Food & Drink"
        }
    ],
    "sg:phone":"+1 802 257 5065",
    "sg:postcode":"05301",
    "sg:province":"VT",
    "sg:tags":[
        "eating"
    ],
    "wof:name":"Brattleboro Village Pizza",
    "wof:placetype":"venue"
},
  "geometry": {"coordinates":[-72.55604700000001,42.88572],"type":"Point"}
}