{
  "type": "Feature",
  "properties": {
    "iso:country":"US",
    "sg:address":"606 State Rte 12",
    "sg:city":"Northfield",
    "sg:classifiers":[
        {
            "category":"Banks & Credit Unions",
            "subcategory":"Investment Brokerage",
            "type":"Services"
        },
        {
            "category":"Insurance",
            "subcategory":"Insurance Agent",
            "type":"Services"
        }
    ],
    "sg:phone":"+1 802 485 6953",
    "sg:postcode":"05663",
    "sg:province":"VT",
    "sg:tags":[
        "security"
    ],
    "wof:name":"John F Fricke & Associates",
    "wof:placetype":"venue"
},
  "geometry": {"coordinates":[-72.65749099999999,44.140286],"type":"Point"}
}