{
  "type": "Feature",
  "properties": {
    "addr:full":"605 Awesome View Ln Dorset VT 05251",
    "addr:housenumber":"605",
    "addr:postcode":"05251",
    "addr:street":"Awesome View Ln",
    "iso:country":"US",
    "sg:address":"605 Awesome View Ln",
    "sg:city":"Dorset",
    "sg:classifiers":[
        {
            "category":"Manufacturing",
            "subcategory":"Metals",
            "type":"Manufacturing & Wholesale Goods"
        }
    ],
    "sg:phone":"+1 802 867 5949",
    "sg:postcode":"05251",
    "sg:province":"VT",
    "sg:tags":[
        "used",
        "hydrant",
        "for",
        "mfg",
        "operates",
        "water",
        "brass"
    ],
    "wof:name":"Rogers Corp",
    "wof:placetype":"venue"
},
  "geometry": {"coordinates":[-73.09257599999999,43.248257],"type":"Point"}
}