{
  "type": "Feature",
  "properties": {
    "iso:country":"US",
    "sg:address":"69 Basswood Ridge",
    "sg:city":"Colchester",
    "sg:classifiers":[
        {
            "category":"Real Estate",
            "subcategory":"Real Estate Operator",
            "type":"Services"
        }
    ],
    "sg:phone":"+1 802 879 0708",
    "sg:postcode":"05446",
    "sg:province":"VT",
    "sg:tags":[
        "building",
        "nonresidential"
    ],
    "wof:name":"Set Two Properties LLC",
    "wof:placetype":"venue"
},
  "geometry": {"coordinates":[-73.18850399999999,44.566594],"type":"Point"}
}