{
  "type": "Feature",
  "properties": {
    "iso:country":"US",
    "sg:address":"101 Panton Rd",
    "sg:city":"Vergennes",
    "sg:classifiers":[
        {
            "category":"Manufacturing",
            "subcategory":"Electronics",
            "type":"Manufacturing & Wholesale Goods"
        }
    ],
    "sg:phone":"+1 802 877 2182",
    "sg:postcode":"05491",
    "sg:province":"VT",
    "sg:tags":[
        "equipment",
        "component",
        "electronic",
        "mfg"
    ],
    "sg:website":"www.nathaniel.com",
    "wof:name":"Nathaniel Electronics",
    "wof:placetype":"venue"
},
  "geometry": {"coordinates":[-73.26998,44.161973],"type":"Point"}
}