{
  "type": "Feature",
  "properties": {
    "iso:country":"US",
    "sg:address":"152 Main St",
    "sg:city":"Stowe",
    "sg:classifiers":[
        {
            "category":"Real Estate",
            "subcategory":"Architect",
            "type":"Services"
        }
    ],
    "sg:phone":"+1 802 253 7628",
    "sg:postcode":"05672",
    "sg:province":"VT",
    "wof:name":"Working Design GKW",
    "wof:placetype":"venue"
},
  "geometry": {"coordinates":[-72.684485,44.465243],"type":"Point"}
}