{
  "type": "Feature",
  "properties": {
    "iso:country":"US",
    "sg:address":"1572 Pawlet Mountain Rd",
    "sg:city":"Pawlet",
    "sg:classifiers":[
        {
            "category":"Farming",
            "subcategory":"Farm",
            "type":"Manufacturing & Wholesale Goods"
        }
    ],
    "sg:phone":"+1 802 394 2412",
    "sg:postcode":"05761",
    "sg:province":"VT",
    "sg:tags":[
        "crop",
        "general"
    ],
    "wof:name":"Chambeau Family Farm LLC",
    "wof:placetype":"venue"
},
  "geometry": {"coordinates":[-73.205581,43.269535],"type":"Point"}
}