{
  "type": "Feature",
  "properties": {
    "iso:country":"US",
    "sg:address":"665 State Rte 10",
    "sg:city":"Chester",
    "sg:classifiers":[
        {
            "category":"Restaurant",
            "type":"Food & Drink"
        }
    ],
    "sg:phone":"+1 802 875 2346",
    "sg:postcode":"05143",
    "sg:province":"VT",
    "wof:name":"Old Town Farm Inn",
    "wof:placetype":"venue"
},
  "geometry": {"coordinates":[-72.595613,43.327339],"type":"Point"}
}