{
  "type": "Feature",
  "properties": {
    "iso:country":"US",
    "sg:address":"439 Main St",
    "sg:city":"Bennington",
    "sg:classifiers":[
        {
            "category":"Home & Garden",
            "subcategory":"Building Materials",
            "type":"Retail Goods"
        }
    ],
    "sg:phone":"+1 802 440 8046",
    "sg:postcode":"05201",
    "sg:province":"VT",
    "wof:name":"Guardian Building Products",
    "wof:placetype":"venue"
},
  "geometry": {"coordinates":[-73.19581599999999,42.878121],"type":"Point"}
}