{
  "type": "Feature",
  "properties": {
    "addr:full":"28 Hudson Ter Pittsford VT 05763",
    "addr:housenumber":"28",
    "addr:postcode":"05763",
    "addr:street":"Hudson Ter",
    "iso:country":"US",
    "sg:address":"28 Hudson Ter",
    "sg:city":"Pittsford",
    "sg:classifiers":[
        {
            "category":"Professional",
            "subcategory":"Management & Consulting",
            "type":"Services"
        }
    ],
    "sg:phone":"+1 802 483 2081",
    "sg:postcode":"05763",
    "sg:province":"VT",
    "wof:name":"Cradle To Cubby",
    "wof:placetype":"venue"
},
  "geometry": {"coordinates":[-72.985479,43.695608],"type":"Point"}
}