{
  "type": "Feature",
  "properties": {
    "iso:country":"US",
    "sg:address":"1 Main St",
    "sg:city":"Burlington",
    "sg:classifiers":[
        {
            "category":"Health Services",
            "subcategory":"Doctor",
            "type":"Services"
        }
    ],
    "sg:phone":"+1 802 651 1050",
    "sg:postcode":"05401",
    "sg:province":"VT",
    "sg:tags":[
        "physician",
        "surgeon"
    ],
    "wof:name":"American Academy-Pediatrics",
    "wof:placetype":"venue"
},
  "geometry": {"coordinates":[-73.218661,44.475724],"type":"Point"}
}