{
  "type": "Feature",
  "properties": {
    "iso:country":"US",
    "sg:address":"539 Moscow Rd",
    "sg:city":"Moscow",
    "sg:classifiers":[
        {
            "category":"Shopping",
            "subcategory":"Discount & Variety Stores",
            "type":"Retail Goods"
        }
    ],
    "sg:phone":"+1 802 253 7363",
    "sg:postcode":"05672",
    "sg:province":"VT",
    "sg:tags":[
        "merchandise",
        "general"
    ],
    "wof:name":"Moscow General Store",
    "wof:placetype":"venue"
},
  "geometry": {"coordinates":[-72.717744,44.441908],"type":"Point"}
}