{
  "type": "Feature",
  "properties": {
    "iso:country":"US",
    "sg:address":"366 Depot St",
    "sg:city":"Manchester Ctr",
    "sg:classifiers":[
        {
            "category":"Retail",
            "subcategory":"Self-service Laundry",
            "type":"Services"
        }
    ],
    "sg:phone":"+1 802 362 1510",
    "sg:postcode":"05255",
    "sg:province":"VT",
    "wof:name":"Manchester Laundromat",
    "wof:placetype":"venue"
},
  "geometry": {"coordinates":[-73.052053,43.174306],"type":"Point"}
}