{
  "type": "Feature",
  "properties": {
    "addr:full":"35 Johnson's Curve Rd Putney VT 05346",
    "addr:housenumber":"35",
    "addr:postcode":"05346",
    "addr:street":"Johnson'S Curve Rd",
    "iso:country":"US",
    "sg:address":"35 Johnson's Curve Rd",
    "sg:city":"Putney",
    "sg:classifiers":[
        {
            "category":"Farming",
            "subcategory":"Livestock Farm",
            "type":"Manufacturing & Wholesale Goods"
        }
    ],
    "sg:phone":"+1 802 387 4071",
    "sg:postcode":"05346",
    "sg:province":"VT",
    "sg:tags":[
        "specialty",
        "animal"
    ],
    "wof:name":"Bee Haven Apiaries of Vermont",
    "wof:placetype":"venue"
},
  "geometry": {"coordinates":[-72.53307599999999,42.960954],"type":"Point"}
}