{
  "type": "Feature",
  "properties": {
    "addr:full":"2191 Lower Waterford Rd Saint Johnsbury VT 05848",
    "addr:housenumber":"2191",
    "addr:postcode":"05848",
    "addr:street":"Lower Waterford Rd",
    "iso:country":"US",
    "sg:address":"2191 Lower Waterford Rd",
    "sg:city":"Saint Johnsbury",
    "sg:classifiers":[
        {
            "category":"Building & Trades",
            "subcategory":"Construction",
            "type":"Services"
        }
    ],
    "sg:phone":"+1 802 748 2947",
    "sg:postcode":"05848",
    "sg:province":"VT",
    "sg:tags":[
        "house"
    ],
    "wof:name":"Hooker Construction & Renovati",
    "wof:placetype":"venue"
},
  "geometry": {"coordinates":[-71.944343,44.339611],"type":"Point"}
}