{
  "type": "Feature",
  "properties": {
    "iso:country":"US",
    "sg:address":"56 Cinda St",
    "sg:city":"South Burlington",
    "sg:classifiers":[
        {
            "category":"Building & Trades",
            "subcategory":"Construction",
            "type":"Services"
        }
    ],
    "sg:phone":"+1 802 860 7315",
    "sg:postcode":"05403",
    "sg:province":"VT",
    "sg:tags":[
        "new",
        "com",
        "home"
    ],
    "wof:name":"Yandow Dousevicz Construction",
    "wof:placetype":"venue"
},
  "geometry": {"coordinates":[-73.14755100000001,44.480814],"type":"Point"}
}