{
  "type": "Feature",
  "properties": {
    "iso:country":"US",
    "sg:address":"11 Overlake Park",
    "sg:city":"Burlington",
    "sg:classifiers":[
        {
            "category":"Recreation",
            "type":"Entertainment"
        }
    ],
    "sg:phone":"+1 802 660 8944",
    "sg:postcode":"05401",
    "sg:province":"VT",
    "wof:name":"Kathy Jaffe Interactive Fitnes",
    "wof:placetype":"venue"
},
  "geometry": {"coordinates":[-73.201932,44.46919],"type":"Point"}
}