{
  "type": "Feature",
  "properties": {
    "iso:country":"US",
    "sg:address":"1425 State Rte 116",
    "sg:city":"Bristol",
    "sg:classifiers":[
        {
            "category":"Farming",
            "subcategory":"Farm",
            "type":"Manufacturing & Wholesale Goods"
        }
    ],
    "sg:phone":"+1 802 453 3348",
    "sg:postcode":"05443",
    "sg:province":"VT",
    "sg:tags":[
        "school",
        "bus",
        "crop",
        "general",
        "real estate"
    ],
    "wof:name":"Robert G Fuller",
    "wof:placetype":"venue"
},
  "geometry": {"coordinates":[-73.09699500000001,44.108892],"type":"Point"}
}