{
  "type": "Feature",
  "properties": {
    "iso:country":"US",
    "sg:address":"21 East St",
    "sg:city":"Brookfield",
    "sg:classifiers":[
        {
            "category":"Organizations",
            "subcategory":"Community Association",
            "type":"Services"
        }
    ],
    "sg:phone":"+1 802 276 9911",
    "sg:postcode":"05036",
    "sg:province":"VT",
    "wof:name":"Brookfield Masonic Temple",
    "wof:placetype":"venue"
},
  "geometry": {"coordinates":[-72.58814099999999,44.043651],"type":"Point"}
}