{
  "type": "Feature",
  "properties": {
    "addr:full":"4 Grey Birch Dr Colchester VT 05446",
    "addr:housenumber":"4",
    "addr:postcode":"05446",
    "addr:street":"Grey Birch Dr",
    "iso:country":"US",
    "sg:address":"4 Grey Birch Dr",
    "sg:city":"Colchester",
    "sg:classifiers":[
        {
            "category":"Building & Trades",
            "subcategory":"Construction",
            "type":"Services"
        }
    ],
    "sg:phone":"+1 802 864 0220",
    "sg:postcode":"05446",
    "sg:province":"VT",
    "sg:tags":[
        "contractor"
    ],
    "wof:name":"Potvin Construction Inc",
    "wof:placetype":"venue"
},
  "geometry": {"coordinates":[-73.266514,44.541975],"type":"Point"}
}