{
  "type": "Feature",
  "properties": {
    "iso:country":"US",
    "sg:address":"157 Kellogg Rd",
    "sg:city":"Colchester",
    "sg:classifiers":[
        {
            "category":"Building & Trades",
            "subcategory":"Cleaning & Sanitation",
            "type":"Services"
        }
    ],
    "sg:phone":"+1 802 879 0229",
    "sg:postcode":"05488",
    "sg:province":"VT",
    "sg:tags":[
        "house"
    ],
    "wof:name":"Superior Cleaning Svc",
    "wof:placetype":"venue"
},
  "geometry": {"coordinates":[-73.118894,44.835306],"type":"Point"}
}