{
  "type": "Feature",
  "properties": {
    "iso:country":"US",
    "sg:address":"204 Lincoln Ave",
    "sg:city":"Rutland",
    "sg:classifiers":[
        {
            "category":"Building & Trades",
            "subcategory":"Plumbing",
            "type":"Services"
        }
    ],
    "sg:phone":"+1 802 775 2893",
    "sg:postcode":"05701",
    "sg:province":"VT",
    "sg:tags":[
        "plumbing",
        "contractor"
    ],
    "wof:name":"Bernie's Plumbing & Heating",
    "wof:placetype":"venue"
},
  "geometry": {"coordinates":[-72.97887,43.625926],"type":"Point"}
}