{
  "type": "Feature",
  "properties": {
    "iso:country":"US",
    "sg:address":"1920 E Montpelier Rd",
    "sg:city":"East Montpelier",
    "sg:classifiers":[
        {
            "category":"Freight",
            "type":"Transportation"
        }
    ],
    "sg:phone":"+1 802 229 2392",
    "sg:postcode":"05651",
    "sg:province":"VT",
    "sg:tags":[
        "warehouse",
        "self",
        "storage"
    ],
    "wof:name":"Salvation Army Warehouse",
    "wof:placetype":"venue"
},
  "geometry": {"coordinates":[-72.501896,44.257332],"type":"Point"}
}