{
  "type": "Feature",
  "properties": {
    "iso:country":"US",
    "sg:address":"914 Main St",
    "sg:city":"Proctorsville",
    "sg:classifiers":[
        {
            "category":"Building & Trades",
            "subcategory":"Construction",
            "type":"Services"
        }
    ],
    "sg:phone":"+1 802 226 7561",
    "sg:postcode":"05153",
    "sg:province":"VT",
    "sg:tags":[
        "contractor"
    ],
    "wof:name":"Barr's Builders",
    "wof:placetype":"venue"
},
  "geometry": {"coordinates":[-72.63560099999999,43.384233],"type":"Point"}
}