{
  "type": "Feature",
  "properties": {
    "iso:country":"US",
    "sg:address":"145 State St",
    "sg:city":"Montpelier",
    "sg:classifiers":[
        {
            "category":"Organizations",
            "subcategory":"Religious Organization",
            "type":"Services"
        }
    ],
    "sg:phone":"+1 802 223 2477",
    "sg:postcode":"05602",
    "sg:province":"VT",
    "sg:tags":[
        "church"
    ],
    "wof:name":"First Church-Christ Scientist",
    "wof:placetype":"venue"
},
  "geometry": {"coordinates":[-72.581816,44.261553],"type":"Point"}
}