{
  "type": "Feature",
  "properties": {
    "addr:full":"145 Main St Pownal VT 05261",
    "addr:housenumber":"145",
    "addr:postcode":"05261",
    "addr:street":"Main St",
    "iso:country":"US",
    "sg:address":"145 Main St",
    "sg:city":"Pownal",
    "sg:classifiers":[
        {
            "category":"Professional",
            "subcategory":"Lawyer & Legal Services",
            "type":"Services"
        }
    ],
    "sg:phone":"+1 802 823 5034",
    "sg:postcode":"05261",
    "sg:province":"VT",
    "sg:tags":[
        "attorney"
    ],
    "wof:name":"Margaret Lillie",
    "wof:placetype":"venue"
},
  "geometry": {"coordinates":[-73.24185199999999,42.767395],"type":"Point"}
}