{
  "type": "Feature",
  "properties": {
    "iso:country":"US",
    "sg:address":"170 Main St",
    "sg:city":"Montpelier",
    "sg:classifiers":[
        {
            "category":"Education",
            "subcategory":"School",
            "type":"Public Place"
        }
    ],
    "sg:phone":"+1 802 223 3404",
    "sg:postcode":"05602",
    "sg:province":"VT",
    "sg:tags":[
        "consulting",
        "management"
    ],
    "wof:name":"Main Street Middle School",
    "wof:placetype":"venue"
},
  "geometry": {"coordinates":[-72.569231,44.26264],"type":"Point"}
}