{
  "type": "Feature",
  "properties": {
    "iso:country":"US",
    "sg:address":"314 North St",
    "sg:city":"Bennington",
    "sg:classifiers":[
        {
            "category":"Restaurant",
            "type":"Food & Drink"
        }
    ],
    "sg:phone":"+1 802 442 5140",
    "sg:postcode":"05201",
    "sg:province":"VT",
    "sg:tags":[
        "diner"
    ],
    "wof:name":"Blue Benn",
    "wof:placetype":"venue"
},
  "geometry": {"coordinates":[-73.19721199999999,42.885231],"type":"Point"}
}