{
  "type": "Feature",
  "properties": {
    "iso:country":"US",
    "sg:address":"578 Georgia Shore Rd",
    "sg:city":"St Albans",
    "sg:classifiers":[
        {
            "category":"Building & Trades",
            "subcategory":"Construction",
            "type":"Services"
        }
    ],
    "sg:phone":"+1 802 527 1398",
    "sg:postcode":"05478",
    "sg:province":"VT",
    "sg:tags":[
        "woodworker"
    ],
    "wof:name":"J & Ps Creations",
    "wof:placetype":"venue"
},
  "geometry": {"coordinates":[-73.13493800000001,44.800947],"type":"Point"}
}