{
  "type": "Feature",
  "properties": {
    "addr:full":"174 Ave C Williston VT 05495",
    "addr:housenumber":"174",
    "addr:postcode":"05495",
    "addr:street":"Ave C",
    "iso:country":"US",
    "sg:address":"174 Ave C",
    "sg:city":"Williston",
    "sg:classifiers":[
        {
            "category":"Professional",
            "subcategory":"Management & Consulting",
            "type":"Services"
        }
    ],
    "sg:phone":"+1 802 383 0944",
    "sg:postcode":"05495",
    "sg:province":"VT",
    "sg:tags":[
        "logistics"
    ],
    "wof:name":"DNL Logistics",
    "wof:placetype":"venue"
},
  "geometry": {"coordinates":[-73.125703,44.464088],"type":"Point"}
}