{
  "type": "Feature",
  "properties": {
    "iso:country":"US",
    "sg:address":"310 Brennan Woods Dr",
    "sg:city":"Williston",
    "sg:classifiers":[
        {
            "category":"Shopping",
            "subcategory":"Jewelry",
            "type":"Retail Goods"
        }
    ],
    "sg:phone":"+1 802 878 6614",
    "sg:postcode":"05495",
    "sg:province":"VT",
    "wof:name":"Sparkle Jewelry Design",
    "wof:placetype":"venue"
},
  "geometry": {"coordinates":[-73.094043,44.459182],"type":"Point"}
}