{
  "type": "Feature",
  "properties": {
    "iso:country":"US",
    "sg:address":"378 Prospect St",
    "sg:city":"Barre",
    "sg:classifiers":[
        {
            "category":"Restaurant",
            "type":"Food & Drink"
        }
    ],
    "sg:phone":"+1 802 476 7357",
    "sg:postcode":"05641",
    "sg:province":"VT",
    "sg:tags":[
        "eating"
    ],
    "wof:name":"Summit Dining Svcs Ww",
    "wof:placetype":"venue"
},
  "geometry": {"coordinates":[-72.52101999999999,44.19599],"type":"Point"}
}