{
  "type": "Feature",
  "properties": {
    "iso:country":"US",
    "sg:address":"495 Old Turnpike Rd",
    "sg:city":"Mt Holly",
    "sg:classifiers":[
        {
            "category":"Retail",
            "subcategory":"Repair Shop",
            "type":"Services"
        },
        {
            "category":"Wholesale",
            "subcategory":"Electrical",
            "type":"Manufacturing & Wholesale Goods"
        }
    ],
    "sg:phone":"+1 802 259 2213",
    "sg:postcode":"05758",
    "sg:province":"VT",
    "sg:tags":[
        "control",
        "security",
        "system",
        "furniture"
    ],
    "sg:website":"www.countrysidela.com",
    "wof:name":"Countryside Locks & Alarms",
    "wof:placetype":"venue"
},
  "geometry": {"coordinates":[-72.809535,43.453638],"type":"Point"}
}