{
  "type": "Feature",
  "properties": {
    "iso:country":"US",
    "sg:address":"65 Cayuga Ct",
    "sg:city":"Burlington",
    "sg:classifiers":[
        {
            "category":"Wholesale",
            "subcategory":"Electrical",
            "type":"Manufacturing & Wholesale Goods"
        }
    ],
    "sg:phone":"+1 802 862 8030",
    "sg:postcode":"05408",
    "sg:province":"VT",
    "sg:tags":[
        "sound",
        "equipment",
        "system"
    ],
    "wof:name":"Kevin Healy Productions",
    "wof:placetype":"venue"
},
  "geometry": {"coordinates":[-72.575941,44.21006],"type":"Point"}
}