{
  "type": "Feature",
  "properties": {
    "iso:country":"US",
    "sg:address":"4513 Main St",
    "sg:city":"Manchester Ctr",
    "sg:classifiers":[
        {
            "category":"Shopping",
            "subcategory":"Clothing, Apparel, & Fashions",
            "type":"Retail Goods"
        }
    ],
    "sg:phone":"+1 802 362 2086",
    "sg:postcode":"05255",
    "sg:province":"VT",
    "sg:tags":[
        "sportswear"
    ],
    "wof:name":"Pacific Sunwear",
    "wof:placetype":"venue"
},
  "geometry": {"coordinates":[-73.062004,43.173055],"type":"Point"}
}