{
  "type": "Feature",
  "properties": {
    "iso:country":"US",
    "sg:address":"231 Stage Rd",
    "sg:city":"South Pomfret",
    "sg:classifiers":[
        {
            "category":"Recreation",
            "type":"Entertainment"
        }
    ],
    "sg:phone":"+1 802 457 2971",
    "sg:postcode":"05067",
    "sg:province":"VT",
    "sg:tags":[
        "instruction",
        "skiing"
    ],
    "sg:website":"www.skirunners.org",
    "wof:name":"Woodstock Ski Runners",
    "wof:placetype":"venue"
},
  "geometry": {"coordinates":[-72.563664,43.679061],"type":"Point"}
}