{
  "type": "Feature",
  "properties": {
    "iso:country":"US",
    "sg:address":"30 Allen Rd",
    "sg:city":"Grand Isle",
    "sg:classifiers":[
        {
            "category":"Building & Trades",
            "subcategory":"Construction",
            "type":"Services"
        }
    ],
    "sg:phone":"+1 802 372 5781",
    "sg:postcode":"05458",
    "sg:province":"VT",
    "sg:tags":[
        "roofing",
        "contractor"
    ],
    "wof:name":"Turnbaugh Roofing",
    "wof:placetype":"venue"
},
  "geometry": {"coordinates":[-73.310953,44.702501],"type":"Point"}
}