{
  "type": "Feature",
  "properties": {
    "iso:country":"US",
    "sg:address":"1172 E Lakeshore Dr",
    "sg:city":"Colchester",
    "sg:classifiers":[
        {
            "category":"Professional",
            "subcategory":"Business Services",
            "type":"Services"
        }
    ],
    "sg:phone":"+1 802 878 3863",
    "sg:postcode":"05446",
    "sg:province":"VT",
    "wof:name":"Perkins Word Inc",
    "wof:placetype":"venue"
},
  "geometry": {"coordinates":[-73.195059,44.551318],"type":"Point"}
}