{
  "type": "Feature",
  "properties": {
    "addr:full":"54 Twin Oaks Ter South Burlington VT 05403",
    "addr:housenumber":"54",
    "addr:postcode":"05403",
    "addr:street":"Twin Oaks Ter",
    "iso:country":"US",
    "sg:address":"54 Twin Oaks Ter",
    "sg:city":"South Burlington",
    "sg:classifiers":[
        {
            "category":"Organizations",
            "subcategory":"Non-profit Organization",
            "type":"Services"
        }
    ],
    "sg:phone":"+1 802 847 7880",
    "sg:postcode":"05403",
    "sg:province":"VT",
    "sg:tags":[
        "info",
        "addiction",
        "abuse",
        "treatment",
        "drug"
    ],
    "wof:name":"UVM Treatment Research Ctr",
    "wof:placetype":"venue"
},
  "geometry": {"coordinates":[-73.16933899999999,44.451183],"type":"Point"}
}