{
  "type": "Feature",
  "properties": {
    "iso:country":"US",
    "sg:address":"35 Dorset Ln",
    "sg:city":"Williston",
    "sg:classifiers":[
        {
            "category":"Social Services",
            "subcategory":"Child Care",
            "type":"Services"
        }
    ],
    "sg:phone":"+1 802 878 5899",
    "sg:postcode":"05495",
    "sg:province":"VT",
    "wof:name":"Children Unlimited Inc",
    "wof:placetype":"venue"
},
  "geometry": {"coordinates":[-73.11904,44.476651],"type":"Point"}
}