{
  "type": "Feature",
  "properties": {
    "addr:full":"96 Airport Rd Shaftsbury VT 05262",
    "addr:housenumber":"96",
    "addr:postcode":"05262",
    "addr:street":"Airport Rd",
    "iso:country":"US",
    "sg:address":"96 Airport Rd",
    "sg:city":"Shaftsbury",
    "sg:classifiers":[
        {
            "category":"Government",
            "subcategory":"Police Station",
            "type":"Public Place"
        }
    ],
    "sg:phone":"+1 802 442 5421",
    "sg:postcode":"05262",
    "sg:province":"VT",
    "sg:tags":[
        "state"
    ],
    "wof:name":"State Police",
    "wof:placetype":"venue"
},
  "geometry": {"coordinates":[-73.202218,42.955636],"type":"Point"}
}