{
  "type": "Feature",
  "properties": {
    "addr:full":"3 Church St Woodstock VT 05091",
    "addr:housenumber":"3",
    "addr:postcode":"05091",
    "addr:street":"Church St",
    "iso:country":"US",
    "sg:address":"3 Church St",
    "sg:city":"Woodstock",
    "sg:classifiers":[
        {
            "category":"Travel",
            "subcategory":"Hotels & Motels",
            "type":"Entertainment"
        }
    ],
    "sg:phone":"+1 802 457 1925",
    "sg:postcode":"05091",
    "sg:province":"VT",
    "sg:tags":[
        "breakfast",
        "accommodation",
        "bed"
    ],
    "wof:name":"Three Church Street",
    "wof:placetype":"venue"
},
  "geometry": {"coordinates":[-72.52195,43.622776],"type":"Point"}
}