{
  "type": "Feature",
  "properties": {
    "iso:country":"US",
    "sg:address":"14 College St",
    "sg:city":"Middlebury",
    "sg:classifiers":[
        {
            "category":"Food & Beverages",
            "subcategory":"Bakery",
            "type":"Retail Goods"
        }
    ],
    "sg:phone":"+1 802 388 3371",
    "sg:postcode":"05753",
    "sg:province":"VT",
    "wof:name":"Otter Creek Bakery",
    "wof:placetype":"venue"
},
  "geometry": {"coordinates":[-73.179557,44.010099],"type":"Point"}
}