{
  "type": "Feature",
  "properties": {
    "iso:country":"US",
    "sg:address":"46 Granite St",
    "sg:city":"Barre",
    "sg:classifiers":[
        {
            "category":"Professional",
            "type":"Services"
        }
    ],
    "sg:phone":"+1 802 476 0567",
    "sg:postcode":"05641",
    "sg:province":"VT",
    "sg:tags":[
        "establishment"
    ],
    "wof:name":"Barre Historical Society",
    "wof:placetype":"venue"
},
  "geometry": {"coordinates":[-72.506924,44.199059],"type":"Point"}
}