{
  "type": "Feature",
  "properties": {
    "iso:country":"US",
    "sg:address":"16 Tigan St Ste A",
    "sg:city":"Winooski",
    "sg:classifiers":[
        {
            "category":"Manufacturing",
            "subcategory":"Metals",
            "type":"Manufacturing & Wholesale Goods"
        },
        {
            "category":"Building & Trades",
            "subcategory":"Construction",
            "type":"Services"
        },
        {
            "category":"Manufacturing",
            "subcategory":"Building Materials",
            "type":"Manufacturing & Wholesale Goods"
        }
    ],
    "sg:phone":"+1 802 655 8805",
    "sg:postcode":"05404",
    "sg:province":"VT",
    "sg:tags":[
        "sheet",
        "specialty",
        "work",
        "heating",
        "system",
        "fabricator",
        "contractor",
        "air conditioning"
    ],
    "sg:website":"http://www.vhv.com",
    "wof:name":"Quality Air Control",
    "wof:placetype":"venue"
},
  "geometry": {"coordinates":[-73.18526300000001,44.501771],"type":"Point"}
}