{
  "type": "Feature",
  "properties": {
    "iso:country":"US",
    "sg:address":"289 N Main St",
    "sg:city":"Rutland",
    "sg:classifiers":[
        {
            "category":"Building & Trades",
            "subcategory":"Landscaping Services",
            "type":"Services"
        }
    ],
    "sg:phone":"+1 802 775 5686",
    "sg:postcode":"05701",
    "sg:province":"VT",
    "sg:tags":[
        "contractor",
        "nursery",
        "landscape",
        "stock"
    ],
    "wof:name":"Pak Landscape",
    "wof:placetype":"venue"
},
  "geometry": {"coordinates":[-72.97573199999999,43.626881],"type":"Point"}
}