{
  "type": "Feature",
  "properties": {
    "addr:full":"106 John Taplin Rd Derby VT 05829",
    "addr:housenumber":"106",
    "addr:postcode":"05829",
    "addr:street":"John Taplin Rd",
    "iso:country":"US",
    "sg:address":"106 John Taplin Rd",
    "sg:city":"Derby",
    "sg:classifiers":[
        {
            "category":"Manufacturing",
            "subcategory":"Tools & Machinery",
            "type":"Manufacturing & Wholesale Goods"
        }
    ],
    "sg:phone":"+1 802 766 5396",
    "sg:postcode":"05829",
    "sg:province":"VT",
    "sg:tags":[
        "building",
        "shop",
        "industrial",
        "mfg",
        "nonresidential",
        "machine"
    ],
    "wof:name":"North Country Engineering Inc",
    "wof:placetype":"venue"
},
  "geometry": {"coordinates":[-72.11622199999999,44.94613],"type":"Point"}
}