{
  "type": "Feature",
  "properties": {
    "iso:country":"US",
    "sg:address":"40 Depot Rd",
    "sg:city":"Colchester",
    "sg:classifiers":[
        {
            "category":"Building & Trades",
            "subcategory":"Construction",
            "type":"Services"
        }
    ],
    "sg:phone":"+1 802 878 9464",
    "sg:postcode":"05446",
    "sg:province":"VT",
    "sg:tags":[
        "painter"
    ],
    "wof:name":"Pioneer Painting Co",
    "wof:placetype":"venue"
},
  "geometry": {"coordinates":[-73.144102,44.545748],"type":"Point"}
}