{
  "type": "Feature",
  "properties": {
    "addr:full":"75 Pearl St Essex Junction VT 05452",
    "addr:housenumber":"75",
    "addr:postcode":"05452",
    "addr:street":"Pearl St",
    "iso:country":"US",
    "sg:address":"75 Pearl St",
    "sg:city":"Essex Junction",
    "sg:classifiers":[
        {
            "category":"Shopping",
            "subcategory":"Pharmacy",
            "type":"Retail Goods"
        }
    ],
    "sg:phone":"+1 802 878 1668",
    "sg:postcode":"05452",
    "sg:province":"VT",
    "wof:name":"Brooks Pharmacy",
    "wof:placetype":"venue"
},
  "geometry": {"coordinates":[-73.123955,44.496204],"type":"Point"}
}