{
  "type": "Feature",
  "properties": {
    "addr:full":"1772 Hunt Rd New Haven VT 05472",
    "addr:housenumber":"1772",
    "addr:postcode":"05472",
    "addr:street":"Hunt Rd",
    "iso:country":"US",
    "sg:address":"1772 Hunt Rd",
    "sg:city":"New Haven",
    "sg:classifiers":[
        {
            "category":"Professional",
            "type":"Services"
        }
    ],
    "sg:phone":"+1 802 388 6232",
    "sg:postcode":"05472",
    "sg:province":"VT",
    "wof:name":"Thornapple Creations",
    "wof:placetype":"venue"
},
  "geometry": {"coordinates":[-73.151628,44.069507],"type":"Point"}
}