{
  "type": "Feature",
  "properties": {
    "addr:full":"99 Engineers Dr Williston VT 05495",
    "addr:housenumber":"99",
    "addr:postcode":"05495",
    "addr:street":"Engineers Dr",
    "iso:country":"US",
    "sg:address":"99 Engineers Dr",
    "sg:city":"Williston",
    "sg:classifiers":[
        {
            "category":"Retail",
            "subcategory":"Auto Repair",
            "type":"Services"
        }
    ],
    "sg:phone":"+1 802 862 9894",
    "sg:postcode":"05495",
    "sg:province":"VT",
    "sg:tags":[
        "truck"
    ],
    "wof:name":"Korpi Truck Svc",
    "wof:placetype":"venue"
},
  "geometry": {"coordinates":[-73.133815,44.455872],"type":"Point"}
}