{
  "type": "Feature",
  "properties": {
    "iso:country":"US",
    "sg:address":"75 Central St",
    "sg:city":"Woodstock",
    "sg:classifiers":[
        {
            "category":"Shopping",
            "subcategory":"Gifts & Souvenirs",
            "type":"Retail Goods"
        }
    ],
    "sg:phone":"+1 802 457 9366",
    "sg:postcode":"05091",
    "sg:province":"VT",
    "sg:tags":[
        "shop"
    ],
    "wof:name":"Fossilglass",
    "wof:placetype":"venue"
},
  "geometry": {"coordinates":[-72.514251,43.626701],"type":"Point"}
}