{
  "type": "Feature",
  "properties": {
    "iso:country":"US",
    "sg:address":"19 E Manchester Rd",
    "sg:city":"Manchester Ctr",
    "sg:classifiers":[
        {
            "category":"Health Services",
            "subcategory":"Chiropractor",
            "type":"Services"
        }
    ],
    "sg:phone":"+1 802 362 3040",
    "sg:postcode":"05255",
    "sg:province":"VT",
    "wof:name":"Chiropractic Care Ctr",
    "wof:placetype":"venue"
},
  "geometry": {"coordinates":[-73.04908500000001,43.167569],"type":"Point"}
}