{
  "type": "Feature",
  "properties": {
    "addr:full":"85 Gates St White River Junction VT 05001",
    "addr:housenumber":"85",
    "addr:postcode":"05001",
    "addr:street":"Gates St",
    "iso:country":"US",
    "sg:address":"85 Gates St",
    "sg:city":"White River Junction",
    "sg:classifiers":[
        {
            "category":"Personal",
            "subcategory":"Beauty Salon",
            "type":"Services"
        }
    ],
    "sg:phone":"+1 802 649 8100",
    "sg:postcode":"05001",
    "sg:province":"VT",
    "sg:tags":[
        "shop"
    ],
    "wof:name":"Figaros Scissors",
    "wof:placetype":"venue"
},
  "geometry": {"coordinates":[-72.321276,43.648589],"type":"Point"}
}