{
  "type": "Feature",
  "properties": {
    "addr:full":"95 Planeview Rd Morrisville VT 05661",
    "addr:housenumber":"95",
    "addr:postcode":"05661",
    "addr:street":"Planeview Rd",
    "iso:country":"US",
    "sg:address":"95 Planeview Rd",
    "sg:city":"Morrisville",
    "sg:classifiers":[
        {
            "category":"Shopping",
            "subcategory":"Used Merchandise",
            "type":"Retail Goods"
        }
    ],
    "sg:phone":"+1 802 888 4577",
    "sg:postcode":"05661",
    "sg:province":"VT",
    "wof:name":"Plane View Used Furniture",
    "wof:placetype":"venue"
},
  "geometry": {"coordinates":[-72.618358,44.52862],"type":"Point"}
}