{
  "type": "Feature",
  "properties": {
    "addr:full":"41 Pleasant St Woodstock VT 05091",
    "addr:housenumber":"41",
    "addr:postcode":"05091",
    "addr:street":"Pleasant St",
    "iso:country":"US",
    "sg:address":"41 Pleasant St",
    "sg:city":"Woodstock",
    "sg:classifiers":[
        {
            "category":"Travel",
            "subcategory":"Hotels & Motels",
            "type":"Entertainment"
        }
    ],
    "sg:phone":"+1 802 457 1255",
    "sg:postcode":"05091",
    "sg:province":"VT",
    "sg:tags":[
        "breakfast",
        "accommodation",
        "bed"
    ],
    "wof:name":"Village Inn",
    "wof:placetype":"venue"
},
  "geometry": {"coordinates":[-72.510898,43.626753],"type":"Point"}
}