{
  "type": "Feature",
  "properties": {
    "iso:country":"US",
    "sg:address":"38 Range Rd",
    "sg:city":"Underhill",
    "sg:classifiers":[
        {
            "category":"Building & Trades",
            "subcategory":"Construction",
            "type":"Services"
        }
    ],
    "sg:phone":"+1 802 899 1430",
    "sg:postcode":"05489",
    "sg:province":"VT",
    "sg:tags":[
        "remodeling",
        "painting",
        "contractor"
    ],
    "wof:name":"Bahr Property Management",
    "wof:placetype":"venue"
},
  "geometry": {"coordinates":[-72.904207,44.507575],"type":"Point"}
}