{
  "type": "Feature",
  "properties": {
    "addr:full":"109 S Main St Waterbury VT 05676",
    "addr:housenumber":"109",
    "addr:postcode":"05676",
    "addr:street":"S Main St",
    "iso:country":"US",
    "sg:address":"109 S Main St",
    "sg:city":"Waterbury",
    "sg:classifiers":[
        {
            "category":"Organizations",
            "subcategory":"Religious Organization",
            "type":"Services"
        }
    ],
    "sg:phone":"+1 802 244 7734",
    "sg:postcode":"05676",
    "sg:province":"VT",
    "wof:name":"Saintandrew Perish",
    "wof:placetype":"venue"
},
  "geometry": {"coordinates":[-72.75059899999999,44.331905],"type":"Point"}
}