{
  "type": "Feature",
  "properties": {
    "addr:full":"65 Winooski Falls Way Winooski VT 05404",
    "addr:housenumber":"65",
    "addr:postcode":"05404",
    "addr:street":"Winooski Falls Way",
    "iso:country":"US",
    "sg:address":"65 Winooski Falls Way",
    "sg:city":"Winooski",
    "sg:classifiers":[
        {
            "category":"Deli",
            "type":"Food & Drink"
        }
    ],
    "sg:phone":"+1 802 651 4056",
    "sg:postcode":"05404",
    "sg:province":"VT",
    "sg:tags":[
        "delicatessen"
    ],
    "wof:name":"Winooski Falls Market & Deli",
    "wof:placetype":"venue"
},
  "geometry": {"coordinates":[-73.182689,44.49025],"type":"Point"}
}