{
  "type": "Feature",
  "properties": {
    "iso:country":"US",
    "sg:address":"27 Main St",
    "sg:city":"Bristol",
    "sg:classifiers":[
        {
            "category":"Shopping",
            "subcategory":"Used Merchandise",
            "type":"Retail Goods"
        }
    ],
    "sg:phone":"+1 802 453 5020",
    "sg:postcode":"05443",
    "sg:province":"VT",
    "sg:tags":[
        "antique"
    ],
    "wof:name":"Bristol Antique Shoppe",
    "wof:placetype":"venue"
},
  "geometry": {"coordinates":[-73.078,44.132988],"type":"Point"}
}