{
  "type": "Feature",
  "properties": {
    "iso:country":"US",
    "sg:address":"105 Court St",
    "sg:city":"Middlebury",
    "sg:classifiers":[
        {
            "category":"Retail",
            "subcategory":"Photofinishing",
            "type":"Services"
        }
    ],
    "sg:phone":"+1 802 388 4404",
    "sg:postcode":"05753",
    "sg:province":"VT",
    "sg:tags":[
        "photo",
        "finishing"
    ],
    "wof:name":"Lightning Photo Inc",
    "wof:placetype":"venue"
},
  "geometry": {"coordinates":[-73.16075499999999,44.006985],"type":"Point"}
}