{
  "type": "Feature",
  "properties": {
    "iso:country":"US",
    "sg:address":"108 Mountain Rd",
    "sg:city":"Waterbury",
    "sg:classifiers":[
        {
            "category":"Building & Trades",
            "subcategory":"Construction",
            "type":"Services"
        }
    ],
    "sg:phone":"+1 802 244 8659",
    "sg:postcode":"05672",
    "sg:province":"VT",
    "sg:tags":[
        "dry wall",
        "contractor"
    ],
    "wof:name":"Central Vermont Drywall",
    "wof:placetype":"venue"
},
  "geometry": {"coordinates":[-72.688419,44.467817],"type":"Point"}
}