{
  "type": "Feature",
  "properties": {
    "addr:full":"90 5th Ave St Johnsbury VT 05819",
    "addr:housenumber":"90",
    "addr:postcode":"05819",
    "addr:street":"5Th Ave",
    "iso:country":"US",
    "sg:address":"90 5th Ave",
    "sg:city":"St Johnsbury",
    "sg:classifiers":[
        {
            "category":"Retail",
            "subcategory":"Repair Shop",
            "type":"Services"
        }
    ],
    "sg:phone":"+1 802 748 0077",
    "sg:postcode":"05819",
    "sg:province":"VT",
    "sg:tags":[
        "refinishing",
        "furniture"
    ],
    "wof:name":"Chair Care & Klappert Furn",
    "wof:placetype":"venue"
},
  "geometry": {"coordinates":[-72.018264,44.415599],"type":"Point"}
}