{
  "type": "Feature",
  "properties": {
    "iso:country":"US",
    "sg:address":"97 Tracy Dr",
    "sg:city":"Burlington",
    "sg:classifiers":[
        {
            "category":"Building & Trades",
            "subcategory":"Construction",
            "type":"Services"
        }
    ],
    "sg:phone":"+1 802 862 9159",
    "sg:postcode":"05408",
    "sg:province":"VT",
    "sg:tags":[
        "house"
    ],
    "wof:name":"Ken Eldred Builder",
    "wof:placetype":"venue"
},
  "geometry": {"coordinates":[-72.496494,44.196121],"type":"Point"}
}