{
  "type": "Feature",
  "properties": {
    "addr:full":"1 Cinda St South Burlington VT 05403",
    "addr:housenumber":"1",
    "addr:postcode":"05403",
    "addr:street":"Cinda St",
    "iso:country":"US",
    "sg:address":"1 Cinda St",
    "sg:city":"South Burlington",
    "sg:classifiers":[
        {
            "category":"Health Services",
            "subcategory":"Doctor",
            "type":"Services"
        }
    ],
    "sg:phone":"+1 802 862 7569",
    "sg:postcode":"05403",
    "sg:province":"VT",
    "wof:name":"Associates In Orthodontics PC",
    "wof:placetype":"venue"
},
  "geometry": {"coordinates":[-73.14804599999999,44.48166],"type":"Point"}
}