{
  "type": "Feature",
  "properties": {
    "iso:country":"US",
    "sg:address":"983 Romar Rd",
    "sg:city":"East Fairfield",
    "sg:classifiers":[
        {
            "category":"Retail",
            "subcategory":"Repair Shop",
            "type":"Services"
        }
    ],
    "sg:phone":"+1 802 827 6681",
    "sg:postcode":"05448",
    "sg:province":"VT",
    "sg:tags":[
        "building",
        "apartment",
        "upholsterer"
    ],
    "wof:name":"Essex Upholstery Shop",
    "wof:placetype":"venue"
},
  "geometry": {"coordinates":[-72.91233,44.765557],"type":"Point"}
}