{
  "type": "Feature",
  "properties": {
    "iso:country":"US",
    "sg:address":"198 Charles Ave",
    "sg:city":"Middlebury",
    "sg:classifiers":[
        {
            "category":"Shopping",
            "subcategory":"Used Merchandise",
            "type":"Retail Goods"
        }
    ],
    "sg:phone":"+1 802 388 6546",
    "sg:postcode":"05753",
    "sg:province":"VT",
    "wof:name":"Goodwins Antiques",
    "wof:placetype":"venue"
},
  "geometry": {"coordinates":[-73.163436,44.008671],"type":"Point"}
}