{
  "type": "Feature",
  "properties": {
    "addr:full":"79 N Main St St Albans VT 05478",
    "addr:housenumber":"79",
    "addr:postcode":"05478",
    "addr:street":"N Main St",
    "iso:country":"US",
    "sg:address":"79 N Main St",
    "sg:city":"St Albans",
    "sg:classifiers":[
        {
            "category":"Professional",
            "subcategory":"Management & Consulting",
            "type":"Services"
        }
    ],
    "sg:phone":"+1 802 524 0963",
    "sg:postcode":"05478",
    "sg:province":"VT",
    "sg:tags":[
        "consultant",
        "business"
    ],
    "wof:name":"Little Apple Press",
    "wof:placetype":"venue"
},
  "geometry": {"coordinates":[-73.083232,44.811585],"type":"Point"}
}