{
  "type": "Feature",
  "properties": {
    "iso:country":"US",
    "sg:address":"4 Autumn St",
    "sg:city":"St Johnsbury",
    "sg:classifiers":[
        {
            "category":"Freight",
            "type":"Transportation"
        }
    ],
    "sg:phone":"+1 802 748 4304",
    "sg:postcode":"05819",
    "sg:province":"VT",
    "sg:tags":[
        "trucking"
    ],
    "wof:name":"John Colgrove Trucking",
    "wof:placetype":"venue"
},
  "geometry": {"coordinates":[-72.025479,44.419546],"type":"Point"}
}