{
  "type": "Feature",
  "properties": {
    "iso:country":"US",
    "sg:address":"2767 Fay Brook Rd",
    "sg:city":"Sharon",
    "sg:classifiers":[
        {
            "category":"Retail",
            "subcategory":"Animal Services",
            "type":"Services"
        }
    ],
    "sg:phone":"+1 802 763 2516",
    "sg:postcode":"05065",
    "sg:province":"VT",
    "wof:name":"Denlore Morgan Horse Farm",
    "wof:placetype":"venue"
},
  "geometry": {"coordinates":[-72.442965,43.813815],"type":"Point"}
}