{
  "type": "Feature",
  "properties": {
    "iso:country":"US",
    "sg:address":"35 Terrace St",
    "sg:city":"Montpelier",
    "sg:classifiers":[
        {
            "category":"Health Services",
            "subcategory":"Health Practitioner",
            "type":"Services"
        }
    ],
    "sg:phone":"+1 802 229 5296",
    "sg:postcode":"05602",
    "sg:province":"VT",
    "sg:tags":[
        "psychologist"
    ],
    "sg:website":"www.dmcoaching.com",
    "wof:name":"Diana Mc Leod Pro Coaching",
    "wof:placetype":"venue"
},
  "geometry": {"coordinates":[-72.586737,44.266208],"type":"Point"}
}