{
  "type": "Feature",
  "properties": {
    "addr:full":"195 Falls Rd Shelburne VT 05482",
    "addr:housenumber":"195",
    "addr:postcode":"05482",
    "addr:street":"Falls Rd",
    "iso:country":"US",
    "sg:address":"195 Falls Rd",
    "sg:city":"Shelburne",
    "sg:classifiers":[
        {
            "category":"Restaurant",
            "type":"Food & Drink"
        }
    ],
    "sg:phone":"+1 802 985 9100",
    "sg:postcode":"05482",
    "sg:province":"VT",
    "sg:tags":[
        "traditional",
        "american"
    ],
    "sg:website":"theshelburnekitchen.com/",
    "wof:name":"The Shelburne Kitchen",
    "wof:placetype":"venue"
},
  "geometry": {"coordinates":[-73.22631800000001,44.378006],"type":"Point"}
}