{
  "type": "Feature",
  "properties": {
    "iso:country":"US",
    "sg:address":"234 N Main St",
    "sg:city":"Danby",
    "sg:classifiers":[
        {
            "category":"Education",
            "subcategory":"School",
            "type":"Public Place"
        }
    ],
    "sg:phone":"+1 802 293 5191",
    "sg:postcode":"05739",
    "sg:province":"VT",
    "wof:name":"Currier Memorial School",
    "wof:placetype":"venue"
},
  "geometry": {"coordinates":[-72.99691300000001,43.350695],"type":"Point"}
}