{
  "type": "Feature",
  "properties": {
    "iso:country":"US",
    "sg:address":"230 Pioneer Dr",
    "sg:city":"Williston",
    "sg:classifiers":[
        {
            "category":"Wholesale",
            "subcategory":"Hardware",
            "type":"Manufacturing & Wholesale Goods"
        }
    ],
    "sg:phone":"+1 802 651 8900",
    "sg:postcode":"05495",
    "sg:province":"VT",
    "sg:tags":[
        "equipment",
        "energy",
        "solar"
    ],
    "wof:name":"Power Battery & Truck Parts",
    "wof:placetype":"venue"
},
  "geometry": {"coordinates":[-73.131373,44.443009],"type":"Point"}
}