{
  "type": "Feature",
  "properties": {
    "iso:country":"US",
    "sg:address":"30 Champlain Dr",
    "sg:city":"Colchester",
    "sg:classifiers":[
        {
            "category":"Wholesale",
            "subcategory":"Electrical",
            "type":"Manufacturing & Wholesale Goods"
        }
    ],
    "sg:phone":"+1 802 655 7090",
    "sg:postcode":"05446",
    "sg:province":"VT",
    "sg:tags":[
        "equipment",
        "electric",
        "supply"
    ],
    "wof:name":"Walsh Electric Supply Co",
    "wof:placetype":"venue"
},
  "geometry": {"coordinates":[-73.178585,44.514307],"type":"Point"}
}