{
  "type": "Feature",
  "properties": {
    "iso:country":"US",
    "sg:address":"559 Sheddsville Rd",
    "sg:city":"Brownsville",
    "sg:classifiers":[
        {
            "category":"Retail",
            "subcategory":"Repair Shop",
            "type":"Services"
        }
    ],
    "sg:phone":"+1 802 484 5048",
    "sg:postcode":"05089",
    "sg:province":"VT",
    "sg:tags":[
        "welding"
    ],
    "wof:name":"Ouelette Welding",
    "wof:placetype":"venue"
},
  "geometry": {"coordinates":[-72.4879,43.482588],"type":"Point"}
}