{
  "type": "Feature",
  "properties": {
    "iso:country":"US",
    "sg:address":"109 State St",
    "sg:city":"Montpelier",
    "sg:classifiers":[
        {
            "category":"Government",
            "subcategory":"Court House",
            "type":"Public Place"
        }
    ],
    "sg:phone":"+1 802 828 5623",
    "sg:postcode":"05602",
    "sg:province":"VT",
    "sg:tags":[
        "legal"
    ],
    "wof:name":"General Counsel & ADM Law",
    "wof:placetype":"venue"
},
  "geometry": {"coordinates":[-72.581816,44.261553],"type":"Point"}
}