{
  "type": "Feature",
  "properties": {
    "addr:full":"46 Willey St Barre VT 05641",
    "addr:housenumber":"46",
    "addr:postcode":"05641",
    "addr:street":"Willey St",
    "iso:country":"US",
    "sg:address":"46 Willey St",
    "sg:city":"Barre",
    "sg:classifiers":[
        {
            "category":"Building & Trades",
            "subcategory":"Construction",
            "type":"Services"
        }
    ],
    "sg:phone":"+1 802 479 0897",
    "sg:postcode":"05641",
    "sg:province":"VT",
    "sg:tags":[
        "sandblasting"
    ],
    "wof:name":"Dessureau Sandblast Co",
    "wof:placetype":"venue"
},
  "geometry": {"coordinates":[-72.519722,44.208799],"type":"Point"}
}