{
  "type": "Feature",
  "properties": {
    "iso:country":"US",
    "sg:address":"1433 Wayside Rd",
    "sg:city":"Woodstock",
    "sg:classifiers":[
        {
            "category":"Manufacturing",
            "subcategory":"Building Materials",
            "type":"Manufacturing & Wholesale Goods"
        },
        {
            "category":"Building & Trades",
            "subcategory":"Construction",
            "type":"Services"
        }
    ],
    "sg:phone":"+1 802 457 4933",
    "sg:postcode":"05035",
    "sg:province":"VT",
    "sg:tags":[
        "cabinet",
        "wood",
        "maker",
        "kitchen",
        "mfg"
    ],
    "wof:name":"Kenneth Scatchard Cabinets",
    "wof:placetype":"venue"
},
  "geometry": {"coordinates":[-72.59389899999999,43.668357],"type":"Point"}
}