{
  "type": "Feature",
  "properties": {
    "iso:country":"US",
    "sg:address":"104 Cheney Rd",
    "sg:city":"Dorset",
    "sg:classifiers":[
        {
            "category":"Arts & Performance",
            "subcategory":"Theater",
            "type":"Entertainment"
        }
    ],
    "sg:phone":"+1 802 867 5777",
    "sg:postcode":"05251",
    "sg:province":"VT",
    "wof:name":"Dorset Playhouse",
    "wof:placetype":"venue"
},
  "geometry": {"coordinates":[-73.101553,43.252044],"type":"Point"}
}