{
  "type": "Feature",
  "properties": {
    "iso:country":"US",
    "sg:address":"4241 State Rte 17",
    "sg:city":"Vergennes",
    "sg:classifiers":[
        {
            "category":"Autos & Motor Vehicles",
            "subcategory":"Auto Supplies",
            "type":"Retail Goods"
        }
    ],
    "sg:phone":"+1 802 759 2054",
    "sg:postcode":"05491",
    "sg:province":"VT",
    "sg:tags":[
        "automobile",
        "parts"
    ],
    "wof:name":"Reed's Sales & Svc",
    "wof:placetype":"venue"
},
  "geometry": {"coordinates":[-73.243695,44.086338],"type":"Point"}
}