{
  "type": "Feature",
  "properties": {
    "addr:full":"217 Northside Dr Bennington VT 05201",
    "addr:housenumber":"217",
    "addr:postcode":"05201",
    "addr:street":"Northside Dr",
    "iso:country":"US",
    "sg:address":"217 Northside Dr",
    "sg:city":"Bennington",
    "sg:classifiers":[
        {
            "category":"Restaurant",
            "type":"Food & Drink"
        }
    ],
    "sg:phone":"+1 802 442 5644",
    "sg:postcode":"05201",
    "sg:province":"VT",
    "wof:name":"Northside Dairy Bar",
    "wof:placetype":"venue"
},
  "geometry": {"coordinates":[-73.21046800000001,42.899899],"type":"Point"}
}