{
  "type": "Feature",
  "properties": {
    "addr:full":"171 S Main St St Albans VT 05478",
    "addr:housenumber":"171",
    "addr:postcode":"05478",
    "addr:street":"S Main St",
    "iso:country":"US",
    "sg:address":"171 S Main St",
    "sg:city":"St Albans",
    "sg:classifiers":[
        {
            "category":"Food & Beverages",
            "subcategory":"Groceries & Convenience Stores",
            "type":"Retail Goods"
        }
    ],
    "sg:phone":"+1 802 524 9123",
    "sg:postcode":"05478",
    "sg:province":"VT",
    "wof:name":"J & L's Snack Shop",
    "wof:placetype":"venue"
},
  "geometry": {"coordinates":[-73.088194,44.802389],"type":"Point"}
}