{
  "type": "Feature",
  "properties": {
    "iso:country":"US",
    "sg:address":"327 State Rte 105",
    "sg:city":"North Troy",
    "sg:classifiers":[
        {
            "category":"Recreation",
            "type":"Entertainment"
        }
    ],
    "sg:phone":"+1 802 988 9664",
    "sg:postcode":"05859",
    "sg:province":"VT",
    "wof:name":"Creative Choices Inc",
    "wof:placetype":"venue"
},
  "geometry": {"coordinates":[-72.401234,44.99528],"type":"Point"}
}