{
  "type": "Feature",
  "properties": {
    "iso:country":"US",
    "sg:address":"555 Shelburne Rd",
    "sg:city":"Burlington",
    "sg:classifiers":[
        {
            "category":"Shopping",
            "subcategory":"Clothing, Apparel, & Fashions",
            "type":"Retail Goods"
        }
    ],
    "sg:phone":"+1 802 859 1880",
    "sg:postcode":"05401",
    "sg:province":"VT",
    "wof:name":"Db/Dbw 0697",
    "wof:placetype":"venue"
},
  "geometry": {"coordinates":[-73.20929599999999,44.448468],"type":"Point"}
}