{
  "type": "Feature",
  "properties": {
    "iso:country":"US",
    "sg:address":"72 N Main St",
    "sg:city":"St Albans",
    "sg:classifiers":[
        {
            "category":"Shopping",
            "subcategory":"Hobbies, Toys, & Games",
            "type":"Retail Goods"
        }
    ],
    "sg:phone":"+1 802 524 3446",
    "sg:postcode":"05478",
    "sg:province":"VT",
    "sg:tags":[
        "supply"
    ],
    "wof:name":"Heros Kingdom",
    "wof:placetype":"venue"
},
  "geometry": {"coordinates":[-73.08295,44.813522],"type":"Point"}
}