{
  "type": "Feature",
  "properties": {
    "iso:country":"US",
    "sg:address":"4 US Hwy 5",
    "sg:city":"Windsor",
    "sg:classifiers":[
        {
            "category":"Retail",
            "subcategory":"Repair Shop",
            "type":"Services"
        },
        {
            "category":"Autos & Motor Vehicles",
            "subcategory":"Motorcycle Sales",
            "type":"Retail Goods"
        }
    ],
    "sg:phone":"+1 802 674 5572",
    "sg:postcode":"05089",
    "sg:province":"VT",
    "sg:tags":[
        "scooter",
        "used",
        "snowmobile"
    ],
    "wof:name":"Exit 9 Motor Sports",
    "wof:placetype":"venue"
},
  "geometry": {"coordinates":[-72.40028100000001,43.525706],"type":"Point"}
}