{
  "type": "Feature",
  "properties": {
    "addr:full":"295 Main St Norwich VT 05055",
    "addr:housenumber":"295",
    "addr:postcode":"05055",
    "addr:street":"Main St",
    "iso:country":"US",
    "sg:address":"295 Main St",
    "sg:city":"Norwich",
    "sg:classifiers":[
        {
            "category":"Shopping",
            "subcategory":"Jewelry",
            "type":"Retail Goods"
        }
    ],
    "sg:phone":"+1 802 649 2244",
    "sg:postcode":"05055",
    "sg:province":"VT",
    "sg:tags":[
        "designer"
    ],
    "wof:name":"Thin Air Studio",
    "wof:placetype":"venue"
},
  "geometry": {"coordinates":[-72.308184,43.713179],"type":"Point"}
}