{
  "type": "Feature",
  "properties": {
    "iso:country":"US",
    "sg:address":"233 Squires Rd",
    "sg:city":"Manchester Ctr",
    "sg:classifiers":[
        {
            "category":"Manufacturing",
            "subcategory":"Buildings",
            "type":"Manufacturing & Wholesale Goods"
        }
    ],
    "sg:phone":"+1 802 442 7177",
    "sg:postcode":"05251",
    "sg:province":"VT",
    "sg:tags":[
        "prefab"
    ],
    "wof:name":"Vermont Quality Homes",
    "wof:placetype":"venue"
},
  "geometry": {"coordinates":[-73.058403,43.208594],"type":"Point"}
}