{
  "type": "Feature",
  "properties": {
    "iso:country":"US",
    "sg:address":"311 Maple Tree Pl",
    "sg:city":"Williston",
    "sg:classifiers":[
        {
            "category":"Professional",
            "subcategory":"Business Services",
            "type":"Services"
        }
    ],
    "sg:phone":"+1 802 878 9790",
    "sg:postcode":"05495",
    "sg:province":"VT",
    "sg:tags":[
        "interior",
        "consultant",
        "design",
        "decorator"
    ],
    "wof:name":"Special Care Interior Dcrtng",
    "wof:placetype":"venue"
},
  "geometry": {"coordinates":[-73.107007,44.446456],"type":"Point"}
}