{
  "type": "Feature",
  "properties": {
    "iso:country":"US",
    "sg:address":"985 Remick Rd",
    "sg:city":"St Johnsbury",
    "sg:classifiers":[
        {
            "category":"Real Estate",
            "subcategory":"Surveying",
            "type":"Services"
        }
    ],
    "sg:phone":"+1 802 748 3784",
    "sg:postcode":"05819",
    "sg:province":"VT",
    "sg:tags":[
        "surveyor"
    ],
    "wof:name":"Northeast Surveys",
    "wof:placetype":"venue"
},
  "geometry": {"coordinates":[-71.93316799999999,44.388687],"type":"Point"}
}