{
  "type": "Feature",
  "properties": {
    "iso:country":"US",
    "sg:address":"337 N Main St",
    "sg:city":"Bradford",
    "sg:classifiers":[
        {
            "category":"Building & Trades",
            "subcategory":"Construction",
            "type":"Services"
        }
    ],
    "sg:phone":"+1 802 222 3400",
    "sg:postcode":"05033",
    "sg:province":"VT",
    "sg:tags":[
        "contractor"
    ],
    "wof:name":"Keith Michelson",
    "wof:placetype":"venue"
},
  "geometry": {"coordinates":[-72.12352300000001,43.988084],"type":"Point"}
}