{
  "type": "Feature",
  "properties": {
    "iso:country":"US",
    "sg:address":"10 N Champlain St",
    "sg:city":"Burlington",
    "sg:classifiers":[
        {
            "category":"Professional",
            "subcategory":"Advertising",
            "type":"Services"
        }
    ],
    "sg:phone":"+1 802 865 3469",
    "sg:postcode":"05401",
    "sg:province":"VT",
    "sg:tags":[
        "distribution"
    ],
    "wof:name":"Zingher Tools",
    "wof:placetype":"venue"
},
  "geometry": {"coordinates":[-73.21742500000001,44.481113],"type":"Point"}
}