{
  "type": "Feature",
  "properties": {
    "addr:full":"70 Websterville Rd Barre VT 05641",
    "addr:housenumber":"70",
    "addr:postcode":"05641",
    "addr:street":"Websterville Rd",
    "iso:country":"US",
    "sg:address":"70 Websterville Rd",
    "sg:city":"Barre",
    "sg:classifiers":[
        {
            "category":"Education",
            "subcategory":"School",
            "type":"Public Place"
        }
    ],
    "sg:phone":"+1 802 476 6617",
    "sg:postcode":"05641",
    "sg:province":"VT",
    "wof:name":"Barre Town Elementary School",
    "wof:placetype":"venue"
},
  "geometry": {"coordinates":[-72.49094599999999,44.17001],"type":"Point"}
}