{
  "type": "Feature",
  "properties": {
    "iso:country":"US",
    "sg:address":"2 Lower Main St E",
    "sg:city":"Johnson",
    "sg:classifiers":[
        {
            "category":"Shopping",
            "subcategory":"Crafts & Fabrics",
            "type":"Retail Goods"
        }
    ],
    "sg:phone":"+1 802 635 9851",
    "sg:postcode":"05656",
    "sg:province":"VT",
    "sg:tags":[
        "yarn"
    ],
    "wof:name":"River Muse Yarns",
    "wof:placetype":"venue"
},
  "geometry": {"coordinates":[-72.67924499999999,44.635238],"type":"Point"}
}