{
  "type": "Feature",
  "properties": {
    "addr:full":"2160 Mountain Rd Stowe VT 05672",
    "addr:housenumber":"2160",
    "addr:postcode":"05672",
    "addr:street":"Mountain Rd",
    "iso:country":"US",
    "sg:address":"2160 Mountain Rd",
    "sg:city":"Stowe",
    "sg:classifiers":[
        {
            "category":"Shopping",
            "subcategory":"Bicycles & Sporting Goods",
            "type":"Retail Goods"
        }
    ],
    "sg:phone":"+1 802 253 7975",
    "sg:postcode":"05672",
    "sg:province":"VT",
    "sg:tags":[
        "r"
    ],
    "wof:name":"Stowe Action Outfitters",
    "wof:placetype":"venue"
},
  "geometry": {"coordinates":[-72.716289,44.474398],"type":"Point"}
}