{
  "type": "Feature",
  "properties": {
    "addr:full":"623 Concord Ave St Johnsbury VT 05819",
    "addr:housenumber":"623",
    "addr:postcode":"05819",
    "addr:street":"Concord Ave",
    "iso:country":"US",
    "sg:address":"623 Concord Ave",
    "sg:city":"St Johnsbury",
    "sg:classifiers":[
        {
            "category":"Personal",
            "subcategory":"Beauty Salon",
            "type":"Services"
        }
    ],
    "sg:phone":"+1 802 748 2332",
    "sg:postcode":"05819",
    "sg:province":"VT",
    "wof:name":"Absolute Transitions",
    "wof:placetype":"venue"
},
  "geometry": {"coordinates":[-72.00444,44.421371],"type":"Point"}
}