{
  "type": "Feature",
  "properties": {
    "iso:country":"US",
    "sg:address":"10 Conant Sq",
    "sg:city":"Brandon",
    "sg:classifiers":[
        {
            "category":"Health Services",
            "subcategory":"Health Practitioner",
            "type":"Services"
        }
    ],
    "sg:phone":"+1 802 388 1122",
    "sg:postcode":"05733",
    "sg:province":"VT",
    "sg:tags":[
        "psychologist"
    ],
    "wof:name":"Lisa M Stephen Phd PC",
    "wof:placetype":"venue"
},
  "geometry": {"coordinates":[-73.092422,43.799934],"type":"Point"}
}