{
  "type": "Feature",
  "properties": {
    "addr:full":"1 Rowley Ln Burlington VT 05468",
    "addr:housenumber":"1",
    "addr:postcode":"05468",
    "addr:street":"Rowley Ln",
    "iso:country":"US",
    "sg:address":"1 Rowley Ln",
    "sg:city":"Burlington",
    "sg:classifiers":[
        {
            "category":"Railroad",
            "type":"Transportation"
        }
    ],
    "sg:phone":"+1 802 658 2550",
    "sg:postcode":"05468",
    "sg:province":"VT",
    "sg:website":"www.vermontrailway.com",
    "wof:name":"Vermont Rail System",
    "wof:placetype":"venue"
},
  "geometry": {"coordinates":[-73.122095,44.612498],"type":"Point"}
}