{
  "type": "Feature",
  "properties": {
    "addr:full":"66 Logwood Cir Essex Junction VT 05452",
    "addr:housenumber":"66",
    "addr:postcode":"05452",
    "addr:street":"Logwood Cir",
    "iso:country":"US",
    "sg:address":"66 Logwood Cir",
    "sg:city":"Essex Junction",
    "sg:classifiers":[
        {
            "category":"Building & Trades",
            "subcategory":"Landscaping Services",
            "type":"Services"
        }
    ],
    "sg:phone":"+1 802 879 8970",
    "sg:postcode":"05452",
    "sg:province":"VT",
    "sg:tags":[
        "lawn",
        "maintenance",
        "grounds"
    ],
    "wof:name":"S & D Lawn Svc",
    "wof:placetype":"venue"
},
  "geometry": {"coordinates":[-73.055328,44.481671],"type":"Point"}
}