{
  "type": "Feature",
  "properties": {
    "addr:full":"468 Woodstock Rd Woodstock VT 05091",
    "addr:housenumber":"468",
    "addr:postcode":"05091",
    "addr:street":"Woodstock Rd",
    "iso:country":"US",
    "sg:address":"468 Woodstock Rd",
    "sg:city":"Woodstock",
    "sg:classifiers":[
        {
            "category":"Food & Beverages",
            "subcategory":"Groceries & Convenience Stores",
            "type":"Retail Goods"
        }
    ],
    "sg:phone":"+1 802 457 3658",
    "sg:postcode":"05091",
    "sg:province":"VT",
    "sg:tags":[
        "deli",
        "fresh",
        "produce",
        "take"
    ],
    "wof:name":"Woodstock Farmers Market Inc",
    "wof:placetype":"venue"
},
  "geometry": {"coordinates":[-72.50597500000001,43.628696],"type":"Point"}
}