{
  "type": "Feature",
  "properties": {
    "iso:country":"US",
    "sg:address":"3609 US Hwy 5",
    "sg:city":"Derby",
    "sg:classifiers":[
        {
            "category":"Freight",
            "type":"Transportation"
        }
    ],
    "sg:phone":"+1 802 766 5441",
    "sg:postcode":"05829",
    "sg:province":"VT",
    "wof:name":"DHL Danzas Air & Ocean",
    "wof:placetype":"venue"
},
  "geometry": {"coordinates":[-72.140204,44.952747],"type":"Point"}
}