{
  "type": "Feature",
  "properties": {
    "iso:country":"US",
    "sg:address":"25 Orchard St",
    "sg:city":"Springfield",
    "sg:classifiers":[
        {
            "category":"Retail",
            "subcategory":"Repair Shop",
            "type":"Services"
        }
    ],
    "sg:phone":"+1 802 885 1300",
    "sg:postcode":"05156",
    "sg:province":"VT",
    "sg:tags":[
        "taxidermist"
    ],
    "sg:website":"www.foxchaircapes.com",
    "wof:name":"Fox Chair Mountain Capes",
    "wof:placetype":"venue"
},
  "geometry": {"coordinates":[-72.477118,43.301054],"type":"Point"}
}