{
  "type": "Feature",
  "properties": {
    "addr:full":"6305 Shelburne Rd Shelburne VT 05482",
    "addr:housenumber":"6305",
    "addr:postcode":"05482",
    "addr:street":"Shelburne Rd",
    "iso:country":"US",
    "sg:address":"6305 Shelburne Rd",
    "sg:city":"Shelburne",
    "sg:classifiers":[
        {
            "category":"Farming",
            "subcategory":"Nursery",
            "type":"Manufacturing & Wholesale Goods"
        }
    ],
    "sg:phone":"+1 802 425 3899",
    "sg:postcode":"05482",
    "sg:province":"VT",
    "sg:tags":[
        "greenhouse"
    ],
    "wof:name":"Trudi's Plants & Produce",
    "wof:placetype":"venue"
},
  "geometry": {"coordinates":[-73.232782,44.366281],"type":"Point"}
}