{
  "type": "Feature",
  "properties": {
    "iso:country":"US",
    "sg:address":"349 S Willard St",
    "sg:city":"Burlington",
    "sg:classifiers":[
        {
            "category":"Travel",
            "subcategory":"Hotels & Motels",
            "type":"Entertainment"
        }
    ],
    "sg:phone":"+1 802 651 8710",
    "sg:postcode":"05401",
    "sg:province":"VT",
    "sg:tags":[
        "breakfast",
        "accommodation",
        "bed"
    ],
    "sg:website":"www.willardstreetinn.com",
    "wof:name":"Willard Street Inn",
    "wof:placetype":"venue"
},
  "geometry": {"coordinates":[-73.20509300000001,44.470265],"type":"Point"}
}