{
  "type": "Feature",
  "properties": {
    "iso:country":"US",
    "sg:address":"100 Railroad Row",
    "sg:city":"White River Jct",
    "sg:classifiers":[
        {
            "category":"Organizations",
            "subcategory":"Professional Association",
            "type":"Services"
        }
    ],
    "sg:phone":"+1 802 295 7900",
    "sg:postcode":"05001",
    "sg:province":"VT",
    "sg:tags":[
        "chambers",
        "commerce"
    ],
    "sg:website":"www.quechee.com",
    "wof:name":"Hartford Area Chamber Of Com",
    "wof:placetype":"venue"
},
  "geometry": {"coordinates":[-72.318034,43.648911],"type":"Point"}
}