{
  "type": "Feature",
  "properties": {
    "addr:full":"51 Main St Milton VT 05468",
    "addr:housenumber":"51",
    "addr:postcode":"05468",
    "addr:street":"Main St",
    "iso:country":"US",
    "sg:address":"51 Main St",
    "sg:city":"Milton",
    "sg:classifiers":[
        {
            "category":"Organizations",
            "subcategory":"Religious Organization",
            "type":"Services"
        }
    ],
    "sg:phone":"+1 802 893 4388",
    "sg:postcode":"05468",
    "sg:province":"VT",
    "sg:tags":[
        "church"
    ],
    "wof:name":"United Church Of Milton",
    "wof:placetype":"venue"
},
  "geometry": {"coordinates":[-73.106511,44.639023],"type":"Point"}
}