{
  "type": "Feature",
  "properties": {
    "iso:country":"US",
    "sg:address":"40 River St",
    "sg:city":"Milton",
    "sg:classifiers":[
        {
            "category":"Restaurant",
            "type":"Food & Drink"
        }
    ],
    "sg:phone":"+1 802 893 2227",
    "sg:postcode":"05468",
    "sg:province":"VT",
    "wof:name":"Rosario's",
    "wof:placetype":"venue"
},
  "geometry": {"coordinates":[-73.113556,44.63644],"type":"Point"}
}