{
  "type": "Feature",
  "properties": {
    "addr:full":"76 Main St Ludlow VT 05149",
    "addr:housenumber":"76",
    "addr:postcode":"05149",
    "addr:street":"Main St",
    "iso:country":"US",
    "sg:address":"76 Main St",
    "sg:city":"Ludlow",
    "sg:classifiers":[
        {
            "category":"Building & Trades",
            "subcategory":"Plumbing",
            "type":"Services"
        }
    ],
    "sg:phone":"+1 802 228 3356",
    "sg:postcode":"05149",
    "sg:province":"VT",
    "sg:tags":[
        "contractor"
    ],
    "wof:name":"Miele Plumbing & Heating",
    "wof:placetype":"venue"
},
  "geometry": {"coordinates":[-72.692916,43.396833],"type":"Point"}
}