{
  "type": "Feature",
  "properties": {
    "addr:full":"14 School St Bristol VT 05443",
    "addr:housenumber":"14",
    "addr:postcode":"05443",
    "addr:street":"School St",
    "iso:country":"US",
    "sg:address":"14 School St",
    "sg:city":"Bristol",
    "sg:classifiers":[
        {
            "category":"Health Services",
            "subcategory":"Health Practitioner",
            "type":"Services"
        }
    ],
    "sg:phone":"+1 802 453 5698",
    "sg:postcode":"05443",
    "sg:province":"VT",
    "sg:tags":[
        "homeopath"
    ],
    "wof:name":"E Mac Farlane Homeopathy",
    "wof:placetype":"venue"
},
  "geometry": {"coordinates":[-73.080332,44.134595],"type":"Point"}
}