{
  "type": "Feature",
  "properties": {
    "iso:country":"US",
    "sg:address":"8 Mountain View Dr",
    "sg:city":"Swanton",
    "sg:classifiers":[
        {
            "category":"Professional",
            "subcategory":"Business Services",
            "type":"Services"
        }
    ],
    "sg:phone":"+1 802 479 0646",
    "sg:postcode":"05488",
    "sg:province":"VT",
    "wof:name":"Rfk Associates Inc",
    "wof:placetype":"venue"
},
  "geometry": {"coordinates":[-73.097966,44.856096],"type":"Point"}
}