{
  "type": "Feature",
  "properties": {
    "iso:country":"US",
    "sg:address":"130 S Main St",
    "sg:city":"Rutland",
    "sg:classifiers":[
        {
            "category":"Retail",
            "subcategory":"Auto Rental",
            "type":"Services"
        }
    ],
    "sg:phone":"+1 802 747 0001",
    "sg:postcode":"05701",
    "sg:province":"VT",
    "sg:tags":[
        "passenger",
        "used",
        "car",
        "automobile"
    ],
    "wof:name":"U-Save Auto Rental",
    "wof:placetype":"venue"
},
  "geometry": {"coordinates":[-72.972043,43.606964],"type":"Point"}
}