{
  "type": "Feature",
  "properties": {
    "addr:full":"366 E Main St Concord VT 05824",
    "addr:housenumber":"366",
    "addr:postcode":"05824",
    "addr:street":"E Main St",
    "iso:country":"US",
    "sg:address":"366 E Main St",
    "sg:city":"Concord",
    "sg:classifiers":[
        {
            "category":"Retail",
            "subcategory":"Auto Repair",
            "type":"Services"
        }
    ],
    "sg:phone":"+1 802 695 3328",
    "sg:postcode":"05824",
    "sg:province":"VT",
    "sg:tags":[
        "wrecker"
    ],
    "wof:name":"Tony's Wrecker Svc",
    "wof:placetype":"venue"
},
  "geometry": {"coordinates":[-71.86994,44.453521],"type":"Point"}
}