{
  "type": "Feature",
  "properties": {
    "iso:country":"US",
    "sg:address":"1549 Pencil Mill Rd",
    "sg:city":"Castleton",
    "sg:classifiers":[
        {
            "category":"Building & Trades",
            "subcategory":"Construction",
            "type":"Services"
        }
    ],
    "sg:phone":"+1 802 273 2527",
    "sg:postcode":"05735",
    "sg:province":"VT",
    "sg:tags":[
        "general",
        "nonresidential",
        "contractor"
    ],
    "wof:name":"John Trombley Construction",
    "wof:placetype":"venue"
},
  "geometry": {"coordinates":[-73.18346099999999,43.691034],"type":"Point"}
}