{
  "type": "Feature",
  "properties": {
    "iso:country":"US",
    "sg:address":"118 N Main St",
    "sg:city":"St Albans",
    "sg:classifiers":[
        {
            "category":"Personal",
            "subcategory":"Beauty Salon",
            "type":"Services"
        }
    ],
    "sg:phone":"+1 802 527 7780",
    "sg:postcode":"05478",
    "sg:province":"VT",
    "sg:tags":[
        "shop"
    ],
    "wof:name":"Creative Changes Inc",
    "wof:placetype":"venue"
},
  "geometry": {"coordinates":[-73.082928,44.814005],"type":"Point"}
}