{
  "type": "Feature",
  "properties": {
    "iso:country":"US",
    "sg:address":"192 Stratton Rd",
    "sg:city":"Rutland",
    "sg:classifiers":[
        {
            "category":"Personal",
            "subcategory":"Beauty Salon",
            "type":"Services"
        }
    ],
    "sg:phone":"+1 802 855 8756",
    "sg:postcode":"05701",
    "sg:province":"VT",
    "wof:name":"Laura's Hair Frenzy",
    "wof:placetype":"venue"
},
  "geometry": {"coordinates":[-72.95594800000001,43.603611],"type":"Point"}
}