{
  "type": "Feature",
  "properties": {
    "iso:country":"US",
    "sg:address":"307 Weeks Hill Rd",
    "sg:city":"Stowe",
    "sg:classifiers":[
        {
            "category":"Building & Trades",
            "subcategory":"Cleaning & Sanitation",
            "type":"Services"
        },
        {
            "category":"Real Estate",
            "subcategory":"Real Estate Agent",
            "type":"Services"
        }
    ],
    "sg:phone":"+1 802 253 9803",
    "sg:postcode":"05672",
    "sg:province":"VT",
    "sg:tags":[
        "property",
        "management",
        "maintenance"
    ],
    "wof:name":"Tyler Property Management Svcs",
    "wof:placetype":"venue"
},
  "geometry": {"coordinates":[-72.68984500000001,44.476994],"type":"Point"}
}