{
  "type": "Feature",
  "properties": {
    "iso:country":"US",
    "sg:address":"198 Boardman St",
    "sg:city":"Middlebury",
    "sg:classifiers":[
        {
            "category":"Home & Garden",
            "subcategory":"Building Materials",
            "type":"Retail Goods"
        }
    ],
    "sg:phone":"+1 802 388 9049",
    "sg:postcode":"05753",
    "sg:province":"VT",
    "sg:tags":[
        "glass",
        "window",
        "plate"
    ],
    "wof:name":"R J Desabrais & Sons Glass Svc",
    "wof:placetype":"venue"
},
  "geometry": {"coordinates":[-73.14546199999999,44.001043],"type":"Point"}
}