{
  "type": "Feature",
  "properties": {
    "addr:full":"71 Milo White Rd Jericho VT 05465",
    "addr:housenumber":"71",
    "addr:postcode":"05465",
    "addr:street":"Milo White Rd",
    "iso:country":"US",
    "sg:address":"71 Milo White Rd",
    "sg:city":"Jericho",
    "sg:classifiers":[
        {
            "category":"Retail",
            "subcategory":"Veterinary Services",
            "type":"Services"
        }
    ],
    "sg:phone":"+1 802 899 3375",
    "sg:postcode":"05465",
    "sg:province":"VT",
    "sg:tags":[
        "veterinarian"
    ],
    "wof:name":"Home Veterinary Svc",
    "wof:placetype":"venue"
},
  "geometry": {"coordinates":[-72.977468,44.441525],"type":"Point"}
}