{
  "type": "Feature",
  "properties": {
    "addr:full":"100 Spruce Ln Williston VT 05495",
    "addr:housenumber":"100",
    "addr:postcode":"05495",
    "addr:street":"Spruce Ln",
    "iso:country":"US",
    "sg:address":"100 Spruce Ln",
    "sg:city":"Williston",
    "sg:classifiers":[
        {
            "category":"Shopping",
            "subcategory":"Gifts & Souvenirs",
            "type":"Retail Goods"
        }
    ],
    "sg:phone":"+1 802 872 9733",
    "sg:postcode":"05495",
    "sg:province":"VT",
    "sg:tags":[
        "shop"
    ],
    "wof:name":"Christmas Tree Shops",
    "wof:placetype":"venue"
},
  "geometry": {"coordinates":[-73.057435,44.447581],"type":"Point"}
}