{
  "type": "Feature",
  "properties": {
    "addr:full":"130 Gosse Ct Burlington VT 05408",
    "addr:housenumber":"130",
    "addr:postcode":"05408",
    "addr:street":"Gosse Ct",
    "iso:country":"US",
    "sg:address":"130 Gosse Ct",
    "sg:city":"Burlington",
    "sg:classifiers":[
        {
            "category":"Government",
            "subcategory":"Office",
            "type":"Public Place"
        }
    ],
    "sg:phone":"+1 802 660 0723",
    "sg:postcode":"05408",
    "sg:province":"VT",
    "sg:tags":[
        "national",
        "guard"
    ],
    "wof:name":"Military Vermont Department",
    "wof:placetype":"venue"
},
  "geometry": {"coordinates":[-72.48908400000001,44.205197],"type":"Point"}
}