{
  "type": "Feature",
  "properties": {
    "addr:full":"19 Belmont Ave Brattleboro VT 05301",
    "addr:housenumber":"19",
    "addr:postcode":"05301",
    "addr:street":"Belmont Ave",
    "iso:country":"US",
    "sg:address":"19 Belmont Ave",
    "sg:city":"Brattleboro",
    "sg:classifiers":[
        {
            "category":"Health Services",
            "subcategory":"Doctor",
            "type":"Services"
        }
    ],
    "sg:phone":"+1 802 257 0505",
    "sg:postcode":"05301",
    "sg:province":"VT",
    "sg:tags":[
        "medical"
    ],
    "wof:name":"Burton Tepfer MD",
    "wof:placetype":"venue"
},
  "geometry": {"coordinates":[-72.568257,42.844038],"type":"Point"}
}