{
  "type": "Feature",
  "properties": {
    "iso:country":"US",
    "sg:address":"291 Juniper Dr",
    "sg:city":"South Burlington",
    "sg:classifiers":[
        {
            "category":"Professional",
            "subcategory":"Management & Consulting",
            "type":"Services"
        }
    ],
    "sg:phone":"+1 802 878 8332",
    "sg:postcode":"05403",
    "sg:province":"VT",
    "sg:tags":[
        "consultant",
        "business"
    ],
    "wof:name":"Advant Edge Products Inc",
    "wof:placetype":"venue"
},
  "geometry": {"coordinates":[-73.175397,44.473481],"type":"Point"}
}