{
  "type": "Feature",
  "properties": {
    "addr:full":"899 Main St Colchester VT 05446",
    "addr:housenumber":"899",
    "addr:postcode":"05446",
    "addr:street":"Main St",
    "iso:country":"US",
    "sg:address":"899 Main St",
    "sg:city":"Colchester",
    "sg:classifiers":[
        {
            "category":"Social Services",
            "type":"Services"
        }
    ],
    "sg:phone":"+1 802 658 2888",
    "sg:postcode":"05446",
    "sg:province":"VT",
    "sg:tags":[
        "counselor",
        "marriage",
        "family"
    ],
    "wof:name":"Wright House",
    "wof:placetype":"venue"
},
  "geometry": {"coordinates":[-73.14903099999999,44.544171],"type":"Point"}
}