{
  "type": "Feature",
  "properties": {
    "iso:country":"US",
    "sg:address":"61 Main St",
    "sg:city":"Fair Haven",
    "sg:classifiers":[
        {
            "category":"Cinema",
            "subcategory":"Movie Rental",
            "type":"Entertainment"
        }
    ],
    "sg:phone":"+1 802 265 2261",
    "sg:postcode":"05743",
    "sg:province":"VT",
    "sg:tags":[
        "leasing",
        "video",
        "disc",
        "tape"
    ],
    "wof:name":"Video One",
    "wof:placetype":"venue"
},
  "geometry": {"coordinates":[-73.26509799999999,43.59252],"type":"Point"}
}