{
  "type": "Feature",
  "properties": {
    "iso:country":"US",
    "sg:address":"70 Pond Dr",
    "sg:city":"Stowe",
    "sg:classifiers":[
        {
            "category":"Shopping",
            "subcategory":"Jewelry",
            "type":"Retail Goods"
        }
    ],
    "sg:phone":"+1 802 253 7000",
    "sg:postcode":"05672",
    "sg:province":"VT",
    "sg:tags":[
        "jeweler"
    ],
    "wof:name":"Stowe Gems",
    "wof:placetype":"venue"
},
  "geometry": {"coordinates":[-72.727245,44.489041],"type":"Point"}
}