{
  "type": "Feature",
  "properties": {
    "iso:country":"US",
    "sg:address":"348 Dewey St",
    "sg:city":"Bennington",
    "sg:classifiers":[
        {
            "category":"Social Services",
            "type":"Services"
        }
    ],
    "sg:phone":"+1 802 447 0860",
    "sg:postcode":"05201",
    "sg:province":"VT",
    "sg:tags":[
        "counseling"
    ],
    "wof:name":"United Counseling Service-Bnn",
    "wof:placetype":"venue"
},
  "geometry": {"coordinates":[-73.205015,42.870344],"type":"Point"}
}