{
  "type": "Feature",
  "properties": {
    "iso:country":"US",
    "sg:address":"4 Frazier Rd",
    "sg:city":"Morrisville",
    "sg:classifiers":[
        {
            "category":"Home & Garden",
            "subcategory":"Household Appliances",
            "type":"Retail Goods"
        }
    ],
    "sg:phone":"+1 802 888 4159",
    "sg:postcode":"05661",
    "sg:province":"VT",
    "wof:name":"Chuck's Appliance Svc",
    "wof:placetype":"venue"
},
  "geometry": {"coordinates":[-72.58691399999999,44.576195],"type":"Point"}
}