{
  "type": "Feature",
  "properties": {
    "iso:country":"US",
    "sg:address":"535 US Hwy 302",
    "sg:city":"Barre",
    "sg:classifiers":[
        {
            "category":"Home & Garden",
            "subcategory":"Garden Supply",
            "type":"Retail Goods"
        }
    ],
    "sg:phone":"+1 802 476 5037",
    "sg:postcode":"05641",
    "sg:province":"VT",
    "wof:name":"Gas Farm Marke The",
    "wof:placetype":"venue"
},
  "geometry": {"coordinates":[-72.514,44.208349],"type":"Point"}
}