{
  "type": "Feature",
  "properties": {
    "iso:country":"US",
    "sg:address":"394 Railroad St",
    "sg:city":"St Johnsbury",
    "sg:classifiers":[
        {
            "category":"Real Estate",
            "subcategory":"Real Estate Operator",
            "type":"Services"
        }
    ],
    "sg:phone":"+1 802 751 8222",
    "sg:postcode":"05819",
    "sg:province":"VT",
    "sg:tags":[
        "apartment"
    ],
    "wof:name":"Passumpsic View Apartments",
    "wof:placetype":"venue"
},
  "geometry": {"coordinates":[-72.015677,44.41821],"type":"Point"}
}