{
  "type": "Feature",
  "properties": {
    "iso:country":"US",
    "sg:address":"188 Main St",
    "sg:city":"Burlington",
    "sg:classifiers":[
        {
            "category":"Restaurant",
            "type":"Food & Drink"
        }
    ],
    "sg:menulink":"http://www.allmenus.com/vt/burlington/275298-nectars/menu/",
    "sg:phone":"+1 802 658 4771",
    "sg:postcode":"05401",
    "sg:province":"VT",
    "sg:tags":[
        "american"
    ],
    "wof:name":"Nectar's",
    "wof:placetype":"venue"
},
  "geometry": {"coordinates":[-73.21190900000001,44.476082],"type":"Point"}
}