{
  "type": "Feature",
  "properties": {
    "iso:country":"US",
    "sg:address":"35 Upper Bailey Rd",
    "sg:city":"Thetford Center",
    "sg:classifiers":[
        {
            "category":"Professional",
            "subcategory":"Management & Consulting",
            "type":"Services"
        }
    ],
    "sg:phone":"+1 802 785 2994",
    "sg:postcode":"05075",
    "sg:province":"VT",
    "wof:name":"Vickers Et Al",
    "wof:placetype":"venue"
},
  "geometry": {"coordinates":[-72.30189300000001,43.824207],"type":"Point"}
}