{
  "type": "Feature",
  "properties": {
    "iso:country":"US",
    "sg:address":"159 Lindsay Exd",
    "sg:city":"Newport",
    "sg:classifiers":[
        {
            "category":"Manufacturing",
            "subcategory":"Apparel",
            "type":"Manufacturing & Wholesale Goods"
        }
    ],
    "sg:phone":"+1 802 334 1590",
    "sg:postcode":"05855",
    "sg:province":"VT",
    "wof:name":"Scrappy Patches Mch Quilting",
    "wof:placetype":"venue"
},
  "geometry": {"coordinates":[-72.189126,44.970087],"type":"Point"}
}