{
  "type": "Feature",
  "properties": {
    "iso:country":"US",
    "sg:address":"857 Pine St",
    "sg:city":"Burlington",
    "sg:classifiers":[
        {
            "category":"Arts & Performance",
            "subcategory":"Theater",
            "type":"Entertainment"
        }
    ],
    "sg:phone":"+1 802 862 0981",
    "sg:postcode":"05401",
    "sg:province":"VT",
    "sg:tags":[
        "magician"
    ],
    "wof:name":"Merlin The Magician",
    "wof:placetype":"venue"
},
  "geometry": {"coordinates":[-73.214288,44.455688],"type":"Point"}
}