{
  "type": "Feature",
  "properties": {
    "iso:country":"US",
    "sg:address":"340 Malletts Bay Ave",
    "sg:city":"Colchester",
    "sg:classifiers":[
        {
            "category":"Insurance",
            "subcategory":"Insurance Agent",
            "type":"Services"
        }
    ],
    "sg:phone":"+1 802 862 3481",
    "sg:postcode":"05446",
    "sg:province":"VT",
    "sg:tags":[
        "adjuster"
    ],
    "wof:name":"Bullock Insurance Adjustment",
    "wof:placetype":"venue"
},
  "geometry": {"coordinates":[-73.20844,44.533696],"type":"Point"}
}