{
  "type": "Feature",
  "properties": {
    "addr:city":"Huntington",
    "addr:full":"900 Sherman Hollow Rd Huntington, Vt 05462-9420",
    "addr:house_number":"900",
    "addr:housenumber":"900",
    "addr:phone":"+1 802-434-2167",
    "addr:postcode":"05462-9420",
    "addr:road":"Sherman Hollow Rd",
    "addr:state":"VT",
    "addr:street":"Sherman Hollow Rd",
    "iso:country":"US",
    "sg:address":"900 Sherman Hollow Rd",
    "sg:city":"Huntington",
    "sg:classifiers":[
        {
            "category":"Museum",
            "type":"Entertainment"
        }
    ],
    "sg:phone":"+1 802 434 2167",
    "sg:postcode":"05462",
    "sg:province":"VT",
    "wof:airports":[
        102532853
    ],
    "wof:name":"Birds Of Vermont Museum",
    "wof:placetype":"venue"
},
  "geometry": {"coordinates":[-73.02663,44.3596],"type":"Point"}
}