{
  "type": "Feature",
  "properties": {
    "iso:country":"US",
    "sg:address":"900 Sherman Hollow Rd",
    "sg:city":"Huntington",
    "sg:classifiers":[
        {
            "category":"Museum",
            "type":"Entertainment"
        }
    ],
    "sg:phone":"+1 802 434 2167",
    "sg:postcode":"05462",
    "sg:province":"VT",
    "wof:name":"Birds Of Vt Museum Inc",
    "wof:placetype":"venue"
},
  "geometry": {"coordinates":[-73.008196,44.352385],"type":"Point"}
}