{
  "type": "Feature",
  "properties": {
    "iso:country":"US",
    "sg:address":"3 Mill St",
    "sg:city":"Middlebury",
    "sg:classifiers":[
        {
            "category":"Wholesale",
            "subcategory":"Construction Materials",
            "type":"Manufacturing & Wholesale Goods"
        }
    ],
    "sg:phone":"+1 802 388 6336",
    "sg:postcode":"05753",
    "sg:province":"VT",
    "sg:tags":[
        "timberland",
        "company",
        "timber"
    ],
    "wof:name":"Northern Timber Constr Carver",
    "wof:placetype":"venue"
},
  "geometry": {"coordinates":[-73.168975,44.013015],"type":"Point"}
}