{
  "type": "Feature",
  "properties": {
    "addr:full":"440 Woodstock Rd Woodstock VT 05091",
    "addr:housenumber":"440",
    "addr:postcode":"05091",
    "addr:street":"Woodstock Rd",
    "iso:country":"US",
    "sg:address":"440 Woodstock Rd",
    "sg:city":"Woodstock",
    "sg:classifiers":[
        {
            "category":"Building & Trades",
            "subcategory":"Equipment Rental",
            "type":"Services"
        }
    ],
    "sg:phone":"+1 802 457 3006",
    "sg:postcode":"05091",
    "sg:province":"VT",
    "sg:tags":[
        "yard"
    ],
    "wof:name":"Woodstock Farm Garden & Pet",
    "wof:placetype":"venue"
},
  "geometry": {"coordinates":[-72.504268,43.632816],"type":"Point"}
}