{
  "type": "Feature",
  "properties": {
    "iso:country":"US",
    "sg:address":"72 Indian Brook Rd",
    "sg:city":"Essex Junction",
    "sg:classifiers":[
        {
            "category":"Recreation",
            "type":"Entertainment"
        }
    ],
    "sg:phone":"+1 802 878 8683",
    "sg:postcode":"05452",
    "sg:province":"VT",
    "wof:name":"New Horizons Farm",
    "wof:placetype":"venue"
},
  "geometry": {"coordinates":[-73.082809,44.516654],"type":"Point"}
}