{
  "type": "Feature",
  "properties": {
    "iso:country":"US",
    "sg:address":"2766 Mount Philo Rd",
    "sg:city":"Charlotte",
    "sg:classifiers":[
        {
            "category":"Farming",
            "subcategory":"Dairy Farm",
            "type":"Manufacturing & Wholesale Goods"
        }
    ],
    "sg:phone":"+1 802 425 2774",
    "sg:postcode":"05445",
    "sg:province":"VT",
    "wof:name":"Murray Foote",
    "wof:placetype":"venue"
},
  "geometry": {"coordinates":[-73.223759,44.315809],"type":"Point"}
}