{
  "type": "Feature",
  "properties": {
    "iso:country":"US",
    "sg:address":"109 Reservoir Rd",
    "sg:city":"Chester",
    "sg:classifiers":[
        {
            "category":"Building & Trades",
            "subcategory":"Construction",
            "type":"Services"
        }
    ],
    "sg:phone":"+1 802 875 2578",
    "sg:postcode":"05143",
    "sg:province":"VT",
    "wof:name":"Riley Paving Inc",
    "wof:placetype":"venue"
},
  "geometry": {"coordinates":[-72.62881,43.272201],"type":"Point"}
}