{
  "type": "Feature",
  "properties": {
    "iso:country":"US",
    "sg:address":"879 Gray Rd",
    "sg:city":"North Montpelier",
    "sg:classifiers":[
        {
            "category":"Health Services",
            "subcategory":"Clinic",
            "type":"Services"
        }
    ],
    "sg:phone":"+1 802 223 1177",
    "sg:postcode":"05602",
    "sg:province":"VT",
    "sg:tags":[
        "counseling",
        "mental"
    ],
    "sg:website":"www.nirvanafarm.org",
    "wof:name":"Desmarais Tina",
    "wof:placetype":"venue"
},
  "geometry": {"coordinates":[-72.42718499999999,44.336278],"type":"Point"}
}