{
  "type": "Feature",
  "properties": {
    "addr:full":"153 Coventry St Newport VT 05855",
    "addr:housenumber":"153",
    "addr:postcode":"05855",
    "addr:street":"Coventry St",
    "iso:country":"US",
    "sg:address":"153 Coventry St",
    "sg:city":"Newport",
    "sg:classifiers":[
        {
            "category":"Food & Beverages",
            "subcategory":"Groceries & Convenience Stores",
            "type":"Retail Goods"
        }
    ],
    "sg:phone":"+1 802 334 2132",
    "sg:postcode":"05855",
    "sg:province":"VT",
    "wof:name":"Jimmy KWIK Store",
    "wof:placetype":"venue"
},
  "geometry": {"coordinates":[-72.207005,44.934554],"type":"Point"}
}