{
  "type": "Feature",
  "properties": {
    "iso:country":"US",
    "sg:address":"23 N Main St",
    "sg:city":"White River Jct",
    "sg:classifiers":[
        {
            "category":"Shopping",
            "subcategory":"Used Merchandise",
            "type":"Retail Goods"
        },
        {
            "category":"Home & Garden",
            "subcategory":"Furniture",
            "type":"Retail Goods"
        }
    ],
    "sg:phone":"+1 802 295 6370",
    "sg:postcode":"05001",
    "sg:province":"VT",
    "wof:name":"Main Street Furniture Inc",
    "wof:placetype":"venue"
},
  "geometry": {"coordinates":[-72.321123,43.649577],"type":"Point"}
}