{
  "type": "Feature",
  "properties": {
    "iso:country":"US",
    "sg:address":"8 Saxon Hill Rd",
    "sg:city":"Essex Junction",
    "sg:classifiers":[
        {
            "category":"Autos & Motor Vehicles",
            "subcategory":"Automobile Sales",
            "type":"Retail Goods"
        }
    ],
    "sg:phone":"+1 802 878 3131",
    "sg:postcode":"05452",
    "sg:province":"VT",
    "sg:tags":[
        "car",
        "dealer"
    ],
    "wof:name":"Ashline Auto",
    "wof:placetype":"venue"
},
  "geometry": {"coordinates":[-73.022862,44.499598],"type":"Point"}
}