{
  "type": "Feature",
  "properties": {
    "addr:full":"208 Flynn Ave Burlington VT 05401",
    "addr:housenumber":"208",
    "addr:postcode":"05401",
    "addr:street":"Flynn Ave",
    "iso:country":"US",
    "sg:address":"208 Flynn Ave",
    "sg:city":"Burlington",
    "sg:classifiers":[
        {
            "category":"Organizations",
            "subcategory":"Professional Association",
            "type":"Services"
        }
    ],
    "sg:phone":"+1 802 651 9692",
    "sg:postcode":"05401",
    "sg:province":"VT",
    "wof:name":"Vermont Community Access Media",
    "wof:placetype":"venue"
},
  "geometry": {"coordinates":[-73.21784,44.455652],"type":"Point"}
}