{
  "type": "Feature",
  "properties": {
    "iso:country":"US",
    "sg:address":"266 Pine St",
    "sg:city":"Burlington",
    "sg:classifiers":[
        {
            "category":"Building & Trades",
            "subcategory":"Construction",
            "type":"Services"
        }
    ],
    "sg:phone":"+1 802 660 8899",
    "sg:postcode":"05401",
    "sg:province":"VT",
    "sg:tags":[
        "asbestos",
        "removal"
    ],
    "wof:name":"Alderson Environmental Svc",
    "wof:placetype":"venue"
},
  "geometry": {"coordinates":[-73.215271,44.472707],"type":"Point"}
}