{
  "type": "Feature",
  "properties": {
    "iso:country":"US",
    "sg:address":"24 Stratton Rd",
    "sg:city":"Rutland",
    "sg:classifiers":[
        {
            "category":"Personal",
            "subcategory":"Beauty Salon",
            "type":"Services"
        }
    ],
    "sg:phone":"+1 802 773 6880",
    "sg:postcode":"05701",
    "sg:province":"VT",
    "sg:tags":[
        "shop"
    ],
    "wof:name":"Hair Fx",
    "wof:placetype":"venue"
},
  "geometry": {"coordinates":[-72.95681399999999,43.617964],"type":"Point"}
}