{
  "type": "Feature",
  "properties": {
    "iso:country":"US",
    "sg:address":"7252 Main St",
    "sg:city":"Manchester Ctr",
    "sg:classifiers":[
        {
            "category":"Health Services",
            "subcategory":"Podiatrist",
            "type":"Services"
        }
    ],
    "sg:phone":"+1 802 362 9959",
    "sg:postcode":"05255",
    "sg:province":"VT",
    "wof:name":"Manchester Podiatry",
    "wof:placetype":"venue"
},
  "geometry": {"coordinates":[-73.029347,43.198901],"type":"Point"}
}