{
  "type": "Feature",
  "properties": {
    "iso:country":"US",
    "sg:address":"39 Cemetery Rd",
    "sg:city":"Corinth",
    "sg:classifiers":[
        {
            "category":"Building & Trades",
            "subcategory":"Construction",
            "type":"Services"
        }
    ],
    "sg:phone":"+1 802 685 4635",
    "sg:postcode":"05039",
    "sg:province":"VT",
    "sg:tags":[
        "excavation",
        "contractor"
    ],
    "wof:name":"Bob Osgood Excavating",
    "wof:placetype":"venue"
},
  "geometry": {"coordinates":[-72.347869,44.00835],"type":"Point"}
}