{
  "type": "Feature",
  "properties": {
    "iso:country":"US",
    "sg:address":"61 South St",
    "sg:city":"New Haven",
    "sg:classifiers":[
        {
            "category":"Building & Trades",
            "subcategory":"Construction",
            "type":"Services"
        }
    ],
    "sg:phone":"+1 802 453 3374",
    "sg:postcode":"05472",
    "sg:province":"VT",
    "sg:tags":[
        "house"
    ],
    "wof:name":"Liberty Construction Inc",
    "wof:placetype":"venue"
},
  "geometry": {"coordinates":[-73.153381,44.123537],"type":"Point"}
}