{
  "type": "Feature",
  "properties": {
    "addr:full":"540 US Hwy 7 Swanton VT 05488",
    "addr:housenumber":"540",
    "addr:postcode":"05488",
    "addr:street":"Us Hwy 7",
    "iso:country":"US",
    "sg:address":"540 US Hwy 7",
    "sg:city":"Swanton",
    "sg:classifiers":[
        {
            "category":"Freight",
            "type":"Transportation"
        }
    ],
    "sg:phone":"+1 802 868 7103",
    "sg:postcode":"05488",
    "sg:province":"VT",
    "sg:tags":[
        "distance",
        "local",
        "long",
        "trucking"
    ],
    "wof:name":"Norman Lapan Trucking",
    "wof:placetype":"venue"
},
  "geometry": {"coordinates":[-73.094112,44.857154],"type":"Point"}
}