{
  "type": "Feature",
  "properties": {
    "iso:country":"US",
    "sg:address":"5134 Ethan Allen Hwy",
    "sg:city":"Saint Albans",
    "sg:classifiers":[
        {
            "category":"Building & Trades",
            "subcategory":"Construction",
            "type":"Services"
        }
    ],
    "sg:phone":"+1 802 527 2116",
    "sg:postcode":"05478",
    "sg:province":"VT",
    "sg:tags":[
        "concrete",
        "contractor"
    ],
    "wof:name":"Cathy Bossonneauc Farm",
    "wof:placetype":"venue"
},
  "geometry": {"coordinates":[-73.113265,44.746086],"type":"Point"}
}