{
  "type": "Feature",
  "properties": {
    "iso:country":"US",
    "sg:address":"100 Talbert St",
    "sg:city":"White River Jct",
    "sg:classifiers":[
        {
            "category":"Retail",
            "subcategory":"Auto Repair",
            "type":"Services"
        }
    ],
    "sg:phone":"+1 802 295 7716",
    "sg:postcode":"05001",
    "sg:province":"VT",
    "sg:tags":[
        "wrecker"
    ],
    "wof:name":"Alliance Towing & Recovery",
    "wof:placetype":"venue"
},
  "geometry": {"coordinates":[-72.32988899999999,43.650192],"type":"Point"}
}