{
  "type": "Feature",
  "properties": {
    "iso:country":"US",
    "sg:address":"4276 Main St",
    "sg:city":"Waitsfield",
    "sg:classifiers":[
        {
            "category":"Manufacturing",
            "subcategory":"Glass & Minerals",
            "type":"Manufacturing & Wholesale Goods"
        }
    ],
    "sg:phone":"+1 802 496 2231",
    "sg:postcode":"05673",
    "sg:province":"VT",
    "wof:name":"Luminosity Stained Glass",
    "wof:placetype":"venue"
},
  "geometry": {"coordinates":[-72.82913499999999,44.188675],"type":"Point"}
}