{
  "type": "Feature",
  "properties": {
    "iso:country":"US",
    "sg:address":"110 Timberlake Dr",
    "sg:city":"Colchester",
    "sg:classifiers":[
        {
            "category":"Professional",
            "subcategory":"Business Services",
            "type":"Services"
        }
    ],
    "sg:phone":"+1 802 863 4920",
    "sg:postcode":"05446",
    "sg:province":"VT",
    "wof:name":"Home Wise",
    "wof:placetype":"venue"
},
  "geometry": {"coordinates":[-73.24759400000001,44.550233],"type":"Point"}
}