{
  "type": "Feature",
  "properties": {
    "iso:country":"US",
    "sg:address":"28 Lafountain St",
    "sg:city":"Burlington",
    "sg:classifiers":[
        {
            "category":"Retail",
            "subcategory":"Auto Repair",
            "type":"Services"
        }
    ],
    "sg:phone":"+1 802 658 5508",
    "sg:postcode":"05401",
    "sg:province":"VT",
    "sg:tags":[
        "body",
        "painting",
        "repairing",
        "automobile"
    ],
    "wof:name":"Straight Line Autobody",
    "wof:placetype":"venue"
},
  "geometry": {"coordinates":[-73.215264,44.485401],"type":"Point"}
}