{
  "type": "Feature",
  "properties": {
    "iso:country":"US",
    "sg:address":"76 Houle Ave",
    "sg:city":"Morrisville",
    "sg:classifiers":[
        {
            "category":"Retail",
            "subcategory":"Repair Shop",
            "type":"Services"
        }
    ],
    "sg:phone":"+1 802 888 2394",
    "sg:postcode":"05661",
    "sg:province":"VT",
    "sg:tags":[
        "welding"
    ],
    "wof:name":"Leo's Small Engine",
    "wof:placetype":"venue"
},
  "geometry": {"coordinates":[-72.587864,44.568268],"type":"Point"}
}