{
  "type": "Feature",
  "properties": {
    "addr:full":"40 Ward St Burlington VT 05401",
    "addr:housenumber":"40",
    "addr:postcode":"05401",
    "addr:street":"Ward St",
    "iso:country":"US",
    "sg:address":"40 Ward St",
    "sg:city":"Burlington",
    "sg:classifiers":[
        {
            "category":"Organizations",
            "subcategory":"Membership Organization",
            "type":"Services"
        }
    ],
    "sg:phone":"+1 802 862 6859",
    "sg:postcode":"05401",
    "sg:province":"VT",
    "wof:name":"Tibetan Association Vermont",
    "wof:placetype":"venue"
},
  "geometry": {"coordinates":[-73.221734,44.487098],"type":"Point"}
}