{
  "type": "Feature",
  "properties": {
    "iso:country":"US",
    "sg:address":"129 Prospect Pkwy",
    "sg:city":"Burlington",
    "sg:classifiers":[
        {
            "category":"Professional",
            "type":"Services"
        }
    ],
    "sg:phone":"+1 802 865 0479",
    "sg:postcode":"05401",
    "sg:province":"VT",
    "wof:name":"Viets",
    "wof:placetype":"venue"
},
  "geometry": {"coordinates":[-73.202856,44.456617],"type":"Point"}
}