{
  "type": "Feature",
  "properties": {
    "iso:country":"US",
    "sg:address":"1204 Richardson Rd",
    "sg:city":"Corinth",
    "sg:classifiers":[
        {
            "category":"Professional",
            "subcategory":"Art Services",
            "type":"Services"
        }
    ],
    "sg:phone":"+1 802 439 5391",
    "sg:postcode":"05039",
    "sg:province":"VT",
    "sg:tags":[
        "commercial",
        "design"
    ],
    "wof:name":"Linda Petoff Productions",
    "wof:placetype":"venue"
},
  "geometry": {"coordinates":[-72.28057,44.054704],"type":"Point"}
}