{
  "type": "Feature",
  "properties": {
    "iso:country":"US",
    "sg:address":"16 Dorset St",
    "sg:city":"South Burlington",
    "sg:classifiers":[
        {
            "category":"Manufacturing",
            "subcategory":"Electronics",
            "type":"Manufacturing & Wholesale Goods"
        }
    ],
    "sg:phone":"+1 802 658 8585",
    "sg:postcode":"05403",
    "sg:province":"VT",
    "sg:tags":[
        "mfg",
        "boards",
        "circuit",
        "printed"
    ],
    "wof:name":"Pycon Inc",
    "wof:placetype":"venue"
},
  "geometry": {"coordinates":[-73.18123300000001,44.467202],"type":"Point"}
}