{
  "type": "Feature",
  "properties": {
    "addr:full":"18 Shadow Lawn Brattleboro VT 05301",
    "addr:housenumber":"18",
    "addr:postcode":"05301",
    "addr:street":"Shadow Lawn",
    "iso:country":"US",
    "sg:address":"18 Shadow Lawn",
    "sg:city":"Brattleboro",
    "sg:classifiers":[
        {
            "category":"Health Services",
            "subcategory":"Health Practitioner",
            "type":"Services"
        }
    ],
    "sg:phone":"+1 802 254 4324",
    "sg:postcode":"05301",
    "sg:province":"VT",
    "wof:name":"William D Lax PHD",
    "wof:placetype":"venue"
},
  "geometry": {"coordinates":[-72.57228000000001,42.851039],"type":"Point"}
}