{
  "type": "Feature",
  "properties": {
    "iso:country":"US",
    "sg:address":"135 Main St",
    "sg:city":"Essex Junction",
    "sg:classifiers":[
        {
            "category":"Government",
            "subcategory":"Fire Station",
            "type":"Public Place"
        }
    ],
    "sg:phone":"+1 802 879 7900",
    "sg:postcode":"05452",
    "sg:province":"VT",
    "sg:tags":[
        "equipment",
        "safety"
    ],
    "wof:name":"Safety Systems Of Vermont",
    "wof:placetype":"venue"
},
  "geometry": {"coordinates":[-73.10124399999999,44.496414],"type":"Point"}
}