{
  "type": "Feature",
  "properties": {
    "iso:country":"US",
    "sg:address":"100 Shelburne Rd",
    "sg:city":"Burlington",
    "sg:classifiers":[
        {
            "category":"Shopping",
            "subcategory":"Florist",
            "type":"Retail Goods"
        }
    ],
    "sg:phone":"+1 802 864 0376",
    "sg:postcode":"05401",
    "sg:province":"VT",
    "wof:name":"Corbett Richard Flowers",
    "wof:placetype":"venue"
},
  "geometry": {"coordinates":[-73.207915,44.461888],"type":"Point"}
}