{
  "type": "Feature",
  "properties": {
    "addr:full":"655 Columbus Smith Rd Salisbury VT 05769",
    "addr:housenumber":"655",
    "addr:postcode":"05769",
    "addr:street":"Columbus Smith Rd",
    "iso:country":"US",
    "sg:address":"655 Columbus Smith Rd",
    "sg:city":"Salisbury",
    "sg:classifiers":[
        {
            "category":"Health Services",
            "subcategory":"Nursing And Care Facility",
            "type":"Services"
        },
        {
            "category":"Health Services",
            "subcategory":"Health Practitioner",
            "type":"Services"
        }
    ],
    "sg:phone":"+1 802 352 9838",
    "sg:postcode":"05769",
    "sg:province":"VT",
    "sg:tags":[
        "home",
        "eldercare-home"
    ],
    "wof:name":"Happy Hearts Home Care",
    "wof:placetype":"venue"
},
  "geometry": {"coordinates":[-73.14829,43.939862],"type":"Point"}
}