{
  "type": "Feature",
  "properties": {
    "addr:full":"146 Pleasant St Exd Ludlow VT 05149",
    "addr:housenumber":"146",
    "addr:postcode":"05149",
    "addr:street":"Pleasant St Exd",
    "iso:country":"US",
    "sg:address":"146 Pleasant St Exd",
    "sg:city":"Ludlow",
    "sg:classifiers":[
        {
            "category":"Manufacturing",
            "subcategory":"Building Materials",
            "type":"Manufacturing & Wholesale Goods"
        }
    ],
    "sg:phone":"+1 802 228 2020",
    "sg:postcode":"05149",
    "sg:province":"VT",
    "sg:tags":[
        "door"
    ],
    "wof:name":"JELD-Wen Windows & Doors",
    "wof:placetype":"venue"
},
  "geometry": {"coordinates":[-72.683061,43.3924],"type":"Point"}
}