{
  "type": "Feature",
  "properties": {
    "addr:full":"111 Barber St Bennington VT 05201",
    "addr:housenumber":"111",
    "addr:postcode":"05201",
    "addr:street":"Barber St",
    "iso:country":"US",
    "sg:address":"111 Barber St",
    "sg:city":"Bennington",
    "sg:classifiers":[
        {
            "category":"Social Services",
            "type":"Services"
        }
    ],
    "sg:phone":"+1 802 447 8734",
    "sg:postcode":"05201",
    "sg:province":"VT",
    "wof:name":"Benn Myotherapy/Mssg",
    "wof:placetype":"venue"
},
  "geometry": {"coordinates":[-73.191642,42.872789],"type":"Point"}
}