{
  "type": "Feature",
  "properties": {
    "addr:full":"79 Town Line Rd Rutland VT 05701",
    "addr:housenumber":"79",
    "addr:postcode":"05701",
    "addr:street":"Town Line Rd",
    "iso:country":"US",
    "sg:address":"79 Town Line Rd",
    "sg:city":"Rutland",
    "sg:classifiers":[
        {
            "category":"Shopping",
            "subcategory":"Catalog Store",
            "type":"Retail Goods"
        }
    ],
    "sg:phone":"+1 802 775 2445",
    "sg:postcode":"05701",
    "sg:province":"VT",
    "sg:tags":[
        "mail",
        "house"
    ],
    "wof:name":"Green Mountain Folk Food",
    "wof:placetype":"venue"
},
  "geometry": {"coordinates":[-72.937253,43.633795],"type":"Point"}
}