{
  "type": "Feature",
  "properties": {
    "addr:full":"78 Rose St Unit 10 Burlington VT 05401",
    "addr:housenumber":"78;10",
    "addr:postcode":"05401",
    "addr:street":"Rose St Unit",
    "iso:country":"US",
    "sg:address":"78 Rose St Unit 10",
    "sg:city":"Burlington",
    "sg:classifiers":[
        {
            "category":"Building & Trades",
            "subcategory":"Construction",
            "type":"Services"
        }
    ],
    "sg:phone":"+1 802 864 9045",
    "sg:postcode":"05401",
    "sg:province":"VT",
    "sg:tags":[
        "roofing",
        "industrial",
        "contractors-commercial",
        "contractor"
    ],
    "sg:website":"http://www.rooftoppottery.com",
    "wof:name":"Roof Top Pottery",
    "wof:placetype":"venue"
},
  "geometry": {"coordinates":[-73.21655800000001,44.486401],"type":"Point"}
}