{
  "type": "Feature",
  "properties": {
    "iso:country":"US",
    "sg:address":"136 N Main St",
    "sg:city":"Barre",
    "sg:classifiers":[
        {
            "category":"Personal",
            "subcategory":"Beauty Salon",
            "type":"Services"
        }
    ],
    "sg:phone":"+1 802 479 2800",
    "sg:postcode":"05641",
    "sg:province":"VT",
    "wof:name":"Anita's",
    "wof:placetype":"venue"
},
  "geometry": {"coordinates":[-72.503141,44.198625],"type":"Point"}
}