{
  "type": "Feature",
  "properties": {
    "addr:full":"1717 Williston Rd South Burlington VT 05403",
    "addr:housenumber":"1717",
    "addr:postcode":"05403",
    "addr:street":"Williston Rd",
    "iso:country":"US",
    "sg:address":"1717 Williston Rd",
    "sg:city":"South Burlington",
    "sg:classifiers":[
        {
            "category":"Shopping",
            "subcategory":"Crafts & Fabrics",
            "type":"Retail Goods"
        }
    ],
    "sg:phone":"+1 802 862 3288",
    "sg:postcode":"05403",
    "sg:province":"VT",
    "sg:tags":[
        "shop",
        "sewing",
        "mi"
    ],
    "wof:name":"Rags & Riches LTD",
    "wof:placetype":"venue"
},
  "geometry": {"coordinates":[-73.154448,44.463206],"type":"Point"}
}