{
  "type": "Feature",
  "properties": {
    "addr:full":"25 Maple Ave Barre VT 05641",
    "addr:housenumber":"25",
    "addr:postcode":"05641",
    "addr:street":"Maple Ave",
    "iso:country":"US",
    "sg:address":"25 Maple Ave",
    "sg:city":"Barre",
    "sg:classifiers":[
        {
            "category":"Real Estate",
            "subcategory":"Real Estate Agent",
            "type":"Services"
        }
    ],
    "sg:phone":"+1 802 476 7124",
    "sg:postcode":"05641",
    "sg:province":"VT",
    "sg:tags":[
        "appraisal",
        "appraiser"
    ],
    "wof:name":"Ellison Appraisal Associates",
    "wof:placetype":"venue"
},
  "geometry": {"coordinates":[-72.50589100000001,44.203579],"type":"Point"}
}