{
  "type": "Feature",
  "properties": {
    "addr:full":"123 E Main St Readsboro VT 05350",
    "addr:housenumber":"123",
    "addr:postcode":"05350",
    "addr:street":"E Main St",
    "iso:country":"US",
    "sg:address":"123 E Main St",
    "sg:city":"Readsboro",
    "sg:classifiers":[
        {
            "category":"Building & Trades",
            "subcategory":"Plumbing",
            "type":"Services"
        },
        {
            "category":"Government",
            "subcategory":"Department Of Motor Vehicles",
            "type":"Public Place"
        }
    ],
    "sg:phone":"+1 802 362 2344",
    "sg:postcode":"05350",
    "sg:province":"VT",
    "sg:tags":[
        "plumber",
        "tank",
        "cleaning"
    ],
    "wof:name":"Roto-Rooter Plumbers",
    "wof:placetype":"venue"
},
  "geometry": {"coordinates":[-72.945697,42.772294],"type":"Point"}
}