{
  "type": "Feature",
  "properties": {
    "iso:country":"US",
    "sg:address":"223 Ave D",
    "sg:city":"Williston",
    "sg:classifiers":[
        {
            "category":"Shopping",
            "subcategory":"Catalog Store",
            "type":"Retail Goods"
        },
        {
            "category":"Home & Garden",
            "subcategory":"Garden Supply",
            "type":"Retail Goods"
        }
    ],
    "sg:phone":"+1 802 985 9455",
    "sg:postcode":"05495",
    "sg:province":"VT",
    "sg:tags":[
        "bulb",
        "seed",
        "other",
        "wildflower"
    ],
    "wof:name":"American Meadows Inc",
    "wof:placetype":"venue"
},
  "geometry": {"coordinates":[-73.123088,44.464252],"type":"Point"}
}