{
  "type": "Feature",
  "properties": {
    "iso:country":"US",
    "sg:address":"62 Oak St",
    "sg:city":"Burlington",
    "sg:classifiers":[
        {
            "category":"Recreation",
            "type":"Entertainment"
        },
        {
            "category":"Social Services",
            "type":"Services"
        }
    ],
    "sg:phone":"+1 802 864 5263",
    "sg:postcode":"05401",
    "sg:province":"VT",
    "sg:tags":[
        "center",
        "for",
        "club",
        "youth",
        "membership",
        "organization"
    ],
    "sg:website":"www.bandgclub.org",
    "wof:name":"Boys & Girls CLB of Burlington",
    "wof:placetype":"venue"
},
  "geometry": {"coordinates":[-73.21165499999999,44.489843],"type":"Point"}
}