{
  "type": "Feature",
  "properties": {
    "addr:full":"33 Commerce Ave South Burlington VT 05403",
    "addr:housenumber":"33",
    "addr:postcode":"05403",
    "addr:street":"Commerce Ave",
    "iso:country":"US",
    "sg:address":"33 Commerce Ave",
    "sg:city":"South Burlington",
    "sg:classifiers":[
        {
            "category":"Building & Trades",
            "subcategory":"Landscaping Services",
            "type":"Services"
        }
    ],
    "sg:phone":"+1 802 863 8007",
    "sg:postcode":"05403",
    "sg:province":"VT",
    "sg:tags":[
        "lawn",
        "maintenance",
        "grounds"
    ],
    "wof:name":"Trugreen Chemlawn",
    "wof:placetype":"venue"
},
  "geometry": {"coordinates":[-73.15975400000001,44.483022],"type":"Point"}
}