{
  "type": "Feature",
  "properties": {
    "addr:full":"238 Union St Bennington VT 05201",
    "addr:housenumber":"238",
    "addr:postcode":"05201",
    "addr:street":"Union St",
    "iso:country":"US",
    "sg:address":"238 Union St",
    "sg:city":"Bennington",
    "sg:classifiers":[
        {
            "category":"Organizations",
            "subcategory":"Non-profit Organization",
            "type":"Services"
        }
    ],
    "sg:phone":"+1 802 442 6934",
    "sg:postcode":"05201",
    "sg:province":"VT",
    "wof:name":"Sunrise Family Resource Ctr",
    "wof:placetype":"venue"
},
  "geometry": {"coordinates":[-73.18902,42.876856],"type":"Point"}
}