{
  "type": "Feature",
  "properties": {
    "addr:full":"305 Guyette Rd East Montpelier VT 05651",
    "addr:housenumber":"305",
    "addr:postcode":"05651",
    "addr:street":"Guyette Rd",
    "iso:country":"US",
    "sg:address":"305 Guyette Rd",
    "sg:city":"East Montpelier",
    "sg:classifiers":[
        {
            "category":"Professional",
            "subcategory":"Management & Consulting",
            "type":"Services"
        }
    ],
    "sg:phone":"+1 802 223 0976",
    "sg:postcode":"05651",
    "sg:province":"VT",
    "sg:tags":[
        "business"
    ],
    "wof:name":"Richardson Associates",
    "wof:placetype":"venue"
},
  "geometry": {"coordinates":[-72.468096,44.300661],"type":"Point"}
}