{
  "type": "Feature",
  "properties": {
    "iso:country":"US",
    "sg:address":"5 Lawson Ln",
    "sg:city":"Burlington",
    "sg:classifiers":[
        {
            "category":"Professional",
            "subcategory":"Computer Services",
            "type":"Services"
        }
    ],
    "sg:phone":"+1 802 864 9245",
    "sg:postcode":"05401",
    "sg:province":"VT",
    "sg:tags":[
        "repair"
    ],
    "wof:name":"Rent A Geek",
    "wof:placetype":"venue"
},
  "geometry": {"coordinates":[-73.214657,44.47676],"type":"Point"}
}