{
  "type": "Feature",
  "properties": {
    "iso:country":"US",
    "sg:address":"14 Main St",
    "sg:city":"Chester",
    "sg:classifiers":[
        {
            "category":"Health Services",
            "subcategory":"Chiropractor",
            "type":"Services"
        }
    ],
    "sg:phone":"+1 802 875 5001",
    "sg:postcode":"05143",
    "sg:province":"VT",
    "wof:name":"Chester Chiropractic",
    "wof:placetype":"venue"
},
  "geometry": {"coordinates":[-72.59765,43.264131],"type":"Point"}
}