{
  "type": "Feature",
  "properties": {
    "iso:country":"US",
    "sg:address":"2614 Pawlet Mountain Rd",
    "sg:city":"Pawlet",
    "sg:classifiers":[
        {
            "category":"Building & Trades",
            "subcategory":"Construction",
            "type":"Services"
        }
    ],
    "sg:phone":"+1 802 394 2439",
    "sg:postcode":"05251",
    "sg:province":"VT",
    "sg:tags":[
        "house"
    ],
    "wof:name":"Mdc Construction",
    "wof:placetype":"venue"
},
  "geometry": {"coordinates":[-73.19380700000001,43.310465],"type":"Point"}
}