{
  "type": "Feature",
  "properties": {
    "iso:country":"US",
    "sg:address":"41 Bouchard Rd",
    "sg:city":"Franklin",
    "sg:classifiers":[
        {
            "category":"Farming",
            "subcategory":"Farm",
            "type":"Manufacturing & Wholesale Goods"
        }
    ],
    "sg:phone":"+1 802 285 6796",
    "sg:postcode":"05457",
    "sg:province":"VT",
    "wof:name":"Bouchard Farm Inc",
    "wof:placetype":"venue"
},
  "geometry": {"coordinates":[-72.98580800000001,45.007236],"type":"Point"}
}