{
  "type": "Feature",
  "properties": {
    "addr:full":"198 E Main St Newport VT 05855",
    "addr:housenumber":"198",
    "addr:postcode":"05855",
    "addr:street":"E Main St",
    "iso:country":"US",
    "sg:address":"198 E Main St",
    "sg:city":"Newport",
    "sg:classifiers":[
        {
            "category":"Autos & Motor Vehicles",
            "subcategory":"Auto Supplies",
            "type":"Retail Goods"
        }
    ],
    "sg:phone":"+1 802 334 6579",
    "sg:postcode":"05855",
    "sg:province":"VT",
    "wof:name":"Fisher Auto Parts Inc",
    "wof:placetype":"venue"
},
  "geometry": {"coordinates":[-72.202051,44.9427],"type":"Point"}
}