{
  "type": "Feature",
  "properties": {
    "iso:country":"US",
    "sg:address":"37 Moccasin Ave",
    "sg:city":"Grand Isle",
    "sg:classifiers":[
        {
            "category":"Building & Trades",
            "subcategory":"Construction",
            "type":"Services"
        }
    ],
    "sg:phone":"+1 802 372 5678",
    "sg:postcode":"05458",
    "sg:province":"VT",
    "sg:tags":[
        "maintenance",
        "contractor"
    ],
    "wof:name":"Mc Allister Maintenance Inc",
    "wof:placetype":"venue"
},
  "geometry": {"coordinates":[-73.31955600000001,44.734562],"type":"Point"}
}