{
  "type": "Feature",
  "properties": {
    "iso:country":"US",
    "sg:address":"260 S Main St",
    "sg:city":"Rutland",
    "sg:classifiers":[
        {
            "category":"Food & Beverages",
            "subcategory":"Groceries & Convenience Stores",
            "type":"Retail Goods"
        }
    ],
    "sg:phone":"+1 802 775 9021",
    "sg:postcode":"05701",
    "sg:province":"VT",
    "sg:tags":[
        "carwash"
    ],
    "wof:name":"Gulf Mart & Car Wash",
    "wof:placetype":"venue"
},
  "geometry": {"coordinates":[-72.971671,43.60498],"type":"Point"}
}