{
  "type": "Feature",
  "properties": {
    "iso:country":"US",
    "sg:address":"348 Chapin Rd",
    "sg:city":"Essex Junction",
    "sg:classifiers":[
        {
            "category":"Professional",
            "subcategory":"Art Services",
            "type":"Services"
        }
    ],
    "sg:phone":"+1 802 878 3636",
    "sg:postcode":"05452",
    "sg:province":"VT",
    "sg:tags":[
        "commercial",
        "design"
    ],
    "wof:name":"Rev Imaging Inc",
    "wof:placetype":"venue"
},
  "geometry": {"coordinates":[-73.054625,44.556967],"type":"Point"}
}