{
  "type": "Feature",
  "properties": {
    "iso:country":"US",
    "sg:address":"179 E Main St",
    "sg:city":"Hyde Park",
    "sg:classifiers":[
        {
            "category":"Government",
            "subcategory":"Court House",
            "type":"Public Place"
        }
    ],
    "sg:phone":"+1 802 888 7921",
    "sg:postcode":"05655",
    "sg:province":"VT",
    "sg:tags":[
        "state",
        "counsel"
    ],
    "wof:name":"Public Defender",
    "wof:placetype":"venue"
},
  "geometry": {"coordinates":[-72.611135,44.593113],"type":"Point"}
}