{
  "type": "Feature",
  "properties": {
    "iso:country":"US",
    "sg:address":"154 Flat Iron Rd",
    "sg:city":"Reading",
    "sg:classifiers":[
        {
            "category":"Building & Trades",
            "subcategory":"Electrical",
            "type":"Services"
        }
    ],
    "sg:phone":"+1 802 484 1291",
    "sg:postcode":"05062",
    "sg:province":"VT",
    "sg:tags":[
        "electrical",
        "contractor"
    ],
    "wof:name":"Mill Brook Electric",
    "wof:placetype":"venue"
},
  "geometry": {"coordinates":[-72.531876,43.472502],"type":"Point"}
}