{
  "type": "Feature",
  "properties": {
    "addr:full":"3109 State Rte 100 Waterbury VT 05676",
    "addr:housenumber":"3109",
    "addr:postcode":"05676",
    "addr:street":"State Rte 100",
    "iso:country":"US",
    "sg:address":"3109 State Rte 100",
    "sg:city":"Waterbury",
    "sg:classifiers":[
        {
            "category":"Retail",
            "subcategory":"Auto Repair",
            "type":"Services"
        }
    ],
    "sg:phone":"+1 802 244 5172",
    "sg:postcode":"05676",
    "sg:province":"VT",
    "sg:tags":[
        "painting"
    ],
    "wof:name":"J & D Enterprises",
    "wof:placetype":"venue"
},
  "geometry": {"coordinates":[-72.781493,44.285385],"type":"Point"}
}