{
  "type": "Feature",
  "properties": {
    "addr:full":"2559 Glen Rd Newport VT 05855",
    "addr:housenumber":"2559",
    "addr:postcode":"05855",
    "addr:street":"Glen Rd",
    "iso:country":"US",
    "sg:address":"2559 Glen Rd",
    "sg:city":"Newport",
    "sg:classifiers":[
        {
            "category":"Government",
            "subcategory":"Jail",
            "type":"Public Place"
        }
    ],
    "sg:phone":"+1 802 334 3364",
    "sg:postcode":"05855",
    "sg:province":"VT",
    "sg:tags":[
        "govt",
        "state",
        "institution"
    ],
    "wof:name":"Northern State Correctional",
    "wof:placetype":"venue"
},
  "geometry": {"coordinates":[-72.193794,44.905672],"type":"Point"}
}