{
  "type": "Feature",
  "properties": {
    "addr:full":"28 Barre St Montpelier VT 05602",
    "addr:housenumber":"28",
    "addr:postcode":"05602",
    "addr:street":"Barre St",
    "iso:country":"US",
    "sg:address":"28 Barre St",
    "sg:city":"Montpelier",
    "sg:classifiers":[
        {
            "category":"Professional",
            "subcategory":"Lawyer & Legal Services",
            "type":"Services"
        }
    ],
    "sg:phone":"+1 802 229 2000",
    "sg:postcode":"05602",
    "sg:province":"VT",
    "sg:tags":[
        "attorney"
    ],
    "wof:name":"Bauer Anderson & Gravel",
    "wof:placetype":"venue"
},
  "geometry": {"coordinates":[-72.575779,44.257917],"type":"Point"}
}