{
  "type": "Feature",
  "properties": {
    "iso:country":"US",
    "sg:address":"2545 Richville Rd",
    "sg:city":"Manchester Center",
    "sg:classifiers":[
        {
            "category":"Farming",
            "subcategory":"Farm",
            "type":"Manufacturing & Wholesale Goods"
        }
    ],
    "sg:phone":"+1 802 362 4088",
    "sg:postcode":"05255",
    "sg:province":"VT",
    "sg:tags":[
        "crop",
        "general"
    ],
    "wof:name":"Bushee Battenkill Valley Farm",
    "wof:placetype":"venue"
},
  "geometry": {"coordinates":[-73.051461,43.156197],"type":"Point"}
}