{
  "type": "Feature",
  "properties": {
    "addr:full":"336 Martindale Rd Shelburne VT 05482",
    "addr:housenumber":"336",
    "addr:postcode":"05482",
    "addr:street":"Martindale Rd",
    "iso:country":"US",
    "sg:address":"336 Martindale Rd",
    "sg:city":"Shelburne",
    "sg:classifiers":[
        {
            "category":"Restaurant",
            "type":"Food & Drink"
        }
    ],
    "sg:phone":"+1 802 985 3871",
    "sg:postcode":"05482",
    "sg:province":"VT",
    "sg:tags":[
        "caterer"
    ],
    "wof:name":"Catering By Dale",
    "wof:placetype":"venue"
},
  "geometry": {"coordinates":[-73.204311,44.415121],"type":"Point"}
}