{
  "type": "Feature",
  "properties": {
    "iso:country":"US",
    "sg:address":"150 Chez Ln",
    "sg:city":"Cambridge",
    "sg:classifiers":[
        {
            "category":"Travel",
            "subcategory":"Hotels & Motels",
            "type":"Entertainment"
        }
    ],
    "sg:phone":"+1 802 644 5985",
    "sg:postcode":"05444",
    "sg:province":"VT",
    "sg:website":"www.notchglenrentals.com",
    "wof:name":"Notch Glen Rentals",
    "wof:placetype":"venue"
},
  "geometry": {"coordinates":[-72.92800099999999,44.639801],"type":"Point"}
}