{
  "type": "Feature",
  "properties": {
    "iso:country":"US",
    "sg:address":"726 Mountain Rd",
    "sg:city":"Bristol",
    "sg:classifiers":[
        {
            "category":"Building & Trades",
            "subcategory":"Electrical",
            "type":"Services"
        }
    ],
    "sg:phone":"+1 802 951 8687",
    "sg:postcode":"05443",
    "sg:province":"VT",
    "sg:tags":[
        "electrical",
        "contractor"
    ],
    "wof:name":"Prosons Electric Inc",
    "wof:placetype":"venue"
},
  "geometry": {"coordinates":[-73.097804,44.245099],"type":"Point"}
}