{
  "type": "Feature",
  "properties": {
    "iso:country":"US",
    "sg:address":"36 Diamond St",
    "sg:city":"Saint Albans",
    "sg:classifiers":[
        {
            "category":"Professional",
            "subcategory":"Computer Services",
            "type":"Services"
        }
    ],
    "sg:phone":"+1 802 527 2176",
    "sg:postcode":"05478",
    "sg:province":"VT",
    "sg:tags":[
        "datum"
    ],
    "wof:name":"Sam Mishra",
    "wof:placetype":"venue"
},
  "geometry": {"coordinates":[-73.08263100000001,44.804448],"type":"Point"}
}