{
  "type": "Feature",
  "properties": {
    "iso:country":"US",
    "sg:address":"910 Hackadam Rd",
    "sg:city":"Fair Haven",
    "sg:classifiers":[
        {
            "category":"Government",
            "subcategory":"Fire Station",
            "type":"Public Place"
        }
    ],
    "sg:phone":"+1 802 265 8630",
    "sg:postcode":"05743",
    "sg:province":"VT",
    "sg:tags":[
        "protection"
    ],
    "wof:name":"West Haven Volunteer Fire Dept",
    "wof:placetype":"venue"
},
  "geometry": {"coordinates":[-73.32440099999999,43.636189],"type":"Point"}
}