{
  "type": "Feature",
  "properties": {
    "iso:country":"US",
    "sg:address":"195 Flynn Ave",
    "sg:city":"Burlington",
    "sg:classifiers":[
        {
            "category":"Home & Garden",
            "subcategory":"Building Materials",
            "type":"Retail Goods"
        }
    ],
    "sg:phone":"+1 802 660 0447",
    "sg:postcode":"05401",
    "sg:province":"VT",
    "sg:tags":[
        "glass",
        "leaded"
    ],
    "wof:name":"Green Mountain Glassworks",
    "wof:placetype":"venue"
},
  "geometry": {"coordinates":[-73.220142,44.455627],"type":"Point"}
}