{
  "type": "Feature",
  "properties": {
    "iso:country":"US",
    "sg:address":"171 Saint John St",
    "sg:city":"Rutland",
    "sg:classifiers":[
        {
            "category":"Building & Trades",
            "subcategory":"Plumbing",
            "type":"Services"
        }
    ],
    "sg:phone":"+1 802 773 9502",
    "sg:postcode":"05701",
    "sg:province":"VT",
    "sg:tags":[
        "contractor"
    ],
    "wof:name":"Erwin Plumbing & Heating",
    "wof:placetype":"venue"
},
  "geometry": {"coordinates":[-72.95871,43.616575],"type":"Point"}
}