{
  "type": "Feature",
  "properties": {
    "iso:country":"US",
    "sg:address":"951 Nichols Hill Rd",
    "sg:city":"Dorset",
    "sg:classifiers":[
        {
            "category":"Professional",
            "type":"Services"
        }
    ],
    "sg:phone":"+1 802 867 0375",
    "sg:postcode":"05251",
    "sg:province":"VT",
    "wof:name":"Dml Corp",
    "wof:placetype":"venue"
},
  "geometry": {"coordinates":[-73.11769,43.23053],"type":"Point"}
}