{
  "type": "Feature",
  "properties": {
    "iso:country":"US",
    "sg:address":"37 Miller Brook Rd",
    "sg:city":"Killington",
    "sg:classifiers":[
        {
            "category":"Freight",
            "type":"Transportation"
        }
    ],
    "sg:phone":"+1 802 422 4939",
    "sg:postcode":"05751",
    "sg:province":"VT",
    "sg:tags":[
        "trucking"
    ],
    "wof:name":"Coe Transport",
    "wof:placetype":"venue"
},
  "geometry": {"coordinates":[-72.788836,43.644483],"type":"Point"}
}