{
  "type": "Feature",
  "properties": {
    "addr:full":"280 East Ave Burlington VT 05401",
    "addr:housenumber":"280",
    "addr:postcode":"05401",
    "addr:street":"East Ave",
    "iso:country":"US",
    "sg:address":"280 East Ave",
    "sg:city":"Burlington",
    "sg:classifiers":[
        {
            "category":"Professional",
            "subcategory":"Engineering",
            "type":"Services"
        }
    ],
    "sg:phone":"+1 802 656 3255",
    "sg:postcode":"05401",
    "sg:province":"VT",
    "wof:name":"Technical Services Program",
    "wof:placetype":"venue"
},
  "geometry": {"coordinates":[-73.190597,44.474929],"type":"Point"}
}