{
  "type": "Feature",
  "properties": {
    "iso:country":"US",
    "sg:address":"6367 State Rte 7a",
    "sg:city":"Arlington",
    "sg:classifiers":[
        {
            "category":"Shopping",
            "subcategory":"Gifts & Souvenirs",
            "type":"Retail Goods"
        }
    ],
    "sg:phone":"+1 802 362 2045",
    "sg:postcode":"05250",
    "sg:province":"VT",
    "sg:tags":[
        "shop"
    ],
    "wof:name":"Sunderland Country Shoppes",
    "wof:placetype":"venue"
},
  "geometry": {"coordinates":[-73.13821799999999,43.101214],"type":"Point"}
}