{
  "type": "Feature",
  "properties": {
    "iso:country":"US",
    "sg:address":"342 Wood Rd",
    "sg:city":"White River Junction",
    "sg:classifiers":[
        {
            "category":"Autos & Motor Vehicles",
            "subcategory":"Automobile Sales",
            "type":"Retail Goods"
        }
    ],
    "sg:phone":"+1 802 280 3012",
    "sg:postcode":"05059",
    "sg:province":"VT",
    "wof:name":"Merchants Rent-A-Car Inc",
    "wof:placetype":"venue"
},
  "geometry": {"coordinates":[-72.44794,43.634108],"type":"Point"}
}