{
  "type": "Feature",
  "properties": {
    "iso:country":"US",
    "sg:address":"500 Main St",
    "sg:city":"Randolph Center",
    "sg:classifiers":[
        {
            "category":"Professional",
            "subcategory":"Management & Consulting",
            "type":"Services"
        }
    ],
    "sg:phone":"+1 802 728 9101",
    "sg:postcode":"05045",
    "sg:province":"VT",
    "sg:tags":[
        "education",
        "business"
    ],
    "wof:name":"Vermont Business Educatn Corp",
    "wof:placetype":"venue"
},
  "geometry": {"coordinates":[-72.141124,43.908252],"type":"Point"}
}