{
  "type": "Feature",
  "properties": {
    "iso:country":"US",
    "sg:address":"48 Windcrest Rd",
    "sg:city":"Rutland",
    "sg:classifiers":[
        {
            "category":"Home & Garden",
            "subcategory":"Furniture",
            "type":"Retail Goods"
        }
    ],
    "sg:phone":"+1 802 775 0175",
    "sg:postcode":"05701",
    "sg:province":"VT",
    "sg:tags":[
        "equipment",
        "kitchen",
        "cabinet"
    ],
    "wof:name":"Lavalley Kitchen & Bath",
    "wof:placetype":"venue"
},
  "geometry": {"coordinates":[-72.964276,43.575525],"type":"Point"}
}