{
  "type": "Feature",
  "properties": {
    "addr:full":"309 Main St Norwich VT 05055",
    "addr:housenumber":"309",
    "addr:postcode":"05055",
    "addr:street":"Main St",
    "iso:country":"US",
    "sg:address":"309 Main St",
    "sg:city":"Norwich",
    "sg:classifiers":[
        {
            "category":"Banks & Credit Unions",
            "subcategory":"Bank",
            "type":"Services"
        }
    ],
    "sg:phone":"+1 802 649 5556",
    "sg:postcode":"05055",
    "sg:province":"VT",
    "sg:tags":[
        "loan",
        "real estate"
    ],
    "wof:name":"Eastern Mountain Mortgage Co",
    "wof:placetype":"venue"
},
  "geometry": {"coordinates":[-72.308702,43.715204],"type":"Point"}
}