{
  "type": "Feature",
  "properties": {
    "iso:country":"US",
    "sg:address":"655 Main St",
    "sg:city":"Bennington",
    "sg:classifiers":[
        {
            "category":"Social Services",
            "type":"Services"
        }
    ],
    "sg:phone":"+1 802 447 4811",
    "sg:postcode":"05201",
    "sg:province":"VT",
    "sg:tags":[
        "health"
    ],
    "wof:name":"Maureen McClintock Acsw",
    "wof:placetype":"venue"
},
  "geometry": {"coordinates":[-73.19063300000001,42.877986],"type":"Point"}
}