{
  "type": "Feature",
  "properties": {
    "iso:country":"US",
    "sg:address":"23 Edson St",
    "sg:city":"Burlington",
    "sg:classifiers":[
        {
            "category":"Professional",
            "type":"Services"
        }
    ],
    "sg:phone":"+1 802 658 8806",
    "sg:postcode":"05408",
    "sg:province":"VT",
    "wof:name":"Helping Hands Consulting",
    "wof:placetype":"venue"
},
  "geometry": {"coordinates":[-72.575941,44.21006],"type":"Point"}
}