{
  "type": "Feature",
  "properties": {
    "iso:country":"US",
    "sg:address":"120 Elm St",
    "sg:city":"Bennington",
    "sg:classifiers":[
        {
            "category":"Health Services",
            "subcategory":"Doctor",
            "type":"Services"
        }
    ],
    "sg:phone":"+1 802 442 3900",
    "sg:postcode":"05201",
    "sg:province":"VT",
    "sg:tags":[
        "medical"
    ],
    "wof:name":"Joseph Kratzer MD",
    "wof:placetype":"venue"
},
  "geometry": {"coordinates":[-73.19745899999999,42.87658],"type":"Point"}
}