{
  "type": "Feature",
  "properties": {
    "iso:country":"US",
    "sg:address":"3634 Bonnyvale Rd",
    "sg:city":"Guilford",
    "sg:classifiers":[
        {
            "category":"Building & Trades",
            "subcategory":"Landscaping Services",
            "type":"Services"
        }
    ],
    "sg:phone":"+1 802 254 2293",
    "sg:postcode":"05301",
    "sg:province":"VT",
    "sg:tags":[
        "tree"
    ],
    "wof:name":"Mayotte's Tree & Crane Svc",
    "wof:placetype":"venue"
},
  "geometry": {"coordinates":[-72.62864500000001,42.813224],"type":"Point"}
}