{
  "type": "Feature",
  "properties": {
    "iso:country":"US",
    "sg:address":"1067 Turnpike Rd",
    "sg:city":"Norwich",
    "sg:classifiers":[
        {
            "category":"Professional",
            "subcategory":"Advertising",
            "type":"Services"
        }
    ],
    "sg:phone":"+1 802 649 1976",
    "sg:postcode":"05055",
    "sg:province":"VT",
    "sg:tags":[
        "mail"
    ],
    "wof:name":"J C Manheimer & Co",
    "wof:placetype":"venue"
},
  "geometry": {"coordinates":[-72.31699999999999,43.735085],"type":"Point"}
}