{
  "type": "Feature",
  "properties": {
    "iso:country":"US",
    "sg:address":"146 Atcherson Hollow Rd",
    "sg:city":"Chester",
    "sg:classifiers":[
        {
            "category":"Real Estate",
            "subcategory":"Real Estate Agent",
            "type":"Services"
        }
    ],
    "sg:phone":"+1 802 869 2252",
    "sg:postcode":"05143",
    "sg:province":"VT",
    "wof:name":"Noble Realty",
    "wof:placetype":"venue"
},
  "geometry": {"coordinates":[-72.553686,43.160817],"type":"Point"}
}