{
  "type": "Feature",
  "properties": {
    "iso:country":"US",
    "sg:address":"2004 Memorial Dr",
    "sg:city":"St Johnsbury",
    "sg:classifiers":[
        {
            "category":"Food & Beverages",
            "subcategory":"Groceries & Convenience Stores",
            "type":"Retail Goods"
        }
    ],
    "sg:phone":"+1 802 748 2004",
    "sg:postcode":"05819",
    "sg:province":"VT",
    "sg:tags":[
        "grocer"
    ],
    "wof:name":"Sav-A-Lot",
    "wof:placetype":"venue"
},
  "geometry": {"coordinates":[-72.015384,44.461097],"type":"Point"}
}