{
  "type": "Feature",
  "properties": {
    "iso:country":"US",
    "sg:address":"89 Bellows Rd",
    "sg:city":"Springfield",
    "sg:classifiers":[
        {
            "category":"Retail",
            "subcategory":"Repair Shop",
            "type":"Services"
        }
    ],
    "sg:phone":"+1 802 885 3517",
    "sg:postcode":"05156",
    "sg:province":"VT",
    "sg:tags":[
        "upholsterer"
    ],
    "wof:name":"Hurd's Upholstering",
    "wof:placetype":"venue"
},
  "geometry": {"coordinates":[-72.514745,43.300353],"type":"Point"}
}