{
  "type": "Feature",
  "properties": {
    "addr:full":"99 School St Canaan VT 05903",
    "addr:housenumber":"99",
    "addr:postcode":"05903",
    "addr:street":"School St",
    "iso:country":"US",
    "sg:address":"99 School St",
    "sg:city":"Canaan",
    "sg:classifiers":[
        {
            "category":"Education",
            "subcategory":"School",
            "type":"Public Place"
        }
    ],
    "sg:phone":"+1 802 266 8910",
    "sg:postcode":"05903",
    "sg:province":"VT",
    "wof:name":"Canaan Memorial School",
    "wof:placetype":"venue"
},
  "geometry": {"coordinates":[-71.53718000000001,44.995779],"type":"Point"}
}