{
  "type": "Feature",
  "properties": {
    "iso:country":"US",
    "sg:address":"2549 Huntington Rd",
    "sg:city":"Richmond",
    "sg:classifiers":[
        {
            "category":"Retail",
            "subcategory":"Auto Repair",
            "type":"Services"
        }
    ],
    "sg:phone":"+1 802 434 3940",
    "sg:postcode":"05477",
    "sg:province":"VT",
    "sg:tags":[
        "repairing",
        "automobile"
    ],
    "wof:name":"Washburn's Servicenter Inc",
    "wof:placetype":"venue"
},
  "geometry": {"coordinates":[-72.999926,44.371947],"type":"Point"}
}