{
  "type": "Feature",
  "properties": {
    "iso:country":"US",
    "sg:address":"370 River St",
    "sg:city":"Montpelier",
    "sg:classifiers":[
        {
            "category":"Personal",
            "subcategory":"Beauty Salon",
            "type":"Services"
        }
    ],
    "sg:phone":"+1 802 223 6888",
    "sg:postcode":"05602",
    "sg:province":"VT",
    "wof:name":"Dosha Salon & Day Spa",
    "wof:placetype":"venue"
},
  "geometry": {"coordinates":[-72.55330600000001,44.237695],"type":"Point"}
}