{
  "type": "Feature",
  "properties": {
    "iso:country":"US",
    "sg:address":"342 Whitney Creek Rd",
    "sg:city":"Vergennes",
    "sg:classifiers":[
        {
            "category":"Building & Trades",
            "subcategory":"Plumbing",
            "type":"Services"
        }
    ],
    "sg:phone":"+1 802 759 2220",
    "sg:postcode":"05491",
    "sg:province":"VT",
    "sg:tags":[
        "plumbing",
        "contractor"
    ],
    "wof:name":"Bienvenue & Ackel Inc",
    "wof:placetype":"venue"
},
  "geometry": {"coordinates":[-73.398956,44.033294],"type":"Point"}
}