{
  "type": "Feature",
  "properties": {
    "iso:country":"US",
    "sg:address":"37 Benny Rd",
    "sg:city":"Fairfax",
    "sg:classifiers":[
        {
            "category":"Building & Trades",
            "subcategory":"Plumbing",
            "type":"Services"
        }
    ],
    "sg:phone":"+1 802 849 6274",
    "sg:postcode":"05454",
    "sg:province":"VT",
    "sg:tags":[
        "contractor"
    ],
    "wof:name":"A Plus Mechanical",
    "wof:placetype":"venue"
},
  "geometry": {"coordinates":[-72.98942599999999,44.667972],"type":"Point"}
}