{
  "type": "Feature",
  "properties": {
    "addr:full":"7 Court St Newfane VT 05345",
    "addr:housenumber":"7",
    "addr:postcode":"05345",
    "addr:street":"Court St",
    "iso:country":"US",
    "sg:address":"7 Court St",
    "sg:city":"Newfane",
    "sg:classifiers":[
        {
            "category":"Government",
            "subcategory":"Court House",
            "type":"Public Place"
        }
    ],
    "sg:phone":"+1 802 365 4257",
    "sg:postcode":"05345",
    "sg:province":"VT",
    "sg:tags":[
        "county"
    ],
    "wof:name":"Windham County Superior Court",
    "wof:placetype":"venue"
},
  "geometry": {"coordinates":[-72.655473,42.986418],"type":"Point"}
}