{
  "type": "Feature",
  "properties": {
    "iso:country":"US",
    "sg:address":"516 Main St",
    "sg:city":"Orwell",
    "sg:classifiers":[
        {
            "category":"Personal",
            "subcategory":"Beauty Salon",
            "type":"Services"
        }
    ],
    "sg:phone":"+1 802 948 2202",
    "sg:postcode":"05760",
    "sg:province":"VT",
    "wof:name":"Marions Family Hair Care",
    "wof:placetype":"venue"
},
  "geometry": {"coordinates":[-73.297813,43.803761],"type":"Point"}
}