{
  "type": "Feature",
  "properties": {
    "iso:country":"US",
    "sg:address":"3 Crest Rd",
    "sg:city":"Saint Albans",
    "sg:classifiers":[
        {
            "category":"Health Services",
            "subcategory":"Doctor",
            "type":"Services"
        }
    ],
    "sg:phone":"+1 802 527 1282",
    "sg:postcode":"05478",
    "sg:province":"VT",
    "sg:tags":[
        "medical"
    ],
    "wof:name":"Bruce Foerster MD",
    "wof:placetype":"venue"
},
  "geometry": {"coordinates":[-73.070944,44.807953],"type":"Point"}
}