{
  "type": "Feature",
  "properties": {
    "iso:country":"US",
    "sg:address":"22 Church St",
    "sg:city":"Bristol",
    "sg:classifiers":[
        {
            "category":"Building & Trades",
            "subcategory":"Construction",
            "type":"Services"
        }
    ],
    "sg:phone":"+1 802 453 3906",
    "sg:postcode":"05443",
    "sg:province":"VT",
    "wof:name":"Frank D Lossman Contractor",
    "wof:placetype":"venue"
},
  "geometry": {"coordinates":[-73.080591,44.135324],"type":"Point"}
}