{
  "type": "Feature",
  "properties": {
    "addr:full":"570 Sangamon Rd Pittsford VT 05763",
    "addr:housenumber":"570",
    "addr:postcode":"05763",
    "addr:street":"Sangamon Rd",
    "iso:country":"US",
    "sg:address":"570 Sangamon Rd",
    "sg:city":"Pittsford",
    "sg:classifiers":[
        {
            "category":"Professional",
            "subcategory":"Business Services",
            "type":"Services"
        }
    ],
    "sg:phone":"+1 802 483 6137",
    "sg:postcode":"05763",
    "sg:province":"VT",
    "wof:name":"Interior Plant Works Vermon",
    "wof:placetype":"venue"
},
  "geometry": {"coordinates":[-72.973314,43.688228],"type":"Point"}
}