{
  "type": "Feature",
  "properties": {
    "iso:country":"US",
    "sg:address":"1 Scale Ave",
    "sg:city":"Rutland",
    "sg:classifiers":[
        {
            "category":"Freight",
            "type":"Transportation"
        }
    ],
    "sg:phone":"+1 802 786 9008",
    "sg:postcode":"05701",
    "sg:province":"VT",
    "sg:tags":[
        "distance",
        "storage",
        "moving",
        "long",
        "local"
    ],
    "wof:name":"Alpaca Transport",
    "wof:placetype":"venue"
},
  "geometry": {"coordinates":[-72.97369999999999,43.600792],"type":"Point"}
}