{
  "type": "Feature",
  "properties": {
    "iso:country":"US",
    "sg:address":"257 S Champlain St",
    "sg:city":"Burlington",
    "sg:classifiers":[
        {
            "category":"Building & Trades",
            "subcategory":"Construction",
            "type":"Services"
        }
    ],
    "sg:phone":"+1 802 864 8183",
    "sg:postcode":"05401",
    "sg:province":"VT",
    "sg:tags":[
        "designer"
    ],
    "wof:name":"Manock Comprehensive Design",
    "wof:placetype":"venue"
},
  "geometry": {"coordinates":[-73.21693,44.472958],"type":"Point"}
}