{
  "type": "Feature",
  "properties": {
    "addr:full":"10 North St Bristol VT 05443",
    "addr:housenumber":"10",
    "addr:postcode":"05443",
    "addr:street":"North St",
    "iso:country":"US",
    "sg:address":"10 North St",
    "sg:city":"Bristol",
    "sg:classifiers":[
        {
            "category":"Building & Trades",
            "subcategory":"Plumbing",
            "type":"Services"
        }
    ],
    "sg:phone":"+1 802 453 4919",
    "sg:postcode":"05443",
    "sg:province":"VT",
    "sg:tags":[
        "contractor",
        "fabricated",
        "mfg"
    ],
    "wof:name":"Chiptec Corp",
    "wof:placetype":"venue"
},
  "geometry": {"coordinates":[-73.078699,44.133204],"type":"Point"}
}