{
  "type": "Feature",
  "properties": {
    "addr:full":"953 E Lake Rd Ludlow VT 05149",
    "addr:housenumber":"953",
    "addr:postcode":"05149",
    "addr:street":"E Lake Rd",
    "iso:country":"US",
    "sg:address":"953 E Lake Rd",
    "sg:city":"Ludlow",
    "sg:classifiers":[
        {
            "category":"Travel",
            "subcategory":"Hotels & Motels",
            "type":"Entertainment"
        }
    ],
    "sg:phone":"+1 802 228 8799",
    "sg:postcode":"05149",
    "sg:province":"VT",
    "sg:tags":[
        "operation",
        "eating"
    ],
    "sg:website":"www.combesfamilyinn.com",
    "wof:name":"Combes Family Inn",
    "wof:placetype":"venue"
},
  "geometry": {"coordinates":[-72.69451599999999,43.453544],"type":"Point"}
}