{
  "type": "Feature",
  "properties": {
    "addr:full":"90 Allen Rd South Burlington VT 05403",
    "addr:housenumber":"90",
    "addr:postcode":"05403",
    "addr:street":"Allen Rd",
    "iso:country":"US",
    "sg:address":"90 Allen Rd",
    "sg:city":"South Burlington",
    "sg:classifiers":[
        {
            "category":"Social Services",
            "subcategory":"Adult Care",
            "type":"Services"
        },
        {
            "category":"Health Services",
            "subcategory":"Nursing And Care Facility",
            "type":"Services"
        }
    ],
    "sg:phone":"+1 802 863 3926",
    "sg:postcode":"05403",
    "sg:province":"VT",
    "sg:tags":[
        "home",
        "retirement",
        "community",
        "residential"
    ],
    "wof:name":"Allenwood At Pillsbury Manor",
    "wof:placetype":"venue"
},
  "geometry": {"coordinates":[-73.20909399999999,44.422334],"type":"Point"}
}