{
  "type": "Feature",
  "properties": {
    "iso:country":"US",
    "sg:address":"160 Seward Rd",
    "sg:city":"Rutland",
    "sg:classifiers":[
        {
            "category":"Building & Trades",
            "subcategory":"Plumbing",
            "type":"Services"
        }
    ],
    "sg:phone":"+1 802 773 1209",
    "sg:postcode":"05701",
    "sg:province":"VT",
    "sg:tags":[
        "contractor"
    ],
    "sg:website":"www.thegranitegroup.com",
    "wof:name":"Granite Group",
    "wof:placetype":"venue"
},
  "geometry": {"coordinates":[-72.96618100000001,43.585546],"type":"Point"}
}