{
  "type": "Feature",
  "properties": {
    "iso:country":"US",
    "sg:address":"60 Institute Rd",
    "sg:city":"Burlington",
    "sg:classifiers":[
        {
            "category":"Autos & Motor Vehicles",
            "subcategory":"Boat Sales",
            "type":"Retail Goods"
        }
    ],
    "sg:phone":"+1 802 865 6777",
    "sg:postcode":"05401",
    "sg:province":"VT",
    "sg:tags":[
        "canoe"
    ],
    "wof:name":"Umiak Outdoor Outfitters",
    "wof:placetype":"venue"
},
  "geometry": {"coordinates":[-73.23574499999999,44.494737],"type":"Point"}
}