{
  "type": "Feature",
  "properties": {
    "iso:country":"US",
    "sg:address":"77 Concord Ave",
    "sg:city":"St Johnsbury",
    "sg:classifiers":[
        {
            "category":"Retail",
            "subcategory":"Repair Shop",
            "type":"Services"
        }
    ],
    "sg:phone":"+1 802 748 9719",
    "sg:postcode":"05819",
    "sg:province":"VT",
    "sg:tags":[
        "gas",
        "appliance"
    ],
    "wof:name":"Northeast Propane Svc",
    "wof:placetype":"venue"
},
  "geometry": {"coordinates":[-72.013779,44.425685],"type":"Point"}
}