{
  "type": "Feature",
  "properties": {
    "addr:full":"4793 State Rte 114 East Burke VT 05832",
    "addr:housenumber":"4793",
    "addr:postcode":"05832",
    "addr:street":"State Rte 114 East",
    "iso:country":"US",
    "sg:address":"4793 State Rte 114",
    "sg:city":"East Burke",
    "sg:classifiers":[
        {
            "category":"Manufacturing",
            "subcategory":"Lumber",
            "type":"Manufacturing & Wholesale Goods"
        }
    ],
    "sg:phone":"+1 802 467 3904",
    "sg:postcode":"05832",
    "sg:province":"VT",
    "sg:tags":[
        "company",
        "logging"
    ],
    "wof:name":"Walter Bandy Jr & Son",
    "wof:placetype":"venue"
},
  "geometry": {"coordinates":[-71.895534,44.637667],"type":"Point"}
}