{
  "type": "Feature",
  "properties": {
    "iso:country":"US",
    "sg:address":"46 Howard St",
    "sg:city":"Morrisville",
    "sg:classifiers":[
        {
            "category":"Building & Trades",
            "subcategory":"Electrical",
            "type":"Services"
        }
    ],
    "sg:phone":"+1 802 888 2362",
    "sg:postcode":"05661",
    "sg:province":"VT",
    "sg:tags":[
        "electrical",
        "contractor"
    ],
    "wof:name":"Wilder Electric",
    "wof:placetype":"venue"
},
  "geometry": {"coordinates":[-72.598202,44.557316],"type":"Point"}
}