{
  "type": "Feature",
  "properties": {
    "iso:country":"US",
    "sg:address":"100 Pearl St",
    "sg:city":"Essex Junction",
    "sg:classifiers":[
        {
            "category":"Autos & Motor Vehicles",
            "subcategory":"Automobile Sales",
            "type":"Retail Goods"
        }
    ],
    "sg:phone":"+1 802 879 1532",
    "sg:postcode":"05452",
    "sg:province":"VT",
    "sg:tags":[
        "automotive",
        "au",
        "general"
    ],
    "sg:website":"www.vermontmercury.com",
    "wof:name":"Capital Lincoln Mercury",
    "wof:placetype":"venue"
},
  "geometry": {"coordinates":[-73.12187299999999,44.495155],"type":"Point"}
}