{
  "type": "Feature",
  "properties": {
    "iso:country":"US",
    "sg:address":"499 Beaver Creek Rd",
    "sg:city":"Shelburne",
    "sg:classifiers":[
        {
            "category":"Communications",
            "type":"Services"
        }
    ],
    "sg:phone":"+1 802 985 8682",
    "sg:postcode":"05482",
    "sg:province":"VT",
    "sg:tags":[
        "communication"
    ],
    "wof:name":"Zeus Communications",
    "wof:placetype":"venue"
},
  "geometry": {"coordinates":[-73.19456599999999,44.3941],"type":"Point"}
}