{
  "type": "Feature",
  "properties": {
    "iso:country":"US",
    "sg:address":"1114 Putney Rd",
    "sg:city":"Brattleboro",
    "sg:classifiers":[
        {
            "category":"Autos & Motor Vehicles",
            "subcategory":"Fuel & Gas Station",
            "type":"Retail Goods"
        }
    ],
    "sg:phone":"+1 802 254 7397",
    "sg:postcode":"05301",
    "sg:province":"VT",
    "sg:tags":[
        "oil"
    ],
    "wof:name":"Brattleboro Mobil",
    "wof:placetype":"venue"
},
  "geometry": {"coordinates":[-72.556921,42.884535],"type":"Point"}
}