{
  "type": "Feature",
  "properties": {
    "iso:country":"US",
    "sg:address":"132 Mountain Rd",
    "sg:city":"Stowe",
    "sg:classifiers":[
        {
            "category":"Home & Garden",
            "subcategory":"Furniture",
            "type":"Retail Goods"
        }
    ],
    "sg:phone":"+1 802 253 3710",
    "sg:postcode":"05672",
    "sg:province":"VT",
    "wof:name":"Cotswold Furniture Makers",
    "wof:placetype":"venue"
},
  "geometry": {"coordinates":[-72.688602,44.467515],"type":"Point"}
}