{
  "type": "Feature",
  "properties": {
    "iso:country":"US",
    "sg:address":"710 State Rte 30",
    "sg:city":"Townshend",
    "sg:classifiers":[
        {
            "category":"Retail",
            "subcategory":"Veterinary Services",
            "type":"Services"
        }
    ],
    "sg:phone":"+1 802 365 9663",
    "sg:postcode":"05353",
    "sg:province":"VT",
    "sg:tags":[
        "veterinarian"
    ],
    "wof:name":"Townsend Animal Clinic",
    "wof:placetype":"venue"
},
  "geometry": {"coordinates":[-72.658997,43.02923],"type":"Point"}
}