{
  "type": "Feature",
  "properties": {
    "addr:full":"59 Weed Rd Essex Junction VT 05452",
    "addr:housenumber":"59",
    "addr:postcode":"05452",
    "addr:street":"Weed Rd",
    "iso:country":"US",
    "sg:address":"59 Weed Rd",
    "sg:city":"Essex Junction",
    "sg:classifiers":[
        {
            "category":"Professional",
            "subcategory":"Management & Consulting",
            "type":"Services"
        }
    ],
    "sg:phone":"+1 802 878 3044",
    "sg:postcode":"05452",
    "sg:province":"VT",
    "sg:tags":[
        "public",
        "relations"
    ],
    "wof:name":"Vermont Holstein Association",
    "wof:placetype":"venue"
},
  "geometry": {"coordinates":[-73.02302400000001,44.507748],"type":"Point"}
}