{
  "type": "Feature",
  "properties": {
    "iso:country":"US",
    "sg:address":"7 Airport Dr",
    "sg:city":"Bristol",
    "sg:classifiers":[
        {
            "category":"Education",
            "subcategory":"School",
            "type":"Public Place"
        }
    ],
    "sg:phone":"+1 802 453 2333",
    "sg:postcode":"05443",
    "sg:province":"VT",
    "wof:name":"Mt Abraham Union High School",
    "wof:placetype":"venue"
},
  "geometry": {"coordinates":[-73.090287,44.133115],"type":"Point"}
}