{
  "type": "Feature",
  "properties": {
    "addr:full":"309 US Hwy 302 Barre VT 05641",
    "addr:housenumber":"309",
    "addr:postcode":"05641",
    "addr:street":"Us Hwy 302",
    "iso:country":"US",
    "sg:address":"309 US Hwy 302",
    "sg:city":"Barre",
    "sg:classifiers":[
        {
            "category":"Retail",
            "subcategory":"Repair Shop",
            "type":"Services"
        }
    ],
    "sg:phone":"+1 802 479 0811",
    "sg:postcode":"05641",
    "sg:province":"VT",
    "sg:tags":[
        "electrical"
    ],
    "wof:name":"Morel Electronics",
    "wof:placetype":"venue"
},
  "geometry": {"coordinates":[-72.430325,44.15268],"type":"Point"}
}