{
  "type": "Feature",
  "properties": {
    "iso:country":"US",
    "sg:address":"77 Wales St",
    "sg:city":"Rutland",
    "sg:classifiers":[
        {
            "category":"Food & Beverages",
            "subcategory":"Groceries & Convenience Stores",
            "type":"Retail Goods"
        },
        {
            "category":"Food & Beverages",
            "subcategory":"Specialty",
            "type":"Retail Goods"
        }
    ],
    "sg:phone":"+1 802 773 0737",
    "sg:postcode":"05701",
    "sg:province":"VT",
    "sg:tags":[
        "health",
        "diet"
    ],
    "wof:name":"Rutland Area Food Co Op",
    "wof:placetype":"venue"
},
  "geometry": {"coordinates":[-72.977718,43.606952],"type":"Point"}
}