{
  "type": "Feature",
  "properties": {
    "addr:full":"75 Hunt St Fairfax VT 05454",
    "addr:housenumber":"75",
    "addr:postcode":"05454",
    "addr:street":"Hunt St",
    "iso:country":"US",
    "sg:address":"75 Hunt St",
    "sg:city":"Fairfax",
    "sg:classifiers":[
        {
            "category":"Education",
            "subcategory":"Library",
            "type":"Public Place"
        }
    ],
    "sg:phone":"+1 802 849 2420",
    "sg:postcode":"05454",
    "sg:province":"VT",
    "wof:name":"Fairfax Community Library",
    "wof:placetype":"venue"
},
  "geometry": {"coordinates":[-73.013836,44.663018],"type":"Point"}
}