{
  "type": "Feature",
  "properties": {
    "addr:full":"13 Park Ct Rutland VT 05701",
    "addr:housenumber":"13",
    "addr:postcode":"05701",
    "addr:street":"Park Ct",
    "iso:country":"US",
    "sg:address":"13 Park Ct",
    "sg:city":"Rutland",
    "sg:classifiers":[
        {
            "category":"Restaurant",
            "type":"Food & Drink"
        }
    ],
    "sg:phone":"+1 802 773 7895",
    "sg:postcode":"05701",
    "sg:province":"VT",
    "sg:tags":[
        "eating"
    ],
    "wof:name":"Mollys Table Mates",
    "wof:placetype":"venue"
},
  "geometry": {"coordinates":[-72.966352,43.618458],"type":"Point"}
}