{
  "type": "Feature",
  "properties": {
    "addr:full":"11 Pioneer St Essex Junction VT 05452",
    "addr:housenumber":"11",
    "addr:postcode":"05452",
    "addr:street":"Pioneer St",
    "iso:country":"US",
    "sg:address":"11 Pioneer St",
    "sg:city":"Essex Junction",
    "sg:classifiers":[
        {
            "category":"Building & Trades",
            "subcategory":"Construction",
            "type":"Services"
        }
    ],
    "sg:phone":"+1 802 878 2274",
    "sg:postcode":"05452",
    "sg:province":"VT",
    "sg:tags":[
        "roofing",
        "contractor"
    ],
    "wof:name":"Cedar Creek Roofing & Siding",
    "wof:placetype":"venue"
},
  "geometry": {"coordinates":[-73.129424,44.507695],"type":"Point"}
}