{
  "type": "Feature",
  "properties": {
    "addr:full":"306 E Lake Rd Ludlow VT 05149",
    "addr:housenumber":"306",
    "addr:postcode":"05149",
    "addr:street":"E Lake Rd",
    "iso:country":"US",
    "sg:address":"306 E Lake Rd",
    "sg:city":"Ludlow",
    "sg:classifiers":[
        {
            "category":"Wholesale",
            "subcategory":"Farm Supplies",
            "type":"Manufacturing & Wholesale Goods"
        }
    ],
    "sg:phone":"+1 802 228 5453",
    "sg:postcode":"05149",
    "sg:province":"VT",
    "wof:name":"Vermont Wild Roots & Edible",
    "wof:placetype":"venue"
},
  "geometry": {"coordinates":[-72.694316,43.450729],"type":"Point"}
}