{
  "type": "Feature",
  "properties": {
    "addr:full":"150 Flatow Rd Ludlow VT 05149",
    "addr:housenumber":"150",
    "addr:postcode":"05149",
    "addr:street":"Flatow Rd",
    "iso:country":"US",
    "sg:address":"150 Flatow Rd",
    "sg:city":"Ludlow",
    "sg:classifiers":[
        {
            "category":"Retail",
            "subcategory":"Veterinary Services",
            "type":"Services"
        }
    ],
    "sg:phone":"+1 802 228 4765",
    "sg:postcode":"05149",
    "sg:province":"VT",
    "wof:name":"Hadon Veterinary Clinic",
    "wof:placetype":"venue"
},
  "geometry": {"coordinates":[-72.690929,43.352709],"type":"Point"}
}