{
  "type": "Feature",
  "properties": {
    "iso:country":"US",
    "sg:address":"230 College St",
    "sg:city":"Burlington",
    "sg:classifiers":[
        {
            "category":"Professional",
            "type":"Services"
        }
    ],
    "sg:phone":"+1 802 863 7992",
    "sg:postcode":"05401",
    "sg:province":"VT",
    "wof:name":"Burlington Dscver Jazz Fstival",
    "wof:placetype":"venue"
},
  "geometry": {"coordinates":[-73.209417,44.477328],"type":"Point"}
}