{
  "type": "Feature",
  "properties": {
    "iso:country":"US",
    "sg:address":"1564 Valley Rd",
    "sg:city":"Derby Line",
    "sg:classifiers":[
        {
            "category":"Wholesale",
            "subcategory":"Machinery & Supplies",
            "type":"Manufacturing & Wholesale Goods"
        }
    ],
    "sg:phone":"+1 802 895 4159",
    "sg:postcode":"05830",
    "sg:province":"VT",
    "sg:tags":[
        "farm",
        "equipment"
    ],
    "wof:name":"CJM Farm Eq Inc",
    "wof:placetype":"venue"
},
  "geometry": {"coordinates":[-72.027767,44.977486],"type":"Point"}
}