{
  "type": "Feature",
  "properties": {
    "iso:country":"US",
    "sg:address":"536 Woodbury Rd",
    "sg:city":"Springfield",
    "sg:classifiers":[
        {
            "category":"Social Services",
            "subcategory":"Child Care",
            "type":"Services"
        }
    ],
    "sg:phone":"+1 802 885 2020",
    "sg:postcode":"05156",
    "sg:province":"VT",
    "sg:tags":[
        "day"
    ],
    "wof:name":"B&D Day Care For Dogs Inc",
    "wof:placetype":"venue"
},
  "geometry": {"coordinates":[-72.45137200000001,43.311031],"type":"Point"}
}