{
  "type": "Feature",
  "properties": {
    "iso:country":"US",
    "sg:address":"36 Roger St",
    "sg:city":"Winooski",
    "sg:classifiers":[
        {
            "category":"Retail",
            "subcategory":"Laundry & Dry Cleaning",
            "type":"Services"
        }
    ],
    "sg:phone":"+1 802 655 2033",
    "sg:postcode":"05404",
    "sg:province":"VT",
    "sg:tags":[
        "cleaners",
        "rug",
        "carpet"
    ],
    "wof:name":"All Seasons Cleaning Svc",
    "wof:placetype":"venue"
},
  "geometry": {"coordinates":[-73.171701,44.496291],"type":"Point"}
}