{
  "type": "Feature",
  "properties": {
    "iso:country":"US",
    "sg:address":"4973 Main St",
    "sg:city":"Manchester Ctr",
    "sg:classifiers":[
        {
            "category":"Shopping",
            "subcategory":"Clothing, Apparel, & Fashions",
            "type":"Retail Goods"
        }
    ],
    "sg:phone":"+1 802 362 1157",
    "sg:postcode":"05255",
    "sg:province":"VT",
    "sg:tags":[
        "sweater"
    ],
    "wof:name":"Knitty Gritty",
    "wof:placetype":"venue"
},
  "geometry": {"coordinates":[-73.05407700000001,43.177618],"type":"Point"}
}