{
  "type": "Feature",
  "properties": {
    "addr:full":"4161 State Rte 14 Irasburg VT 05845",
    "addr:housenumber":"4161",
    "addr:postcode":"05845",
    "addr:street":"State Rte 14",
    "iso:country":"US",
    "sg:address":"4161 State Rte 14",
    "sg:city":"Irasburg",
    "sg:classifiers":[
        {
            "category":"Retail",
            "subcategory":"Auto Repair",
            "type":"Services"
        }
    ],
    "sg:phone":"+1 802 754 2234",
    "sg:postcode":"05845",
    "sg:province":"VT",
    "sg:tags":[
        "general"
    ],
    "wof:name":"Riverside Garage",
    "wof:placetype":"venue"
},
  "geometry": {"coordinates":[-72.28636,44.808521],"type":"Point"}
}