{
  "type": "Feature",
  "properties": {
    "iso:country":"US",
    "sg:address":"1079 Shattuck Hill Rd",
    "sg:city":"Newport",
    "sg:classifiers":[
        {
            "category":"Real Estate",
            "subcategory":"Real Estate Agent",
            "type":"Services"
        }
    ],
    "sg:phone":"+1 802 334 1838",
    "sg:postcode":"05855",
    "sg:province":"VT",
    "wof:name":"Kingdom Brochure Distribution",
    "wof:placetype":"venue"
},
  "geometry": {"coordinates":[-72.182159,44.953139],"type":"Point"}
}