{
  "type": "Feature",
  "properties": {
    "iso:country":"US",
    "sg:address":"3749 Popple Dungeon Rd",
    "sg:city":"Chester",
    "sg:classifiers":[
        {
            "category":"Manufacturing",
            "subcategory":"Signs",
            "type":"Manufacturing & Wholesale Goods"
        }
    ],
    "sg:phone":"+1 802 875 2308",
    "sg:postcode":"05143",
    "sg:province":"VT",
    "wof:name":"Hastings Signs & Vinyl Graphic",
    "wof:placetype":"venue"
},
  "geometry": {"coordinates":[-72.662519,43.232562],"type":"Point"}
}