{
  "type": "Feature",
  "properties": {
    "iso:country":"US",
    "sg:address":"403 N East Rd",
    "sg:city":"Wallingford",
    "sg:classifiers":[
        {
            "category":"Farming",
            "subcategory":"Fish & Marine Products",
            "type":"Manufacturing & Wholesale Goods"
        }
    ],
    "sg:phone":"+1 802 446 2337",
    "sg:postcode":"05773",
    "sg:province":"VT",
    "sg:tags":[
        "preserves",
        "fishing",
        "hunting"
    ],
    "wof:name":"Tinmouth Hunting Preserve",
    "wof:placetype":"venue"
},
  "geometry": {"coordinates":[-73.018097,43.47548],"type":"Point"}
}