{
  "type": "Feature",
  "properties": {
    "addr:full":"420 Pine St Burlington VT 05401",
    "addr:housenumber":"420",
    "addr:postcode":"05401",
    "addr:street":"Pine St",
    "iso:country":"US",
    "sg:address":"420 Pine St",
    "sg:city":"Burlington",
    "sg:classifiers":[
        {
            "category":"Manufacturing",
            "subcategory":"Printing",
            "type":"Manufacturing & Wholesale Goods"
        }
    ],
    "sg:phone":"+1 802 864 7628",
    "sg:postcode":"05401",
    "sg:province":"VT",
    "sg:tags":[
        "screen"
    ],
    "sg:website":"www.cultureworks.com",
    "wof:name":"Amalgamated Culture Work",
    "wof:placetype":"venue"
},
  "geometry": {"coordinates":[-73.21502599999999,44.468691],"type":"Point"}
}