{
  "type": "Feature",
  "properties": {
    "iso:country":"US",
    "sg:address":"8 Glen Orne Dr",
    "sg:city":"Brattleboro",
    "sg:classifiers":[
        {
            "category":"Transit Center",
            "subcategory":"Freight",
            "type":"Transportation"
        },
        {
            "category":"Freight",
            "type":"Transportation"
        }
    ],
    "sg:phone":"+1 802 257 5124",
    "sg:postcode":"05301",
    "sg:province":"VT",
    "sg:tags":[
        "local",
        "trucking-motor",
        "trucking"
    ],
    "sg:website":"http://www.disilvacompanies.com",
    "wof:name":"Brattleboro Hauling",
    "wof:placetype":"venue"
},
  "geometry": {"coordinates":[-72.544387,42.89368],"type":"Point"}
}