{
  "type": "Feature",
  "properties": {
    "addr:full":"1604 Blakely Rd Colchester VT 05446",
    "addr:housenumber":"1604",
    "addr:postcode":"05446",
    "addr:street":"Blakely Rd",
    "iso:country":"US",
    "sg:address":"1604 Blakely Rd",
    "sg:city":"Colchester",
    "sg:classifiers":[
        {
            "category":"Professional",
            "subcategory":"Business Services",
            "type":"Services"
        }
    ],
    "sg:phone":"+1 802 655 3040",
    "sg:postcode":"05446",
    "sg:province":"VT",
    "wof:name":"Colchester Grange",
    "wof:placetype":"venue"
},
  "geometry": {"coordinates":[-73.19267499999999,44.529856],"type":"Point"}
}