{
  "type": "Feature",
  "properties": {
    "addr:full":"134 Main St Essex Junction VT 05452",
    "addr:housenumber":"134",
    "addr:postcode":"05452",
    "addr:street":"Main St",
    "iso:country":"US",
    "sg:address":"134 Main St",
    "sg:city":"Essex Junction",
    "sg:classifiers":[
        {
            "category":"Communications",
            "subcategory":"Radio Station",
            "type":"Services"
        }
    ],
    "sg:phone":"+1 802 878 8885",
    "sg:postcode":"05452",
    "sg:province":"VT",
    "sg:tags":[
        "company",
        "broadcasting"
    ],
    "wof:name":"CMI Radio Network",
    "wof:placetype":"venue"
},
  "geometry": {"coordinates":[-73.101308,44.496558],"type":"Point"}
}