{
  "type": "Feature",
  "properties": {
    "iso:country":"US",
    "sg:address":"19 North Ave",
    "sg:city":"Newport",
    "sg:classifiers":[
        {
            "category":"Bars & Pubs",
            "type":"Food & Drink"
        }
    ],
    "sg:phone":"+1 802 334 2224",
    "sg:postcode":"05860",
    "sg:province":"VT",
    "wof:name":"Jasper's Tavern",
    "wof:placetype":"venue"
},
  "geometry": {"coordinates":[-72.20495699999999,44.811591],"type":"Point"}
}