{
  "type": "Feature",
  "properties": {
    "iso:country":"US",
    "sg:address":"1257 East Rd",
    "sg:city":"Colchester",
    "sg:classifiers":[
        {
            "category":"Retail",
            "subcategory":"Auto Repair",
            "type":"Services"
        }
    ],
    "sg:phone":"+1 802 872 5710",
    "sg:postcode":"05446",
    "sg:province":"VT",
    "sg:tags":[
        "body"
    ],
    "wof:name":"Lanny Clark Rovers",
    "wof:placetype":"venue"
},
  "geometry": {"coordinates":[-73.126701,44.578978],"type":"Point"}
}