{
  "type": "Feature",
  "properties": {
    "addr:full":"1566 Center Fayston Rd Moretown VT 05660",
    "addr:housenumber":"1566",
    "addr:postcode":"05660",
    "addr:street":"Center Fayston Rd",
    "iso:country":"US",
    "sg:address":"1566 Center Fayston Rd",
    "sg:city":"Moretown",
    "sg:classifiers":[
        {
            "category":"Retail",
            "subcategory":"Repair Shop",
            "type":"Services"
        }
    ],
    "sg:phone":"+1 802 496 2100",
    "sg:postcode":"05660",
    "sg:province":"VT",
    "sg:tags":[
        "appliance"
    ],
    "wof:name":"To 100 Appliance Repair",
    "wof:placetype":"venue"
},
  "geometry": {"coordinates":[-72.835067,44.216231],"type":"Point"}
}