{
  "type": "Feature",
  "properties": {
    "addr:full":"364 Railroad St Saint Johnsbury VT 05819",
    "addr:housenumber":"364",
    "addr:postcode":"05819",
    "addr:street":"Railroad St",
    "iso:country":"US",
    "sg:address":"364 Railroad St",
    "sg:city":"Saint Johnsbury",
    "sg:classifiers":[
        {
            "category":"Government",
            "subcategory":"Court House",
            "type":"Public Place"
        }
    ],
    "sg:phone":"+1 802 748 5176",
    "sg:postcode":"05819",
    "sg:province":"VT",
    "sg:tags":[
        "defender"
    ],
    "wof:name":"Caledonia County District Off",
    "wof:placetype":"venue"
},
  "geometry": {"coordinates":[-72.01568,44.418628],"type":"Point"}
}