{
  "type": "Feature",
  "properties": {
    "addr:full":"256 Grove St Brandon VT 05733",
    "addr:housenumber":"256",
    "addr:postcode":"05733",
    "addr:street":"Grove St",
    "iso:country":"US",
    "sg:address":"256 Grove St",
    "sg:city":"Brandon",
    "sg:classifiers":[
        {
            "category":"Wholesale",
            "subcategory":"Motor Vehicles",
            "type":"Manufacturing & Wholesale Goods"
        }
    ],
    "sg:phone":"+1 802 247 8286",
    "sg:postcode":"05733",
    "sg:province":"VT",
    "sg:tags":[
        "automobile",
        "used"
    ],
    "wof:name":"Brandon Auto Sales Inc",
    "wof:placetype":"venue"
},
  "geometry": {"coordinates":[-73.098826,43.805663],"type":"Point"}
}