{
  "type": "Feature",
  "properties": {
    "iso:country":"US",
    "sg:address":"1001 Pidgeon Hill Rd",
    "sg:city":"Franklin",
    "sg:classifiers":[
        {
            "category":"Professional",
            "type":"Services"
        }
    ],
    "sg:phone":"+1 802 285 6752",
    "sg:postcode":"05457",
    "sg:province":"VT",
    "sg:tags":[
        "establishment"
    ],
    "wof:name":"Borderview Farm",
    "wof:placetype":"venue"
},
  "geometry": {"coordinates":[-72.93043900000001,45.010739],"type":"Point"}
}