{
  "type": "Feature",
  "properties": {
    "iso:country":"US",
    "sg:address":"12 Central St",
    "sg:city":"Essex Junction",
    "sg:classifiers":[
        {
            "category":"Organizations",
            "subcategory":"Religious Organization",
            "type":"Services"
        }
    ],
    "sg:phone":"+1 802 879 4259",
    "sg:postcode":"05452",
    "sg:province":"VT",
    "wof:name":"Hero Worship Comics",
    "wof:placetype":"venue"
},
  "geometry": {"coordinates":[-73.108233,44.493534],"type":"Point"}
}