{
  "type": "Feature",
  "properties": {
    "iso:country":"US",
    "sg:address":"52 State St",
    "sg:city":"Montpelier",
    "sg:classifiers":[
        {
            "category":"Professional",
            "subcategory":"Lawyer & Legal Services",
            "type":"Services"
        }
    ],
    "sg:phone":"+1 802 225 5500",
    "sg:postcode":"05602",
    "sg:province":"VT",
    "sg:tags":[
        "attorney"
    ],
    "wof:name":"Downs Rachlin Martin Attys",
    "wof:placetype":"venue"
},
  "geometry": {"coordinates":[-72.57689999999999,44.260339],"type":"Point"}
}