{
  "type": "Feature",
  "properties": {
    "iso:country":"US",
    "sg:address":"51 Jalbert Rd",
    "sg:city":"Barre",
    "sg:classifiers":[
        {
            "category":"Shopping",
            "subcategory":"Catalog Store",
            "type":"Retail Goods"
        }
    ],
    "sg:phone":"+1 802 479 2024",
    "sg:postcode":"05641",
    "sg:province":"VT",
    "sg:tags":[
        "house",
        "mail"
    ],
    "wof:name":"Christmas In Vermont",
    "wof:placetype":"venue"
},
  "geometry": {"coordinates":[-72.444782,44.190036],"type":"Point"}
}