{
  "type": "Feature",
  "properties": {
    "iso:country":"US",
    "sg:address":"878 Royalton Tpke",
    "sg:city":"South Royalton",
    "sg:classifiers":[
        {
            "category":"Home & Garden",
            "subcategory":"Garden Supply",
            "type":"Retail Goods"
        }
    ],
    "sg:phone":"+1 802 763 3907",
    "sg:postcode":"05068",
    "sg:province":"VT",
    "wof:name":"Riverbend Garden Center",
    "wof:placetype":"venue"
},
  "geometry": {"coordinates":[-72.58999,43.729691],"type":"Point"}
}