{
  "type": "Feature",
  "properties": {
    "iso:country":"US",
    "sg:address":"27 Main St",
    "sg:city":"Saxtons River",
    "sg:classifiers":[
        {
            "category":"Travel",
            "subcategory":"Hotels & Motels",
            "type":"Entertainment"
        }
    ],
    "sg:phone":"+1 802 869 2110",
    "sg:postcode":"05154",
    "sg:province":"VT",
    "sg:tags":[
        "inn"
    ],
    "sg:website":"www.innsaxtonsriver.com",
    "wof:name":"Inn At Saxtons River",
    "wof:placetype":"venue"
},
  "geometry": {"coordinates":[-72.507195,43.138703],"type":"Point"}
}