{
  "type": "Feature",
  "properties": {
    "addr:full":"1193 Portland St Saint Johnsbury VT 05819",
    "addr:housenumber":"1193",
    "addr:postcode":"05819",
    "addr:street":"Portland St",
    "iso:country":"US",
    "sg:address":"1193 Portland St",
    "sg:city":"Saint Johnsbury",
    "sg:classifiers":[
        {
            "category":"Professional",
            "subcategory":"Management & Consulting",
            "type":"Services"
        }
    ],
    "sg:phone":"+1 802 748 3636",
    "sg:postcode":"05819",
    "sg:province":"VT",
    "sg:tags":[
        "business"
    ],
    "wof:name":"Express Fleet Service Inc",
    "wof:placetype":"venue"
},
  "geometry": {"coordinates":[-71.99225800000001,44.421561],"type":"Point"}
}