{
  "type": "Feature",
  "properties": {
    "iso:country":"US",
    "sg:address":"120 N Main St",
    "sg:city":"St Albans",
    "sg:classifiers":[
        {
            "category":"Banks & Credit Unions",
            "subcategory":"Bank",
            "type":"Services"
        }
    ],
    "sg:phone":"+1 802 524 9000",
    "sg:postcode":"05478",
    "sg:province":"VT",
    "wof:name":"Union Bank",
    "wof:placetype":"venue"
},
  "geometry": {"coordinates":[-73.08293399999999,44.813946],"type":"Point"}
}