{
  "type": "Feature",
  "properties": {
    "addr:full":"215 College St Burlington VT 05401",
    "addr:housenumber":"215",
    "addr:postcode":"05401",
    "addr:street":"College St",
    "iso:country":"US",
    "sg:address":"215 College St",
    "sg:city":"Burlington",
    "sg:classifiers":[
        {
            "category":"Professional",
            "subcategory":"Business Services",
            "type":"Services"
        }
    ],
    "sg:phone":"+1 802 865 1140",
    "sg:postcode":"05401",
    "sg:province":"VT",
    "sg:tags":[
        "recording",
        "studio"
    ],
    "sg:website":"www.thebookingagency.com",
    "wof:name":"Big Heavy World",
    "wof:placetype":"venue"
},
  "geometry": {"coordinates":[-73.21127,44.477071],"type":"Point"}
}