{
  "type": "Feature",
  "properties": {
    "iso:country":"US",
    "sg:address":"181 Main St",
    "sg:city":"Newport",
    "sg:classifiers":[
        {
            "category":"Shopping",
            "subcategory":"Jewelry",
            "type":"Retail Goods"
        }
    ],
    "sg:phone":"+1 802 334 2930",
    "sg:postcode":"05825",
    "sg:province":"VT",
    "sg:tags":[
        "jeweler"
    ],
    "wof:name":"Myers' Jewelry Store",
    "wof:placetype":"venue"
},
  "geometry": {"coordinates":[-72.263634,44.867072],"type":"Point"}
}