{
  "type": "Feature",
  "properties": {
    "iso:country":"US",
    "sg:address":"85 S Park Dr",
    "sg:city":"Colchester",
    "sg:classifiers":[
        {
            "category":"Restaurant",
            "type":"Food & Drink"
        }
    ],
    "sg:menulink":"http://www.allmenus.com/vt/colchester/246077-juniors-italian/menu/",
    "sg:phone":"+1 802 655 5555",
    "sg:postcode":"05446",
    "sg:province":"VT",
    "sg:tags":[
        "italian"
    ],
    "wof:name":"Junior's Italian ",
    "wof:placetype":"venue"
},
  "geometry": {"coordinates":[-73.180476,44.503839],"type":"Point"}
}