{
  "type": "Feature",
  "properties": {
    "addr:full":"125 College St Burlington VT 05401",
    "addr:housenumber":"125",
    "addr:postcode":"05401",
    "addr:street":"College St",
    "iso:country":"US",
    "sg:address":"125 College St",
    "sg:city":"Burlington",
    "sg:classifiers":[
        {
            "category":"Professional",
            "subcategory":"Lawyer & Legal Services",
            "type":"Services"
        }
    ],
    "sg:phone":"+1 802 864 3120",
    "sg:postcode":"05401",
    "sg:province":"VT",
    "sg:tags":[
        "attorney"
    ],
    "sg:website":"www.schoenberglegal.com",
    "wof:name":"Schoenberg & Associates",
    "wof:placetype":"venue"
},
  "geometry": {"coordinates":[-73.21469500000001,44.476923],"type":"Point"}
}