{
  "type": "Feature",
  "properties": {
    "iso:country":"US",
    "sg:address":"28 Main St",
    "sg:city":"Montpelier",
    "sg:classifiers":[
        {
            "category":"Restaurant",
            "type":"Food & Drink"
        }
    ],
    "sg:phone":"+1 802 229 6112",
    "sg:postcode":"05602",
    "sg:province":"VT",
    "wof:name":"Rhapsody",
    "wof:placetype":"venue"
},
  "geometry": {"coordinates":[-72.57646800000001,44.258922],"type":"Point"}
}