{
  "type": "Feature",
  "properties": {
    "iso:country":"US",
    "sg:address":"390 S Prospect St",
    "sg:city":"Burlington",
    "sg:classifiers":[
        {
            "category":"Organizations",
            "subcategory":"Religious Organization",
            "type":"Services"
        }
    ],
    "sg:phone":"+1 802 862 8403",
    "sg:postcode":"05401",
    "sg:province":"VT",
    "wof:name":"Catholic Center At UVM",
    "wof:placetype":"venue"
},
  "geometry": {"coordinates":[-73.200379,44.469209],"type":"Point"}
}