{
  "type": "Feature",
  "properties": {
    "addr:full":"4 Laurette Dr Essex Junction VT 05446",
    "addr:housenumber":"4",
    "addr:postcode":"05446",
    "addr:street":"Laurette Dr",
    "iso:country":"US",
    "sg:address":"4 Laurette Dr",
    "sg:city":"Essex Junction",
    "sg:classifiers":[
        {
            "category":"Manufacturing",
            "subcategory":"Furniture",
            "type":"Manufacturing & Wholesale Goods"
        }
    ],
    "sg:phone":"+1 802 655 7777",
    "sg:postcode":"05446",
    "sg:province":"VT",
    "sg:tags":[
        "mfg",
        "mill",
        "drape",
        "fabric",
        "cotton"
    ],
    "wof:name":"Gordons Window Decor Centl V T",
    "wof:placetype":"venue"
},
  "geometry": {"coordinates":[-73.140968,44.50444],"type":"Point"}
}