{
  "type": "Feature",
  "properties": {
    "iso:country":"US",
    "sg:address":"1 W Seminary St",
    "sg:city":"Brandon",
    "sg:classifiers":[
        {
            "category":"Government",
            "subcategory":"Police Station",
            "type":"Public Place"
        }
    ],
    "sg:phone":"+1 802 247 0222",
    "sg:postcode":"05733",
    "sg:province":"VT",
    "sg:tags":[
        "grocery",
        "protection"
    ],
    "wof:name":"Brandon Police Dept",
    "wof:placetype":"venue"
},
  "geometry": {"coordinates":[-73.08814700000001,43.800571],"type":"Point"}
}