{
  "type": "Feature",
  "properties": {
    "addr:full":"21 Main St Chester VT 05143",
    "addr:housenumber":"21",
    "addr:postcode":"05143",
    "addr:street":"Main St",
    "iso:country":"US",
    "sg:address":"21 Main St",
    "sg:city":"Chester",
    "sg:classifiers":[
        {
            "category":"Home & Garden",
            "subcategory":"Hardware",
            "type":"Retail Goods"
        }
    ],
    "sg:phone":"+1 802 875 2693",
    "sg:postcode":"05143",
    "sg:province":"VT",
    "wof:name":"Chester Hardware True Value",
    "wof:placetype":"venue"
},
  "geometry": {"coordinates":[-72.59734,43.263874],"type":"Point"}
}