{
  "type": "Feature",
  "properties": {
    "iso:country":"US",
    "sg:address":"38 Union St",
    "sg:city":"Brandon",
    "sg:classifiers":[
        {
            "category":"Manufacturing",
            "subcategory":"Pet Food",
            "type":"Manufacturing & Wholesale Goods"
        }
    ],
    "sg:phone":"+1 802 247 3731",
    "sg:postcode":"05733",
    "sg:province":"VT",
    "sg:tags":[
        "feed"
    ],
    "wof:name":"Blue Seal Feeds & Needs",
    "wof:placetype":"venue"
},
  "geometry": {"coordinates":[-73.088545,43.795071],"type":"Point"}
}