{
  "type": "Feature",
  "properties": {
    "iso:country":"US",
    "sg:address":"177 Elm Hill St",
    "sg:city":"Springfield",
    "sg:classifiers":[
        {
            "category":"Personal",
            "type":"Services"
        }
    ],
    "sg:phone":"+1 802 345 0661",
    "sg:postcode":"05156",
    "sg:province":"VT",
    "wof:name":"Mountain Valet Inc",
    "wof:placetype":"venue"
},
  "geometry": {"coordinates":[-72.48152399999999,43.307186],"type":"Point"}
}