{
  "type": "Feature",
  "properties": {
    "iso:country":"US",
    "sg:address":"26 Summit Pl",
    "sg:city":"Saint Albans",
    "sg:classifiers":[
        {
            "category":"Retail",
            "subcategory":"Auto Repair",
            "type":"Services"
        }
    ],
    "sg:phone":"+1 802 527 0896",
    "sg:postcode":"05478",
    "sg:province":"VT",
    "sg:tags":[
        "automotive"
    ],
    "wof:name":"Dent Doctor Inc",
    "wof:placetype":"venue"
},
  "geometry": {"coordinates":[-73.073787,44.826236],"type":"Point"}
}