{
  "type": "Feature",
  "properties": {
    "iso:country":"US",
    "sg:address":"595 Dorset St",
    "sg:city":"South Burlington",
    "sg:classifiers":[
        {
            "category":"Professional",
            "subcategory":"Engineering",
            "type":"Services"
        }
    ],
    "sg:phone":"+1 802 660 9212",
    "sg:postcode":"05403",
    "sg:province":"VT",
    "sg:tags":[
        "engineer"
    ],
    "wof:name":"Doherty & Co",
    "wof:placetype":"venue"
},
  "geometry": {"coordinates":[-73.18053,44.461969],"type":"Point"}
}