{
  "type": "Feature",
  "properties": {
    "iso:country":"US",
    "sg:address":"12 Dorr Dr",
    "sg:city":"Rutland",
    "sg:classifiers":[
        {
            "category":"Restaurant",
            "type":"Food & Drink"
        }
    ],
    "sg:phone":"+1 802 422 3293",
    "sg:postcode":"05701",
    "sg:province":"VT",
    "sg:tags":[
        "italian"
    ],
    "wof:name":"Peppinos Inc",
    "wof:placetype":"venue"
},
  "geometry": {"coordinates":[-73.001553,43.602086],"type":"Point"}
}