{
  "type": "Feature",
  "properties": {
    "addr:full":"43 Harrison Dr Ludlow VT 05158",
    "addr:housenumber":"43",
    "addr:postcode":"05158",
    "addr:street":"Harrison Dr",
    "iso:country":"US",
    "sg:address":"43 Harrison Dr",
    "sg:city":"Ludlow",
    "sg:classifiers":[
        {
            "category":"Real Estate",
            "subcategory":"Real Estate Agent",
            "type":"Services"
        }
    ],
    "sg:phone":"+1 802 228 4934",
    "sg:postcode":"05158",
    "sg:province":"VT",
    "wof:name":"Winterplace Administration Ofc",
    "wof:placetype":"venue"
},
  "geometry": {"coordinates":[-72.464152,43.063044],"type":"Point"}
}