{
  "type": "Feature",
  "properties": {
    "addr:full":"2090 New Boston Rd Saint Johnsbury VT 05819",
    "addr:housenumber":"2090",
    "addr:postcode":"05819",
    "addr:street":"New Boston Rd",
    "iso:country":"US",
    "sg:address":"2090 New Boston Rd",
    "sg:city":"Saint Johnsbury",
    "sg:classifiers":[
        {
            "category":"Professional",
            "subcategory":"Engineering",
            "type":"Services"
        }
    ],
    "sg:phone":"+1 802 748 0115",
    "sg:postcode":"05819",
    "sg:province":"VT",
    "sg:tags":[
        "consultant",
        "construction"
    ],
    "wof:name":"Nationwide Cnstr Cnsulting LLC",
    "wof:placetype":"venue"
},
  "geometry": {"coordinates":[-71.99676100000001,44.491324],"type":"Point"}
}