{
  "type": "Feature",
  "properties": {
    "iso:country":"US",
    "sg:address":"296 Pleasant St",
    "sg:city":"Island Pond",
    "sg:classifiers":[
        {
            "category":"Manufacturing",
            "subcategory":"Textiles",
            "type":"Manufacturing & Wholesale Goods"
        }
    ],
    "sg:phone":"+1 802 723 4203",
    "sg:postcode":"05846",
    "sg:province":"VT",
    "wof:name":"Geotex Fabricators",
    "wof:placetype":"venue"
},
  "geometry": {"coordinates":[-71.881686,44.807193],"type":"Point"}
}