{
  "type": "Feature",
  "properties": {
    "iso:country":"US",
    "sg:address":"26 Vale Dr",
    "sg:city":"South Burlington",
    "sg:classifiers":[
        {
            "category":"Health Services",
            "subcategory":"Optometrist",
            "type":"Services"
        }
    ],
    "sg:phone":"+1 802 658 4598",
    "sg:postcode":"05403",
    "sg:province":"VT",
    "wof:name":"Dora Sudarsky Od",
    "wof:placetype":"venue"
},
  "geometry": {"coordinates":[-73.18638300000001,44.435157],"type":"Point"}
}