{
  "type": "Feature",
  "properties": {
    "addr:full":"275 College St Burlington VT 05401",
    "addr:housenumber":"275",
    "addr:postcode":"05401",
    "addr:street":"College St",
    "iso:country":"US",
    "sg:address":"275 College St",
    "sg:city":"Burlington",
    "sg:classifiers":[
        {
            "category":"Professional",
            "subcategory":"Lawyer & Legal Services",
            "type":"Services"
        }
    ],
    "sg:phone":"+1 802 861 7000",
    "sg:postcode":"05401",
    "sg:province":"VT",
    "wof:name":"Murphy Liam Esq",
    "wof:placetype":"venue"
},
  "geometry": {"coordinates":[-73.207232,44.477328],"type":"Point"}
}