{
  "type": "Feature",
  "properties": {
    "addr:full":"301 S Main St Richford VT 05476",
    "addr:housenumber":"301",
    "addr:postcode":"05476",
    "addr:street":"S Main St",
    "iso:country":"US",
    "sg:address":"301 S Main St",
    "sg:city":"Richford",
    "sg:classifiers":[
        {
            "category":"Food & Beverages",
            "subcategory":"Groceries & Convenience Stores",
            "type":"Retail Goods"
        }
    ],
    "sg:phone":"+1 802 848 7800",
    "sg:postcode":"05476",
    "sg:province":"VT",
    "wof:name":"South Main Quick Stop",
    "wof:placetype":"venue"
},
  "geometry": {"coordinates":[-72.675797,44.989572],"type":"Point"}
}