{
  "type": "Feature",
  "properties": {
    "addr:full":"1437 Royalton Tpke South Royalton VT 05068",
    "addr:housenumber":"1437",
    "addr:postcode":"05068",
    "addr:street":"Royalton Tpke South",
    "iso:country":"US",
    "sg:address":"1437 Royalton Tpke",
    "sg:city":"South Royalton",
    "sg:classifiers":[
        {
            "category":"Building & Trades",
            "subcategory":"Construction",
            "type":"Services"
        }
    ],
    "sg:phone":"+1 802 763 7868",
    "sg:postcode":"05068",
    "sg:province":"VT",
    "sg:tags":[
        "excavation",
        "excavating",
        "contractor"
    ],
    "wof:name":"Lamson Gregory & Shop",
    "wof:placetype":"venue"
},
  "geometry": {"coordinates":[-72.59054399999999,43.736611],"type":"Point"}
}