{
  "type": "Feature",
  "properties": {
    "iso:country":"US",
    "sg:address":"996 Main St",
    "sg:city":"Fairfax",
    "sg:classifiers":[
        {
            "category":"Farming",
            "subcategory":"Dairy Farm",
            "type":"Manufacturing & Wholesale Goods"
        }
    ],
    "sg:phone":"+1 802 849 6589",
    "sg:postcode":"05454",
    "sg:province":"VT",
    "wof:name":"Ralph McNall",
    "wof:placetype":"venue"
},
  "geometry": {"coordinates":[-73.009276,44.655909],"type":"Point"}
}