{
  "type": "Feature",
  "properties": {
    "iso:country":"US",
    "sg:address":"115 Ferry Rd",
    "sg:city":"Charlotte",
    "sg:classifiers":[
        {
            "category":"Education",
            "subcategory":"Library",
            "type":"Public Place"
        }
    ],
    "sg:phone":"+1 802 425 3864",
    "sg:postcode":"05445",
    "sg:province":"VT",
    "wof:name":"Charlotte Community Library",
    "wof:placetype":"venue"
},
  "geometry": {"coordinates":[-73.248985,44.310999],"type":"Point"}
}