{
  "type": "Feature",
  "properties": {
    "iso:country":"US",
    "sg:address":"148 Channel Rd",
    "sg:city":"Wallingford",
    "sg:phone":"+1 802 446 2812",
    "sg:postcode":"05773",
    "sg:province":"VT",
    "sg:tags":[
        "farm",
        "herb"
    ],
    "wof:name":"Tinmouth Channel Farm",
    "wof:placetype":"venue"
},
  "geometry": {"coordinates":[-73.043995,43.440981],"type":"Point"}
}