{
  "type": "Feature",
  "properties": {
    "iso:country":"US",
    "sg:address":"314 Royalton Tpke",
    "sg:city":"South Royalton",
    "sg:classifiers":[
        {
            "category":"Social Services",
            "subcategory":"Child Care",
            "type":"Services"
        }
    ],
    "sg:phone":"+1 802 763 7908",
    "sg:postcode":"05068",
    "sg:province":"VT",
    "wof:name":"Magic Mountain Day Care Ctr",
    "wof:placetype":"venue"
},
  "geometry": {"coordinates":[-72.59092099999999,43.724327],"type":"Point"}
}