{
  "type": "Feature",
  "properties": {
    "iso:country":"US",
    "sg:address":"3519 Belvidere Rd",
    "sg:city":"Eden",
    "sg:classifiers":[
        {
            "category":"Shopping",
            "subcategory":"Bicycles & Sporting Goods",
            "type":"Retail Goods"
        }
    ],
    "sg:phone":"+1 802 635 7734",
    "sg:postcode":"05652",
    "sg:province":"VT",
    "sg:tags":[
        "gun",
        "gunsmith"
    ],
    "wof:name":"Moose Crossing Gun Shop",
    "wof:placetype":"venue"
},
  "geometry": {"coordinates":[-72.579294,44.754899],"type":"Point"}
}