{
  "type": "Feature",
  "properties": {
    "iso:country":"US",
    "sg:address":"14 Wenonah Ave",
    "sg:city":"Essex Junction",
    "sg:classifiers":[
        {
            "category":"Retail",
            "subcategory":"Portrait Studio",
            "type":"Services"
        }
    ],
    "sg:phone":"+1 802 878 5092",
    "sg:postcode":"05452",
    "sg:province":"VT",
    "sg:tags":[
        "photo"
    ],
    "wof:name":"Vermont Splendor",
    "wof:placetype":"venue"
},
  "geometry": {"coordinates":[-73.12785700000001,44.491291],"type":"Point"}
}