{
  "type": "Feature",
  "properties": {
    "addr:full":"127 College Rd Lyndon Center VT 05850",
    "addr:housenumber":"127",
    "addr:postcode":"05850",
    "addr:street":"College Rd",
    "iso:country":"US",
    "sg:address":"127 College Rd",
    "sg:city":"Lyndon Center",
    "sg:classifiers":[
        {
            "category":"Education",
            "subcategory":"School",
            "type":"Public Place"
        }
    ],
    "sg:phone":"+1 802 626 3357",
    "sg:postcode":"05850",
    "sg:province":"VT",
    "sg:website":"www.lyndoninstitute.org",
    "wof:name":"Lyndon Institute Inc",
    "wof:placetype":"venue"
},
  "geometry": {"coordinates":[-72.013544,44.537415],"type":"Point"}
}