{
  "type": "Feature",
  "properties": {
    "iso:country":"US",
    "sg:address":"151 Gore Rd",
    "sg:city":"Highgate Center",
    "sg:classifiers":[
        {
            "category":"Real Estate",
            "subcategory":"Real Estate Agent",
            "type":"Services"
        }
    ],
    "sg:phone":"+1 802 868 3558",
    "sg:postcode":"05459",
    "sg:province":"VT",
    "wof:name":"Boudreau Real Estate",
    "wof:placetype":"venue"
},
  "geometry": {"coordinates":[-73.041883,44.942017],"type":"Point"}
}