{
  "type": "Feature",
  "properties": {
    "addr:full":"76 Andover St Ludlow VT 05149",
    "addr:housenumber":"76",
    "addr:postcode":"05149",
    "addr:street":"Andover St",
    "iso:country":"US",
    "sg:address":"76 Andover St",
    "sg:city":"Ludlow",
    "sg:classifiers":[
        {
            "category":"Home & Garden",
            "subcategory":"Carpets & Floor Coverings",
            "type":"Retail Goods"
        }
    ],
    "sg:phone":"+1 802 228 5750",
    "sg:postcode":"05149",
    "sg:province":"VT",
    "wof:name":"Okemo Valley Carpet",
    "wof:placetype":"venue"
},
  "geometry": {"coordinates":[-72.708777,43.389],"type":"Point"}
}