{
  "type": "Feature",
  "properties": {
    "iso:country":"US",
    "sg:address":"50 Catella Rd",
    "sg:city":"Essex Junction",
    "sg:classifiers":[
        {
            "category":"Building & Trades",
            "subcategory":"Plumbing",
            "type":"Services"
        }
    ],
    "sg:phone":"+1 802 872 8961",
    "sg:postcode":"05452",
    "sg:province":"VT",
    "sg:tags":[
        "contractor"
    ],
    "wof:name":"Stiched On Time (llc)",
    "wof:placetype":"venue"
},
  "geometry": {"coordinates":[-73.01755199999999,44.538066],"type":"Point"}
}