{
  "type": "Feature",
  "properties": {
    "addr:full":"114 River St Montpelier VT 05602",
    "addr:housenumber":"114",
    "addr:postcode":"05602",
    "addr:street":"River St",
    "iso:country":"US",
    "sg:address":"114 River St",
    "sg:city":"Montpelier",
    "sg:classifiers":[
        {
            "category":"Recreation",
            "type":"Entertainment"
        }
    ],
    "sg:phone":"+1 802 223 1405",
    "sg:postcode":"05602",
    "sg:province":"VT",
    "sg:tags":[
        "martial",
        "arts",
        "instruction"
    ],
    "wof:name":"Gentle Dragon Taekwondo",
    "wof:placetype":"venue"
},
  "geometry": {"coordinates":[-72.56283999999999,44.248979],"type":"Point"}
}