{
  "type": "Feature",
  "properties": {
    "addr:full":"28 Catherine St St Albans VT 05478",
    "addr:housenumber":"28",
    "addr:postcode":"05478",
    "addr:street":"Catherine St",
    "iso:country":"US",
    "sg:address":"28 Catherine St",
    "sg:city":"St Albans",
    "sg:classifiers":[
        {
            "category":"Education",
            "subcategory":"School",
            "type":"Public Place"
        }
    ],
    "sg:phone":"+1 802 524 1544",
    "sg:postcode":"05478",
    "sg:province":"VT",
    "wof:name":"Migrant Education Program",
    "wof:placetype":"venue"
},
  "geometry": {"coordinates":[-73.085778,44.810467],"type":"Point"}
}