{
  "type": "Feature",
  "properties": {
    "iso:country":"US",
    "sg:address":"80 Marble St",
    "sg:city":"West Rutland",
    "sg:classifiers":[
        {
            "category":"Professional",
            "type":"Services"
        }
    ],
    "sg:phone":"+1 802 438 5212",
    "sg:postcode":"05777",
    "sg:province":"VT",
    "sg:tags":[
        "sculptor"
    ],
    "wof:name":"Campbell Plaster & Iron",
    "wof:placetype":"venue"
},
  "geometry": {"coordinates":[-73.04888699999999,43.596544],"type":"Point"}
}