{
  "type": "Feature",
  "properties": {
    "iso:country":"US",
    "sg:address":"54 Main St",
    "sg:city":"Montpelier",
    "sg:classifiers":[
        {
            "category":"Shopping",
            "subcategory":"Stationery & Office Supplies",
            "type":"Retail Goods"
        }
    ],
    "sg:phone":"+1 802 223 2393",
    "sg:postcode":"05602",
    "sg:province":"VT",
    "sg:tags":[
        "cards",
        "book",
        "greeting"
    ],
    "wof:name":"Capitol Stationers Inc",
    "wof:placetype":"venue"
},
  "geometry": {"coordinates":[-72.57612899999999,44.259212],"type":"Point"}
}