{
  "type": "Feature",
  "properties": {
    "addr:full":"103 S Main St Waterbury VT 05676",
    "addr:housenumber":"103",
    "addr:postcode":"05676",
    "addr:street":"S Main St",
    "iso:country":"US",
    "sg:address":"103 S Main St",
    "sg:city":"Waterbury",
    "sg:classifiers":[
        {
            "category":"Government",
            "subcategory":"Police Station",
            "type":"Public Place"
        }
    ],
    "sg:phone":"+1 802 244 6941",
    "sg:postcode":"05676",
    "sg:province":"VT",
    "sg:tags":[
        "state"
    ],
    "wof:name":"Department Of Public Safety",
    "wof:placetype":"venue"
},
  "geometry": {"coordinates":[-72.750687,44.332037],"type":"Point"}
}