{
  "type": "Feature",
  "properties": {
    "iso:country":"US",
    "sg:address":"1733 Case St",
    "sg:city":"Middlebury",
    "sg:classifiers":[
        {
            "category":"Food & Beverages",
            "subcategory":"Fruits & Vegetables",
            "type":"Retail Goods"
        }
    ],
    "sg:phone":"+1 802 388 9411",
    "sg:postcode":"05753",
    "sg:province":"VT",
    "sg:tags":[
        "produce"
    ],
    "wof:name":"Marble Rose Farm",
    "wof:placetype":"venue"
},
  "geometry": {"coordinates":[-73.105013,43.993685],"type":"Point"}
}