{
  "type": "Feature",
  "properties": {
    "addr:full":"81 State Rte 7b North Clarendon VT 05759",
    "addr:housenumber":"81",
    "addr:postcode":"05759",
    "addr:street":"State Rte 7B North",
    "iso:country":"US",
    "sg:address":"81 State Rte 7b",
    "sg:city":"North Clarendon",
    "sg:classifiers":[
        {
            "category":"Retail",
            "subcategory":"Auto Rental",
            "type":"Services"
        }
    ],
    "sg:phone":"+1 802 775 7735",
    "sg:postcode":"05759",
    "sg:province":"VT",
    "sg:tags":[
        "truck",
        "trailer",
        "utility"
    ],
    "wof:name":"U-Haul",
    "wof:placetype":"venue"
},
  "geometry": {"coordinates":[-72.932693,43.527834],"type":"Point"}
}