{
  "type": "Feature",
  "properties": {
    "iso:country":"US",
    "sg:address":"155 Osgood Hill Rd",
    "sg:city":"Essex Junction",
    "sg:classifiers":[
        {
            "category":"Retail",
            "subcategory":"Veterinary Services",
            "type":"Services"
        }
    ],
    "sg:phone":"+1 802 872 0730",
    "sg:postcode":"05452",
    "sg:province":"VT",
    "sg:tags":[
        "veterinarian"
    ],
    "wof:name":"Animal Housecalls",
    "wof:placetype":"venue"
},
  "geometry": {"coordinates":[-73.005117,44.554028],"type":"Point"}
}