{
  "type": "Feature",
  "properties": {
    "iso:country":"US",
    "sg:address":"9 Spencer Dr",
    "sg:city":"Bellows Falls",
    "sg:classifiers":[
        {
            "category":"Manufacturing",
            "subcategory":"Tools & Machinery",
            "type":"Manufacturing & Wholesale Goods"
        }
    ],
    "sg:phone":"+1 802 463 3927",
    "sg:postcode":"05101",
    "sg:province":"VT",
    "sg:tags":[
        "machine",
        "shop"
    ],
    "wof:name":"Mach Chamberlain Inc",
    "wof:placetype":"venue"
},
  "geometry": {"coordinates":[-72.455037,43.168855],"type":"Point"}
}