{
  "type": "Feature",
  "properties": {
    "iso:country":"US",
    "sg:address":"112 Northgate Rd",
    "sg:city":"Burlington",
    "sg:classifiers":[
        {
            "category":"Organizations",
            "subcategory":"Religious Organization",
            "type":"Services"
        }
    ],
    "sg:phone":"+1 802 651 9493",
    "sg:postcode":"05408",
    "sg:province":"VT",
    "wof:name":"Burlington Street Ministries",
    "wof:placetype":"venue"
},
  "geometry": {"coordinates":[-72.592493,44.572189],"type":"Point"}
}