{
  "type": "Feature",
  "properties": {
    "addr:full":"30 Susie Wilson Rd Essex Junction VT 05452",
    "addr:housenumber":"30",
    "addr:postcode":"05452",
    "addr:street":"Susie Wilson Rd",
    "iso:country":"US",
    "sg:address":"30 Susie Wilson Rd",
    "sg:city":"Essex Junction",
    "sg:classifiers":[
        {
            "category":"Retail",
            "subcategory":"Laundry & Dry Cleaning",
            "type":"Services"
        }
    ],
    "sg:phone":"+1 802 872 0193",
    "sg:postcode":"05452",
    "sg:province":"VT",
    "sg:tags":[
        "cleaners"
    ],
    "wof:name":"Mountain Air Cleaners Inc",
    "wof:placetype":"venue"
},
  "geometry": {"coordinates":[-73.134471,44.507348],"type":"Point"}
}