{
  "type": "Feature",
  "properties": {
    "addr:full":"170 S Main St Ste 5 Rutland VT 05701",
    "addr:housenumber":"170;5",
    "addr:postcode":"05701",
    "addr:street":"S Main St Ste",
    "iso:country":"US",
    "sg:address":"170 S Main St Ste 5",
    "sg:city":"Rutland",
    "sg:classifiers":[
        {
            "category":"Wholesale",
            "subcategory":"Non-durable Goods",
            "type":"Manufacturing & Wholesale Goods"
        },
        {
            "category":"Shopping",
            "subcategory":"Beauty & Cosmetics",
            "type":"Retail Goods"
        },
        {
            "category":"Personal",
            "subcategory":"Barber",
            "type":"Services"
        }
    ],
    "sg:phone":"+1 802 773 2128",
    "sg:postcode":"05701",
    "sg:province":"VT",
    "sg:tags":[
        "equipment",
        "manufacturer",
        "supplies-wholesale",
        "salons-equipment",
        "supply"
    ],
    "wof:name":"Cb Sullivan Co Inc",
    "wof:placetype":"venue"
},
  "geometry": {"coordinates":[-72.970139,43.596981],"type":"Point"}
}