{
  "type": "Feature",
  "properties": {
    "iso:country":"US",
    "sg:address":"389 State Rte 15",
    "sg:city":"Jericho",
    "sg:classifiers":[
        {
            "category":"Travel",
            "subcategory":"Hotels & Motels",
            "type":"Entertainment"
        }
    ],
    "sg:phone":"+1 802 899 2234",
    "sg:postcode":"05465",
    "sg:province":"VT",
    "wof:name":"Sinclair Inn Bed & Breakfast",
    "wof:placetype":"venue"
},
  "geometry": {"coordinates":[-72.999263,44.50419],"type":"Point"}
}