{
  "type": "Feature",
  "properties": {
    "iso:country":"US",
    "sg:address":"1110 Pine St",
    "sg:city":"Burlington",
    "sg:classifiers":[
        {
            "category":"Social Services",
            "type":"Services"
        }
    ],
    "sg:phone":"+1 802 651 7049",
    "sg:postcode":"05401",
    "sg:province":"VT",
    "wof:name":"Xxxxxxxxxxxxx",
    "wof:placetype":"venue"
},
  "geometry": {"coordinates":[-73.214533,44.448702],"type":"Point"}
}