{
  "type": "Feature",
  "properties": {
    "addr:full":"45 Hinesburg Rd South Burlington VT 05403",
    "addr:housenumber":"45",
    "addr:postcode":"05403",
    "addr:street":"Hinesburg Rd",
    "iso:country":"US",
    "sg:address":"45 Hinesburg Rd",
    "sg:city":"South Burlington",
    "sg:classifiers":[
        {
            "category":"Shopping",
            "subcategory":"Crafts & Fabrics",
            "type":"Retail Goods"
        }
    ],
    "sg:phone":"+1 802 864 0648",
    "sg:postcode":"05403",
    "sg:province":"VT",
    "sg:tags":[
        "sewing"
    ],
    "sg:website":"www.joann.com",
    "wof:name":"Jo-Ann Fabrics & Crafts",
    "wof:placetype":"venue"
},
  "geometry": {"coordinates":[-73.17138,44.466785],"type":"Point"}
}