{
  "type": "Feature",
  "properties": {
    "iso:country":"US",
    "sg:address":"121 Main St",
    "sg:city":"Readsboro",
    "sg:classifiers":[
        {
            "category":"Personal",
            "subcategory":"Beauty Salon",
            "type":"Services"
        }
    ],
    "sg:phone":"+1 802 423 8203",
    "sg:postcode":"05350",
    "sg:province":"VT",
    "sg:tags":[
        "shop"
    ],
    "wof:name":"Country Kuts & Kurls",
    "wof:placetype":"venue"
},
  "geometry": {"coordinates":[-72.950931,42.77335],"type":"Point"}
}