{
  "type": "Feature",
  "properties": {
    "iso:country":"US",
    "sg:address":"93 Russell St",
    "sg:city":"Winooski",
    "sg:classifiers":[
        {
            "category":"Building & Trades",
            "subcategory":"Cleaning & Sanitation",
            "type":"Services"
        }
    ],
    "sg:phone":"+1 802 655 9067",
    "sg:postcode":"05404",
    "sg:province":"VT",
    "sg:tags":[
        "house"
    ],
    "wof:name":"Toni's Touch",
    "wof:placetype":"venue"
},
  "geometry": {"coordinates":[-73.179348,44.495882],"type":"Point"}
}