{
  "type": "Feature",
  "properties": {
    "addr:full":"129 Church St Rutland VT 05701",
    "addr:housenumber":"129",
    "addr:postcode":"05701",
    "addr:street":"Church St",
    "iso:country":"US",
    "sg:address":"129 Church St",
    "sg:city":"Rutland",
    "sg:classifiers":[
        {
            "category":"Health Services",
            "subcategory":"Nursing And Care Facility",
            "type":"Services"
        }
    ],
    "sg:phone":"+1 802 773 9107",
    "sg:postcode":"05701",
    "sg:province":"VT",
    "sg:tags":[
        "home",
        "retirement",
        "community"
    ],
    "wof:name":"Parker House",
    "wof:placetype":"venue"
},
  "geometry": {"coordinates":[-72.97879399999999,43.617404],"type":"Point"}
}