{
  "type": "Feature",
  "properties": {
    "iso:country":"US",
    "sg:address":"1879 Williston Rd",
    "sg:city":"South Burlington",
    "sg:classifiers":[
        {
            "category":"Building & Trades",
            "subcategory":"Plumbing",
            "type":"Services"
        }
    ],
    "sg:phone":"+1 802 865 9900",
    "sg:postcode":"05403",
    "sg:province":"VT",
    "sg:tags":[
        "conditioning",
        "contractor",
        "system",
        "air"
    ],
    "wof:name":"Avonda Air Systems Inc",
    "wof:placetype":"venue"
},
  "geometry": {"coordinates":[-73.157647,44.464002],"type":"Point"}
}