{
  "type": "Feature",
  "properties": {
    "addr:full":"16 Iris Way White River Junction VT 05001",
    "addr:housenumber":"16",
    "addr:postcode":"05001",
    "addr:street":"Iris Way",
    "iso:country":"US",
    "sg:address":"16 Iris Way",
    "sg:city":"White River Junction",
    "sg:classifiers":[
        {
            "category":"Professional",
            "subcategory":"Management & Consulting",
            "type":"Services"
        }
    ],
    "sg:phone":"+1 802 296 7752",
    "sg:postcode":"05001",
    "sg:province":"VT",
    "sg:tags":[
        "environmental",
        "consultant"
    ],
    "wof:name":"Leslie Sonder",
    "wof:placetype":"venue"
},
  "geometry": {"coordinates":[-72.324477,43.693937],"type":"Point"}
}