{
  "type": "Feature",
  "properties": {
    "iso:country":"US",
    "sg:address":"76 Mitchell Rd",
    "sg:city":"Barre",
    "sg:classifiers":[
        {
            "category":"Building & Trades",
            "subcategory":"Electrical",
            "type":"Services"
        }
    ],
    "sg:phone":"+1 802 476 9460",
    "sg:postcode":"05641",
    "sg:province":"VT",
    "sg:tags":[
        "electrical",
        "contractor"
    ],
    "wof:name":"Phoenix Electric",
    "wof:placetype":"venue"
},
  "geometry": {"coordinates":[-72.471109,44.230482],"type":"Point"}
}