{
  "type": "Feature",
  "properties": {
    "iso:country":"US",
    "sg:address":"425 Taylor Dr",
    "sg:city":"Windsor",
    "sg:classifiers":[
        {
            "category":"Banks & Credit Unions",
            "subcategory":"Investment Brokerage",
            "type":"Services"
        }
    ],
    "sg:phone":"+1 802 674 9415",
    "sg:postcode":"05089",
    "sg:province":"VT",
    "wof:name":"Savior Venture Capital Corp",
    "wof:placetype":"venue"
},
  "geometry": {"coordinates":[-72.396367,43.500455],"type":"Point"}
}