{
  "type": "Feature",
  "properties": {
    "iso:country":"US",
    "sg:address":"43 Lower Newton Rd",
    "sg:city":"St Albans",
    "sg:phone":"+1 802 527 1287",
    "sg:postcode":"05478",
    "sg:province":"VT",
    "sg:tags":[
        "gas"
    ],
    "wof:name":"Liberty Propane Gas Inc",
    "wof:placetype":"venue"
},
  "geometry": {"coordinates":[-73.08609300000001,44.820384],"type":"Point"}
}