{
  "type": "Feature",
  "properties": {
    "addr:full":"219 Blake Roy Rd Middlebury VT 05753",
    "addr:housenumber":"219",
    "addr:postcode":"05753",
    "addr:street":"Blake Roy Rd",
    "iso:country":"US",
    "sg:address":"219 Blake Roy Rd",
    "sg:city":"Middlebury",
    "sg:classifiers":[
        {
            "category":"Professional",
            "subcategory":"Testing Lab",
            "type":"Services"
        }
    ],
    "sg:phone":"+1 802 388 3390",
    "sg:postcode":"05753",
    "sg:province":"VT",
    "sg:tags":[
        "laboratory"
    ],
    "sg:website":"www.vrelabs.com",
    "wof:name":"Green Mountain Electromagnetic",
    "wof:placetype":"venue"
},
  "geometry": {"coordinates":[-73.13558500000001,43.96179],"type":"Point"}
}