{
  "type": "Feature",
  "properties": {
    "iso:country":"US",
    "sg:address":"206 Charles St",
    "sg:city":"Lyndonville",
    "sg:classifiers":[
        {
            "category":"Professional",
            "subcategory":"Computer Services",
            "type":"Services"
        }
    ],
    "sg:phone":"+1 802 626 7246",
    "sg:postcode":"05851",
    "sg:province":"VT",
    "sg:tags":[
        "datum"
    ],
    "wof:name":"Electronic Data Systems Corp",
    "wof:placetype":"venue"
},
  "geometry": {"coordinates":[-72.000271,44.529748],"type":"Point"}
}