{
  "type": "Feature",
  "properties": {
    "addr:full":"34 S Main St Saint Albans VT 05478",
    "addr:housenumber":"34",
    "addr:postcode":"05478",
    "addr:street":"S Main St",
    "iso:country":"US",
    "sg:address":"34 S Main St",
    "sg:city":"Saint Albans",
    "sg:classifiers":[
        {
            "category":"Social Services",
            "type":"Services"
        }
    ],
    "sg:phone":"+1 802 527 2262",
    "sg:postcode":"05478",
    "sg:province":"VT",
    "wof:name":"Bridges Adolescent Services",
    "wof:placetype":"venue"
},
  "geometry": {"coordinates":[-73.083714,44.809791],"type":"Point"}
}