{
  "type": "Feature",
  "properties": {
    "addr:full":"575 Dorset St South Burlington VT 05403",
    "addr:housenumber":"575",
    "addr:postcode":"05403",
    "addr:street":"Dorset St",
    "iso:country":"US",
    "sg:address":"575 Dorset St",
    "sg:city":"South Burlington",
    "sg:classifiers":[
        {
            "category":"Government",
            "subcategory":"Office",
            "type":"Public Place"
        }
    ],
    "sg:phone":"+1 802 846 4107",
    "sg:postcode":"05403",
    "sg:province":"VT",
    "sg:tags":[
        "city"
    ],
    "wof:name":"South Burlington City Manager",
    "wof:placetype":"venue"
},
  "geometry": {"coordinates":[-73.180525,44.461921],"type":"Point"}
}