{
  "type": "Feature",
  "properties": {
    "iso:country":"US",
    "sg:address":"102 Union St",
    "sg:city":"Newport",
    "sg:classifiers":[
        {
            "category":"Sports & Exercise",
            "subcategory":"Gym",
            "type":"Entertainment"
        }
    ],
    "sg:phone":"+1 802 334 2777",
    "sg:postcode":"05855",
    "sg:province":"VT",
    "sg:tags":[
        "club",
        "health",
        "studio",
        "gymnasium"
    ],
    "wof:name":"Kingdom Racquet & Fitness Club",
    "wof:placetype":"venue"
},
  "geometry": {"coordinates":[-72.203199,44.943661],"type":"Point"}
}