{
  "type": "Feature",
  "properties": {
    "iso:country":"US",
    "sg:address":"274 N Winooski Ave",
    "sg:city":"Burlington",
    "sg:classifiers":[
        {
            "category":"Shopping",
            "subcategory":"Used Merchandise",
            "type":"Retail Goods"
        }
    ],
    "sg:phone":"+1 802 865 9599",
    "sg:postcode":"05401",
    "sg:province":"VT",
    "wof:name":"Greener Pastures Clothing Co",
    "wof:placetype":"venue"
},
  "geometry": {"coordinates":[-73.20945399999999,44.486398],"type":"Point"}
}