{
  "type": "Feature",
  "properties": {
    "iso:country":"US",
    "sg:address":"3 College St",
    "sg:city":"Burlington",
    "sg:classifiers":[
        {
            "category":"Professional",
            "subcategory":"Testing Lab",
            "type":"Services"
        }
    ],
    "sg:phone":"+1 802 859 3086",
    "sg:postcode":"05401",
    "sg:province":"VT",
    "sg:tags":[
        "laboratory"
    ],
    "wof:name":"Rubenstein Ecosystem Science",
    "wof:placetype":"venue"
},
  "geometry": {"coordinates":[-73.22077400000001,44.476738],"type":"Point"}
}