{
  "type": "Feature",
  "properties": {
    "iso:country":"US",
    "sg:address":"279 Main St",
    "sg:city":"Shoreham",
    "sg:classifiers":[
        {
            "category":"Education",
            "subcategory":"Library",
            "type":"Public Place"
        }
    ],
    "sg:phone":"+1 802 897 2647",
    "sg:postcode":"05770",
    "sg:province":"VT",
    "wof:name":"Platte Memorial Library",
    "wof:placetype":"venue"
},
  "geometry": {"coordinates":[-73.314333,43.893739],"type":"Point"}
}