{
  "type": "Feature",
  "properties": {
    "iso:country":"US",
    "sg:address":"6578 State Rte 22A",
    "sg:city":"Vergennes",
    "sg:classifiers":[
        {
            "category":"Farming",
            "subcategory":"Dairy Farm",
            "type":"Manufacturing & Wholesale Goods"
        }
    ],
    "sg:phone":"+1 802 759 2817",
    "sg:postcode":"05491",
    "sg:province":"VT",
    "wof:name":"Waterman Farm Roger",
    "wof:placetype":"venue"
},
  "geometry": {"coordinates":[-73.303867,44.065596],"type":"Point"}
}