{
  "type": "Feature",
  "properties": {
    "iso:country":"US",
    "sg:address":"20 Jericho Rd",
    "sg:city":"Essex Junction",
    "sg:classifiers":[
        {
            "category":"Organizations",
            "subcategory":"Religious Organization",
            "type":"Services"
        }
    ],
    "sg:phone":"+1 802 878 5997",
    "sg:postcode":"05452",
    "sg:province":"VT",
    "wof:name":"St Pius X",
    "wof:placetype":"venue"
},
  "geometry": {"coordinates":[-73.05609800000001,44.509572],"type":"Point"}
}