{
  "type": "Feature",
  "properties": {
    "iso:country":"US",
    "sg:address":"280 Seward Rd",
    "sg:city":"Rutland",
    "sg:classifiers":[
        {
            "category":"Manufacturing",
            "subcategory":"Printing",
            "type":"Manufacturing & Wholesale Goods"
        }
    ],
    "sg:phone":"+1 802 773 9137",
    "sg:postcode":"05701",
    "sg:province":"VT",
    "sg:tags":[
        "lithographic",
        "commercial"
    ],
    "wof:name":"Moore Business Forms Inc",
    "wof:placetype":"venue"
},
  "geometry": {"coordinates":[-72.962598,43.585882],"type":"Point"}
}