{
  "type": "Feature",
  "properties": {
    "iso:country":"US",
    "sg:address":"889 May Farm Rd",
    "sg:city":"Barton",
    "sg:classifiers":[
        {
            "category":"Manufacturing",
            "subcategory":"Retail Goods",
            "type":"Manufacturing & Wholesale Goods"
        }
    ],
    "sg:phone":"+1 802 525 6268",
    "sg:postcode":"05822",
    "sg:province":"VT",
    "sg:tags":[
        "manufacture",
        "candle"
    ],
    "wof:name":"Scented Flame of Vermont",
    "wof:placetype":"venue"
},
  "geometry": {"coordinates":[-72.189419,44.772775],"type":"Point"}
}