{
  "type": "Feature",
  "properties": {
    "iso:country":"US",
    "sg:address":"80 Hollow Rd",
    "sg:city":"North Ferrisburg",
    "sg:classifiers":[
        {
            "category":"Wholesale",
            "subcategory":"Auto Parts",
            "type":"Manufacturing & Wholesale Goods"
        }
    ],
    "sg:phone":"+1 802 425 3961",
    "sg:postcode":"05473",
    "sg:province":"VT",
    "wof:name":"J PS Equipment Service Center",
    "wof:placetype":"venue"
},
  "geometry": {"coordinates":[-73.172791,44.24695],"type":"Point"}
}