{
  "type": "Feature",
  "properties": {
    "addr:full":"11 Court St Middlebury VT 05753",
    "addr:housenumber":"11",
    "addr:postcode":"05753",
    "addr:street":"Court St",
    "iso:country":"US",
    "sg:address":"11 Court St",
    "sg:city":"Middlebury",
    "sg:classifiers":[
        {
            "category":"Professional",
            "subcategory":"Accounting & Tax Preparation",
            "type":"Services"
        }
    ],
    "sg:phone":"+1 802 388 6307",
    "sg:postcode":"05753",
    "sg:province":"VT",
    "sg:tags":[
        "accountant"
    ],
    "wof:name":"Miller Deverell & Co",
    "wof:placetype":"venue"
},
  "geometry": {"coordinates":[-73.165209,44.013268],"type":"Point"}
}