{
  "type": "Feature",
  "properties": {
    "addr:full":"70 Birch St Bradford VT 05033",
    "addr:housenumber":"70",
    "addr:postcode":"05033",
    "addr:street":"Birch St",
    "iso:country":"US",
    "sg:address":"70 Birch St",
    "sg:city":"Bradford",
    "sg:classifiers":[
        {
            "category":"Social Services",
            "subcategory":"Adult Care",
            "type":"Services"
        }
    ],
    "sg:phone":"+1 802 222 5332",
    "sg:postcode":"05033",
    "sg:province":"VT",
    "sg:tags":[
        "home",
        "residential"
    ],
    "wof:name":"Blue Spruce Home-The Retired",
    "wof:placetype":"venue"
},
  "geometry": {"coordinates":[-72.11335099999999,44.011578],"type":"Point"}
}