{
  "type": "Feature",
  "properties": {
    "iso:country":"US",
    "sg:address":"45 Bellevue Ave",
    "sg:city":"Rutland",
    "sg:classifiers":[
        {
            "category":"Communications",
            "subcategory":"Film & Video Production",
            "type":"Services"
        }
    ],
    "sg:phone":"+1 802 775 0867",
    "sg:postcode":"05701",
    "sg:province":"VT",
    "sg:tags":[
        "motion",
        "picture"
    ],
    "wof:name":"Videoguy",
    "wof:placetype":"venue"
},
  "geometry": {"coordinates":[-72.969359,43.613881],"type":"Point"}
}