{
  "type": "Feature",
  "properties": {
    "addr:full":"58 Congress St Morrisville VT 05661",
    "addr:housenumber":"58",
    "addr:postcode":"05661",
    "addr:street":"Congress St",
    "iso:country":"US",
    "sg:address":"58 Congress St",
    "sg:city":"Morrisville",
    "sg:classifiers":[
        {
            "category":"Shopping",
            "subcategory":"Pharmacy",
            "type":"Retail Goods"
        }
    ],
    "sg:phone":"+1 802 888 4973",
    "sg:postcode":"05661",
    "sg:province":"VT",
    "wof:name":"Brooks Pharmacy",
    "wof:placetype":"venue"
},
  "geometry": {"coordinates":[-72.598011,44.560968],"type":"Point"}
}