{
  "type": "Feature",
  "properties": {
    "iso:country":"US",
    "sg:address":"4106 Fort Bridgman Rd",
    "sg:city":"Vernon",
    "sg:classifiers":[
        {
            "category":"Building & Trades",
            "subcategory":"Plumbing",
            "type":"Services"
        },
        {
            "category":"Wholesale",
            "subcategory":"Construction Materials",
            "type":"Manufacturing & Wholesale Goods"
        },
        {
            "category":"Home & Garden",
            "subcategory":"Building Materials",
            "type":"Retail Goods"
        },
        {
            "category":"Building & Trades",
            "subcategory":"Construction",
            "type":"Services"
        }
    ],
    "sg:phone":"+1 802 579 1525",
    "sg:postcode":"05354",
    "sg:province":"VT",
    "sg:tags":[
        "heater",
        "plumber",
        "supply",
        "heating",
        "specialty",
        "water",
        "part",
        "fixtures",
        "contractor"
    ],
    "wof:name":"Harvey Plumbing and Heating",
    "wof:placetype":"venue"
},
  "geometry": {"coordinates":[-72.471442,42.739905],"type":"Point"}
}