{
  "type": "Feature",
  "properties": {
    "addr:full":"49 Center St Brandon VT 05733",
    "addr:housenumber":"49",
    "addr:postcode":"05733",
    "addr:street":"Center St",
    "iso:country":"US",
    "sg:address":"49 Center St",
    "sg:city":"Brandon",
    "sg:classifiers":[
        {
            "category":"Government",
            "subcategory":"Office",
            "type":"Public Place"
        }
    ],
    "sg:phone":"+1 802 247 5721",
    "sg:postcode":"05733",
    "sg:province":"VT",
    "sg:tags":[
        "executive"
    ],
    "wof:name":"Rutland Cnty-Brandon Town Hall",
    "wof:placetype":"venue"
},
  "geometry": {"coordinates":[-73.088809,43.799372],"type":"Point"}
}