{
  "type": "Feature",
  "properties": {
    "iso:country":"US",
    "sg:address":"9 Merchants Row",
    "sg:city":"Rutland",
    "sg:classifiers":[
        {
            "category":"Government",
            "subcategory":"Jail",
            "type":"Public Place"
        }
    ],
    "sg:phone":"+1 802 786 5098",
    "sg:postcode":"05701",
    "sg:province":"VT",
    "sg:tags":[
        "govt",
        "state",
        "institution"
    ],
    "wof:name":"Corrections Dept",
    "wof:placetype":"venue"
},
  "geometry": {"coordinates":[-72.979888,43.606304],"type":"Point"}
}