{
  "type": "Feature",
  "properties": {
    "iso:country":"US",
    "sg:address":"8 George St",
    "sg:city":"Winooski",
    "sg:classifiers":[
        {
            "category":"Professional",
            "subcategory":"Business Services",
            "type":"Services"
        }
    ],
    "sg:phone":"+1 802 655 3182",
    "sg:postcode":"05404",
    "sg:province":"VT",
    "wof:name":"Residential Inspection Service",
    "wof:placetype":"venue"
},
  "geometry": {"coordinates":[-73.178639,44.498455],"type":"Point"}
}