{
  "type": "Feature",
  "properties": {
    "addr:full":"46 S Meadow Dr Burlington VT 05401",
    "addr:housenumber":"46",
    "addr:postcode":"05401",
    "addr:street":"S Meadow Dr",
    "iso:country":"US",
    "sg:address":"46 S Meadow Dr",
    "sg:city":"Burlington",
    "sg:classifiers":[
        {
            "category":"Building & Trades",
            "subcategory":"Construction",
            "type":"Services"
        }
    ],
    "sg:phone":"+1 802 862 1349",
    "sg:postcode":"05401",
    "sg:province":"VT",
    "sg:tags":[
        "house"
    ],
    "wof:name":"Carpentry Contracting Imprvs",
    "wof:placetype":"venue"
},
  "geometry": {"coordinates":[-73.21312,44.450102],"type":"Point"}
}