{
  "type": "Feature",
  "properties": {
    "addr:full":"3990 Main Rd Huntington VT 05462",
    "addr:housenumber":"3990",
    "addr:postcode":"05462",
    "addr:street":"Main Rd",
    "iso:country":"US",
    "sg:address":"3990 Main Rd",
    "sg:city":"Huntington",
    "sg:classifiers":[
        {
            "category":"Building & Trades",
            "subcategory":"Construction",
            "type":"Services"
        }
    ],
    "sg:phone":"+1 802 434 2043",
    "sg:postcode":"05462",
    "sg:province":"VT",
    "sg:tags":[
        "contractor"
    ],
    "wof:name":"Lacaillade Masonry Inc",
    "wof:placetype":"venue"
},
  "geometry": {"coordinates":[-72.987971,44.312188],"type":"Point"}
}