{
  "type": "Feature",
  "properties": {
    "addr:full":"19 Lincoln Ave St Albans VT 05478",
    "addr:housenumber":"19",
    "addr:postcode":"05478",
    "addr:street":"Lincoln Ave",
    "iso:country":"US",
    "sg:address":"19 Lincoln Ave",
    "sg:city":"St Albans",
    "sg:classifiers":[
        {
            "category":"Insurance",
            "subcategory":"Insurance Agent",
            "type":"Services"
        }
    ],
    "sg:phone":"+1 802 527 0108",
    "sg:postcode":"05478",
    "sg:province":"VT",
    "wof:name":"Spectrum Benefits",
    "wof:placetype":"venue"
},
  "geometry": {"coordinates":[-73.080073,44.811853],"type":"Point"}
}