{
  "type": "Feature",
  "properties": {
    "addr:full":"28 S Main St Rutland VT 05701",
    "addr:housenumber":"28",
    "addr:postcode":"05701",
    "addr:street":"S Main St",
    "iso:country":"US",
    "sg:address":"28 S Main St",
    "sg:city":"Rutland",
    "sg:classifiers":[
        {
            "category":"Shopping",
            "subcategory":"Used Merchandise",
            "type":"Retail Goods"
        }
    ],
    "sg:phone":"+1 802 773 8229",
    "sg:postcode":"05701",
    "sg:province":"VT",
    "sg:tags":[
        "old",
        "book",
        "rare"
    ],
    "sg:website":"www.tuttlebooks.com",
    "wof:name":"Tuttle Antiquarian Books Inc",
    "wof:placetype":"venue"
},
  "geometry": {"coordinates":[-72.972292,43.608278],"type":"Point"}
}