{
  "type": "Feature",
  "properties": {
    "addr:full":"95 Charlestown Rd Springfield VT 05156",
    "addr:housenumber":"95",
    "addr:postcode":"05156",
    "addr:street":"Charlestown Rd",
    "iso:country":"US",
    "sg:address":"95 Charlestown Rd",
    "sg:city":"Springfield",
    "sg:classifiers":[
        {
            "category":"Retail",
            "subcategory":"Auto Repair",
            "type":"Services"
        }
    ],
    "sg:phone":"+1 802 885 5000",
    "sg:postcode":"05156",
    "sg:province":"VT",
    "sg:tags":[
        "repairing",
        "automobile"
    ],
    "wof:name":"Matulonis Auto Body Inc",
    "wof:placetype":"venue"
},
  "geometry": {"coordinates":[-72.46452499999999,43.276603],"type":"Point"}
}