{
  "type": "Feature",
  "properties": {
    "iso:country":"US",
    "sg:address":"548 Pond Rd",
    "sg:city":"Vernon",
    "sg:classifiers":[
        {
            "category":"Real Estate",
            "subcategory":"Real Estate Operator",
            "type":"Services"
        }
    ],
    "sg:phone":"+1 802 257 5041",
    "sg:postcode":"05354",
    "sg:province":"VT",
    "sg:tags":[
        "building",
        "park",
        "nonresidential"
    ],
    "wof:name":"Godfrey Properties Inc",
    "wof:placetype":"venue"
},
  "geometry": {"coordinates":[-72.51241400000001,42.748909],"type":"Point"}
}