{
  "type": "Feature",
  "properties": {
    "iso:country":"US",
    "sg:address":"397 River St",
    "sg:city":"Chester",
    "sg:classifiers":[
        {
            "category":"Professional",
            "subcategory":"Research",
            "type":"Services"
        }
    ],
    "sg:phone":"+1 802 875 6420",
    "sg:postcode":"05143",
    "sg:province":"VT",
    "sg:tags":[
        "nonphysical",
        "commercial"
    ],
    "wof:name":"Prg Reasearch & Consulting",
    "wof:placetype":"venue"
},
  "geometry": {"coordinates":[-72.594706,43.259457],"type":"Point"}
}