{
  "type": "Feature",
  "properties": {
    "addr:full":"4 Morse Dr Essex Junction VT 05452",
    "addr:housenumber":"4",
    "addr:postcode":"05452",
    "addr:street":"Morse Dr",
    "iso:country":"US",
    "sg:address":"4 Morse Dr",
    "sg:city":"Essex Junction",
    "sg:classifiers":[
        {
            "category":"Health Services",
            "subcategory":"Clinic",
            "type":"Services"
        }
    ],
    "sg:phone":"+1 802 879 3312",
    "sg:postcode":"05452",
    "sg:province":"VT",
    "sg:tags":[
        "home",
        "care"
    ],
    "wof:name":"Aquatic Physical Therapy",
    "wof:placetype":"venue"
},
  "geometry": {"coordinates":[-73.13958599999999,44.509999],"type":"Point"}
}