{
  "type": "Feature",
  "properties": {
    "addr:full":"119 Park St Bennington VT 05201",
    "addr:housenumber":"119",
    "addr:postcode":"05201",
    "addr:street":"Park St",
    "iso:country":"US",
    "sg:address":"119 Park St",
    "sg:city":"Bennington",
    "sg:classifiers":[
        {
            "category":"Food & Beverages",
            "subcategory":"Groceries & Convenience Stores",
            "type":"Retail Goods"
        },
        {
            "category":"Food & Beverages",
            "subcategory":"Liquor & Beverages",
            "type":"Retail Goods"
        }
    ],
    "sg:phone":"+1 802 442 2351",
    "sg:postcode":"05201",
    "sg:province":"VT",
    "sg:tags":[
        "grocer",
        "alcoholic"
    ],
    "wof:name":"Beshara's Discount Beverage",
    "wof:placetype":"venue"
},
  "geometry": {"coordinates":[-73.193201,42.880358],"type":"Point"}
}