{
  "type": "Feature",
  "properties": {
    "addr:full":"112 Lake St Burlington VT 05401",
    "addr:housenumber":"112",
    "addr:postcode":"05401",
    "addr:street":"Lake St",
    "iso:country":"US",
    "sg:address":"112 Lake St",
    "sg:city":"Burlington",
    "sg:classifiers":[
        {
            "category":"Restaurant",
            "type":"Food & Drink"
        }
    ],
    "sg:phone":"+1 802 658 4844",
    "sg:postcode":"05401",
    "sg:province":"VT",
    "wof:name":"Taste Of Burlington",
    "wof:placetype":"venue"
},
  "geometry": {"coordinates":[-73.22153299999999,44.480429],"type":"Point"}
}