{
  "type": "Feature",
  "properties": {
    "addr:full":"194 Rockingham St Bellows Falls VT 05101",
    "addr:housenumber":"194",
    "addr:postcode":"05101",
    "addr:street":"Rockingham St",
    "iso:country":"US",
    "sg:address":"194 Rockingham St",
    "sg:city":"Bellows Falls",
    "sg:classifiers":[
        {
            "category":"Manufacturing",
            "subcategory":"Textiles",
            "type":"Manufacturing & Wholesale Goods"
        }
    ],
    "sg:phone":"+1 802 463 3286",
    "sg:postcode":"05101",
    "sg:province":"VT",
    "sg:tags":[
        "mill",
        "sewing",
        "fabric"
    ],
    "wof:name":"Thistledown Quilts",
    "wof:placetype":"venue"
},
  "geometry": {"coordinates":[-72.45495699999999,43.141988],"type":"Point"}
}