{
  "type": "Feature",
  "properties": {
    "iso:country":"US",
    "sg:address":"682 Stevens Rd",
    "sg:city":"Pittsford",
    "sg:classifiers":[
        {
            "category":"Building & Trades",
            "subcategory":"Plumbing",
            "type":"Services"
        }
    ],
    "sg:phone":"+1 802 483 6400",
    "sg:postcode":"05763",
    "sg:province":"VT",
    "sg:tags":[
        "repair",
        "contractor"
    ],
    "wof:name":"Bobs Heating Service Inc",
    "wof:placetype":"venue"
},
  "geometry": {"coordinates":[-73.027557,43.677685],"type":"Point"}
}