{
  "type": "Feature",
  "properties": {
    "addr:full":"Main Jeffersonville VT 05464",
    "addr:postcode":"05464",
    "addr:street":"Main",
    "iso:country":"US",
    "sg:address":"Main",
    "sg:city":"Jeffersonville",
    "sg:classifiers":[
        {
            "category":"Professional",
            "subcategory":"Lawyer & Legal Services",
            "type":"Services"
        }
    ],
    "sg:phone":"+1 802 644 5643",
    "sg:postcode":"05464",
    "sg:province":"VT",
    "wof:name":"Sheredy Alan R Atty",
    "wof:placetype":"venue"
},
  "geometry": {"coordinates":[-72.832199,44.643902],"type":"Point"}
}