{
  "type": "Feature",
  "properties": {
    "iso:country":"US",
    "sg:address":"72 Church St",
    "sg:city":"Shelburne",
    "sg:classifiers":[
        {
            "category":"Organizations",
            "subcategory":"Religious Organization",
            "type":"Services"
        }
    ],
    "sg:phone":"+1 802 985 2373",
    "sg:postcode":"05482",
    "sg:province":"VT",
    "sg:tags":[
        "church"
    ],
    "wof:name":"St Catherine Of Siena",
    "wof:placetype":"venue"
},
  "geometry": {"coordinates":[-73.227671,44.378038],"type":"Point"}
}