{
  "type": "Feature",
  "properties": {
    "addr:full":"506 Hercules Dr Colchester VT 05446",
    "addr:housenumber":"506",
    "addr:postcode":"05446",
    "addr:street":"Hercules Dr",
    "iso:country":"US",
    "sg:address":"506 Hercules Dr",
    "sg:city":"Colchester",
    "sg:classifiers":[
        {
            "category":"Autos & Motor Vehicles",
            "subcategory":"Auto Supplies",
            "type":"Retail Goods"
        }
    ],
    "sg:phone":"+1 802 655 3354",
    "sg:postcode":"05446",
    "sg:province":"VT",
    "sg:tags":[
        "equipment",
        "racing",
        "car",
        "automobile"
    ],
    "sg:website":"www.vermontsportscar.com",
    "wof:name":"Vermont Sports Car",
    "wof:placetype":"venue"
},
  "geometry": {"coordinates":[-73.17371199999999,44.504547],"type":"Point"}
}