{
  "type": "Feature",
  "properties": {
    "addr:full":"427 Washington Hwy Morrisville VT 05661",
    "addr:housenumber":"427",
    "addr:postcode":"05661",
    "addr:street":"Washington Hwy",
    "iso:country":"US",
    "sg:address":"427 Washington Hwy",
    "sg:city":"Morrisville",
    "sg:classifiers":[
        {
            "category":"Retail",
            "subcategory":"Repair Shop",
            "type":"Services"
        }
    ],
    "sg:phone":"+1 802 888 6852",
    "sg:postcode":"05661",
    "sg:province":"VT",
    "sg:tags":[
        "electrical",
        "health"
    ],
    "wof:name":"Green Mtn Speech & Hearing Ser",
    "wof:placetype":"venue"
},
  "geometry": {"coordinates":[-72.59365699999999,44.554658],"type":"Point"}
}