{
  "type": "Feature",
  "properties": {
    "iso:country":"US",
    "sg:address":"1594 Monkton Rd",
    "sg:city":"Vergennes",
    "sg:classifiers":[
        {
            "category":"Professional",
            "subcategory":"Computer Services",
            "type":"Services"
        }
    ],
    "sg:phone":"+1 802 877 6278",
    "sg:postcode":"05491",
    "sg:province":"VT",
    "sg:tags":[
        "related"
    ],
    "wof:name":"Peter Barratt",
    "wof:placetype":"venue"
},
  "geometry": {"coordinates":[-73.20567699999999,44.175652],"type":"Point"}
}