{
  "type": "Feature",
  "properties": {
    "iso:country":"US",
    "sg:address":"5376 Shelburne Rd",
    "sg:city":"Shelburne",
    "sg:classifiers":[
        {
            "category":"Government",
            "subcategory":"Fire Station",
            "type":"Public Place"
        }
    ],
    "sg:phone":"+1 802 985 2366",
    "sg:postcode":"05482",
    "sg:province":"VT",
    "sg:tags":[
        "department"
    ],
    "wof:name":"Shelburne Volunteer Fire Department",
    "wof:placetype":"venue"
},
  "geometry": {"coordinates":[-73.22816400000001,44.379005],"type":"Point"}
}