{
  "type": "Feature",
  "properties": {
    "iso:country":"US",
    "sg:address":"25 Bear Mountain Rd",
    "sg:city":"East Wallingford",
    "sg:classifiers":[
        {
            "category":"Organizations",
            "subcategory":"Community Association",
            "type":"Services"
        }
    ],
    "sg:phone":"+1 802 259 3009",
    "sg:postcode":"05742",
    "sg:province":"VT",
    "wof:name":"Wsi Environmental Services",
    "wof:placetype":"venue"
},
  "geometry": {"coordinates":[-72.91515,43.439807],"type":"Point"}
}