{
  "type": "Feature",
  "properties": {
    "addr:full":"530 Webster Rd Orleans VT 05860",
    "addr:housenumber":"530",
    "addr:postcode":"05860",
    "addr:street":"Webster Rd",
    "iso:country":"US",
    "sg:address":"530 Webster Rd",
    "sg:city":"Orleans",
    "sg:classifiers":[
        {
            "category":"Farming",
            "subcategory":"Dairy Farm",
            "type":"Manufacturing & Wholesale Goods"
        }
    ],
    "sg:phone":"+1 802 754 6875",
    "sg:postcode":"05860",
    "sg:province":"VT",
    "sg:tags":[
        "agricultural",
        "production",
        "livestock"
    ],
    "wof:name":"Terry Perkins",
    "wof:placetype":"venue"
},
  "geometry": {"coordinates":[-72.221272,44.854814],"type":"Point"}
}