{
  "type": "Feature",
  "properties": {
    "iso:country":"US",
    "sg:address":"462 S Willard St",
    "sg:city":"Burlington",
    "sg:classifiers":[
        {
            "category":"Building & Trades",
            "subcategory":"Construction",
            "type":"Services"
        }
    ],
    "sg:phone":"+1 802 865 6056",
    "sg:postcode":"05401",
    "sg:province":"VT",
    "sg:tags":[
        "restoration",
        "preservation"
    ],
    "wof:name":"Ronald Wanamaker",
    "wof:placetype":"venue"
},
  "geometry": {"coordinates":[-73.206436,44.466176],"type":"Point"}
}