{
  "type": "Feature",
  "properties": {
    "iso:country":"US",
    "sg:address":"802 Industrial Ave",
    "sg:city":"Williston",
    "sg:classifiers":[
        {
            "category":"Health Services",
            "subcategory":"Chiropractor",
            "type":"Services"
        }
    ],
    "sg:phone":"+1 802 863 2272",
    "sg:postcode":"05495",
    "sg:province":"VT",
    "sg:website":"www.willistonchiropractic.com",
    "wof:name":"Williston Center-Chiro & Sport",
    "wof:placetype":"venue"
},
  "geometry": {"coordinates":[-73.11687499999999,44.464477],"type":"Point"}
}