{
  "type": "Feature",
  "properties": {
    "iso:country":"US",
    "sg:address":"266 North St",
    "sg:city":"Winooski",
    "sg:classifiers":[
        {
            "category":"Building & Trades",
            "subcategory":"Landscaping Services",
            "type":"Services"
        }
    ],
    "sg:phone":"+1 802 655 4498",
    "sg:postcode":"05404",
    "sg:province":"VT",
    "wof:name":"ATL Lawn & Property Maint",
    "wof:placetype":"venue"
},
  "geometry": {"coordinates":[-73.18977,44.500114],"type":"Point"}
}