{
  "type": "Feature",
  "properties": {
    "iso:country":"US",
    "sg:address":"2921 E Main St",
    "sg:city":"Richmond",
    "sg:classifiers":[
        {
            "category":"Shopping",
            "type":"Retail Goods"
        }
    ],
    "sg:phone":"+1 802 434 2400",
    "sg:postcode":"05477",
    "sg:province":"VT",
    "sg:tags":[
        "wedding",
        "supply"
    ],
    "wof:name":"Snaffle Sweets",
    "wof:placetype":"venue"
},
  "geometry": {"coordinates":[-72.943241,44.389619],"type":"Point"}
}