{
  "type": "Feature",
  "properties": {
    "addr:full":"278 W Lakeshore Dr Colchester VT 05446",
    "addr:housenumber":"278",
    "addr:postcode":"05446",
    "addr:street":"W Lakeshore Dr",
    "iso:country":"US",
    "sg:address":"278 W Lakeshore Dr",
    "sg:city":"Colchester",
    "sg:classifiers":[
        {
            "category":"Recreation",
            "subcategory":"Marina",
            "type":"Entertainment"
        }
    ],
    "sg:phone":"+1 802 862 4072",
    "sg:postcode":"05446",
    "sg:province":"VT",
    "wof:name":"Malletts Bay Marina",
    "wof:placetype":"venue"
},
  "geometry": {"coordinates":[-73.221553,44.547554],"type":"Point"}
}