{
  "type": "Feature",
  "properties": {
    "addr:full":"664 Ferno Rd Williamstown VT 05679",
    "addr:housenumber":"664",
    "addr:postcode":"05679",
    "addr:street":"Ferno Rd",
    "iso:country":"US",
    "sg:address":"664 Ferno Rd",
    "sg:city":"Williamstown",
    "sg:classifiers":[
        {
            "category":"Personal",
            "subcategory":"Beauty Salon",
            "type":"Services"
        }
    ],
    "sg:phone":"+1 802 485 7125",
    "sg:postcode":"05679",
    "sg:province":"VT",
    "wof:name":"Wood Cutters",
    "wof:placetype":"venue"
},
  "geometry": {"coordinates":[-72.59972999999999,44.122283],"type":"Point"}
}