{
  "type": "Feature",
  "properties": {
    "iso:country":"US",
    "sg:address":"35 S Main St",
    "sg:city":"Stowe",
    "sg:classifiers":[
        {
            "category":"Real Estate",
            "subcategory":"Real Estate Agent",
            "type":"Services"
        }
    ],
    "sg:phone":"+1 802 253 7878",
    "sg:postcode":"05672",
    "sg:province":"VT",
    "wof:name":"Homefield Real Estate",
    "wof:placetype":"venue"
},
  "geometry": {"coordinates":[-72.68803800000001,44.46526],"type":"Point"}
}