{
  "type": "Feature",
  "properties": {
    "iso:country":"US",
    "sg:address":"4 The Green",
    "sg:city":"Woodstock",
    "sg:classifiers":[
        {
            "category":"Professional",
            "type":"Services"
        }
    ],
    "sg:phone":"+1 802 457 4356",
    "sg:postcode":"05091",
    "sg:province":"VT",
    "sg:tags":[
        "establishment"
    ],
    "wof:name":"Sovernet",
    "wof:placetype":"venue"
},
  "geometry": {"coordinates":[-72.518911,43.624929],"type":"Point"}
}