{
  "type": "Feature",
  "properties": {
    "iso:country":"US",
    "sg:address":"1025 Shelburne Rd",
    "sg:city":"South Burlington",
    "sg:classifiers":[
        {
            "category":"Restaurant",
            "type":"Food & Drink"
        }
    ],
    "sg:menulink":"http://www.allmenus.com/vt/south-burlington/13756-olive-garden-italian-restaurant/menu/",
    "sg:phone":"+1 802 863 4907",
    "sg:postcode":"05403",
    "sg:province":"VT",
    "sg:tags":[
        "italian"
    ],
    "wof:name":"Olive Garden Italian Restaurant",
    "wof:placetype":"venue"
},
  "geometry": {"coordinates":[-73.210111,44.439841],"type":"Point"}
}