{
  "type": "Feature",
  "properties": {
    "iso:country":"US",
    "sg:address":"85 N Main St",
    "sg:city":"White River Junction",
    "sg:classifiers":[
        {
            "category":"Utilities",
            "subcategory":"Cable",
            "type":"Services"
        }
    ],
    "sg:phone":"+1 802 295 6688",
    "sg:postcode":"05001",
    "sg:province":"VT",
    "sg:tags":[
        "television"
    ],
    "wof:name":"Upper Vly Educatn Connection",
    "wof:placetype":"venue"
},
  "geometry": {"coordinates":[-72.321123,43.649577],"type":"Point"}
}