{
  "type": "Feature",
  "properties": {
    "iso:country":"US",
    "sg:address":"112 Spring Rd",
    "sg:city":"Tunbridge",
    "sg:classifiers":[
        {
            "category":"Manufacturing",
            "subcategory":"Metals",
            "type":"Manufacturing & Wholesale Goods"
        }
    ],
    "sg:phone":"+1 802 889 3736",
    "sg:postcode":"05077",
    "sg:province":"VT",
    "sg:tags":[
        "furnace",
        "construction",
        "material",
        "blast",
        "works"
    ],
    "wof:name":"Corner Rail Company",
    "wof:placetype":"venue"
},
  "geometry": {"coordinates":[-72.502641,43.897568],"type":"Point"}
}