{
  "type": "Feature",
  "properties": {
    "iso:country":"US",
    "sg:address":"50 Depot St",
    "sg:city":"Lyndonville",
    "sg:classifiers":[
        {
            "category":"Personal",
            "subcategory":"Tanning Parlor",
            "type":"Services"
        }
    ],
    "sg:phone":"+1 802 626 5443",
    "sg:postcode":"05851",
    "sg:province":"VT",
    "sg:tags":[
        "salon"
    ],
    "wof:name":"All Around Tan",
    "wof:placetype":"venue"
},
  "geometry": {"coordinates":[-72.004079,44.534876],"type":"Point"}
}