{
  "type": "Feature",
  "properties": {
    "iso:country":"US",
    "sg:address":"3 S Main St",
    "sg:city":"Alburg",
    "sg:classifiers":[
        {
            "category":"Banks & Credit Unions",
            "subcategory":"Bank",
            "type":"Services"
        }
    ],
    "sg:phone":"+1 802 796 3411",
    "sg:postcode":"05440",
    "sg:province":"VT",
    "wof:name":"Chittenden Bank",
    "wof:placetype":"venue"
},
  "geometry": {"coordinates":[-73.299935,44.976702],"type":"Point"}
}