{
  "type": "Feature",
  "properties": {
    "iso:country":"US",
    "sg:address":"360 Estey Rd",
    "sg:city":"Bristol",
    "sg:classifiers":[
        {
            "category":"Farming",
            "subcategory":"Dairy Farm",
            "type":"Manufacturing & Wholesale Goods"
        }
    ],
    "sg:phone":"+1 802 453 3135",
    "sg:postcode":"05443",
    "sg:province":"VT",
    "wof:name":"Tower Hill Farm",
    "wof:placetype":"venue"
},
  "geometry": {"coordinates":[-73.119055,44.174894],"type":"Point"}
}