{
  "type": "Feature",
  "properties": {
    "addr:full":"434 Middle Rd Milton VT 05468",
    "addr:housenumber":"434",
    "addr:postcode":"05468",
    "addr:street":"Middle Rd",
    "iso:country":"US",
    "sg:address":"434 Middle Rd",
    "sg:city":"Milton",
    "sg:classifiers":[
        {
            "category":"Building & Trades",
            "subcategory":"Construction",
            "type":"Services"
        }
    ],
    "sg:phone":"+1 802 893 4363",
    "sg:postcode":"05468",
    "sg:province":"VT",
    "sg:tags":[
        "painter"
    ],
    "wof:name":"Sam Spear Painting & Dcrtng",
    "wof:placetype":"venue"
},
  "geometry": {"coordinates":[-73.130734,44.590445],"type":"Point"}
}