{
  "type": "Feature",
  "properties": {
    "iso:country":"US",
    "sg:address":"86 Harrington Ave",
    "sg:city":"Rutland",
    "sg:classifiers":[
        {
            "category":"Professional",
            "subcategory":"Management & Consulting",
            "type":"Services"
        }
    ],
    "sg:phone":"+1 802 775 1892",
    "sg:postcode":"05701",
    "sg:province":"VT",
    "sg:tags":[
        "public",
        "relations"
    ],
    "wof:name":"Big Benji B Promotions",
    "wof:placetype":"venue"
},
  "geometry": {"coordinates":[-72.966138,43.611987],"type":"Point"}
}