{
  "type": "Feature",
  "properties": {
    "iso:country":"US",
    "sg:address":"327 Old Ferry Rd",
    "sg:city":"Brattleboro",
    "sg:classifiers":[
        {
            "category":"Government",
            "subcategory":"Office",
            "type":"Public Place"
        }
    ],
    "sg:phone":"+1 802 257 0272",
    "sg:postcode":"05301",
    "sg:province":"VT",
    "sg:tags":[
        "county",
        "program"
    ],
    "wof:name":"Windham County Solid Waste",
    "wof:placetype":"venue"
},
  "geometry": {"coordinates":[-72.54073200000001,42.894648],"type":"Point"}
}