{
  "type": "Feature",
  "properties": {
    "iso:country":"US",
    "sg:address":"9 Haywood Ave",
    "sg:city":"Rutland",
    "sg:classifiers":[
        {
            "category":"Health Services",
            "subcategory":"Nursing And Care Facility",
            "type":"Services"
        }
    ],
    "sg:phone":"+1 802 775 0007",
    "sg:postcode":"05701",
    "sg:province":"VT",
    "sg:tags":[
        "home",
        "convalescent"
    ],
    "sg:website":"www.jhv.com",
    "wof:name":"Mountain View Ctr",
    "wof:placetype":"venue"
},
  "geometry": {"coordinates":[-72.958955,43.594429],"type":"Point"}
}