{
  "type": "Feature",
  "properties": {
    "iso:country":"US",
    "sg:address":"1 Scale Ave",
    "sg:city":"Rutland",
    "sg:classifiers":[
        {
            "category":"Building & Trades",
            "subcategory":"Cleaning & Sanitation",
            "type":"Services"
        }
    ],
    "sg:phone":"+1 802 773 7765",
    "sg:postcode":"05701",
    "sg:province":"VT",
    "sg:tags":[
        "polishing",
        "waxing",
        "floor"
    ],
    "wof:name":"Commercial Building Svc",
    "wof:placetype":"venue"
},
  "geometry": {"coordinates":[-72.97369999999999,43.600792],"type":"Point"}
}