{
  "type": "Feature",
  "properties": {
    "addr:full":"282 Maple St Perkinsville VT 05151",
    "addr:housenumber":"282",
    "addr:postcode":"05151",
    "addr:street":"Maple St",
    "iso:country":"US",
    "sg:address":"282 Maple St",
    "sg:city":"Perkinsville",
    "sg:classifiers":[
        {
            "category":"Government",
            "subcategory":"Office",
            "type":"Public Place"
        }
    ],
    "sg:phone":"+1 802 263 5272",
    "sg:postcode":"05151",
    "sg:province":"VT",
    "sg:tags":[
        "village"
    ],
    "wof:name":"Town Garage",
    "wof:placetype":"venue"
},
  "geometry": {"coordinates":[-72.512146,43.368262],"type":"Point"}
}