{
  "type": "Feature",
  "properties": {
    "addr:full":"207 Park St Burlington VT 05401",
    "addr:housenumber":"207",
    "addr:postcode":"05401",
    "addr:street":"Park St",
    "iso:country":"US",
    "sg:address":"207 Park St",
    "sg:city":"Burlington",
    "sg:classifiers":[
        {
            "category":"Professional",
            "subcategory":"Business Services",
            "type":"Services"
        }
    ],
    "sg:phone":"+1 802 865 1794",
    "sg:postcode":"05401",
    "sg:province":"VT",
    "wof:name":"Third Sector Associates",
    "wof:placetype":"venue"
},
  "geometry": {"coordinates":[-73.21950200000001,44.487326],"type":"Point"}
}