{
  "type": "Feature",
  "properties": {
    "iso:country":"US",
    "sg:address":"54 Shaw Mansion Rd",
    "sg:city":"Waterbury Center",
    "sg:classifiers":[
        {
            "category":"Wholesale",
            "subcategory":"Electrical",
            "type":"Manufacturing & Wholesale Goods"
        }
    ],
    "sg:phone":"+1 802 244 1787",
    "sg:postcode":"05677",
    "sg:province":"VT",
    "sg:tags":[
        "alarm",
        "burglar",
        "system"
    ],
    "wof:name":"Alarm Control Instruments",
    "wof:placetype":"venue"
},
  "geometry": {"coordinates":[-72.70044300000001,44.35916],"type":"Point"}
}