{
  "type": "Feature",
  "properties": {
    "iso:country":"US",
    "sg:address":"25 Butler Dr",
    "sg:city":"South Burlington",
    "sg:classifiers":[
        {
            "category":"Professional",
            "subcategory":"Research",
            "type":"Services"
        }
    ],
    "sg:phone":"+1 802 863 4296",
    "sg:postcode":"05403",
    "sg:province":"VT",
    "sg:tags":[
        "consulting",
        "i",
        "turn",
        "conservation",
        "economic",
        "key"
    ],
    "wof:name":"Green Light Energy Inc",
    "wof:placetype":"venue"
},
  "geometry": {"coordinates":[-73.16135300000001,44.435014],"type":"Point"}
}