{
  "type": "Feature",
  "properties": {
    "iso:country":"US",
    "sg:address":"4318 Main St",
    "sg:city":"Waitsfield",
    "sg:classifiers":[
        {
            "category":"Social Services",
            "subcategory":"Child Care",
            "type":"Services"
        }
    ],
    "sg:phone":"+1 802 496 9352",
    "sg:postcode":"05673",
    "sg:province":"VT",
    "wof:name":"Little Faces Daycare",
    "wof:placetype":"venue"
},
  "geometry": {"coordinates":[-72.829162,44.18867],"type":"Point"}
}