{
  "type": "Feature",
  "properties": {
    "addr:full":"555 Shelburne Rd Burlington VT 05401",
    "addr:housenumber":"555",
    "addr:postcode":"05401",
    "addr:street":"Shelburne Rd",
    "iso:country":"US",
    "sg:address":"555 Shelburne Rd",
    "sg:city":"Burlington",
    "sg:classifiers":[
        {
            "category":"Home & Garden",
            "subcategory":"Furniture",
            "type":"Retail Goods"
        }
    ],
    "sg:phone":"+1 802 865 9911",
    "sg:postcode":"05401",
    "sg:province":"VT",
    "wof:name":"Ashley Home Store",
    "wof:placetype":"venue"
},
  "geometry": {"coordinates":[-73.20929599999999,44.448468],"type":"Point"}
}