{
  "type": "Feature",
  "properties": {
    "iso:country":"US",
    "sg:address":"72 Castle Hill Rd",
    "sg:city":"Wilmington",
    "sg:classifiers":[
        {
            "category":"Manufacturing",
            "subcategory":"Wood Products",
            "type":"Manufacturing & Wholesale Goods"
        },
        {
            "category":"Building & Trades",
            "subcategory":"Construction",
            "type":"Services"
        }
    ],
    "sg:phone":"+1 802 464 8392",
    "sg:postcode":"05363",
    "sg:province":"VT",
    "sg:tags":[
        "millwork-wholesale",
        "manufacturer",
        "carpenter",
        "millwork"
    ],
    "sg:website":"http://www.ericsprenger.com",
    "wof:name":"Eric Sprenger Fine Woodworking",
    "wof:placetype":"venue"
},
  "geometry": {"coordinates":[-72.87969699999999,42.866476],"type":"Point"}
}