{
  "type": "Feature",
  "properties": {
    "addr:full":"19 Church St Burlington VT 05401",
    "addr:housenumber":"19",
    "addr:postcode":"05401",
    "addr:street":"Church St",
    "iso:country":"US",
    "sg:address":"19 Church St",
    "sg:city":"Burlington",
    "sg:classifiers":[
        {
            "category":"Building & Trades",
            "subcategory":"Cleaning & Sanitation",
            "type":"Services"
        }
    ],
    "sg:phone":"+1 802 951 5800",
    "sg:postcode":"05401",
    "sg:province":"VT",
    "sg:tags":[
        "janitor"
    ],
    "wof:name":"First Choice Restoration",
    "wof:placetype":"venue"
},
  "geometry": {"coordinates":[-73.212813,44.479727],"type":"Point"}
}