{
  "type": "Feature",
  "properties": {
    "iso:country":"US",
    "sg:address":"698 Putney Rd",
    "sg:city":"Brattleboro",
    "sg:classifiers":[
        {
            "category":"Recreation",
            "type":"Entertainment"
        }
    ],
    "sg:phone":"+1 802 257 4797",
    "sg:postcode":"05301",
    "sg:province":"VT",
    "sg:tags":[
        "martial",
        "arts",
        "instruction"
    ],
    "wof:name":"Brattleboro School Of Budo",
    "wof:placetype":"venue"
},
  "geometry": {"coordinates":[-72.55710000000001,42.868338],"type":"Point"}
}