{
  "type": "Feature",
  "properties": {
    "iso:country":"US",
    "sg:address":"64 Chester Rd",
    "sg:city":"Springfield",
    "sg:classifiers":[
        {
            "category":"Professional",
            "subcategory":"Lawyer & Legal Services",
            "type":"Services"
        }
    ],
    "sg:phone":"+1 802 885 4530",
    "sg:postcode":"05156",
    "sg:province":"VT",
    "sg:tags":[
        "attorney"
    ],
    "wof:name":"Barry J Polidor PC",
    "wof:placetype":"venue"
},
  "geometry": {"coordinates":[-72.502692,43.299211],"type":"Point"}
}