{
  "type": "Feature",
  "properties": {
    "iso:country":"US",
    "sg:address":"98 Reservoir Rd",
    "sg:city":"Springfield",
    "sg:classifiers":[
        {
            "category":"Government",
            "subcategory":"Office",
            "type":"Public Place"
        }
    ],
    "sg:phone":"+1 802 886 2775",
    "sg:postcode":"05156",
    "sg:province":"VT",
    "sg:tags":[
        "federal"
    ],
    "wof:name":"US Army Corps Of Engineers",
    "wof:placetype":"venue"
},
  "geometry": {"coordinates":[-72.502005,43.342867],"type":"Point"}
}