{
  "type": "Feature",
  "properties": {
    "iso:country":"US",
    "sg:address":"11 Killoran Dr",
    "sg:city":"Essex Junction",
    "sg:classifiers":[
        {
            "category":"Building & Trades",
            "subcategory":"Landscaping Services",
            "type":"Services"
        }
    ],
    "sg:phone":"+1 802 879 0000",
    "sg:postcode":"05452",
    "sg:province":"VT",
    "sg:tags":[
        "supply"
    ],
    "wof:name":"Shade Tree Associates Inc",
    "wof:placetype":"venue"
},
  "geometry": {"coordinates":[-73.124809,44.494958],"type":"Point"}
}