{
  "type": "Feature",
  "properties": {
    "iso:country":"US",
    "sg:address":"2025 Waterbury Rd",
    "sg:city":"Stowe",
    "sg:classifiers":[
        {
            "category":"Retail",
            "subcategory":"Auto Repair",
            "type":"Services"
        }
    ],
    "sg:phone":"+1 802 253 7239",
    "sg:postcode":"05672",
    "sg:province":"VT",
    "sg:tags":[
        "body",
        "automobile",
        "painting"
    ],
    "wof:name":"Nichols Sales & Svc Inc",
    "wof:placetype":"venue"
},
  "geometry": {"coordinates":[-72.71708700000001,44.427506],"type":"Point"}
}