{
  "type": "Feature",
  "properties": {
    "iso:country":"US",
    "sg:address":"164 S Main St",
    "sg:city":"Barre",
    "sg:classifiers":[
        {
            "category":"Banks & Credit Unions",
            "subcategory":"Bank",
            "type":"Services"
        }
    ],
    "sg:phone":"+1 802 476 5951",
    "sg:postcode":"05641",
    "sg:province":"VT",
    "sg:tags":[
        "loan",
        "real estate"
    ],
    "wof:name":"Universal Mortgage",
    "wof:placetype":"venue"
},
  "geometry": {"coordinates":[-72.498563,44.187259],"type":"Point"}
}