{
  "type": "Feature",
  "properties": {
    "iso:country":"US",
    "sg:address":"424 Bent Rd",
    "sg:city":"Marshfield",
    "sg:classifiers":[
        {
            "category":"Manufacturing",
            "subcategory":"Food",
            "type":"Manufacturing & Wholesale Goods"
        }
    ],
    "sg:phone":"+1 802 426 3234",
    "sg:postcode":"05658",
    "sg:province":"VT",
    "sg:tags":[
        "beef",
        "mfg",
        "farm",
        "eggs",
        "dairy",
        "cattle",
        "pickle"
    ],
    "wof:name":"Hill Farm of Vermont",
    "wof:placetype":"venue"
},
  "geometry": {"coordinates":[-72.388453,44.329439],"type":"Point"}
}