{
  "type": "Feature",
  "properties": {
    "iso:country":"US",
    "sg:address":"467 W Milton Rd",
    "sg:city":"Milton",
    "sg:classifiers":[
        {
            "category":"Real Estate",
            "subcategory":"Real Estate Operator",
            "type":"Services"
        }
    ],
    "sg:phone":"+1 802 893 7952",
    "sg:postcode":"05468",
    "sg:province":"VT",
    "sg:tags":[
        "building",
        "house",
        "apartment"
    ],
    "wof:name":"J M Rowley Corp",
    "wof:placetype":"venue"
},
  "geometry": {"coordinates":[-73.175614,44.622363],"type":"Point"}
}