{
  "type": "Feature",
  "properties": {
    "addr:full":"2263 Greenbush Rd North Ferrisburg VT 05473",
    "addr:housenumber":"2263",
    "addr:postcode":"05473",
    "addr:street":"Greenbush Rd",
    "iso:country":"US",
    "sg:address":"2263 Greenbush Rd",
    "sg:city":"North Ferrisburg",
    "sg:classifiers":[
        {
            "category":"Freight",
            "type":"Transportation"
        }
    ],
    "sg:phone":"+1 802 425 3020",
    "sg:postcode":"05473",
    "sg:province":"VT",
    "sg:tags":[
        "petroleum",
        "transport"
    ],
    "wof:name":"J A Devos & Sons Inc",
    "wof:placetype":"venue"
},
  "geometry": {"coordinates":[-73.247726,44.254453],"type":"Point"}
}