{
  "type": "Feature",
  "properties": {
    "iso:country":"US",
    "sg:address":"48 West Rd",
    "sg:city":"Manchester",
    "sg:classifiers":[
        {
            "category":"Education",
            "subcategory":"Library",
            "type":"Public Place"
        }
    ],
    "sg:phone":"+1 802 362 2607",
    "sg:postcode":"05254",
    "sg:province":"VT",
    "wof:name":"Mark Skinner Library",
    "wof:placetype":"venue"
},
  "geometry": {"coordinates":[-73.07198099999999,43.16597],"type":"Point"}
}