{
  "type": "Feature",
  "properties": {
    "addr:full":"2071 Williston Rd South Burlington VT 05403",
    "addr:housenumber":"2071",
    "addr:postcode":"05403",
    "addr:street":"Williston Rd",
    "iso:country":"US",
    "sg:address":"2071 Williston Rd",
    "sg:city":"South Burlington",
    "sg:classifiers":[
        {
            "category":"Retail",
            "subcategory":"Auto Rental",
            "type":"Services"
        }
    ],
    "sg:phone":"+1 802 862 0200",
    "sg:postcode":"05403",
    "sg:province":"VT",
    "sg:tags":[
        "passenger",
        "paper",
        "car"
    ],
    "wof:name":"Rent-A-Wreck",
    "wof:placetype":"venue"
},
  "geometry": {"coordinates":[-73.154073,44.462951],"type":"Point"}
}