{
  "type": "Feature",
  "properties": {
    "addr:full":"23 W 2nd St Barre VT 05641",
    "addr:housenumber":"23",
    "addr:postcode":"05641",
    "addr:street":"W 2Nd St",
    "iso:country":"US",
    "sg:address":"23 W 2nd St",
    "sg:city":"Barre",
    "sg:phone":"+1 802 479 1200",
    "sg:postcode":"05641",
    "sg:province":"VT",
    "sg:tags":[
        "equipment",
        "station"
    ],
    "wof:name":"Safety-Kleen Corp",
    "wof:placetype":"venue"
},
  "geometry": {"coordinates":[-72.51306,44.20712],"type":"Point"}
}