{
  "type": "Feature",
  "properties": {
    "iso:country":"US",
    "sg:address":"29 Barber Ter",
    "sg:city":"South Burlington",
    "sg:classifiers":[
        {
            "category":"Professional",
            "subcategory":"Engineering",
            "type":"Services"
        }
    ],
    "sg:phone":"+1 802 658 4044",
    "sg:postcode":"05403",
    "sg:province":"VT",
    "wof:name":"Wolbach Engineering Inc",
    "wof:placetype":"venue"
},
  "geometry": {"coordinates":[-73.16192100000001,44.469138],"type":"Point"}
}