{
  "type": "Feature",
  "properties": {
    "addr:full":"21 Curtis Ave Rutland VT 05701",
    "addr:housenumber":"21",
    "addr:postcode":"05701",
    "addr:street":"Curtis Ave",
    "iso:country":"US",
    "sg:address":"21 Curtis Ave",
    "sg:city":"Rutland",
    "sg:classifiers":[
        {
            "category":"Retail",
            "subcategory":"Auto Rental",
            "type":"Services"
        }
    ],
    "sg:phone":"+1 802 773 5901",
    "sg:postcode":"05701",
    "sg:province":"VT",
    "sg:tags":[
        "renting",
        "automobile"
    ],
    "wof:name":"Thrifty Car Rental",
    "wof:placetype":"venue"
},
  "geometry": {"coordinates":[-72.968198,43.591961],"type":"Point"}
}