{
  "type": "Feature",
  "properties": {
    "iso:country":"US",
    "sg:address":"101 Church St",
    "sg:city":"Burlington",
    "sg:classifiers":[
        {
            "category":"Food & Beverages",
            "subcategory":"Candy",
            "type":"Retail Goods"
        }
    ],
    "sg:phone":"+1 802 864 4457",
    "sg:postcode":"05401",
    "sg:province":"VT",
    "sg:tags":[
        "confectionery"
    ],
    "wof:name":"Sweet Thing",
    "wof:placetype":"venue"
},
  "geometry": {"coordinates":[-73.212504,44.475093],"type":"Point"}
}