{
  "type": "Feature",
  "properties": {
    "iso:country":"US",
    "sg:address":"101 Main St",
    "sg:city":"Ludlow",
    "sg:classifiers":[
        {
            "category":"Insurance",
            "subcategory":"Insurance Agent",
            "type":"Services"
        }
    ],
    "sg:phone":"+1 802 228 3733",
    "sg:postcode":"05149",
    "sg:province":"VT",
    "wof:name":"Finn & Stone Inc",
    "wof:placetype":"venue"
},
  "geometry": {"coordinates":[-72.697553,43.396139],"type":"Point"}
}