{
  "type": "Feature",
  "properties": {
    "iso:country":"US",
    "sg:address":"144 Nudist Camp Rd",
    "sg:city":"Chester",
    "sg:classifiers":[
        {
            "category":"Retail",
            "subcategory":"Repair Shop",
            "type":"Services"
        }
    ],
    "sg:phone":"+1 802 875 4949",
    "sg:postcode":"05143",
    "sg:province":"VT",
    "wof:name":"Finishing Touches",
    "wof:placetype":"venue"
},
  "geometry": {"coordinates":[-72.6677,43.237175],"type":"Point"}
}