{
  "type": "Feature",
  "properties": {
    "iso:country":"US",
    "sg:address":"241 S Main St",
    "sg:city":"Montgomery Ctr",
    "sg:classifiers":[
        {
            "category":"Restaurant",
            "type":"Food & Drink"
        }
    ],
    "sg:phone":"+1 802 326 4391",
    "sg:postcode":"05471",
    "sg:province":"VT",
    "sg:website":"www.troutinn.com",
    "wof:name":"Inn On Trout River",
    "wof:placetype":"venue"
},
  "geometry": {"coordinates":[-72.607401,44.874118],"type":"Point"}
}