{
  "type": "Feature",
  "properties": {
    "iso:country":"US",
    "sg:address":"891 E Burke Rd",
    "sg:city":"Lyndonville",
    "sg:classifiers":[
        {
            "category":"Retail",
            "subcategory":"Auto Repair",
            "type":"Services"
        }
    ],
    "sg:phone":"+1 802 626 3282",
    "sg:postcode":"05851",
    "sg:province":"VT",
    "sg:tags":[
        "repairing",
        "automobile"
    ],
    "wof:name":"Burke View Garage",
    "wof:placetype":"venue"
},
  "geometry": {"coordinates":[-71.970528,44.553987],"type":"Point"}
}