{
  "type": "Feature",
  "properties": {
    "iso:country":"US",
    "sg:address":"336 Malletts Bay Ave",
    "sg:city":"Colchester",
    "sg:classifiers":[
        {
            "category":"Wholesale",
            "subcategory":"Electrical",
            "type":"Manufacturing & Wholesale Goods"
        }
    ],
    "sg:phone":"+1 802 863 1800",
    "sg:postcode":"05446",
    "sg:province":"VT",
    "sg:tags":[
        "control"
    ],
    "wof:name":"Temperature Control Of Vermont",
    "wof:placetype":"venue"
},
  "geometry": {"coordinates":[-73.208449,44.533753],"type":"Point"}
}