{
  "type": "Feature",
  "properties": {
    "iso:country":"US",
    "sg:address":"35 Sherry Rd",
    "sg:city":"South Burlington",
    "sg:classifiers":[
        {
            "category":"Building & Trades",
            "subcategory":"Construction",
            "type":"Services"
        }
    ],
    "sg:phone":"+1 802 657 0011",
    "sg:postcode":"05403",
    "sg:province":"VT",
    "sg:tags":[
        "contractor"
    ],
    "wof:name":"B&B Roofing",
    "wof:placetype":"venue"
},
  "geometry": {"coordinates":[-73.181113,44.459503],"type":"Point"}
}