{
  "type": "Feature",
  "properties": {
    "iso:country":"US",
    "sg:address":"1593 Hardscrabble Rd",
    "sg:city":"Bristol",
    "sg:classifiers":[
        {
            "category":"Real Estate",
            "subcategory":"Real Estate Operator",
            "type":"Services"
        }
    ],
    "sg:phone":"+1 802 453 2226",
    "sg:postcode":"05443",
    "sg:province":"VT",
    "sg:tags":[
        "property",
        "lessor"
    ],
    "wof:name":"Livingston Farm",
    "wof:placetype":"venue"
},
  "geometry": {"coordinates":[-73.119163,44.180309],"type":"Point"}
}