{
  "type": "Feature",
  "properties": {
    "iso:country":"US",
    "sg:address":"21 Lunde Ln",
    "sg:city":"Barre",
    "sg:classifiers":[
        {
            "category":"Organizations",
            "subcategory":"Professional Association",
            "type":"Services"
        }
    ],
    "sg:phone":"+1 802 476 7633",
    "sg:postcode":"05641",
    "sg:province":"VT",
    "sg:tags":[
        "pharmacist"
    ],
    "wof:name":"Vermont Pharmacists Assn",
    "wof:placetype":"venue"
},
  "geometry": {"coordinates":[-72.508481,44.207118],"type":"Point"}
}