{
  "type": "Feature",
  "properties": {
    "iso:country":"US",
    "sg:address":"50 Shelburnewood Dr",
    "sg:city":"Shelburne",
    "sg:classifiers":[
        {
            "category":"Food & Beverages",
            "subcategory":"Specialty",
            "type":"Retail Goods"
        }
    ],
    "sg:phone":"+1 802 985 4118",
    "sg:postcode":"05482",
    "sg:province":"VT",
    "sg:tags":[
        "vitamin"
    ],
    "wof:name":"Vitamin Connection",
    "wof:placetype":"venue"
},
  "geometry": {"coordinates":[-73.22728499999999,44.380598],"type":"Point"}
}