{
  "type": "Feature",
  "properties": {
    "addr:full":"95 Oak St St Johnsbury VT 05819",
    "addr:housenumber":"95",
    "addr:postcode":"05819",
    "addr:street":"Oak St",
    "iso:country":"US",
    "sg:address":"95 Oak St",
    "sg:city":"St Johnsbury",
    "sg:classifiers":[
        {
            "category":"Professional",
            "subcategory":"Business Services",
            "type":"Services"
        }
    ],
    "sg:phone":"+1 802 748 1144",
    "sg:postcode":"05819",
    "sg:province":"VT",
    "sg:tags":[
        "organizing"
    ],
    "wof:name":"To Do List",
    "wof:placetype":"venue"
},
  "geometry": {"coordinates":[-72.013857,44.426627],"type":"Point"}
}