{
  "type": "Feature",
  "properties": {
    "iso:country":"US",
    "sg:address":"210 Northside Dr",
    "sg:city":"Bennington",
    "sg:classifiers":[
        {
            "category":"Restaurant",
            "type":"Food & Drink"
        }
    ],
    "sg:menulink":"http://www.allmenus.com/vt/bennington/195715-wendys/menu/",
    "sg:phone":"+1 802 442 2843",
    "sg:postcode":"05201",
    "sg:province":"VT",
    "sg:tags":[
        "burger",
        "american",
        "soup"
    ],
    "wof:name":"Wendy's",
    "wof:placetype":"venue"
},
  "geometry": {"coordinates":[-73.208737,42.898609],"type":"Point"}
}