{
  "type": "Feature",
  "properties": {
    "iso:country":"US",
    "sg:address":"34 Mountain Top Rd",
    "sg:city":"Chittenden",
    "sg:classifiers":[
        {
            "category":"Professional",
            "subcategory":"Lawyer & Legal Services",
            "type":"Services"
        }
    ],
    "sg:phone":"+1 802 483 6650",
    "sg:postcode":"05737",
    "sg:province":"VT",
    "wof:name":"Linda Aylesworth-Reis PC",
    "wof:placetype":"venue"
},
  "geometry": {"coordinates":[-72.947169,43.710302],"type":"Point"}
}