{
  "type": "Feature",
  "properties": {
    "iso:country":"US",
    "sg:address":"1328 Gates Farm Rd",
    "sg:city":"Wolcott",
    "sg:classifiers":[
        {
            "category":"Real Estate",
            "subcategory":"Real Estate Agent",
            "type":"Services"
        }
    ],
    "sg:phone":"+1 802 888 1271",
    "sg:postcode":"05680",
    "sg:province":"VT",
    "sg:tags":[
        "property",
        "company",
        "management"
    ],
    "wof:name":"Pace Properties Inc",
    "wof:placetype":"venue"
},
  "geometry": {"coordinates":[-72.449924,44.524463],"type":"Point"}
}