{
  "type": "Feature",
  "properties": {
    "iso:country":"US",
    "sg:address":"515 Depot St",
    "sg:city":"Manchester Ctr",
    "sg:classifiers":[
        {
            "category":"Home & Garden",
            "subcategory":"Home Furnishings",
            "type":"Retail Goods"
        }
    ],
    "sg:phone":"+1 802 362 0997",
    "sg:postcode":"05255",
    "sg:province":"VT",
    "sg:tags":[
        "glassware",
        "chinaware"
    ],
    "wof:name":"Mikasa",
    "wof:placetype":"venue"
},
  "geometry": {"coordinates":[-73.0483,43.173155],"type":"Point"}
}