{
  "type": "Feature",
  "properties": {
    "iso:country":"US",
    "sg:address":"38 Water St",
    "sg:city":"Orleans",
    "sg:classifiers":[
        {
            "category":"Professional",
            "subcategory":"Lawyer & Legal Services",
            "type":"Services"
        }
    ],
    "sg:phone":"+1 802 754 2200",
    "sg:postcode":"05860",
    "sg:province":"VT",
    "sg:tags":[
        "attorney"
    ],
    "wof:name":"Vincent Illuzzi Law Office",
    "wof:placetype":"venue"
},
  "geometry": {"coordinates":[-72.201914,44.810043],"type":"Point"}
}