{
  "type": "Feature",
  "properties": {
    "addr:full":"2 Lincoln St Essex Junction VT 05452",
    "addr:housenumber":"2",
    "addr:postcode":"05452",
    "addr:street":"Lincoln St",
    "iso:country":"US",
    "sg:address":"2 Lincoln St",
    "sg:city":"Essex Junction",
    "sg:classifiers":[
        {
            "category":"Health Services",
            "subcategory":"Nursing And Care Facility",
            "type":"Services"
        }
    ],
    "sg:phone":"+1 802 879 7135",
    "sg:postcode":"05452",
    "sg:province":"VT",
    "sg:tags":[
        "home",
        "rest"
    ],
    "wof:name":"National Council On The Aging",
    "wof:placetype":"venue"
},
  "geometry": {"coordinates":[-73.11095,44.491071],"type":"Point"}
}