{
  "type": "Feature",
  "properties": {
    "addr:full":"4626 Williston Rd Williston VT 05495",
    "addr:housenumber":"4626",
    "addr:postcode":"05495",
    "addr:street":"Williston Rd",
    "iso:country":"US",
    "sg:address":"4626 Williston Rd",
    "sg:city":"Williston",
    "sg:classifiers":[
        {
            "category":"Wholesale",
            "subcategory":"Motor Vehicles",
            "type":"Manufacturing & Wholesale Goods"
        }
    ],
    "sg:phone":"+1 802 865 2266",
    "sg:postcode":"05495",
    "sg:province":"VT",
    "sg:tags":[
        "commercial",
        "truck"
    ],
    "wof:name":"Superior Trucks USA",
    "wof:placetype":"venue"
},
  "geometry": {"coordinates":[-73.096217,44.443363],"type":"Point"}
}