{
  "type": "Feature",
  "properties": {
    "iso:country":"US",
    "sg:address":"210 Morning Star Ln",
    "sg:city":"Northfield",
    "sg:classifiers":[
        {
            "category":"Education",
            "subcategory":"School",
            "type":"Public Place"
        }
    ],
    "sg:phone":"+1 802 485 4140",
    "sg:postcode":"05663",
    "sg:province":"VT",
    "wof:name":"Institute For Visionary Leader",
    "wof:placetype":"venue"
},
  "geometry": {"coordinates":[-72.730808,44.135638],"type":"Point"}
}