{
  "type": "Feature",
  "properties": {
    "addr:full":"378 McCullough Hill Rd Montpelier VT 05602",
    "addr:housenumber":"378",
    "addr:postcode":"05602",
    "addr:street":"Mccullough Hill Rd",
    "iso:country":"US",
    "sg:address":"378 McCullough Hill Rd",
    "sg:city":"Montpelier",
    "sg:classifiers":[
        {
            "category":"Building & Trades",
            "subcategory":"Construction",
            "type":"Services"
        }
    ],
    "sg:phone":"+1 802 223 7782",
    "sg:postcode":"05602",
    "sg:province":"VT",
    "sg:tags":[
        "house",
        "general",
        "family",
        "contractor"
    ],
    "wof:name":"Vermont Property Improvement",
    "wof:placetype":"venue"
},
  "geometry": {"coordinates":[-72.64980300000001,44.300618],"type":"Point"}
}