{
  "type": "Feature",
  "properties": {
    "iso:country":"US",
    "sg:address":"126 Covered Bridge Rd",
    "sg:city":"North Ferrisburg",
    "sg:classifiers":[
        {
            "category":"Professional",
            "subcategory":"Management & Consulting",
            "type":"Services"
        }
    ],
    "sg:phone":"+1 802 425 2178",
    "sg:postcode":"05473",
    "sg:province":"VT",
    "sg:tags":[
        "environmental"
    ],
    "wof:name":"Phoenix Chemistry Services",
    "wof:placetype":"venue"
},
  "geometry": {"coordinates":[-73.18300600000001,44.266711],"type":"Point"}
}