{
  "type": "Feature",
  "properties": {
    "iso:country":"US",
    "sg:address":"4183 Bonnyvale Rd",
    "sg:city":"Brattleboro",
    "sg:classifiers":[
        {
            "category":"Farming",
            "subcategory":"Livestock Farm",
            "type":"Manufacturing & Wholesale Goods"
        }
    ],
    "sg:phone":"+1 802 257 0267",
    "sg:postcode":"05301",
    "sg:province":"VT",
    "sg:tags":[
        "equine"
    ],
    "wof:name":"Rebeccas Alpacas",
    "wof:placetype":"venue"
},
  "geometry": {"coordinates":[-72.623706,42.806277],"type":"Point"}
}