{
  "type": "Feature",
  "properties": {
    "addr:full":"108 Cherry St Burlington VT 05401",
    "addr:housenumber":"108",
    "addr:postcode":"05401",
    "addr:street":"Cherry St",
    "iso:country":"US",
    "sg:address":"108 Cherry St",
    "sg:city":"Burlington",
    "sg:classifiers":[
        {
            "category":"Health Services",
            "subcategory":"Clinic",
            "type":"Services"
        }
    ],
    "sg:phone":"+1 802 651 1550",
    "sg:postcode":"05401",
    "sg:province":"VT",
    "sg:tags":[
        "consulting",
        "specialty",
        "business",
        "outpatient"
    ],
    "wof:name":"Vermont Department of Health",
    "wof:placetype":"venue"
},
  "geometry": {"coordinates":[-73.21328200000001,44.479354],"type":"Point"}
}