{
  "type": "Feature",
  "properties": {
    "iso:country":"US",
    "sg:address":"1065 Martel Exd",
    "sg:city":"St George",
    "sg:classifiers":[
        {
            "category":"Building & Trades",
            "subcategory":"Landscaping Services",
            "type":"Services"
        }
    ],
    "sg:phone":"+1 802 878 9740",
    "sg:postcode":"05495",
    "sg:province":"VT",
    "sg:tags":[
        "landscape",
        "contractor"
    ],
    "wof:name":"Top Dog Landscaping",
    "wof:placetype":"venue"
},
  "geometry": {"coordinates":[-73.101887,44.377435],"type":"Point"}
}