{
  "type": "Feature",
  "properties": {
    "addr:full":"1169 North Ave Burlington VT 05401",
    "addr:housenumber":"1169",
    "addr:postcode":"05401",
    "addr:street":"North Ave",
    "iso:country":"US",
    "sg:address":"1169 North Ave",
    "sg:city":"Burlington",
    "sg:classifiers":[
        {
            "category":"Shopping",
            "subcategory":"Gifts & Souvenirs",
            "type":"Retail Goods"
        }
    ],
    "sg:phone":"+1 802 658 0435",
    "sg:postcode":"05401",
    "sg:province":"VT",
    "sg:tags":[
        "cards",
        "greeting"
    ],
    "wof:name":"Brooks Pharmacy",
    "wof:placetype":"venue"
},
  "geometry": {"coordinates":[-73.24548799999999,44.507275],"type":"Point"}
}