{
  "type": "Feature",
  "properties": {
    "iso:country":"US",
    "sg:address":"82 S Main St",
    "sg:city":"Waterbury",
    "sg:classifiers":[
        {
            "category":"Professional",
            "type":"Services"
        }
    ],
    "sg:phone":"+1 802 244 5506",
    "sg:postcode":"05676",
    "sg:province":"VT",
    "sg:tags":[
        "establishment"
    ],
    "wof:name":"Pomerleau Agency",
    "wof:placetype":"venue"
},
  "geometry": {"coordinates":[-72.752882,44.334414],"type":"Point"}
}