{
  "type": "Feature",
  "properties": {
    "addr:full":"646 Lake Dunmore Rd Salisbury VT 05769",
    "addr:housenumber":"646",
    "addr:postcode":"05769",
    "addr:street":"Lake Dunmore Rd",
    "iso:country":"US",
    "sg:address":"646 Lake Dunmore Rd",
    "sg:city":"Salisbury",
    "sg:classifiers":[
        {
            "category":"Government",
            "subcategory":"Office",
            "type":"Public Place"
        }
    ],
    "sg:phone":"+1 802 352 4371",
    "sg:postcode":"05769",
    "sg:province":"VT",
    "sg:tags":[
        "hatchery",
        "fish"
    ],
    "wof:name":"Salisbury Hatchery",
    "wof:placetype":"venue"
},
  "geometry": {"coordinates":[-73.098602,43.925979],"type":"Point"}
}