{
  "type": "Feature",
  "properties": {
    "iso:country":"US",
    "sg:address":"732 Buck Hill Rd W",
    "sg:city":"Hinesburg",
    "sg:classifiers":[
        {
            "category":"Building & Trades",
            "subcategory":"Construction",
            "type":"Services"
        }
    ],
    "sg:phone":"+1 802 343 6821",
    "sg:postcode":"05461",
    "sg:province":"VT",
    "sg:tags":[
        "contractor"
    ],
    "wof:name":"A R Dennison General Contr",
    "wof:placetype":"venue"
},
  "geometry": {"coordinates":[-73.084704,44.326954],"type":"Point"}
}