{
  "type": "Feature",
  "properties": {
    "addr:full":"102 Dorset St South Burlington VT 05403",
    "addr:housenumber":"102",
    "addr:postcode":"05403",
    "addr:street":"Dorset St",
    "iso:country":"US",
    "sg:address":"102 Dorset St",
    "sg:city":"South Burlington",
    "sg:classifiers":[
        {
            "category":"Shopping",
            "subcategory":"Books",
            "type":"Retail Goods"
        }
    ],
    "sg:phone":"+1 802 864 8001",
    "sg:postcode":"05403",
    "sg:province":"VT",
    "wof:name":"Barnes & Noble",
    "wof:placetype":"venue"
},
  "geometry": {"coordinates":[-73.18135100000001,44.468418],"type":"Point"}
}