{
  "type": "Feature",
  "properties": {
    "addr:full":"84 Court Sq Middlebury VT 05753",
    "addr:housenumber":"84",
    "addr:postcode":"05753",
    "addr:street":"Court Sq",
    "iso:country":"US",
    "sg:address":"84 Court Sq",
    "sg:city":"Middlebury",
    "sg:classifiers":[
        {
            "category":"Autos & Motor Vehicles",
            "subcategory":"Fuel & Gas Station",
            "type":"Retail Goods"
        }
    ],
    "sg:phone":"+1 802 388 3670",
    "sg:postcode":"05753",
    "sg:province":"VT",
    "sg:tags":[
        "oil"
    ],
    "wof:name":"Citgo Coc Middlebury",
    "wof:placetype":"venue"
},
  "geometry": {"coordinates":[-73.16648499999999,44.014242],"type":"Point"}
}