{
  "type": "Feature",
  "properties": {
    "iso:country":"US",
    "sg:address":"4020 Middle Rd",
    "sg:city":"North Clarendon",
    "sg:classifiers":[
        {
            "category":"Farming",
            "subcategory":"Dairy Farm",
            "type":"Manufacturing & Wholesale Goods"
        }
    ],
    "sg:phone":"+1 802 775 4424",
    "sg:postcode":"05759",
    "sg:province":"VT",
    "wof:name":"Cold River Farm",
    "wof:placetype":"venue"
},
  "geometry": {"coordinates":[-72.97196599999999,43.569339],"type":"Point"}
}