{
  "type": "Feature",
  "properties": {
    "addr:full":"5420 Shelburne Rd Shelburne VT 05482",
    "addr:housenumber":"5420",
    "addr:postcode":"05482",
    "addr:street":"Shelburne Rd",
    "iso:country":"US",
    "sg:address":"5420 Shelburne Rd",
    "sg:city":"Shelburne",
    "sg:classifiers":[
        {
            "category":"Recreation",
            "type":"Entertainment"
        }
    ],
    "sg:phone":"+1 802 985 9551",
    "sg:postcode":"05482",
    "sg:province":"VT",
    "sg:tags":[
        "parks"
    ],
    "wof:name":"Recreation Dept",
    "wof:placetype":"venue"
},
  "geometry": {"coordinates":[-73.22815199999999,44.378668],"type":"Point"}
}