{
  "type": "Feature",
  "properties": {
    "addr:full":"214 School St Fairlee VT 05045",
    "addr:housenumber":"214",
    "addr:postcode":"05045",
    "addr:street":"School St",
    "iso:country":"US",
    "sg:address":"214 School St",
    "sg:city":"Fairlee",
    "sg:classifiers":[
        {
            "category":"Education",
            "subcategory":"School",
            "type":"Public Place"
        }
    ],
    "sg:phone":"+1 802 333 9755",
    "sg:postcode":"05045",
    "sg:province":"VT",
    "sg:website":"www.rivendellschool.org",
    "wof:name":"Samuel Morey Elementary School",
    "wof:placetype":"venue"
},
  "geometry": {"coordinates":[-72.147757,43.907304],"type":"Point"}
}