{
  "type": "Feature",
  "properties": {
    "addr:full":"1669 Mountain Rd Stowe VT 05672",
    "addr:housenumber":"1669",
    "addr:postcode":"05672",
    "addr:street":"Mountain Rd",
    "iso:country":"US",
    "sg:address":"1669 Mountain Rd",
    "sg:city":"Stowe",
    "sg:classifiers":[
        {
            "category":"Retail",
            "subcategory":"Animal Services",
            "type":"Services"
        }
    ],
    "sg:phone":"+1 802 253 7785",
    "sg:postcode":"05672",
    "sg:province":"VT",
    "sg:tags":[
        "pet"
    ],
    "wof:name":"Stowe Dogs",
    "wof:placetype":"venue"
},
  "geometry": {"coordinates":[-72.70851,44.47255],"type":"Point"}
}