{
  "type": "Feature",
  "properties": {
    "iso:country":"US",
    "sg:address":"18 Montvert Rd",
    "sg:city":"Middletown Spgs",
    "sg:classifiers":[
        {
            "category":"Building & Trades",
            "subcategory":"Construction",
            "type":"Services"
        }
    ],
    "sg:phone":"+1 802 235 2301",
    "sg:postcode":"05757",
    "sg:province":"VT",
    "sg:tags":[
        "masonry",
        "contractor"
    ],
    "wof:name":"Theron Krouse",
    "wof:placetype":"venue"
},
  "geometry": {"coordinates":[-73.11714000000001,43.482377],"type":"Point"}
}