{
  "type": "Feature",
  "properties": {
    "iso:country":"US",
    "sg:address":"4 White Birch Dr",
    "sg:city":"Springfield",
    "sg:classifiers":[
        {
            "category":"Real Estate",
            "subcategory":"Real Estate Agent",
            "type":"Services"
        }
    ],
    "sg:phone":"+1 802 886 3100",
    "sg:postcode":"05156",
    "sg:province":"VT",
    "wof:name":"Pedden Acres Real Estate",
    "wof:placetype":"venue"
},
  "geometry": {"coordinates":[-72.5056,43.324435],"type":"Point"}
}