{
  "type": "Feature",
  "properties": {
    "addr:full":"91 West St Proctor VT 05765",
    "addr:housenumber":"91",
    "addr:postcode":"05765",
    "addr:street":"West St",
    "iso:country":"US",
    "sg:address":"91 West St",
    "sg:city":"Proctor",
    "sg:classifiers":[
        {
            "category":"Building & Trades",
            "subcategory":"Construction",
            "type":"Services"
        }
    ],
    "sg:phone":"+1 802 459 2029",
    "sg:postcode":"05765",
    "sg:province":"VT",
    "sg:tags":[
        "house",
        "construct",
        "contractor"
    ],
    "wof:name":"Bruce Carringtion Exterior Hom",
    "wof:placetype":"venue"
},
  "geometry": {"coordinates":[-73.04286,43.650247],"type":"Point"}
}