{
  "type": "Feature",
  "properties": {
    "iso:country":"US",
    "sg:address":"98 Carroll Rd",
    "sg:city":"Waitsfield",
    "sg:classifiers":[
        {
            "category":"Manufacturing",
            "subcategory":"Signs",
            "type":"Manufacturing & Wholesale Goods"
        }
    ],
    "sg:phone":"+1 802 496 2318",
    "sg:postcode":"05673",
    "sg:province":"VT",
    "wof:name":"Wood & Wood",
    "wof:placetype":"venue"
},
  "geometry": {"coordinates":[-72.834282,44.187864],"type":"Point"}
}