{
  "type": "Feature",
  "properties": {
    "iso:country":"US",
    "sg:address":"27 Missisquoi St",
    "sg:city":"Enosburg Falls",
    "sg:classifiers":[
        {
            "category":"Home & Garden",
            "subcategory":"Household Appliances",
            "type":"Retail Goods"
        }
    ],
    "sg:phone":"+1 802 933 2082",
    "sg:postcode":"05450",
    "sg:province":"VT",
    "wof:name":"Deuso Appliance Svc",
    "wof:placetype":"venue"
},
  "geometry": {"coordinates":[-72.80465599999999,44.906955],"type":"Point"}
}