{
  "type": "Feature",
  "properties": {
    "addr:full":"424 Westford Rd Milton VT 05468",
    "addr:housenumber":"424",
    "addr:postcode":"05468",
    "addr:street":"Westford Rd",
    "iso:country":"US",
    "sg:address":"424 Westford Rd",
    "sg:city":"Milton",
    "sg:classifiers":[
        {
            "category":"Building & Trades",
            "subcategory":"Construction",
            "type":"Services"
        }
    ],
    "sg:phone":"+1 802 893 7263",
    "sg:postcode":"05468",
    "sg:province":"VT",
    "sg:tags":[
        "general",
        "contractor"
    ],
    "wof:name":"Billado Construction & Prprty",
    "wof:placetype":"venue"
},
  "geometry": {"coordinates":[-73.06244599999999,44.643411],"type":"Point"}
}