{
  "type": "Feature",
  "properties": {
    "iso:country":"US",
    "sg:address":"207 Main St",
    "sg:city":"Ludlow",
    "sg:classifiers":[
        {
            "category":"Shopping",
            "subcategory":"Bicycles & Sporting Goods",
            "type":"Retail Goods"
        }
    ],
    "sg:phone":"+1 802 228 2003",
    "sg:postcode":"05149",
    "sg:province":"VT",
    "sg:tags":[
        "snowboard"
    ],
    "wof:name":"Odyssey Board Shop",
    "wof:placetype":"venue"
},
  "geometry": {"coordinates":[-72.70300400000001,43.395974],"type":"Point"}
}