{
  "type": "Feature",
  "properties": {
    "iso:country":"US",
    "sg:address":"357 Western Ave",
    "sg:city":"Saint Johnsbury",
    "sg:classifiers":[
        {
            "category":"Health Services",
            "subcategory":"Clinic",
            "type":"Services"
        }
    ],
    "sg:phone":"+1 802 748 8194",
    "sg:postcode":"05819",
    "sg:province":"VT",
    "sg:tags":[
        "planning",
        "family"
    ],
    "wof:name":"Planned Prnthood of Nthrn Neng",
    "wof:placetype":"venue"
},
  "geometry": {"coordinates":[-72.026822,44.417632],"type":"Point"}
}