{
  "type": "Feature",
  "properties": {
    "iso:country":"US",
    "sg:address":"134 Portland St",
    "sg:city":"St Johnsbury",
    "sg:classifiers":[
        {
            "category":"Professional",
            "type":"Services"
        }
    ],
    "sg:phone":"+1 802 748 1943",
    "sg:postcode":"05819",
    "sg:province":"VT",
    "sg:tags":[
        "establishment"
    ],
    "wof:name":"Portland Street Valero",
    "wof:placetype":"venue"
},
  "geometry": {"coordinates":[-72.013333,44.419675],"type":"Point"}
}