{
  "type": "Feature",
  "properties": {
    "addr:full":"110 Center Rd Albany VT 05820",
    "addr:housenumber":"110",
    "addr:postcode":"05820",
    "addr:street":"Center Rd",
    "iso:country":"US",
    "sg:address":"110 Center Rd",
    "sg:city":"Albany",
    "sg:classifiers":[
        {
            "category":"Professional",
            "subcategory":"Lawyer & Legal Services",
            "type":"Services"
        }
    ],
    "sg:phone":"+1 802 755 6200",
    "sg:postcode":"05820",
    "sg:province":"VT",
    "sg:tags":[
        "attorney"
    ],
    "wof:name":"Ruth Oberg Law Office",
    "wof:placetype":"venue"
},
  "geometry": {"coordinates":[-72.359128,44.727649],"type":"Point"}
}