{
  "type": "Feature",
  "properties": {
    "addr:full":"162 Chocolate Moose Ln Lyndonville VT 05851",
    "addr:housenumber":"162",
    "addr:postcode":"05851",
    "addr:street":"Chocolate Moose Ln",
    "iso:country":"US",
    "sg:address":"162 Chocolate Moose Ln",
    "sg:city":"Lyndonville",
    "sg:classifiers":[
        {
            "category":"Manufacturing",
            "subcategory":"Retail Goods",
            "type":"Manufacturing & Wholesale Goods"
        }
    ],
    "sg:phone":"+1 802 626 8346",
    "sg:postcode":"05851",
    "sg:province":"VT",
    "sg:tags":[
        "manufacturer"
    ],
    "wof:name":"Authentic Scotch Shortbreads",
    "wof:placetype":"venue"
},
  "geometry": {"coordinates":[-72.021317,44.527748],"type":"Point"}
}