{
  "type": "Feature",
  "properties": {
    "addr:full":"1147 Hartford Ave White River Jct VT 05001",
    "addr:housenumber":"1147",
    "addr:postcode":"05001",
    "addr:street":"Hartford Ave",
    "iso:country":"US",
    "sg:address":"1147 Hartford Ave",
    "sg:city":"White River Jct",
    "sg:classifiers":[
        {
            "category":"Restaurant",
            "type":"Food & Drink"
        }
    ],
    "sg:phone":"+1 802 295 5393",
    "sg:postcode":"05001",
    "sg:province":"VT",
    "sg:tags":[
        "supply",
        "seafood",
        "caterer",
        "party",
        "retail",
        "rental"
    ],
    "wof:name":"Blood's Seafood Catering",
    "wof:placetype":"venue"
},
  "geometry": {"coordinates":[-72.313069,43.663334],"type":"Point"}
}