{
  "type": "Feature",
  "properties": {
    "addr:full":"11 Checkerberry Sq Milton VT 05468",
    "addr:housenumber":"11",
    "addr:postcode":"05468",
    "addr:street":"Checkerberry Sq",
    "iso:country":"US",
    "sg:address":"11 Checkerberry Sq",
    "sg:city":"Milton",
    "sg:classifiers":[
        {
            "category":"Freight",
            "type":"Transportation"
        }
    ],
    "sg:phone":"+1 802 893 2313",
    "sg:postcode":"05468",
    "sg:province":"VT",
    "sg:tags":[
        "commercial",
        "storage"
    ],
    "wof:name":"Milton Mini-Storage",
    "wof:placetype":"venue"
},
  "geometry": {"coordinates":[-73.13947,44.62806],"type":"Point"}
}