{
  "type": "Feature",
  "properties": {
    "iso:country":"US",
    "sg:address":"138 Pleasant St",
    "sg:city":"South Ryegate",
    "sg:classifiers":[
        {
            "category":"Retail",
            "subcategory":"Repair Shop",
            "type":"Services"
        }
    ],
    "sg:phone":"+1 802 584 4612",
    "sg:postcode":"05069",
    "sg:province":"VT",
    "sg:tags":[
        "equipment",
        "coffee",
        "sales"
    ],
    "wof:name":"Brew Tech Inc",
    "wof:placetype":"venue"
},
  "geometry": {"coordinates":[-72.13731300000001,44.185399],"type":"Point"}
}