{
  "type": "Feature",
  "properties": {
    "iso:country":"US",
    "sg:address":"125 Staniford Rd",
    "sg:city":"Burlington",
    "sg:classifiers":[
        {
            "category":"Real Estate",
            "subcategory":"Real Estate Agent",
            "type":"Services"
        }
    ],
    "sg:phone":"+1 802 862 7178",
    "sg:postcode":"05408",
    "sg:province":"VT",
    "wof:name":"Cjc Enterprises Inc",
    "wof:placetype":"venue"
},
  "geometry": {"coordinates":[-72.345586,44.384797],"type":"Point"}
}