{
  "type": "Feature",
  "properties": {
    "addr:full":"82 State Rte 12 Montpelier VT 05602",
    "addr:housenumber":"82",
    "addr:postcode":"05602",
    "addr:street":"State Rte 12",
    "iso:country":"US",
    "sg:address":"82 State Rte 12",
    "sg:city":"Montpelier",
    "sg:classifiers":[
        {
            "category":"Farming",
            "subcategory":"Nursery",
            "type":"Manufacturing & Wholesale Goods"
        }
    ],
    "sg:phone":"+1 802 229 2345",
    "sg:postcode":"05602",
    "sg:province":"VT",
    "sg:tags":[
        "ornamental"
    ],
    "wof:name":"Edward Peterson",
    "wof:placetype":"venue"
},
  "geometry": {"coordinates":[-72.57572999999999,44.259689],"type":"Point"}
}