{
  "type": "Feature",
  "properties": {
    "addr:full":"2466 St George Rd Williston VT 05495",
    "addr:housenumber":"2466",
    "addr:postcode":"05495",
    "addr:street":"St George Rd",
    "iso:country":"US",
    "sg:address":"2466 St George Rd",
    "sg:city":"Williston",
    "sg:classifiers":[
        {
            "category":"Autos & Motor Vehicles",
            "subcategory":"Automobile Sales",
            "type":"Retail Goods"
        }
    ],
    "sg:phone":"+1 802 878 3391",
    "sg:postcode":"05495",
    "sg:province":"VT",
    "sg:tags":[
        "car",
        "dealer"
    ],
    "sg:website":"www.importedcarcenter.com",
    "wof:name":"Imported Car Ctr",
    "wof:placetype":"venue"
},
  "geometry": {"coordinates":[-73.110969,44.447276],"type":"Point"}
}