{
  "type": "Feature",
  "properties": {
    "addr:full":"8411 State Rte 111 Morgan VT 05853",
    "addr:housenumber":"8411",
    "addr:postcode":"05853",
    "addr:street":"State Rte 111",
    "iso:country":"US",
    "sg:address":"8411 State Rte 111",
    "sg:city":"Morgan",
    "sg:classifiers":[
        {
            "category":"Shopping",
            "subcategory":"Discount & Variety Stores",
            "type":"Retail Goods"
        }
    ],
    "sg:phone":"+1 802 895 2726",
    "sg:postcode":"05853",
    "sg:province":"VT",
    "sg:tags":[
        "merchandise",
        "general"
    ],
    "wof:name":"Morgan Country Store",
    "wof:placetype":"venue"
},
  "geometry": {"coordinates":[-72.01414200000001,44.912978],"type":"Point"}
}