{
  "type": "Feature",
  "properties": {
    "iso:country":"US",
    "sg:address":"13 Kilburn St",
    "sg:city":"Burlington",
    "sg:classifiers":[
        {
            "category":"Organizations",
            "subcategory":"Professional Association",
            "type":"Services"
        }
    ],
    "sg:phone":"+1 802 660 9001",
    "sg:postcode":"05401",
    "sg:province":"VT",
    "wof:name":"Vermont Lodge & Rest Assoc",
    "wof:placetype":"venue"
},
  "geometry": {"coordinates":[-73.213415,44.471021],"type":"Point"}
}