{
  "type": "Feature",
  "properties": {
    "iso:country":"US",
    "sg:address":"405 Pine St",
    "sg:city":"Burlington",
    "sg:classifiers":[
        {
            "category":"Wholesale",
            "subcategory":"Vending Machines",
            "type":"Manufacturing & Wholesale Goods"
        }
    ],
    "sg:phone":"+1 802 864 1900",
    "sg:postcode":"05401",
    "sg:province":"VT",
    "wof:name":"Farrell Vending Svc Inc",
    "wof:placetype":"venue"
},
  "geometry": {"coordinates":[-73.215002,44.468201],"type":"Point"}
}