{
  "type": "Feature",
  "properties": {
    "iso:country":"US",
    "sg:address":"1186 Memorial Dr",
    "sg:city":"St Johnsbury",
    "sg:classifiers":[
        {
            "category":"Real Estate",
            "subcategory":"Real Estate Agent",
            "type":"Services"
        }
    ],
    "sg:phone":"+1 802 748 9842",
    "sg:postcode":"05819",
    "sg:province":"VT",
    "sg:tags":[
        "management"
    ],
    "wof:name":"A D Enterprises",
    "wof:placetype":"venue"
},
  "geometry": {"coordinates":[-72.015565,44.449725],"type":"Point"}
}