{
  "type": "Feature",
  "properties": {
    "iso:country":"US",
    "sg:address":"147 Plank Rd",
    "sg:city":"Mineville",
    "sg:classifiers":[
        {
            "category":"Government",
            "subcategory":"Office",
            "type":"Public Place"
        }
    ],
    "sg:phone":"+1 518 942 3343",
    "sg:postcode":"12956",
    "sg:province":"NY",
    "sg:tags":[
        "village"
    ],
    "wof:name":"Moriah Business Park",
    "wof:placetype":"venue"
},
  "geometry": {"coordinates":[-73.511106,44.075217],"type":"Point"}
}