{
  "type": "Feature",
  "properties": {
    "iso:country":"US",
    "sg:address":"36 Eastern Ave",
    "sg:city":"St Johnsbury",
    "sg:classifiers":[
        {
            "category":"Personal",
            "subcategory":"Beauty Salon",
            "type":"Services"
        }
    ],
    "sg:phone":"+1 802 748 2606",
    "sg:postcode":"05819",
    "sg:province":"VT",
    "sg:tags":[
        "shop"
    ],
    "wof:name":"Style Maker",
    "wof:placetype":"venue"
},
  "geometry": {"coordinates":[-72.016482,44.417913],"type":"Point"}
}