{
  "type": "Feature",
  "properties": {
    "iso:country":"US",
    "sg:address":"308 Pine St",
    "sg:city":"Burlington",
    "sg:classifiers":[
        {
            "category":"Professional",
            "subcategory":"Management & Consulting",
            "type":"Services"
        }
    ],
    "sg:phone":"+1 802 865 0155",
    "sg:postcode":"05401",
    "sg:province":"VT",
    "sg:tags":[
        "consultant",
        "statistical"
    ],
    "wof:name":"Lansky Consulting",
    "wof:placetype":"venue"
},
  "geometry": {"coordinates":[-73.215148,44.470874],"type":"Point"}
}