{
  "type": "Feature",
  "properties": {
    "addr:full":"5351 Main St Waitsfield VT 05673",
    "addr:housenumber":"5351",
    "addr:postcode":"05673",
    "addr:street":"Main St",
    "iso:country":"US",
    "sg:address":"5351 Main St",
    "sg:city":"Waitsfield",
    "sg:classifiers":[
        {
            "category":"Restaurant",
            "type":"Food & Drink"
        }
    ],
    "sg:phone":"+1 802 496 8880",
    "sg:postcode":"05673",
    "sg:province":"VT",
    "wof:name":"Den",
    "wof:placetype":"venue"
},
  "geometry": {"coordinates":[-72.839372,44.182088],"type":"Point"}
}