{
  "type": "Feature",
  "properties": {
    "iso:country":"US",
    "sg:address":"49 Manseau St",
    "sg:city":"Winooski",
    "sg:classifiers":[
        {
            "category":"Real Estate",
            "subcategory":"Real Estate Agent",
            "type":"Services"
        }
    ],
    "sg:phone":"+1 802 310 6973",
    "sg:postcode":"05404",
    "sg:province":"VT",
    "wof:name":"Michael J Van Buren",
    "wof:placetype":"venue"
},
  "geometry": {"coordinates":[-73.177494,44.494646],"type":"Point"}
}