{
  "type": "Feature",
  "properties": {
    "iso:country":"US",
    "sg:address":"101 Main St",
    "sg:city":"Windsor",
    "sg:classifiers":[
        {
            "category":"Building & Trades",
            "subcategory":"Plumbing",
            "type":"Services"
        }
    ],
    "sg:phone":"+1 802 674 2415",
    "sg:postcode":"05089",
    "sg:province":"VT",
    "sg:tags":[
        "plumbing",
        "contractor"
    ],
    "wof:name":"Levesque Plumbing & Heating",
    "wof:placetype":"venue"
},
  "geometry": {"coordinates":[-72.386438,43.480007],"type":"Point"}
}