{
  "type": "Feature",
  "properties": {
    "iso:country":"US",
    "sg:address":"278 N Main St",
    "sg:city":"St Albans",
    "sg:classifiers":[
        {
            "category":"Health Services",
            "subcategory":"Chiropractor",
            "type":"Services"
        }
    ],
    "sg:phone":"+1 802 527 7064",
    "sg:postcode":"05478",
    "sg:province":"VT",
    "wof:name":"Clear Family Chiropractic",
    "wof:placetype":"venue"
},
  "geometry": {"coordinates":[-73.081653,44.820405],"type":"Point"}
}