{
  "type": "Feature",
  "properties": {
    "iso:country":"US",
    "sg:address":"42 Packard Rd",
    "sg:city":"Jericho",
    "sg:classifiers":[
        {
            "category":"Professional",
            "subcategory":"Art Services",
            "type":"Services"
        }
    ],
    "sg:phone":"+1 802 899 4524",
    "sg:postcode":"05465",
    "sg:province":"VT",
    "sg:tags":[
        "commercial",
        "design"
    ],
    "wof:name":"Marcy Design",
    "wof:placetype":"venue"
},
  "geometry": {"coordinates":[-72.971744,44.502485],"type":"Point"}
}