{
  "type": "Feature",
  "properties": {
    "iso:country":"US",
    "sg:address":"1155 US Hwy 5",
    "sg:city":"Windsor",
    "sg:classifiers":[
        {
            "category":"Building & Trades",
            "subcategory":"Construction",
            "type":"Services"
        }
    ],
    "sg:phone":"+1 802 674 5827",
    "sg:postcode":"05089",
    "sg:province":"VT",
    "sg:tags":[
        "home",
        "improvement"
    ],
    "wof:name":"Scott's Contracting",
    "wof:placetype":"venue"
},
  "geometry": {"coordinates":[-72.38837100000001,43.49646],"type":"Point"}
}