{
  "type": "Feature",
  "properties": {
    "addr:full":"341 US Hwy 5 Windsor VT 05089",
    "addr:housenumber":"341",
    "addr:postcode":"05089",
    "addr:street":"Us Hwy 5",
    "iso:country":"US",
    "sg:address":"341 US Hwy 5",
    "sg:city":"Windsor",
    "sg:classifiers":[
        {
            "category":"Restaurant",
            "type":"Food & Drink"
        }
    ],
    "sg:phone":"+1 802 674 6653",
    "sg:postcode":"05089",
    "sg:province":"VT",
    "sg:tags":[
        "eating"
    ],
    "wof:name":"Green Mountain Smokehouse",
    "wof:placetype":"venue"
},
  "geometry": {"coordinates":[-72.389748,43.473139],"type":"Point"}
}