{
  "type": "Feature",
  "properties": {
    "addr:full":"118 Clark Rd Williamstown VT 05679",
    "addr:housenumber":"118",
    "addr:postcode":"05679",
    "addr:street":"Clark Rd",
    "iso:country":"US",
    "sg:address":"118 Clark Rd",
    "sg:city":"Williamstown",
    "sg:classifiers":[
        {
            "category":"Travel",
            "subcategory":"Hotels & Motels",
            "type":"Entertainment"
        }
    ],
    "sg:phone":"+1 802 433 1355",
    "sg:postcode":"05679",
    "sg:province":"VT",
    "sg:tags":[
        "breakfast",
        "accommodation",
        "bed"
    ],
    "wof:name":"Autumn Harvest",
    "wof:placetype":"venue"
},
  "geometry": {"coordinates":[-72.572163,44.118001],"type":"Point"}
}