{
  "type": "Feature",
  "properties": {
    "iso:country":"US",
    "sg:address":"37 Main St",
    "sg:city":"Saxtons River",
    "sg:classifiers":[
        {
            "category":"Restaurant",
            "type":"Food & Drink"
        }
    ],
    "sg:phone":"+1 802 869 2380",
    "sg:postcode":"05154",
    "sg:province":"VT",
    "wof:name":"Golden Egg",
    "wof:placetype":"venue"
},
  "geometry": {"coordinates":[-72.509327,43.138433],"type":"Point"}
}