{
  "type": "Feature",
  "properties": {
    "addr:full":"661 State Forest Rd Groton VT 05046",
    "addr:housenumber":"661",
    "addr:postcode":"05046",
    "addr:street":"State Forest Rd",
    "iso:country":"US",
    "sg:address":"661 State Forest Rd",
    "sg:city":"Groton",
    "sg:classifiers":[
        {
            "category":"Shopping",
            "subcategory":"Computers & Home Electronics",
            "type":"Retail Goods"
        }
    ],
    "sg:phone":"+1 802 584 3292",
    "sg:postcode":"05046",
    "sg:province":"VT",
    "wof:name":"Daves Antenna Service",
    "wof:placetype":"venue"
},
  "geometry": {"coordinates":[-72.25391999999999,44.245529],"type":"Point"}
}