{
  "type": "Feature",
  "properties": {
    "addr:full":"12 Dover Rd Williamsville VT 05362",
    "addr:housenumber":"12",
    "addr:postcode":"05362",
    "addr:street":"Dover Rd",
    "iso:country":"US",
    "sg:address":"12 Dover Rd",
    "sg:city":"Williamsville",
    "sg:classifiers":[
        {
            "category":"Shopping",
            "subcategory":"Used Merchandise",
            "type":"Retail Goods"
        }
    ],
    "sg:phone":"+1 802 348 7400",
    "sg:postcode":"05362",
    "sg:province":"VT",
    "wof:name":"Copper Penny",
    "wof:placetype":"venue"
},
  "geometry": {"coordinates":[-72.676699,42.947735],"type":"Point"}
}