{
  "type": "Feature",
  "properties": {
    "iso:country":"US",
    "sg:address":"160 Holt Rd",
    "sg:city":"Plainfield",
    "sg:classifiers":[
        {
            "category":"Manufacturing",
            "subcategory":"Musical Instruments",
            "type":"Manufacturing & Wholesale Goods"
        }
    ],
    "sg:phone":"+1 802 454 1004",
    "sg:postcode":"05667",
    "sg:province":"VT",
    "sg:tags":[
        "mfg"
    ],
    "wof:name":"Stork Custom Mouthpieces",
    "wof:placetype":"venue"
},
  "geometry": {"coordinates":[-72.37864399999999,44.277132],"type":"Point"}
}