{
  "type": "Feature",
  "properties": {
    "iso:country":"US",
    "sg:address":"312 School St",
    "sg:city":"Bennington",
    "sg:classifiers":[
        {
            "category":"Building & Trades",
            "subcategory":"Construction",
            "type":"Services"
        }
    ],
    "sg:phone":"+1 802 447 7476",
    "sg:postcode":"05201",
    "sg:province":"VT",
    "sg:tags":[
        "general",
        "contractor"
    ],
    "wof:name":"Burdick & Sons Contractors",
    "wof:placetype":"venue"
},
  "geometry": {"coordinates":[-73.19488,42.882198],"type":"Point"}
}