{
  "type": "Feature",
  "properties": {
    "iso:country":"US",
    "sg:address":"23 1st St",
    "sg:city":"Swanton",
    "sg:classifiers":[
        {
            "category":"Insurance",
            "subcategory":"Insurance Agent",
            "type":"Services"
        }
    ],
    "sg:phone":"+1 802 868 7328",
    "sg:postcode":"05488",
    "sg:province":"VT",
    "wof:name":"Champlain Insuring Inc",
    "wof:placetype":"venue"
},
  "geometry": {"coordinates":[-73.124481,44.918231],"type":"Point"}
}