{
  "type": "Feature",
  "properties": {
    "addr:full":"1760 Main St Quechee VT 05045",
    "addr:housenumber":"1760",
    "addr:postcode":"05045",
    "addr:street":"Main St",
    "iso:country":"US",
    "sg:address":"1760 Main St",
    "sg:city":"Quechee",
    "sg:classifiers":[
        {
            "category":"Restaurant",
            "type":"Food & Drink"
        }
    ],
    "sg:phone":"+1 802 295 1470",
    "sg:postcode":"05045",
    "sg:province":"VT",
    "sg:website":"www.simonpearce.com",
    "wof:name":"Simon Pearce Restaurant",
    "wof:placetype":"venue"
},
  "geometry": {"coordinates":[-72.129077,43.917229],"type":"Point"}
}