{
  "type": "Feature",
  "properties": {
    "iso:country":"US",
    "sg:address":"6 Browns River Rd",
    "sg:city":"Essex Junction",
    "sg:classifiers":[
        {
            "category":"Manufacturing",
            "subcategory":"Apparel",
            "type":"Manufacturing & Wholesale Goods"
        }
    ],
    "sg:phone":"+1 802 879 1249",
    "sg:postcode":"05452",
    "sg:province":"VT",
    "sg:tags":[
        "textile",
        "product",
        "fabricated",
        "mfg"
    ],
    "wof:name":"Toque Uncommon",
    "wof:placetype":"venue"
},
  "geometry": {"coordinates":[-73.05806800000001,44.512256],"type":"Point"}
}