{
  "type": "Feature",
  "properties": {
    "iso:country":"US",
    "sg:address":"2850 Old County Rd",
    "sg:city":"St Johnsbury",
    "sg:classifiers":[
        {
            "category":"Building & Trades",
            "subcategory":"Construction",
            "type":"Services"
        }
    ],
    "sg:phone":"+1 802 748 9475",
    "sg:postcode":"05819",
    "sg:province":"VT",
    "sg:tags":[
        "contractor"
    ],
    "wof:name":"Ken's Karpentry",
    "wof:placetype":"venue"
},
  "geometry": {"coordinates":[-71.89639,44.369531],"type":"Point"}
}