{
  "type": "Feature",
  "properties": {
    "iso:country":"US",
    "sg:address":"2748 US Hwy 7",
    "sg:city":"Pittsford",
    "sg:classifiers":[
        {
            "category":"Real Estate",
            "subcategory":"Real Estate Agent",
            "type":"Services"
        }
    ],
    "sg:phone":"+1 802 483 9500",
    "sg:postcode":"05763",
    "sg:province":"VT",
    "wof:name":"A J Grace Land Office",
    "wof:placetype":"venue"
},
  "geometry": {"coordinates":[-73.010595,43.700879],"type":"Point"}
}