{
  "type": "Feature",
  "properties": {
    "iso:country":"US",
    "sg:address":"2681 Leicester Whiting Rd",
    "sg:city":"Whiting",
    "sg:classifiers":[
        {
            "category":"Wholesale",
            "subcategory":"Farm Supplies",
            "type":"Manufacturing & Wholesale Goods"
        }
    ],
    "sg:phone":"+1 802 247 6700",
    "sg:postcode":"05778",
    "sg:province":"VT",
    "sg:tags":[
        "grain"
    ],
    "wof:name":"Depot Farm Supply",
    "wof:placetype":"venue"
},
  "geometry": {"coordinates":[-73.15385499999999,43.854169],"type":"Point"}
}