{
  "type": "Feature",
  "properties": {
    "iso:country":"US",
    "sg:address":"29 Ridgewood Rd",
    "sg:city":"Springfield",
    "sg:classifiers":[
        {
            "category":"Health Services",
            "subcategory":"Doctor",
            "type":"Services"
        }
    ],
    "sg:phone":"+1 802 885 6373",
    "sg:postcode":"05156",
    "sg:province":"VT",
    "sg:tags":[
        "physician",
        "surgeon",
        "medical"
    ],
    "sg:website":"www.aaos.org",
    "wof:name":"Connecticut Valley Orthopedic",
    "wof:placetype":"venue"
},
  "geometry": {"coordinates":[-72.492976,43.298501],"type":"Point"}
}