{
  "type": "Feature",
  "properties": {
    "iso:country":"US",
    "sg:address":"122 Merchants Row",
    "sg:city":"Rutland",
    "sg:classifiers":[
        {
            "category":"Taxi",
            "type":"Transportation"
        }
    ],
    "sg:phone":"+1 802 775 2775",
    "sg:postcode":"05701",
    "sg:province":"VT",
    "sg:tags":[
        "taxicab",
        "sanitary"
    ],
    "wof:name":"M & M Travel",
    "wof:placetype":"venue"
},
  "geometry": {"coordinates":[-72.98053299999999,43.607943],"type":"Point"}
}