{
  "type": "Feature",
  "properties": {
    "iso:country":"US",
    "sg:address":"87 Main St",
    "sg:city":"Newport",
    "sg:classifiers":[
        {
            "category":"Government",
            "subcategory":"Court House",
            "type":"Public Place"
        }
    ],
    "sg:phone":"+1 802 334 7911",
    "sg:postcode":"05825",
    "sg:province":"VT",
    "sg:tags":[
        "defender"
    ],
    "wof:name":"Orleans County District Office",
    "wof:placetype":"venue"
},
  "geometry": {"coordinates":[-72.26361199999999,44.867114],"type":"Point"}
}