{
  "type": "Feature",
  "properties": {
    "iso:country":"US",
    "sg:address":"143 Lawrence Rd",
    "sg:city":"Springfield",
    "sg:classifiers":[
        {
            "category":"Building & Trades",
            "subcategory":"Construction",
            "type":"Services"
        }
    ],
    "sg:phone":"+1 802 463 3018",
    "sg:postcode":"05156",
    "sg:province":"VT",
    "sg:tags":[
        "hog",
        "installation",
        "fence",
        "beef",
        "excavation",
        "work",
        "cattle"
    ],
    "wof:name":"Fischer Farm",
    "wof:placetype":"venue"
},
  "geometry": {"coordinates":[-72.473027,43.22372],"type":"Point"}
}