{
  "type": "Feature",
  "properties": {
    "iso:country":"US",
    "sg:address":"400 E Hill Rd",
    "sg:city":"Plainfield",
    "sg:classifiers":[
        {
            "category":"Building & Trades",
            "subcategory":"Plumbing",
            "type":"Services"
        }
    ],
    "sg:phone":"+1 802 454 7722",
    "sg:postcode":"05601",
    "sg:province":"VT",
    "sg:tags":[
        "heating",
        "contractor"
    ],
    "wof:name":"Averills Plumbing & Heating",
    "wof:placetype":"venue"
},
  "geometry": {"coordinates":[-72.409706,44.360301],"type":"Point"}
}