{
  "type": "Feature",
  "properties": {
    "iso:country":"US",
    "sg:address":"60 Main St",
    "sg:city":"Milton",
    "sg:classifiers":[
        {
            "category":"Building & Trades",
            "subcategory":"Cleaning & Sanitation",
            "type":"Services"
        }
    ],
    "sg:phone":"+1 802 893 8065",
    "sg:postcode":"05468",
    "sg:province":"VT",
    "sg:tags":[
        "house"
    ],
    "wof:name":"All Stars Cleaning & Lighting",
    "wof:placetype":"venue"
},
  "geometry": {"coordinates":[-73.10561,44.639009],"type":"Point"}
}