{
  "type": "Feature",
  "properties": {
    "iso:country":"US",
    "sg:address":"570 Mills Point Rd",
    "sg:city":"Colchester",
    "sg:classifiers":[
        {
            "category":"Building & Trades",
            "subcategory":"Construction",
            "type":"Services"
        }
    ],
    "sg:phone":"+1 802 862 2982",
    "sg:postcode":"05446",
    "sg:province":"VT",
    "sg:tags":[
        "contractor"
    ],
    "wof:name":"Carty Construction",
    "wof:placetype":"venue"
},
  "geometry": {"coordinates":[-73.296772,44.554575],"type":"Point"}
}