{
  "type": "Feature",
  "properties": {
    "addr:full":"758 Clemens Rd Chester VT 05143",
    "addr:housenumber":"758",
    "addr:postcode":"05143",
    "addr:street":"Clemens Rd",
    "iso:country":"US",
    "sg:address":"758 Clemens Rd",
    "sg:city":"Chester",
    "sg:classifiers":[
        {
            "category":"Building & Trades",
            "subcategory":"Construction",
            "type":"Services"
        }
    ],
    "sg:phone":"+1 802 875 6349",
    "sg:postcode":"05143",
    "sg:province":"VT",
    "sg:tags":[
        "work",
        "carpentry"
    ],
    "wof:name":"Kevin Rushton Builders",
    "wof:placetype":"venue"
},
  "geometry": {"coordinates":[-72.60326999999999,43.332721],"type":"Point"}
}