{
  "type": "Feature",
  "properties": {
    "iso:country":"US",
    "sg:address":"13 Main St",
    "sg:city":"Montpelier",
    "sg:classifiers":[
        {
            "category":"Shopping",
            "subcategory":"Used Merchandise",
            "type":"Retail Goods"
        }
    ],
    "sg:phone":"+1 802 229 4002",
    "sg:postcode":"05602",
    "sg:province":"VT",
    "sg:tags":[
        "clothing"
    ],
    "wof:name":"Heather's Nearly New",
    "wof:placetype":"venue"
},
  "geometry": {"coordinates":[-72.57612899999999,44.259212],"type":"Point"}
}