{
  "type": "Feature",
  "properties": {
    "iso:country":"US",
    "sg:address":"1704 Main St",
    "sg:city":"Fairfax",
    "sg:classifiers":[
        {
            "category":"Wholesale",
            "subcategory":"Electrical",
            "type":"Manufacturing & Wholesale Goods"
        }
    ],
    "sg:phone":"+1 802 849 2045",
    "sg:postcode":"05454",
    "sg:province":"VT",
    "sg:tags":[
        "parts",
        "electric",
        "motor"
    ],
    "wof:name":"J & P Electric Motor Svc",
    "wof:placetype":"venue"
},
  "geometry": {"coordinates":[-73.037161,44.708414],"type":"Point"}
}