{
  "type": "Feature",
  "properties": {
    "addr:full":"170 N Main St Rutland VT 05701",
    "addr:housenumber":"170",
    "addr:postcode":"05701",
    "addr:street":"N Main St",
    "iso:country":"US",
    "sg:address":"170 N Main St",
    "sg:city":"Rutland",
    "sg:classifiers":[
        {
            "category":"Health Services",
            "subcategory":"Doctor",
            "type":"Services"
        },
        {
            "category":"Health Services",
            "subcategory":"Clinic",
            "type":"Services"
        },
        {
            "category":"Health Services",
            "subcategory":"Health Practitioner",
            "type":"Services"
        },
        {
            "category":"Health Services",
            "subcategory":"Chiropractor",
            "type":"Services"
        }
    ],
    "sg:phone":"+1 802 775 1986",
    "sg:postcode":"05701",
    "sg:province":"VT",
    "sg:tags":[
        "nutritionist",
        "physician",
        "medical",
        "surgeon",
        "chiropractic"
    ],
    "wof:name":"Moelter Chiropractic Clinic, Pc",
    "wof:placetype":"venue"
},
  "geometry": {"coordinates":[-72.97412799999999,43.618532],"type":"Point"}
}