{
  "type": "Feature",
  "properties": {
    "iso:country":"US",
    "sg:address":"19 W Main St",
    "sg:city":"Wilmington",
    "sg:classifiers":[
        {
            "category":"Restaurant",
            "type":"Food & Drink"
        }
    ],
    "sg:phone":"+1 802 464 4776",
    "sg:postcode":"05363",
    "sg:province":"VT",
    "sg:tags":[
        "pizza"
    ],
    "wof:name":"Zuppardi's Apizza",
    "wof:placetype":"venue"
},
  "geometry": {"coordinates":[-72.871105,42.868462],"type":"Point"}
}