{
  "type": "Feature",
  "properties": {
    "iso:country":"US",
    "sg:address":"254 Benmont Ave",
    "sg:city":"Bennington",
    "sg:classifiers":[
        {
            "category":"Arts & Performance",
            "subcategory":"Theater",
            "type":"Entertainment"
        }
    ],
    "sg:phone":"+1 802 447 0564",
    "sg:postcode":"05201",
    "sg:province":"VT",
    "wof:name":"Oldcastle Theatre Co",
    "wof:placetype":"venue"
},
  "geometry": {"coordinates":[-73.20154700000001,42.8895],"type":"Point"}
}