{
  "type": "Feature",
  "properties": {
    "iso:country":"US",
    "sg:address":"7360 Spear St",
    "sg:city":"Shelburne",
    "sg:classifiers":[
        {
            "category":"Health Services",
            "subcategory":"Dentist",
            "type":"Services"
        }
    ],
    "sg:phone":"+1 802 985 8955",
    "sg:postcode":"05482",
    "sg:province":"VT",
    "wof:name":"Podruch Leeann Dent",
    "wof:placetype":"venue"
},
  "geometry": {"coordinates":[-73.199699,44.363899],"type":"Point"}
}