{
  "type": "Feature",
  "properties": {
    "addr:full":"218 River St Essex Junction VT 05452",
    "addr:housenumber":"218",
    "addr:postcode":"05452",
    "addr:street":"River St",
    "iso:country":"US",
    "sg:address":"218 River St",
    "sg:city":"Essex Junction",
    "sg:classifiers":[
        {
            "category":"Recreation",
            "type":"Entertainment"
        }
    ],
    "sg:phone":"+1 802 878 5074",
    "sg:postcode":"05452",
    "sg:province":"VT",
    "wof:name":"Sure Strike Charters",
    "wof:placetype":"venue"
},
  "geometry": {"coordinates":[-73.112067,44.484394],"type":"Point"}
}