{
  "type": "Feature",
  "properties": {
    "iso:country":"US",
    "sg:address":"166 Davis Ln",
    "sg:city":"Waterbury",
    "sg:classifiers":[
        {
            "category":"Professional",
            "subcategory":"Computer Services",
            "type":"Services"
        }
    ],
    "sg:phone":"+1 802 244 5433",
    "sg:postcode":"05675",
    "sg:province":"VT",
    "sg:tags":[
        "design",
        "system"
    ],
    "sg:website":"www.netlinkdatacom.com",
    "wof:name":"Netlink Data-Com",
    "wof:placetype":"venue"
},
  "geometry": {"coordinates":[-72.41452200000001,44.10462],"type":"Point"}
}