{
  "type": "Feature",
  "properties": {
    "addr:full":"7 Commonwealth Ave Ludlow VT 05149",
    "addr:housenumber":"7",
    "addr:postcode":"05149",
    "addr:street":"Commonwealth Ave",
    "iso:country":"US",
    "sg:address":"7 Commonwealth Ave",
    "sg:city":"Ludlow",
    "sg:classifiers":[
        {
            "category":"Manufacturing",
            "subcategory":"Food",
            "type":"Manufacturing & Wholesale Goods"
        }
    ],
    "sg:phone":"+1 802 228 3172",
    "sg:postcode":"05149",
    "sg:province":"VT",
    "sg:tags":[
        "preparation",
        "mfg"
    ],
    "wof:name":"Pinnacle Sugar House",
    "wof:placetype":"venue"
},
  "geometry": {"coordinates":[-72.694153,43.399416],"type":"Point"}
}