{
  "type": "Feature",
  "properties": {
    "addr:full":"1 Merchants Row Rutland VT 05701",
    "addr:housenumber":"1",
    "addr:postcode":"05701",
    "addr:street":"Merchants Row",
    "iso:country":"US",
    "sg:address":"1 Merchants Row",
    "sg:city":"Rutland",
    "sg:classifiers":[
        {
            "category":"Social Services",
            "type":"Services"
        }
    ],
    "sg:phone":"+1 802 775 4774",
    "sg:postcode":"05701",
    "sg:province":"VT",
    "sg:tags":[
        "worker"
    ],
    "wof:name":"Lisa Chapman Licsw",
    "wof:placetype":"venue"
},
  "geometry": {"coordinates":[-72.979924,43.606437],"type":"Point"}
}