{
  "type": "Feature",
  "properties": {
    "addr:full":"1536 US Hwy 2 Waterbury VT 05676",
    "addr:housenumber":"1536",
    "addr:postcode":"05676",
    "addr:street":"Us Hwy 2",
    "iso:country":"US",
    "sg:address":"1536 US Hwy 2",
    "sg:city":"Waterbury",
    "sg:classifiers":[
        {
            "category":"Building & Trades",
            "subcategory":"Construction",
            "type":"Services"
        }
    ],
    "sg:phone":"+1 802 244 8503",
    "sg:postcode":"05676",
    "sg:province":"VT",
    "sg:tags":[
        "hanging",
        "contractor"
    ],
    "wof:name":"Wilson Painting",
    "wof:placetype":"venue"
},
  "geometry": {"coordinates":[-72.79309499999999,44.356612],"type":"Point"}
}