{
  "type": "Feature",
  "properties": {
    "addr:full":"18 Central St Woodstock VT 05091",
    "addr:housenumber":"18",
    "addr:postcode":"05091",
    "addr:street":"Central St",
    "iso:country":"US",
    "sg:address":"18 Central St",
    "sg:city":"Woodstock",
    "sg:classifiers":[
        {
            "category":"Organizations",
            "subcategory":"Professional Association",
            "type":"Services"
        }
    ],
    "sg:phone":"+1 802 457 3555",
    "sg:postcode":"05091",
    "sg:province":"VT",
    "sg:tags":[
        "chambers",
        "commerce"
    ],
    "wof:name":"Woodstock Chamber Of Commerce",
    "wof:placetype":"venue"
},
  "geometry": {"coordinates":[-72.518047,43.625103],"type":"Point"}
}