{
  "type": "Feature",
  "properties": {
    "addr:full":"29 Sunset Dr Morrisville VT 05661",
    "addr:housenumber":"29",
    "addr:postcode":"05661",
    "addr:street":"Sunset Dr",
    "iso:country":"US",
    "sg:address":"29 Sunset Dr",
    "sg:city":"Morrisville",
    "sg:classifiers":[
        {
            "category":"Freight",
            "type":"Transportation"
        }
    ],
    "sg:phone":"+1 802 888 6200",
    "sg:postcode":"05661",
    "sg:province":"VT",
    "wof:name":"Rural Community Transportation",
    "wof:placetype":"venue"
},
  "geometry": {"coordinates":[-72.592795,44.577058],"type":"Point"}
}