{
  "type": "Feature",
  "properties": {
    "iso:country":"US",
    "sg:address":"34 Park St",
    "sg:city":"Essex Junction",
    "sg:classifiers":[
        {
            "category":"Retail",
            "subcategory":"Repair Shop",
            "type":"Services"
        }
    ],
    "sg:phone":"+1 802 879 7184",
    "sg:postcode":"05452",
    "sg:province":"VT",
    "sg:tags":[
        "oil",
        "burner"
    ],
    "wof:name":"Northern Coal & Oil",
    "wof:placetype":"venue"
},
  "geometry": {"coordinates":[-73.11212999999999,44.489031],"type":"Point"}
}