{
  "type": "Feature",
  "properties": {
    "addr:full":"87 Bishop Ave Williston VT 05495",
    "addr:housenumber":"87",
    "addr:postcode":"05495",
    "addr:street":"Bishop Ave",
    "iso:country":"US",
    "sg:address":"87 Bishop Ave",
    "sg:city":"Williston",
    "sg:classifiers":[
        {
            "category":"Organizations",
            "subcategory":"Community Association",
            "type":"Services"
        }
    ],
    "sg:phone":"+1 802 879 8850",
    "sg:postcode":"05495",
    "sg:province":"VT",
    "sg:tags":[
        "fraternal"
    ],
    "wof:name":"Green Mountain Masonic Ctr",
    "wof:placetype":"venue"
},
  "geometry": {"coordinates":[-73.111656,44.446345],"type":"Point"}
}