{
  "type": "Feature",
  "properties": {
    "addr:full":"27 Center St Brandon VT 05733",
    "addr:housenumber":"27",
    "addr:postcode":"05733",
    "addr:street":"Center St",
    "iso:country":"US",
    "sg:address":"27 Center St",
    "sg:city":"Brandon",
    "sg:classifiers":[
        {
            "category":"Cinema",
            "subcategory":"Movie Rental",
            "type":"Entertainment"
        }
    ],
    "sg:phone":"+1 802 247 5313",
    "sg:postcode":"05733",
    "sg:province":"VT",
    "sg:tags":[
        "video",
        "durable",
        "good",
        "tape"
    ],
    "wof:name":"Showtime Video",
    "wof:placetype":"venue"
},
  "geometry": {"coordinates":[-73.088256,43.798263],"type":"Point"}
}