{
  "type": "Feature",
  "properties": {
    "addr:full":"43 N Main St White River Jct VT 05001",
    "addr:housenumber":"43",
    "addr:postcode":"05001",
    "addr:street":"N Main St",
    "iso:country":"US",
    "sg:address":"43 N Main St",
    "sg:city":"White River Jct",
    "sg:classifiers":[
        {
            "category":"Professional",
            "subcategory":"Employment Agencies",
            "type":"Services"
        }
    ],
    "sg:phone":"+1 802 296 3732",
    "sg:postcode":"05001",
    "sg:province":"VT",
    "sg:tags":[
        "opportunity"
    ],
    "wof:name":"J Ryder Search Inc",
    "wof:placetype":"venue"
},
  "geometry": {"coordinates":[-72.321123,43.649577],"type":"Point"}
}