{
  "type": "Feature",
  "properties": {
    "addr:full":"1854 King Hill Rd Fairlee VT 05045",
    "addr:housenumber":"1854",
    "addr:postcode":"05045",
    "addr:street":"King Hill Rd",
    "iso:country":"US",
    "sg:address":"1854 King Hill Rd",
    "sg:city":"Fairlee",
    "sg:classifiers":[
        {
            "category":"Retail",
            "subcategory":"Auto Repair",
            "type":"Services"
        }
    ],
    "sg:phone":"+1 802 333 3300",
    "sg:postcode":"05045",
    "sg:province":"VT",
    "sg:tags":[
        "general"
    ],
    "wof:name":"Pauls Garage",
    "wof:placetype":"venue"
},
  "geometry": {"coordinates":[-72.233056,43.923201],"type":"Point"}
}