{
  "type": "Feature",
  "properties": {
    "addr:full":"348 Main St Montgomery Ctr VT 05471",
    "addr:housenumber":"348",
    "addr:postcode":"05471",
    "addr:street":"Main St",
    "iso:country":"US",
    "sg:address":"348 Main St",
    "sg:city":"Montgomery Ctr",
    "sg:classifiers":[
        {
            "category":"Home & Garden",
            "subcategory":"Garden Supply",
            "type":"Retail Goods"
        }
    ],
    "sg:phone":"+1 802 326 4004",
    "sg:postcode":"05471",
    "sg:province":"VT",
    "sg:tags":[
        "nurseryman"
    ],
    "wof:name":"D & N Greenhouses",
    "wof:placetype":"venue"
},
  "geometry": {"coordinates":[-72.613866,44.880848],"type":"Point"}
}