{
  "type": "Feature",
  "properties": {
    "addr:full":"23 Goodwood Ln Dorset VT 05251",
    "addr:housenumber":"23",
    "addr:postcode":"05251",
    "addr:street":"Goodwood Ln",
    "iso:country":"US",
    "sg:address":"23 Goodwood Ln",
    "sg:city":"Dorset",
    "sg:classifiers":[
        {
            "category":"Home & Garden",
            "subcategory":"Furniture",
            "type":"Retail Goods"
        }
    ],
    "sg:phone":"+1 802 867 5541",
    "sg:postcode":"05251",
    "sg:province":"VT",
    "sg:tags":[
        "store"
    ],
    "wof:name":"Mosheim Custom Furniture",
    "wof:placetype":"venue"
},
  "geometry": {"coordinates":[-73.11148300000001,43.284632],"type":"Point"}
}