{
  "type": "Feature",
  "properties": {
    "iso:country":"US",
    "sg:address":"233 Pearl St",
    "sg:city":"Burlington",
    "sg:classifiers":[
        {
            "category":"Professional",
            "subcategory":"Lawyer & Legal Services",
            "type":"Services"
        }
    ],
    "sg:phone":"+1 802 651 9000",
    "sg:postcode":"05401",
    "sg:province":"VT",
    "sg:tags":[
        "attorney"
    ],
    "sg:website":"www.vermontelderlaw.com",
    "wof:name":"Elder Law Group",
    "wof:placetype":"venue"
},
  "geometry": {"coordinates":[-73.209991,44.480526],"type":"Point"}
}