{
  "type": "Feature",
  "properties": {
    "addr:full":"3 Jericho E Jericho VT 05465",
    "addr:housenumber":"3;e",
    "addr:postcode":"05465",
    "iso:country":"US",
    "sg:address":"3 Jericho E",
    "sg:city":"Jericho",
    "sg:classifiers":[
        {
            "category":"Health Services",
            "subcategory":"Health Practitioner",
            "type":"Services"
        }
    ],
    "sg:phone":"+1 802 899 1925",
    "sg:postcode":"05465",
    "sg:province":"VT",
    "wof:name":"Tranquility Massage",
    "wof:placetype":"venue"
},
  "geometry": {"coordinates":[-72.961125,44.510768],"type":"Point"}
}