{
  "type": "Feature",
  "properties": {
    "addr:full":"6 Cherrierville Rd Fairfax VT 05454",
    "addr:housenumber":"6",
    "addr:postcode":"05454",
    "addr:street":"Cherrierville Rd",
    "iso:country":"US",
    "sg:address":"6 Cherrierville Rd",
    "sg:city":"Fairfax",
    "sg:classifiers":[
        {
            "category":"Professional",
            "type":"Services"
        }
    ],
    "sg:phone":"+1 802 849 2145",
    "sg:postcode":"05454",
    "sg:province":"VT",
    "wof:name":"Charles Cox",
    "wof:placetype":"venue"
},
  "geometry": {"coordinates":[-73.020533,44.718431],"type":"Point"}
}