{
  "type": "Feature",
  "properties": {
    "iso:country":"US",
    "sg:address":"114 Nelson Farm Rd",
    "sg:city":"Moretown",
    "sg:classifiers":[
        {
            "category":"Manufacturing",
            "subcategory":"Apparel",
            "type":"Manufacturing & Wholesale Goods"
        }
    ],
    "sg:phone":"+1 802 496 2446",
    "sg:postcode":"05660",
    "sg:province":"VT",
    "wof:name":"Blankets of Snow",
    "wof:placetype":"venue"
},
  "geometry": {"coordinates":[-72.83424599999999,44.240925],"type":"Point"}
}