{
  "type": "Feature",
  "properties": {
    "addr:full":"2000 Guptil Rd Waterbury Center VT 05677",
    "addr:postcode":"05677",
    "addr:street":"Guptil Rd",
    "iso:country":"US",
    "sg:address":"2000 Guptil Rd",
    "sg:city":"Waterbury Center",
    "sg:classifiers":[
        {
            "category":"Food & Beverages",
            "subcategory":"Groceries & Convenience Stores",
            "type":"Retail Goods"
        }
    ],
    "sg:phone":"+1 802 244 7500",
    "sg:postcode":"05677",
    "sg:province":"VT",
    "sg:tags":[
        "grocer"
    ],
    "wof:name":"T J's General Store Inc",
    "wof:placetype":"venue"
},
  "geometry": {"coordinates":[-72.71774000000001,44.368908],"type":"Point"}
}