{
  "type": "Feature",
  "properties": {
    "iso:country":"US",
    "sg:address":"518 Turkey Ln",
    "sg:city":"Hinesburg",
    "sg:classifiers":[
        {
            "category":"Organizations",
            "subcategory":"Membership Organization",
            "type":"Services"
        }
    ],
    "sg:phone":"+1 802 482 5319",
    "sg:postcode":"05461",
    "sg:province":"VT",
    "wof:name":"Compassionate Friends",
    "wof:placetype":"venue"
},
  "geometry": {"coordinates":[-73.10227999999999,44.281389],"type":"Point"}
}