{
  "type": "Feature",
  "properties": {
    "addr:full":"3 Brownell Way South Burlington VT 05403",
    "addr:housenumber":"3",
    "addr:postcode":"05403",
    "addr:street":"Brownell Way",
    "iso:country":"US",
    "sg:address":"3 Brownell Way",
    "sg:city":"South Burlington",
    "sg:classifiers":[
        {
            "category":"Freight",
            "type":"Transportation"
        }
    ],
    "sg:phone":"+1 802 863 2709",
    "sg:postcode":"05403",
    "sg:province":"VT",
    "sg:tags":[
        "operator",
        "local",
        "trucking"
    ],
    "wof:name":"G & E Delivery Inc",
    "wof:placetype":"venue"
},
  "geometry": {"coordinates":[-73.196477,44.429785],"type":"Point"}
}