{
  "type": "Feature",
  "properties": {
    "iso:country":"US",
    "sg:address":"16 Pleasant St",
    "sg:city":"Essex Junction",
    "sg:classifiers":[
        {
            "category":"Shopping",
            "subcategory":"Clothing, Apparel, & Fashions",
            "type":"Retail Goods"
        }
    ],
    "sg:phone":"+1 802 878 2548",
    "sg:postcode":"05452",
    "sg:province":"VT",
    "sg:tags":[
        "industrial",
        "glove"
    ],
    "wof:name":"H A Spear & Sons",
    "wof:placetype":"venue"
},
  "geometry": {"coordinates":[-73.106352,44.493354],"type":"Point"}
}