{
  "type": "Feature",
  "properties": {
    "iso:country":"US",
    "sg:address":"13 Washington St Exd",
    "sg:city":"Middlebury",
    "sg:classifiers":[
        {
            "category":"Social Services",
            "subcategory":"Child Care",
            "type":"Services"
        }
    ],
    "sg:phone":"+1 802 388 3866",
    "sg:postcode":"05753",
    "sg:province":"VT",
    "sg:tags":[
        "day"
    ],
    "wof:name":"Sunshine Daycare Preschool",
    "wof:placetype":"venue"
},
  "geometry": {"coordinates":[-73.15541,44.020886],"type":"Point"}
}