{
  "type": "Feature",
  "properties": {
    "iso:country":"US",
    "sg:address":"49 Commerce Ave",
    "sg:city":"South Burlington",
    "sg:classifiers":[
        {
            "category":"Retail",
            "subcategory":"Auto Repair",
            "type":"Services"
        }
    ],
    "sg:phone":"+1 802 865 5299",
    "sg:postcode":"05403",
    "sg:province":"VT",
    "sg:tags":[
        "repairing",
        "automobile",
        "general"
    ],
    "wof:name":"Maglaris Automotive Services",
    "wof:placetype":"venue"
},
  "geometry": {"coordinates":[-73.15973200000001,44.48282],"type":"Point"}
}