{
  "type": "Feature",
  "properties": {
    "iso:country":"US",
    "sg:address":"14 Addie Ln",
    "sg:city":"Shelburne",
    "sg:classifiers":[
        {
            "category":"Travel",
            "subcategory":"Travel Agent",
            "type":"Entertainment"
        }
    ],
    "sg:phone":"+1 802 985 2326",
    "sg:postcode":"05482",
    "sg:province":"VT",
    "sg:tags":[
        "consultant"
    ],
    "wof:name":"Earth Journeys",
    "wof:placetype":"venue"
},
  "geometry": {"coordinates":[-73.214187,44.370194],"type":"Point"}
}