{
  "type": "Feature",
  "properties": {
    "iso:country":"US",
    "sg:address":"100 Geary Rd S",
    "sg:city":"Bristol",
    "sg:classifiers":[
        {
            "category":"Arts & Performance",
            "subcategory":"Theater",
            "type":"Entertainment"
        }
    ],
    "sg:phone":"+1 802 453 5425",
    "sg:postcode":"05443",
    "sg:province":"VT",
    "sg:tags":[
        "group"
    ],
    "wof:name":"Magicians Without Borders",
    "wof:placetype":"venue"
},
  "geometry": {"coordinates":[-72.97067,44.071648],"type":"Point"}
}