{
  "type": "Feature",
  "properties": {
    "iso:country":"US",
    "sg:address":"15 Cabin Ln",
    "sg:city":"Waterbury Center",
    "sg:classifiers":[
        {
            "category":"Home & Garden",
            "subcategory":"Garden Supply",
            "type":"Retail Goods"
        }
    ],
    "sg:phone":"+1 802 244 8523",
    "sg:postcode":"05677",
    "sg:province":"VT",
    "sg:tags":[
        "center"
    ],
    "sg:website":"www.evergreengardensvt.com",
    "wof:name":"Evergreen Gardens Of Vermont",
    "wof:placetype":"venue"
},
  "geometry": {"coordinates":[-72.71929,44.39551],"type":"Point"}
}