{
  "type": "Feature",
  "properties": {
    "iso:country":"US",
    "sg:address":"706 Main St",
    "sg:city":"Castleton",
    "sg:classifiers":[
        {
            "category":"Social Services",
            "type":"Services"
        }
    ],
    "sg:phone":"+1 802 468 5325",
    "sg:postcode":"05735",
    "sg:province":"VT",
    "sg:tags":[
        "organization",
        "welfare"
    ],
    "sg:website":"www.fortysevenmain.com",
    "wof:name":"Forty Seven Main Street Inc",
    "wof:placetype":"venue"
},
  "geometry": {"coordinates":[-73.179506,43.611421],"type":"Point"}
}