{
  "type": "Feature",
  "properties": {
    "iso:country":"US",
    "sg:address":"13 State Rte 15A",
    "sg:city":"Morrisville",
    "sg:classifiers":[
        {
            "category":"Shopping",
            "subcategory":"Books",
            "type":"Retail Goods"
        }
    ],
    "sg:phone":"+1 802 888 8474",
    "sg:postcode":"05661",
    "sg:province":"VT",
    "sg:tags":[
        "dealer"
    ],
    "wof:name":"Narrow Way Bookstore",
    "wof:placetype":"venue"
},
  "geometry": {"coordinates":[-72.59822,44.5617],"type":"Point"}
}