{
  "type": "Feature",
  "properties": {
    "addr:full":"17 Towne Farm Ln Stowe VT 05672",
    "addr:housenumber":"17",
    "addr:postcode":"05672",
    "addr:street":"Towne Farm Ln",
    "iso:country":"US",
    "sg:address":"17 Towne Farm Ln",
    "sg:city":"Stowe",
    "sg:classifiers":[
        {
            "category":"Shopping",
            "type":"Retail Goods"
        }
    ],
    "sg:phone":"+1 802 253 8943",
    "sg:postcode":"05672",
    "sg:province":"VT",
    "sg:tags":[
        "art",
        "gallery",
        "dealer"
    ],
    "wof:name":"Christopher Curtis Studio",
    "wof:placetype":"venue"
},
  "geometry": {"coordinates":[-72.701645,44.475024],"type":"Point"}
}