{
  "type": "Feature",
  "properties": {
    "iso:country":"US",
    "sg:address":"85 Jericho St",
    "sg:city":"White River Junction",
    "sg:classifiers":[
        {
            "category":"Retail",
            "subcategory":"Repair Shop",
            "type":"Services"
        }
    ],
    "sg:phone":"+1 802 296 8022",
    "sg:postcode":"05001",
    "sg:province":"VT",
    "wof:name":"Wolken Auto Seatcovers",
    "wof:placetype":"venue"
},
  "geometry": {"coordinates":[-72.386313,43.694071],"type":"Point"}
}