{
  "type": "Feature",
  "properties": {
    "iso:country":"US",
    "sg:address":"82 Diamond Run Mall Pl",
    "sg:city":"Rutland",
    "sg:classifiers":[
        {
            "category":"Shopping",
            "subcategory":"Department Store",
            "type":"Retail Goods"
        }
    ],
    "sg:phone":"+1 802 770 3049",
    "sg:postcode":"05701",
    "sg:province":"VT",
    "wof:name":"Sears Roebuck & Co",
    "wof:placetype":"venue"
},
  "geometry": {"coordinates":[-72.96544400000001,43.579131],"type":"Point"}
}