{
  "type": "Feature",
  "properties": {
    "iso:country":"US",
    "sg:address":"144 State Rte 14",
    "sg:city":"Hartford",
    "sg:classifiers":[
        {
            "category":"Building & Trades",
            "subcategory":"Construction",
            "type":"Services"
        }
    ],
    "sg:phone":"+1 802 296 7246",
    "sg:postcode":"05001",
    "sg:province":"VT",
    "sg:tags":[
        "excavating",
        "contractor"
    ],
    "wof:name":"Daniel S Clay",
    "wof:placetype":"venue"
},
  "geometry": {"coordinates":[-72.330444,43.655978],"type":"Point"}
}