{
  "type": "Feature",
  "properties": {
    "iso:country":"US",
    "sg:address":"108 Chelsea St",
    "sg:city":"South Royalton",
    "sg:classifiers":[
        {
            "category":"Restaurant",
            "type":"Food & Drink"
        }
    ],
    "sg:phone":"+1 802 763 8685",
    "sg:postcode":"05068",
    "sg:province":"VT",
    "wof:name":"Chelsea Station",
    "wof:placetype":"venue"
},
  "geometry": {"coordinates":[-72.519683,43.822341],"type":"Point"}
}