{
  "type": "Feature",
  "properties": {
    "addr:full":"9431 State Rte 36 East Fairfield VT 05448",
    "addr:housenumber":"9431",
    "addr:postcode":"05448",
    "addr:street":"State Rte 36 East",
    "iso:country":"US",
    "sg:address":"9431 State Rte 36",
    "sg:city":"East Fairfield",
    "sg:classifiers":[
        {
            "category":"Autos & Motor Vehicles",
            "subcategory":"Fuel & Gas Station",
            "type":"Retail Goods"
        }
    ],
    "sg:phone":"+1 802 827 3778",
    "sg:postcode":"05448",
    "sg:province":"VT",
    "sg:tags":[
        "oil"
    ],
    "wof:name":"Shell",
    "wof:placetype":"venue"
},
  "geometry": {"coordinates":[-72.948488,44.744496],"type":"Point"}
}