{
  "type": "Feature",
  "properties": {
    "iso:country":"US",
    "sg:address":"16 Morning Dove Ln",
    "sg:city":"Brandon",
    "sg:classifiers":[
        {
            "category":"Retail",
            "subcategory":"Repair Shop",
            "type":"Services"
        }
    ],
    "sg:phone":"+1 802 247 4411",
    "sg:postcode":"05733",
    "sg:province":"VT",
    "sg:tags":[
        "electrical"
    ],
    "wof:name":"Family Heat & Appliance",
    "wof:placetype":"venue"
},
  "geometry": {"coordinates":[-73.06336,43.818701],"type":"Point"}
}