{
  "type": "Feature",
  "properties": {
    "addr:full":"3649 Lower Newton Rd Swanton VT 05488",
    "addr:housenumber":"3649",
    "addr:postcode":"05488",
    "addr:street":"Lower Newton Rd",
    "iso:country":"US",
    "sg:address":"3649 Lower Newton Rd",
    "sg:city":"Swanton",
    "sg:classifiers":[
        {
            "category":"Government",
            "subcategory":"Jail",
            "type":"Public Place"
        }
    ],
    "sg:phone":"+1 802 524 6771",
    "sg:postcode":"05488",
    "sg:province":"VT",
    "sg:tags":[
        "govt",
        "state",
        "institution"
    ],
    "wof:name":"Norwest State Correctional Fac",
    "wof:placetype":"venue"
},
  "geometry": {"coordinates":[-73.132727,44.853816],"type":"Point"}
}