{
  "type": "Feature",
  "properties": {
    "addr:full":"11 Beaver Meadow Rd Norwich VT 05055",
    "addr:housenumber":"11",
    "addr:postcode":"05055",
    "addr:street":"Beaver Meadow Rd",
    "iso:country":"US",
    "sg:address":"11 Beaver Meadow Rd",
    "sg:city":"Norwich",
    "sg:classifiers":[
        {
            "category":"Health Services",
            "subcategory":"Doctor",
            "type":"Services"
        }
    ],
    "sg:phone":"+1 802 649 2266",
    "sg:postcode":"05055",
    "sg:province":"VT",
    "sg:tags":[
        "physician",
        "surgeon"
    ],
    "wof:name":"Matrix Health Systems",
    "wof:placetype":"venue"
},
  "geometry": {"coordinates":[-72.310686,43.71546],"type":"Point"}
}