{
  "type": "Feature",
  "properties": {
    "iso:country":"US",
    "sg:address":"11 Lincoln St",
    "sg:city":"Essex Junction",
    "sg:classifiers":[
        {
            "category":"Government",
            "subcategory":"Office",
            "type":"Public Place"
        }
    ],
    "sg:phone":"+1 802 879 5217",
    "sg:postcode":"05452",
    "sg:province":"VT",
    "sg:tags":[
        "state",
        "program",
        "health"
    ],
    "wof:name":"Health & Human Svc",
    "wof:placetype":"venue"
},
  "geometry": {"coordinates":[-73.11094,44.491331],"type":"Point"}
}