{
  "type": "Feature",
  "properties": {
    "addr:full":"307 North St Bennington VT 05201",
    "addr:housenumber":"307",
    "addr:postcode":"05201",
    "addr:street":"North St",
    "iso:country":"US",
    "sg:address":"307 North St",
    "sg:city":"Bennington",
    "sg:classifiers":[
        {
            "category":"Shopping",
            "subcategory":"Used Merchandise",
            "type":"Retail Goods"
        }
    ],
    "sg:phone":"+1 802 442 2612",
    "sg:postcode":"05201",
    "sg:province":"VT",
    "sg:tags":[
        "antique"
    ],
    "wof:name":"Four Corners East Inc",
    "wof:placetype":"venue"
},
  "geometry": {"coordinates":[-73.19687399999999,42.884381],"type":"Point"}
}