{
  "type": "Feature",
  "properties": {
    "addr:full":"29 Stagecoach Rd Barre VT 05641",
    "addr:housenumber":"29",
    "addr:postcode":"05641",
    "addr:street":"Stagecoach Rd",
    "iso:country":"US",
    "sg:address":"29 Stagecoach Rd",
    "sg:city":"Barre",
    "sg:classifiers":[
        {
            "category":"Restaurant",
            "type":"Food & Drink"
        }
    ],
    "sg:phone":"+1 802 479 0686",
    "sg:postcode":"05641",
    "sg:province":"VT",
    "sg:tags":[
        "operates"
    ],
    "wof:name":"Cafe Bradley",
    "wof:placetype":"venue"
},
  "geometry": {"coordinates":[-72.438768,44.176743],"type":"Point"}
}