{
  "type": "Feature",
  "properties": {
    "iso:country":"US",
    "sg:address":"6 Lower Plains Rd",
    "sg:city":"Middlebury",
    "sg:classifiers":[
        {
            "category":"Building & Trades",
            "subcategory":"Landscaping Services",
            "type":"Services"
        }
    ],
    "sg:phone":"+1 802 388 4529",
    "sg:postcode":"05740",
    "sg:province":"VT",
    "sg:tags":[
        "landscape",
        "contractor"
    ],
    "wof:name":"Tom Bodette Landscaping & Lawn",
    "wof:placetype":"venue"
},
  "geometry": {"coordinates":[-73.09114099999999,43.961177],"type":"Point"}
}