{
  "type": "Feature",
  "properties": {
    "iso:country":"US",
    "sg:address":"620 Lawrence Pl",
    "sg:city":"Williston",
    "sg:classifiers":[
        {
            "category":"Autos & Motor Vehicles",
            "subcategory":"Auto Supplies",
            "type":"Retail Goods"
        }
    ],
    "sg:phone":"+1 802 878 1023",
    "sg:postcode":"05495",
    "sg:province":"VT",
    "sg:tags":[
        "automobile",
        "accessory"
    ],
    "sg:website":"www.rackwarehouse.com",
    "wof:name":"Rack Warehouse",
    "wof:placetype":"venue"
},
  "geometry": {"coordinates":[-73.112996,44.451466],"type":"Point"}
}