{
  "type": "Feature",
  "properties": {
    "iso:country":"US",
    "sg:address":"1123 Main St",
    "sg:city":"Fairfax",
    "sg:classifiers":[
        {
            "category":"Bakery",
            "type":"Food & Drink"
        }
    ],
    "sg:phone":"+1 802 849 6601",
    "sg:postcode":"05454",
    "sg:province":"VT",
    "wof:name":"Foothills Bakery",
    "wof:placetype":"venue"
},
  "geometry": {"coordinates":[-72.97350299999999,44.646702],"type":"Point"}
}