{
  "type": "Feature",
  "properties": {
    "addr:full":"204 N Main St Rutland VT 05701",
    "addr:housenumber":"204",
    "addr:postcode":"05701",
    "addr:street":"N Main St",
    "iso:country":"US",
    "sg:address":"204 N Main St",
    "sg:city":"Rutland",
    "sg:classifiers":[
        {
            "category":"Health Services",
            "subcategory":"Doctor",
            "type":"Services"
        }
    ],
    "sg:phone":"+1 802 775 5286",
    "sg:postcode":"05701",
    "sg:province":"VT",
    "sg:tags":[
        "dentist"
    ],
    "wof:name":"Heaton & Fisch Dental Assoc PC",
    "wof:placetype":"venue"
},
  "geometry": {"coordinates":[-72.97509700000001,43.624169],"type":"Point"}
}