{
  "type": "Feature",
  "properties": {
    "iso:country":"US",
    "sg:address":"159 Pearl St",
    "sg:city":"Essex Junction",
    "sg:classifiers":[
        {
            "category":"Personal",
            "subcategory":"Beauty Salon",
            "type":"Services"
        }
    ],
    "sg:phone":"+1 802 878 5596",
    "sg:postcode":"05452",
    "sg:province":"VT",
    "wof:name":"Shear Styles",
    "wof:placetype":"venue"
},
  "geometry": {"coordinates":[-73.127455,44.497853],"type":"Point"}
}