{
  "type": "Feature",
  "properties": {
    "iso:country":"US",
    "sg:address":"183 Cooper Rd",
    "sg:city":"Milton",
    "sg:classifiers":[
        {
            "category":"Professional",
            "subcategory":"Art Services",
            "type":"Services"
        }
    ],
    "sg:phone":"+1 802 893 2316",
    "sg:postcode":"05468",
    "sg:province":"VT",
    "sg:tags":[
        "commercial",
        "design"
    ],
    "wof:name":"Thick & Thin Graphics",
    "wof:placetype":"venue"
},
  "geometry": {"coordinates":[-73.095735,44.670566],"type":"Point"}
}