{
  "type": "Feature",
  "properties": {
    "addr:full":"225 White River Ln White River Jct VT 05001",
    "addr:housenumber":"225",
    "addr:postcode":"05001",
    "addr:street":"White River Ln",
    "iso:country":"US",
    "sg:address":"225 White River Ln",
    "sg:city":"White River Jct",
    "sg:classifiers":[
        {
            "category":"Real Estate",
            "subcategory":"Real Estate Agent",
            "type":"Services"
        }
    ],
    "sg:phone":"+1 802 295 9338",
    "sg:postcode":"05001",
    "sg:province":"VT",
    "sg:tags":[
        "consultant"
    ],
    "wof:name":"Business Locators",
    "wof:placetype":"venue"
},
  "geometry": {"coordinates":[-72.42920700000001,43.722088],"type":"Point"}
}