{
  "type": "Feature",
  "properties": {
    "iso:country":"US",
    "sg:address":"1079 S Barre Rd",
    "sg:city":"Barre",
    "sg:classifiers":[
        {
            "category":"Health Services",
            "subcategory":"Nursing And Care Facility",
            "type":"Services"
        },
        {
            "category":"Social Services",
            "subcategory":"Adult Care",
            "type":"Services"
        }
    ],
    "sg:phone":"+1 802 479 3118",
    "sg:postcode":"05641",
    "sg:province":"VT",
    "sg:tags":[
        "residential",
        "skilled",
        "home"
    ],
    "wof:name":"Cota's Hospitality Home",
    "wof:placetype":"venue"
},
  "geometry": {"coordinates":[-72.51310100000001,44.15954],"type":"Point"}
}