{
  "type": "Feature",
  "properties": {
    "iso:country":"US",
    "sg:address":"1027 Pine St",
    "sg:city":"Burlington",
    "sg:classifiers":[
        {
            "category":"Professional",
            "subcategory":"Art Services",
            "type":"Services"
        }
    ],
    "sg:phone":"+1 802 863 8299",
    "sg:postcode":"05401",
    "sg:province":"VT",
    "sg:tags":[
        "photographer"
    ],
    "wof:name":"Alan Jakubek Photography",
    "wof:placetype":"venue"
},
  "geometry": {"coordinates":[-73.21462,44.449581],"type":"Point"}
}