{
  "type": "Feature",
  "properties": {
    "addr:full":"1959 Sheldon Rd Saint Albans VT 05478",
    "addr:housenumber":"1959",
    "addr:postcode":"05478",
    "addr:street":"Sheldon Rd",
    "iso:country":"US",
    "sg:address":"1959 Sheldon Rd",
    "sg:city":"Saint Albans",
    "sg:classifiers":[
        {
            "category":"Professional",
            "subcategory":"Management & Consulting",
            "type":"Services"
        }
    ],
    "sg:phone":"+1 802 782 2434",
    "sg:postcode":"05478",
    "sg:province":"VT",
    "wof:name":"White Rose Wedding",
    "wof:placetype":"venue"
},
  "geometry": {"coordinates":[-73.04212,44.842532],"type":"Point"}
}