{
  "type": "Feature",
  "properties": {
    "iso:country":"US",
    "sg:address":"1194 Main St",
    "sg:city":"St Johnsbury",
    "sg:classifiers":[
        {
            "category":"Social Services",
            "type":"Services"
        }
    ],
    "sg:phone":"+1 802 748 8722",
    "sg:postcode":"05819",
    "sg:province":"VT",
    "sg:tags":[
        "counselor",
        "marriage",
        "family"
    ],
    "wof:name":"Marilyn Mc Enery",
    "wof:placetype":"venue"
},
  "geometry": {"coordinates":[-72.020909,44.418785],"type":"Point"}
}