{
  "type": "Feature",
  "properties": {
    "iso:country":"US",
    "sg:address":"7 Fayette Dr",
    "sg:city":"South Burlington",
    "sg:classifiers":[
        {
            "category":"Health Services",
            "subcategory":"Doctor",
            "type":"Services"
        }
    ],
    "sg:phone":"+1 802 865 3655",
    "sg:postcode":"05403",
    "sg:province":"VT",
    "sg:tags":[
        "medical",
        "clinic"
    ],
    "wof:name":"Champlain Valley Urgent Care",
    "wof:placetype":"venue"
},
  "geometry": {"coordinates":[-73.21321500000001,44.438256],"type":"Point"}
}