{
  "type": "Feature",
  "properties": {
    "addr:full":"37 Newton Rd Chester VT 05143",
    "addr:housenumber":"37",
    "addr:postcode":"05143",
    "addr:street":"Newton Rd",
    "iso:country":"US",
    "sg:address":"37 Newton Rd",
    "sg:city":"Chester",
    "sg:classifiers":[
        {
            "category":"Building & Trades",
            "subcategory":"Construction",
            "type":"Services"
        }
    ],
    "sg:phone":"+1 802 875 1843",
    "sg:postcode":"05143",
    "sg:province":"VT",
    "sg:tags":[
        "hanging",
        "contractor"
    ],
    "wof:name":"Mikes Painting",
    "wof:placetype":"venue"
},
  "geometry": {"coordinates":[-72.615336,43.334486],"type":"Point"}
}