{
  "type": "Feature",
  "properties": {
    "iso:country":"US",
    "sg:address":"118 Birge St",
    "sg:city":"Brattleboro",
    "sg:classifiers":[
        {
            "category":"Wholesale",
            "subcategory":"Machinery & Supplies",
            "type":"Manufacturing & Wholesale Goods"
        },
        {
            "category":"Building & Trades",
            "subcategory":"Plumbing",
            "type":"Services"
        }
    ],
    "sg:phone":"+1 802 254 2242",
    "sg:postcode":"05301",
    "sg:province":"VT",
    "sg:tags":[
        "installs",
        "sprinkler",
        "system"
    ],
    "wof:name":"Southern Vermont Sprinkler Svc",
    "wof:placetype":"venue"
},
  "geometry": {"coordinates":[-72.56857599999999,42.849631],"type":"Point"}
}