{
  "type": "Feature",
  "properties": {
    "addr:full":"176 Main St Burlington VT 05401",
    "addr:housenumber":"176",
    "addr:postcode":"05401",
    "addr:street":"Main St",
    "iso:country":"US",
    "sg:address":"176 Main St",
    "sg:city":"Burlington",
    "sg:classifiers":[
        {
            "category":"Bakery",
            "type":"Food & Drink"
        },
        {
            "category":"Coffee & Tea",
            "type":"Food & Drink"
        },
        {
            "category":"Bagels",
            "type":"Food & Drink"
        },
        {
            "category":"Donuts",
            "type":"Food & Drink"
        }
    ],
    "sg:menulink":"http://www.allmenus.com/vt/burlington/139021-dunkin-donuts/menu/",
    "sg:phone":"+1 802 657 4125",
    "sg:postcode":"05401",
    "sg:province":"VT",
    "sg:tags":[
        "american",
        "pastry"
    ],
    "wof:name":"Dunkin' Donuts",
    "wof:placetype":"venue"
},
  "geometry": {"coordinates":[-73.21208900000001,44.476165],"type":"Point"}
}