{
  "type": "Feature",
  "properties": {
    "addr:full":"177 State Rte 12 Montpelier VT 05602",
    "addr:housenumber":"177",
    "addr:postcode":"05602",
    "addr:street":"State Rte 12",
    "iso:country":"US",
    "sg:address":"177 State Rte 12",
    "sg:city":"Montpelier",
    "sg:classifiers":[
        {
            "category":"Professional",
            "type":"Services"
        }
    ],
    "sg:phone":"+1 802 229 4246",
    "sg:postcode":"05602",
    "sg:province":"VT",
    "wof:name":"Ridgerunner Products",
    "wof:placetype":"venue"
},
  "geometry": {"coordinates":[-72.57179499999999,44.264163],"type":"Point"}
}