{
  "type": "Feature",
  "properties": {
    "iso:country":"US",
    "sg:address":"5768 Main St",
    "sg:city":"Manchester Ctr",
    "sg:classifiers":[
        {
            "category":"Retail",
            "subcategory":"Auto Repair",
            "type":"Services"
        }
    ],
    "sg:phone":"+1 802 362 2605",
    "sg:postcode":"05255",
    "sg:province":"VT",
    "sg:tags":[
        "body",
        "shop",
        "painting",
        "automobile"
    ],
    "wof:name":"Manchester Auto Body",
    "wof:placetype":"venue"
},
  "geometry": {"coordinates":[-73.047025,43.180444],"type":"Point"}
}