{
  "type": "Feature",
  "properties": {
    "iso:country":"US",
    "sg:address":"2 Church St",
    "sg:city":"Burlington",
    "sg:classifiers":[
        {
            "category":"Social Services",
            "type":"Services"
        }
    ],
    "sg:phone":"+1 802 658 7999",
    "sg:postcode":"05401",
    "sg:province":"VT",
    "sg:tags":[
        "counselor",
        "marriage",
        "family"
    ],
    "wof:name":"Family Works",
    "wof:placetype":"venue"
},
  "geometry": {"coordinates":[-73.212721,44.479293],"type":"Point"}
}