{
  "type": "Feature",
  "properties": {
    "addr:full":"53 Lakeview Ter Burlington VT 05401",
    "addr:housenumber":"53",
    "addr:postcode":"05401",
    "addr:street":"Lakeview Ter",
    "iso:country":"US",
    "sg:address":"53 Lakeview Ter",
    "sg:city":"Burlington",
    "sg:classifiers":[
        {
            "category":"Education",
            "subcategory":"Special Training",
            "type":"Public Place"
        }
    ],
    "sg:phone":"+1 802 657 3818",
    "sg:postcode":"05401",
    "sg:province":"VT",
    "sg:tags":[
        "educational"
    ],
    "wof:name":"Hands On Productions",
    "wof:placetype":"venue"
},
  "geometry": {"coordinates":[-73.22571600000001,44.487098],"type":"Point"}
}