{
  "type": "Feature",
  "properties": {
    "iso:country":"US",
    "sg:address":"102 Malletts Bay Ave",
    "sg:city":"Winooski",
    "sg:classifiers":[
        {
            "category":"Building & Trades",
            "subcategory":"Construction",
            "type":"Services"
        }
    ],
    "sg:phone":"+1 802 655 8905",
    "sg:postcode":"05404",
    "sg:province":"VT",
    "sg:tags":[
        "general",
        "contractor"
    ],
    "wof:name":"Can Do Construction",
    "wof:placetype":"venue"
},
  "geometry": {"coordinates":[-73.192547,44.494902],"type":"Point"}
}