{
  "type": "Feature",
  "properties": {
    "addr:full":"4768 Georgia Shore Rd St Albans VT 05478",
    "addr:housenumber":"4768",
    "addr:postcode":"05478",
    "addr:street":"Georgia Shore Rd",
    "iso:country":"US",
    "sg:address":"4768 Georgia Shore Rd",
    "sg:city":"St Albans",
    "sg:classifiers":[
        {
            "category":"Manufacturing",
            "subcategory":"Printing",
            "type":"Manufacturing & Wholesale Goods"
        }
    ],
    "sg:phone":"+1 802 524 3298",
    "sg:postcode":"05478",
    "sg:province":"VT",
    "sg:tags":[
        "commercial",
        "copying",
        "offset"
    ],
    "wof:name":"North Country Press",
    "wof:placetype":"venue"
},
  "geometry": {"coordinates":[-73.160321,44.766337],"type":"Point"}
}