{
  "type": "Feature",
  "properties": {
    "iso:country":"US",
    "sg:address":"212 Fairway Dr",
    "sg:city":"Williston",
    "sg:classifiers":[
        {
            "category":"Professional",
            "subcategory":"Management & Consulting",
            "type":"Services"
        }
    ],
    "sg:phone":"+1 802 879 8518",
    "sg:postcode":"05495",
    "sg:province":"VT",
    "sg:tags":[
        "business"
    ],
    "wof:name":"Dennis Lambert",
    "wof:placetype":"venue"
},
  "geometry": {"coordinates":[-73.059775,44.443957],"type":"Point"}
}