{
  "type": "Feature",
  "properties": {
    "iso:country":"US",
    "sg:address":"221 Northside Dr",
    "sg:city":"Bennington",
    "sg:classifiers":[
        {
            "category":"Building & Trades",
            "subcategory":"Construction",
            "type":"Services"
        }
    ],
    "sg:phone":"+1 802 442 7177",
    "sg:postcode":"05201",
    "sg:province":"VT",
    "sg:tags":[
        "house"
    ],
    "wof:name":"Vermont Quality Homes",
    "wof:placetype":"venue"
},
  "geometry": {"coordinates":[-73.2103,42.899829],"type":"Point"}
}