{
  "type": "Feature",
  "properties": {
    "addr:full":"260 S Main St Rutland VT 05701",
    "addr:housenumber":"260",
    "addr:postcode":"05701",
    "addr:street":"S Main St",
    "iso:country":"US",
    "sg:address":"260 S Main St",
    "sg:city":"Rutland",
    "sg:classifiers":[
        {
            "category":"Professional",
            "subcategory":"Accounting & Tax Preparation",
            "type":"Services"
        }
    ],
    "sg:phone":"+1 802 775 4738",
    "sg:postcode":"05701",
    "sg:province":"VT",
    "sg:tags":[
        "bookkeeping",
        "general"
    ],
    "wof:name":"Balanced Bookkeeping Solutions",
    "wof:placetype":"venue"
},
  "geometry": {"coordinates":[-72.971671,43.60498],"type":"Point"}
}