{
  "type": "Feature",
  "properties": {
    "iso:country":"US",
    "sg:address":"1753 Panton Rd",
    "sg:city":"Vergennes",
    "sg:classifiers":[
        {
            "category":"Building & Trades",
            "subcategory":"Construction",
            "type":"Services"
        }
    ],
    "sg:phone":"+1 802 475 2132",
    "sg:postcode":"05491",
    "sg:province":"VT",
    "sg:tags":[
        "house"
    ],
    "wof:name":"Harbor Construction",
    "wof:placetype":"venue"
},
  "geometry": {"coordinates":[-73.29253199999999,44.156398],"type":"Point"}
}