{
  "type": "Feature",
  "properties": {
    "iso:country":"US",
    "sg:address":"109 Raymond Rd",
    "sg:city":"Colchester",
    "sg:classifiers":[
        {
            "category":"Building & Trades",
            "subcategory":"Landscaping Services",
            "type":"Services"
        }
    ],
    "sg:phone":"+1 802 893 3505",
    "sg:postcode":"05446",
    "sg:province":"VT",
    "sg:tags":[
        "landscape",
        "contractor"
    ],
    "wof:name":"Maple Leaf Landscaping",
    "wof:placetype":"venue"
},
  "geometry": {"coordinates":[-73.18879099999999,44.593717],"type":"Point"}
}