{
  "type": "Feature",
  "properties": {
    "addr:full":"170 North St Bennington VT 05201",
    "addr:housenumber":"170",
    "addr:postcode":"05201",
    "addr:street":"North St",
    "iso:country":"US",
    "sg:address":"170 North St",
    "sg:city":"Bennington",
    "sg:classifiers":[
        {
            "category":"Shopping",
            "subcategory":"Musical Instruments",
            "type":"Retail Goods"
        }
    ],
    "sg:phone":"+1 802 442 4977",
    "sg:postcode":"05201",
    "sg:province":"VT",
    "wof:name":"Faller Music Co",
    "wof:placetype":"venue"
},
  "geometry": {"coordinates":[-73.197131,42.879631],"type":"Point"}
}