{
  "type": "Feature",
  "properties": {
    "iso:country":"US",
    "sg:address":"59 Franklin St",
    "sg:city":"Brandon",
    "sg:classifiers":[
        {
            "category":"Autos & Motor Vehicles",
            "subcategory":"Auto Supplies",
            "type":"Retail Goods"
        },
        {
            "category":"Retail",
            "subcategory":"Auto Repair",
            "type":"Services"
        }
    ],
    "sg:phone":"+1 802 247 3718",
    "sg:postcode":"05733",
    "sg:province":"VT",
    "sg:tags":[
        "automobile",
        "part",
        "accessory"
    ],
    "wof:name":"Green Mountain Garage",
    "wof:placetype":"venue"
},
  "geometry": {"coordinates":[-73.08023,43.794588],"type":"Point"}
}