{
  "type": "Feature",
  "properties": {
    "iso:country":"US",
    "sg:address":"2137 Glover Rd",
    "sg:city":"Barton",
    "sg:classifiers":[
        {
            "category":"Real Estate",
            "subcategory":"Real Estate Agent",
            "type":"Services"
        }
    ],
    "sg:phone":"+1 802 525 4706",
    "sg:postcode":"05839",
    "sg:province":"VT",
    "wof:name":"Fontaine Real & Rosalie",
    "wof:placetype":"venue"
},
  "geometry": {"coordinates":[-72.18480700000001,44.719607],"type":"Point"}
}