{
  "type": "Feature",
  "properties": {
    "addr:full":"93 High St Brattleboro VT 05301",
    "addr:housenumber":"93",
    "addr:postcode":"05301",
    "addr:street":"High St",
    "iso:country":"US",
    "sg:address":"93 High St",
    "sg:city":"Brattleboro",
    "sg:classifiers":[
        {
            "category":"Health Services",
            "subcategory":"Doctor",
            "type":"Services"
        }
    ],
    "sg:phone":"+1 802 254 4770",
    "sg:postcode":"05301",
    "sg:province":"VT",
    "sg:tags":[
        "dentist"
    ],
    "wof:name":"Family Dentistry",
    "wof:placetype":"venue"
},
  "geometry": {"coordinates":[-72.562495,42.853411],"type":"Point"}
}