{
  "type": "Feature",
  "properties": {
    "iso:country":"US",
    "sg:address":"155 Dorset St",
    "sg:city":"South Burlington",
    "sg:classifiers":[
        {
            "category":"Shopping",
            "subcategory":"Hobbies, Toys, & Games",
            "type":"Retail Goods"
        }
    ],
    "sg:phone":"+1 802 658 6061",
    "sg:postcode":"05403",
    "sg:province":"VT",
    "wof:name":"K-B Toys",
    "wof:placetype":"venue"
},
  "geometry": {"coordinates":[-73.181234,44.465566],"type":"Point"}
}