{
  "type": "Feature",
  "properties": {
    "iso:country":"US",
    "sg:address":"89 Main St",
    "sg:city":"Montpelier",
    "sg:classifiers":[
        {
            "category":"Government",
            "subcategory":"Office",
            "type":"Public Place"
        }
    ],
    "sg:phone":"+1 802 828 2900",
    "sg:postcode":"05602",
    "sg:province":"VT",
    "sg:tags":[
        "home",
        "state",
        "program",
        "health",
        "care"
    ],
    "wof:name":"Health Care Administration",
    "wof:placetype":"venue"
},
  "geometry": {"coordinates":[-72.57509400000001,44.260297],"type":"Point"}
}