{
  "type": "Feature",
  "properties": {
    "iso:country":"US",
    "sg:address":"31 Dog River Dr",
    "sg:city":"Northfield",
    "sg:classifiers":[
        {
            "category":"Social Services",
            "type":"Services"
        }
    ],
    "sg:phone":"+1 802 485 4293",
    "sg:postcode":"05663",
    "sg:province":"VT",
    "sg:tags":[
        "organization",
        "welfare"
    ],
    "wof:name":"CERV",
    "wof:placetype":"venue"
},
  "geometry": {"coordinates":[-72.657329,44.163245],"type":"Point"}
}