{
  "type": "Feature",
  "properties": {
    "addr:full":"1099 North Ave Burlington VT 05401",
    "addr:housenumber":"1099",
    "addr:postcode":"05401",
    "addr:street":"North Ave",
    "iso:country":"US",
    "sg:address":"1099 North Ave",
    "sg:city":"Burlington",
    "sg:classifiers":[
        {
            "category":"Real Estate",
            "subcategory":"Real Estate Agent",
            "type":"Services"
        }
    ],
    "sg:phone":"+1 802 658 6688",
    "sg:postcode":"05401",
    "sg:province":"VT",
    "wof:name":"Hauke Realty",
    "wof:placetype":"venue"
},
  "geometry": {"coordinates":[-73.243506,44.50593],"type":"Point"}
}