{
  "type": "Feature",
  "properties": {
    "iso:country":"US",
    "sg:address":"71 N Main St",
    "sg:city":"St Albans",
    "sg:classifiers":[
        {
            "category":"Shopping",
            "subcategory":"Gifts & Souvenirs",
            "type":"Retail Goods"
        }
    ],
    "sg:phone":"+1 802 527 9680",
    "sg:postcode":"05478",
    "sg:province":"VT",
    "sg:tags":[
        "shop"
    ],
    "wof:name":"Garden Patch",
    "wof:placetype":"venue"
},
  "geometry": {"coordinates":[-73.083186,44.811906],"type":"Point"}
}