{
  "type": "Feature",
  "properties": {
    "addr:full":"239 Hopson Rd Norwich VT 05055",
    "addr:housenumber":"239",
    "addr:postcode":"05055",
    "addr:street":"Hopson Rd",
    "iso:country":"US",
    "sg:address":"239 Hopson Rd",
    "sg:city":"Norwich",
    "sg:classifiers":[
        {
            "category":"Organizations",
            "subcategory":"Non-profit Organization",
            "type":"Services"
        }
    ],
    "sg:phone":"+1 802 649 2823",
    "sg:postcode":"05055",
    "sg:province":"VT",
    "sg:tags":[
        "social"
    ],
    "wof:name":"Eugen Rosenstock Huessy F",
    "wof:placetype":"venue"
},
  "geometry": {"coordinates":[-72.31945899999999,43.704578],"type":"Point"}
}