{
  "type": "Feature",
  "properties": {
    "addr:full":"127 Cumberland Rd Burlington VT 05408",
    "addr:housenumber":"127",
    "addr:postcode":"05408",
    "addr:street":"Cumberland Rd",
    "iso:country":"US",
    "sg:address":"127 Cumberland Rd",
    "sg:city":"Burlington",
    "sg:classifiers":[
        {
            "category":"Building & Trades",
            "subcategory":"Landscaping Services",
            "type":"Services"
        }
    ],
    "sg:phone":"+1 802 859 0568",
    "sg:postcode":"05408",
    "sg:province":"VT",
    "sg:tags":[
        "landscape"
    ],
    "wof:name":"Spring Valley Landscape",
    "wof:placetype":"venue"
},
  "geometry": {"coordinates":[-72.719584,44.312005],"type":"Point"}
}