{
  "type": "Feature",
  "properties": {
    "iso:country":"US",
    "sg:address":"5 S Main St",
    "sg:city":"St Albans",
    "sg:classifiers":[
        {
            "category":"Government",
            "subcategory":"Office",
            "type":"Public Place"
        }
    ],
    "sg:phone":"+1 802 524 4898",
    "sg:postcode":"05478",
    "sg:province":"VT",
    "sg:tags":[
        "federal",
        "taxation"
    ],
    "wof:name":"Ud Customs Svc",
    "wof:placetype":"venue"
},
  "geometry": {"coordinates":[-73.083427,44.810569],"type":"Point"}
}