{
  "type": "Feature",
  "properties": {
    "iso:country":"US",
    "sg:address":"162 Rutland Rd",
    "sg:city":"West Rutland",
    "sg:classifiers":[
        {
            "category":"Manufacturing",
            "subcategory":"Tools & Machinery",
            "type":"Manufacturing & Wholesale Goods"
        }
    ],
    "sg:phone":"+1 802 438 5173",
    "sg:postcode":"05777",
    "sg:province":"VT",
    "sg:tags":[
        "industrial",
        "mfg"
    ],
    "wof:name":"Menard Manufacturing",
    "wof:placetype":"venue"
},
  "geometry": {"coordinates":[-73.0254,43.596178],"type":"Point"}
}