{
  "type": "Feature",
  "properties": {
    "iso:country":"US",
    "sg:address":"205 College St",
    "sg:city":"Burlington",
    "sg:classifiers":[
        {
            "category":"Bars & Pubs",
            "type":"Food & Drink"
        },
        {
            "category":"Restaurant",
            "type":"Food & Drink"
        }
    ],
    "sg:phone":"+1 802 864 8209",
    "sg:postcode":"05401",
    "sg:province":"VT",
    "sg:tags":[
        "drinking"
    ],
    "wof:name":"Finnigan's Pub",
    "wof:placetype":"venue"
},
  "geometry": {"coordinates":[-73.21225699999999,44.477027],"type":"Point"}
}