{
  "type": "Feature",
  "properties": {
    "addr:full":"103 White Rocks Rd Brandon VT 05733",
    "addr:housenumber":"103",
    "addr:postcode":"05733",
    "addr:street":"White Rocks Rd",
    "iso:country":"US",
    "sg:address":"103 White Rocks Rd",
    "sg:city":"Brandon",
    "sg:classifiers":[
        {
            "category":"Shopping",
            "subcategory":"Books",
            "type":"Retail Goods"
        }
    ],
    "sg:phone":"+1 802 660 8060",
    "sg:postcode":"05733",
    "sg:province":"VT",
    "wof:name":"Spirit Dancer Books and Gifts",
    "wof:placetype":"venue"
},
  "geometry": {"coordinates":[-72.998722,43.854991],"type":"Point"}
}