{
  "type": "Feature",
  "properties": {
    "iso:country":"US",
    "sg:address":"1 Home St",
    "sg:city":"Richford",
    "sg:classifiers":[
        {
            "category":"Utilities",
            "subcategory":"Electric",
            "type":"Services"
        }
    ],
    "sg:phone":"+1 802 848 7426",
    "sg:postcode":"05476",
    "sg:province":"VT",
    "sg:tags":[
        "company"
    ],
    "wof:name":"Citizens Utilities Co",
    "wof:placetype":"venue"
},
  "geometry": {"coordinates":[-72.671823,44.988028],"type":"Point"}
}