{
  "type": "Feature",
  "properties": {
    "addr:full":"31 Mine Rd Johnson VT 05656",
    "addr:housenumber":"31",
    "addr:postcode":"05656",
    "addr:street":"Mine Rd",
    "iso:country":"US",
    "sg:address":"31 Mine Rd",
    "sg:city":"Johnson",
    "sg:classifiers":[
        {
            "category":"Manufacturing",
            "subcategory":"Lumber",
            "type":"Manufacturing & Wholesale Goods"
        }
    ],
    "sg:phone":"+1 802 635 7483",
    "sg:postcode":"05656",
    "sg:province":"VT",
    "sg:tags":[
        "syrup",
        "maple",
        "sugar"
    ],
    "wof:name":"Butternut Mountain Farm",
    "wof:placetype":"venue"
},
  "geometry": {"coordinates":[-72.63513500000001,44.654828],"type":"Point"}
}