{
  "type": "Feature",
  "properties": {
    "addr:full":"357 Main St Barton VT 05822",
    "addr:housenumber":"357",
    "addr:postcode":"05822",
    "addr:street":"Main St",
    "iso:country":"US",
    "sg:address":"357 Main St",
    "sg:city":"Barton",
    "sg:classifiers":[
        {
            "category":"Restaurant",
            "type":"Food & Drink"
        }
    ],
    "sg:phone":"+1 802 525 9992",
    "sg:postcode":"05822",
    "sg:province":"VT",
    "sg:tags":[
        "caterer"
    ],
    "wof:name":"Nellie Jo's Deli & Catering",
    "wof:placetype":"venue"
},
  "geometry": {"coordinates":[-72.17909400000001,44.75017],"type":"Point"}
}