{
  "type": "Feature",
  "properties": {
    "iso:country":"US",
    "sg:address":"410 Shelburne Rd",
    "sg:city":"Burlington",
    "sg:classifiers":[
        {
            "category":"Health Services",
            "subcategory":"Doctor",
            "type":"Services"
        }
    ],
    "sg:phone":"+1 802 860 1928",
    "sg:postcode":"05401",
    "sg:province":"VT",
    "sg:tags":[
        "physician",
        "medical",
        "surgeon"
    ],
    "wof:name":"Hagan & Rinehart Pediatricians",
    "wof:placetype":"venue"
},
  "geometry": {"coordinates":[-73.20878999999999,44.453136],"type":"Point"}
}