{
  "type": "Feature",
  "properties": {
    "iso:country":"US",
    "sg:address":"201 Hill St",
    "sg:city":"Barre",
    "sg:classifiers":[
        {
            "category":"Health Services",
            "subcategory":"Hospital",
            "type":"Services"
        }
    ],
    "sg:phone":"+1 802 479 1477",
    "sg:postcode":"05641",
    "sg:province":"VT",
    "sg:tags":[
        "mental"
    ],
    "wof:name":"Washington County Mental Hlth",
    "wof:placetype":"venue"
},
  "geometry": {"coordinates":[-72.48696700000001,44.192443],"type":"Point"}
}