{
  "type": "Feature",
  "properties": {
    "iso:country":"US",
    "sg:address":"61 Central St",
    "sg:city":"Woodstock",
    "sg:classifiers":[
        {
            "category":"Manufacturing",
            "subcategory":"Soap",
            "type":"Manufacturing & Wholesale Goods"
        }
    ],
    "sg:phone":"+1 802 457 4208",
    "sg:postcode":"05091",
    "sg:province":"VT",
    "sg:tags":[
        "detergent"
    ],
    "wof:name":"Trillium Soaps Of Vermont",
    "wof:placetype":"venue"
},
  "geometry": {"coordinates":[-72.51616799999999,43.62603],"type":"Point"}
}