{
  "type": "Feature",
  "properties": {
    "iso:country":"US",
    "sg:address":"39 Park St",
    "sg:city":"Essex Junction",
    "sg:classifiers":[
        {
            "category":"Shopping",
            "subcategory":"Department Store",
            "type":"Retail Goods"
        },
        {
            "category":"Food & Beverages",
            "subcategory":"Liquor & Beverages",
            "type":"Retail Goods"
        }
    ],
    "sg:phone":"+1 802 879 7101",
    "sg:postcode":"05452",
    "sg:province":"VT",
    "sg:tags":[
        "variety",
        "soft",
        "mfg"
    ],
    "wof:name":"Five Corners Discount Beverage",
    "wof:placetype":"venue"
},
  "geometry": {"coordinates":[-73.112577,44.488278],"type":"Point"}
}