{
  "type": "Feature",
  "properties": {
    "iso:country":"US",
    "sg:address":"22 Commerce St",
    "sg:city":"Hinesburg",
    "sg:classifiers":[
        {
            "category":"Home & Garden",
            "subcategory":"Hardware",
            "type":"Retail Goods"
        }
    ],
    "sg:phone":"+1 802 482 2980",
    "sg:postcode":"05461",
    "sg:province":"VT",
    "sg:tags":[
        "store"
    ],
    "wof:name":"Estey Hardware Inc",
    "wof:placetype":"venue"
},
  "geometry": {"coordinates":[-73.10806700000001,44.334783],"type":"Point"}
}