{
  "type": "Feature",
  "properties": {
    "iso:country":"US",
    "sg:address":"110 Mountain St",
    "sg:city":"Bristol",
    "sg:classifiers":[
        {
            "category":"Building & Trades",
            "subcategory":"Plumbing",
            "type":"Services"
        }
    ],
    "sg:phone":"+1 802 453 3760",
    "sg:postcode":"05443",
    "sg:province":"VT",
    "sg:tags":[
        "plumbing",
        "contractor"
    ],
    "wof:name":"Mid-State Plumber",
    "wof:placetype":"venue"
},
  "geometry": {"coordinates":[-73.07753099999999,44.142065],"type":"Point"}
}