{
  "type": "Feature",
  "properties": {
    "iso:country":"US",
    "sg:address":"78 Elliot St",
    "sg:city":"Brattleboro",
    "sg:classifiers":[
        {
            "category":"Restaurant",
            "type":"Food & Drink"
        }
    ],
    "sg:phone":"+1 802 257 0863",
    "sg:postcode":"05301",
    "sg:province":"VT",
    "wof:name":"Mike's Restaurant Inc",
    "wof:placetype":"venue"
},
  "geometry": {"coordinates":[-72.559766,42.851795],"type":"Point"}
}