{
  "type": "Feature",
  "properties": {
    "iso:country":"US",
    "sg:address":"26 Corona St",
    "sg:city":"Brandon",
    "sg:classifiers":[
        {
            "category":"Manufacturing",
            "subcategory":"Wood Products",
            "type":"Manufacturing & Wholesale Goods"
        }
    ],
    "sg:phone":"+1 802 247 4620",
    "sg:postcode":"05733",
    "sg:province":"VT",
    "sg:tags":[
        "pallet"
    ],
    "wof:name":"Hayes Recycled Pallets",
    "wof:placetype":"venue"
},
  "geometry": {"coordinates":[-73.098994,43.790622],"type":"Point"}
}