{
  "type": "Feature",
  "properties": {
    "addr:full":"463 US Hwy 5 Newport VT 05855",
    "addr:housenumber":"463",
    "addr:postcode":"05855",
    "addr:street":"Us Hwy 5",
    "iso:country":"US",
    "sg:address":"463 US Hwy 5",
    "sg:city":"Newport",
    "sg:classifiers":[
        {
            "category":"Building & Trades",
            "subcategory":"Construction",
            "type":"Services"
        }
    ],
    "sg:phone":"+1 802 766 4789",
    "sg:postcode":"05855",
    "sg:province":"VT",
    "sg:tags":[
        "general",
        "contractor"
    ],
    "wof:name":"Mario R Paul Excavating Inc",
    "wof:placetype":"venue"
},
  "geometry": {"coordinates":[-72.19508500000001,44.942983],"type":"Point"}
}