{
  "type": "Feature",
  "properties": {
    "iso:country":"US",
    "sg:address":"106 Highpoint Center",
    "sg:city":"Colchester",
    "sg:classifiers":[
        {
            "category":"Banks & Credit Unions",
            "subcategory":"Investment Brokerage",
            "type":"Services"
        }
    ],
    "sg:phone":"+1 802 893 7107",
    "sg:postcode":"05446",
    "sg:province":"VT",
    "sg:tags":[
        "consultant",
        "planning",
        "financial"
    ],
    "wof:name":"Jim Hedbor Financial Svc",
    "wof:placetype":"venue"
},
  "geometry": {"coordinates":[-73.183103,44.503961],"type":"Point"}
}