{
  "type": "Feature",
  "properties": {
    "iso:country":"US",
    "sg:address":"169 Washington St",
    "sg:city":"Barre",
    "sg:classifiers":[
        {
            "category":"Autos & Motor Vehicles",
            "subcategory":"Fuel & Gas Station",
            "type":"Retail Goods"
        }
    ],
    "sg:phone":"+1 802 476 4133",
    "sg:postcode":"05641",
    "sg:province":"VT",
    "sg:tags":[
        "oil"
    ],
    "wof:name":"Washington Street Exxon",
    "wof:placetype":"venue"
},
  "geometry": {"coordinates":[-72.492667,44.192184],"type":"Point"}
}