{
  "type": "Feature",
  "properties": {
    "addr:full":"102 Hill Rd Newfane VT 05345",
    "addr:housenumber":"102",
    "addr:postcode":"05345",
    "addr:street":"Hill Rd",
    "iso:country":"US",
    "sg:address":"102 Hill Rd",
    "sg:city":"Newfane",
    "sg:classifiers":[
        {
            "category":"Farming",
            "subcategory":"Livestock Farm",
            "type":"Manufacturing & Wholesale Goods"
        }
    ],
    "sg:phone":"+1 802 365 7668",
    "sg:postcode":"05345",
    "sg:province":"VT",
    "sg:tags":[
        "beef",
        "feedlot",
        "cattle"
    ],
    "wof:name":"West Rver Stbls Madowbrook Frm",
    "wof:placetype":"venue"
},
  "geometry": {"coordinates":[-72.635924,43.002923],"type":"Point"}
}