{
  "type": "Feature",
  "properties": {
    "addr:full":"456 S Barre Rd Barre VT 05641",
    "addr:housenumber":"456",
    "addr:postcode":"05641",
    "addr:street":"S Barre Rd",
    "iso:country":"US",
    "sg:address":"456 S Barre Rd",
    "sg:city":"Barre",
    "sg:classifiers":[
        {
            "category":"Banks & Credit Unions",
            "subcategory":"Bank",
            "type":"Services"
        }
    ],
    "sg:phone":"+1 802 479 1300",
    "sg:postcode":"05641",
    "sg:province":"VT",
    "wof:name":"Banknorth",
    "wof:placetype":"venue"
},
  "geometry": {"coordinates":[-72.511881,44.162867],"type":"Point"}
}