{
  "type": "Feature",
  "properties": {
    "iso:country":"US",
    "sg:address":"21 Chittenden Rd",
    "sg:city":"Rutland",
    "sg:classifiers":[
        {
            "category":"Building & Trades",
            "subcategory":"Landscaping Services",
            "type":"Services"
        }
    ],
    "sg:phone":"+1 802 773 8724",
    "sg:postcode":"05701",
    "sg:province":"VT",
    "wof:name":"Grassdogs Lawncare",
    "wof:placetype":"venue"
},
  "geometry": {"coordinates":[-72.942835,43.670993],"type":"Point"}
}