{
  "type": "Feature",
  "properties": {
    "iso:country":"US",
    "sg:address":"143 Etta Fraiser Dr",
    "sg:city":"Windsor",
    "sg:classifiers":[
        {
            "category":"Professional",
            "subcategory":"Lawyer & Legal Services",
            "type":"Services"
        }
    ],
    "sg:phone":"+1 802 674 6599",
    "sg:postcode":"05089",
    "sg:province":"VT",
    "sg:tags":[
        "attorney"
    ],
    "wof:name":"Kathleen London Law Office",
    "wof:placetype":"venue"
},
  "geometry": {"coordinates":[-72.387248,43.47789],"type":"Point"}
}