{
  "type": "Feature",
  "properties": {
    "iso:country":"US",
    "sg:address":"85 Prim Rd Ste 401",
    "sg:city":"Colchester",
    "sg:classifiers":[
        {
            "category":"Health Services",
            "subcategory":"Chiropractor",
            "type":"Services"
        }
    ],
    "sg:phone":"+1 802 860 0382",
    "sg:postcode":"05446",
    "sg:province":"VT",
    "sg:tags":[
        "chiropractic"
    ],
    "wof:name":"Family First Chiropractic",
    "wof:placetype":"venue"
},
  "geometry": {"coordinates":[-73.23401800000001,44.551095],"type":"Point"}
}