{
  "type": "Feature",
  "properties": {
    "iso:country":"US",
    "sg:address":"1110 Meehan Rd",
    "sg:city":"Bristol",
    "sg:classifiers":[
        {
            "category":"Building & Trades",
            "subcategory":"Construction",
            "type":"Services"
        }
    ],
    "sg:phone":"+1 802 453 2255",
    "sg:postcode":"05443",
    "sg:province":"VT",
    "sg:tags":[
        "roofing",
        "industrial",
        "contractors-commercial",
        "contractor"
    ],
    "sg:website":"http://www.friendconstructionvt.com",
    "wof:name":"Friend Construction",
    "wof:placetype":"venue"
},
  "geometry": {"coordinates":[-73.041535,44.175616],"type":"Point"}
}