{
  "type": "Feature",
  "properties": {
    "iso:country":"US",
    "sg:address":"65 Millet St",
    "sg:city":"Richmond",
    "sg:classifiers":[
        {
            "category":"Professional",
            "subcategory":"Engineering",
            "type":"Services"
        }
    ],
    "sg:phone":"+1 802 434 4944",
    "sg:postcode":"05477",
    "sg:province":"VT",
    "wof:name":"Wright-Pierce",
    "wof:placetype":"venue"
},
  "geometry": {"coordinates":[-72.993038,44.406865],"type":"Point"}
}