{
  "type": "Feature",
  "properties": {
    "iso:country":"US",
    "sg:address":"2079 W Creek Rd",
    "sg:city":"Florence",
    "sg:classifiers":[
        {
            "category":"Professional",
            "subcategory":"Computer Services",
            "type":"Services"
        }
    ],
    "sg:phone":"+1 802 483 6881",
    "sg:postcode":"05744",
    "sg:province":"VT",
    "sg:tags":[
        "network",
        "sales"
    ],
    "wof:name":"Silloway Networks",
    "wof:placetype":"venue"
},
  "geometry": {"coordinates":[-73.06024499999999,43.718497],"type":"Point"}
}