{
  "type": "Feature",
  "properties": {
    "iso:country":"US",
    "sg:address":"2736 State Rte 153",
    "sg:city":"West Pawlet",
    "sg:classifiers":[
        {
            "category":"Travel",
            "subcategory":"Campground",
            "type":"Entertainment"
        }
    ],
    "sg:phone":"+1 802 645 0216",
    "sg:postcode":"05775",
    "sg:province":"VT",
    "sg:tags":[
        "camp"
    ],
    "sg:website":"www.campcatherinecapers.com",
    "wof:name":"Camp Catherine Capers",
    "wof:placetype":"venue"
},
  "geometry": {"coordinates":[-73.25189899999999,43.353511],"type":"Point"}
}