{
  "type": "Feature",
  "properties": {
    "iso:country":"US",
    "sg:address":"PO Box 105",
    "sg:city":"Bennington",
    "sg:classifiers":[
        {
            "category":"Professional",
            "subcategory":"Computer Services",
            "type":"Services"
        }
    ],
    "sg:postcode":"05201",
    "sg:province":"VT",
    "sg:tags":[
        "festival",
        "entertainment-news",
        "music",
        "concert",
        "bands",
        "dance",
        "theatre",
        "culture",
        "entertainment-industry"
    ],
    "sg:website":"http://kadmusarts.com/",
    "wof:name":"KadmusArts",
    "wof:placetype":"venue"
},
  "geometry": {"coordinates":[-73.213441,42.883412],"type":"Point"}
}