{
  "type": "Feature",
  "properties": {
    "iso:country":"US",
    "sg:address":"3989 State Rte 100",
    "sg:city":"Pittsfield",
    "sg:classifiers":[
        {
            "category":"Travel",
            "subcategory":"Hotels & Motels",
            "type":"Entertainment"
        }
    ],
    "sg:phone":"+1 802 746 8987",
    "sg:postcode":"05747",
    "sg:province":"VT",
    "sg:tags":[
        "resort",
        "center",
        "skiing"
    ],
    "wof:name":"Fleur De Lis",
    "wof:placetype":"venue"
},
  "geometry": {"coordinates":[-72.842795,43.967219],"type":"Point"}
}