{
  "type": "Feature",
  "properties": {
    "iso:country":"US",
    "sg:address":"12 River St",
    "sg:city":"Springfield",
    "sg:classifiers":[
        {
            "category":"Building & Trades",
            "subcategory":"Construction",
            "type":"Services"
        }
    ],
    "sg:phone":"+1 802 885 3538",
    "sg:postcode":"05156",
    "sg:province":"VT",
    "sg:tags":[
        "product",
        "asphalt"
    ],
    "wof:name":"Factory Falls Inc",
    "wof:placetype":"venue"
},
  "geometry": {"coordinates":[-72.48199099999999,43.298701],"type":"Point"}
}