{
  "type": "Feature",
  "properties": {
    "iso:country":"US",
    "sg:address":"1646 Dane Hill Rd",
    "sg:city":"West Charleston",
    "sg:classifiers":[
        {
            "category":"Farming",
            "subcategory":"Farm",
            "type":"Manufacturing & Wholesale Goods"
        }
    ],
    "sg:phone":"+1 802 895 4006",
    "sg:postcode":"05872",
    "sg:province":"VT",
    "sg:tags":[
        "crop",
        "general"
    ],
    "wof:name":"Danestead Farm",
    "wof:placetype":"venue"
},
  "geometry": {"coordinates":[-72.079458,44.872631],"type":"Point"}
}