{
  "type": "Feature",
  "properties": {
    "iso:country":"US",
    "sg:address":"1 Cross St",
    "sg:city":"Middlebury",
    "sg:classifiers":[
        {
            "category":"Professional",
            "subcategory":"Lawyer & Legal Services",
            "type":"Services"
        }
    ],
    "sg:phone":"+1 802 388 7966",
    "sg:postcode":"05753",
    "sg:province":"VT",
    "sg:tags":[
        "firm",
        "attorney",
        "law"
    ],
    "wof:name":"Neuse Smith & Venman PC",
    "wof:placetype":"venue"
},
  "geometry": {"coordinates":[-73.16408699999999,44.011607],"type":"Point"}
}