{
  "type": "Feature",
  "properties": {
    "iso:country":"US",
    "sg:address":"2878 State Rte 18",
    "sg:city":"St Johnsbury",
    "sg:classifiers":[
        {
            "category":"Building & Trades",
            "subcategory":"Construction",
            "type":"Services"
        }
    ],
    "sg:phone":"+1 802 748 6555",
    "sg:postcode":"05819",
    "sg:province":"VT",
    "sg:tags":[
        "boring",
        "drilling",
        "contractor"
    ],
    "wof:name":"Bore Tech",
    "wof:placetype":"venue"
},
  "geometry": {"coordinates":[-71.922624,44.400107],"type":"Point"}
}