{
  "type": "Feature",
  "properties": {
    "iso:country":"US",
    "sg:address":"1820 Shelburne Rd",
    "sg:city":"South Burlington",
    "sg:classifiers":[
        {
            "category":"Professional",
            "subcategory":"Computer Services",
            "type":"Services"
        }
    ],
    "sg:phone":"+1 802 862 7500",
    "sg:postcode":"05403",
    "sg:province":"VT",
    "sg:tags":[
        "processing",
        "datum"
    ],
    "wof:name":"P-Rom Software Inc",
    "wof:placetype":"venue"
},
  "geometry": {"coordinates":[-73.210981,44.432821],"type":"Point"}
}