{
  "type": "Feature",
  "properties": {
    "iso:country":"US",
    "sg:address":"2367 Hollow Rd",
    "sg:city":"North Ferrisburg",
    "sg:classifiers":[
        {
            "category":"Building & Trades",
            "subcategory":"Construction",
            "type":"Services"
        }
    ],
    "sg:phone":"+1 802 425 2021",
    "sg:postcode":"05473",
    "sg:province":"VT",
    "sg:tags":[
        "general",
        "contractor"
    ],
    "wof:name":"Francis Driscoll Gen Constr",
    "wof:placetype":"venue"
},
  "geometry": {"coordinates":[-73.179782,44.253969],"type":"Point"}
}