{
  "type": "Feature",
  "properties": {
    "iso:country":"US",
    "sg:address":"300 Cornerstone Dr",
    "sg:city":"Williston",
    "sg:classifiers":[
        {
            "category":"Insurance",
            "subcategory":"Insurance Agent",
            "type":"Services"
        }
    ],
    "sg:phone":"+1 802 879 8525",
    "sg:postcode":"05495",
    "sg:province":"VT",
    "wof:name":"Mc Gregor Peyko",
    "wof:placetype":"venue"
},
  "geometry": {"coordinates":[-73.103087,44.44659],"type":"Point"}
}