{
  "type": "Feature",
  "properties": {
    "iso:country":"US",
    "sg:address":"224 Melrose St",
    "sg:city":"Brattleboro",
    "sg:classifiers":[
        {
            "category":"Real Estate",
            "subcategory":"Real Estate Operator",
            "type":"Services"
        }
    ],
    "sg:phone":"+1 802 254 6071",
    "sg:postcode":"05301",
    "sg:province":"VT",
    "sg:tags":[
        "apartment"
    ],
    "wof:name":"Ledgewood Heights Apartments",
    "wof:placetype":"venue"
},
  "geometry": {"coordinates":[-72.59751199999999,42.853421],"type":"Point"}
}