{
  "type": "Feature",
  "properties": {
    "iso:country":"US",
    "sg:address":"25 Jonergin Dr",
    "sg:city":"Swanton",
    "sg:classifiers":[
        {
            "category":"Manufacturing",
            "subcategory":"Printing",
            "type":"Manufacturing & Wholesale Goods"
        }
    ],
    "sg:phone":"+1 802 868 5727",
    "sg:postcode":"05488",
    "sg:province":"VT",
    "sg:tags":[
        "printer"
    ],
    "wof:name":"Mylan Technologies Inc",
    "wof:placetype":"venue"
},
  "geometry": {"coordinates":[-73.133396,44.933599],"type":"Point"}
}