{
  "type": "Feature",
  "properties": {
    "addr:full":"2121 Essex Rd Williston VT 05495",
    "addr:housenumber":"2121",
    "addr:postcode":"05495",
    "addr:street":"Essex Rd",
    "iso:country":"US",
    "sg:address":"2121 Essex Rd",
    "sg:city":"Williston",
    "sg:classifiers":[
        {
            "category":"Shopping",
            "subcategory":"Shoes",
            "type":"Retail Goods"
        }
    ],
    "sg:phone":"+1 802 879 6640",
    "sg:postcode":"05495",
    "sg:province":"VT",
    "wof:name":"Lennys Shoes and Apparel",
    "wof:placetype":"venue"
},
  "geometry": {"coordinates":[-73.111045,44.450983],"type":"Point"}
}