{
  "type": "Feature",
  "properties": {
    "iso:country":"US",
    "sg:address":"156 Dugway Rd",
    "sg:city":"Waitsfield",
    "sg:classifiers":[
        {
            "category":"Real Estate",
            "subcategory":"Real Estate Agent",
            "type":"Services"
        }
    ],
    "sg:phone":"+1 802 496 2321",
    "sg:postcode":"05673",
    "sg:province":"VT",
    "sg:tags":[
        "house",
        "construct"
    ],
    "wof:name":"Property Management Inc",
    "wof:placetype":"venue"
},
  "geometry": {"coordinates":[-72.838155,44.180166],"type":"Point"}
}