{
  "type": "Feature",
  "properties": {
    "addr:full":"140 Main St Montpelier VT 05602",
    "addr:housenumber":"140",
    "addr:postcode":"05602",
    "addr:street":"Main St",
    "iso:country":"US",
    "sg:address":"140 Main St",
    "sg:city":"Montpelier",
    "sg:classifiers":[
        {
            "category":"Professional",
            "subcategory":"Management & Consulting",
            "type":"Services"
        }
    ],
    "sg:phone":"+1 802 229 5766",
    "sg:postcode":"05602",
    "sg:province":"VT",
    "sg:tags":[
        "motel",
        "hotel"
    ],
    "wof:name":"Hilltop Inn",
    "wof:placetype":"venue"
},
  "geometry": {"coordinates":[-72.573733,44.261455],"type":"Point"}
}